Workbook

Sheet Cover
B6: =Valuation!$B$5&" -"&" "&Valuation!$B$18&" Rating - TP R$"&Valuation!$B$16&"/sh" -> CURY3 - Outperform Rating - TP R$44/sh
B8: Brazil - Homebuilders
B10: Itaú BBA - Real Estate
B11: Elvis Credendio
B12: Cel.: +55 11 3073-3032
B14: Daniel Gasparete
B15: Cel.: +55 11 3073-3906
B17: Mariangela Castro
B18: Cel.: +55 11 3073-3102
B20: Juliana Veiga
B21: Cel.: +55 11 3073-2025

Sheet Macro
A2: ="CURY3 | "&"TP R$"&Valuation!$B$16&"/sh" -> CURY3 | TP R$44/sh
A3: Macro variables | B3: =B5&RIGHT(B4,2)&B6 -> 1Q10 | C3: =C5&RIGHT(C4,2)&C6 -> 2Q10 | D3: =D5&RIGHT(D4,2)&D6 -> 3Q10 | E3: =E5&RIGHT(E4,2)&E6 -> 4Q10 | F3: =F4&F6 -> 2010 | G3: =G5&RIGHT(G4,2)&G6 -> 1Q11 | H3: =H5&RIGHT(H4,2)&H6 -> 2Q11 | I3: =I5&RIGHT(I4,2)&I6 -> 3Q11 | J3: =J5&RIGHT(J4,2)&J6 -> 4Q11 | K3: =K4&K6 -> 2011 | L3: =L5&RIGHT(L4,2)&L6 -> 1Q12 | M3: =M5&RIGHT(M4,2)&M6 -> 2Q12 | N3: =N5&RIGHT(N4,2)&N6 -> 3Q12 | O3: =O5&RIGHT(O4,2)&O6 -> 4Q12 | P3: =P4&P6 -> 2012 | Q3: =Q5&RIGHT(Q4,2)&Q6 -> 1Q13 | R3: =R5&RIGHT(R4,2)&R6 -> 2Q13 | S3: =S5&RIGHT(S4,2)&S6 -> 3Q13 | T3: =T5&RIGHT(T4,2)&T6 -> 4Q13 | U3: =U4&U6 -> 2013 | V3: =V5&RIGHT(V4,2)&V6 -> 1Q14 | W3: =W5&RIGHT(W4,2)&W6 -> 2Q14 | X3: =X5&RIGHT(X4,2)&X6 -> 3Q14 | Y3: =Y5&RIGHT(Y4,2)&Y6 -> 4Q14 | Z3: =Z4&Z6 -> 2014 | AA3: =AA5&RIGHT(AA4,2)&AA6 -> 1Q15 | AB3: =AB5&RIGHT(AB4,2)&AB6 -> 2Q15 | AC3: =AC5&RIGHT(AC4,2)&AC6 -> 3Q15 | AD3: =AD5&RIGHT(AD4,2)&AD6 -> 4Q15 | AE3: =AE4&AE6 -> 2015 | AF3: =AF5&RIGHT(AF4,2)&AF6 -> 1Q16 | AG3: =AG5&RIGHT(AG4,2)&AG6 -> 2Q16 | AH3: =AH5&RIGHT(AH4,2)&AH6 -> 3Q16 | AI3: =AI5&RIGHT(AI4,2)&AI6 -> 4Q16 | AJ3: =AJ4&AJ6 -> 2016 | AK3: =AK5&RIGHT(AK4,2)&AK6 -> 1Q17 | AL3: =AL5&RIGHT(AL4,2)&AL6 -> 2Q17 | AM3: =AM5&RIGHT(AM4,2)&AM6 -> 3Q17 | AN3: =AN5&RIGHT(AN4,2)&AN6 -> 4Q17 | AO3: =AO4&AO6 -> 2017 | AP3: =AP5&RIGHT(AP4,2)&AP6 -> 1Q18 | AQ3: =AQ5&RIGHT(AQ4,2)&AQ6 -> 2Q18 | AR3: =AR5&RIGHT(AR4,2)&AR6 -> 3Q18 | AS3: =AS5&RIGHT(AS4,2)&AS6 -> 4Q18 | AT3: =AT4&AT6 -> 2018 | AU3: =AU5&RIGHT(AU4,2)&AU6 -> 1Q19 | AV3: =AV5&RIGHT(AV4,2)&AV6 -> 2Q19 | AW3: =AW5&RIGHT(AW4,2)&AW6 -> 3Q19 | AX3: =AX5&RIGHT(AX4,2)&AX6 -> 4Q19 | AY3: =AY4&AY6 -> 2019 | AZ3: =AZ5&RIGHT(AZ4,2)&AZ6 -> 1Q20 | BA3: =BA5&RIGHT(BA4,2)&BA6 -> 2Q20 | BB3: =BB5&RIGHT(BB4,2)&BB6 -> 3Q20 | BC3: =BC5&RIGHT(BC4,2)&BC6 -> 4Q20 | BD3: =BD4&BD6 -> 2020 | BE3: =BE5&RIGHT(BE4,2)&BE6 -> 1Q21 | BF3: =BF5&RIGHT(BF4,2)&BF6 -> 2Q21 | BG3: =BG5&RIGHT(BG4,2)&BG6 -> 3Q21 | BH3: =BH5&RIGHT(BH4,2)&BH6 -> 4Q21 | BI3: =BI4&BI6 -> 2021 | BJ3: =BJ5&RIGHT(BJ4,2)&BJ6 -> 1Q22 | BK3: =BK5&RIGHT(BK4,2)&BK6 -> 2Q22 | BL3: =BL5&RIGHT(BL4,2)&BL6 -> 3Q22 | BM3: =BM5&RIGHT(BM4,2)&BM6 -> 4Q22 | BN3: =BN4&BN6 -> 2022 | BO3: =BO5&RIGHT(BO4,2)&BO6 -> 1Q23 | BP3: =BP5&RIGHT(BP4,2)&BP6 -> 2Q23 | BQ3: =BQ5&RIGHT(BQ4,2)&BQ6 -> 3Q23 | BR3: =BR5&RIGHT(BR4,2)&BR6 -> 4Q23 | BS3: =BS4&BS6 -> 2023 | BT3: =BT5&RIGHT(BT4,2)&BT6 -> 1Q24 | BU3: =BU5&RIGHT(BU4,2)&BU6 -> 2Q24 | BV3: =BV5&RIGHT(BV4,2)&BV6 -> 3Q24 | BW3: =BW5&RIGHT(BW4,2)&BW6 -> 4Q24 | BX3: =BX4&BX6 -> 2024 | BY3: =BY5&RIGHT(BY4,2)&BY6 -> 1Q25 | BZ3: =BZ5&RIGHT(BZ4,2)&BZ6 -> 2Q25 | CA3: =CA5&RIGHT(CA4,2)&CA6 -> 3Q25 | CB3: =CB5&RIGHT(CB4,2)&CB6 -> 4Q25 | CC3: =CC4&CC6 -> 2025 | CD3: =CD5&RIGHT(CD4,2)&CD6 -> 1Q26 | CE3: =CE5&RIGHT(CE4,2)&CE6 -> 2Q26E | CF3: =CF5&RIGHT(CF4,2)&CF6 -> 3Q26E | CG3: =CG5&RIGHT(CG4,2)&CG6 -> 4Q26E | CH3: =CH4&CH6 -> 2026E | CI3: =CI5&RIGHT(CI4,2)&CI6 -> 1Q27E | CJ3: =CJ5&RIGHT(CJ4,2)&CJ6 -> 2Q27E | CK3: =CK5&RIGHT(CK4,2)&CK6 -> 3Q27E | CL3: =CL5&RIGHT(CL4,2)&CL6 -> 4Q27E | CM3: =CM4&CM6 -> 2027E | CN3: =CN5&RIGHT(CN4,2)&CN6 -> 1Q28E | CO3: =CO5&RIGHT(CO4,2)&CO6 -> 2Q28E | CP3: =CP5&RIGHT(CP4,2)&CP6 -> 3Q28E | CQ3: =CQ5&RIGHT(CQ4,2)&CQ6 -> 4Q28E | CR3: =CR4&CR6 -> 2028E | CS3: =CS5&RIGHT(CS4,2)&CS6 -> 1Q29E | CT3: =CT5&RIGHT(CT4,2)&CT6 -> 2Q29E | CU3: =CU5&RIGHT(CU4,2)&CU6 -> 3Q29E | CV3: =CV5&RIGHT(CV4,2)&CV6 -> 4Q29E | CW3: =CW4&CW6 -> 2029E | CX3: =CX5&RIGHT(CX4,2)&CX6 -> 1Q30E | CY3: =CY5&RIGHT(CY4,2)&CY6 -> 2Q30E | CZ3: =CZ5&RIGHT(CZ4,2)&CZ6 -> 3Q30E | DA3: =DA5&RIGHT(DA4,2)&DA6 -> 4Q30E | DB3: =DB4&DB6 -> 2030E
A4: Year | B4: =[1]Macro_Model!B4 -> 2010 | C4: =[1]Macro_Model!C4 -> 2010 | D4: =[1]Macro_Model!D4 -> 2010 | E4: =[1]Macro_Model!E4 -> 2010 | F4: =[1]Macro_Model!F4 -> 2010 | G4: =[1]Macro_Model!G4 -> 2011 | H4: =[1]Macro_Model!H4 -> 2011 | I4: =[1]Macro_Model!I4 -> 2011 | ... DB4: =[1]Macro_Model!DB4 -> 2030
A5: Quarter | B5: =[1]Macro_Model!B5 -> 1Q | C5: =[1]Macro_Model!C5 -> 2Q | D5: =[1]Macro_Model!D5 -> 3Q | E5: =[1]Macro_Model!E5 -> 4Q | F5: =[1]Macro_Model!F5 -> 0 | G5: =[1]Macro_Model!G5 -> 1Q | H5: =[1]Macro_Model!H5 -> 2Q | I5: =[1]Macro_Model!I5 -> 3Q | ... DB5: =[1]Macro_Model!DB5 -> 20
A6: Actual / estimate | CE6: =[1]Macro_Model!CE6 -> E | CF6: =[1]Macro_Model!CF6 -> E | CG6: =[1]Macro_Model!CG6 -> E | CH6: =[1]Macro_Model!CH6 -> E | CI6: =[1]Macro_Model!CI6 -> E | CJ6: =[1]Macro_Model!CJ6 -> E | CK6: =[1]Macro_Model!CK6 -> E | CL6: =[1]Macro_Model!CL6 -> E | ... DB6: =[1]Macro_Model!DB6 -> E
A7: GDP growth y/y | B7: =[1]Macro_Model!B7 -> 0.092091395 | C7: =[1]Macro_Model!C7 -> 0.085177279 | D7: =[1]Macro_Model!D7 -> 0.069071857 | E7: =[1]Macro_Model!E7 -> 0.056893599 | F7: =[1]Macro_Model!F7 -> 0.075282491 | G7: =[1]Macro_Model!G7 -> 0.051951253 | H7: =[1]Macro_Model!H7 -> 0.047004681 | I7: =[1]Macro_Model!I7 -> 0.035373157 | ... DB7: =[1]Macro_Model!DB7 -> 0.017418903
A8: IGP-M q/q | B8: =[1]Macro_Model!B8 -> 0.0277751 | C8: =[1]Macro_Model!C8 -> 0.028275291 | D8: =[1]Macro_Model!D8 -> 0.020898783 | E8: =[1]Macro_Model!E8 -> 0.031799424 | F8: =[1]Macro_Model!F8 -> 0.11323143 | G8: =[1]Macro_Model!G8 -> 0.024312626 | H8: =[1]Macro_Model!H8 -> 0.0069680368 | I8: =[1]Macro_Model!I8 -> 0.0097144444 | ... DB8: =[1]Macro_Model!DB8 -> 0.035
A9: IGP-M y/y | B9: =[1]Macro_Model!B9 -> 0.019435617 | C9: =[1]Macro_Model!C9 -> 0.051669676 | D9: =[1]Macro_Model!D9 -> 0.077734013 | E9: =[1]Macro_Model!E9 -> 0.11323143 | F9: =[1]Macro_Model!F9 -> 0.11323143 | G9: =[1]Macro_Model!G9 -> 0.10948106 | H9: =[1]Macro_Model!H9 -> 0.086491114 | I9: =[1]Macro_Model!I9 -> 0.074588186 | ... DB9: =[1]Macro_Model!DB9 -> 0.035
A10: IPCA q/q | B10: =[1]Macro_Model!B10 -> 0.020635673 | C10: =[1]Macro_Model!C10 -> 0.01002643 | D10: =[1]Macro_Model!D10 -> 0.0049988106 | E10: =[1]Macro_Model!E10 -> 0.02226281 | F10: =[1]Macro_Model!F10 -> 0.059086887 | G10: =[1]Macro_Model!G10 -> 0.02439696 | H10: =[1]Macro_Model!H10 -> 0.013956003 | I10: =[1]Macro_Model!I10 -> 0.010633971 | ... DB10: =[1]Macro_Model!DB10 -> 0.039494898
A11: IPCA y/y | B11: =[1]Macro_Model!B11 -> 0.051660025 | C11: =[1]Macro_Model!C11 -> 0.048410906 | D11: =[1]Macro_Model!D11 -> 0.047042196 | E11: =[1]Macro_Model!E11 -> 0.059086887 | F11: =[1]Macro_Model!F11 -> 0.059086887 | G11: =[1]Macro_Model!G11 -> 0.062989876 | H11: =[1]Macro_Model!H11 -> 0.067125507 | I11: =[1]Macro_Model!I11 -> 0.073109021 | ... DB11: =[1]Macro_Model!DB11 -> 0.039494898
A12: Selic rate (avg) | B12: =[1]Macro_Model!B12 -> 0.0875 | C12: =[1]Macro_Model!C12 -> 0.0975 | D12: =[1]Macro_Model!D12 -> 0.1075 | E12: =[1]Macro_Model!E12 -> 0.1075 | F12: =[1]Macro_Model!F12 -> 0.1 | G12: =[1]Macro_Model!G12 -> 0.11416667 | H12: =[1]Macro_Model!H12 -> 0.12083333 | I12: =[1]Macro_Model!I12 -> 0.12166667 | ... DB12: =[1]Macro_Model!DB12 -> 0.125
A13: CPI q/q
A14: CPI y/y
A15: Treasury rate

Sheet IS
A2: =Valuation!$A$2 -> CURY3 | TP R$44/sh
A3: Income Statement (R$000') | B3: =Macro!B$3 -> 1Q10 | C3: =Macro!C$3 -> 2Q10 | D3: =Macro!D$3 -> 3Q10 | E3: =Macro!E$3 -> 4Q10 | F3: =Macro!F$3 -> 2010 | G3: =Macro!G$3 -> 1Q11 | H3: =Macro!H$3 -> 2Q11 | I3: =Macro!I$3 -> 3Q11 | ... DB3: =Macro!DB$3 -> 2030E
A4: Gross revenues | B4: =B5+B6 -> 0 | C4: =C5+C6 -> 0 | D4: =D5+D6 -> 0 | E4: =E5+E6 -> 0 | F4: =SUM(B4:E4) -> 0 | G4: =G5+G6 -> 0 | H4: =H5+H6 -> 0 | I4: =I5+I6 -> 0 | J4: =J5+J6 -> 0 | K4: =SUM(G4:J4) -> 0 | L4: =L5+L6 -> 0 | M4: =M5+M6 -> 0 | N4: =N5+N6 -> 0 | O4: =O5+O6 -> 0 | P4: =SUM(L4:O4) -> 0 | Q4: =Q5+Q6 -> 0 | R4: =R5+R6 -> 0 | S4: =S5+S6 -> 0 | T4: =T5+T6 -> 0 | U4: =SUM(Q4:T4) -> 0 | V4: =V5+V6 -> 0 | W4: =W5+W6 -> 0 | X4: =X5+X6 -> 0 | Y4: =Y5+Y6 -> 0 | Z4: =SUM(V4:Y4) -> 0 | AA4: =AA5+AA6 -> 0 | AB4: =AB5+AB6 -> 0 | AC4: =AC5+AC6 -> 0 | AD4: =AD5+AD6 -> 0 | AE4: =SUM(AA4:AD4) -> 0 | AF4: =AF5+AF6 -> 0 | AG4: =AG5+AG6 -> 0 | AH4: =AH5+AH6 -> 0 | AI4: =AI5+AI6 -> 0 | AJ4: =SUM(AF4:AI4) -> 0 | AK4: =AK5+AK6 -> 169820.75 | AL4: =AL5+AL6 -> 212580.54 | AM4: =AM5+AM6 -> 221445.97 | AN4: =AN5+AN6 -> 227836.26 | AO4: =SUM(AK4:AN4) -> 831683.52 | AP4: =AP5+AP6 -> 151518.38 | AQ4: =AQ5+AQ6 -> 236895.71 | AR4: =AR5+AR6 -> 268901.91 | AS4: =AS5+AS6 -> 282485.37 | AT4: =SUM(AP4:AS4) -> 939801.36 | AU4: =AU5+AU6 -> 193287 | AV4: =AV5+AV6 -> 273610 | AW4: =AW5+AW6 -> 268175 | AX4: =AX5+AX6 -> 308715 | AY4: =SUM(AU4:AX4) -> 1043787 | AZ4: =AZ5+AZ6 -> 233098 | BA4: =BA5+BA6 -> 252454 | BB4: =BB5+BB6 -> 334505 | BC4: =BC5+BC6 -> 353014 | BD4: =SUM(AZ4:BC4) -> 1173071 | BE4: =BE5+BE6 -> 346976 | BF4: =BF5+BF6 -> 462074 | BG4: =BG5+BG6 -> 466696 | BH4: =BH5+BH6 -> 502424 | BI4: =SUM(BE4:BH4) -> 1778170 | BJ4: =BJ5+BJ6 -> 458170 | BK4: =BK5+BK6 -> 616407 | BL4: =BL5+BL6 -> 640437 | BM4: =BM5+BM6 -> 593421 | BN4: =SUM(BJ4:BM4) -> 2308435 | BO4: =BO5+BO6 -> 607423 | BP4: =BP5+BP6 -> 743352 | BQ4: =BQ5+BQ6 -> 768155 | BR4: =BR5+BR6 -> 829075 | BS4: =SUM(BO4:BR4) -> 2948005 | BT4: =BT5+BT6 -> 854925 | BU4: =BU5+BU6 -> 1017876 | BV4: =BV5+BV6 -> 1078346 | BW4: =BW5+BW6 -> 1056476 | BX4: =SUM(BT4:BW4) -> 4007623 | BY4: =BY5+BY6 -> 1244407 | BZ4: =BZ5+BZ6 -> 1375487 | CA4: =CA5+CA6 -> 1449421 | CB4: =CB5+CB6 -> 1453820 | CC4: =SUM(BY4:CB4) -> 5523135 | CD4: =CD5+CD6 -> 1644474 | CE4: =CE5+CE6 -> 1725754 | CF4: =CF5+CF6 -> 1788351.1 | CG4: =CG5+CG6 -> 1817747 | CH4: =SUM(CD4:CG4) -> 6976326.1 | CI4: =CI5+CI6 -> 1922523.3 | CJ4: =CJ5+CJ6 -> 2187740.6 | CK4: =CK5+CK6 -> 2212729.7 | CL4: =CL5+CL6 -> 2102030.1 | CM4: =SUM(CI4:CL4) -> 8425023.7 | CN4: =CN5+CN6 -> 2209158.7 | CO4: =CO5+CO6 -> 2383613.7 | CP4: =CP5+CP6 -> 2406821.1 | CQ4: =CQ5+CQ6 -> 2350310.3 | CR4: =SUM(CN4:CQ4) -> 9349903.9 | CS4: =CS5+CS6 -> 2431933.4 | CT4: =CT5+CT6 -> 2590266.9 | CU4: =CU5+CU6 -> 2596876.6 | CV4: =CV5+CV6 -> 2524426.7 | CW4: =SUM(CS4:CV4) -> 10143503 | CX4: =CX5+CX6 -> 2598266.2 | CY4: =CY5+CY6 -> 2753812.5 | CZ4: =CZ5+CZ6 -> 2753116.3 | DA4: =DA5+DA6 -> 2671374.3 | DB4: =SUM(CX4:DA4) -> 10776569
A5: Development revenues | F5: =SUM(B5:E5) -> 0 | K5: =SUM(G5:J5) -> 0 | P5: =SUM(L5:O5) -> 0 | U5: =SUM(Q5:T5) -> 0 | Z5: =SUM(V5:Y5) -> 0 | AE5: =SUM(AA5:AD5) -> 0 | AJ5: =SUM(AF5:AI5) -> 0 | AK5: =AK9/(1-AK8) -> 169820.75 | AL5: =AL9/(1-AL8) -> 212580.54 | AM5: =AM9/(1-AM8) -> 221445.97 | AN5: =AN9/(1-AN8) -> 227836.26 | AO5: =SUM(AK5:AN5) -> 831683.52 | AP5: =AP9/(1-AP8) -> 151518.38 | AQ5: =AQ9/(1-AQ8) -> 236895.71 | AR5: =AR9/(1-AR8) -> 268901.91 | AS5: =AS9/(1-AS8) -> 282485.37 | AT5: =SUM(AP5:AS5) -> 939801.36 | AU5: =193732-2076 -> 191656 | AV5: =248291-3205 -> 245086 | AW5: =268629-1695 -> 266934 | AX5: =1063367-24443-8342+100-SUM(AU5:AW5) -> 327006 | AY5: =SUM(AU5:AX5) -> 1030682 | AZ5: =234242-1985 -> 232257 | BA5: =263860-11578-507 -> 251775 | BB5: =830029-8974-3617-SUM(AZ5:BA5) -> 333406 | BC5: =1183813-16767-4243-SUM(AZ5:BB5) -> 345365 | BD5: =SUM(AZ5:BC5) -> 1162803 | BE5: =348556-1130-1564 -> 345862 | BF5: =467360-4492-2158 -> 460710 | BG5: =1290410-12155-6059-SUM(BE5:BF5) -> 465624 | BH5: =1795292-13083-8289-SUM(BE5:BG5) -> 501724 | BI5: =SUM(BE5:BH5) -> 1773920 | BJ5: =459417-740-1572 -> 457105 | BK5: =619527-4298-578 -> 614651 | BL5: =1720898-8316-1765-SUM(BJ5:BK5) -> 639061 | BM5: =2318165-11358-3745-SUM(BJ5:BL5) -> 592245 | BN5: =SUM(BJ5:BM5) -> 2303062 | BO5: =608998-1086-2065 -> 605847 | BP5: =743265-382-704 -> 742179 | BQ5: =767232-2543+1829 -> 766518 | BR5: =2950126-1185-6289-SUM(BO5:BQ5) -> 828108 | BS5: =SUM(BO5:BR5) -> 2942652 | BT5: =851906-1722+2980 -> 853164 | BU5: =1016524+2082-1667 -> 1016939 | BV5: =1084539-6033-160 -> 1078346 | BW5: =4016820+2114-14025-SUM(BT5:BV5) -> 1056460 | BX5: =SUM(BT5:BW5) -> 4004909 | BY5: =1246115-6033-2089 -> 1237993 | BZ5: =1393733-4822-13805 -> 1375106 | CA5: =1461895-3018-11780 -> 1447097 | CB5: =5567252-11984-42968-SUM(BY5:CA5) -> 1452104 | CC5: =SUM(BY5:CB5) -> 5512300 | CD5: =1660432-17750+353 -> 1643035 | CE5: =1742831-3187-14445 -> 1725199 | CF5: =Operating!CF35 -> 1787776 | CG5: =Operating!CG35 -> 1817162.4 | CH5: =SUM(CD5:CG5) -> 6973172.4 | CI5: =Operating!CI35 -> 1921905 | CJ5: =Operating!CJ35 -> 2187037.1 | CK5: =Operating!CK35 -> 2212018.1 | CL5: =Operating!CL35 -> 2101354.1 | CM5: =SUM(CI5:CL5) -> 8422314.3 | CN5: =Operating!CN35 -> 2208448.3 | CO5: =Operating!CO35 -> 2382847.1 | CP5: =Operating!CP35 -> 2406047.1 | CQ5: =Operating!CQ35 -> 2349554.5 | CR5: =SUM(CN5:CQ5) -> 9346897 | CS5: =Operating!CS35 -> 2431151.3 | CT5: =Operating!CT35 -> 2589433.8 | CU5: =Operating!CU35 -> 2596041.4 | CV5: =Operating!CV35 -> 2523614.8 | CW5: =SUM(CS5:CV5) -> 10140241 | CX5: =Operating!CX35 -> 2597430.6 | CY5: =Operating!CY35 -> 2752926.8 | CZ5: =Operating!CZ35 -> 2752230.9 | DA5: =Operating!DA35 -> 2670515.2 | DB5: =SUM(CX5:DA5) -> 10773104
A6: Service revenues | F6: =SUM(B6:E6) -> 0 | K6: =SUM(G6:J6) -> 0 | P6: =SUM(L6:O6) -> 0 | U6: =SUM(Q6:T6) -> 0 | Z6: =SUM(V6:Y6) -> 0 | AE6: =SUM(AA6:AD6) -> 0 | AJ6: =SUM(AF6:AI6) -> 0 | AO6: =SUM(AK6:AN6) -> 0 | AT6: =SUM(AP6:AS6) -> 0 | AU6: 1631 | AV6: 28524 | AW6: 1241 | AX6: =13105-SUM(AU6:AW6) -> -18291 | AY6: =SUM(AU6:AX6) -> 13105 | AZ6: 841 | BA6: 679 | BB6: =2619-SUM(AZ6:BA6) -> 1099 | BC6: =10268-SUM(AZ6:BB6) -> 7649 | BD6: =SUM(AZ6:BC6) -> 10268 | BE6: 1114 | BF6: 1364 | BG6: =3550-SUM(BE6:BF6) -> 1072 | BH6: =4250-SUM(BE6:BG6) -> 700 | BI6: =SUM(BE6:BH6) -> 4250 | BJ6: 1065 | BK6: 1756 | BL6: =4197-SUM(BJ6:BK6) -> 1376 | BM6: =5373-SUM(BJ6:BL6) -> 1176 | BN6: =SUM(BJ6:BM6) -> 5373 | BO6: 1576 | BP6: 1173 | BQ6: 1637 | BR6: =5353-SUM(BO6:BQ6) -> 967 | BS6: =SUM(BO6:BR6) -> 5353 | BT6: 1761 | BU6: 937 | BV6: 0 | BW6: =2714-SUM(BT6:BV6) -> 16 | BX6: =SUM(BT6:BW6) -> 2714 | BY6: 6414 | BZ6: 381 | CA6: 2324 | CB6: =10835-SUM(BY6:CA6) -> 1716 | CC6: =SUM(BY6:CB6) -> 10835 | CD6: 1439 | CE6: 555 | CF6: =Operating!CF41 -> 575.13114 | CG6: =Operating!CG41 -> 584.58482 | CH6: =SUM(CD6:CG6) -> 3153.716 | CI6: =Operating!CI41 -> 618.28072 | CJ6: =Operating!CJ41 -> 703.57424 | CK6: =Operating!CK41 -> 711.61068 | CL6: =Operating!CL41 -> 676.00985 | CM6: =SUM(CI6:CL6) -> 2709.4755 | CN6: =Operating!CN41 -> 710.46226 | CO6: =Operating!CO41 -> 766.56673 | CP6: =Operating!CP41 -> 774.0302 | CQ6: =Operating!CQ41 -> 755.85642 | CR6: =SUM(CN6:CQ6) -> 3006.9156 | CS6: =Operating!CS41 -> 782.10627 | CT6: =Operating!CT41 -> 833.02609 | CU6: =Operating!CU41 -> 835.15176 | CV6: =Operating!CV41 -> 811.85198 | CW6: =SUM(CS6:CV6) -> 3262.1361 | CX6: =Operating!CX41 -> 835.59866 | CY6: =Operating!CY41 -> 885.62212 | CZ6: =Operating!CZ41 -> 885.39824 | DA6: =Operating!DA41 -> 859.11013 | DB6: =SUM(CX6:DA6) -> 3465.7292
A7: Taxes and deductions | F7: =SUM(B7:E7) -> 0 | K7: =SUM(G7:J7) -> 0 | P7: =SUM(L7:O7) -> 0 | U7: =SUM(Q7:T7) -> 0 | Z7: =SUM(V7:Y7) -> 0 | AE7: =SUM(AA7:AD7) -> 0 | AJ7: =SUM(AF7:AI7) -> 0 | AK7: =AK9-AK5 -> -3532.2716 | AL7: =AL9-AL5 -> -4421.6751 | AM7: =AM9-AM5 -> -4606.0762 | AN7: =AN9-AN5 -> -4738.9943 | AO7: =SUM(AK7:AN7) -> -17299.017 | AP7: =AP9-AP5 -> -3151.5822 | AQ7: =AQ9-AQ5 -> -4927.4307 | AR7: =AR9-AR5 -> -5593.1598 | AS7: =AS9-AS5 -> -5875.6957 | AT7: =SUM(AP7:AS7) -> -19547.868 | AU7: -4917 | AV7: -5877 | AW7: -6651 | AX7: =-24510-SUM(AU7:AW7) -> -7065 | AY7: =SUM(AU7:AX7) -> -24510 | AZ7: -5777 | BA7: -6250 | BB7: =-20635-SUM(AZ7:BA7) -> -8608 | BC7: =-28389-SUM(AZ7:BB7) -> -7754 | BD7: =SUM(AZ7:BC7) -> -28389 | BE7: -7690 | BF7: -10737 | BG7: =-28674-SUM(BE7:BF7) -> -10247 | BH7: =-39875-SUM(BE7:BG7) -> -11201 | BI7: =SUM(BE7:BH7) -> -39875 | BJ7: -10796 | BK7: -13624 | BL7: =-38198-SUM(BJ7:BK7) -> -13778 | BM7: =-51141-SUM(BJ7:BL7) -> -12943 | BN7: =SUM(BJ7:BM7) -> -51141 | BO7: -12467 | BP7: -15606 | BQ7: -16281 | BR7: =-61833-SUM(BO7:BQ7) -> -17479 | BS7: =SUM(BO7:BR7) -> -61833 | BT7: -17543 | BU7: -19791 | BV7: -22474 | BW7: =-81313-SUM(BT7:BV7) -> -21505 | BX7: =SUM(BT7:BW7) -> -81313 | BY7: -28223 | BZ7: -28888 | CA7: -32495 | CB7: =-123711-SUM(BY7:CA7) -> -34105 | CC7: =SUM(BY7:CB7) -> -123711 | CD7: -31903 | CE7: -35160 | CF7: =-CF8*CF$4 -> -37197.703 | CG7: =-CG8*CG$4 -> -37809.138 | CH7: =SUM(CD7:CG7) -> -142069.84 | CI7: =-CI8*CI$4 -> -39988.485 | CJ7: =-CJ8*CJ$4 -> -45505.005 | CK7: =-CK8*CK$4 -> -46024.778 | CL7: =-CL8*CL$4 -> -43722.226 | CM7: =SUM(CI7:CL7) -> -175240.49 | CN7: =-CN8*CN$4 -> -45950.501 | CO7: =-CO8*CO$4 -> -49579.165 | CP7: =-CP8*CP$4 -> -50061.879 | CQ7: =-CQ8*CQ$4 -> -48886.455 | CR7: =SUM(CN7:CQ7) -> -194478 | CS7: =-CS8*CS$4 -> -50584.214 | CT7: =-CT8*CT$4 -> -53877.551 | CU7: =-CU8*CU$4 -> -54015.032 | CV7: =-CV8*CV$4 -> -52508.075 | CW7: =SUM(CS7:CV7) -> -210984.87 | CX7: =-CX8*CX$4 -> -54043.937 | CY7: =-CY8*CY$4 -> -57279.299 | CZ7: =-CZ8*CZ$4 -> -57264.819 | DA7: =-DA8*DA$4 -> -55564.586 | DB7: =SUM(CX7:DA7) -> -224152.64
A8: % of gross revenues | B8: =-B7/B$4 -> #DIV/0! | C8: =-C7/C$4 -> #DIV/0! | D8: =-D7/D$4 -> #DIV/0! | E8: =-E7/E$4 -> #DIV/0! | F8: =-F7/F$4 -> #DIV/0! | G8: =-G7/G$4 -> #DIV/0! | H8: =-H7/H$4 -> #DIV/0! | I8: =-I7/I$4 -> #DIV/0! | ... AJ8: =-AJ7/AJ$4 -> #DIV/0! | AK8: 0.0208 | AL8: 0.0208 | AM8: 0.0208 | AN8: 0.0208 | AO8: =-AO7/AO$4 -> 0.0208 | AP8: 0.0208 | AQ8: 0.0208 | AR8: 0.0208 | AS8: 0.0208 | AT8: =-AT7/AT$4 -> 0.0208 | AU8: =-AU7/AU$4 -> 0.025438855 | AV8: =-AV7/AV$4 -> 0.021479478 | AW8: =-AW7/AW$4 -> 0.02480097 | AX8: =-AX7/AX$4 -> 0.022885185 | AY8: =-AY7/AY$4 -> 0.023481802 | AZ8: =-AZ7/AZ$4 -> 0.024783567 | BA8: =-BA7/BA$4 -> 0.024756985 | ... CE8: =-CE7/CE$4 -> 0.020373703 | CF8: 0.0208 | CG8: 0.0208 | CH8: =-CH7/CH$4 -> 0.020364564 | CI8: 0.0208 | CJ8: 0.0208 | CK8: 0.0208 | CL8: 0.0208 | CM8: =-CM7/CM$4 -> 0.0208 | CN8: 0.0208 | CO8: 0.0208 | CP8: 0.0208 | CQ8: 0.0208 | CR8: =-CR7/CR$4 -> 0.0208 | CS8: 0.0208 | CT8: 0.0208 | CU8: 0.0208 | CV8: 0.0208 | CW8: =-CW7/CW$4 -> 0.0208 | CX8: 0.0208 | CY8: 0.0208 | CZ8: 0.0208 | DA8: 0.0208 | DB8: =-DB7/DB$4 -> 0.0208
A9: Net Revenues | B9: =B4+B7 -> 0 | C9: =C4+C7 -> 0 | D9: =D4+D7 -> 0 | E9: =E4+E7 -> 0 | F9: =SUM(B9:E9) -> 0 | G9: =G4+G7 -> 0 | H9: =H4+H7 -> 0 | I9: =I4+I7 -> 0 | J9: =J4+J7 -> 0 | K9: =SUM(G9:J9) -> 0 | L9: =L4+L7 -> 0 | M9: =M4+M7 -> 0 | N9: =N4+N7 -> 0 | O9: =O4+O7 -> 0 | P9: =SUM(L9:O9) -> 0 | Q9: =Q4+Q7 -> 0 | R9: =R4+R7 -> 0 | S9: =S4+S7 -> 0 | T9: =T4+T7 -> 0 | U9: =SUM(Q9:T9) -> 0 | V9: =V4+V7 -> 0 | W9: =W4+W7 -> 0 | X9: =X4+X7 -> 0 | Y9: =Y4+Y7 -> 0 | Z9: =SUM(V9:Y9) -> 0 | AA9: =AA4+AA7 -> 0 | AB9: =AB4+AB7 -> 0 | AC9: =AC4+AC7 -> 0 | AD9: =AD4+AD7 -> 0 | AE9: =SUM(AA9:AD9) -> 0 | AF9: =AF4+AF7 -> 0 | AG9: =AG4+AG7 -> 0 | AH9: =AH4+AH7 -> 0 | AI9: =AI4+AI7 -> 0 | AJ9: =SUM(AF9:AI9) -> 0 | AK9: 166288.48 | AL9: 208158.86 | AM9: 216839.89 | AN9: 223097.27 | AO9: =SUM(AK9:AN9) -> 814384.5 | AP9: 148366.79 | AQ9: 231968.28 | AR9: 263308.75 | AS9: 276609.67 | AT9: =SUM(AP9:AS9) -> 920253.5 | AU9: =AU4+AU7 -> 188370 | AV9: =AV4+AV7 -> 267733 | AW9: =AW4+AW7 -> 261524 | AX9: =AX4+AX7 -> 301650 | AY9: =SUM(AU9:AX9) -> 1019277 | AZ9: =AZ4+AZ7 -> 227321 | BA9: =BA4+BA7 -> 246204 | BB9: =BB4+BB7 -> 325897 | BC9: =BC4+BC7 -> 345260 | BD9: =SUM(AZ9:BC9) -> 1144682 | BE9: =BE4+BE7 -> 339286 | BF9: =BF4+BF7 -> 451337 | BG9: =BG4+BG7 -> 456449 | BH9: =BH4+BH7 -> 491223 | BI9: =SUM(BE9:BH9) -> 1738295 | BJ9: =BJ4+BJ7 -> 447374 | BK9: =BK4+BK7 -> 602783 | BL9: =BL4+BL7 -> 626659 | BM9: =BM4+BM7 -> 580478 | BN9: =SUM(BJ9:BM9) -> 2257294 | BO9: =BO4+BO7 -> 594956 | BP9: =BP4+BP7 -> 727746 | BQ9: =BQ4+BQ7 -> 751874 | BR9: =BR4+BR7 -> 811596 | BS9: =SUM(BO9:BR9) -> 2886172 | BT9: =BT4+BT7 -> 837382 | BU9: =BU4+BU7 -> 998085 | BV9: =BV4+BV7 -> 1055872 | BW9: =BW4+BW7 -> 1034971 | BX9: =SUM(BT9:BW9) -> 3926310 | BY9: =BY4+BY7 -> 1216184 | BZ9: =BZ4+BZ7 -> 1346599 | CA9: =CA4+CA7 -> 1416926 | CB9: =CB4+CB7 -> 1419715 | CC9: =SUM(BY9:CB9) -> 5399424 | CD9: =CD4+CD7 -> 1612571 | CE9: =CE4+CE7 -> 1690594 | CF9: =CF4+CF7 -> 1751153.4 | CG9: =CG4+CG7 -> 1779937.9 | CH9: =SUM(CD9:CG9) -> 6834256.3 | CI9: =CI4+CI7 -> 1882534.8 | CJ9: =CJ4+CJ7 -> 2142235.6 | CK9: =CK4+CK7 -> 2166704.9 | CL9: =CL4+CL7 -> 2058307.9 | CM9: =SUM(CI9:CL9) -> 8249783.2 | CN9: =CN4+CN7 -> 2163208.2 | CO9: =CO4+CO7 -> 2334034.5 | CP9: =CP4+CP7 -> 2356759.2 | CQ9: =CQ4+CQ7 -> 2301423.9 | CR9: =SUM(CN9:CQ9) -> 9155425.9 | CS9: =CS4+CS7 -> 2381349.2 | CT9: =CT4+CT7 -> 2536389.3 | CU9: =CU4+CU7 -> 2542861.5 | CV9: =CV4+CV7 -> 2471918.6 | CW9: =SUM(CS9:CV9) -> 9932518.6 | CX9: =CX4+CX7 -> 2544222.2 | CY9: =CY4+CY7 -> 2696533.2 | CZ9: =CZ4+CZ7 -> 2695851.5 | DA9: =DA4+DA7 -> 2615809.7 | DB9: =SUM(CX9:DA9) -> 10552417
A10: Operating Costs | B10: =B11+B13+B14 -> 0 | C10: =C11+C13+C14 -> 0 | D10: =D11+D13+D14 -> 0 | E10: =E11+E13+E14 -> 0 | F10: =SUM(B10:E10) -> 0 | G10: =G11+G13+G14 -> 0 | H10: =H11+H13+H14 -> 0 | I10: =I11+I13+I14 -> 0 | J10: =J11+J13+J14 -> 0 | K10: =SUM(G10:J10) -> 0 | L10: =L11+L13+L14 -> 0 | M10: =M11+M13+M14 -> 0 | N10: =N11+N13+N14 -> 0 | O10: =O11+O13+O14 -> 0 | P10: =SUM(L10:O10) -> 0 | Q10: =Q11+Q13+Q14 -> 0 | R10: =R11+R13+R14 -> 0 | S10: =S11+S13+S14 -> 0 | T10: =T11+T13+T14 -> 0 | U10: =SUM(Q10:T10) -> 0 | V10: =V11+V13+V14 -> 0 | W10: =W11+W13+W14 -> 0 | X10: =X11+X13+X14 -> 0 | Y10: =Y11+Y13+Y14 -> 0 | Z10: =SUM(V10:Y10) -> 0 | AA10: =AA11+AA13+AA14 -> 0 | AB10: =AB11+AB13+AB14 -> 0 | AC10: =AC11+AC13+AC14 -> 0 | AD10: =AD11+AD13+AD14 -> 0 | AE10: =SUM(AA10:AD10) -> 0 | AF10: =AF11+AF13+AF14 -> 0 | AG10: =AG11+AG13+AG14 -> 0 | AH10: =AH11+AH13+AH14 -> 0 | AI10: =AI11+AI13+AI14 -> 0 | AJ10: =SUM(AF10:AI10) -> 0 | AK10: =AK11+AK13+AK14 -> -128091.89 | AL10: =AL11+AL13+AL14 -> -152984.22 | AM10: =AM11+AM13+AM14 -> -151238.84 | AN10: =AN11+AN13+AN14 -> -138225.36 | AO10: =SUM(AK10:AN10) -> -570540.31 | AP10: =AP11+AP13+AP14 -> -103828.06 | AQ10: =AQ11+AQ13+AQ14 -> -159413.27 | AR10: =AR11+AR13+AR14 -> -165749.62 | AS10: =AS11+AS13+AS14 -> -176534.66 | AT10: =SUM(AP10:AS10) -> -605525.61 | AU10: =AU11+AU13+AU14 -> -133039 | AV10: =AV11+AV13+AV14 -> -166982 | AW10: =AW11+AW13+AW14 -> -180689 | AX10: =AX11+AX13+AX14 -> -182682 | AY10: =SUM(AU10:AX10) -> -663392 | AZ10: =AZ11+AZ13+AZ14 -> -149181 | BA10: =BA11+BA13+BA14 -> -159137 | BB10: =BB11+BB13+BB14 -> -202541 | BC10: =BC11+BC13+BC14 -> -205433 | BD10: =SUM(AZ10:BC10) -> -716292 | BE10: =BE11+BE13+BE14 -> -218944 | BF10: =BF11+BF13+BF14 -> -288421 | BG10: =BG11+BG13+BG14 -> -281478 | BH10: =BH11+BH13+BH14 -> -304781 | BI10: =SUM(BE10:BH10) -> -1093624 | BJ10: =BJ11+BJ13+BJ14 -> -281465 | BK10: =BK11+BK13+BK14 -> -387286 | BL10: =BL11+BL13+BL14 -> -392916 | BM10: =BM11+BM13+BM14 -> -358735 | BN10: =SUM(BJ10:BM10) -> -1420402 | BO10: =BO11+BO13+BO14 -> -371794 | BP10: =BP11+BP13+BP14 -> -453192 | BQ10: =BQ11+BQ13+BQ14 -> -467971 | BR10: =BR11+BR13+BR14 -> -497862 | BS10: =SUM(BO10:BR10) -> -1790819 | BT10: =BT11+BT13+BT14 -> -520773 | BU10: =BU11+BU13+BU14 -> -615554 | BV10: =BV11+BV13+BV14 -> -646426 | BW10: =BW11+BW13+BW14 -> -630617 | BX10: =SUM(BT10:BW10) -> -2413370 | BY10: =BY11+BY13+BY14 -> -741296 | BZ10: =BZ11+BZ13+BZ14 -> -813823 | CA10: =CA11+CA13+CA14 -> -850699 | CB10: =CB11+CB13+CB14 -> -847019 | CC10: =SUM(BY10:CB10) -> -3252837 | CD10: =CD11+CD13+CD14 -> -982915 | CE10: =CE11+CE13+CE14 -> -1022232 | CF10: =CF11+CF13+CF14 -> -1052994.3 | CG10: =CG11+CG13+CG14 -> -1072359 | CH10: =SUM(CD10:CG10) -> -4130500.3 | CI10: =CI11+CI13+CI14 -> -1144943.6 | CJ10: =CJ11+CJ13+CJ14 -> -1292162.2 | CK10: =CK11+CK13+CK14 -> -1297905.5 | CL10: =CL11+CL13+CL14 -> -1228667.6 | CM10: =SUM(CI10:CL10) -> -4963679 | CN10: =CN11+CN13+CN14 -> -1319066.6 | CO10: =CO11+CO13+CO14 -> -1426000.7 | CP10: =CP11+CP13+CP14 -> -1444561.5 | CQ10: =CQ11+CQ13+CQ14 -> -1411852 | CR10: =SUM(CN10:CQ10) -> -5601480.8 | CS10: =CS11+CS13+CS14 -> -1470743.5 | CT10: =CT11+CT13+CT14 -> -1570168.6 | CU10: =CU11+CU13+CU14 -> -1579946.6 | CV10: =CV11+CV13+CV14 -> -1537500.9 | CW10: =SUM(CS10:CV10) -> -6158359.6 | CX10: =CX11+CX13+CX14 -> -1582104.5 | CY10: =CY11+CY13+CY14 -> -1679258.8 | CZ10: =CZ11+CZ13+CZ14 -> -1684471 | DA10: =DA11+DA13+DA14 -> -1635900.3 | DB10: =SUM(CX10:DA10) -> -6581734.5
A11: Development costs | F11: =SUM(B11:E11) -> 0 | K11: =SUM(G11:J11) -> 0 | P11: =SUM(L11:O11) -> 0 | U11: =SUM(Q11:T11) -> 0 | Z11: =SUM(V11:Y11) -> 0 | AE11: =SUM(AA11:AD11) -> 0 | AJ11: =SUM(AF11:AI11) -> 0 | AK11: -128091.89 | AL11: -152984.22 | AM11: -151238.84 | AN11: -138225.36 | AO11: =SUM(AK11:AN11) -> -570540.31 | AP11: -103828.06 | AQ11: -159413.27 | AR11: -165749.62 | AS11: -176534.66 | AT11: =SUM(AP11:AS11) -> -605525.61 | AU11: =-124775-AU13 -> -122991 | AV11: =-158457-AV13 -> -156928 | AW11: =-180689-AW13-AW14 -> -171768 | AX11: =-634880-SUM(AU11:AW11)-SUM(AU13:AX13) -> -176867 | AY11: =SUM(AU11:AX11) -> -628554 | AZ11: =-139488-AZ13 -> -138123 | BA11: =-149870-BA13 -> -148184 | BB11: =-202541-BB13-BB14 -> -196526 | BC11: =-682997-SUM(AZ11:BB11)-SUM(AZ13:BC13) -> -195949 | BD11: =SUM(AZ11:BC11) -> -678782 | BE11: =-213294-BE13+1020-122 -> -212274 | BF11: =-283327+2687 -> -280640 | BG11: =-275625-5853-BG13-BG14 -> -271663 | BH11: =-1082692-SUM(BE11:BG11)-SUM(BE13:BH13) -> -316781 | BI11: =SUM(BE11:BH11) -> -1081358 | BJ11: =-279593-BJ13+604-607 -> -278989 | BK11: =-388579+2608 -> -385971 | BL11: =-391796-1120-BL13-BL14 -> -383036 | BM11: =-1415751-SUM(BJ11:BL11)-SUM(BJ13:BM13) -> -364471 | BN11: =SUM(BJ11:BM11) -> -1412467 | BO11: =-371450-BO13+1477-1299 -> -369973 | BP11: =-452163+725 -> -451438 | BQ11: =-463481-2863 -> -466344 | BR11: =-1789464-SUM(BO11:BQ11)-SUM(BO13:BR13) -> -495745 | BS11: =SUM(BO11:BR11) -> -1783500 | BT11: =-515984-BT13-2219-1856 -> -518203 | BU11: =-611200-1474 -> -612674 | BV11: =-643412+660 -> -642752 | BW11: =-2410748-SUM(BT11:BV11)-SUM(BT13:BW13) -> -628758 | BX11: =SUM(BT11:BW11) -> -2402387 | BY11: =-740484-BY13+1505-1711 -> -738979 | BZ11: =-812123+2758 -> -809365 | CA11: =-848164+1716 -> -846448 | CB11: =-3248989-SUM(BY11:CA11)-SUM(BY13:CB13) -> -841641 | CC11: =SUM(BY11:CB11) -> -3236433 | CD11: =-982117-CD13 -> -977874 | CE11: =-1021269-CE13 -> -1015994 | CF11: =-(1-CF12)*CF5 -> -1050671.7 | CG11: =-(1-CG12)*CG5 -> -1070567 | CH11: =SUM(CD11:CG11) -> -4115106.7 | CI11: =-(1-CI12)*CI5 -> -1134817 | CJ11: =-(1-CJ12)*CJ5 -> -1286483.3 | CK11: =-(1-CK12)*CK5 -> -1292383.2 | CL11: =-(1-CL12)*CL5 -> -1223499.4 | CM11: =SUM(CI11:CL11) -> -4937182.9 | CN11: =-(1-CN12)*CN5 -> -1315759.5 | CO11: =-(1-CO12)*CO5 -> -1424092.8 | CP11: =-(1-CP12)*CP5 -> -1440027.9 | CQ11: =-(1-CQ12)*CQ5 -> -1407292.4 | CR11: =SUM(CN11:CQ11) -> -5587172.7 | CS11: =-(1-CS12)*CS5 -> -1469208.3 | CT11: =-(1-CT12)*CT5 -> -1569730.1 | CU11: =-(1-CU12)*CU5 -> -1576021 | CV11: =-(1-CV12)*CV5 -> -1533238.4 | CW11: =SUM(CS11:CV11) -> -6148197.8 | CX11: =-(1-CX12)*CX5 -> -1581059.4 | CY11: =-(1-CY12)*CY5 -> -1679333.2 | CZ11: =-(1-CZ12)*CZ5 -> -1680614.3 | DA11: =-(1-DA12)*DA5 -> -1631601.8 | DB11: =SUM(CX11:DA11) -> -6572608.7
A12: Development gross margin (%) | B12: =(1+B11/B5) -> #DIV/0! | C12: =(1+C11/C5) -> #DIV/0! | D12: =(1+D11/D5) -> #DIV/0! | E12: =(1+E11/E5) -> #DIV/0! | F12: =(1+F11/F5) -> #DIV/0! | G12: =(1+G11/G5) -> #DIV/0! | H12: =(1+H11/H5) -> #DIV/0! | I12: =(1+I11/I5) -> #DIV/0! | ... CE12: =(1+CE11/CE5) -> 0.41108591 | CF12: =(CF118*Operating!CF37+CE110*Operating!CF39)/Operating!CF35 -> 0.41230238 | CG12: =(CG118*Operating!CG37+CF110*Operating!CG39)/Operating!CG35 -> 0.41085783 | CH12: =(1+CH11/CH5) -> 0.40986592 | CI12: =(CI118*Operating!CI37+CH110*Operating!CI39)/Operating!CI35-0.25% -> 0.40953531 | CJ12: =(CJ118*Operating!CJ37+CI110*Operating!CJ39)/Operating!CJ35+0.25% -> 0.41176889 | CK12: =(CK118*Operating!CK37+CJ110*Operating!CK39)/Operating!CK35+0.75% -> 0.41574474 | CL12: =(CL118*Operating!CL37+CK110*Operating!CL39)/Operating!CL35+1% -> 0.41775669 | CM12: =(1+CM11/CM5) -> 0.41379736 | CN12: =(CN118*Operating!CN37+CM110*Operating!CN39)/Operating!CN35 -> 0.40421537 | CO12: =(CO118*Operating!CO37+CN110*Operating!CO39)/Operating!CO35 -> 0.40235662 | CP12: =(CP118*Operating!CP37+CO110*Operating!CP39)/Operating!CP35 -> 0.40149635 | CQ12: =(CQ118*Operating!CQ37+CP110*Operating!CQ39)/Operating!CQ35 -> 0.40103864 | CR12: =(1+CR11/CR5) -> 0.40224305 | CS12: =(CS118*Operating!CS37+CR110*Operating!CS39)/Operating!CS35 -> 0.39567386 | CT12: =(CT118*Operating!CT37+CS110*Operating!CT39)/Operating!CT35 -> 0.39379408 | CU12: =(CU118*Operating!CU37+CT110*Operating!CU39)/Operating!CU35 -> 0.39291377 | CV12: =(CV118*Operating!CV37+CU110*Operating!CV39)/Operating!CV35 -> 0.39244358 | CW12: =(1+CW11/CW5) -> 0.39368329 | CX12: =(CX118*Operating!CX37+CW110*Operating!CX39)/Operating!CX35 -> 0.3912987 | CY12: =(CY118*Operating!CY37+CX110*Operating!CY39)/Operating!CY35 -> 0.38998261 | CZ12: =(CZ118*Operating!CZ37+CY110*Operating!CZ39)/Operating!CZ35 -> 0.38936291 | DA12: =(DA118*Operating!DA37+CZ110*Operating!DA39)/Operating!DA35 -> 0.38903107 | DB12: =(1+DB11/DB5) -> 0.38990573
A13: Capitalized interest expenses | F13: =SUM(B13:E13) -> 0 | K13: =SUM(G13:J13) -> 0 | P13: =SUM(L13:O13) -> 0 | U13: =SUM(Q13:T13) -> 0 | Z13: =SUM(V13:Y13) -> 0 | AE13: =SUM(AA13:AD13) -> 0 | AJ13: =SUM(AF13:AI13) -> 0 | AO13: =SUM(AK13:AN13) -> 0 | AT13: =SUM(AP13:AS13) -> 0 | AU13: -1784 | AV13: -1529 | AW13: -1146 | AX13: =-6326-SUM(AU13:AW13) -> -1867 | AY13: =SUM(AU13:AX13) -> -6326 | AZ13: -1365 | BA13: -1686 | BB13: -409 | BC13: =-4215-SUM(AZ13:BB13) -> -755 | BD13: =SUM(AZ13:BC13) -> -4215 | BE13: -122 | BF13: -142 | BG13: -339 | BH13: =-1334-SUM(BE13:BG13) -> -731 | BI13: =SUM(BE13:BH13) -> -1334 | BJ13: -607 | BK13: -564 | BL13: -1100 | BM13: =-3284-SUM(BJ13:BL13) -> -1013 | BN13: =SUM(BJ13:BM13) -> -3284 | BO13: -1299 | BP13: -1415 | BQ13: -1489 | BR13: =-5964-SUM(BO13:BQ13) -> -1761 | BS13: =SUM(BO13:BR13) -> -5964 | BT13: -1856 | BU13: -2127 | BV13: -2041 | BW13: =-8361-SUM(BT13:BV13) -> -2337 | BX13: =SUM(BT13:BW13) -> -8361 | BY13: -1711 | BZ13: -3457 | CA13: -3061 | CB13: =-12556-SUM(BY13:CA13) -> -4327 | CC13: =SUM(BY13:CB13) -> -12556 | CD13: -4243 | CE13: -5275 | CF13: =-('BS & FCF'!CE144/(Operating!CE26+Operating!CE27))*Operating!CF37-0.15%*Operating!CF39 -> -1324.691 | CG13: =-('BS & FCF'!CF144/(Operating!CF26+Operating!CF27))*Operating!CG37-0.15%*Operating!CG39 -> -777.64985 | CH13: =SUM(CD13:CG13) -> -11620.341 | CI13: =-('BS & FCF'!CH144/(Operating!CH26+Operating!CH27))*Operating!CI37-1%*Operating!CI39 -> -9053.7812 | CJ13: =-('BS & FCF'!CI144/(Operating!CI26+Operating!CI27))*Operating!CJ37-1%*Operating!CJ39 -> -4458.1304 | CK13: =-('BS & FCF'!CJ144/(Operating!CJ26+Operating!CJ27))*Operating!CK37-1%*Operating!CK39 -> -4287.5977 | CL13: =-('BS & FCF'!CK144/(Operating!CK26+Operating!CK27))*Operating!CL37-1%*Operating!CL39 -> -3995.3233 | CM13: =SUM(CI13:CL13) -> -21794.833 | CN13: =-('BS & FCF'!CM144/(Operating!CM26+Operating!CM27))*Operating!CN37-1%*Operating!CN39 -> -2074.3152 | CO13: =-('BS & FCF'!CN144/(Operating!CN26+Operating!CN27))*Operating!CO37-1%*Operating!CO39 -> -577.8202 | CP13: =-('BS & FCF'!CO144/(Operating!CO26+Operating!CO27))*Operating!CP37-1%*Operating!CP39 -> -3190.4684 | CQ13: =-('BS & FCF'!CP144/(Operating!CP26+Operating!CP27))*Operating!CQ37-1%*Operating!CQ39 -> -3248.0964 | CR13: =SUM(CN13:CQ13) -> -9090.7002 | CS13: =-('BS & FCF'!CR144/(Operating!CR26+Operating!CR27))*Operating!CS37-1%*Operating!CS39 -> -178.17007 | CT13: =-('BS & FCF'!CS144/(Operating!CS26+Operating!CS27))*Operating!CT37-1%*Operating!CT39 -> 1006.9738 | CU13: =-('BS & FCF'!CT144/(Operating!CT26+Operating!CT27))*Operating!CU37-1%*Operating!CU39 -> -2476.5475 | CV13: =-('BS & FCF'!CU144/(Operating!CU26+Operating!CU27))*Operating!CV37-1%*Operating!CV39 -> -2853.8118 | CW13: =SUM(CS13:CV13) -> -4501.5555 | CX13: =-('BS & FCF'!CW144/(Operating!CW26+Operating!CW27))*Operating!CX37-1%*Operating!CX39 -> 404.77316 | CY13: =-('BS & FCF'!CX144/(Operating!CX26+Operating!CX27))*Operating!CY37-1%*Operating!CY39 -> 1611.1276 | CZ13: =-('BS & FCF'!CY144/(Operating!CY26+Operating!CY27))*Operating!CZ37-1%*Operating!CZ39 -> -2320.411 | DA13: =-('BS & FCF'!CZ144/(Operating!CZ26+Operating!CZ27))*Operating!DA37-1%*Operating!DA39 -> -2807.7926 | DB13: =SUM(CX13:DA13) -> -3112.3029
A14: Service costs | F14: =SUM(B14:E14) -> 0 | K14: =SUM(G14:J14) -> 0 | P14: =SUM(L14:O14) -> 0 | U14: =SUM(Q14:T14) -> 0 | Z14: =SUM(V14:Y14) -> 0 | AE14: =SUM(AA14:AD14) -> 0 | AJ14: =SUM(AF14:AI14) -> 0 | AO14: =SUM(AK14:AN14) -> 0 | AT14: =SUM(AP14:AS14) -> 0 | AU14: -8264 | AV14: -8525 | AW14: -7775 | AX14: =-28512-SUM(AU14:AW14) -> -3948 | AY14: =SUM(AU14:AX14) -> -28512 | AZ14: -9693 | BA14: -9267 | BB14: -5606 | BC14: =-33295-SUM(AZ14:BB14) -> -8729 | BD14: =SUM(AZ14:BC14) -> -33295 | BE14: -6548 | BF14: -7639 | BG14: -9476 | BH14: =-10932-SUM(BE14:BG14) -> 12731 | BI14: =SUM(BE14:BH14) -> -10932 | BJ14: -1869 | BK14: -751 | BL14: -8780 | BM14: =-4651-SUM(BJ14:BL14) -> 6749 | BN14: =SUM(BJ14:BM14) -> -4651 | BO14: -522 | BP14: -339 | BQ14: -138 | BR14: =-1355-SUM(BO14:BQ14) -> -356 | BS14: =SUM(BO14:BR14) -> -1355 | BT14: -714 | BU14: -753 | BV14: -1633 | BW14: =-2622-SUM(BT14:BV14) -> 478 | BX14: =SUM(BT14:BW14) -> -2622 | BY14: -606 | BZ14: -1001 | CA14: -1190 | CB14: =-3848-SUM(BY14:CA14) -> -1051 | CC14: =SUM(BY14:CB14) -> -3848 | CD14: -798 | CE14: -963 | CF14: =-CF6*(1-CF15) -> -997.93025 | CG14: =-CG6*(1-CG15) -> -1014.3337 | CH14: =SUM(CD14:CG14) -> -3773.2639 | CI14: =-CI6*(1-CI15) -> -1072.8006 | CJ14: =-CJ6*(1-CJ15) -> -1220.7964 | CK14: =-CK6*(1-CK15) -> -1234.7407 | CL14: =-CL6*(1-CL15) -> -1172.9684 | CM14: =SUM(CI14:CL14) -> -4701.3061 | CN14: =-CN6*(1-CN15) -> -1232.748 | CO14: =-CO6*(1-CO15) -> -1330.0969 | CP14: =-CP6*(1-CP15) -> -1343.047 | CQ14: =-CQ6*(1-CQ15) -> -1311.513 | CR14: =SUM(CN14:CQ14) -> -5217.4049 | CS14: =-CS6*(1-CS15) -> -1357.0601 | CT14: =-CT6*(1-CT15) -> -1445.4128 | CU14: =-CU6*(1-CU15) -> -1449.1012 | CV14: =-CV6*(1-CV15) -> -1408.6729 | CW14: =SUM(CS14:CV14) -> -5660.247 | CX14: =-CX6*(1-CX15) -> -1449.8766 | CY14: =-CY6*(1-CY15) -> -1536.6741 | CZ14: =-CZ6*(1-CZ15) -> -1536.2856 | DA14: =-DA6*(1-DA15) -> -1490.6722 | DB14: =SUM(CX14:DA14) -> -6013.5084
A15: Services gross margin (%) | B15: =(1+B14/B6) -> #DIV/0! | C15: =(1+C14/C6) -> #DIV/0! | D15: =(1+D14/D6) -> #DIV/0! | E15: =(1+E14/E6) -> #DIV/0! | F15: =(1+F14/F6) -> #DIV/0! | G15: =(1+G14/G6) -> #DIV/0! | H15: =(1+H14/H6) -> #DIV/0! | I15: =(1+I14/I6) -> #DIV/0! | ... CE15: =(1+CE14/CE6) -> -0.73513514 | CF15: =CE15 -> -0.73513514 | CG15: =CF15 -> -0.73513514 | CH15: =(1+CH14/CH6) -> -0.19645014 | CI15: =CG15 -> -0.73513514 | CJ15: =CI15 -> -0.73513514 | CK15: =CJ15 -> -0.73513514 | CL15: =CK15 -> -0.73513514 | CM15: =(1+CM14/CM6) -> -0.73513514 | CN15: =CL15 -> -0.73513514 | CO15: =CN15 -> -0.73513514 | CP15: =CO15 -> -0.73513514 | CQ15: =CP15 -> -0.73513514 | CR15: =(1+CR14/CR6) -> -0.73513514 | CS15: =CQ15 -> -0.73513514 | CT15: =CS15 -> -0.73513514 | CU15: =CT15 -> -0.73513514 | CV15: =CU15 -> -0.73513514 | CW15: =(1+CW14/CW6) -> -0.73513514 | CX15: =CV15 -> -0.73513514 | CY15: =CX15 -> -0.73513514 | CZ15: =CY15 -> -0.73513514 | DA15: =CZ15 -> -0.73513514 | DB15: =(1+DB14/DB6) -> -0.73513514
A16: Gross profit | B16: =B9+B10 -> 0 | C16: =C9+C10 -> 0 | D16: =D9+D10 -> 0 | E16: =E9+E10 -> 0 | F16: =SUM(B16:E16) -> 0 | G16: =G9+G10 -> 0 | H16: =H9+H10 -> 0 | I16: =I9+I10 -> 0 | J16: =J9+J10 -> 0 | K16: =SUM(G16:J16) -> 0 | L16: =L9+L10 -> 0 | M16: =M9+M10 -> 0 | N16: =N9+N10 -> 0 | O16: =O9+O10 -> 0 | P16: =SUM(L16:O16) -> 0 | Q16: =Q9+Q10 -> 0 | R16: =R9+R10 -> 0 | S16: =S9+S10 -> 0 | T16: =T9+T10 -> 0 | U16: =SUM(Q16:T16) -> 0 | V16: =V9+V10 -> 0 | W16: =W9+W10 -> 0 | X16: =X9+X10 -> 0 | Y16: =Y9+Y10 -> 0 | Z16: =SUM(V16:Y16) -> 0 | AA16: =AA9+AA10 -> 0 | AB16: =AB9+AB10 -> 0 | AC16: =AC9+AC10 -> 0 | AD16: =AD9+AD10 -> 0 | AE16: =SUM(AA16:AD16) -> 0 | AF16: =AF9+AF10 -> 0 | AG16: =AG9+AG10 -> 0 | AH16: =AH9+AH10 -> 0 | AI16: =AI9+AI10 -> 0 | AJ16: =SUM(AF16:AI16) -> 0 | AK16: =AK9+AK10 -> 38196.587 | AL16: =AL9+AL10 -> 55174.636 | AM16: =AM9+AM10 -> 65601.052 | AN16: =AN9+AN10 -> 84871.913 | AO16: =SUM(AK16:AN16) -> 243844.19 | AP16: =AP9+AP10 -> 44538.737 | AQ16: =AQ9+AQ10 -> 72555.003 | AR16: =AR9+AR10 -> 97559.137 | AS16: =AS9+AS10 -> 100075.01 | AT16: =SUM(AP16:AS16) -> 314727.89 | AU16: =AU9+AU10 -> 55331 | AV16: =AV9+AV10 -> 100751 | AW16: =AW9+AW10 -> 80835 | AX16: =AX9+AX10 -> 118968 | AY16: =SUM(AU16:AX16) -> 355885 | AZ16: =AZ9+AZ10 -> 78140 | BA16: =BA9+BA10 -> 87067 | BB16: =BB9+BB10 -> 123356 | BC16: =BC9+BC10 -> 139827 | BD16: =SUM(AZ16:BC16) -> 428390 | BE16: =BE9+BE10 -> 120342 | BF16: =BF9+BF10 -> 162916 | BG16: =BG9+BG10 -> 174971 | BH16: =BH9+BH10 -> 186442 | BI16: =SUM(BE16:BH16) -> 644671 | BJ16: =BJ9+BJ10 -> 165909 | BK16: =BK9+BK10 -> 215497 | BL16: =BL9+BL10 -> 233743 | BM16: =BM9+BM10 -> 221743 | BN16: =SUM(BJ16:BM16) -> 836892 | BO16: =BO9+BO10 -> 223162 | BP16: =BP9+BP10 -> 274554 | BQ16: =BQ9+BQ10 -> 283903 | BR16: =BR9+BR10 -> 313734 | BS16: =SUM(BO16:BR16) -> 1095353 | BT16: =BT9+BT10 -> 316609 | BU16: =BU9+BU10 -> 382531 | BV16: =BV9+BV10 -> 409446 | BW16: =BW9+BW10 -> 404354 | BX16: =SUM(BT16:BW16) -> 1512940 | BY16: =BY9+BY10 -> 474888 | BZ16: =BZ9+BZ10 -> 532776 | CA16: =CA9+CA10 -> 566227 | CB16: =CB9+CB10 -> 572696 | CC16: =SUM(BY16:CB16) -> 2146587 | CD16: =CD9+CD10 -> 629656 | CE16: =CE9+CE10 -> 668362 | CF16: =CF9+CF10 -> 698159.09 | CG16: =CG9+CG10 -> 707578.88 | CH16: =SUM(CD16:CG16) -> 2703756 | CI16: =CI9+CI10 -> 737591.18 | CJ16: =CJ9+CJ10 -> 850073.46 | CK16: =CK9+CK10 -> 868799.38 | CL16: =CL9+CL10 -> 829640.22 | CM16: =SUM(CI16:CL16) -> 3286104.2 | CN16: =CN9+CN10 -> 844141.63 | CO16: =CO9+CO10 -> 908033.8 | CP16: =CP9+CP10 -> 912197.76 | CQ16: =CQ9+CQ10 -> 889571.92 | CR16: =SUM(CN16:CQ16) -> 3553945.1 | CS16: =CS9+CS10 -> 910605.67 | CT16: =CT9+CT10 -> 966220.75 | CU16: =CU9+CU10 -> 962914.87 | CV16: =CV9+CV10 -> 934417.73 | CW16: =SUM(CS16:CV16) -> 3774159 | CX16: =CX9+CX10 -> 962117.76 | CY16: =CY9+CY10 -> 1017274.4 | CZ16: =CZ9+CZ10 -> 1011380.5 | DA16: =DA9+DA10 -> 979909.45 | DB16: =SUM(CX16:DA16) -> 3970682.1
A17: Operating expenses | B17: =B18+B21+B23+B30+B34 -> 0 | C17: =C18+C21+C23+C30+C34 -> 0 | D17: =D18+D21+D23+D30+D34 -> 0 | E17: =E18+E21+E23+E30+E34 -> 0 | F17: =SUM(B17:E17) -> 0 | G17: =G18+G21+G23+G30+G34 -> 0 | H17: =H18+H21+H23+H30+H34 -> 0 | I17: =I18+I21+I23+I30+I34 -> 0 | J17: =J18+J21+J23+J30+J34 -> 0 | K17: =SUM(G17:J17) -> 0 | L17: =L18+L21+L23+L30+L34 -> 0 | M17: =M18+M21+M23+M30+M34 -> 0 | N17: =N18+N21+N23+N30+N34 -> 0 | O17: =O18+O21+O23+O30+O34 -> 0 | P17: =SUM(L17:O17) -> 0 | Q17: =Q18+Q21+Q23+Q30+Q34 -> 0 | R17: =R18+R21+R23+R30+R34 -> 0 | S17: =S18+S21+S23+S30+S34 -> 0 | T17: =T18+T21+T23+T30+T34 -> 0 | U17: =SUM(Q17:T17) -> 0 | V17: =V18+V21+V23+V30+V34 -> 0 | W17: =W18+W21+W23+W30+W34 -> 0 | X17: =X18+X21+X23+X30+X34 -> 0 | Y17: =Y18+Y21+Y23+Y30+Y34 -> 0 | Z17: =SUM(V17:Y17) -> 0 | AA17: =AA18+AA21+AA23+AA30+AA34 -> 0 | AB17: =AB18+AB21+AB23+AB30+AB34 -> 0 | AC17: =AC18+AC21+AC23+AC30+AC34 -> 0 | AD17: =AD18+AD21+AD23+AD30+AD34 -> 0 | AE17: =SUM(AA17:AD17) -> 0 | AF17: =AF18+AF21+AF23+AF30+AF34 -> 0 | AG17: =AG18+AG21+AG23+AG30+AG34 -> 0 | AH17: =AH18+AH21+AH23+AH30+AH34 -> 0 | AI17: =AI18+AI21+AI23+AI30+AI34 -> 0 | AJ17: =SUM(AF17:AI17) -> 0 | AK17: =AK18+AK21+AK23+AK30+AK34 -> -21731.519 | AL17: =AL18+AL21+AL23+AL30+AL34 -> -35087.854 | AM17: =AM18+AM21+AM23+AM30+AM34 -> -15726.313 | AN17: =AN18+AN21+AN23+AN30+AN34 -> -28703.093 | AO17: =SUM(AK17:AN17) -> -101248.78 | AP17: =AP18+AP21+AP23+AP30+AP34 -> -20941.817 | AQ17: =AQ18+AQ21+AQ23+AQ30+AQ34 -> -27935.059 | AR17: =AR18+AR21+AR23+AR30+AR34 -> -38728.351 | AS17: =AS18+AS21+AS23+AS30+AS34 -> -32661.014 | AT17: =SUM(AP17:AS17) -> -120266.24 | AU17: =AU18+AU21+AU23+AU30+AU34 -> -27074 | AV17: =AV18+AV21+AV23+AV30+AV34 -> -21483 | AW17: =AW18+AW21+AW23+AW30+AW34 -> -35652 | AX17: =AX18+AX21+AX23+AX30+AX34 -> -45581 | AY17: =SUM(AU17:AX17) -> -129790 | AZ17: =AZ18+AZ21+AZ23+AZ30+AZ34 -> -54985 | BA17: =BA18+BA21+BA23+BA30+BA34 -> -41183 | BB17: =BB18+BB21+BB23+BB30+BB34 -> -57238 | BC17: =BC18+BC21+BC23+BC30+BC34 -> -58772 | BD17: =SUM(AZ17:BC17) -> -212178 | BE17: =BE18+BE21+BE23+BE30+BE34 -> -61395 | BF17: =BF18+BF21+BF23+BF30+BF34 -> -77551 | BG17: =BG18+BG21+BG23+BG30+BG34 -> -89995 | BH17: =BH18+BH21+BH23+BH30+BH34 -> -64089 | BI17: =SUM(BE17:BH17) -> -293030 | BJ17: =BJ18+BJ21+BJ23+BJ30+BJ34 -> -90921 | BK17: =BK18+BK21+BK23+BK30+BK34 -> -108110 | BL17: =BL18+BL21+BL23+BL30+BL34 -> -123338 | BM17: =BM18+BM21+BM23+BM30+BM34 -> -109519 | BN17: =SUM(BJ17:BM17) -> -431888 | BO17: =BO18+BO21+BO23+BO30+BO34 -> -113770 | BP17: =BP18+BP21+BP23+BP30+BP34 -> -132289 | BQ17: =BQ18+BQ21+BQ23+BQ30+BQ34 -> -151884 | BR17: =BR18+BR21+BR23+BR30+BR34 -> -129381 | BS17: =SUM(BO17:BR17) -> -527324 | BT17: =BT18+BT21+BT23+BT30+BT34 -> -142353 | BU17: =BU18+BU21+BU23+BU30+BU34 -> -186341 | BV17: =BV18+BV21+BV23+BV30+BV34 -> -205856 | BW17: =BW18+BW21+BW23+BW30+BW34 -> -189794 | BX17: =SUM(BT17:BW17) -> -724344 | BY17: =BY18+BY21+BY23+BY30+BY34 -> -210221 | BZ17: =BZ18+BZ21+BZ23+BZ30+BZ34 -> -234180 | CA17: =CA18+CA21+CA23+CA30+CA34 -> -246254 | CB17: =CB18+CB21+CB23+CB30+CB34 -> -235686 | CC17: =SUM(BY17:CB17) -> -926341 | CD17: =CD18+CD21+CD23+CD30+CD34 -> -237220 | CE17: =CE18+CE21+CE23+CE30+CE34 -> -312057 | CF17: =CF18+CF21+CF23+CF30+CF34 -> -306500.85 | CG17: =CG18+CG21+CG23+CG30+CG34 -> -283458.39 | CH17: =SUM(CD17:CG17) -> -1139236.2 | CI17: =CI18+CI21+CI23+CI30+CI34 -> -295845.95 | CJ17: =CJ18+CJ21+CJ23+CJ30+CJ34 -> -368818.99 | CK17: =CK18+CK21+CK23+CK30+CK34 -> -350803.1 | CL17: =CL18+CL21+CL23+CL30+CL34 -> -324855.76 | CM17: =SUM(CI17:CL17) -> -1340323.8 | CN17: =CN18+CN21+CN23+CN30+CN34 -> -299604.01 | CO17: =CO18+CO21+CO23+CO30+CO34 -> -370651.68 | CP17: =CP18+CP21+CP23+CP30+CP34 -> -352377.65 | CQ17: =CQ18+CQ21+CQ23+CQ30+CQ34 -> -327844.07 | CR17: =SUM(CN17:CQ17) -> -1350477.4 | CS17: =CS18+CS21+CS23+CS30+CS34 -> -321028.56 | CT17: =CT18+CT21+CT23+CT30+CT34 -> -393303.72 | CU17: =CU18+CU21+CU23+CU30+CU34 -> -372906.78 | CV17: =CV18+CV21+CV23+CV30+CV34 -> -345782.47 | CW17: =SUM(CS17:CV17) -> -1433021.5 | CX17: =CX18+CX21+CX23+CX30+CX34 -> -336902.79 | CY17: =CY18+CY21+CY23+CY30+CY34 -> -411263.24 | CZ17: =CZ18+CZ21+CZ23+CZ30+CZ34 -> -389655.31 | DA17: =DA18+DA21+DA23+DA30+DA34 -> -361386.07 | DB17: =SUM(CX17:DA17) -> -1499207.4
A18: Selling expenses | F18: =SUM(B18:E18) -> 0 | K18: =SUM(G18:J18) -> 0 | P18: =SUM(L18:O18) -> 0 | U18: =SUM(Q18:T18) -> 0 | Z18: =SUM(V18:Y18) -> 0 | AE18: =SUM(AA18:AD18) -> 0 | AJ18: =SUM(AF18:AI18) -> 0 | AK18: -19606.696 | AL18: -27523.964 | AM18: -23200.763 | AN18: -33013.443 | AO18: =SUM(AK18:AN18) -> -103344.87 | AP18: -16280.821 | AQ18: -22900 | AR18: -21281.703 | AS18: -25372.387 | AT18: =SUM(AP18:AS18) -> -85834.911 | AU18: -14144 | AV18: -20312 | AW18: -26575 | AX18: =-100668-SUM(AU18:AW18) -> -39637 | AY18: =SUM(AU18:AX18) -> -100668 | AZ18: -22046 | BA18: -26343 | BB18: -27428 | BC18: =-102804-SUM(AZ18:BB18) -> -26987 | BD18: =SUM(AZ18:BC18) -> -102804 | BE18: -30360 | BF18: -38953 | BG18: -47954 | BH18: =-164226-SUM(BE18:BG18) -> -46959 | BI18: =SUM(BE18:BH18) -> -164226 | BJ18: -44417 | BK18: -53835 | BL18: -59384 | BM18: =-212188-SUM(BJ18:BL18) -> -54552 | BN18: =SUM(BJ18:BM18) -> -212188 | BO18: -62031 | BP18: -66728 | BQ18: -80995 | BR18: =-285230-SUM(BO18:BQ18) -> -75476 | BS18: =SUM(BO18:BR18) -> -285230 | BT18: -76092 | BU18: -97945 | BV18: -113852 | BW18: =-391872-SUM(BT18:BV18) -> -103983 | BX18: =SUM(BT18:BW18) -> -391872 | BY18: -106236 | BZ18: -124747 | CA18: -134823 | CB18: =-494891-SUM(BY18:CA18) -> -129085 | CC18: =SUM(BY18:CB18) -> -494891 | CD18: -119070 | CE18: -166790 | CF18: =-CF20*(Operating!CF15+Operating!CF17) -> -163627.19 | CG18: =-CG20*(Operating!CG15+Operating!CG17) -> -154137.4 | CH18: =SUM(CD18:CG18) -> -603624.6 | CI18: =-CI20*(Operating!CI15+Operating!CI17) -> -160924.93 | CJ18: =-CJ20*(Operating!CJ15+Operating!CJ17) -> -210691.65 | CK18: =-CK20*(Operating!CK15+Operating!CK17) -> -187004.39 | CL18: =-CL20*(Operating!CL15+Operating!CL17) -> -176952.22 | CM18: =SUM(CI18:CL18) -> -735573.2 | CN18: =-CN20*(Operating!CN15+Operating!CN17) -> -168185.39 | CO18: =-CO20*(Operating!CO15+Operating!CO17) -> -218522.09 | CP18: =-CP20*(Operating!CP15+Operating!CP17) -> -193750.85 | CQ18: =-CQ20*(Operating!CQ15+Operating!CQ17) -> -184180.09 | CR18: =SUM(CN18:CQ18) -> -764638.41 | CS18: =-CS20*(Operating!CS15+Operating!CS17) -> -179900.41 | CT18: =-CT20*(Operating!CT15+Operating!CT17) -> -231245.68 | CU18: =-CU20*(Operating!CU15+Operating!CU17) -> -203998.04 | CV18: =-CV20*(Operating!CV15+Operating!CV17) -> -193099.5 | CW18: =SUM(CS18:CV18) -> -808243.63 | CX18: =-CX20*(Operating!CX15+Operating!CX17) -> -187825.12 | CY18: =-CY20*(Operating!CY15+Operating!CY17) -> -241040.02 | CZ18: =-CZ20*(Operating!CZ15+Operating!CZ17) -> -212474.19 | DA18: =-DA20*(Operating!DA15+Operating!DA17) -> -200991.77 | DB18: =SUM(CX18:DA18) -> -842331.1
A19: % of net revenues | B19: =-B18/B9 -> #DIV/0! | C19: =-C18/C9 -> #DIV/0! | D19: =-D18/D9 -> #DIV/0! | E19: =-E18/E9 -> #DIV/0! | F19: =-F18/F9 -> #DIV/0! | G19: =-G18/G9 -> #DIV/0! | H19: =-H18/H9 -> #DIV/0! | I19: =-I18/I9 -> #DIV/0! | ... DB19: =-DB18/DB9 -> 0.079823526
A20: % of net sales | B20: =-B18/(Operating!B15+Operating!B17) -> #DIV/0! | C20: =-C18/(Operating!C15+Operating!C17) -> #DIV/0! | D20: =-D18/(Operating!D15+Operating!D17) -> #DIV/0! | E20: =-E18/(Operating!E15+Operating!E17) -> #DIV/0! | F20: =-F18/(Operating!F15+Operating!F17) -> #DIV/0! | G20: =-G18/(Operating!G15+Operating!G17) -> #DIV/0! | H20: =-H18/(Operating!H15+Operating!H17) -> #DIV/0! | I20: =-I18/(Operating!I15+Operating!I17) -> #DIV/0! | ... CE20: =-CE18/(Operating!CE15+Operating!CE17) -> 0.075242478 | CF20: 0.0675 | CG20: =CF20 -> 0.0675 | CH20: =-CH18/(Operating!CH15+Operating!CH17) -> 0.063820081 | CI20: 0.055 | CJ20: 0.07 | CK20: =CJ20 -> 0.07 | CL20: =CK20 -> 0.07 | CM20: =-CM18/(Operating!CM15+Operating!CM17) -> 0.066058558 | CN20: 0.055 | CO20: 0.07 | CP20: =CK20 -> 0.07 | CQ20: =CL20 -> 0.07 | CR20: =-CR18/(Operating!CR15+Operating!CR17) -> 0.066038515 | CS20: =CN20 -> 0.055 | CT20: =CO20 -> 0.07 | CU20: =CP20 -> 0.07 | CV20: =CQ20 -> 0.07 | CW20: =-CW18/(Operating!CW15+Operating!CW17) -> 0.065993896 | CX20: =CS20 -> 0.055 | CY20: =CT20 -> 0.07 | CZ20: =CU20 -> 0.07 | DA20: =CV20 -> 0.07 | DB20: =-DB18/(Operating!DB15+Operating!DB17) -> 0.065987099
A21: G&A expenses | F21: =SUM(B21:E21) -> 0 | K21: =SUM(G21:J21) -> 0 | P21: =SUM(L21:O21) -> 0 | U21: =SUM(Q21:T21) -> 0 | Z21: =SUM(V21:Y21) -> 0 | AE21: =SUM(AA21:AD21) -> 0 | AJ21: =SUM(AF21:AI21) -> 0 | AK21: -7678.198 | AL21: -11511.16 | AM21: -8775.254 | AN21: -15305.771 | AO21: =SUM(AK21:AN21) -> -43270.383 | AP21: -10376.184 | AQ21: -10511.935 | AR21: -15626.307 | AS21: -9316.124 | AT21: =SUM(AP21:AS21) -> -45830.55 | AU21: =-26240-AU32 -> -24386 | AV21: =-27173-AV32 -> -26994 | AW21: =-24843-AW32 -> -24444 | AX21: =-96843-SUM(AU21:AW21)-SUM(AU32:AX32) -> -19864 | AY21: =SUM(AU21:AX21) -> -95688 | AZ21: =-28376-AZ32 -> -25451 | BA21: =-14508-BA32 -> -14201 | BB21: =-25631-BB32 -> -25266 | BC21: =-96892-SUM(AZ21:BB21)-SUM(AZ32:BC32) -> -30415 | BD21: =SUM(AZ21:BC21) -> -95333 | BE21: =-20615-BE32 -> -20280 | BF21: =-24043-BF32 -> -23688 | BG21: =-31117-BG32 -> -30752 | BH21: =-102464-SUM(BE21:BG21)-SUM(BE32:BH32) -> -26306 | BI21: =SUM(BE21:BH21) -> -101026 | BJ21: =-22810-BJ32 -> -22356 | BK21: =-34143-BK32 -> -33684 | BL21: =-49409-BL32 -> -48993 | BM21: =-136568-SUM(BJ21:BL21)-SUM(BJ32:BM32) -> -29683 | BN21: =SUM(BJ21:BM21) -> -134716 | BO21: =-33375-BO32 -> -32599 | BP21: =-42088-BP32 -> -41367 | BQ21: =-54245-BQ32 -> -53549 | BR21: =-165783-SUM(BO21:BQ21)-SUM(BO32:BR32) -> -35293 | BS21: =SUM(BO21:BR21) -> -162808 | BT21: =-41298-BT32 -> -40769 | BU21: =-62203-BU32 -> -61475 | BV21: =-68034-BV32 -> -67309 | BW21: =-224429-SUM(BT21:BV21)-SUM(BT32:BW32) -> -52203 | BX21: =SUM(BT21:BW21) -> -221756 | BY21: =-50355-BY32 -> -50151 | BZ21: =-64402-BZ32 -> -64176 | CA21: =-66007-CA32 -> -65788 | CB21: =-239339-SUM(BY21:CA21)-SUM(BY32:CB32) -> -58359 | CC21: =SUM(BY21:CB21) -> -238474 | CD21: =-64932-CD32 -> -64720 | CE21: =-78364-CE32 -> -78166 | CF21: =CA21*(1+Macro!CF11)*1.15 -> -79327.125 | CG21: =CB21*(1+Macro!CG11)*1.1 -> -67631.616 | CH21: =SUM(CD21:CG21) -> -289844.74 | CI21: =CD21*(1+Macro!CI11)*1.1 -> -74706.251 | CJ21: =CE21*(1+Macro!CJ11)*1.1 -> -89760.345 | CK21: =CF21*(1+Macro!CK11)*1.1 -> -91001.34 | CL21: =CG21*(1+Macro!CL11)*1.1 -> -77777.23 | CM21: =SUM(CI21:CL21) -> -333245.17 | CN21: =CI21*(1+Macro!CN11) -> -78102.864 | CO21: =CJ21*(1+Macro!CO11) -> -93841.412 | CP21: =CK21*(1+Macro!CP11) -> -95138.831 | CQ21: =CL21*(1+Macro!CQ11) -> -81313.47 | CR21: =SUM(CN21:CQ21) -> -348396.58 | CS21: =CN21*(1+Macro!CS11) -> -81226.979 | CT21: =CO21*(1+Macro!CT11) -> -97595.068 | CU21: =CP21*(1+Macro!CU11) -> -98944.384 | CV21: =CQ21*(1+Macro!CV11) -> -84566.009 | CW21: =SUM(CS21:CV21) -> -362332.44 | CX21: =CS21*(1+Macro!CX11) -> -84435.03 | CY21: =CT21*(1+Macro!CY11) -> -101449.58 | CZ21: =CU21*(1+Macro!CZ11) -> -102852.18 | DA21: =CV21*(1+Macro!DA11) -> -87905.934 | DB21: =SUM(CX21:DA21) -> -376642.72
A22: as % of net revenues | B22: =-B21/B9 -> #DIV/0! | C22: =-C21/C9 -> #DIV/0! | D22: =-D21/D9 -> #DIV/0! | E22: =-E21/E9 -> #DIV/0! | F22: =-F21/F9 -> #DIV/0! | G22: =-G21/G9 -> #DIV/0! | H22: =-H21/H9 -> #DIV/0! | I22: =-I21/I9 -> #DIV/0! | ... DB22: =-DB21/DB9 -> 0.035692556
A23: Net financial results | B23: =B24+B26+B28 -> 0 | C23: =C24+C26+C28 -> 0 | D23: =D24+D26+D28 -> 0 | E23: =E24+E26+E28 -> 0 | F23: =SUM(B23:E23) -> 0 | G23: =G24+G26+G28 -> 0 | H23: =H24+H26+H28 -> 0 | I23: =I24+I26+I28 -> 0 | J23: =J24+J26+J28 -> 0 | K23: =SUM(G23:J23) -> 0 | L23: =L24+L26+L28 -> 0 | M23: =M24+M26+M28 -> 0 | N23: =N24+N26+N28 -> 0 | O23: =O24+O26+O28 -> 0 | P23: =SUM(L23:O23) -> 0 | Q23: =Q24+Q26+Q28 -> 0 | R23: =R24+R26+R28 -> 0 | S23: =S24+S26+S28 -> 0 | T23: =T24+T26+T28 -> 0 | U23: =SUM(Q23:T23) -> 0 | V23: =V24+V26+V28 -> 0 | W23: =W24+W26+W28 -> 0 | X23: =X24+X26+X28 -> 0 | Y23: =Y24+Y26+Y28 -> 0 | Z23: =SUM(V23:Y23) -> 0 | AA23: =AA24+AA26+AA28 -> 0 | AB23: =AB24+AB26+AB28 -> 0 | AC23: =AC24+AC26+AC28 -> 0 | AD23: =AD24+AD26+AD28 -> 0 | AE23: =SUM(AA23:AD23) -> 0 | AF23: =AF24+AF26+AF28 -> 0 | AG23: =AG24+AG26+AG28 -> 0 | AH23: =AH24+AH26+AH28 -> 0 | AI23: =AI24+AI26+AI28 -> 0 | AJ23: =SUM(AF23:AI23) -> 0 | AK23: =AK24+AK26+AK28 -> 3661.195 | AL23: =AL24+AL26+AL28 -> 3156.298 | AM23: =AM24+AM26+AM28 -> 5088.347 | AN23: =AN24+AN26+AN28 -> 3151.127 | AO23: =SUM(AK23:AN23) -> 15056.967 | AP23: =AP24+AP26+AP28 -> 2109.936 | AQ23: =AQ24+AQ26+AQ28 -> 1101.435 | AR23: =AR24+AR26+AR28 -> -340.327 | AS23: =AS24+AS26+AS28 -> -408.829 | AT23: =SUM(AP23:AS23) -> 2462.215 | AU23: =AU24+AU26+AU28 -> -453 | AV23: =AV24+AV26+AV28 -> 262 | AW23: =AW24+AW26+AW28 -> -4443 | AX23: =AX24+AX26+AX28 -> -6780 | AY23: =SUM(AU23:AX23) -> -11414 | AZ23: =AZ24+AZ26+AZ28 -> -2175 | BA23: =BA24+BA26+BA28 -> -2892 | BB23: =BB24+BB26+BB28 -> -1211 | BC23: =BC24+BC26+BC28 -> -2532 | BD23: =SUM(AZ23:BC23) -> -8810 | BE23: =BE24+BE26+BE28 -> -5034 | BF23: =BF24+BF26+BF28 -> -5376 | BG23: =BG24+BG26+BG28 -> -1071 | BH23: =BH24+BH26+BH28 -> -13246 | BI23: =SUM(BE23:BH23) -> -24727 | BJ23: =BJ24+BJ26+BJ28 -> -4085 | BK23: =BK24+BK26+BK28 -> -4609 | BL23: =BL24+BL26+BL28 -> -4065 | BM23: =BM24+BM26+BM28 -> -11678 | BN23: =SUM(BJ23:BM23) -> -24437 | BO23: =BO24+BO26+BO28 -> -5444 | BP23: =BP24+BP26+BP28 -> -5601 | BQ23: =BQ24+BQ26+BQ28 -> -3546 | BR23: =BR24+BR26+BR28 -> 680 | BS23: =SUM(BO23:BR23) -> -13911 | BT23: =BT24+BT26+BT28 -> -4917 | BU23: =BU24+BU26+BU28 -> -5749 | BV23: =BV24+BV26+BV28 -> -7613 | BW23: =BW24+BW26+BW28 -> -12805 | BX23: =SUM(BT23:BW23) -> -31084 | BY23: =BY24+BY26+BY28 -> -14580 | BZ23: =BZ24+BZ26+BZ28 -> -15628 | CA23: =CA24+CA26+CA28 -> -8694 | CB23: =CB24+CB26+CB28 -> -8912 | CC23: =SUM(BY23:CB23) -> -47814 | CD23: =CD24+CD26+CD28 -> -10709 | CE23: =CE24+CE26+CE28 -> -22120 | CF23: =CF24+CF26+CF28 -> -6498.0808 | CG23: =CG24+CG26+CG28 -> -3840.7339 | CH23: =SUM(CD23:CG23) -> -43167.815 | CI23: =CI24+CI26+CI28 -> 459.79597 | CJ23: =CJ24+CJ26+CJ28 -> -441.87402 | CK23: =CK24+CK26+CK28 -> -4204.8966 | CL23: =CL24+CL26+CL28 -> -4592.2103 | CM23: =SUM(CI23:CL23) -> -8779.185 | CN23: =CN24+CN26+CN28 -> 6678.4524 | CO23: =CO24+CO26+CO28 -> 6480.1804 | CP23: =CP24+CP26+CP28 -> 1915.7566 | CQ23: =CQ24+CQ26+CQ28 -> 1487.5283 | CR23: =SUM(CN23:CQ23) -> 16561.918 | CS23: =CS24+CS26+CS28 -> 6140.5866 | CT23: =CT24+CT26+CT28 -> 5910.9847 | CU23: =CU24+CU26+CU28 -> 590.91023 | CV23: =CV24+CV26+CV28 -> 441.03986 | CW23: =SUM(CS23:CV23) -> 13083.521 | CX23: =CX24+CX26+CX28 -> 5908.8803 | CY23: =CY24+CY26+CY28 -> 6042.1781 | CZ23: =CZ24+CZ26+CZ28 -> 480.75567 | DA23: =DA24+DA26+DA28 -> 84.544732 | DB23: =SUM(CX23:DA23) -> 12516.359
A24: Financial income | F24: =SUM(B24:E24) -> 0 | K24: =SUM(G24:J24) -> 0 | P24: =SUM(L24:O24) -> 0 | U24: =SUM(Q24:T24) -> 0 | Z24: =SUM(V24:Y24) -> 0 | AE24: =SUM(AA24:AD24) -> 0 | AJ24: =SUM(AF24:AI24) -> 0 | AK24: 4427.36 | AL24: 4201.649 | AM24: 6442 | AN24: 5265.735 | AO24: =SUM(AK24:AN24) -> 20336.744 | AP24: 2670.841 | AQ24: 2209.223 | AR24: 3401.065 | AS24: 2850.52 | AT24: =SUM(AP24:AS24) -> 11131.649 | AU24: 3012 | AV24: 5477 | AW24: 3325 | AX24: =15275-SUM(AU24:AW24) -> 3461 | AY24: =SUM(AU24:AX24) -> 15275 | AZ24: 2784 | BA24: 2827 | BB24: 5428 | BC24: =14673-SUM(AZ24:BB24) -> 3634 | BD24: =SUM(AZ24:BC24) -> 14673 | BE24: 2222 | BF24: 3924 | BG24: 10356 | BH24: =24987-SUM(BE24:BG24) -> 8485 | BI24: =SUM(BE24:BH24) -> 24987 | BJ24: 12977 | BK24: 17605 | BL24: 18795 | BM24: =64031-SUM(BJ24:BL24) -> 14654 | BN24: =SUM(BJ24:BM24) -> 64031 | BO24: 20228 | BP24: 20425 | BQ24: 19668 | BR24: =86216-SUM(BO24:BQ24) -> 25895 | BS24: =SUM(BO24:BR24) -> 86216 | BT24: 19889 | BU24: 25350 | BV24: 32060 | BW24: =106081-SUM(BT24:BV24) -> 28782 | BX24: =SUM(BT24:BW24) -> 106081 | BY24: 36752 | BZ24: 35218 | CA24: 47368 | CB24: =170022-SUM(BY24:CA24) -> 50684 | CC24: =SUM(BY24:CB24) -> 170022 | CD24: 49093 | CE24: 48168 | CF24: =CF25*(AVERAGE('BS & FCF'!CE6:CF6)+AVERAGE('BS & FCF'!CE7:CF7))/4 -> 45176.935 | CG24: =CG25*(AVERAGE('BS & FCF'!CF6:CG6)+AVERAGE('BS & FCF'!CF7:CG7))/4 -> 48044.102 | CH24: =SUM(CD24:CG24) -> 190482.04 | CI24: =CI25*(AVERAGE('BS & FCF'!CH6:CI6)+AVERAGE('BS & FCF'!CH7:CI7))/4 -> 54954.745 | CJ24: =CJ25*(AVERAGE('BS & FCF'!CI6:CJ6)+AVERAGE('BS & FCF'!CI7:CJ7))/4 -> 55568.921 | CK24: =CK25*(AVERAGE('BS & FCF'!CJ6:CK6)+AVERAGE('BS & FCF'!CJ7:CK7))/4 -> 51347.011 | CL24: =CL25*(AVERAGE('BS & FCF'!CK6:CL6)+AVERAGE('BS & FCF'!CK7:CL7))/4 -> 51314.596 | CM24: =SUM(CI24:CL24) -> 213185.27 | CN24: =CN25*(AVERAGE('BS & FCF'!CM6:CN6)+AVERAGE('BS & FCF'!CM7:CN7))/4 -> 57668.519 | CO24: =CO25*(AVERAGE('BS & FCF'!CN6:CO6)+AVERAGE('BS & FCF'!CN7:CO7))/4 -> 59914.559 | CP24: =CP25*(AVERAGE('BS & FCF'!CO6:CP6)+AVERAGE('BS & FCF'!CO7:CP7))/4 -> 56092.829 | CQ24: =CQ25*(AVERAGE('BS & FCF'!CP6:CQ6)+AVERAGE('BS & FCF'!CP7:CQ7))/4 -> 55927.822 | CR24: =SUM(CN24:CQ24) -> 229603.73 | CS24: =CS25*(AVERAGE('BS & FCF'!CR6:CS6)+AVERAGE('BS & FCF'!CR7:CS7))/4 -> 62314.782 | CT24: =CT25*(AVERAGE('BS & FCF'!CS6:CT6)+AVERAGE('BS & FCF'!CS7:CT7))/4 -> 64260.516 | CU24: =CU25*(AVERAGE('BS & FCF'!CT6:CU6)+AVERAGE('BS & FCF'!CT7:CU7))/4 -> 59568.004 | CV24: =CV25*(AVERAGE('BS & FCF'!CU6:CV6)+AVERAGE('BS & FCF'!CU7:CV7))/4 -> 59385.408 | CW24: =SUM(CS24:CV24) -> 245528.71 | CX24: =CX25*(AVERAGE('BS & FCF'!CW6:CX6)+AVERAGE('BS & FCF'!CW7:CX7))/4 -> 66251.237 | CY24: =CY25*(AVERAGE('BS & FCF'!CX6:CY6)+AVERAGE('BS & FCF'!CX7:CY7))/4 -> 68337.271 | CZ24: =CZ25*(AVERAGE('BS & FCF'!CY6:CZ6)+AVERAGE('BS & FCF'!CY7:CZ7))/4 -> 63187.881 | DA24: =DA25*(AVERAGE('BS & FCF'!CZ6:DA6)+AVERAGE('BS & FCF'!CZ7:DA7))/4 -> 62565.668 | DB24: =SUM(CX24:DA24) -> 260342.06
A25: Avg. cash rate (%) | B25: =(1+(B24)/(AVERAGE('BS & FCF'!A6:B6)+AVERAGE('BS & FCF'!A7:B7)))^4-1 -> #DIV/0! | C25: =(1+(C24)/(AVERAGE('BS & FCF'!B6:C6)+AVERAGE('BS & FCF'!B7:C7)))^4-1 -> #DIV/0! | D25: =(1+(D24)/(AVERAGE('BS & FCF'!C6:D6)+AVERAGE('BS & FCF'!C7:D7)))^4-1 -> #DIV/0! | E25: =(1+(E24)/(AVERAGE('BS & FCF'!D6:E6)+AVERAGE('BS & FCF'!D7:E7)))^4-1 -> #DIV/0! | F25: =(F24)/(AVERAGE('BS & FCF'!B6:E6)+AVERAGE('BS & FCF'!B7:E7)) -> #DIV/0! | G25: =(1+(G24)/(AVERAGE('BS & FCF'!F6:G6)+AVERAGE('BS & FCF'!F7:G7)))^4-1 -> #DIV/0! | H25: =(1+(H24)/(AVERAGE('BS & FCF'!G6:H6)+AVERAGE('BS & FCF'!G7:H7)))^4-1 -> #DIV/0! | I25: =(1+(I24)/(AVERAGE('BS & FCF'!H6:I6)+AVERAGE('BS & FCF'!H7:I7)))^4-1 -> #DIV/0! | J25: =(1+(J24)/(AVERAGE('BS & FCF'!I6:J6)+AVERAGE('BS & FCF'!I7:J7)))^4-1 -> #DIV/0! | K25: =(K24)/(AVERAGE('BS & FCF'!G6:J6)+AVERAGE('BS & FCF'!G7:J7)) -> #DIV/0! | L25: =(1+(L24)/(AVERAGE('BS & FCF'!K6:L6)+AVERAGE('BS & FCF'!K7:L7)))^4-1 -> #DIV/0! | M25: =(1+(M24)/(AVERAGE('BS & FCF'!L6:M6)+AVERAGE('BS & FCF'!L7:M7)))^4-1 -> #DIV/0! | N25: =(1+(N24)/(AVERAGE('BS & FCF'!M6:N6)+AVERAGE('BS & FCF'!M7:N7)))^4-1 -> #DIV/0! | O25: =(1+(O24)/(AVERAGE('BS & FCF'!N6:O6)+AVERAGE('BS & FCF'!N7:O7)))^4-1 -> #DIV/0! | P25: =(P24)/(AVERAGE('BS & FCF'!L6:O6)+AVERAGE('BS & FCF'!L7:O7)) -> #DIV/0! | Q25: =(1+(Q24)/(AVERAGE('BS & FCF'!P6:Q6)+AVERAGE('BS & FCF'!P7:Q7)))^4-1 -> #DIV/0! | R25: =(1+(R24)/(AVERAGE('BS & FCF'!Q6:R6)+AVERAGE('BS & FCF'!Q7:R7)))^4-1 -> #DIV/0! | S25: =(1+(S24)/(AVERAGE('BS & FCF'!R6:S6)+AVERAGE('BS & FCF'!R7:S7)))^4-1 -> #DIV/0! | T25: =(1+(T24)/(AVERAGE('BS & FCF'!S6:T6)+AVERAGE('BS & FCF'!S7:T7)))^4-1 -> #DIV/0! | U25: =(U24)/(AVERAGE('BS & FCF'!Q6:T6)+AVERAGE('BS & FCF'!Q7:T7)) -> #DIV/0! | V25: =(1+(V24)/(AVERAGE('BS & FCF'!U6:V6)+AVERAGE('BS & FCF'!U7:V7)))^4-1 -> #DIV/0! | W25: =(1+(W24)/(AVERAGE('BS & FCF'!V6:W6)+AVERAGE('BS & FCF'!V7:W7)))^4-1 -> #DIV/0! | X25: =(1+(X24)/(AVERAGE('BS & FCF'!W6:X6)+AVERAGE('BS & FCF'!W7:X7)))^4-1 -> #DIV/0! | Y25: =(1+(Y24)/(AVERAGE('BS & FCF'!X6:Y6)+AVERAGE('BS & FCF'!X7:Y7)))^4-1 -> #DIV/0! | Z25: =(Z24)/(AVERAGE('BS & FCF'!V6:Y6)+AVERAGE('BS & FCF'!V7:Y7)) -> #DIV/0! | AA25: =(1+(AA24)/(AVERAGE('BS & FCF'!Z6:AA6)+AVERAGE('BS & FCF'!Z7:AA7)))^4-1 -> #DIV/0! | AB25: =(1+(AB24)/(AVERAGE('BS & FCF'!AA6:AB6)+AVERAGE('BS & FCF'!AA7:AB7)))^4-1 -> #DIV/0! | AC25: =(1+(AC24)/(AVERAGE('BS & FCF'!AB6:AC6)+AVERAGE('BS & FCF'!AB7:AC7)))^4-1 -> #DIV/0! | AD25: =(1+(AD24)/(AVERAGE('BS & FCF'!AC6:AD6)+AVERAGE('BS & FCF'!AC7:AD7)))^4-1 -> #DIV/0! | AE25: =(AE24)/(AVERAGE('BS & FCF'!AA6:AD6)+AVERAGE('BS & FCF'!AA7:AD7)) -> #DIV/0! | AF25: =(1+(AF24)/(AVERAGE('BS & FCF'!AE6:AF6)+AVERAGE('BS & FCF'!AE7:AF7)))^4-1 -> #DIV/0! | AG25: =(1+(AG24)/(AVERAGE('BS & FCF'!AF6:AG6)+AVERAGE('BS & FCF'!AF7:AG7)))^4-1 -> #DIV/0! | AH25: =(1+(AH24)/(AVERAGE('BS & FCF'!AG6:AH6)+AVERAGE('BS & FCF'!AG7:AH7)))^4-1 -> #DIV/0! | AI25: =(1+(AI24)/(AVERAGE('BS & FCF'!AH6:AI6)+AVERAGE('BS & FCF'!AH7:AI7)))^4-1 -> #DIV/0! | AJ25: =(AJ24)/(AVERAGE('BS & FCF'!AF6:AI6)+AVERAGE('BS & FCF'!AF7:AI7)) -> #DIV/0! | AK25: =(1+(AK24)/(AVERAGE('BS & FCF'!AJ6:AK6)+AVERAGE('BS & FCF'!AJ7:AK7)))^4-1 -> 0.25842563 | AL25: =(1+(AL24)/(AVERAGE('BS & FCF'!AK6:AL6)+AVERAGE('BS & FCF'!AK7:AL7)))^4-1 -> 0.13065467 | AM25: =(1+(AM24)/(AVERAGE('BS & FCF'!AL6:AM6)+AVERAGE('BS & FCF'!AL7:AM7)))^4-1 -> 0.21212243 | AN25: =(1+(AN24)/(AVERAGE('BS & FCF'!AM6:AN6)+AVERAGE('BS & FCF'!AM7:AN7)))^4-1 -> 0.12368919 | AO25: =(AO24)/(AVERAGE('BS & FCF'!AK6:AN6)+AVERAGE('BS & FCF'!AK7:AN7)) -> 0.13004239 | AP25: =(1+(AP24)/(AVERAGE('BS & FCF'!AO6:AP6)+AVERAGE('BS & FCF'!AO7:AP7)))^4-1 -> 0.060856863 | AQ25: =(1+(AQ24)/(AVERAGE('BS & FCF'!AP6:AQ6)+AVERAGE('BS & FCF'!AP7:AQ7)))^4-1 -> 0.061870386 | AR25: =(1+(AR24)/(AVERAGE('BS & FCF'!AQ6:AR6)+AVERAGE('BS & FCF'!AQ7:AR7)))^4-1 -> 0.079773085 | AS25: =(1+(AS24)/(AVERAGE('BS & FCF'!AR6:AS6)+AVERAGE('BS & FCF'!AR7:AS7)))^4-1 -> 0.04925846 | AT25: =(AT24)/(AVERAGE('BS & FCF'!AP6:AS6)+AVERAGE('BS & FCF'!AP7:AS7)) -> 0.05831004 | AU25: =(1+(AU24)/(AVERAGE('BS & FCF'!AT6:AU6)+AVERAGE('BS & FCF'!AT7:AU7)))^4-1 -> 0.048363797 | AV25: =(1+(AV24)/(AVERAGE('BS & FCF'!AU6:AV6)+AVERAGE('BS & FCF'!AU7:AV7)))^4-1 -> 0.087337917 | AW25: =(1+(AW24)/(AVERAGE('BS & FCF'!AV6:AW6)+AVERAGE('BS & FCF'!AV7:AW7)))^4-1 -> 0.045720108 | AX25: =(1+(AX24)/(AVERAGE('BS & FCF'!AW6:AX6)+AVERAGE('BS & FCF'!AW7:AX7)))^4-1 -> 0.042422997 | AY25: =(AY24)/(AVERAGE('BS & FCF'!AU6:AX6)+AVERAGE('BS & FCF'!AU7:AX7)) -> 0.051745193 | AZ25: =(1+(AZ24)/(AVERAGE('BS & FCF'!AY6:AZ6)+AVERAGE('BS & FCF'!AY7:AZ7)))^4-1 -> 0.031441291 | BA25: =(1+(BA24)/(AVERAGE('BS & FCF'!AZ6:BA6)+AVERAGE('BS & FCF'!AZ7:BA7)))^4-1 -> 0.027394912 | BB25: =(1+(BB24)/(AVERAGE('BS & FCF'!BA6:BB6)+AVERAGE('BS & FCF'!BA7:BB7)))^4-1 -> 0.039712323 | BC25: =(1+(BC24)/(AVERAGE('BS & FCF'!BB6:BC6)+AVERAGE('BS & FCF'!BB7:BC7)))^4-1 -> 0.027048763 | BD25: =(BD24)/(AVERAGE('BS & FCF'!AZ6:BC6)+AVERAGE('BS & FCF'!AZ7:BC7)) -> 0.030574658 | BE25: =(1+(BE24)/(AVERAGE('BS & FCF'!BD6:BE6)+AVERAGE('BS & FCF'!BD7:BE7)))^4-1 -> 0.02007833 | BF25: =(1+(BF24)/(AVERAGE('BS & FCF'!BE6:BF6)+AVERAGE('BS & FCF'!BE7:BF7)))^4-1 -> 0.033612651 | BG25: =(1+(BG24)/(AVERAGE('BS & FCF'!BF6:BG6)+AVERAGE('BS & FCF'!BF7:BG7)))^4-1 -> 0.08075581 | BH25: =(1+(BH24)/(AVERAGE('BS & FCF'!BG6:BH6)+AVERAGE('BS & FCF'!BG7:BH7)))^4-1 -> 0.059891839 | BI25: =(BI24)/(AVERAGE('BS & FCF'!BE6:BH6)+AVERAGE('BS & FCF'!BE7:BH7)) -> 0.047500461 | BJ25: =(1+(BJ24)/(AVERAGE('BS & FCF'!BI6:BJ6)+AVERAGE('BS & FCF'!BI7:BJ7)))^4-1 -> 0.088915474 | BK25: =(1+(BK24)/(AVERAGE('BS & FCF'!BJ6:BK6)+AVERAGE('BS & FCF'!BJ7:BK7)))^4-1 -> 0.1135731 | BL25: =(1+(BL24)/(AVERAGE('BS & FCF'!BK6:BL6)+AVERAGE('BS & FCF'!BK7:BL7)))^4-1 -> 0.11849688 | BM25: =(1+(BM24)/(AVERAGE('BS & FCF'!BL6:BM6)+AVERAGE('BS & FCF'!BL7:BM7)))^4-1 -> 0.084306741 | BN25: =(BN24)/(AVERAGE('BS & FCF'!BJ6:BM6)+AVERAGE('BS & FCF'!BJ7:BM7)) -> 0.093974043 | BO25: =(1+(BO24)/(AVERAGE('BS & FCF'!BN6:BO6)+AVERAGE('BS & FCF'!BN7:BO7)))^4-1 -> 0.11008824 | BP25: =(1+(BP24)/(AVERAGE('BS & FCF'!BO6:BP6)+AVERAGE('BS & FCF'!BO7:BP7)))^4-1 -> 0.1075388 | BQ25: =(1+(BQ24)/(AVERAGE('BS & FCF'!BP6:BQ6)+AVERAGE('BS & FCF'!BP7:BQ7)))^4-1 -> 0.082607783 | BR25: =(1+(BR24)/(AVERAGE('BS & FCF'!BQ6:BR6)+AVERAGE('BS & FCF'!BQ7:BR7)))^4-1 -> 0.1011943 | BS25: =(BS24)/(AVERAGE('BS & FCF'!BO6:BR6)+AVERAGE('BS & FCF'!BO7:BR7)) -> 0.093138546 | BT25: =(1+(BT24)/(AVERAGE('BS & FCF'!BS6:BT6)+AVERAGE('BS & FCF'!BS7:BT7)))^4-1 -> 0.080557124 | BU25: =(1+(BU24)/(AVERAGE('BS & FCF'!BT6:BU6)+AVERAGE('BS & FCF'!BT7:BU7)))^4-1 -> 0.080070713 | BV25: =(1+(BV24)/(AVERAGE('BS & FCF'!BU6:BV6)+AVERAGE('BS & FCF'!BU7:BV7)))^4-1 -> 0.087594393 | BW25: =(1+(BW24)/(AVERAGE('BS & FCF'!BV6:BW6)+AVERAGE('BS & FCF'!BV7:BW7)))^4-1 -> 0.082387998 | BX25: =(BX24)/(AVERAGE('BS & FCF'!BT6:BW6)+AVERAGE('BS & FCF'!BT7:BW7)) -> 0.077328531 | BY25: =(1+(BY24)/(AVERAGE('BS & FCF'!BX6:BY6)+AVERAGE('BS & FCF'!BX7:BY7)))^4-1 -> 0.10182059 | BZ25: =(1+(BZ24)/(AVERAGE('BS & FCF'!BY6:BZ6)+AVERAGE('BS & FCF'!BY7:BZ7)))^4-1 -> 0.093720521 | CA25: =(1+(CA24)/(AVERAGE('BS & FCF'!BZ6:CA6)+AVERAGE('BS & FCF'!BZ7:CA7)))^4-1 -> 0.11852829 | CB25: =(1+(CB24)/(AVERAGE('BS & FCF'!CA6:CB6)+AVERAGE('BS & FCF'!CA7:CB7)))^4-1 -> 0.11787504 | CC25: =(CC24)/(AVERAGE('BS & FCF'!BY6:CB6)+AVERAGE('BS & FCF'!BY7:CB7)) -> 0.10153195 | CD25: =(1+(CD24)/(AVERAGE('BS & FCF'!CC6:CD6)+AVERAGE('BS & FCF'!CC7:CD7)))^4-1 -> 0.11436765 | CE25: =(1+(CE24)/(AVERAGE('BS & FCF'!CD6:CE6)+AVERAGE('BS & FCF'!CD7:CE7)))^4-1 -> 0.11726821 | CF25: =Macro!CF12*0.75 -> 0.105625 | CG25: =Macro!CG12*0.75 -> 0.105 | CH25: =(CH24)/(AVERAGE('BS & FCF'!CD6:CG6)+AVERAGE('BS & FCF'!CD7:CG7)) -> 0.10750043 | CI25: =Macro!CI12*0.75 -> 0.105 | CJ25: =Macro!CJ12*0.75 -> 0.1 | CK25: =Macro!CK12*0.75 -> 0.095 | CL25: =Macro!CL12*0.75 -> 0.09375 | CM25: =(CM24)/(AVERAGE('BS & FCF'!CI6:CL6)+AVERAGE('BS & FCF'!CI7:CL7)) -> 0.096634902 | CN25: =Macro!CN12*0.75 -> 0.09375 | CO25: =Macro!CO12*0.75 -> 0.09375 | CP25: =Macro!CP12*0.75 -> 0.09375 | CQ25: =Macro!CQ12*0.75 -> 0.09375 | CR25: =(CR24)/(AVERAGE('BS & FCF'!CN6:CQ6)+AVERAGE('BS & FCF'!CN7:CQ7)) -> 0.092907921 | CS25: =Macro!CS12*0.75 -> 0.09375 | CT25: =Macro!CT12*0.75 -> 0.09375 | CU25: =Macro!CU12*0.75 -> 0.09375 | CV25: =Macro!CV12*0.75 -> 0.09375 | CW25: =(CW24)/(AVERAGE('BS & FCF'!CS6:CV6)+AVERAGE('BS & FCF'!CS7:CV7)) -> 0.093081583 | CX25: =Macro!CX12*0.75 -> 0.09375 | CY25: =Macro!CY12*0.75 -> 0.09375 | CZ25: =Macro!CZ12*0.75 -> 0.09375 | DA25: =Macro!DA12*0.75 -> 0.09375 | DB25: =(DB24)/(AVERAGE('BS & FCF'!CX6:DA6)+AVERAGE('BS & FCF'!CX7:DA7)) -> 0.093225821
A26: Financial expenses | F26: =SUM(B26:E26) -> 0 | K26: =SUM(G26:J26) -> 0 | P26: =SUM(L26:O26) -> 0 | U26: =SUM(Q26:T26) -> 0 | Z26: =SUM(V26:Y26) -> 0 | AE26: =SUM(AA26:AD26) -> 0 | AJ26: =SUM(AF26:AI26) -> 0 | AK26: -766.165 | AL26: -1045.351 | AM26: -1353.653 | AN26: -2114.608 | AO26: =SUM(AK26:AN26) -> -5279.777 | AP26: -560.905 | AQ26: -1107.788 | AR26: -3741.392 | AS26: -3259.349 | AT26: =SUM(AP26:AS26) -> -8669.434 | AU26: -3465 | AV26: -5215 | AW26: -7768 | AX26: =-26689-SUM(AU26:AW26) -> -10241 | AY26: =SUM(AU26:AX26) -> -26689 | AZ26: -4959 | BA26: -5719 | BB26: -6639 | BC26: =-23483-SUM(AZ26:BB26) -> -6166 | BD26: =SUM(AZ26:BC26) -> -23483 | BE26: -7256 | BF26: -9300 | BG26: -11427 | BH26: =-49714-SUM(BE26:BG26) -> -21731 | BI26: =SUM(BE26:BH26) -> -49714 | BJ26: -17062 | BK26: -22214 | BL26: -22860 | BM26: =-88468-SUM(BJ26:BL26) -> -26332 | BN26: =SUM(BJ26:BM26) -> -88468 | BO26: -25672 | BP26: -26026 | BQ26: -23214 | BR26: =-100127-SUM(BO26:BQ26) -> -25215 | BS26: =SUM(BO26:BR26) -> -100127 | BT26: -24806 | BU26: -31099 | BV26: -39673 | BW26: =-137165-SUM(BT26:BV26) -> -41587 | BX26: =SUM(BT26:BW26) -> -137165 | BY26: -51332 | BZ26: -50846 | CA26: -56062 | CB26: =-217836-SUM(BY26:CA26) -> -59596 | CC26: =SUM(BY26:CB26) -> -217836 | CD26: -59802 | CE26: -70288 | CF26: =CF95+CF94 -> -51675.015 | CG26: =CG95+CG94 -> -51884.836 | CH26: =SUM(CD26:CG26) -> -233649.85 | CI26: =CI95+CI94 -> -54494.949 | CJ26: =CJ95+CJ94 -> -56010.795 | CK26: =CK95+CK94 -> -55551.908 | CL26: =CL95+CL94 -> -55906.806 | CM26: =SUM(CI26:CL26) -> -221964.46 | CN26: =CN95+CN94 -> -50990.067 | CO26: =CO95+CO94 -> -53434.378 | CP26: =CP95+CP94 -> -54177.072 | CQ26: =CQ95+CQ94 -> -54440.294 | CR26: =SUM(CN26:CQ26) -> -213041.81 | CS26: =CS95+CS94 -> -56174.196 | CT26: =CT95+CT94 -> -58349.531 | CU26: =CU95+CU94 -> -58977.094 | CV26: =CV95+CV94 -> -58944.368 | CW26: =SUM(CS26:CV26) -> -232445.19 | CX26: =CX95+CX94 -> -60342.356 | CY26: =CY95+CY94 -> -62295.093 | CZ26: =CZ95+CZ94 -> -62707.126 | DA26: =DA95+DA94 -> -62481.123 | DB26: =SUM(CX26:DA26) -> -247825.7
A27: Avg. debt rate (%) | B27: =(1-B26/AVERAGE('BS & FCF'!A51:B51))^4-1 -> #DIV/0! | C27: =(1-C26/AVERAGE('BS & FCF'!B51:C51))^4-1 -> #DIV/0! | D27: =(1-D26/AVERAGE('BS & FCF'!C51:D51))^4-1 -> #DIV/0! | E27: =(1-E26/AVERAGE('BS & FCF'!D51:E51))^4-1 -> #DIV/0! | F27: =-F26/AVERAGE('BS & FCF'!B51:E51) -> #DIV/0! | G27: =(1-G26/AVERAGE('BS & FCF'!F51:G51))^4-1 -> #DIV/0! | H27: =(1-H26/AVERAGE('BS & FCF'!G51:H51))^4-1 -> #DIV/0! | I27: =(1-I26/AVERAGE('BS & FCF'!H51:I51))^4-1 -> #DIV/0! | J27: =(1-J26/AVERAGE('BS & FCF'!I51:J51))^4-1 -> #DIV/0! | K27: =-K26/AVERAGE('BS & FCF'!G51:J51) -> #DIV/0! | L27: =(1-L26/AVERAGE('BS & FCF'!K51:L51))^4-1 -> #DIV/0! | M27: =(1-M26/AVERAGE('BS & FCF'!L51:M51))^4-1 -> #DIV/0! | N27: =(1-N26/AVERAGE('BS & FCF'!M51:N51))^4-1 -> #DIV/0! | O27: =(1-O26/AVERAGE('BS & FCF'!N51:O51))^4-1 -> #DIV/0! | P27: =-P26/AVERAGE('BS & FCF'!L51:O51) -> #DIV/0! | Q27: =(1-Q26/AVERAGE('BS & FCF'!P51:Q51))^4-1 -> #DIV/0! | R27: =(1-R26/AVERAGE('BS & FCF'!Q51:R51))^4-1 -> #DIV/0! | S27: =(1-S26/AVERAGE('BS & FCF'!R51:S51))^4-1 -> #DIV/0! | T27: =(1-T26/AVERAGE('BS & FCF'!S51:T51))^4-1 -> #DIV/0! | U27: =-U26/AVERAGE('BS & FCF'!Q51:T51) -> #DIV/0! | V27: =(1-V26/AVERAGE('BS & FCF'!U51:V51))^4-1 -> #DIV/0! | W27: =(1-W26/AVERAGE('BS & FCF'!V51:W51))^4-1 -> #DIV/0! | X27: =(1-X26/AVERAGE('BS & FCF'!W51:X51))^4-1 -> #DIV/0! | Y27: =(1-Y26/AVERAGE('BS & FCF'!X51:Y51))^4-1 -> #DIV/0! | Z27: =-Z26/AVERAGE('BS & FCF'!V51:Y51) -> #DIV/0! | AA27: =(1-AA26/AVERAGE('BS & FCF'!Z51:AA51))^4-1 -> #DIV/0! | AB27: =(1-AB26/AVERAGE('BS & FCF'!AA51:AB51))^4-1 -> #DIV/0! | AC27: =(1-AC26/AVERAGE('BS & FCF'!AB51:AC51))^4-1 -> #DIV/0! | AD27: =(1-AD26/AVERAGE('BS & FCF'!AC51:AD51))^4-1 -> #DIV/0! | AE27: =-AE26/AVERAGE('BS & FCF'!AA51:AD51) -> #DIV/0! | AF27: =(1-AF26/AVERAGE('BS & FCF'!AE51:AF51))^4-1 -> #DIV/0! | AG27: =(1-AG26/AVERAGE('BS & FCF'!AF51:AG51))^4-1 -> #DIV/0! | AH27: =(1-AH26/AVERAGE('BS & FCF'!AG51:AH51))^4-1 -> #DIV/0! | AI27: =(1-AI26/AVERAGE('BS & FCF'!AH51:AI51))^4-1 -> #DIV/0! | AJ27: =-AJ26/AVERAGE('BS & FCF'!AF51:AI51) -> #DIV/0! | AK27: =(1-AK26/AVERAGE('BS & FCF'!AJ51:AK51))^4-1 -> 0.031620608 | AL27: =(1-AL26/AVERAGE('BS & FCF'!AK51:AL51))^4-1 -> 0.021876929 | AM27: =(1-AM26/AVERAGE('BS & FCF'!AL51:AM51))^4-1 -> 0.029043185 | AN27: =(1-AN26/AVERAGE('BS & FCF'!AM51:AN51))^4-1 -> 0.045855545 | AO27: =-AO26/AVERAGE('BS & FCF'!AK51:AN51) -> 0.027766781 | AP27: =(1-AP26/AVERAGE('BS & FCF'!AO51:AP51))^4-1 -> 0.013259973 | AQ27: =(1-AQ26/AVERAGE('BS & FCF'!AP51:AQ51))^4-1 -> 0.031904455 | AR27: =(1-AR26/AVERAGE('BS & FCF'!AQ51:AR51))^4-1 -> 0.088386598 | AS27: =(1-AS26/AVERAGE('BS & FCF'!AR51:AS51))^4-1 -> 0.060774007 | AT27: =-AT26/AVERAGE('BS & FCF'!AP51:AS51) -> 0.048178176 | AU27: =(1-AU26/AVERAGE('BS & FCF'!AT51:AU51))^4-1 -> 0.065326971 | AV27: =(1-AV26/AVERAGE('BS & FCF'!AU51:AV51))^4-1 -> 0.098429668 | AW27: =(1-AW26/AVERAGE('BS & FCF'!AV51:AW51))^4-1 -> 0.15234017 | AX27: =(1-AX26/AVERAGE('BS & FCF'!AW51:AX51))^4-1 -> 0.17595504 | AY27: =-AY26/AVERAGE('BS & FCF'!AU51:AX51) -> 0.11423863 | AZ27: =(1-AZ26/AVERAGE('BS & FCF'!AY51:AZ51))^4-1 -> 0.069890676 | BA27: =(1-BA26/AVERAGE('BS & FCF'!AZ51:BA51))^4-1 -> 0.074487147 | BB27: =(1-BB26/AVERAGE('BS & FCF'!BA51:BB51))^4-1 -> 0.085332718 | BC27: =(1-BC26/AVERAGE('BS & FCF'!BB51:BC51))^4-1 -> 0.087349532 | BD27: =-BD26/AVERAGE('BS & FCF'!AZ51:BC51) -> 0.077372568 | BE27: =(1-BE26/AVERAGE('BS & FCF'!BD51:BE51))^4-1 -> 0.10826012 | BF27: =(1-BF26/AVERAGE('BS & FCF'!BE51:BF51))^4-1 -> 0.14199678 | BG27: =(1-BG26/AVERAGE('BS & FCF'!BF51:BG51))^4-1 -> 0.14575037 | BH27: =(1-BH26/AVERAGE('BS & FCF'!BG51:BH51))^4-1 -> 0.24172513 | BI27: =-BI26/AVERAGE('BS & FCF'!BE51:BH51) -> 0.14923124 | BJ27: =(1-BJ26/AVERAGE('BS & FCF'!BI51:BJ51))^4-1 -> 0.18628551 | BK27: =(1-BK26/AVERAGE('BS & FCF'!BJ51:BK51))^4-1 -> 0.24470533 | BL27: =(1-BL26/AVERAGE('BS & FCF'!BK51:BL51))^4-1 -> 0.23167319 | BM27: =(1-BM26/AVERAGE('BS & FCF'!BL51:BM51))^4-1 -> 0.24449123 | BN27: =-BN26/AVERAGE('BS & FCF'!BJ51:BM51) -> 0.20492425 | BO27: =(1-BO26/AVERAGE('BS & FCF'!BN51:BO51))^4-1 -> 0.23289337 | BP27: =(1-BP26/AVERAGE('BS & FCF'!BO51:BP51))^4-1 -> 0.23148872 | BQ27: =(1-BQ26/AVERAGE('BS & FCF'!BP51:BQ51))^4-1 -> 0.17227632 | BR27: =(1-BR26/AVERAGE('BS & FCF'!BQ51:BR51))^4-1 -> 0.17009858 | BS27: =-BS26/AVERAGE('BS & FCF'!BO51:BR51) -> 0.17934305 | BT27: =(1-BT26/AVERAGE('BS & FCF'!BS51:BT51))^4-1 -> 0.17357409 | BU27: =(1-BU26/AVERAGE('BS & FCF'!BT51:BU51))^4-1 -> 0.15626146 | BV27: =(1-BV26/AVERAGE('BS & FCF'!BU51:BV51))^4-1 -> 0.15348997 | BW27: =(1-BW26/AVERAGE('BS & FCF'!BV51:BW51))^4-1 -> 0.16903536 | BX27: =-BX26/AVERAGE('BS & FCF'!BT51:BW51) -> 0.14547393 | BY27: =(1-BY26/AVERAGE('BS & FCF'!BX51:BY51))^4-1 -> 0.19362599 | BZ27: =(1-BZ26/AVERAGE('BS & FCF'!BY51:BZ51))^4-1 -> 0.16682539 | CA27: =(1-CA26/AVERAGE('BS & FCF'!BZ51:CA51))^4-1 -> 0.18203655 | CB27: =(1-CB26/AVERAGE('BS & FCF'!CA51:CB51))^4-1 -> 0.18160532 | CC27: =-CC26/AVERAGE('BS & FCF'!BY51:CB51) -> 0.16184566 | CD27: =(1-CD26/AVERAGE('BS & FCF'!CC51:CD51))^4-1 -> 0.18039188 | CE27: =(1-CE26/AVERAGE('BS & FCF'!CD51:CE51))^4-1 -> 0.22567627 | CF27: =(1-CF26/AVERAGE('BS & FCF'!CE51:CF51))^4-1 -> 0.16195833 | CG27: =(1-CG26/AVERAGE('BS & FCF'!CF51:CG51))^4-1 -> 0.161 | CH27: =-CH26/AVERAGE('BS & FCF'!CD51:CG51) -> 0.17235534 | CI27: =(1-CI26/AVERAGE('BS & FCF'!CH51:CI51))^4-1 -> 0.161 | CJ27: =(1-CJ26/AVERAGE('BS & FCF'!CI51:CJ51))^4-1 -> 0.15333333 | CK27: =(1-CK26/AVERAGE('BS & FCF'!CJ51:CK51))^4-1 -> 0.14566667 | CL27: =(1-CL26/AVERAGE('BS & FCF'!CK51:CL51))^4-1 -> 0.14375 | CM27: =-CM26/AVERAGE('BS & FCF'!CI51:CL51) -> 0.13960673 | CN27: =(1-CN26/AVERAGE('BS & FCF'!CM51:CN51))^4-1 -> 0.125 | CO27: =(1-CO26/AVERAGE('BS & FCF'!CN51:CO51))^4-1 -> 0.125 | CP27: =(1-CP26/AVERAGE('BS & FCF'!CO51:CP51))^4-1 -> 0.125 | CQ27: =(1-CQ26/AVERAGE('BS & FCF'!CP51:CQ51))^4-1 -> 0.125 | CR27: =-CR26/AVERAGE('BS & FCF'!CN51:CQ51) -> 0.1180342 | CS27: =(1-CS26/AVERAGE('BS & FCF'!CR51:CS51))^4-1 -> 0.125 | CT27: =(1-CT26/AVERAGE('BS & FCF'!CS51:CT51))^4-1 -> 0.125 | CU27: =(1-CU26/AVERAGE('BS & FCF'!CT51:CU51))^4-1 -> 0.125 | CV27: =(1-CV26/AVERAGE('BS & FCF'!CU51:CV51))^4-1 -> 0.125 | CW27: =-CW26/AVERAGE('BS & FCF'!CS51:CV51) -> 0.11844252 | CX27: =(1-CX26/AVERAGE('BS & FCF'!CW51:CX51))^4-1 -> 0.125 | CY27: =(1-CY26/AVERAGE('BS & FCF'!CX51:CY51))^4-1 -> 0.125 | CZ27: =(1-CZ26/AVERAGE('BS & FCF'!CY51:CZ51))^4-1 -> 0.125 | DA27: =(1-DA26/AVERAGE('BS & FCF'!CZ51:DA51))^4-1 -> 0.125 | DB27: =-DB26/AVERAGE('BS & FCF'!CX51:DA51) -> 0.11870719
A28: Client financing (direct sales) | B28: 0 | C28: 0 | D28: 0 | E28: 0 | F28: =SUM(B28:E28) -> 0 | G28: 0 | H28: 0 | I28: 0 | J28: 0 | K28: =SUM(G28:J28) -> 0 | L28: 0 | M28: 0 | N28: 0 | O28: 0 | P28: =SUM(L28:O28) -> 0 | Q28: 0 | R28: 0 | S28: 0 | T28: 0 | U28: =SUM(Q28:T28) -> 0 | V28: 0 | W28: 0 | X28: 0 | Y28: 0 | Z28: =SUM(V28:Y28) -> 0 | AA28: 0 | AB28: 0 | AC28: 0 | AD28: 0 | AE28: =SUM(AA28:AD28) -> 0 | AF28: 0 | AG28: 0 | AH28: 0 | AI28: 0 | AJ28: =SUM(AF28:AI28) -> 0 | AK28: 0 | AL28: 0 | AM28: 0 | AN28: 0 | AO28: =SUM(AK28:AN28) -> 0 | AP28: 0 | AQ28: 0 | AR28: 0 | AS28: 0 | AT28: =SUM(AP28:AS28) -> 0 | AU28: 0 | AV28: 0 | AW28: 0 | AX28: 0 | AY28: =SUM(AU28:AX28) -> 0 | AZ28: 0 | BA28: 0 | BB28: 0 | BC28: 0 | BD28: =SUM(AZ28:BC28) -> 0 | BE28: 0 | BF28: 0 | BG28: 0 | BH28: 0 | BI28: =SUM(BE28:BH28) -> 0 | BJ28: 0 | BK28: 0 | BL28: 0 | BM28: 0 | BN28: =SUM(BJ28:BM28) -> 0 | BO28: 0 | BP28: 0 | BQ28: 0 | BR28: 0 | BS28: =SUM(BO28:BR28) -> 0 | BT28: 0 | BU28: 0 | BV28: 0 | BW28: 0 | BX28: =SUM(BT28:BW28) -> 0 | BY28: 0 | BZ28: 0 | CA28: 0 | CB28: 0 | CC28: =SUM(BY28:CB28) -> 0 | CD28: 0 | CE28: 0 | CF28: =((1+AVERAGE('BS & FCF'!CE11:CF11))^1/4)*CF29 -> 0 | CG28: =((1+AVERAGE('BS & FCF'!CF11:CG11))^1/4)*CG29 -> 0 | CH28: =SUM(CD28:CG28) -> 0 | CI28: =((1+AVERAGE('BS & FCF'!CH11:CI11))^1/4)*CI29 -> 0 | CJ28: =((1+AVERAGE('BS & FCF'!CI11:CJ11))^1/4)*CJ29 -> 0 | CK28: =((1+AVERAGE('BS & FCF'!CJ11:CK11))^1/4)*CK29 -> 0 | CL28: =((1+AVERAGE('BS & FCF'!CK11:CL11))^1/4)*CL29 -> 0 | CM28: =SUM(CI28:CL28) -> 0 | CN28: =((1+AVERAGE('BS & FCF'!CM11:CN11))^1/4)*CN29 -> 0 | CO28: =((1+AVERAGE('BS & FCF'!CN11:CO11))^1/4)*CO29 -> 0 | CP28: =((1+AVERAGE('BS & FCF'!CO11:CP11))^1/4)*CP29 -> 0 | CQ28: =((1+AVERAGE('BS & FCF'!CP11:CQ11))^1/4)*CQ29 -> 0 | CR28: =SUM(CN28:CQ28) -> 0 | CS28: =((1+AVERAGE('BS & FCF'!CR11:CS11))^1/4)*CS29 -> 0 | CT28: =((1+AVERAGE('BS & FCF'!CS11:CT11))^1/4)*CT29 -> 0 | CU28: =((1+AVERAGE('BS & FCF'!CT11:CU11))^1/4)*CU29 -> 0 | CV28: =((1+AVERAGE('BS & FCF'!CU11:CV11))^1/4)*CV29 -> 0 | CW28: =SUM(CS28:CV28) -> 0 | CX28: =((1+AVERAGE('BS & FCF'!CW11:CX11))^1/4)*CX29 -> 0 | CY28: =((1+AVERAGE('BS & FCF'!CX11:CY11))^1/4)*CY29 -> 0 | CZ28: =((1+AVERAGE('BS & FCF'!CY11:CZ11))^1/4)*CZ29 -> 0 | DA28: =((1+AVERAGE('BS & FCF'!CZ11:DA11))^1/4)*DA29 -> 0 | DB28: =SUM(CX28:DA28) -> 0
A29: Avg. client financing rate (%) | B29: =IFERROR((1-B28/AVERAGE('BS & FCF'!A11:B11))^4-1,0) -> 0 | C29: =IFERROR((1-C28/AVERAGE('BS & FCF'!B11:C11))^4-1,0) -> 0 | D29: =IFERROR((1-D28/AVERAGE('BS & FCF'!C11:D11))^4-1,0) -> 0 | E29: =IFERROR((1-E28/AVERAGE('BS & FCF'!D11:E11))^4-1,0) -> 0 | F29: =IFERROR(-F28/AVERAGE('BS & FCF'!B11:E11),0) -> 0 | G29: =IFERROR((1-G28/AVERAGE('BS & FCF'!F11:G11))^4-1,0) -> 0 | H29: =IFERROR((1-H28/AVERAGE('BS & FCF'!G11:H11))^4-1,0) -> 0 | I29: =IFERROR((1-I28/AVERAGE('BS & FCF'!H11:I11))^4-1,0) -> 0 | J29: =IFERROR((1-J28/AVERAGE('BS & FCF'!I11:J11))^4-1,0) -> 0 | K29: =IFERROR(-K28/AVERAGE('BS & FCF'!G11:J11),0) -> 0 | L29: =IFERROR((1-L28/AVERAGE('BS & FCF'!K11:L11))^4-1,0) -> 0 | M29: =IFERROR((1-M28/AVERAGE('BS & FCF'!L11:M11))^4-1,0) -> 0 | N29: =IFERROR((1-N28/AVERAGE('BS & FCF'!M11:N11))^4-1,0) -> 0 | O29: =IFERROR((1-O28/AVERAGE('BS & FCF'!N11:O11))^4-1,0) -> 0 | P29: =IFERROR(-P28/AVERAGE('BS & FCF'!L11:O11),0) -> 0 | Q29: =IFERROR((1-Q28/AVERAGE('BS & FCF'!P11:Q11))^4-1,0) -> 0 | R29: =IFERROR((1-R28/AVERAGE('BS & FCF'!Q11:R11))^4-1,0) -> 0 | S29: =IFERROR((1-S28/AVERAGE('BS & FCF'!R11:S11))^4-1,0) -> 0 | T29: =IFERROR((1-T28/AVERAGE('BS & FCF'!S11:T11))^4-1,0) -> 0 | U29: =IFERROR(-U28/AVERAGE('BS & FCF'!Q11:T11),0) -> 0 | V29: =IFERROR((1-V28/AVERAGE('BS & FCF'!U11:V11))^4-1,0) -> 0 | W29: =IFERROR((1-W28/AVERAGE('BS & FCF'!V11:W11))^4-1,0) -> 0 | X29: =IFERROR((1-X28/AVERAGE('BS & FCF'!W11:X11))^4-1,0) -> 0 | Y29: =IFERROR((1-Y28/AVERAGE('BS & FCF'!X11:Y11))^4-1,0) -> 0 | Z29: =IFERROR(-Z28/AVERAGE('BS & FCF'!V11:Y11),0) -> 0 | AA29: =IFERROR((1-AA28/AVERAGE('BS & FCF'!Z11:AA11))^4-1,0) -> 0 | AB29: =IFERROR((1-AB28/AVERAGE('BS & FCF'!AA11:AB11))^4-1,0) -> 0 | AC29: =IFERROR((1-AC28/AVERAGE('BS & FCF'!AB11:AC11))^4-1,0) -> 0 | AD29: =IFERROR((1-AD28/AVERAGE('BS & FCF'!AC11:AD11))^4-1,0) -> 0 | AE29: =IFERROR(-AE28/AVERAGE('BS & FCF'!AA11:AD11),0) -> 0 | AF29: =IFERROR((1-AF28/AVERAGE('BS & FCF'!AE11:AF11))^4-1,0) -> 0 | AG29: =IFERROR((1-AG28/AVERAGE('BS & FCF'!AF11:AG11))^4-1,0) -> 0 | AH29: =IFERROR((1-AH28/AVERAGE('BS & FCF'!AG11:AH11))^4-1,0) -> 0 | AI29: =IFERROR((1-AI28/AVERAGE('BS & FCF'!AH11:AI11))^4-1,0) -> 0 | AJ29: =IFERROR(-AJ28/AVERAGE('BS & FCF'!AF11:AI11),0) -> 0 | AK29: =IFERROR((1-AK28/AVERAGE('BS & FCF'!AJ11:AK11))^4-1,0) -> 0 | AL29: =IFERROR((1-AL28/AVERAGE('BS & FCF'!AK11:AL11))^4-1,0) -> 0 | AM29: =IFERROR((1-AM28/AVERAGE('BS & FCF'!AL11:AM11))^4-1,0) -> 0 | AN29: =IFERROR((1-AN28/AVERAGE('BS & FCF'!AM11:AN11))^4-1,0) -> 0 | AO29: =IFERROR(-AO28/AVERAGE('BS & FCF'!AK11:AN11),0) -> 0 | AP29: =IFERROR((1-AP28/AVERAGE('BS & FCF'!AO11:AP11))^4-1,0) -> 0 | AQ29: =IFERROR((1-AQ28/AVERAGE('BS & FCF'!AP11:AQ11))^4-1,0) -> 0 | AR29: =IFERROR((1-AR28/AVERAGE('BS & FCF'!AQ11:AR11))^4-1,0) -> 0 | AS29: =IFERROR((1-AS28/AVERAGE('BS & FCF'!AR11:AS11))^4-1,0) -> 0 | AT29: =IFERROR(-AT28/AVERAGE('BS & FCF'!AP11:AS11),0) -> 0 | AU29: =IFERROR((1-AU28/AVERAGE('BS & FCF'!AT11:AU11))^4-1,0) -> 0 | AV29: =IFERROR((1-AV28/AVERAGE('BS & FCF'!AU11:AV11))^4-1,0) -> 0 | AW29: =IFERROR((1-AW28/AVERAGE('BS & FCF'!AV11:AW11))^4-1,0) -> 0 | AX29: =IFERROR((1-AX28/AVERAGE('BS & FCF'!AW11:AX11))^4-1,0) -> 0 | AY29: =IFERROR(-AY28/AVERAGE('BS & FCF'!AU11:AX11),0) -> 0 | AZ29: =IFERROR((1-AZ28/AVERAGE('BS & FCF'!AY11:AZ11))^4-1,0) -> 0 | BA29: =IFERROR((1-BA28/AVERAGE('BS & FCF'!AZ11:BA11))^4-1,0) -> 0 | BB29: =IFERROR((1-BB28/AVERAGE('BS & FCF'!BA11:BB11))^4-1,0) -> 0 | BC29: =IFERROR((1-BC28/AVERAGE('BS & FCF'!BB11:BC11))^4-1,0) -> 0 | BD29: =IFERROR(-BD28/AVERAGE('BS & FCF'!AZ11:BC11),0) -> 0 | BE29: =IFERROR((1-BE28/AVERAGE('BS & FCF'!BD11:BE11))^4-1,0) -> 0 | BF29: =IFERROR((1-BF28/AVERAGE('BS & FCF'!BE11:BF11))^4-1,0) -> 0 | BG29: =IFERROR((1-BG28/AVERAGE('BS & FCF'!BF11:BG11))^4-1,0) -> 0 | BH29: =IFERROR((1-BH28/AVERAGE('BS & FCF'!BG11:BH11))^4-1,0) -> 0 | BI29: =IFERROR(-BI28/AVERAGE('BS & FCF'!BE11:BH11),0) -> 0 | BJ29: =IFERROR((1-BJ28/AVERAGE('BS & FCF'!BI11:BJ11))^4-1,0) -> 0 | BK29: =IFERROR((1-BK28/AVERAGE('BS & FCF'!BJ11:BK11))^4-1,0) -> 0 | BL29: =IFERROR((1-BL28/AVERAGE('BS & FCF'!BK11:BL11))^4-1,0) -> 0 | BM29: =IFERROR((1-BM28/AVERAGE('BS & FCF'!BL11:BM11))^4-1,0) -> 0 | BN29: =IFERROR(-BN28/AVERAGE('BS & FCF'!BJ11:BM11),0) -> 0 | BO29: =IFERROR((1-BO28/AVERAGE('BS & FCF'!BN11:BO11))^4-1,0) -> 0 | BP29: =IFERROR((1-BP28/AVERAGE('BS & FCF'!BO11:BP11))^4-1,0) -> 0 | BQ29: =IFERROR((1-BQ28/AVERAGE('BS & FCF'!BP11:BQ11))^4-1,0) -> 0 | BR29: =IFERROR((1-BR28/AVERAGE('BS & FCF'!BQ11:BR11))^4-1,0) -> 0 | BS29: =IFERROR(-BS28/AVERAGE('BS & FCF'!BO11:BR11),0) -> 0 | BT29: =IFERROR((1-BT28/AVERAGE('BS & FCF'!BS11:BT11))^4-1,0) -> 0 | BU29: =IFERROR((1-BU28/AVERAGE('BS & FCF'!BT11:BU11))^4-1,0) -> 0 | BV29: =IFERROR((1-BV28/AVERAGE('BS & FCF'!BU11:BV11))^4-1,0) -> 0 | BW29: =IFERROR((1-BW28/AVERAGE('BS & FCF'!BV11:BW11))^4-1,0) -> 0 | BX29: =IFERROR(-BX28/AVERAGE('BS & FCF'!BT11:BW11),0) -> 0 | BY29: =IFERROR((1+BY28/AVERAGE('BS & FCF'!BX11:BY11))^4-1,0) -> 0 | BZ29: =IFERROR((1-BZ28/AVERAGE('BS & FCF'!BY11:BZ11))^4-1,0) -> 0 | CA29: =IFERROR((1-CA28/AVERAGE('BS & FCF'!BZ11:CA11))^4-1,0) -> 0 | CB29: =IFERROR((1-CB28/AVERAGE('BS & FCF'!CA11:CB11))^4-1,0) -> 0 | CC29: =IFERROR(CC28/AVERAGE('BS & FCF'!BY11:CB11),0) -> 0 | CD29: =IFERROR((1+CD28/AVERAGE('BS & FCF'!CC11:CD11))^4-1,0) -> 0 | CE29: =IFERROR((1-CE28/AVERAGE('BS & FCF'!CD11:CE11))^4-1,0) -> 0 | CF29: =CE29 -> 0 | CG29: =CF29 -> 0 | CH29: =IFERROR(CH28/AVERAGE('BS & FCF'!CD11:CG11),0) -> 0 | CI29: =CG29 -> 0 | CJ29: =CI29 -> 0 | CK29: =CJ29 -> 0 | CL29: =CK29 -> 0 | CM29: =IFERROR(CM28/AVERAGE('BS & FCF'!CI11:CL11),0) -> 0 | CN29: =CL29 -> 0 | CO29: =CN29 -> 0 | CP29: =CO29 -> 0 | CQ29: =CP29 -> 0 | CR29: =IFERROR(CR28/AVERAGE('BS & FCF'!CN11:CQ11),0) -> 0 | CS29: =CQ29 -> 0 | CT29: =CS29 -> 0 | CU29: =CT29 -> 0 | CV29: =CU29 -> 0 | CW29: =IFERROR(CW28/AVERAGE('BS & FCF'!CS11:CV11),0) -> 0 | CX29: =CV29 -> 0 | CY29: =CX29 -> 0 | CZ29: =CY29 -> 0 | DA29: =CZ29 -> 0 | DB29: =IFERROR(DB28/AVERAGE('BS & FCF'!CX11:DA11),0) -> 0
A30: Other Operating Expenses | B30: =B31+B32+B33 -> 0 | C30: =C31+C32+C33 -> 0 | D30: =D31+D32+D33 -> 0 | E30: =E31+E32+E33 -> 0 | F30: =SUM(B30:E30) -> 0 | G30: =G31+G32+G33 -> 0 | H30: =H31+H32+H33 -> 0 | I30: =I31+I32+I33 -> 0 | J30: =J31+J32+J33 -> 0 | K30: =SUM(G30:J30) -> 0 | L30: =L31+L32+L33 -> 0 | M30: =M31+M32+M33 -> 0 | N30: =N31+N32+N33 -> 0 | O30: =O31+O32+O33 -> 0 | P30: =SUM(L30:O30) -> 0 | Q30: =Q31+Q32+Q33 -> 0 | R30: =R31+R32+R33 -> 0 | S30: =S31+S32+S33 -> 0 | T30: =T31+T32+T33 -> 0 | U30: =SUM(Q30:T30) -> 0 | V30: =V31+V32+V33 -> 0 | W30: =W31+W32+W33 -> 0 | X30: =X31+X32+X33 -> 0 | Y30: =Y31+Y32+Y33 -> 0 | Z30: =SUM(V30:Y30) -> 0 | AA30: =AA31+AA32+AA33 -> 0 | AB30: =AB31+AB32+AB33 -> 0 | AC30: =AC31+AC32+AC33 -> 0 | AD30: =AD31+AD32+AD33 -> 0 | AE30: =SUM(AA30:AD30) -> 0 | AF30: =AF31+AF32+AF33 -> 0 | AG30: =AG31+AG32+AG33 -> 0 | AH30: =AH31+AH32+AH33 -> 0 | AI30: =AI31+AI32+AI33 -> 0 | AJ30: =SUM(AF30:AI30) -> 0 | AK30: =AK31+AK32+AK33 -> 1897.551 | AL30: =AL31+AL32+AL33 -> 879.217 | AM30: =AM31+AM32+AM33 -> 10691.399 | AN30: =AN31+AN32+AN33 -> 15799.157 | AO30: =SUM(AK30:AN30) -> 29267.324 | AP30: =AP31+AP32+AP33 -> 3254.54 | AQ30: =AQ31+AQ32+AQ33 -> 1197.336 | AR30: =AR31+AR32+AR33 -> 1677.188 | AS30: =AS31+AS32+AS33 -> 3306.184 | AT30: =SUM(AP30:AS30) -> 9435.248 | AU30: =AU31+AU32+AU33 -> 12268 | AV30: =AV31+AV32+AV33 -> 26623 | AW30: =AW31+AW32+AW33 -> 18961 | AX30: =AX31+AX32+AX33 -> 18642 | AY30: =SUM(AU30:AX30) -> 76494 | AZ30: =AZ31+AZ32+AZ33 -> -6104 | BA30: =BA31+BA32+BA33 -> 2058 | BB30: =BB31+BB32+BB33 -> -3669 | BC30: =BC31+BC32+BC33 -> 124 | BD30: =SUM(AZ30:BC30) -> -7591 | BE30: =BE31+BE32+BE33 -> -6859 | BF30: =BF31+BF32+BF33 -> -11260 | BG30: =BG31+BG32+BG33 -> -9272 | BH30: =BH31+BH32+BH33 -> 23413 | BI30: =SUM(BE30:BH30) -> -3978 | BJ30: =BJ31+BJ32+BJ33 -> -19752 | BK30: =BK31+BK32+BK33 -> -15841 | BL30: =BL31+BL32+BL33 -> -11872 | BM30: =BM31+BM32+BM33 -> -13461 | BN30: =SUM(BJ30:BM30) -> -60926 | BO30: =BO31+BO32+BO33 -> -13586 | BP30: =BP31+BP32+BP33 -> -19289 | BQ30: =BQ31+BQ32+BQ33 -> -13499 | BR30: =BR31+BR32+BR33 -> -20648 | BS30: =SUM(BO30:BR30) -> -67022 | BT30: =BT31+BT32+BT33 -> -21874 | BU30: =BU31+BU32+BU33 -> -23978 | BV30: =BV31+BV32+BV33 -> -20472 | BW30: =BW31+BW32+BW33 -> -21847 | BX30: =SUM(BT30:BW30) -> -88171 | BY30: =BY31+BY32+BY33 -> -39942 | BZ30: =BZ31+BZ32+BZ33 -> -30720 | CA30: =CA31+CA32+CA33 -> -39423 | CB30: =CB31+CB32+CB33 -> -42467 | CC30: =SUM(BY30:CB30) -> -152552 | CD30: =CD31+CD32+CD33 -> -45003 | CE30: =CE31+CE32+CE33 -> -45995 | CF30: =CF31+CF32+CF33 -> -57819.702 | CG30: =CG31+CG32+CG33 -> -58627.922 | CH30: =SUM(CD30:CG30) -> -207445.62 | CI30: =CI31+CI32+CI33 -> -61508.437 | CJ30: =CJ31+CJ32+CJ33 -> -68799.662 | CK30: =CK31+CK32+CK33 -> -69486.733 | CL30: =CL31+CL32+CL33 -> -66443.566 | CM30: =SUM(CI30:CL30) -> -266238.4 | CN30: =CN31+CN32+CN33 -> -60951.249 | CO30: =CO31+CO32+CO33 -> -65747.312 | CP30: =CP31+CP32+CP33 -> -66385.404 | CQ30: =CQ31+CQ32+CQ33 -> -64831.951 | CR30: =SUM(CN30:CQ30) -> -257915.92 | CS30: =CS31+CS32+CS33 -> -67075.957 | CT30: =CT31+CT32+CT33 -> -71428.821 | CU30: =CU31+CU32+CU33 -> -71610.622 | CV30: =CV31+CV32+CV33 -> -69618.985 | CW30: =SUM(CS30:CV30) -> -279734.38 | CX30: =CX31+CX32+CX33 -> -71649.012 | CY30: =CY31+CY32+CY33 -> -75925.253 | CZ30: =CZ31+CZ32+CZ33 -> -75906.209 | DA30: =DA31+DA32+DA33 -> -73659.121 | DB30: =SUM(CX30:DA30) -> -297139.6
A31: Expenses | F31: =SUM(B31:E31) -> 0 | K31: =SUM(G31:J31) -> 0 | P31: =SUM(L31:O31) -> 0 | U31: =SUM(Q31:T31) -> 0 | Z31: =SUM(V31:Y31) -> 0 | AE31: =SUM(AA31:AD31) -> 0 | AJ31: =SUM(AF31:AI31) -> 0 | AK31: 1897.551 | AL31: 879.217 | AM31: 10691.399 | AN31: 15799.157 | AO31: =SUM(AK31:AN31) -> 29267.324 | AP31: 3254.54 | AQ31: 1197.336 | AR31: 1677.188 | AS31: 3306.184 | AT31: =SUM(AP31:AS31) -> 9435.248 | AU31: =23718-9596 -> 14122 | AV31: =28892-2090 -> 26802 | AW31: =20410-1050 -> 19360 | AX31: =120320-42671-SUM(AU31:AW31) -> 17365 | AY31: =SUM(AU31:AX31) -> 77649 | AZ31: =1328-4507 -> -3179 | BA31: =9179-6814 -> 2365 | BB31: =2943-6247 -> -3304 | BC31: =11840-17872-SUM(AZ31:BB31) -> -1914 | BD31: =SUM(AZ31:BC31) -> -6032 | BE31: =0-6524 -> -6524 | BF31: =0-10905 -> -10905 | BG31: -8907 | BH31: =40444-42984-SUM(BE31:BG31) -> 23796 | BI31: =SUM(BE31:BH31) -> -2540 | BJ31: =0-19298 -> -19298 | BK31: =0-15382 -> -15382 | BL31: -11456 | BM31: =2756-61830-SUM(BJ31:BL31) -> -12938 | BN31: =SUM(BJ31:BM31) -> -59074 | BO31: =-12810 -> -12810 | BP31: =0-18568 -> -18568 | BQ31: -12803 | BR31: =0-64047-SUM(BO31:BQ31) -> -19866 | BS31: =SUM(BO31:BR31) -> -64047 | BT31: -21345 | BU31: =0-23250 -> -23250 | BV31: -19747 | BW31: =2965-88463-SUM(BT31:BV31) -> -21156 | BX31: =SUM(BT31:BW31) -> -85498 | BY31: -39738 | BZ31: =-30494 -> -30494 | CA31: -39204 | CB31: =-151687-SUM(BY31:CA31) -> -42251 | CC31: =SUM(BY31:CB31) -> -151687 | CD31: -44791 | CE31: -45797 | CF31: =-2.75%*CF5-(90000*75%/8) -> -57601.339 | CG31: =-2.75%*CG5-(90000*75%/8) -> -58409.467 | CH31: =SUM(CD31:CG31) -> -206598.81 | CI31: =-2.75%*CI5-(90000*75%/8) -> -61289.888 | CJ31: =-2.75%*CJ5-(90000*75%/8) -> -68581.019 | CK31: =-2.75%*CK5-(90000*75%/8) -> -69267.998 | CL31: =-2.75%*CL5-(90000*75%/8) -> -66224.737 | CM31: =SUM(CI31:CL31) -> -265363.64 | CN31: =-2.75%*CN5 -> -60732.327 | CO31: =-2.75%*CO5 -> -65528.296 | CP31: =-2.75%*CP5 -> -66166.295 | CQ31: =-2.75%*CQ5 -> -64612.748 | CR31: =SUM(CN31:CQ31) -> -257039.67 | CS31: =-2.75%*CS5 -> -66856.66 | CT31: =-2.75%*CT5 -> -71209.431 | CU31: =-2.75%*CU5 -> -71391.139 | CV31: =-2.75%*CV5 -> -69399.407 | CW31: =SUM(CS31:CV31) -> -278856.64 | CX31: =-2.75%*CX5 -> -71429.341 | CY31: =-2.75%*CY5 -> -75705.488 | CZ31: =-2.75%*CZ5 -> -75686.35 | DA31: =-2.75%*DA5 -> -73439.168 | DB31: =SUM(CX31:DA31) -> -296260.35
A32: D&A | F32: =SUM(B32:E32) -> 0 | K32: =SUM(G32:J32) -> 0 | P32: =SUM(L32:O32) -> 0 | U32: =SUM(Q32:T32) -> 0 | Z32: =SUM(V32:Y32) -> 0 | AE32: =SUM(AA32:AD32) -> 0 | AJ32: =SUM(AF32:AI32) -> 0 | AO32: =SUM(AK32:AN32) -> 0 | AT32: =SUM(AP32:AS32) -> 0 | AU32: -1854 | AV32: -179 | AW32: -399 | AX32: =-1155-SUM(AU32:AW32) -> 1277 | AY32: =SUM(AU32:AX32) -> -1155 | AZ32: -2925 | BA32: -307 | BB32: -365 | BC32: =-1559-SUM(AZ32:BB32) -> 2038 | BD32: =SUM(AZ32:BC32) -> -1559 | BE32: -335 | BF32: -355 | BG32: -365 | BH32: =-1438-SUM(BE32:BG32) -> -383 | BI32: =SUM(BE32:BH32) -> -1438 | BJ32: -454 | BK32: -459 | BL32: -416 | BM32: =-1852-SUM(BJ32:BL32) -> -523 | BN32: =SUM(BJ32:BM32) -> -1852 | BO32: -776 | BP32: -721 | BQ32: -696 | BR32: =-2975-SUM(BO32:BQ32) -> -782 | BS32: =SUM(BO32:BR32) -> -2975 | BT32: -529 | BU32: -728 | BV32: -725 | BW32: =-2673-SUM(BT32:BV32) -> -691 | BX32: =SUM(BT32:BW32) -> -2673 | BY32: -204 | BZ32: -226 | CA32: -219 | CB32: =-865-SUM(BY32:CA32) -> -216 | CC32: =SUM(BY32:CB32) -> -865 | CD32: -212 | CE32: -198 | CF32: =CE32*CF64/CE64 -> -218.36232 | CG32: =CF32*CG64/CF64 -> -218.45556 | CH32: =SUM(CD32:CG32) -> -846.81788 | CI32: =CH32*CI64/CH64 -> -218.54883 | CJ32: =CI32*CJ64/CI64 -> -218.64215 | CK32: =CJ32*CK64/CJ64 -> -218.7355 | CL32: =CK32*CL64/CK64 -> -218.82889 | CM32: =SUM(CI32:CL32) -> -874.75537 | CN32: =CM32*CN64/CM64 -> -218.92233 | CO32: =CN32*CO64/CN64 -> -219.0158 | CP32: =CO32*CP64/CO64 -> -219.10932 | CQ32: =CP32*CQ64/CP64 -> -219.20287 | CR32: =SUM(CN32:CQ32) -> -876.25032 | CS32: =CR32*CS64/CR64 -> -219.29646 | CT32: =CS32*CT64/CS64 -> -219.3901 | CU32: =CT32*CU64/CT64 -> -219.48377 | CV32: =CU32*CV64/CU64 -> -219.57748 | CW32: =SUM(CS32:CV32) -> -877.74782 | CX32: =CW32*CX64/CW64 -> -219.67124 | CY32: =CX32*CY64/CX64 -> -219.76503 | CZ32: =CY32*CZ64/CY64 -> -219.85887 | DA32: =CZ32*DA64/CZ64 -> -219.95274 | DB32: =SUM(CX32:DA32) -> -879.24787
A33: Extraordinary items | F33: =SUM(B33:E33) -> 0 | K33: =SUM(G33:J33) -> 0 | P33: =SUM(L33:O33) -> 0 | U33: =SUM(Q33:T33) -> 0 | Z33: =SUM(V33:Y33) -> 0 | AE33: =SUM(AA33:AD33) -> 0 | AJ33: =SUM(AF33:AI33) -> 0 | AO33: =SUM(AK33:AN33) -> 0 | AT33: =SUM(AP33:AS33) -> 0 | AU33: 0 | AV33: 0 | AW33: 0 | AX33: 0 | AY33: =SUM(AU33:AX33) -> 0 | AZ33: 0 | BA33: 0 | BB33: 0 | BC33: 0 | BD33: =SUM(AZ33:BC33) -> 0 | BE33: 0 | BF33: 0 | BG33: 0 | BH33: 0 | BI33: =SUM(BE33:BH33) -> 0 | BJ33: 0 | BK33: 0 | BL33: 0 | BM33: 0 | BN33: =SUM(BJ33:BM33) -> 0 | BO33: 0 | BP33: 0 | BQ33: 0 | BR33: 0 | BS33: =SUM(BO33:BR33) -> 0 | BT33: 0 | BU33: 0 | BV33: 0 | BW33: 0 | BX33: =SUM(BT33:BW33) -> 0 | BY33: 0 | BZ33: 0 | CA33: 0 | CB33: 0 | CC33: =SUM(BY33:CB33) -> 0 | CD33: 0 | CE33: 0 | CF33: 0 | CG33: 0 | CH33: =SUM(CD33:CG33) -> 0 | CI33: 0 | CJ33: 0 | CK33: 0 | CL33: 0 | CM33: =SUM(CI33:CL33) -> 0 | CN33: 0 | CO33: 0 | CP33: 0 | CQ33: 0 | CR33: =SUM(CN33:CQ33) -> 0 | CS33: 0 | CT33: 0 | CU33: 0 | CV33: 0 | CW33: =SUM(CS33:CV33) -> 0 | CX33: 0 | CY33: 0 | CZ33: 0 | DA33: 0 | DB33: =SUM(CX33:DA33) -> 0
A34: Equity Income | F34: =SUM(B34:E34) -> 0 | K34: =SUM(G34:J34) -> 0 | P34: =SUM(L34:O34) -> 0 | U34: =SUM(Q34:T34) -> 0 | Z34: =SUM(V34:Y34) -> 0 | AE34: =SUM(AA34:AD34) -> 0 | AJ34: =SUM(AF34:AI34) -> 0 | AK34: -5.371 | AL34: -88.245 | AM34: 469.958 | AN34: 665.837 | AO34: =SUM(AK34:AN34) -> 1042.179 | AP34: 350.712 | AQ34: 3178.105 | AR34: -3157.202 | AS34: -869.858 | AT34: =SUM(AP34:AS34) -> -498.243 | AU34: -359 | AV34: -1062 | AW34: 849 | AX34: =1486-SUM(AU34:AW34) -> 2058 | AY34: =SUM(AU34:AX34) -> 1486 | AZ34: 791 | BA34: 195 | BB34: 336 | BC34: =2360-SUM(AZ34:BB34) -> 1038 | BD34: =SUM(AZ34:BC34) -> 2360 | BE34: 1138 | BF34: 1726 | BG34: -946 | BH34: =927-SUM(BE34:BG34) -> -991 | BI34: =SUM(BE34:BH34) -> 927 | BJ34: -311 | BK34: -141 | BL34: 976 | BM34: =379-SUM(BJ34:BL34) -> -145 | BN34: =SUM(BJ34:BM34) -> 379 | BO34: -110 | BP34: 696 | BQ34: -295 | BR34: =1647-SUM(BO34:BQ34) -> 1356 | BS34: =SUM(BO34:BR34) -> 1647 | BT34: 1299 | BU34: 2806 | BV34: 3390 | BW34: =8539-SUM(BT34:BV34) -> 1044 | BX34: =SUM(BT34:BW34) -> 8539 | BY34: 688 | BZ34: 1091 | CA34: 2474 | CB34: =7390-SUM(BY34:CA34) -> 3137 | CC34: =SUM(BY34:CB34) -> 7390 | CD34: 2282 | CE34: 1014 | CF34: ='BS & FCF'!CF21*10%/4 -> 771.25259 | CG34: ='BS & FCF'!CG21*10%/4 -> 779.28351 | CH34: =SUM(CD34:CG34) -> 4846.5361 | CI34: ='BS & FCF'!CI21*10%/4 -> 833.88023 | CJ34: ='BS & FCF'!CJ21*10%/4 -> 874.54796 | CK34: ='BS & FCF'!CK21*10%/4 -> 894.26501 | CL34: ='BS & FCF'!CL21*10%/4 -> 909.47125 | CM34: =SUM(CI34:CL34) -> 3512.1645 | CN34: ='BS & FCF'!CN21*10%/4 -> 957.03623 | CO34: ='BS & FCF'!CO21*10%/4 -> 978.947 | CP34: ='BS & FCF'!CP21*10%/4 -> 981.66976 | CQ34: ='BS & FCF'!CQ21*10%/4 -> 993.91159 | CR34: =SUM(CN34:CQ34) -> 3911.5646 | CS34: ='BS & FCF'!CS21*10%/4 -> 1034.195 | CT34: ='BS & FCF'!CT21*10%/4 -> 1054.87 | CU34: ='BS & FCF'!CU21*10%/4 -> 1055.3506 | CV34: ='BS & FCF'!CV21*10%/4 -> 1060.9874 | CW34: =SUM(CS34:CV34) -> 4205.403 | CX34: ='BS & FCF'!CX21*10%/4 -> 1097.4912 | CY34: ='BS & FCF'!CY21*10%/4 -> 1109.4366 | CZ34: ='BS & FCF'!CZ21*10%/4 -> 1096.52 | DA34: ='BS & FCF'!DA21*10%/4 -> 1086.2048 | DB34: =SUM(CX34:DA34) -> 4389.6526
A35: Operating income | B35: =B16+B17 -> 0 | C35: =C16+C17 -> 0 | D35: =D16+D17 -> 0 | E35: =E16+E17 -> 0 | F35: =SUM(B35:E35) -> 0 | G35: =G16+G17 -> 0 | H35: =H16+H17 -> 0 | I35: =I16+I17 -> 0 | J35: =J16+J17 -> 0 | K35: =SUM(G35:J35) -> 0 | L35: =L16+L17 -> 0 | M35: =M16+M17 -> 0 | N35: =N16+N17 -> 0 | O35: =O16+O17 -> 0 | P35: =SUM(L35:O35) -> 0 | Q35: =Q16+Q17 -> 0 | R35: =R16+R17 -> 0 | S35: =S16+S17 -> 0 | T35: =T16+T17 -> 0 | U35: =SUM(Q35:T35) -> 0 | V35: =V16+V17 -> 0 | W35: =W16+W17 -> 0 | X35: =X16+X17 -> 0 | Y35: =Y16+Y17 -> 0 | Z35: =SUM(V35:Y35) -> 0 | AA35: =AA16+AA17 -> 0 | AB35: =AB16+AB17 -> 0 | AC35: =AC16+AC17 -> 0 | AD35: =AD16+AD17 -> 0 | AE35: =SUM(AA35:AD35) -> 0 | AF35: =AF16+AF17 -> 0 | AG35: =AG16+AG17 -> 0 | AH35: =AH16+AH17 -> 0 | AI35: =AI16+AI17 -> 0 | AJ35: =SUM(AF35:AI35) -> 0 | AK35: =AK16+AK17 -> 16465.068 | AL35: =AL16+AL17 -> 20086.782 | AM35: =AM16+AM17 -> 49874.739 | AN35: =AN16+AN17 -> 56168.82 | AO35: =SUM(AK35:AN35) -> 142595.41 | AP35: =AP16+AP17 -> 23596.92 | AQ35: =AQ16+AQ17 -> 44619.944 | AR35: =AR16+AR17 -> 58830.786 | AS35: =AS16+AS17 -> 67413.999 | AT35: =SUM(AP35:AS35) -> 194461.65 | AU35: =AU16+AU17 -> 28257 | AV35: =AV16+AV17 -> 79268 | AW35: =AW16+AW17 -> 45183 | AX35: =AX16+AX17 -> 73387 | AY35: =SUM(AU35:AX35) -> 226095 | AZ35: =AZ16+AZ17 -> 23155 | BA35: =BA16+BA17 -> 45884 | BB35: =BB16+BB17 -> 66118 | BC35: =BC16+BC17 -> 81055 | BD35: =SUM(AZ35:BC35) -> 216212 | BE35: =BE16+BE17 -> 58947 | BF35: =BF16+BF17 -> 85365 | BG35: =BG16+BG17 -> 84976 | BH35: =BH16+BH17 -> 122353 | BI35: =SUM(BE35:BH35) -> 351641 | BJ35: =BJ16+BJ17 -> 74988 | BK35: =BK16+BK17 -> 107387 | BL35: =BL16+BL17 -> 110405 | BM35: =BM16+BM17 -> 112224 | BN35: =SUM(BJ35:BM35) -> 405004 | BO35: =BO16+BO17 -> 109392 | BP35: =BP16+BP17 -> 142265 | BQ35: =BQ16+BQ17 -> 132019 | BR35: =BR16+BR17 -> 184353 | BS35: =SUM(BO35:BR35) -> 568029 | BT35: =BT16+BT17 -> 174256 | BU35: =BU16+BU17 -> 196190 | BV35: =BV16+BV17 -> 203590 | BW35: =BW16+BW17 -> 214560 | BX35: =SUM(BT35:BW35) -> 788596 | BY35: =BY16+BY17 -> 264667 | BZ35: =BZ16+BZ17 -> 298596 | CA35: =CA16+CA17 -> 319973 | CB35: =CB16+CB17 -> 337010 | CC35: =SUM(BY35:CB35) -> 1220246 | CD35: =CD16+CD17 -> 392436 | CE35: =CE16+CE17 -> 356305 | CF35: =CF16+CF17 -> 391658.25 | CG35: =CG16+CG17 -> 424120.48 | CH35: =SUM(CD35:CG35) -> 1564519.7 | CI35: =CI16+CI17 -> 441745.24 | CJ35: =CJ16+CJ17 -> 481254.47 | CK35: =CK16+CK17 -> 517996.28 | CL35: =CL16+CL17 -> 504784.47 | CM35: =SUM(CI35:CL35) -> 1945780.5 | CN35: =CN16+CN17 -> 544537.62 | CO35: =CO16+CO17 -> 537382.11 | CP35: =CP16+CP17 -> 559820.11 | CQ35: =CQ16+CQ17 -> 561727.85 | CR35: =SUM(CN35:CQ35) -> 2203467.7 | CS35: =CS16+CS17 -> 589577.11 | CT35: =CT16+CT17 -> 572917.04 | CU35: =CU16+CU17 -> 590008.09 | CV35: =CV16+CV17 -> 588635.26 | CW35: =SUM(CS35:CV35) -> 2341137.5 | CX35: =CX16+CX17 -> 625214.97 | CY35: =CY16+CY17 -> 606011.13 | CZ35: =CZ16+CZ17 -> 621725.21 | DA35: =DA16+DA17 -> 618523.38 | DB35: =SUM(CX35:DA35) -> 2471474.7
A36: Non-operating income (expenses) | F36: =SUM(B36:E36) -> 0 | K36: =SUM(G36:J36) -> 0 | P36: =SUM(L36:O36) -> 0 | U36: =SUM(Q36:T36) -> 0 | Z36: =SUM(V36:Y36) -> 0 | AE36: =SUM(AA36:AD36) -> 0 | AJ36: =SUM(AF36:AI36) -> 0 | AK36: 0 | AL36: 0 | AM36: 0 | AN36: 0 | AO36: =SUM(AK36:AN36) -> 0 | AP36: 0 | AQ36: 0 | AR36: 0 | AS36: 0 | AT36: =SUM(AP36:AS36) -> 0 | AU36: 0 | AV36: 0 | AW36: 0 | AX36: 0 | AY36: =SUM(AU36:AX36) -> 0 | AZ36: 0 | BA36: 0 | BB36: 0 | BC36: 0 | BD36: =SUM(AZ36:BC36) -> 0 | BE36: 0 | BF36: 0 | BG36: 0 | BH36: 0 | BI36: =SUM(BE36:BH36) -> 0 | BJ36: 0 | BK36: 0 | BL36: 0 | BM36: 0 | BN36: =SUM(BJ36:BM36) -> 0 | BO36: 0 | BP36: 0 | BQ36: 0 | BR36: 0 | BS36: =SUM(BO36:BR36) -> 0 | BT36: 0 | BU36: 0 | BV36: 0 | BW36: 0 | BX36: =SUM(BT36:BW36) -> 0 | BY36: 0 | BZ36: 0 | CA36: 0 | CB36: 0 | CC36: =SUM(BY36:CB36) -> 0 | CD36: 0 | CE36: 0 | CF36: 0 | CG36: 0 | CH36: =SUM(CD36:CG36) -> 0 | CI36: 0 | CJ36: 0 | CK36: 0 | CL36: 0 | CM36: =SUM(CI36:CL36) -> 0 | CN36: 0 | CO36: 0 | CP36: 0 | CQ36: 0 | CR36: =SUM(CN36:CQ36) -> 0 | CS36: 0 | CT36: 0 | CU36: 0 | CV36: 0 | CW36: =SUM(CS36:CV36) -> 0 | CX36: 0 | CY36: 0 | CZ36: 0 | DA36: 0 | DB36: =SUM(CX36:DA36) -> 0
A37: Income before income tax | B37: =B35+B36 -> 0 | C37: =C35+C36 -> 0 | D37: =D35+D36 -> 0 | E37: =E35+E36 -> 0 | F37: =SUM(B37:E37) -> 0 | G37: =G35+G36 -> 0 | H37: =H35+H36 -> 0 | I37: =I35+I36 -> 0 | J37: =J35+J36 -> 0 | K37: =SUM(G37:J37) -> 0 | L37: =L35+L36 -> 0 | M37: =M35+M36 -> 0 | N37: =N35+N36 -> 0 | O37: =O35+O36 -> 0 | P37: =SUM(L37:O37) -> 0 | Q37: =Q35+Q36 -> 0 | R37: =R35+R36 -> 0 | S37: =S35+S36 -> 0 | T37: =T35+T36 -> 0 | U37: =SUM(Q37:T37) -> 0 | V37: =V35+V36 -> 0 | W37: =W35+W36 -> 0 | X37: =X35+X36 -> 0 | Y37: =Y35+Y36 -> 0 | Z37: =SUM(V37:Y37) -> 0 | AA37: =AA35+AA36 -> 0 | AB37: =AB35+AB36 -> 0 | AC37: =AC35+AC36 -> 0 | AD37: =AD35+AD36 -> 0 | AE37: =SUM(AA37:AD37) -> 0 | AF37: =AF35+AF36 -> 0 | AG37: =AG35+AG36 -> 0 | AH37: =AH35+AH36 -> 0 | AI37: =AI35+AI36 -> 0 | AJ37: =SUM(AF37:AI37) -> 0 | AK37: =AK35+AK36 -> 16465.068 | AL37: =AL35+AL36 -> 20086.782 | AM37: =AM35+AM36 -> 49874.739 | AN37: =AN35+AN36 -> 56168.82 | AO37: =SUM(AK37:AN37) -> 142595.41 | AP37: =AP35+AP36 -> 23596.92 | AQ37: =AQ35+AQ36 -> 44619.944 | AR37: =AR35+AR36 -> 58830.786 | AS37: =AS35+AS36 -> 67413.999 | AT37: =SUM(AP37:AS37) -> 194461.65 | AU37: =AU35+AU36 -> 28257 | AV37: =AV35+AV36 -> 79268 | AW37: =AW35+AW36 -> 45183 | AX37: =AX35+AX36 -> 73387 | AY37: =SUM(AU37:AX37) -> 226095 | AZ37: =AZ35+AZ36 -> 23155 | BA37: =BA35+BA36 -> 45884 | BB37: =BB35+BB36 -> 66118 | BC37: =BC35+BC36 -> 81055 | BD37: =SUM(AZ37:BC37) -> 216212 | BE37: =BE35+BE36 -> 58947 | BF37: =BF35+BF36 -> 85365 | BG37: =BG35+BG36 -> 84976 | BH37: =BH35+BH36 -> 122353 | BI37: =SUM(BE37:BH37) -> 351641 | BJ37: =BJ35+BJ36 -> 74988 | BK37: =BK35+BK36 -> 107387 | BL37: =BL35+BL36 -> 110405 | BM37: =BM35+BM36 -> 112224 | BN37: =SUM(BJ37:BM37) -> 405004 | BO37: =BO35+BO36 -> 109392 | BP37: =BP35+BP36 -> 142265 | BQ37: =BQ35+BQ36 -> 132019 | BR37: =BR35+BR36 -> 184353 | BS37: =SUM(BO37:BR37) -> 568029 | BT37: =BT35+BT36 -> 174256 | BU37: =BU35+BU36 -> 196190 | BV37: =BV35+BV36 -> 203590 | BW37: =BW35+BW36 -> 214560 | BX37: =SUM(BT37:BW37) -> 788596 | BY37: =BY35+BY36 -> 264667 | BZ37: =BZ35+BZ36 -> 298596 | CA37: =CA35+CA36 -> 319973 | CB37: =CB35+CB36 -> 337010 | CC37: =SUM(BY37:CB37) -> 1220246 | CD37: =CD35+CD36 -> 392436 | CE37: =CE35+CE36 -> 356305 | CF37: =CF35+CF36 -> 391658.25 | CG37: =CG35+CG36 -> 424120.48 | CH37: =SUM(CD37:CG37) -> 1564519.7 | CI37: =CI35+CI36 -> 441745.24 | CJ37: =CJ35+CJ36 -> 481254.47 | CK37: =CK35+CK36 -> 517996.28 | CL37: =CL35+CL36 -> 504784.47 | CM37: =SUM(CI37:CL37) -> 1945780.5 | CN37: =CN35+CN36 -> 544537.62 | CO37: =CO35+CO36 -> 537382.11 | CP37: =CP35+CP36 -> 559820.11 | CQ37: =CQ35+CQ36 -> 561727.85 | CR37: =SUM(CN37:CQ37) -> 2203467.7 | CS37: =CS35+CS36 -> 589577.11 | CT37: =CT35+CT36 -> 572917.04 | CU37: =CU35+CU36 -> 590008.09 | CV37: =CV35+CV36 -> 588635.26 | CW37: =SUM(CS37:CV37) -> 2341137.5 | CX37: =CX35+CX36 -> 625214.97 | CY37: =CY35+CY36 -> 606011.13 | CZ37: =CZ35+CZ36 -> 621725.21 | DA37: =DA35+DA36 -> 618523.38 | DB37: =SUM(CX37:DA37) -> 2471474.7
A38: Income tax | F38: =SUM(B38:E38) -> 0 | K38: =SUM(G38:J38) -> 0 | P38: =SUM(L38:O38) -> 0 | U38: =SUM(Q38:T38) -> 0 | Z38: =SUM(V38:Y38) -> 0 | AE38: =SUM(AA38:AD38) -> 0 | AJ38: =SUM(AF38:AI38) -> 0 | AK38: -2531.394 | AL38: -1974.132 | AM38: -3848.193 | AN38: -5466.183 | AO38: =SUM(AK38:AN38) -> -13819.902 | AP38: -2836.992 | AQ38: -4774.862 | AR38: -5401.951 | AS38: -5436.554 | AT38: =SUM(AP38:AS38) -> -18450.359 | AU38: -4567 | AV38: -5053 | AW38: -5661 | AX38: =-21283-SUM(AU38:AW38) -> -6002 | AY38: =SUM(AU38:AX38) -> -21283 | AZ38: -7071 | BA38: -5058 | BB38: -5901 | BC38: =-24650-SUM(AZ38:BB38) -> -6620 | BD38: =SUM(AZ38:BC38) -> -24650 | BE38: -5387 | BF38: -6221 | BG38: -9486 | BH38: =-31893-SUM(BE38:BG38) -> -10799 | BI38: =SUM(BE38:BH38) -> -31893 | BJ38: -9507 | BK38: -12324 | BL38: -13899 | BM38: =-50756-SUM(BJ38:BL38) -> -15026 | BN38: =SUM(BJ38:BM38) -> -50756 | BO38: -13709 | BP38: -15906 | BQ38: -18328 | BR38: =-67835-SUM(BO38:BQ38) -> -19892 | BS38: =SUM(BO38:BR38) -> -67835 | BT38: -17229 | BU38: -19957 | BV38: -21440 | BW38: =-86551-SUM(BT38:BV38) -> -27925 | BX38: =SUM(BT38:BW38) -> -86551 | BY38: -22310 | BZ38: -28545 | CA38: -37023 | CB38: =-127835-SUM(BY38:CA38) -> -39957 | CC38: =SUM(BY38:CB38) -> -127835 | CD38: -37247 | CE38: -42103 | CF38: =-CF39*(CF4+'BS & FCF'!CF96) -> -47760.41 | CG38: =-CG39*(CG4+'BS & FCF'!CG96) -> -47677.754 | CH38: =SUM(CD38:CG38) -> -174788.16 | CI38: =-CI39*(CI4+'BS & FCF'!CI96) -> -47800.436 | CJ38: =-CJ39*(CJ4+'BS & FCF'!CJ96) -> -54202.699 | CK38: =-CK39*(CK4+'BS & FCF'!CK96) -> -55289.111 | CL38: =-CL39*(CL4+'BS & FCF'!CL96) -> -53841.638 | CM38: =SUM(CI38:CL38) -> -211133.88 | CN38: =-CN39*(CN4+'BS & FCF'!CN96) -> -40164.308 | CO38: =-CO39*(CO4+'BS & FCF'!CO96) -> -44226.788 | CP38: =-CP39*(CP4+'BS & FCF'!CP96) -> -44686.365 | CQ38: =-CQ39*(CQ4+'BS & FCF'!CQ96) -> -43175.702 | CR38: =SUM(CN38:CQ38) -> -172253.16 | CS38: =-CS39*(CS4+'BS & FCF'!CS96) -> -44943.212 | CT38: =-CT39*(CT4+'BS & FCF'!CT96) -> -48109.85 | CU38: =-CU39*(CU4+'BS & FCF'!CU96) -> -48367.133 | CV38: =-CV39*(CV4+'BS & FCF'!CV96) -> -47101.297 | CW38: =SUM(CS38:CV38) -> -188521.49 | CX38: =-CX39*(CX4+'BS & FCF'!CX96) -> -48580.156 | CY38: =-CY39*(CY4+'BS & FCF'!CY96) -> -51588.538 | CZ38: =-CZ39*(CZ4+'BS & FCF'!CZ96) -> -51632.56 | DA38: =-DA39*(DA4+'BS & FCF'!DA96) -> -50136.104 | DB38: =SUM(CX38:DA38) -> -201937.36
A39: Cash tax rate (% of collection) | B39: =-B38/(B4+'BS & FCF'!B96) -> #VALUE! | C39: =-C38/(C4+'BS & FCF'!C96) -> #DIV/0! | D39: =-D38/(D4+'BS & FCF'!D96) -> #DIV/0! | E39: =-E38/(E4+'BS & FCF'!E96) -> #DIV/0! | F39: =-F38/(F4+'BS & FCF'!F96) -> #VALUE! | G39: =-G38/(G4+'BS & FCF'!G96) -> #DIV/0! | H39: =-H38/(H4+'BS & FCF'!H96) -> #DIV/0! | I39: =-I38/(I4+'BS & FCF'!I96) -> #DIV/0! | ... CE39: =-CE38/(CE4+'BS & FCF'!CE96) -> 0.02711435 | CF39: =CE39 -> 0.02711435 | CG39: =CF39 -> 0.02711435 | CH39: =-CH38/(CH4+'BS & FCF'!CH96) -> 0.027631563 | CI39: =CG39 -> 0.02711435 | CJ39: =CI39 -> 0.02711435 | CK39: =CJ39 -> 0.02711435 | CL39: =CK39 -> 0.02711435 | CM39: =-CM38/(CM4+'BS & FCF'!CM96) -> 0.02711435 | CN39: 0.0192 | CO39: 0.0192 | CP39: 0.0192 | CQ39: 0.0192 | CR39: =-CR38/(CR4+'BS & FCF'!CR96) -> 0.0192 | CS39: 0.0192 | CT39: 0.0192 | CU39: 0.0192 | CV39: 0.0192 | CW39: =-CW38/(CW4+'BS & FCF'!CW96) -> 0.0192 | CX39: 0.0192 | CY39: 0.0192 | CZ39: 0.0192 | DA39: 0.0192 | DB39: =-DB38/(DB4+'BS & FCF'!DB96) -> 0.0192
A40: Deffered taxes | F40: =SUM(B40:E40) -> 0 | K40: =SUM(G40:J40) -> 0 | P40: =SUM(L40:O40) -> 0 | U40: =SUM(Q40:T40) -> 0 | Z40: =SUM(V40:Y40) -> 0 | AE40: =SUM(AA40:AD40) -> 0 | AJ40: =SUM(AF40:AI40) -> 0 | AK40: 0 | AL40: 0 | AM40: 0 | AN40: 0 | AO40: =SUM(AK40:AN40) -> 0 | AP40: 0 | AQ40: 0 | AR40: 0 | AS40: 0 | AT40: =SUM(AP40:AS40) -> 0 | AU40: -184 | AV40: -481 | AW40: 782 | AX40: =-756-SUM(AU40:AW40) -> -873 | AY40: =SUM(AU40:AX40) -> -756 | AZ40: -666 | BA40: 186 | BB40: -1002 | BC40: =-1564-SUM(AZ40:BB40) -> -82 | BD40: =SUM(AZ40:BC40) -> -1564 | BE40: -1492 | BF40: -2193 | BG40: -843 | BH40: =-4439-SUM(BE40:BG40) -> 89 | BI40: =SUM(BE40:BH40) -> -4439 | BJ40: -2130 | BK40: -2124 | BL40: -1635 | BM40: =-5808-SUM(BJ40:BL40) -> 81 | BN40: =SUM(BJ40:BM40) -> -5808 | BO40: -1627 | BP40: -2289 | BQ40: -800 | BR40: =-4583-SUM(BO40:BQ40) -> 133 | BS40: =SUM(BO40:BR40) -> -4583 | BT40: -2957 | BU40: -951 | BV40: -1562 | BW40: =-3233-SUM(BT40:BV40) -> 2237 | BX40: =SUM(BT40:BW40) -> -3233 | BY40: -8693 | BZ40: -2894 | CA40: 260 | CB40: =-11191-SUM(BY40:CA40) -> 136 | CC40: =SUM(BY40:CB40) -> -11191 | CD40: -4003 | CE40: -3011 | CF40: =-CF41*CF9-CF38 -> 1030.3648 | CG40: =-CG41*CG9-CG38 -> 179.58623 | CH40: =SUM(CD40:CG40) -> -5804.049 | CI40: =-CI41*CI9-CI38 -> -2435.5613 | CJ40: =-CJ41*CJ9-CJ38 -> -2963.4916 | CK40: =-CK41*CK9-CK38 -> -2530.0492 | CL40: =-CL41*CL9-CL38 -> -1084.9154 | CM40: =SUM(CI40:CL40) -> -9014.0174 | CN40: =-CN41*CN9-CN38 -> -1369.2894 | CO40: =-CO41*CO9-CO38 -> -586.67509 | CP40: =-CP41*CP9-CP38 -> -563.41191 | CQ40: =-CQ41*CQ9-CQ38 -> -1011.6367 | CR40: =SUM(CN40:CQ40) -> -3531.0131 | CS40: =-CS41*CS9-CS38 -> -778.69188 | CT40: =-CT41*CT9-CT38 -> -588.82435 | CU40: =-CU41*CU9-CU38 -> -455.80871 | CV40: =-CV41*CV9-CV38 -> -359.53949 | CW40: =SUM(CS40:CV40) -> -2182.8644 | CX40: =-CX41*CX9-CX38 -> -268.91082 | CY40: =-CY41*CY9-CY38 -> -184.89824 | CZ40: =-CZ41*CZ9-CZ38 -> -127.78848 | DA40: =-DA41*DA9-DA38 -> -87.442931 | DB40: =SUM(CX40:DA40) -> -669.04048
A41: Tax rate (% of revenues) | B41: =-(B38+B40)/B9 -> #DIV/0! | C41: =-(C38+C40)/C9 -> #DIV/0! | D41: =-(D38+D40)/D9 -> #DIV/0! | E41: =-(E38+E40)/E9 -> #DIV/0! | F41: =-(F38+F40)/F9 -> #DIV/0! | G41: =-(G38+G40)/G9 -> #DIV/0! | H41: =-(H38+H40)/H9 -> #DIV/0! | I41: =-(I38+I40)/I9 -> #DIV/0! | ... CE41: =-(CE38+CE40)/CE9 -> 0.026685295 | CF41: =CE41 -> 0.026685295 | CG41: =CF41 -> 0.026685295 | CH41: =-(CH38+CH40)/CH9 -> 0.02642456 | CI41: =CG41 -> 0.026685295 | CJ41: =CI41 -> 0.026685295 | CK41: =CJ41 -> 0.026685295 | CL41: =CK41 -> 0.026685295 | CM41: =-(CM38+CM40)/CM9 -> 0.026685295 | CN41: 0.0192 | CO41: 0.0192 | CP41: 0.0192 | CQ41: 0.0192 | CR41: =-(CR38+CR40)/CR9 -> 0.0192 | CS41: 0.0192 | CT41: 0.0192 | CU41: 0.0192 | CV41: 0.0192 | CW41: =-(CW38+CW40)/CW9 -> 0.0192 | CX41: 0.0192 | CY41: 0.0192 | CZ41: 0.0192 | DA41: 0.0192 | DB41: =-(DB38+DB40)/DB9 -> 0.0192
A42: Majority income | B42: =B37+B38+B40 -> 0 | C42: =C37+C38+C40 -> 0 | D42: =D37+D38+D40 -> 0 | E42: =E37+E38+E40 -> 0 | F42: =SUM(B42:E42) -> 0 | G42: =G37+G38+G40 -> 0 | H42: =H37+H38+H40 -> 0 | I42: =I37+I38+I40 -> 0 | J42: =J37+J38+J40 -> 0 | K42: =SUM(G42:J42) -> 0 | L42: =L37+L38+L40 -> 0 | M42: =M37+M38+M40 -> 0 | N42: =N37+N38+N40 -> 0 | O42: =O37+O38+O40 -> 0 | P42: =SUM(L42:O42) -> 0 | Q42: =Q37+Q38+Q40 -> 0 | R42: =R37+R38+R40 -> 0 | S42: =S37+S38+S40 -> 0 | T42: =T37+T38+T40 -> 0 | U42: =SUM(Q42:T42) -> 0 | V42: =V37+V38+V40 -> 0 | W42: =W37+W38+W40 -> 0 | X42: =X37+X38+X40 -> 0 | Y42: =Y37+Y38+Y40 -> 0 | Z42: =SUM(V42:Y42) -> 0 | AA42: =AA37+AA38+AA40 -> 0 | AB42: =AB37+AB38+AB40 -> 0 | AC42: =AC37+AC38+AC40 -> 0 | AD42: =AD37+AD38+AD40 -> 0 | AE42: =SUM(AA42:AD42) -> 0 | AF42: =AF37+AF38+AF40 -> 0 | AG42: =AG37+AG38+AG40 -> 0 | AH42: =AH37+AH38+AH40 -> 0 | AI42: =AI37+AI38+AI40 -> 0 | AJ42: =SUM(AF42:AI42) -> 0 | AK42: =AK37+AK38+AK40 -> 13933.674 | AL42: =AL37+AL38+AL40 -> 18112.65 | AM42: =AM37+AM38+AM40 -> 46026.546 | AN42: =AN37+AN38+AN40 -> 50702.637 | AO42: =SUM(AK42:AN42) -> 128775.51 | AP42: =AP37+AP38+AP40 -> 20759.928 | AQ42: =AQ37+AQ38+AQ40 -> 39845.082 | AR42: =AR37+AR38+AR40 -> 53428.835 | AS42: =AS37+AS38+AS40 -> 61977.445 | AT42: =SUM(AP42:AS42) -> 176011.29 | AU42: =AU37+AU38+AU40 -> 23506 | AV42: =AV37+AV38+AV40 -> 73734 | AW42: =AW37+AW38+AW40 -> 40304 | AX42: =AX37+AX38+AX40 -> 66512 | AY42: =SUM(AU42:AX42) -> 204056 | AZ42: =AZ37+AZ38+AZ40 -> 15418 | BA42: =BA37+BA38+BA40 -> 41012 | BB42: =BB37+BB38+BB40 -> 59215 | BC42: =BC37+BC38+BC40 -> 74353 | BD42: =SUM(AZ42:BC42) -> 189998 | BE42: =BE37+BE38+BE40 -> 52068 | BF42: =BF37+BF38+BF40 -> 76951 | BG42: =BG37+BG38+BG40 -> 74647 | BH42: =BH37+BH38+BH40 -> 111643 | BI42: =SUM(BE42:BH42) -> 315309 | BJ42: =BJ37+BJ38+BJ40 -> 63351 | BK42: =BK37+BK38+BK40 -> 92939 | BL42: =BL37+BL38+BL40 -> 94871 | BM42: =BM37+BM38+BM40 -> 97279 | BN42: =SUM(BJ42:BM42) -> 348440 | BO42: =BO37+BO38+BO40 -> 94056 | BP42: =BP37+BP38+BP40 -> 124070 | BQ42: =BQ37+BQ38+BQ40 -> 112891 | BR42: =BR37+BR38+BR40 -> 164594 | BS42: =SUM(BO42:BR42) -> 495611 | BT42: =BT37+BT38+BT40 -> 154070 | BU42: =BU37+BU38+BU40 -> 175282 | BV42: =BV37+BV38+BV40 -> 180588 | BW42: =BW37+BW38+BW40 -> 188872 | BX42: =SUM(BT42:BW42) -> 698812 | BY42: =BY37+BY38+BY40 -> 233664 | BZ42: =BZ37+BZ38+BZ40 -> 267157 | CA42: =CA37+CA38+CA40 -> 283210 | CB42: =CB37+CB38+CB40 -> 297189 | CC42: =SUM(BY42:CB42) -> 1081220 | CD42: =CD37+CD38+CD40 -> 351186 | CE42: =CE37+CE38+CE40 -> 311191 | CF42: =CF37+CF38+CF40 -> 344928.2 | CG42: =CG37+CG38+CG40 -> 376622.32 | CH42: =SUM(CD42:CG42) -> 1383927.5 | CI42: =CI37+CI38+CI40 -> 391509.24 | CJ42: =CJ37+CJ38+CJ40 -> 424088.28 | CK42: =CK37+CK38+CK40 -> 460177.12 | CL42: =CL37+CL38+CL40 -> 449857.92 | CM42: =SUM(CI42:CL42) -> 1725632.6 | CN42: =CN37+CN38+CN40 -> 503004.02 | CO42: =CO37+CO38+CO40 -> 492568.65 | CP42: =CP37+CP38+CP40 -> 514570.33 | CQ42: =CQ37+CQ38+CQ40 -> 517540.51 | CR42: =SUM(CN42:CQ42) -> 2027683.5 | CS42: =CS37+CS38+CS40 -> 543855.21 | CT42: =CT37+CT38+CT40 -> 524218.36 | CU42: =CU37+CU38+CU40 -> 541185.15 | CV42: =CV37+CV38+CV40 -> 541174.42 | CW42: =SUM(CS42:CV42) -> 2150433.1 | CX42: =CX37+CX38+CX40 -> 576365.9 | CY42: =CY37+CY38+CY40 -> 554237.69 | CZ42: =CZ37+CZ38+CZ40 -> 569964.86 | DA42: =DA37+DA38+DA40 -> 568299.84 | DB42: =SUM(CX42:DA42) -> 2268868.3
A43: Minority interest | F43: =SUM(B43:E43) -> 0 | K43: =SUM(G43:J43) -> 0 | P43: =SUM(L43:O43) -> 0 | U43: =SUM(Q43:T43) -> 0 | Z43: =SUM(V43:Y43) -> 0 | AE43: =SUM(AA43:AD43) -> 0 | AJ43: =SUM(AF43:AI43) -> 0 | AK43: -1288.908 | AL43: 1501 | AM43: -12400 | AN43: -3753.424 | AO43: =SUM(AK43:AN43) -> -15941.332 | AP43: -652.35 | AQ43: -8289.829 | AR43: -17211.594 | AS43: -18858.055 | AT43: =SUM(AP43:AS43) -> -45011.828 | AU43: -5130 | AV43: -12661 | AW43: -9996 | AX43: =-43928-SUM(AU43:AW43) -> -16141 | AY43: =SUM(AU43:AX43) -> -43928 | AZ43: -8918 | BA43: -4023 | BB43: -9861 | BC43: =-29186-SUM(AZ43:BB43) -> -6384 | BD43: =SUM(AZ43:BC43) -> -29186 | BE43: -2075 | BF43: 1652 | BG43: -7242 | BH43: =-15560-SUM(BE43:BG43) -> -7895 | BI43: =SUM(BE43:BH43) -> -15560 | BJ43: -1448 | BK43: -6614 | BL43: -4999 | BM43: =-18555-SUM(BJ43:BL43) -> -5494 | BN43: =SUM(BJ43:BM43) -> -18555 | BO43: -2207 | BP43: -2697 | BQ43: -4671 | BR43: =-13846-SUM(BO43:BQ43) -> -4271 | BS43: =SUM(BO43:BR43) -> -13846 | BT43: -12829 | BU43: -3035 | BV43: -10017 | BW43: =-48969-SUM(BT43:BV43) -> -23088 | BX43: =SUM(BT43:BW43) -> -48969 | BY43: -20189 | BZ43: -30426 | CA43: -27957 | CB43: =-105684-SUM(BY43:CA43) -> -27112 | CC43: =SUM(BY43:CB43) -> -105684 | CD43: -48319 | CE43: -40740 | CF43: =-40%/4*'BS & FCF'!CE42 -> -39381.7 | CG43: =-40%/4*'BS & FCF'!CF42 -> -39871.666 | CH43: =SUM(CD43:CG43) -> -168312.37 | CI43: =-45%/4*'BS & FCF'!CH42 -> -45322.697 | CJ43: =-45%/4*'BS & FCF'!CI42 -> -48498.013 | CK43: =-45%/4*'BS & FCF'!CJ42 -> -50863.226 | CL43: =-45%/4*'BS & FCF'!CK42 -> -52009.958 | CM43: =SUM(CI43:CL43) -> -196693.89 | CN43: =-45%/4*'BS & FCF'!CM42 -> -52894.345 | CO43: =-45%/4*'BS & FCF'!CN42 -> -55660.697 | CP43: =-45%/4*'BS & FCF'!CO42 -> -56935.016 | CQ43: =-45%/4*'BS & FCF'!CP42 -> -57093.37 | CR43: =SUM(CN43:CQ43) -> -222583.43 | CS43: =-45%/4*'BS & FCF'!CR42 -> -57805.348 | CT43: =-45%/4*'BS & FCF'!CS42 -> -60148.211 | CU43: =-45%/4*'BS & FCF'!CT42 -> -61350.656 | CV43: =-45%/4*'BS & FCF'!CU42 -> -61378.608 | CW43: =SUM(CS43:CV43) -> -240682.82 | CX43: =-45%/4*'BS & FCF'!CW42 -> -61706.438 | CY43: =-45%/4*'BS & FCF'!CX42 -> -63829.482 | CZ43: =-45%/4*'BS & FCF'!CY42 -> -64524.218 | DA43: =-45%/4*'BS & FCF'!CZ42 -> -63772.996 | DB43: =SUM(CX43:DA43) -> -253833.13
A44: % of majority income | B44: =-B43/B42 -> #DIV/0! | C44: =-C43/C42 -> #DIV/0! | D44: =-D43/D42 -> #DIV/0! | E44: =-E43/E42 -> #DIV/0! | F44: =-F43/F42 -> #DIV/0! | G44: =-G43/G42 -> #DIV/0! | H44: =-H43/H42 -> #DIV/0! | I44: =-I43/I42 -> #DIV/0! | ... DB44: =-DB43/DB42 -> 0.11187654
A45: Net income | B45: =B42+B43 -> 0 | C45: =C42+C43 -> 0 | D45: =D42+D43 -> 0 | E45: =E42+E43 -> 0 | F45: =SUM(B45:E45) -> 0 | G45: =G42+G43 -> 0 | H45: =H42+H43 -> 0 | I45: =I42+I43 -> 0 | J45: =J42+J43 -> 0 | K45: =SUM(G45:J45) -> 0 | L45: =L42+L43 -> 0 | M45: =M42+M43 -> 0 | N45: =N42+N43 -> 0 | O45: =O42+O43 -> 0 | P45: =SUM(L45:O45) -> 0 | Q45: =Q42+Q43 -> 0 | R45: =R42+R43 -> 0 | S45: =S42+S43 -> 0 | T45: =T42+T43 -> 0 | U45: =SUM(Q45:T45) -> 0 | V45: =V42+V43 -> 0 | W45: =W42+W43 -> 0 | X45: =X42+X43 -> 0 | Y45: =Y42+Y43 -> 0 | Z45: =SUM(V45:Y45) -> 0 | AA45: =AA42+AA43 -> 0 | AB45: =AB42+AB43 -> 0 | AC45: =AC42+AC43 -> 0 | AD45: =AD42+AD43 -> 0 | AE45: =SUM(AA45:AD45) -> 0 | AF45: =AF42+AF43 -> 0 | AG45: =AG42+AG43 -> 0 | AH45: =AH42+AH43 -> 0 | AI45: =AI42+AI43 -> 0 | AJ45: =SUM(AF45:AI45) -> 0 | AK45: =AK42+AK43 -> 12644.766 | AL45: =AL42+AL43 -> 19613.65 | AM45: =AM42+AM43 -> 33626.546 | AN45: =AN42+AN43 -> 46949.213 | AO45: =SUM(AK45:AN45) -> 112834.18 | AP45: =AP42+AP43 -> 20107.578 | AQ45: =AQ42+AQ43 -> 31555.253 | AR45: =AR42+AR43 -> 36217.241 | AS45: =AS42+AS43 -> 43119.39 | AT45: =SUM(AP45:AS45) -> 130999.46 | AU45: =AU42+AU43 -> 18376 | AV45: =AV42+AV43 -> 61073 | AW45: =AW42+AW43 -> 30308 | AX45: =AX42+AX43 -> 50371 | AY45: =SUM(AU45:AX45) -> 160128 | AZ45: =AZ42+AZ43 -> 6500 | BA45: =BA42+BA43 -> 36989 | BB45: =BB42+BB43 -> 49354 | BC45: =BC42+BC43 -> 67969 | BD45: =SUM(AZ45:BC45) -> 160812 | BE45: =BE42+BE43 -> 49993 | BF45: =BF42+BF43 -> 78603 | BG45: =BG42+BG43 -> 67405 | BH45: =BH42+BH43 -> 103748 | BI45: =SUM(BE45:BH45) -> 299749 | BJ45: =BJ42+BJ43 -> 61903 | BK45: =BK42+BK43 -> 86325 | BL45: =BL42+BL43 -> 89872 | BM45: =BM42+BM43 -> 91785 | BN45: =SUM(BJ45:BM45) -> 329885 | BO45: =BO42+BO43 -> 91849 | BP45: =BP42+BP43 -> 121373 | BQ45: =BQ42+BQ43 -> 108220 | BR45: =BR42+BR43 -> 160323 | BS45: =SUM(BO45:BR45) -> 481765 | BT45: =BT42+BT43 -> 141241 | BU45: =BU42+BU43 -> 172247 | BV45: =BV42+BV43 -> 170571 | BW45: =BW42+BW43 -> 165784 | BX45: =SUM(BT45:BW45) -> 649843 | BY45: =BY42+BY43 -> 213475 | BZ45: =BZ42+BZ43 -> 236731 | CA45: =CA42+CA43 -> 255253 | CB45: =CB42+CB43 -> 270077 | CC45: =SUM(BY45:CB45) -> 975536 | CD45: =CD42+CD43 -> 302867 | CE45: =CE42+CE43 -> 270451 | CF45: =CF42+CF43 -> 305546.5 | CG45: =CG42+CG43 -> 336750.65 | CH45: =SUM(CD45:CG45) -> 1215615.2 | CI45: =CI42+CI43 -> 346186.54 | CJ45: =CJ42+CJ43 -> 375590.27 | CK45: =CK42+CK43 -> 409313.89 | CL45: =CL42+CL43 -> 397847.96 | CM45: =SUM(CI45:CL45) -> 1528938.7 | CN45: =CN42+CN43 -> 450109.67 | CO45: =CO42+CO43 -> 436907.95 | CP45: =CP42+CP43 -> 457635.31 | CQ45: =CQ42+CQ43 -> 460447.14 | CR45: =SUM(CN45:CQ45) -> 1805100.1 | CS45: =CS42+CS43 -> 486049.86 | CT45: =CT42+CT43 -> 464070.15 | CU45: =CU42+CU43 -> 479834.5 | CV45: =CV42+CV43 -> 479795.82 | CW45: =SUM(CS45:CV45) -> 1909750.3 | CX45: =CX42+CX43 -> 514659.47 | CY45: =CY42+CY43 -> 490408.21 | CZ45: =CZ42+CZ43 -> 505440.64 | DA45: =DA42+DA43 -> 504526.84 | DB45: =SUM(CX45:DA45) -> 2015035.2
A47: Per share (R$) | B47: =Macro!B$3 -> 1Q10 | C47: =Macro!C$3 -> 2Q10 | D47: =Macro!D$3 -> 3Q10 | E47: =Macro!E$3 -> 4Q10 | F47: =Macro!F$3 -> 2010 | G47: =Macro!G$3 -> 1Q11 | H47: =Macro!H$3 -> 2Q11 | I47: =Macro!I$3 -> 3Q11 | ... DB47: =Macro!DB$3 -> 2030E
A48: Shares outstanding (ex-treasury, 000') | F48: =E48 -> 0 | K48: =J48 -> 0 | P48: =O48 -> 0 | U48: =T48 -> 0 | Z48: =Y48 -> 0 | AE48: =AD48 -> 0 | AJ48: =AI48 -> 0 | AK48: 273693.27 | AL48: =AK48 -> 273693.27 | AM48: =AL48 -> 273693.27 | AN48: 273693.27 | AO48: =AN48 -> 273693.27 | AP48: 273693.27 | AQ48: =AP48 -> 273693.27 | AR48: =AQ48 -> 273693.27 | AS48: 273693.27 | AT48: =AS48 -> 273693.27 | AU48: 273693.27 | AV48: =AU48 -> 273693.27 | AW48: =AV48 -> 273693.27 | AX48: 273693.27 | AY48: =AX48 -> 273693.27 | AZ48: 273693.27 | BA48: 273693.27 | BB48: 291875.09 | BC48: 291875.09 | BD48: =BC48 -> 291875.09 | BE48: 291875.09 | BF48: 291875.09 | BG48: 291875.09 | BH48: =291785.088-18.6 -> 291766.49 | BI48: =BH48 -> 291766.49 | BJ48: 291875.09 | BK48: =291875.088-1990.8 -> 289884.29 | BL48: =291875.088-1990.8 -> 289884.29 | BM48: =291875.088-1990.8 -> 289884.29 | BN48: =BM48 -> 289884.29 | BO48: =291875.088-1990.8 -> 289884.29 | BP48: =291875.088-1990.8 -> 289884.29 | BQ48: =291875.088-1990.8 -> 289884.29 | BR48: =291875.088-1990.8 -> 289884.29 | BS48: =BR48 -> 289884.29 | BT48: =291875.088-1990.8 -> 289884.29 | BU48: =291875.088-1990.8 -> 289884.29 | BV48: =291875.088-1990.8 -> 289884.29 | BW48: =291875.088-1990.8 -> 289884.29 | BX48: =BW48 -> 289884.29 | BY48: =291875.088-1990.8 -> 289884.29 | BZ48: =291875.088 -> 291875.09 | CA48: =291875.088 -> 291875.09 | CB48: =308047.594-0 -> 308047.59 | CC48: =CB48 -> 308047.59 | CD48: =308047.594-0 -> 308047.59 | CE48: =308047.594-0 -> 308047.59 | CF48: =CE48+CF49+CF50 -> 308047.59 | CG48: =CF48+CG49+CG50 -> 308047.59 | CH48: =CG48 -> 308047.59 | CI48: =CH48+CI49+CI50 -> 308047.59 | CJ48: =CI48+CJ49+CJ50 -> 308047.59 | CK48: =CJ48+CK49+CK50 -> 308047.59 | CL48: =CK48+CL49+CL50 -> 308047.59 | CM48: =CL48 -> 308047.59 | CN48: =CM48+CN49+CN50 -> 308047.59 | CO48: =CN48+CO49+CO50 -> 308047.59 | CP48: =CO48+CP49+CP50 -> 308047.59 | CQ48: =CP48+CQ49+CQ50 -> 308047.59 | CR48: =CQ48 -> 308047.59 | CS48: =CR48+CS49+CS50 -> 308047.59 | CT48: =CS48+CT49+CT50 -> 308047.59 | CU48: =CT48+CU49+CU50 -> 308047.59 | CV48: =CU48+CV49+CV50 -> 308047.59 | CW48: =CV48 -> 308047.59 | CX48: =CW48+CX49+CX50 -> 308047.59 | CY48: =CX48+CY49+CY50 -> 308047.59 | CZ48: =CY48+CZ49+CZ50 -> 308047.59 | DA48: =CZ48+DA49+DA50 -> 308047.59 | DB48: =DA48 -> 308047.59
A49: Equity issuance | F49: =SUM(B49:E49) -> 0 | K49: =SUM(G49:J49) -> 0 | P49: =SUM(L49:O49) -> 0 | U49: =SUM(Q49:T49) -> 0 | Z49: =SUM(V49:Y49) -> 0 | AE49: =SUM(AA49:AD49) -> 0 | AJ49: =SUM(AF49:AI49) -> 0 | AK49: 0 | AL49: 0 | AM49: 0 | AN49: 0 | AO49: =SUM(AK49:AN49) -> 0 | AP49: 0 | AQ49: 0 | AR49: 0 | AS49: 0 | AT49: =SUM(AP49:AS49) -> 0 | AU49: 0 | AV49: 0 | AW49: 0 | AX49: 0 | AY49: =SUM(AU49:AX49) -> 0 | AZ49: 0 | BA49: 0 | BB49: =BB48-BA48 -> 18181.818 | BC49: 0 | BD49: =SUM(AZ49:BC49) -> 18181.818 | BE49: 0 | BF49: 0 | BG49: 0 | BH49: 0 | BI49: =SUM(BE49:BH49) -> 0 | BJ49: 0 | BK49: 0 | BL49: 0 | BM49: 0 | BN49: =SUM(BJ49:BM49) -> 0 | BO49: 0 | BP49: 0 | BQ49: 0 | BR49: 0 | BS49: =SUM(BO49:BR49) -> 0 | BT49: 0 | BU49: 0 | BV49: 0 | BW49: 0 | BX49: =SUM(BT49:BW49) -> 0 | BY49: 0 | BZ49: 0 | CA49: 0 | CB49: 0 | CC49: =SUM(BY49:CB49) -> 0 | CD49: 0 | CE49: 0 | CF49: =('BS & FCF'!CF44-'BS & FCF'!CE44)/Valuation!$B$6 -> 0 | CG49: =('BS & FCF'!CG44-'BS & FCF'!CF44)/Valuation!$B$6 -> 0 | CH49: =SUM(CD49:CG49) -> 0 | CI49: =('BS & FCF'!CI44-'BS & FCF'!CG44)/Valuation!$B$6 -> 0 | CJ49: =('BS & FCF'!CJ44-'BS & FCF'!CI44)/Valuation!$B$6 -> 0 | CK49: =('BS & FCF'!CK44-'BS & FCF'!CJ44)/Valuation!$B$6 -> 0 | CL49: =('BS & FCF'!CL44-'BS & FCF'!CK44)/Valuation!$B$6 -> 0 | CM49: =SUM(CI49:CL49) -> 0 | CN49: =('BS & FCF'!CN44-'BS & FCF'!CL44)/Valuation!$B$6 -> 0 | CO49: =('BS & FCF'!CO44-'BS & FCF'!CN44)/Valuation!$B$6 -> 0 | CP49: =('BS & FCF'!CP44-'BS & FCF'!CO44)/Valuation!$B$6 -> 0 | CQ49: =('BS & FCF'!CQ44-'BS & FCF'!CP44)/Valuation!$B$6 -> 0 | CR49: =SUM(CN49:CQ49) -> 0 | CS49: =('BS & FCF'!CS44-'BS & FCF'!CQ44)/Valuation!$B$6 -> 0 | CT49: =('BS & FCF'!CT44-'BS & FCF'!CS44)/Valuation!$B$6 -> 0 | CU49: =('BS & FCF'!CU44-'BS & FCF'!CT44)/Valuation!$B$6 -> 0 | CV49: =('BS & FCF'!CV44-'BS & FCF'!CU44)/Valuation!$B$6 -> 0 | CW49: =SUM(CS49:CV49) -> 0 | CX49: =('BS & FCF'!CX44-'BS & FCF'!CV44)/Valuation!$B$6 -> 0 | CY49: =('BS & FCF'!CY44-'BS & FCF'!CX44)/Valuation!$B$6 -> 0 | CZ49: =('BS & FCF'!CZ44-'BS & FCF'!CY44)/Valuation!$B$6 -> 0 | DA49: =('BS & FCF'!DA44-'BS & FCF'!CZ44)/Valuation!$B$6 -> 0 | DB49: =SUM(CX49:DA49) -> 0
A50: Share repurchase | B50: =B48-#REF!-B49 -> #REF! | C50: =C48-B48-C49 -> 0 | D50: =D48-C48-D49 -> 0 | E50: =E48-D48-E49 -> 0 | F50: =SUM(B50:E50) -> #REF! | G50: =G48-E48-G49 -> 0 | H50: =H48-G48-H49 -> 0 | I50: =I48-H48-I49 -> 0 | J50: =J48-I48-J49 -> 0 | K50: =SUM(G50:J50) -> 0 | L50: =L48-J48-L49 -> 0 | M50: =M48-L48-M49 -> 0 | N50: =N48-M48-N49 -> 0 | O50: =O48-N48-O49 -> 0 | P50: =SUM(L50:O50) -> 0 | Q50: =Q48-O48-Q49 -> 0 | R50: =R48-Q48-R49 -> 0 | S50: =S48-R48-S49 -> 0 | T50: =T48-S48-T49 -> 0 | U50: =SUM(Q50:T50) -> 0 | V50: =V48-T48-V49 -> 0 | W50: =W48-V48-W49 -> 0 | X50: =X48-W48-X49 -> 0 | Y50: =Y48-X48-Y49 -> 0 | Z50: =SUM(V50:Y50) -> 0 | AA50: =AA48-Y48-AA49 -> 0 | AB50: =AB48-AA48-AB49 -> 0 | AC50: =AC48-AB48-AC49 -> 0 | AD50: =AD48-AC48-AD49 -> 0 | AE50: =SUM(AA50:AD50) -> 0 | AF50: =AF48-AD48-AF49 -> 0 | AG50: =AG48-AF48-AG49 -> 0 | AH50: =AH48-AG48-AH49 -> 0 | AI50: =AI48-AH48-AI49 -> 0 | AJ50: =SUM(AF50:AI50) -> 0 | AK50: =AK48-AI48-AK49 -> 273693.27 | AL50: =AL48-AK48-AL49 -> 0 | AM50: =AM48-AL48-AM49 -> 0 | AN50: =AN48-AM48-AN49 -> 0 | AO50: =SUM(AK50:AN50) -> 273693.27 | AP50: =AP48-AN48-AP49 -> 0 | AQ50: =AQ48-AP48-AQ49 -> 0 | AR50: =AR48-AQ48-AR49 -> 0 | AS50: =AS48-AR48-AS49 -> 0 | AT50: =SUM(AP50:AS50) -> 0 | AU50: =AU48-AS48-AU49 -> 0 | AV50: =AV48-AU48-AV49 -> 0 | AW50: =AW48-AV48-AW49 -> 0 | AX50: =AX48-AW48-AX49 -> 0 | AY50: =SUM(AU50:AX50) -> 0 | AZ50: =AZ48-AX48-AZ49 -> 0 | BA50: =BA48-AZ48-BA49 -> 0 | BB50: =BB48-BA48-BB49 -> 0 | BC50: =BC48-BB48-BC49 -> 0 | BD50: =SUM(AZ50:BC50) -> 0 | BE50: =BE48-BC48-BE49 -> 0 | BF50: =BF48-BE48-BF49 -> 0 | BG50: =BG48-BF48-BG49 -> 0 | BH50: =BH48-BG48-BH49 -> -108.6 | BI50: =SUM(BE50:BH50) -> -108.6 | BJ50: =BJ48-BH48-BJ49 -> 108.6 | BK50: =BK48-BJ48-BK49 -> -1990.8 | BL50: =BL48-BK48-BL49 -> 0 | BM50: =BM48-BL48-BM49 -> 0 | BN50: =SUM(BJ50:BM50) -> -1882.2 | BO50: =BO48-BM48-BO49 -> 0 | BP50: =BP48-BO48-BP49 -> 0 | BQ50: =BQ48-BP48-BQ49 -> 0 | BR50: =BR48-BQ48-BR49 -> 0 | BS50: =SUM(BO50:BR50) -> 0 | BT50: =BT48-BR48-BT49 -> 0 | BU50: =BU48-BT48-BU49 -> 0 | BV50: =BV48-BU48-BV49 -> 0 | BW50: =BW48-BV48-BW49 -> 0 | BX50: =SUM(BT50:BW50) -> 0 | BY50: =BY48-BW48-BY49 -> 0 | BZ50: =BZ48-BY48-BZ49 -> 1990.8 | CA50: =CA48-BZ48-CA49 -> 0 | CB50: =CB48-CA48-CB49 -> 16172.506 | CC50: =SUM(BY50:CB50) -> 18163.306 | CD50: =CD48-CB48-CD49 -> 0 | CE50: =CE48-CD48-CE49 -> 0 | CF50: 0 | CG50: 0 | CH50: =SUM(CD50:CG50) -> 0 | CI50: 0 | CJ50: 0 | CK50: 0 | CL50: 0 | CM50: =SUM(CI50:CL50) -> 0 | CN50: 0 | CO50: 0 | CP50: 0 | CQ50: 0 | CR50: =SUM(CN50:CQ50) -> 0 | CS50: 0 | CT50: 0 | CU50: 0 | CV50: 0 | CW50: =SUM(CS50:CV50) -> 0 | CX50: 0 | CY50: 0 | CZ50: 0 | DA50: 0 | DB50: =SUM(CX50:DA50) -> 0
A51: EPS | B51: =B73/AVERAGE(#REF!,B48) -> #REF! | C51: =C73/AVERAGE(B48,C48) -> #DIV/0! | D51: =D73/AVERAGE(C48,D48) -> #DIV/0! | E51: =E73/AVERAGE(D48,E48) -> #DIV/0! | F51: =F73/AVERAGE(B48:E48) -> #DIV/0! | G51: =G73/AVERAGE(E48,G48) -> #DIV/0! | H51: =H73/AVERAGE(G48,H48) -> #DIV/0! | I51: =I73/AVERAGE(H48,I48) -> #DIV/0! | J51: =J73/AVERAGE(I48,J48) -> #DIV/0! | K51: =K73/AVERAGE(G48:J48) -> #DIV/0! | L51: =L73/AVERAGE(J48,L48) -> #DIV/0! | M51: =M73/AVERAGE(L48,M48) -> #DIV/0! | N51: =N73/AVERAGE(M48,N48) -> #DIV/0! | O51: =O73/AVERAGE(N48,O48) -> #DIV/0! | P51: =P73/AVERAGE(L48:O48) -> #DIV/0! | Q51: =Q73/AVERAGE(O48,Q48) -> #DIV/0! | R51: =R73/AVERAGE(Q48,R48) -> #DIV/0! | S51: =S73/AVERAGE(R48,S48) -> #DIV/0! | T51: =T73/AVERAGE(S48,T48) -> #DIV/0! | U51: =U73/AVERAGE(Q48:T48) -> #DIV/0! | V51: =V73/AVERAGE(T48,V48) -> #DIV/0! | W51: =W73/AVERAGE(V48,W48) -> #DIV/0! | X51: =X73/AVERAGE(W48,X48) -> #DIV/0! | Y51: =Y73/AVERAGE(X48,Y48) -> #DIV/0! | Z51: =Z73/AVERAGE(V48:Y48) -> #DIV/0! | AA51: =AA73/AVERAGE(Y48,AA48) -> #DIV/0! | AB51: =AB73/AVERAGE(AA48,AB48) -> #DIV/0! | AC51: =AC73/AVERAGE(AB48,AC48) -> #DIV/0! | AD51: =AD73/AVERAGE(AC48,AD48) -> #DIV/0! | AE51: =AE73/AVERAGE(AA48:AD48) -> #DIV/0! | AF51: =AF73/AVERAGE(AD48,AF48) -> #DIV/0! | AG51: =AG73/AVERAGE(AF48,AG48) -> #DIV/0! | AH51: =AH73/AVERAGE(AG48,AH48) -> #DIV/0! | AI51: =AI73/AVERAGE(AH48,AI48) -> #DIV/0! | AJ51: =AJ73/AVERAGE(AF48:AI48) -> #DIV/0! | AK51: =AK73/AVERAGE(AI48,AK48) -> 0.0462005 | AL51: =AL73/AVERAGE(AK48,AL48) -> 0.071662887 | AM51: =AM73/AVERAGE(AL48,AM48) -> 0.12286216 | AN51: =AN73/AVERAGE(AM48,AN48) -> 0.17153952 | AO51: =AO73/AVERAGE(AK48:AN48) -> 0.41226507 | AP51: =AP73/AVERAGE(AN48,AP48) -> 0.073467565 | AQ51: =AQ73/AVERAGE(AP48,AQ48) -> 0.11529422 | AR51: =AR73/AVERAGE(AQ48,AR48) -> 0.13232785 | AS51: =AS73/AVERAGE(AR48,AS48) -> 0.1575464 | AT51: =AT73/AVERAGE(AP48:AS48) -> 0.47863604 | AU51: =AU73/AVERAGE(AS48,AU48) -> 0.067140854 | AV51: =AV73/AVERAGE(AU48,AV48) -> 0.22314396 | AW51: =AW73/AVERAGE(AV48,AW48) -> 0.1107371 | AX51: =AX73/AVERAGE(AW48,AX48) -> 0.18404179 | AY51: =AY73/AVERAGE(AU48:AX48) -> 0.58506371 | AZ51: =AZ73/AVERAGE(AX48,AZ48) -> 0.023749214 | BA51: =BA73/AVERAGE(AZ48,BA48) -> 0.13514764 | BB51: =BB73/AVERAGE(BA48,BB48) -> 0.17452886 | BC51: =BC73/AVERAGE(BB48,BC48) -> 0.23287017 | BD51: =BD73/AVERAGE(AZ48:BC48) -> 0.56867396 | BE51: =BE73/AVERAGE(BC48,BE48) -> 0.17128218 | BF51: =BF73/AVERAGE(BD48,BF48) -> 0.26930356 | BG51: =BG73/AVERAGE(BE48,BG48) -> 0.23093783 | BH51: =BH73/AVERAGE(BG48,BH48) -> 0.35551957 | BI51: =BI73/AVERAGE(BE48:BH48) -> 1.0270725 | BJ51: =BJ73/AVERAGE(BH48,BJ48) -> 0.21212677 | BK51: =BK73/AVERAGE(BI48,BK48) -> 0.29682759 | BL51: =BL73/AVERAGE(BJ48,BL48) -> 0.30896623 | BM51: =BM73/AVERAGE(BL48,BM48) -> 0.31662634 | BN51: =BN73/AVERAGE(BJ48:BM48) -> 1.1360381 | BO51: =BO73/AVERAGE(BM48,BO48) -> 0.31684711 | BP51: =BP73/AVERAGE(BN48,BP48) -> 0.41869465 | BQ51: =BQ73/AVERAGE(BP48,BQ48) -> 0.37332137 | BR51: =BR73/AVERAGE(BQ48,BR48) -> 0.55305861 | BS51: =BS73/AVERAGE(BO48:BR48) -> 1.6619217 | BT51: =BT73/AVERAGE(BR48,BT48) -> 0.48723234 | BU51: =BU73/AVERAGE(BT48,BU48) -> 0.59419226 | BV51: =BV73/AVERAGE(BU48,BV48) -> 0.58841064 | BW51: =BW73/AVERAGE(BV48,BW48) -> 0.57189716 | BX51: =BX73/AVERAGE(BT48:BW48) -> 2.2417324 | BY51: =BY73/AVERAGE(BW48,BY48) -> 0.73641452 | BZ51: =BZ73/AVERAGE(BY48,BZ48) -> 0.81384507 | CA51: =CA73/AVERAGE(BZ48,CA48) -> 0.87452822 | CB51: =CB73/AVERAGE(CA48,CB48) -> 0.90037269 | CC51: =CC73/AVERAGE(BY48:CB48) -> 3.3021945 | CD51: =CD73/AVERAGE(CB48,CD48) -> 0.98318249 | CE51: =CE73/AVERAGE(CD48,CE48) -> 0.877952 | CF51: =CF73/AVERAGE(CE48,CF48) -> 0.99188082 | CG51: =CG73/AVERAGE(CF48,CG48) -> 1.0931773 | CH51: =CH73/AVERAGE(CD48:CG48) -> 3.9461926 | CI51: =CI73/AVERAGE(CG48,CI48) -> 1.1238086 | CJ51: =CJ73/AVERAGE(CI48,CJ48) -> 1.2192605 | CK51: =CK73/AVERAGE(CJ48,CK48) -> 1.3287359 | CL51: =CL73/AVERAGE(CK48,CL48) -> 1.2915146 | CM51: =CM73/AVERAGE(CI48:CL48) -> 4.9633196 | CN51: =CN73/AVERAGE(CL48,CN48) -> 1.4611693 | CO51: =CO73/AVERAGE(CN48,CO48) -> 1.4183132 | CP51: =CP73/AVERAGE(CO48,CP48) -> 1.4855994 | CQ51: =CQ73/AVERAGE(CP48,CQ48) -> 1.4947273 | CR51: =CR73/AVERAGE(CN48:CQ48) -> 5.8598091 | CS51: =CS73/AVERAGE(CQ48,CS48) -> 1.5778401 | CT51: =CT73/AVERAGE(CS48,CT48) -> 1.5064885 | CU51: =CU73/AVERAGE(CT48,CU48) -> 1.5576635 | CV51: =CV73/AVERAGE(CU48,CV48) -> 1.5575379 | CW51: =CW73/AVERAGE(CS48:CV48) -> 6.1995301 | CX51: =CX73/AVERAGE(CV48,CX48) -> 1.6707141 | CY51: =CY73/AVERAGE(CX48,CY48) -> 1.5919885 | CZ51: =CZ73/AVERAGE(CY48,CZ48) -> 1.6407875 | DA51: =DA73/AVERAGE(CZ48,DA48) -> 1.6378211 | DB51: =DB73/AVERAGE(CX48:DA48) -> 6.5413111
A52: Adj. EPS | B52: =B74/AVERAGE(#REF!,B48) -> #REF! | C52: =C74/AVERAGE(B48,C48) -> #DIV/0! | D52: =D74/AVERAGE(C48,D48) -> #DIV/0! | E52: =E74/AVERAGE(D48,E48) -> #DIV/0! | F52: =F74/AVERAGE(B48:E48) -> #DIV/0! | G52: =G74/AVERAGE(E48,G48) -> #DIV/0! | H52: =H74/AVERAGE(G48,H48) -> #DIV/0! | I52: =I74/AVERAGE(H48,I48) -> #DIV/0! | J52: =J74/AVERAGE(I48,J48) -> #DIV/0! | K52: =K74/AVERAGE(G48:J48) -> #DIV/0! | L52: =L74/AVERAGE(J48,L48) -> #DIV/0! | M52: =M74/AVERAGE(L48,M48) -> #DIV/0! | N52: =N74/AVERAGE(M48,N48) -> #DIV/0! | O52: =O74/AVERAGE(N48,O48) -> #DIV/0! | P52: =P74/AVERAGE(L48:O48) -> #DIV/0! | Q52: =Q74/AVERAGE(O48,Q48) -> #DIV/0! | R52: =R74/AVERAGE(Q48,R48) -> #DIV/0! | S52: =S74/AVERAGE(R48,S48) -> #DIV/0! | T52: =T74/AVERAGE(S48,T48) -> #DIV/0! | U52: =U74/AVERAGE(Q48:T48) -> #DIV/0! | V52: =V74/AVERAGE(T48,V48) -> #DIV/0! | W52: =W74/AVERAGE(V48,W48) -> #DIV/0! | X52: =X74/AVERAGE(W48,X48) -> #DIV/0! | Y52: =Y74/AVERAGE(X48,Y48) -> #DIV/0! | Z52: =Z74/AVERAGE(V48:Y48) -> #DIV/0! | AA52: =AA74/AVERAGE(Y48,AA48) -> #DIV/0! | AB52: =AB74/AVERAGE(AA48,AB48) -> #DIV/0! | AC52: =AC74/AVERAGE(AB48,AC48) -> #DIV/0! | AD52: =AD74/AVERAGE(AC48,AD48) -> #DIV/0! | AE52: =AE74/AVERAGE(AA48:AD48) -> #DIV/0! | AF52: =AF74/AVERAGE(AD48,AF48) -> #DIV/0! | AG52: =AG74/AVERAGE(AF48,AG48) -> #DIV/0! | AH52: =AH74/AVERAGE(AG48,AH48) -> #DIV/0! | AI52: =AI74/AVERAGE(AH48,AI48) -> #DIV/0! | AJ52: =AJ74/AVERAGE(AF48:AI48) -> #DIV/0! | AK52: =AK74/AVERAGE(AI48,AK48) -> 0.0462005 | AL52: =AL74/AVERAGE(AK48,AL48) -> 0.071662887 | AM52: =AM74/AVERAGE(AL48,AM48) -> 0.12286216 | AN52: =AN74/AVERAGE(AM48,AN48) -> 0.17153952 | AO52: =AO74/AVERAGE(AK48:AN48) -> 0.41226507 | AP52: =AP74/AVERAGE(AN48,AP48) -> 0.073467565 | AQ52: =AQ74/AVERAGE(AP48,AQ48) -> 0.11529422 | AR52: =AR74/AVERAGE(AQ48,AR48) -> 0.13232785 | AS52: =AS74/AVERAGE(AR48,AS48) -> 0.1575464 | AT52: =AT74/AVERAGE(AP48:AS48) -> 0.47863604 | AU52: =AU74/AVERAGE(AS48,AU48) -> 0.067140854 | AV52: =AV74/AVERAGE(AU48,AV48) -> 0.22314396 | AW52: =AW74/AVERAGE(AV48,AW48) -> 0.1107371 | AX52: =AX74/AVERAGE(AW48,AX48) -> 0.18404179 | AY52: =AY74/AVERAGE(AU48:AX48) -> 0.58506371 | AZ52: =AZ74/AVERAGE(AX48,AZ48) -> 0.023749214 | BA52: =BA74/AVERAGE(AZ48,BA48) -> 0.13514764 | BB52: =BB74/AVERAGE(BA48,BB48) -> 0.17452886 | BC52: =BC74/AVERAGE(BB48,BC48) -> 0.23287017 | BD52: =BD74/AVERAGE(AZ48:BC48) -> 0.56867396 | BE52: =BE74/AVERAGE(BC48,BE48) -> 0.17128218 | BF52: =BF74/AVERAGE(BD48,BF48) -> 0.26930356 | BG52: =BG74/AVERAGE(BE48,BG48) -> 0.23093783 | BH52: =BH74/AVERAGE(BG48,BH48) -> 0.35551957 | BI52: =BI74/AVERAGE(BE48:BH48) -> 1.0270725 | BJ52: =BJ74/AVERAGE(BH48,BJ48) -> 0.21212677 | BK52: =BK74/AVERAGE(BI48,BK48) -> 0.29682759 | BL52: =BL74/AVERAGE(BJ48,BL48) -> 0.30896623 | BM52: =BM74/AVERAGE(BL48,BM48) -> 0.31662634 | BN52: =BN74/AVERAGE(BJ48:BM48) -> 1.1360381 | BO52: =BO74/AVERAGE(BM48,BO48) -> 0.31684711 | BP52: =BP74/AVERAGE(BN48,BP48) -> 0.41869465 | BQ52: =BQ74/AVERAGE(BP48,BQ48) -> 0.37332137 | BR52: =BR74/AVERAGE(BQ48,BR48) -> 0.55305861 | BS52: =BS74/AVERAGE(BO48:BR48) -> 1.6619217 | BT52: =BT74/AVERAGE(BR48,BT48) -> 0.48723234 | BU52: =BU74/AVERAGE(BT48,BU48) -> 0.59419226 | BV52: =BV74/AVERAGE(BU48,BV48) -> 0.58841064 | BW52: =BW74/AVERAGE(BV48,BW48) -> 0.57189716 | BX52: =BX74/AVERAGE(BT48:BW48) -> 2.2417324 | BY52: =BY74/AVERAGE(BW48,BY48) -> 0.73641452 | BZ52: =BZ74/AVERAGE(BY48,BZ48) -> 0.81384507 | CA52: =CA74/AVERAGE(BZ48,CA48) -> 0.87452822 | CB52: =CB74/AVERAGE(CA48,CB48) -> 0.90037269 | CC52: =CC74/AVERAGE(BY48:CB48) -> 3.3021945 | CD52: =CD74/AVERAGE(CB48,CD48) -> 0.98318249 | CE52: =CE74/AVERAGE(CD48,CE48) -> 0.877952 | CF52: =CF74/AVERAGE(CE48,CF48) -> 0.99188082 | CG52: =CG74/AVERAGE(CF48,CG48) -> 1.0931773 | CH52: =CH74/AVERAGE(CD48:CG48) -> 3.9461926 | CI52: =CI74/AVERAGE(CG48,CI48) -> 1.1238086 | CJ52: =CJ74/AVERAGE(CI48,CJ48) -> 1.2192605 | CK52: =CK74/AVERAGE(CJ48,CK48) -> 1.3287359 | CL52: =CL74/AVERAGE(CK48,CL48) -> 1.2915146 | CM52: =CM74/AVERAGE(CI48:CL48) -> 4.9633196 | CN52: =CN74/AVERAGE(CL48,CN48) -> 1.4611693 | CO52: =CO74/AVERAGE(CN48,CO48) -> 1.4183132 | CP52: =CP74/AVERAGE(CO48,CP48) -> 1.4855994 | CQ52: =CQ74/AVERAGE(CP48,CQ48) -> 1.4947273 | CR52: =CR74/AVERAGE(CN48:CQ48) -> 5.8598091 | CS52: =CS74/AVERAGE(CQ48,CS48) -> 1.5778401 | CT52: =CT74/AVERAGE(CS48,CT48) -> 1.5064885 | CU52: =CU74/AVERAGE(CT48,CU48) -> 1.5576635 | CV52: =CV74/AVERAGE(CU48,CV48) -> 1.5575379 | CW52: =CW74/AVERAGE(CS48:CV48) -> 6.1995301 | CX52: =CX74/AVERAGE(CV48,CX48) -> 1.6707141 | CY52: =CY74/AVERAGE(CX48,CY48) -> 1.5919885 | CZ52: =CZ74/AVERAGE(CY48,CZ48) -> 1.6407875 | DA52: =DA74/AVERAGE(CZ48,DA48) -> 1.6378211 | DB52: =DB74/AVERAGE(CX48:DA48) -> 6.5413111
A53: DPS | B53: =B55/AVERAGE(#REF!,B48) -> #REF! | C53: =C55/AVERAGE(B48,C48) -> #DIV/0! | D53: =D55/AVERAGE(C48,D48) -> #DIV/0! | E53: =E55/AVERAGE(D48,E48) -> #DIV/0! | F53: =F55/AVERAGE(B48:E48) -> #DIV/0! | G53: =G55/AVERAGE(E48,G48) -> #DIV/0! | H53: =H55/AVERAGE(G48,H48) -> #DIV/0! | I53: =I55/AVERAGE(H48,I48) -> #DIV/0! | J53: =J55/AVERAGE(I48,J48) -> #DIV/0! | K53: =K55/AVERAGE(G48:J48) -> #DIV/0! | L53: =L55/AVERAGE(J48,L48) -> #DIV/0! | M53: =M55/AVERAGE(L48,M48) -> #DIV/0! | N53: =N55/AVERAGE(M48,N48) -> #DIV/0! | O53: =O55/AVERAGE(N48,O48) -> #DIV/0! | P53: =P55/AVERAGE(L48:O48) -> #DIV/0! | Q53: =Q55/AVERAGE(O48,Q48) -> #DIV/0! | R53: =R55/AVERAGE(Q48,R48) -> #DIV/0! | S53: =S55/AVERAGE(R48,S48) -> #DIV/0! | T53: =T55/AVERAGE(S48,T48) -> #DIV/0! | U53: =U55/AVERAGE(Q48:T48) -> #DIV/0! | V53: =V55/AVERAGE(T48,V48) -> #DIV/0! | W53: =W55/AVERAGE(V48,W48) -> #DIV/0! | X53: =X55/AVERAGE(W48,X48) -> #DIV/0! | Y53: =Y55/AVERAGE(X48,Y48) -> #DIV/0! | Z53: =Z55/AVERAGE(V48:Y48) -> #DIV/0! | AA53: =AA55/AVERAGE(Y48,AA48) -> #DIV/0! | AB53: =AB55/AVERAGE(AA48,AB48) -> #DIV/0! | AC53: =AC55/AVERAGE(AB48,AC48) -> #DIV/0! | AD53: =AD55/AVERAGE(AC48,AD48) -> #DIV/0! | AE53: =AE55/AVERAGE(AA48:AD48) -> #DIV/0! | AF53: =AF55/AVERAGE(AD48,AF48) -> #DIV/0! | AG53: =AG55/AVERAGE(AF48,AG48) -> #DIV/0! | AH53: =AH55/AVERAGE(AG48,AH48) -> #DIV/0! | AI53: =AI55/AVERAGE(AH48,AI48) -> #DIV/0! | AJ53: =AJ55/AVERAGE(AF48:AI48) -> #DIV/0! | AK53: =AK55/AVERAGE(AI48,AK48) -> 0 | AL53: =AL55/AVERAGE(AK48,AL48) -> 0 | AM53: =AM55/AVERAGE(AL48,AM48) -> 0 | AN53: =AN55/AVERAGE(AM48,AN48) -> 0 | AO53: =AO55/AVERAGE(AK48:AN48) -> 0 | AP53: =AP55/AVERAGE(AN48,AP48) -> 0 | AQ53: =AQ55/AVERAGE(AP48,AQ48) -> 0 | AR53: =AR55/AVERAGE(AQ48,AR48) -> 0 | AS53: =AS55/AVERAGE(AR48,AS48) -> 0 | AT53: =AT55/AVERAGE(AP48:AS48) -> 0 | AU53: =AU55/AVERAGE(AS48,AU48) -> 0 | AV53: =AV55/AVERAGE(AU48,AV48) -> 0 | AW53: =AW55/AVERAGE(AV48,AW48) -> 0 | AX53: =AX55/AVERAGE(AW48,AX48) -> 0.48959918 | AY53: =AY55/AVERAGE(AU48:AX48) -> 0.48959918 | AZ53: =AZ55/AVERAGE(AX48,AZ48) -> 0 | BA53: =BA55/AVERAGE(AZ48,BA48) -> 0 | BB53: =BB55/AVERAGE(BA48,BB48) -> 0 | BC53: =BC55/AVERAGE(BB48,BC48) -> 0.13085392 | BD53: =BD55/AVERAGE(AZ48:BC48) -> 0.1350606 | BE53: =BE55/AVERAGE(BC48,BE48) -> 0 | BF53: =BF55/AVERAGE(BD48,BF48) -> 0 | BG53: =BG55/AVERAGE(BE48,BG48) -> 0.39400416 | BH53: =BH55/AVERAGE(BG48,BH48) -> 0.17133803 | BI53: =BI55/AVERAGE(BE48:BH48) -> 0.56536291 | BJ53: =BJ55/AVERAGE(BH48,BJ48) -> 0 | BK53: =BK55/AVERAGE(BI48,BK48) -> 0.5157734 | BL53: =BL55/AVERAGE(BJ48,BL48) -> 0 | BM53: =BM55/AVERAGE(BL48,BM48) -> 0 | BN53: =BN55/AVERAGE(BJ48:BM48) -> 0.51656097 | BO53: =BO55/AVERAGE(BM48,BO48) -> 0.20697914 | BP53: =BP55/AVERAGE(BN48,BP48) -> 0.063128637 | BQ53: =BQ55/AVERAGE(BP48,BQ48) -> 0.51744784 | BR53: =BR55/AVERAGE(BQ48,BR48) -> 0.34496523 | BS53: =BS55/AVERAGE(BO48:BR48) -> 1.1325208 | BT53: =BT55/AVERAGE(BR48,BT48) -> 0 | BU53: =BU55/AVERAGE(BT48,BU48) -> 0.4087838 | BV53: =BV55/AVERAGE(BU48,BV48) -> 0.91415786 | BW53: =BW55/AVERAGE(BV48,BW48) -> 0.34496523 | BX53: =BX55/AVERAGE(BT48:BW48) -> 1.6679069 | BY53: =BY55/AVERAGE(BW48,BY48) -> 0.60368915 | BZ53: =BZ55/AVERAGE(BY48,BZ48) -> 0.52942851 | CA53: =CA55/AVERAGE(BZ48,CA48) -> 0.68522463 | CB53: =CB55/AVERAGE(CA48,CB48) -> 2.7436869 | CC53: =CC55/AVERAGE(BY48:CB48) -> 4.5765271 | CD53: =CD55/AVERAGE(CB48,CD48) -> 0.45447523 | CE53: =CE55/AVERAGE(CD48,CE48) -> 0.51940026 | CF53: =CF55/AVERAGE(CE48,CF48) -> 0.61678781 | CG53: =CG55/AVERAGE(CF48,CG48) -> 0.69431657 | CH53: =CH55/AVERAGE(CD48:CG48) -> 2.2849799 | CI53: =CI55/AVERAGE(CG48,CI48) -> 0.81988301 | CJ53: =CJ55/AVERAGE(CI48,CJ48) -> 0.84285647 | CK53: =CK55/AVERAGE(CJ48,CK48) -> 0.91444539 | CL53: =CL55/AVERAGE(CK48,CL48) -> 0.99655192 | CM53: =CM55/AVERAGE(CI48:CL48) -> 3.5737368 | CN53: =CN55/AVERAGE(CL48,CN48) -> 1.1623631 | CO53: =CO55/AVERAGE(CN48,CO48) -> 1.3150523 | CP53: =CP55/AVERAGE(CO48,CP48) -> 1.2764818 | CQ53: =CQ55/AVERAGE(CP48,CQ48) -> 1.3370394 | CR53: =CR55/AVERAGE(CN48:CQ48) -> 5.0909367 | CS53: =CS55/AVERAGE(CQ48,CS48) -> 1.3452545 | CT53: =CT55/AVERAGE(CS48,CT48) -> 1.4200561 | CU53: =CU55/AVERAGE(CT48,CU48) -> 1.3558396 | CV53: =CV55/AVERAGE(CU48,CV48) -> 1.4018972 | CW53: =CW55/AVERAGE(CS48:CV48) -> 5.5230475 | CX53: =CX55/AVERAGE(CV48,CX48) -> 1.4017841 | CY53: =CY55/AVERAGE(CX48,CY48) -> 1.5036427 | CZ53: =CZ55/AVERAGE(CY48,CZ48) -> 1.4327896 | DA53: =DA55/AVERAGE(CZ48,DA48) -> 1.4767088 | DB53: =DB55/AVERAGE(CX48:DA48) -> 5.8149252
A54: Dividends (R$000')
A55: Declared dividends | F55: =SUM(B55:E55) -> 0 | K55: =SUM(G55:J55) -> 0 | P55: =SUM(L55:O55) -> 0 | U55: =SUM(Q55:T55) -> 0 | Z55: =SUM(V55:Y55) -> 0 | AE55: =SUM(AA55:AD55) -> 0 | AJ55: =SUM(AF55:AI55) -> 0 | AK55: 0 | AL55: 0 | AM55: 0 | AN55: 0 | AO55: =SUM(AK55:AN55) -> 0 | AP55: 0 | AQ55: 0 | AR55: 0 | AS55: 0 | AT55: =SUM(AP55:AS55) -> 0 | AU55: 0 | AV55: 0 | AW55: 0 | AX55: 134000 | AY55: =SUM(AU55:AX55) -> 134000 | AZ55: 0 | BA55: 0 | BB55: 0 | BC55: 38193 | BD55: =SUM(AZ55:BC55) -> 38193 | BE55: 0 | BF55: 0 | BG55: 115000 | BH55: 50000 | BI55: =SUM(BE55:BH55) -> 165000 | BJ55: 0 | BK55: 150000 | BL55: 0 | BM55: 0 | BN55: =SUM(BJ55:BM55) -> 150000 | BO55: 60000 | BP55: 18300 | BQ55: 150000 | BR55: 100000 | BS55: =SUM(BO55:BR55) -> 328300 | BT55: 0 | BU55: 118500 | BV55: 265000 | BW55: 100000 | BX55: =SUM(BT55:BW55) -> 483500 | BY55: 175000 | BZ55: 154000 | CA55: 200000 | CB55: =573000+250000 -> 823000 | CC55: =SUM(BY55:CB55) -> 1352000 | CD55: 140000 | CE55: 160000 | CF55: 190000 | CG55: =CF45*70% -> 213882.55 | CH55: =SUM(CD55:CG55) -> 703882.55 | CI55: =CG45*75% -> 252562.99 | CJ55: =CI45*75% -> 259639.91 | CK55: =CJ45*75% -> 281692.7 | CL55: =CK45*75% -> 306985.42 | CM55: =SUM(CI55:CL55) -> 1100881 | CN55: =CL45*90% -> 358063.16 | CO55: =CN45*90% -> 405098.71 | CP55: =CO45*90% -> 393217.16 | CQ55: =CP45*90% -> 411871.78 | CR55: =SUM(CN55:CQ55) -> 1568250.8 | CS55: =CQ45*90% -> 414402.43 | CT55: =CS45*90% -> 437444.87 | CU55: =CT45*90% -> 417663.14 | CV55: =CU45*90% -> 431851.05 | CW55: =SUM(CS55:CV55) -> 1701361.5 | CX55: =CV45*90% -> 431816.23 | CY55: =CX45*90% -> 463193.52 | CZ55: =CY45*90% -> 441367.39 | DA55: =CZ45*90% -> 454896.58 | DB55: =SUM(CX55:DA55) -> 1791273.7
A56: Payout (%) | B56: =B55/B45 -> #DIV/0! | C56: =C55/C45 -> #DIV/0! | D56: =D55/D45 -> #DIV/0! | E56: =E55/E45 -> #DIV/0! | F56: =F55/F45 -> #DIV/0! | G56: =G55/G45 -> #DIV/0! | H56: =H55/H45 -> #DIV/0! | I56: =I55/I45 -> #DIV/0! | ... DB56: =DB55/DB45 -> 0.88895408
A58: Income statement summary | B58: =Macro!B$3 -> 1Q10 | C58: =Macro!C$3 -> 2Q10 | D58: =Macro!D$3 -> 3Q10 | E58: =Macro!E$3 -> 4Q10 | F58: =Macro!F$3 -> 2010 | G58: =Macro!G$3 -> 1Q11 | H58: =Macro!H$3 -> 2Q11 | I58: =Macro!I$3 -> 3Q11 | ... DB58: =Macro!DB$3 -> 2030E
A59: (=) Net revenues | B59: =B9 -> 0 | C59: =C9 -> 0 | D59: =D9 -> 0 | E59: =E9 -> 0 | F59: =F9 -> 0 | G59: =G9 -> 0 | H59: =H9 -> 0 | I59: =I9 -> 0 | ... DB59: =DB9 -> 10552417
A60: (-) COGS (ex-interest) | B60: =B11+B14 -> 0 | C60: =C11+C14 -> 0 | D60: =D11+D14 -> 0 | E60: =E11+E14 -> 0 | F60: =F11+F14 -> 0 | G60: =G11+G14 -> 0 | H60: =H11+H14 -> 0 | I60: =I11+I14 -> 0 | ... DB60: =DB11+DB14 -> -6578622.2
A61: (=) Adjusted gross profit | B61: =B59+B60 -> 0 | C61: =C59+C60 -> 0 | D61: =D59+D60 -> 0 | E61: =E59+E60 -> 0 | F61: =F59+F60 -> 0 | G61: =G59+G60 -> 0 | H61: =H59+H60 -> 0 | I61: =I59+I60 -> 0 | ... DB61: =DB59+DB60 -> 3973794.4
A62: (-) Operating expenses | B62: =B18+B21+B31+B32 -> 0 | C62: =C18+C21+C31+C32 -> 0 | D62: =D18+D21+D31+D32 -> 0 | E62: =E18+E21+E31+E32 -> 0 | F62: =F18+F21+F31+F32 -> 0 | G62: =G18+G21+G31+G32 -> 0 | H62: =H18+H21+H31+H32 -> 0 | I62: =I18+I21+I31+I32 -> 0 | ... DB62: =DB18+DB21+DB31+DB32 -> -1516113.4
A63: (=) EBIT | B63: =B61+B62 -> 0 | C63: =C61+C62 -> 0 | D63: =D61+D62 -> 0 | E63: =E61+E62 -> 0 | F63: =F61+F62 -> 0 | G63: =G61+G62 -> 0 | H63: =H61+H62 -> 0 | I63: =I61+I62 -> 0 | ... DB63: =DB61+DB62 -> 2457681
A64: (+) D&A | F64: =SUM(B64:E64) -> 0 | K64: =SUM(G64:J64) -> 0 | P64: =SUM(L64:O64) -> 0 | U64: =SUM(Q64:T64) -> 0 | Z64: =SUM(V64:Y64) -> 0 | AE64: =SUM(AA64:AD64) -> 0 | AJ64: =SUM(AF64:AI64) -> 0 | AO64: =SUM(AK64:AN64) -> 0 | AT64: =SUM(AP64:AS64) -> 0 | AU64: =-AU32 -> 1854 | AV64: =-AV32 -> 179 | AW64: =-AW32 -> 399 | AX64: =-AX32 -> -1277 | AY64: =SUM(AU64:AX64) -> 1155 | AZ64: =-AZ32 -> 2925 | BA64: =-BA32 -> 307 | BB64: =-BB32 -> 365 | BC64: =-BC32 -> -2038 | BD64: =SUM(AZ64:BC64) -> 1559 | BE64: =-BE32 -> 335 | BF64: =-BF32 -> 355 | BG64: =-BG32 -> 365 | BH64: =-BH32 -> 383 | BI64: =SUM(BE64:BH64) -> 1438 | BJ64: =-BJ32 -> 454 | BK64: =-BK32 -> 459 | BL64: =-BL32 -> 416 | BM64: =-BM32 -> 523 | BN64: =SUM(BJ64:BM64) -> 1852 | BO64: =-BO32 -> 776 | BP64: =-BP32 -> 721 | BQ64: =-BQ32 -> 696 | BR64: =-BR32 -> 782 | BS64: =SUM(BO64:BR64) -> 2975 | BT64: =-BT32 -> 529 | BU64: =-BU32 -> 728 | BV64: =-BV32 -> 725 | BW64: =-BW32 -> 691 | BX64: =SUM(BT64:BW64) -> 2673 | BY64: =-BY32 -> 204 | BZ64: =-BZ32 -> 226 | CA64: =-CA32 -> 219 | CB64: =-CB32 -> 216 | CC64: =SUM(BY64:CB64) -> 865 | CD64: =-CD32 -> 212 | CE64: =-CE32 -> 198 | CF64: ='BS & FCF'!CF121 -> 218.36232 | CG64: ='BS & FCF'!CG121 -> 218.45556 | CH64: =SUM(CD64:CG64) -> 846.81788 | CI64: ='BS & FCF'!CI121 -> 218.54883 | CJ64: ='BS & FCF'!CJ121 -> 218.64215 | CK64: ='BS & FCF'!CK121 -> 218.7355 | CL64: ='BS & FCF'!CL121 -> 218.82889 | CM64: =SUM(CI64:CL64) -> 874.75537 | CN64: ='BS & FCF'!CN121 -> 218.92233 | CO64: ='BS & FCF'!CO121 -> 219.0158 | CP64: ='BS & FCF'!CP121 -> 219.10932 | CQ64: ='BS & FCF'!CQ121 -> 219.20287 | CR64: =SUM(CN64:CQ64) -> 876.25032 | CS64: ='BS & FCF'!CS121 -> 219.29646 | CT64: ='BS & FCF'!CT121 -> 219.3901 | CU64: ='BS & FCF'!CU121 -> 219.48377 | CV64: ='BS & FCF'!CV121 -> 219.57748 | CW64: =SUM(CS64:CV64) -> 877.74782 | CX64: ='BS & FCF'!CX121 -> 219.67124 | CY64: ='BS & FCF'!CY121 -> 219.76503 | CZ64: ='BS & FCF'!CZ121 -> 219.85887 | DA64: ='BS & FCF'!DA121 -> 219.95274 | DB64: =SUM(CX64:DA64) -> 879.24787
A65: (=) EBITDA | B65: =B63+B64 -> 0 | C65: =C63+C64 -> 0 | D65: =D63+D64 -> 0 | E65: =E63+E64 -> 0 | F65: =F63+F64 -> 0 | G65: =G63+G64 -> 0 | H65: =H63+H64 -> 0 | I65: =I63+I64 -> 0 | ... DB65: =DB63+DB64 -> 2458560.2
A66: (+/-) Net financial results | B66: =B67+B68 -> 0 | C66: =C67+C68 -> 0 | D66: =D67+D68 -> 0 | E66: =E67+E68 -> 0 | F66: =F67+F68 -> 0 | G66: =G67+G68 -> 0 | H66: =H67+H68 -> 0 | I66: =I67+I68 -> 0 | ... DB66: =DB67+DB68 -> 9404.056
A67: (+) Interest income | B67: =B24+B28 -> 0 | C67: =C24+C28 -> 0 | D67: =D24+D28 -> 0 | E67: =E24+E28 -> 0 | F67: =F24+F28 -> 0 | G67: =G24+G28 -> 0 | H67: =H24+H28 -> 0 | I67: =I24+I28 -> 0 | ... DB67: =DB24+DB28 -> 260342.06
A68: (-) Interest expense | B68: =B26+B13 -> 0 | C68: =C26+C13 -> 0 | D68: =D26+D13 -> 0 | E68: =E26+E13 -> 0 | F68: =F26+F13 -> 0 | G68: =G26+G13 -> 0 | H68: =H26+H13 -> 0 | I68: =I26+I13 -> 0 | ... DB68: =DB26+DB13 -> -250938
A69: (+/-) Other income (expenses) | B69: =B34+B36+B33 -> 0 | C69: =C34+C36+C33 -> 0 | D69: =D34+D36+D33 -> 0 | E69: =E34+E36+E33 -> 0 | F69: =F34+F36+F33 -> 0 | G69: =G34+G36+G33 -> 0 | H69: =H34+H36+H33 -> 0 | I69: =I34+I36+I33 -> 0 | ... DB69: =DB34+DB36+DB33 -> 4389.6526
A70: (=) EBT | B70: =B37 -> 0 | C70: =C37 -> 0 | D70: =D37 -> 0 | E70: =E37 -> 0 | F70: =F37 -> 0 | G70: =G37 -> 0 | H70: =H37 -> 0 | I70: =I37 -> 0 | ... DB70: =DB37 -> 2471474.7
A71: (-) Income taxes | B71: =B38+B40 -> 0 | C71: =C38+C40 -> 0 | D71: =D38+D40 -> 0 | E71: =E38+E40 -> 0 | F71: =F38+F40 -> 0 | G71: =G38+G40 -> 0 | H71: =H38+H40 -> 0 | I71: =I38+I40 -> 0 | ... DB71: =DB38+DB40 -> -202606.4
A72: (-) Minority interest | B72: =B43 -> 0 | C72: =C43 -> 0 | D72: =D43 -> 0 | E72: =E43 -> 0 | F72: =F43 -> 0 | G72: =G43 -> 0 | H72: =H43 -> 0 | I72: =I43 -> 0 | ... DB72: =DB43 -> -253833.13
A73: (=) Net income (reported) | B73: =B45 -> 0 | C73: =C45 -> 0 | D73: =D45 -> 0 | E73: =E45 -> 0 | F73: =F45 -> 0 | G73: =G45 -> 0 | H73: =H45 -> 0 | I73: =I45 -> 0 | ... DB73: =DB45 -> 2015035.2
A74: (=) Net income (adjusted) | B74: =B73-B33-B36 -> 0 | C74: =C73-C33-C36 -> 0 | D74: =D73-D33-D36 -> 0 | E74: =E73-E33-E36 -> 0 | F74: =F73-F33-F36 -> 0 | G74: =G73-G33-G36 -> 0 | H74: =H73-H33-H36 -> 0 | I74: =I73-I33-I36 -> 0 | ... DB74: =DB73-DB33-DB36 -> 2015035.2
CR75: =CR77-CM77 -> -0.011795954
A76: Margins (%) | B76: =Macro!B$3 -> 1Q10 | C76: =Macro!C$3 -> 2Q10 | D76: =Macro!D$3 -> 3Q10 | E76: =Macro!E$3 -> 4Q10 | F76: =Macro!F$3 -> 2010 | G76: =Macro!G$3 -> 1Q11 | H76: =Macro!H$3 -> 2Q11 | I76: =Macro!I$3 -> 3Q11 | ... DB76: =Macro!DB$3 -> 2030E
A77: Adj. gross margin (ex-interest) | B77: =B61/B$59 -> #DIV/0! | C77: =C61/C$59 -> #DIV/0! | D77: =D61/D$59 -> #DIV/0! | E77: =E61/E$59 -> #DIV/0! | F77: =F61/F$59 -> #DIV/0! | G77: =G61/G$59 -> #DIV/0! | H77: =H61/H$59 -> #DIV/0! | I77: =I61/I$59 -> #DIV/0! | ... DB77: =DB61/DB$59 -> 0.37657672
A78: Gross margin | B78: =(B16)/B9 -> #DIV/0! | C78: =(C16)/C9 -> #DIV/0! | D78: =(D16)/D9 -> #DIV/0! | E78: =(E16)/E9 -> #DIV/0! | F78: =(F16)/F9 -> #DIV/0! | G78: =(G16)/G9 -> #DIV/0! | H78: =(H16)/H9 -> #DIV/0! | I78: =(I16)/I9 -> #DIV/0! | ... DB78: =(DB16)/DB9 -> 0.37628178
A79: Development gross margin (ex-interest) | B79: =(B5+B11)/B5 -> #DIV/0! | C79: =(C5+C11)/C5 -> #DIV/0! | D79: =(D5+D11)/D5 -> #DIV/0! | E79: =(E5+E11)/E5 -> #DIV/0! | F79: =(F5+F11)/F5 -> #DIV/0! | G79: =(G5+G11)/G5 -> #DIV/0! | H79: =(H5+H11)/H5 -> #DIV/0! | I79: =(I5+I11)/I5 -> #DIV/0! | ... DB79: =(DB5+DB11)/DB5 -> 0.38990573
A80: Services gross margin (ex-interest) | B80: =(B6+B14)/B6 -> #DIV/0! | C80: =(C6+C14)/C6 -> #DIV/0! | D80: =(D6+D14)/D6 -> #DIV/0! | E80: =(E6+E14)/E6 -> #DIV/0! | F80: =(F6+F14)/F6 -> #DIV/0! | G80: =(G6+G14)/G6 -> #DIV/0! | H80: =(H6+H14)/H6 -> #DIV/0! | I80: =(I6+I14)/I6 -> #DIV/0! | ... DB80: =(DB6+DB14)/DB6 -> -0.73513514
A81: EBITDA margin | B81: =B65/B$59 -> #DIV/0! | C81: =C65/C$59 -> #DIV/0! | D81: =D65/D$59 -> #DIV/0! | E81: =E65/E$59 -> #DIV/0! | F81: =F65/F$59 -> #DIV/0! | G81: =G65/G$59 -> #DIV/0! | H81: =H65/H$59 -> #DIV/0! | I81: =I65/I$59 -> #DIV/0! | ... DB81: =DB65/DB$59 -> 0.23298552
A82: EBIT Margin | B82: =B63/B59 -> #DIV/0! | C82: =C63/C59 -> #DIV/0! | D82: =D63/D59 -> #DIV/0! | E82: =E63/E59 -> #DIV/0! | F82: =F63/F59 -> #DIV/0! | G82: =G63/G59 -> #DIV/0! | H82: =H63/H59 -> #DIV/0! | I82: =I63/I59 -> #DIV/0! | ... DB82: =DB63/DB59 -> 0.23290219
A83: Adj. net margin | B83: =B74/B$59 -> #DIV/0! | C83: =C74/C$59 -> #DIV/0! | D83: =D74/D$59 -> #DIV/0! | E83: =E74/E$59 -> #DIV/0! | F83: =F74/F$59 -> #DIV/0! | G83: =G74/G$59 -> #DIV/0! | H83: =H74/H$59 -> #DIV/0! | I83: =I74/I$59 -> #DIV/0! | ... DB83: =DB74/DB$59 -> 0.19095485
A84: Growth rate (%)
A85: Net revenue | B85: =B59/#REF!-1 -> #REF! | C85: =C59/#REF!-1 -> #REF! | D85: =D59/#REF!-1 -> #REF! | E85: =E59/#REF!-1 -> #REF! | F85: =F59/#REF!-1 -> #REF! | G85: =G59/#REF!-1 -> #REF! | H85: =H59/#REF!-1 -> #REF! | I85: =I59/#REF!-1 -> #REF! | ... AE85: =AE59/#REF!-1 -> #REF! | AF85: =AF59/AA59-1 -> #DIV/0! | AG85: =AG59/AB59-1 -> #DIV/0! | AH85: =AH59/AC59-1 -> #DIV/0! | AI85: =AI59/AD59-1 -> #DIV/0! | AJ85: =AJ59/AE59-1 -> #DIV/0! | AK85: =AK59/AF59-1 -> #DIV/0! | AL85: =AL59/AG59-1 -> #DIV/0! | AM85: =AM59/AH59-1 -> #DIV/0! | ... DB85: =DB59/CW59-1 -> 0.062410963
A86: Adj. gross profit | B86: =B61/#REF!-1 -> #REF! | C86: =C61/#REF!-1 -> #REF! | D86: =D61/#REF!-1 -> #REF! | E86: =E61/#REF!-1 -> #REF! | F86: =F61/#REF!-1 -> #REF! | G86: =G61/#REF!-1 -> #REF! | H86: =H61/#REF!-1 -> #REF! | I86: =I61/#REF!-1 -> #REF! | ... AE86: =AE61/#REF!-1 -> #REF! | AF86: =AF61/AA61-1 -> #DIV/0! | AG86: =AG61/AB61-1 -> #DIV/0! | AH86: =AH61/AC61-1 -> #DIV/0! | AI86: =AI61/AD61-1 -> #DIV/0! | AJ86: =AJ61/AE61-1 -> #DIV/0! | AK86: =AK61/AF61-1 -> #DIV/0! | AL86: =AL61/AG61-1 -> #DIV/0! | AM86: =AM61/AH61-1 -> #DIV/0! | ... DB86: =DB61/CW61-1 -> 0.051641002
A87: Adj. gross margin (bps) | B87: =(B77-#REF!)*10000 -> #DIV/0! | C87: =(C77-#REF!)*10000 -> #DIV/0! | D87: =(D77-#REF!)*10000 -> #DIV/0! | E87: =(E77-#REF!)*10000 -> #DIV/0! | F87: =(F77-#REF!)*10000 -> #DIV/0! | G87: =(G77-#REF!)*10000 -> #DIV/0! | H87: =(H77-#REF!)*10000 -> #DIV/0! | I87: =(I77-#REF!)*10000 -> #DIV/0! | ... T87: =(T77-#REF!)*10000 -> #DIV/0! | U87: =(U77-P77)*10000 -> #DIV/0! | V87: =(V77-Q77)*10000 -> #DIV/0! | W87: =(W77-R77)*10000 -> #DIV/0! | X87: =(X77-S77)*10000 -> #DIV/0! | Y87: =(Y77-T77)*10000 -> #DIV/0! | Z87: =(Z77-U77)*10000 -> #DIV/0! | AA87: =(AA77-V77)*10000 -> #DIV/0! | AB87: =(AB77-W77)*10000 -> #DIV/0! | ... DB87: =(DB77-CW77)*10000 -> -38.565597
A88: Gross margin (bps) | B88: =(B78-#REF!)*10000 -> #DIV/0! | C88: =(C78-#REF!)*10000 -> #DIV/0! | D88: =(D78-#REF!)*10000 -> #DIV/0! | E88: =(E78-#REF!)*10000 -> #DIV/0! | F88: =(F78-#REF!)*10000 -> #DIV/0! | G88: =(G78-#REF!)*10000 -> #DIV/0! | H88: =(H78-#REF!)*10000 -> #DIV/0! | I88: =(I78-#REF!)*10000 -> #DIV/0! | ... T88: =(T78-#REF!)*10000 -> #DIV/0! | U88: =(U78-P78)*10000 -> #DIV/0! | V88: =(V78-Q78)*10000 -> #DIV/0! | W88: =(W78-R78)*10000 -> #DIV/0! | X88: =(X78-S78)*10000 -> #DIV/0! | Y88: =(Y78-T78)*10000 -> #DIV/0! | Z88: =(Z78-U78)*10000 -> #DIV/0! | AA88: =(AA78-V78)*10000 -> #DIV/0! | AB88: =(AB78-W78)*10000 -> #DIV/0! | ... DB88: =(DB78-CW78)*10000 -> -36.982832
A89: EBITDA | B89: =B65/#REF!-1 -> #REF! | C89: =C65/#REF!-1 -> #REF! | D89: =D65/#REF!-1 -> #REF! | E89: =E65/#REF!-1 -> #REF! | F89: =F65/#REF!-1 -> #REF! | G89: =G65/#REF!-1 -> #REF! | H89: =H65/#REF!-1 -> #REF! | I89: =I65/#REF!-1 -> #REF! | ... AE89: =AE65/#REF!-1 -> #REF! | AF89: =AF65/AA65-1 -> #DIV/0! | AG89: =AG65/AB65-1 -> #DIV/0! | AH89: =AH65/AC65-1 -> #DIV/0! | AI89: =AI65/AD65-1 -> #DIV/0! | AJ89: =AJ65/AE65-1 -> #DIV/0! | AK89: =AK65/AF65-1 -> #DIV/0! | AL89: =AL65/AG65-1 -> #DIV/0! | AM89: =AM65/AH65-1 -> #DIV/0! | ... DB89: =DB65/CW65-1 -> 0.055525848
A90: Net income | B90: =B73/#REF!-1 -> #REF! | C90: =C73/#REF!-1 -> #REF! | D90: =D73/#REF!-1 -> #REF! | E90: =E73/#REF!-1 -> #REF! | F90: =F73/#REF!-1 -> #REF! | G90: =G73/#REF!-1 -> #REF! | H90: =H73/#REF!-1 -> #REF! | I90: =I73/#REF!-1 -> #REF! | ... AE90: =AE73/#REF!-1 -> #REF! | AF90: =AF73/AA73-1 -> #DIV/0! | AG90: =AG73/AB73-1 -> #DIV/0! | AH90: =AH73/AC73-1 -> #DIV/0! | AI90: =AI73/AD73-1 -> #DIV/0! | AJ90: =AJ73/AE73-1 -> #DIV/0! | AK90: =AK73/AF73-1 -> #DIV/0! | AL90: =AL73/AG73-1 -> #DIV/0! | AM90: =AM73/AH73-1 -> #DIV/0! | ... DB90: =DB73/CW73-1 -> 0.055130159
A91: Net margin (bps) | B91: =(B83-#REF!)*10000 -> #DIV/0! | C91: =(C83-#REF!)*10000 -> #DIV/0! | D91: =(D83-#REF!)*10000 -> #DIV/0! | E91: =(E83-#REF!)*10000 -> #DIV/0! | F91: =(F83-#REF!)*10000 -> #DIV/0! | G91: =(G83-#REF!)*10000 -> #DIV/0! | H91: =(H83-#REF!)*10000 -> #DIV/0! | I91: =(I83-#REF!)*10000 -> #DIV/0! | ... AE91: =(AE83-#REF!)*10000 -> #DIV/0! | AF91: =(AF83-AA83)*10000 -> #DIV/0! | AG91: =(AG83-AB83)*10000 -> #DIV/0! | AH91: =(AH83-AC83)*10000 -> #DIV/0! | AI91: =(AI83-AD83)*10000 -> #DIV/0! | AJ91: =(AJ83-AE83)*10000 -> #DIV/0! | AK91: =(AK83-AF83)*10000 -> #DIV/0! | AL91: =(AL83-AG83)*10000 -> #DIV/0! | AM91: =(AM83-AH83)*10000 -> #DIV/0! | ... DB91: =(DB83-CW83)*10000 -> -13.176618
A93: Financial results calculation (R$000') | B93: =Macro!B$3 -> 1Q10 | C93: =Macro!C$3 -> 2Q10 | D93: =Macro!D$3 -> 3Q10 | E93: =Macro!E$3 -> 4Q10 | F93: =Macro!F$3 -> 2010 | G93: =Macro!G$3 -> 1Q11 | H93: =Macro!H$3 -> 2Q11 | I93: =Macro!I$3 -> 3Q11 | ... DB93: =Macro!DB$3 -> 2030E
A94: Capitalized Interest | F94: =SUM(B94:E94) -> 0 | K94: =SUM(G94:J94) -> 0 | P94: =SUM(L94:O94) -> 0 | U94: =SUM(Q94:T94) -> 0 | Z94: =SUM(V94:Y94) -> 0 | AE94: =SUM(AA94:AD94) -> 0 | AJ94: =SUM(AF94:AI94) -> 0 | AO94: =SUM(AK94:AN94) -> 0 | AT94: =SUM(AP94:AS94) -> 0 | AU94: 0 | AV94: 0 | AW94: 0 | AX94: 0 | AY94: =SUM(AU94:AX94) -> 0 | AZ94: 0 | BA94: 0 | BB94: 0 | BC94: 0 | BD94: =SUM(AZ94:BC94) -> 0 | BE94: 0 | BF94: 0 | BG94: 0 | BH94: 0 | BI94: =SUM(BE94:BH94) -> 0 | BJ94: 0 | BK94: 0 | BL94: 0 | BM94: 0 | BN94: =SUM(BJ94:BM94) -> 0 | BO94: 0 | BP94: 0 | BQ94: 0 | BR94: 0 | BS94: =SUM(BO94:BR94) -> 0 | BT94: 0 | BU94: 0 | BV94: 0 | BW94: 0 | BX94: =SUM(BT94:BW94) -> 0 | BY94: 0 | BZ94: 0 | CA94: 0 | CB94: 0 | CC94: =SUM(BY94:CB94) -> 0 | CD94: 0 | CE94: 0 | CF94: =-CF95*CF98 -> 0 | CG94: =-CG95*CG98 -> 0 | CH94: =SUM(CD94:CG94) -> 0 | CI94: =-CI95*CI98 -> 0 | CJ94: =-CJ95*CJ98 -> 0 | CK94: =-CK95*CK98 -> 0 | CL94: =-CL95*CL98 -> 0 | CM94: =SUM(CI94:CL94) -> 0 | CN94: =-CN95*CN98 -> 0 | CO94: =-CO95*CO98 -> 0 | CP94: =-CP95*CP98 -> 0 | CQ94: =-CQ95*CQ98 -> 0 | CR94: =SUM(CN94:CQ94) -> 0 | CS94: =-CS95*CS98 -> 0 | CT94: =-CT95*CT98 -> 0 | CU94: =-CU95*CU98 -> 0 | CV94: =-CV95*CV98 -> 0 | CW94: =SUM(CS94:CV94) -> 0 | CX94: =-CX95*CX98 -> 0 | CY94: =-CY95*CY98 -> 0 | CZ94: =-CZ95*CZ98 -> 0 | DA94: =-DA95*DA98 -> 0 | DB94: =SUM(CX94:DA94) -> 0
A95: Total Interest Expense | B95: =B26-B94 -> 0 | C95: =C26-C94 -> 0 | D95: =D26-D94 -> 0 | E95: =E26-E94 -> 0 | F95: =SUM(B95:E95) -> 0 | G95: =G26-G94 -> 0 | H95: =H26-H94 -> 0 | I95: =I26-I94 -> 0 | J95: =J26-J94 -> 0 | K95: =SUM(G95:J95) -> 0 | L95: =L26-L94 -> 0 | M95: =M26-M94 -> 0 | N95: =N26-N94 -> 0 | O95: =O26-O94 -> 0 | P95: =SUM(L95:O95) -> 0 | Q95: =Q26-Q94 -> 0 | R95: =R26-R94 -> 0 | S95: =S26-S94 -> 0 | T95: =T26-T94 -> 0 | U95: =SUM(Q95:T95) -> 0 | V95: =V26-V94 -> 0 | W95: =W26-W94 -> 0 | X95: =X26-X94 -> 0 | Y95: =Y26-Y94 -> 0 | Z95: =SUM(V95:Y95) -> 0 | AA95: =AA26-AA94 -> 0 | AB95: =AB26-AB94 -> 0 | AC95: =AC26-AC94 -> 0 | AD95: =AD26-AD94 -> 0 | AE95: =SUM(AA95:AD95) -> 0 | AF95: =AF26-AF94 -> 0 | AG95: =AG26-AG94 -> 0 | AH95: =AH26-AH94 -> 0 | AI95: =AI26-AI94 -> 0 | AJ95: =SUM(AF95:AI95) -> 0 | AK95: =AK26-AK94 -> -766.165 | AL95: =AL26-AL94 -> -1045.351 | AM95: =AM26-AM94 -> -1353.653 | AN95: =AN26-AN94 -> -2114.608 | AO95: =SUM(AK95:AN95) -> -5279.777 | AP95: =AP26-AP94 -> -560.905 | AQ95: =AQ26-AQ94 -> -1107.788 | AR95: =AR26-AR94 -> -3741.392 | AS95: =AS26-AS94 -> -3259.349 | AT95: =SUM(AP95:AS95) -> -8669.434 | AU95: =AU26-AU94 -> -3465 | AV95: =AV26-AV94 -> -5215 | AW95: =AW26-AW94 -> -7768 | AX95: =AX26-AX94 -> -10241 | AY95: =SUM(AU95:AX95) -> -26689 | AZ95: =AZ26-AZ94 -> -4959 | BA95: =BA26-BA94 -> -5719 | BB95: =BB26-BB94 -> -6639 | BC95: =BC26-BC94 -> -6166 | BD95: =SUM(AZ95:BC95) -> -23483 | BE95: =BE26-BE94 -> -7256 | BF95: =BF26-BF94 -> -9300 | BG95: =BG26-BG94 -> -11427 | BH95: =BH26-BH94 -> -21731 | BI95: =SUM(BE95:BH95) -> -49714 | BJ95: =BJ26-BJ94 -> -17062 | BK95: =BK26-BK94 -> -22214 | BL95: =BL26-BL94 -> -22860 | BM95: =BM26-BM94 -> -26332 | BN95: =SUM(BJ95:BM95) -> -88468 | BO95: =BO26-BO94 -> -25672 | BP95: =BP26-BP94 -> -26026 | BQ95: =BQ26-BQ94 -> -23214 | BR95: =BR26-BR94 -> -25215 | BS95: =SUM(BO95:BR95) -> -100127 | BT95: =BT26-BT94 -> -24806 | BU95: =BU26-BU94 -> -31099 | BV95: =BV26-BV94 -> -39673 | BW95: =BW26-BW94 -> -41587 | BX95: =SUM(BT95:BW95) -> -137165 | BY95: =BY26-BY94 -> -51332 | BZ95: =BZ26-BZ94 -> -50846 | CA95: =CA26-CA94 -> -56062 | CB95: =CB26-CB94 -> -59596 | CC95: =SUM(BY95:CB95) -> -217836 | CD95: =CD26-CD94 -> -59802 | CE95: =CE26-CE94 -> -70288 | CF95: =CF99+CF102 -> -51675.015 | CG95: =CG99+CG102 -> -51884.836 | CH95: =SUM(CD95:CG95) -> -233649.85 | CI95: =CI99+CI102 -> -54494.949 | CJ95: =CJ99+CJ102 -> -56010.795 | CK95: =CK99+CK102 -> -55551.908 | CL95: =CL99+CL102 -> -55906.806 | CM95: =SUM(CI95:CL95) -> -221964.46 | CN95: =CN99+CN102 -> -50990.067 | CO95: =CO99+CO102 -> -53434.378 | CP95: =CP99+CP102 -> -54177.072 | CQ95: =CQ99+CQ102 -> -54440.294 | CR95: =SUM(CN95:CQ95) -> -213041.81 | CS95: =CS99+CS102 -> -56174.196 | CT95: =CT99+CT102 -> -58349.531 | CU95: =CU99+CU102 -> -58977.094 | CV95: =CV99+CV102 -> -58944.368 | CW95: =SUM(CS95:CV95) -> -232445.19 | CX95: =CX99+CX102 -> -60342.356 | CY95: =CY99+CY102 -> -62295.093 | CZ95: =CZ99+CZ102 -> -62707.126 | DA95: =DA99+DA102 -> -62481.123 | DB95: =SUM(CX95:DA95) -> -247825.7
A96: Yield | B96: =(1-B95/(AVERAGE('BS & FCF'!A28:B28)+AVERAGE('BS & FCF'!A31:B31)))^4-1 -> #DIV/0! | C96: =(1-C95/(AVERAGE('BS & FCF'!B28:C28)+AVERAGE('BS & FCF'!B31:C31)))^4-1 -> #DIV/0! | D96: =(1-D95/(AVERAGE('BS & FCF'!C28:D28)+AVERAGE('BS & FCF'!C31:D31)))^4-1 -> #DIV/0! | E96: =(1-E95/(AVERAGE('BS & FCF'!D28:E28)+AVERAGE('BS & FCF'!D31:E31)))^4-1 -> #DIV/0! | F96: =(1-F95/(AVERAGE('BS & FCF'!B28:E28)+AVERAGE('BS & FCF'!B31:E31)))-1 -> #DIV/0! | G96: =(1-G95/(AVERAGE('BS & FCF'!F28:G28)+AVERAGE('BS & FCF'!F31:G31)))^4-1 -> #DIV/0! | H96: =(1-H95/(AVERAGE('BS & FCF'!G28:H28)+AVERAGE('BS & FCF'!G31:H31)))^4-1 -> #DIV/0! | I96: =(1-I95/(AVERAGE('BS & FCF'!H28:I28)+AVERAGE('BS & FCF'!H31:I31)))^4-1 -> #DIV/0! | J96: =(1-J95/(AVERAGE('BS & FCF'!I28:J28)+AVERAGE('BS & FCF'!I31:J31)))^4-1 -> #DIV/0! | K96: =(1-K95/(AVERAGE('BS & FCF'!G28:J28)+AVERAGE('BS & FCF'!G31:J31)))-1 -> #DIV/0! | L96: =(1-L95/(AVERAGE('BS & FCF'!K28:L28)+AVERAGE('BS & FCF'!K31:L31)))^4-1 -> #DIV/0! | M96: =(1-M95/(AVERAGE('BS & FCF'!L28:M28)+AVERAGE('BS & FCF'!L31:M31)))^4-1 -> #DIV/0! | N96: =(1-N95/(AVERAGE('BS & FCF'!M28:N28)+AVERAGE('BS & FCF'!M31:N31)))^4-1 -> #DIV/0! | O96: =(1-O95/(AVERAGE('BS & FCF'!N28:O28)+AVERAGE('BS & FCF'!N31:O31)))^4-1 -> #DIV/0! | P96: =(1-P95/(AVERAGE('BS & FCF'!L28:O28)+AVERAGE('BS & FCF'!L31:O31)))-1 -> #DIV/0! | Q96: =(1-Q95/(AVERAGE('BS & FCF'!P28:Q28)+AVERAGE('BS & FCF'!P31:Q31)))^4-1 -> #DIV/0! | R96: =(1-R95/(AVERAGE('BS & FCF'!Q28:R28)+AVERAGE('BS & FCF'!Q31:R31)))^4-1 -> #DIV/0! | S96: =(1-S95/(AVERAGE('BS & FCF'!R28:S28)+AVERAGE('BS & FCF'!R31:S31)))^4-1 -> #DIV/0! | T96: =(1-T95/(AVERAGE('BS & FCF'!S28:T28)+AVERAGE('BS & FCF'!S31:T31)))^4-1 -> #DIV/0! | U96: =(1-U95/(AVERAGE('BS & FCF'!Q28:T28)+AVERAGE('BS & FCF'!Q31:T31)))-1 -> #DIV/0! | V96: =(1-V95/(AVERAGE('BS & FCF'!U28:V28)+AVERAGE('BS & FCF'!U31:V31)))^4-1 -> #DIV/0! | W96: =(1-W95/(AVERAGE('BS & FCF'!V28:W28)+AVERAGE('BS & FCF'!V31:W31)))^4-1 -> #DIV/0! | X96: =(1-X95/(AVERAGE('BS & FCF'!W28:X28)+AVERAGE('BS & FCF'!W31:X31)))^4-1 -> #DIV/0! | Y96: =(1-Y95/(AVERAGE('BS & FCF'!X28:Y28)+AVERAGE('BS & FCF'!X31:Y31)))^4-1 -> #DIV/0! | Z96: =(1-Z95/(AVERAGE('BS & FCF'!V28:Y28)+AVERAGE('BS & FCF'!V31:Y31)))-1 -> #DIV/0! | AA96: =(1-AA95/(AVERAGE('BS & FCF'!Z28:AA28)+AVERAGE('BS & FCF'!Z31:AA31)))^4-1 -> #DIV/0! | AB96: =(1-AB95/(AVERAGE('BS & FCF'!AA28:AB28)+AVERAGE('BS & FCF'!AA31:AB31)))^4-1 -> #DIV/0! | AC96: =(1-AC95/(AVERAGE('BS & FCF'!AB28:AC28)+AVERAGE('BS & FCF'!AB31:AC31)))^4-1 -> #DIV/0! | AD96: =(1-AD95/(AVERAGE('BS & FCF'!AC28:AD28)+AVERAGE('BS & FCF'!AC31:AD31)))^4-1 -> #DIV/0! | AE96: =(1-AE95/(AVERAGE('BS & FCF'!AA28:AD28)+AVERAGE('BS & FCF'!AA31:AD31)))-1 -> #DIV/0! | AF96: =(1-AF95/(AVERAGE('BS & FCF'!AE28:AF28)+AVERAGE('BS & FCF'!AE31:AF31)))^4-1 -> #DIV/0! | AG96: =(1-AG95/(AVERAGE('BS & FCF'!AF28:AG28)+AVERAGE('BS & FCF'!AF31:AG31)))^4-1 -> #DIV/0! | AH96: =(1-AH95/(AVERAGE('BS & FCF'!AG28:AH28)+AVERAGE('BS & FCF'!AG31:AH31)))^4-1 -> #DIV/0! | AI96: =(1-AI95/(AVERAGE('BS & FCF'!AH28:AI28)+AVERAGE('BS & FCF'!AH31:AI31)))^4-1 -> #DIV/0! | AJ96: =(1-AJ95/(AVERAGE('BS & FCF'!AF28:AI28)+AVERAGE('BS & FCF'!AF31:AI31)))-1 -> #DIV/0! | AK96: =(1-AK95/(AVERAGE('BS & FCF'!AJ28:AK28)+AVERAGE('BS & FCF'!AJ31:AK31)))^4-1 -> 0.029565471 | AL96: =(1-AL95/(AVERAGE('BS & FCF'!AK28:AL28)+AVERAGE('BS & FCF'!AK31:AL31)))^4-1 -> 0.020746372 | AM96: =(1-AM95/(AVERAGE('BS & FCF'!AL28:AM28)+AVERAGE('BS & FCF'!AL31:AM31)))^4-1 -> 0.027506494 | AN96: =(1-AN95/(AVERAGE('BS & FCF'!AM28:AN28)+AVERAGE('BS & FCF'!AM31:AN31)))^4-1 -> 0.04065119 | AO96: =(1-AO95/(AVERAGE('BS & FCF'!AK28:AN28)+AVERAGE('BS & FCF'!AK31:AN31)))-1 -> 0.025485916 | AP96: =(1-AP95/(AVERAGE('BS & FCF'!AO28:AP28)+AVERAGE('BS & FCF'!AO31:AP31)))^4-1 -> 0.011647504 | AQ96: =(1-AQ95/(AVERAGE('BS & FCF'!AP28:AQ28)+AVERAGE('BS & FCF'!AP31:AQ31)))^4-1 -> 0.029373323 | AR96: =(1-AR95/(AVERAGE('BS & FCF'!AQ28:AR28)+AVERAGE('BS & FCF'!AQ31:AR31)))^4-1 -> 0.072639083 | AS96: =(1-AS95/(AVERAGE('BS & FCF'!AR28:AS28)+AVERAGE('BS & FCF'!AR31:AS31)))^4-1 -> 0.045946085 | AT96: =(1-AT95/(AVERAGE('BS & FCF'!AP28:AS28)+AVERAGE('BS & FCF'!AP31:AS31)))-1 -> 0.039307757 | AU96: =(1-AU95/(AVERAGE('BS & FCF'!AT28:AU28)+AVERAGE('BS & FCF'!AT31:AU31)))^4-1 -> 0.049967771 | AV96: =(1-AV95/(AVERAGE('BS & FCF'!AU28:AV28)+AVERAGE('BS & FCF'!AU31:AV31)))^4-1 -> 0.080905937 | AW96: =(1-AW95/(AVERAGE('BS & FCF'!AV28:AW28)+AVERAGE('BS & FCF'!AV31:AW31)))^4-1 -> 0.12523636 | AX96: =(1-AX95/(AVERAGE('BS & FCF'!AW28:AX28)+AVERAGE('BS & FCF'!AW31:AX31)))^4-1 -> 0.14926961 | AY96: =(1-AY95/(AVERAGE('BS & FCF'!AU28:AX28)+AVERAGE('BS & FCF'!AU31:AX31)))-1 -> 0.096198763 | AZ96: =(1-AZ95/(AVERAGE('BS & FCF'!AY28:AZ28)+AVERAGE('BS & FCF'!AY31:AZ31)))^4-1 -> 0.063219089 | BA96: =(1-BA95/(AVERAGE('BS & FCF'!AZ28:BA28)+AVERAGE('BS & FCF'!AZ31:BA31)))^4-1 -> 0.069023308 | BB96: =(1-BB95/(AVERAGE('BS & FCF'!BA28:BB28)+AVERAGE('BS & FCF'!BA31:BB31)))^4-1 -> 0.081578566 | BC96: =(1-BC95/(AVERAGE('BS & FCF'!BB28:BC28)+AVERAGE('BS & FCF'!BB31:BC31)))^4-1 -> 0.085063737 | BD96: =(1-BD95/(AVERAGE('BS & FCF'!AZ28:BC28)+AVERAGE('BS & FCF'!AZ31:BC31)))-1 -> 0.073508133 | BE96: =(1-BE95/(AVERAGE('BS & FCF'!BD28:BE28)+AVERAGE('BS & FCF'!BD31:BE31)))^4-1 -> 0.1066184 | BF96: =(1-BF95/(AVERAGE('BS & FCF'!BE28:BF28)+AVERAGE('BS & FCF'!BE31:BF31)))^4-1 -> 0.14159629 | BG96: =(1-BG95/(AVERAGE('BS & FCF'!BF28:BG28)+AVERAGE('BS & FCF'!BF31:BG31)))^4-1 -> 0.14540451 | BH96: =(1-BH95/(AVERAGE('BS & FCF'!BG28:BH28)+AVERAGE('BS & FCF'!BG31:BH31)))^4-1 -> 0.24147356 | BI96: =(1-BI95/(AVERAGE('BS & FCF'!BE28:BH28)+AVERAGE('BS & FCF'!BE31:BH31)))-1 -> 0.14898125 | BJ96: =(1-BJ95/(AVERAGE('BS & FCF'!BI28:BJ28)+AVERAGE('BS & FCF'!BI31:BJ31)))^4-1 -> 0.18628551 | BK96: =(1-BK95/(AVERAGE('BS & FCF'!BJ28:BK28)+AVERAGE('BS & FCF'!BJ31:BK31)))^4-1 -> 0.24470533 | BL96: =(1-BL95/(AVERAGE('BS & FCF'!BK28:BL28)+AVERAGE('BS & FCF'!BK31:BL31)))^4-1 -> 0.23167319 | BM96: =(1-BM95/(AVERAGE('BS & FCF'!BL28:BM28)+AVERAGE('BS & FCF'!BL31:BM31)))^4-1 -> 0.24449123 | BN96: =(1-BN95/(AVERAGE('BS & FCF'!BJ28:BM28)+AVERAGE('BS & FCF'!BJ31:BM31)))-1 -> 0.20492425 | BO96: =(1-BO95/(AVERAGE('BS & FCF'!BN28:BO28)+AVERAGE('BS & FCF'!BN31:BO31)))^4-1 -> 0.23289337 | BP96: =(1-BP95/(AVERAGE('BS & FCF'!BO28:BP28)+AVERAGE('BS & FCF'!BO31:BP31)))^4-1 -> 0.23148872 | BQ96: =(1-BQ95/(AVERAGE('BS & FCF'!BP28:BQ28)+AVERAGE('BS & FCF'!BP31:BQ31)))^4-1 -> 0.17227632 | BR96: =(1-BR95/(AVERAGE('BS & FCF'!BQ28:BR28)+AVERAGE('BS & FCF'!BQ31:BR31)))^4-1 -> 0.17009858 | BS96: =(1-BS95/(AVERAGE('BS & FCF'!BO28:BR28)+AVERAGE('BS & FCF'!BO31:BR31)))-1 -> 0.17934305 | BT96: =(1-BT95/(AVERAGE('BS & FCF'!BS28:BT28)+AVERAGE('BS & FCF'!BS31:BT31)))^4-1 -> 0.17357409 | BU96: =(1-BU95/(AVERAGE('BS & FCF'!BT28:BU28)+AVERAGE('BS & FCF'!BT31:BU31)))^4-1 -> 0.15626146 | BV96: =(1-BV95/(AVERAGE('BS & FCF'!BU28:BV28)+AVERAGE('BS & FCF'!BU31:BV31)))^4-1 -> 0.15348997 | BW96: =(1-BW95/(AVERAGE('BS & FCF'!BV28:BW28)+AVERAGE('BS & FCF'!BV31:BW31)))^4-1 -> 0.16903536 | BX96: =(1-BX95/(AVERAGE('BS & FCF'!BT28:BW28)+AVERAGE('BS & FCF'!BT31:BW31)))-1 -> 0.14547393 | BY96: =(1-BY95/(AVERAGE('BS & FCF'!BX28:BY28)+AVERAGE('BS & FCF'!BX31:BY31)))^4-1 -> 0.19362599 | BZ96: =(1-BZ95/(AVERAGE('BS & FCF'!BY28:BZ28)+AVERAGE('BS & FCF'!BY31:BZ31)))^4-1 -> 0.16682539 | CA96: =(1-CA95/(AVERAGE('BS & FCF'!BZ28:CA28)+AVERAGE('BS & FCF'!BZ31:CA31)))^4-1 -> 0.18203655 | CB96: =(1-CB95/(AVERAGE('BS & FCF'!CA28:CB28)+AVERAGE('BS & FCF'!CA31:CB31)))^4-1 -> 0.18160532 | CC96: =(1-CC95/(AVERAGE('BS & FCF'!BY28:CB28)+AVERAGE('BS & FCF'!BY31:CB31)))-1 -> 0.16184566 | CD96: =(1-CD95/(AVERAGE('BS & FCF'!CC28:CD28)+AVERAGE('BS & FCF'!CC31:CD31)))^4-1 -> 0.18039188 | CE96: =(1-CE95/(AVERAGE('BS & FCF'!CD28:CE28)+AVERAGE('BS & FCF'!CD31:CE31)))^4-1 -> 0.22567627 | CF96: =(1-CF95/(AVERAGE('BS & FCF'!CE28:CF28)+AVERAGE('BS & FCF'!CE31:CF31)))^4-1 -> 0.16195833 | CG96: =(1-CG95/(AVERAGE('BS & FCF'!CF28:CG28)+AVERAGE('BS & FCF'!CF31:CG31)))^4-1 -> 0.161 | CH96: =(1-CH95/(AVERAGE('BS & FCF'!CD28:CG28)+AVERAGE('BS & FCF'!CD31:CG31)))-1 -> 0.17235534 | CI96: =(1-CI95/(AVERAGE('BS & FCF'!CH28:CI28)+AVERAGE('BS & FCF'!CH31:CI31)))^4-1 -> 0.161 | CJ96: =(1-CJ95/(AVERAGE('BS & FCF'!CI28:CJ28)+AVERAGE('BS & FCF'!CI31:CJ31)))^4-1 -> 0.15333333 | CK96: =(1-CK95/(AVERAGE('BS & FCF'!CJ28:CK28)+AVERAGE('BS & FCF'!CJ31:CK31)))^4-1 -> 0.14566667 | CL96: =(1-CL95/(AVERAGE('BS & FCF'!CK28:CL28)+AVERAGE('BS & FCF'!CK31:CL31)))^4-1 -> 0.14375 | CM96: =(1-CM95/(AVERAGE('BS & FCF'!CI28:CL28)+AVERAGE('BS & FCF'!CI31:CL31)))-1 -> 0.13960673 | CN96: =(1-CN95/(AVERAGE('BS & FCF'!CM28:CN28)+AVERAGE('BS & FCF'!CM31:CN31)))^4-1 -> 0.125 | CO96: =(1-CO95/(AVERAGE('BS & FCF'!CN28:CO28)+AVERAGE('BS & FCF'!CN31:CO31)))^4-1 -> 0.125 | CP96: =(1-CP95/(AVERAGE('BS & FCF'!CO28:CP28)+AVERAGE('BS & FCF'!CO31:CP31)))^4-1 -> 0.125 | CQ96: =(1-CQ95/(AVERAGE('BS & FCF'!CP28:CQ28)+AVERAGE('BS & FCF'!CP31:CQ31)))^4-1 -> 0.125 | CR96: =(1-CR95/(AVERAGE('BS & FCF'!CN28:CQ28)+AVERAGE('BS & FCF'!CN31:CQ31)))-1 -> 0.1180342 | CS96: =(1-CS95/(AVERAGE('BS & FCF'!CR28:CS28)+AVERAGE('BS & FCF'!CR31:CS31)))^4-1 -> 0.125 | CT96: =(1-CT95/(AVERAGE('BS & FCF'!CS28:CT28)+AVERAGE('BS & FCF'!CS31:CT31)))^4-1 -> 0.125 | CU96: =(1-CU95/(AVERAGE('BS & FCF'!CT28:CU28)+AVERAGE('BS & FCF'!CT31:CU31)))^4-1 -> 0.125 | CV96: =(1-CV95/(AVERAGE('BS & FCF'!CU28:CV28)+AVERAGE('BS & FCF'!CU31:CV31)))^4-1 -> 0.125 | CW96: =(1-CW95/(AVERAGE('BS & FCF'!CS28:CV28)+AVERAGE('BS & FCF'!CS31:CV31)))-1 -> 0.11844252 | CX96: =(1-CX95/(AVERAGE('BS & FCF'!CW28:CX28)+AVERAGE('BS & FCF'!CW31:CX31)))^4-1 -> 0.125 | CY96: =(1-CY95/(AVERAGE('BS & FCF'!CX28:CY28)+AVERAGE('BS & FCF'!CX31:CY31)))^4-1 -> 0.125 | CZ96: =(1-CZ95/(AVERAGE('BS & FCF'!CY28:CZ28)+AVERAGE('BS & FCF'!CY31:CZ31)))^4-1 -> 0.125 | DA96: =(1-DA95/(AVERAGE('BS & FCF'!CZ28:DA28)+AVERAGE('BS & FCF'!CZ31:DA31)))^4-1 -> 0.125 | DB96: =(1-DB95/(AVERAGE('BS & FCF'!CX28:DA28)+AVERAGE('BS & FCF'!CX31:DA31)))-1 -> 0.11870719
A97: % of CDI | B97: =B96/Macro!B12 -> #DIV/0! | C97: =C96/Macro!C12 -> #DIV/0! | D97: =D96/Macro!D12 -> #DIV/0! | E97: =E96/Macro!E12 -> #DIV/0! | F97: =F96/Macro!F12 -> #DIV/0! | G97: =G96/Macro!G12 -> #DIV/0! | H97: =H96/Macro!H12 -> #DIV/0! | I97: =I96/Macro!I12 -> #DIV/0! | ... DB97: =DB96/Macro!DB12 -> 0.94965753
A98: % interest capitalization | B98: =B94/-B95 -> #DIV/0! | C98: =C94/-C95 -> #DIV/0! | D98: =D94/-D95 -> #DIV/0! | E98: =E94/-E95 -> #DIV/0! | F98: =F94/-F95 -> #DIV/0! | G98: =G94/-G95 -> #DIV/0! | H98: =H94/-H95 -> #DIV/0! | I98: =I94/-I95 -> #DIV/0! | ... CE98: =CE94/-CE95 -> 0 | CF98: =CE98 -> 0 | CG98: =CF98 -> 0 | CH98: =CH94/-CH95 -> 0 | CI98: =CG98 -> 0 | CJ98: =CI98 -> 0 | CK98: =CJ98 -> 0 | CL98: =CK98 -> 0 | CM98: =CM94/-CM95 -> 0 | CN98: =CL98 -> 0 | CO98: =CN98 -> 0 | CP98: =CO98 -> 0 | CQ98: =CP98 -> 0 | CR98: =CR94/-CR95 -> 0 | CS98: =CQ98 -> 0 | CT98: =CS98 -> 0 | CU98: =CT98 -> 0 | CV98: =CU98 -> 0 | CW98: =CW94/-CW95 -> 0 | CX98: =CV98 -> 0 | CY98: =CX98 -> 0 | CZ98: =CY98 -> 0 | DA98: =CZ98 -> 0 | DB98: =DB94/-DB95 -> 0
A99: Securitization financial expenses | B99: 0 | C99: 0 | D99: 0 | E99: 0 | F99: =SUM(B99:E99) -> 0 | G99: 0 | H99: 0 | I99: 0 | J99: 0 | K99: =SUM(G99:J99) -> 0 | L99: 0 | M99: 0 | N99: 0 | O99: 0 | P99: =SUM(L99:O99) -> 0 | Q99: 0 | R99: 0 | S99: 0 | T99: 0 | U99: =SUM(Q99:T99) -> 0 | V99: 0 | W99: 0 | X99: 0 | Y99: 0 | Z99: =SUM(V99:Y99) -> 0 | AA99: 0 | AB99: 0 | AC99: 0 | AD99: 0 | AE99: =SUM(AA99:AD99) -> 0 | AF99: 0 | AG99: 0 | AH99: 0 | AI99: 0 | AJ99: =SUM(AF99:AI99) -> 0 | AK99: 0 | AL99: 0 | AM99: 0 | AN99: 0 | AO99: =SUM(AK99:AN99) -> 0 | AP99: 0 | AQ99: 0 | AR99: 0 | AS99: 0 | AT99: =SUM(AP99:AS99) -> 0 | AU99: 0 | AV99: 0 | AW99: 0 | AX99: 0 | AY99: =SUM(AU99:AX99) -> 0 | AZ99: 0 | BA99: 0 | BB99: 0 | BC99: 0 | BD99: =SUM(AZ99:BC99) -> 0 | BE99: 0 | BF99: 0 | BG99: 0 | BH99: 0 | BI99: =SUM(BE99:BH99) -> 0 | BJ99: 0 | BK99: 0 | BL99: 0 | BM99: 0 | BN99: =SUM(BJ99:BM99) -> 0 | BO99: 0 | BP99: 0 | BQ99: 0 | BR99: 0 | BS99: =SUM(BO99:BR99) -> 0 | BT99: 0 | BU99: 0 | BV99: 0 | BW99: 0 | BX99: =SUM(BT99:BW99) -> 0 | BY99: 0 | BZ99: 0 | CA99: 0 | CB99: 0 | CC99: =SUM(BY99:CB99) -> 0 | CD99: 0 | CE99: 0 | CF99: =IFERROR(-CF100*AVERAGE('BS & FCF'!CE32:CF32)/4,0) -> 0 | CG99: =IFERROR(-CG100*AVERAGE('BS & FCF'!CF32:CG32)/4,0) -> 0 | CH99: =SUM(CD99:CG99) -> 0 | CI99: =IFERROR(-CI100*AVERAGE('BS & FCF'!CH32:CI32)/4,0) -> 0 | CJ99: =IFERROR(-CJ100*AVERAGE('BS & FCF'!CI32:CJ32)/4,0) -> 0 | CK99: =IFERROR(-CK100*AVERAGE('BS & FCF'!CJ32:CK32)/4,0) -> 0 | CL99: =IFERROR(-CL100*AVERAGE('BS & FCF'!CK32:CL32)/4,0) -> 0 | CM99: =SUM(CI99:CL99) -> 0 | CN99: =IFERROR(-CN100*AVERAGE('BS & FCF'!CM32:CN32)/4,0) -> 0 | CO99: =IFERROR(-CO100*AVERAGE('BS & FCF'!CN32:CO32)/4,0) -> 0 | CP99: =IFERROR(-CP100*AVERAGE('BS & FCF'!CO32:CP32)/4,0) -> 0 | CQ99: =IFERROR(-CQ100*AVERAGE('BS & FCF'!CP32:CQ32)/4,0) -> 0 | CR99: =SUM(CN99:CQ99) -> 0 | CS99: =IFERROR(-CS100*AVERAGE('BS & FCF'!CR32:CS32)/4,0) -> 0 | CT99: =IFERROR(-CT100*AVERAGE('BS & FCF'!CS32:CT32)/4,0) -> 0 | CU99: =IFERROR(-CU100*AVERAGE('BS & FCF'!CT32:CU32)/4,0) -> 0 | CV99: =IFERROR(-CV100*AVERAGE('BS & FCF'!CU32:CV32)/4,0) -> 0 | CW99: =SUM(CS99:CV99) -> 0 | CX99: =IFERROR(-CX100*AVERAGE('BS & FCF'!CW32:CX32)/4,0) -> 0 | CY99: =IFERROR(-CY100*AVERAGE('BS & FCF'!CX32:CY32)/4,0) -> 0 | CZ99: =IFERROR(-CZ100*AVERAGE('BS & FCF'!CY32:CZ32)/4,0) -> 0 | DA99: =IFERROR(-DA100*AVERAGE('BS & FCF'!CZ32:DA32)/4,0) -> 0 | DB99: =SUM(CX99:DA99) -> 0
A100: Securitization rate | B100: =IFERROR(-B99/AVERAGE('BS & FCF'!A32:B32)*4,0) -> 0 | C100: =IFERROR(-C99/AVERAGE('BS & FCF'!B32:C32)*4,0) -> 0 | D100: =IFERROR(-D99/AVERAGE('BS & FCF'!C32:D32)*4,0) -> 0 | E100: =IFERROR(-E99/AVERAGE('BS & FCF'!D32:E32)*4,0) -> 0 | F100: =IFERROR(((1-F99/(AVERAGE('BS & FCF'!B32:E32)))-1),0) -> 0 | G100: =IFERROR(-G99/AVERAGE('BS & FCF'!F32:G32)*4,0) -> 0 | H100: =IFERROR(-H99/AVERAGE('BS & FCF'!G32:H32)*4,0) -> 0 | I100: =IFERROR(-I99/AVERAGE('BS & FCF'!H32:I32)*4,0) -> 0 | J100: =IFERROR(-J99/AVERAGE('BS & FCF'!I32:J32)*4,0) -> 0 | K100: =IFERROR(((1-K99/(AVERAGE('BS & FCF'!G32:J32)))-1),0) -> 0 | L100: =IFERROR(-L99/AVERAGE('BS & FCF'!K32:L32)*4,0) -> 0 | M100: =IFERROR(-M99/AVERAGE('BS & FCF'!L32:M32)*4,0) -> 0 | N100: =IFERROR(-N99/AVERAGE('BS & FCF'!M32:N32)*4,0) -> 0 | O100: =IFERROR(-O99/AVERAGE('BS & FCF'!N32:O32)*4,0) -> 0 | P100: =IFERROR(((1-P99/(AVERAGE('BS & FCF'!L32:O32)))-1),0) -> 0 | Q100: =IFERROR(-Q99/AVERAGE('BS & FCF'!P32:Q32)*4,0) -> 0 | R100: =IFERROR(-R99/AVERAGE('BS & FCF'!Q32:R32)*4,0) -> 0 | S100: =IFERROR(-S99/AVERAGE('BS & FCF'!R32:S32)*4,0) -> 0 | T100: =IFERROR(-T99/AVERAGE('BS & FCF'!S32:T32)*4,0) -> 0 | U100: =IFERROR(((1-U99/(AVERAGE('BS & FCF'!Q32:T32)))-1),0) -> 0 | V100: =IFERROR(-V99/AVERAGE('BS & FCF'!U32:V32)*4,0) -> 0 | W100: =IFERROR(-W99/AVERAGE('BS & FCF'!V32:W32)*4,0) -> 0 | X100: =IFERROR(-X99/AVERAGE('BS & FCF'!W32:X32)*4,0) -> 0 | Y100: =IFERROR(-Y99/AVERAGE('BS & FCF'!X32:Y32)*4,0) -> 0 | Z100: =IFERROR(((1-Z99/(AVERAGE('BS & FCF'!V32:Y32)))-1),0) -> 0 | AA100: =IFERROR(-AA99/AVERAGE('BS & FCF'!Z32:AA32)*4,0) -> 0 | AB100: =IFERROR(-AB99/AVERAGE('BS & FCF'!AA32:AB32)*4,0) -> 0 | AC100: =IFERROR(-AC99/AVERAGE('BS & FCF'!AB32:AC32)*4,0) -> 0 | AD100: =IFERROR(-AD99/AVERAGE('BS & FCF'!AC32:AD32)*4,0) -> 0 | AE100: =IFERROR(((1-AE99/(AVERAGE('BS & FCF'!AA32:AD32)))-1),0) -> 0 | AF100: =IFERROR(-AF99/AVERAGE('BS & FCF'!AE32:AF32)*4,0) -> 0 | AG100: =IFERROR(-AG99/AVERAGE('BS & FCF'!AF32:AG32)*4,0) -> 0 | AH100: =IFERROR(-AH99/AVERAGE('BS & FCF'!AG32:AH32)*4,0) -> 0 | AI100: =IFERROR(-AI99/AVERAGE('BS & FCF'!AH32:AI32)*4,0) -> 0 | AJ100: =IFERROR(((1-AJ99/(AVERAGE('BS & FCF'!AF32:AI32)))-1),0) -> 0 | AK100: =IFERROR(-AK99/AVERAGE('BS & FCF'!AJ32:AK32)*4,0) -> 0 | AL100: =IFERROR(-AL99/AVERAGE('BS & FCF'!AK32:AL32)*4,0) -> 0 | AM100: =IFERROR(-AM99/AVERAGE('BS & FCF'!AL32:AM32)*4,0) -> 0 | AN100: =IFERROR(-AN99/AVERAGE('BS & FCF'!AM32:AN32)*4,0) -> 0 | AO100: =IFERROR(((1-AO99/(AVERAGE('BS & FCF'!AK32:AN32)))-1),0) -> 0 | AP100: =IFERROR(-AP99/AVERAGE('BS & FCF'!AO32:AP32)*4,0) -> 0 | AQ100: =IFERROR(-AQ99/AVERAGE('BS & FCF'!AP32:AQ32)*4,0) -> 0 | AR100: =IFERROR(-AR99/AVERAGE('BS & FCF'!AQ32:AR32)*4,0) -> 0 | AS100: =IFERROR(-AS99/AVERAGE('BS & FCF'!AR32:AS32)*4,0) -> 0 | AT100: =IFERROR(((1-AT99/(AVERAGE('BS & FCF'!AP32:AS32)))-1),0) -> 0 | AU100: =IFERROR(-AU99/AVERAGE('BS & FCF'!AT32:AU32)*4,0) -> 0 | AV100: =IFERROR(-AV99/AVERAGE('BS & FCF'!AU32:AV32)*4,0) -> 0 | AW100: =IFERROR(-AW99/AVERAGE('BS & FCF'!AV32:AW32)*4,0) -> 0 | AX100: =IFERROR(-AX99/AVERAGE('BS & FCF'!AW32:AX32)*4,0) -> 0 | AY100: =IFERROR(((1-AY99/(AVERAGE('BS & FCF'!AU32:AX32)))-1),0) -> 0 | AZ100: =IFERROR(-AZ99/AVERAGE('BS & FCF'!AY32:AZ32)*4,0) -> 0 | BA100: =IFERROR(-BA99/AVERAGE('BS & FCF'!AZ32:BA32)*4,0) -> 0 | BB100: =IFERROR(-BB99/AVERAGE('BS & FCF'!BA32:BB32)*4,0) -> 0 | BC100: =IFERROR(-BC99/AVERAGE('BS & FCF'!BB32:BC32)*4,0) -> 0 | BD100: =IFERROR(((1-BD99/(AVERAGE('BS & FCF'!AZ32:BC32)))-1),0) -> 0 | BE100: =IFERROR(-BE99/AVERAGE('BS & FCF'!BD32:BE32)*4,0) -> 0 | BF100: =IFERROR(-BF99/AVERAGE('BS & FCF'!BE32:BF32)*4,0) -> 0 | BG100: =IFERROR(-BG99/AVERAGE('BS & FCF'!BF32:BG32)*4,0) -> 0 | BH100: =IFERROR(-BH99/AVERAGE('BS & FCF'!BG32:BH32)*4,0) -> 0 | BI100: =IFERROR(((1-BI99/(AVERAGE('BS & FCF'!BE32:BH32)))-1),0) -> 0 | BJ100: =IFERROR(-BJ99/AVERAGE('BS & FCF'!BI32:BJ32)*4,0) -> 0 | BK100: =IFERROR(-BK99/AVERAGE('BS & FCF'!BJ32:BK32)*4,0) -> 0 | BL100: =IFERROR(-BL99/AVERAGE('BS & FCF'!BK32:BL32)*4,0) -> 0 | BM100: =IFERROR(-BM99/AVERAGE('BS & FCF'!BL32:BM32)*4,0) -> 0 | BN100: =IFERROR(((1-BN99/(AVERAGE('BS & FCF'!BJ32:BM32)))-1),0) -> 0 | BO100: =IFERROR(-BO99/AVERAGE('BS & FCF'!BN32:BO32)*4,0) -> 0 | BP100: =IFERROR(-BP99/AVERAGE('BS & FCF'!BO32:BP32)*4,0) -> 0 | BQ100: =IFERROR(-BQ99/AVERAGE('BS & FCF'!BP32:BQ32)*4,0) -> 0 | BR100: =IFERROR(-BR99/AVERAGE('BS & FCF'!BQ32:BR32)*4,0) -> 0 | BS100: =IFERROR(((1-BS99/(AVERAGE('BS & FCF'!BO32:BR32)))-1),0) -> 0 | BT100: =IFERROR(-BT99/AVERAGE('BS & FCF'!BS32:BT32)*4,0) -> 0 | BU100: =IFERROR(-BU99/AVERAGE('BS & FCF'!BT32:BU32)*4,0) -> 0 | BV100: =IFERROR(-BV99/AVERAGE('BS & FCF'!BU32:BV32)*4,0) -> 0 | BW100: =IFERROR(-BW99/AVERAGE('BS & FCF'!BV32:BW32)*4,0) -> 0 | BX100: =IFERROR(((1-BX99/(AVERAGE('BS & FCF'!BT32:BW32)))-1),0) -> 0 | BY100: =IFERROR(-BY99/AVERAGE('BS & FCF'!BX32:BY32)*4,0) -> 0 | BZ100: =IFERROR(-BZ99/AVERAGE('BS & FCF'!BY32:BZ32)*4,0) -> 0 | CA100: =IFERROR(-CA99/AVERAGE('BS & FCF'!BZ32:CA32)*4,0) -> 0 | CB100: =IFERROR(-CB99/AVERAGE('BS & FCF'!CA32:CB32)*4,0) -> 0 | CC100: =IFERROR(((1-CC99/(AVERAGE('BS & FCF'!BY32:CB32)))-1),0) -> 0 | CD100: =IFERROR(-CD99/AVERAGE('BS & FCF'!CC32:CD32)*4,0) -> 0 | CE100: =IFERROR(-CE99/AVERAGE('BS & FCF'!CD32:CE32)*4,0) -> 0 | CF100: =CF101*Macro!CF12 -> 0 | CG100: =CG101*Macro!CG12 -> 0 | CH100: =IFERROR(((1-CH99/(AVERAGE('BS & FCF'!CD32:CG32)))-1),0) -> 0 | CI100: =CI101*Macro!CI12 -> 0 | CJ100: =CJ101*Macro!CJ12 -> 0 | CK100: =CK101*Macro!CK12 -> 0 | CL100: =CL101*Macro!CL12 -> 0 | CM100: =IFERROR(((1-CM99/(AVERAGE('BS & FCF'!CI32:CL32)))-1),0) -> 0 | CN100: =CN101*Macro!CN12 -> 0 | CO100: =CO101*Macro!CO12 -> 0 | CP100: =CP101*Macro!CP12 -> 0 | CQ100: =CQ101*Macro!CQ12 -> 0 | CR100: =IFERROR(((1-CR99/(AVERAGE('BS & FCF'!CN32:CQ32)))-1),0) -> 0 | CS100: =CS101*Macro!CS12 -> 0 | CT100: =CT101*Macro!CT12 -> 0 | CU100: =CU101*Macro!CU12 -> 0 | CV100: =CV101*Macro!CV12 -> 0 | CW100: =IFERROR(((1-CW99/(AVERAGE('BS & FCF'!CS32:CV32)))-1),0) -> 0 | CX100: =CX101*Macro!CX12 -> 0 | CY100: =CY101*Macro!CY12 -> 0 | CZ100: =CZ101*Macro!CZ12 -> 0 | DA100: =DA101*Macro!DA12 -> 0 | DB100: =IFERROR(((1-DB99/(AVERAGE('BS & FCF'!CX32:DA32)))-1),0) -> 0
A101: % of CDI | B101: =B100/Macro!B12 -> 0 | C101: =C100/Macro!C12 -> 0 | D101: =D100/Macro!D12 -> 0 | E101: =E100/Macro!E12 -> 0 | F101: =F100/Macro!F12 -> 0 | G101: =G100/Macro!G12 -> 0 | H101: =H100/Macro!H12 -> 0 | I101: =I100/Macro!I12 -> 0 | ... CE101: =CE100/Macro!CE12 -> 0 | CF101: =CE101 -> 0 | CG101: =CF101 -> 0 | CH101: =CH100/Macro!CH12 -> 0 | CI101: =CG101 -> 0 | CJ101: =CI101 -> 0 | CK101: =CJ101 -> 0 | CL101: =CK101 -> 0 | CM101: =CM100/Macro!CM12 -> 0 | CN101: =CL101 -> 0 | CO101: =CN101 -> 0 | CP101: =CO101 -> 0 | CQ101: =CP101 -> 0 | CR101: =CR100/Macro!CR12 -> 0 | CS101: =CQ101 -> 0 | CT101: =CS101 -> 0 | CU101: =CT101 -> 0 | CV101: =CU101 -> 0 | CW101: =CW100/Macro!CW12 -> 0 | CX101: =CV101 -> 0 | CY101: =CX101 -> 0 | CZ101: =CY101 -> 0 | DA101: =CZ101 -> 0 | DB101: =DB100/Macro!DB12 -> 0
A102: Financial expenses (ex-securitization) | B102: =B95-B99 -> 0 | C102: =C95-C99 -> 0 | D102: =D95-D99 -> 0 | E102: =E95-E99 -> 0 | F102: =SUM(B102:E102) -> 0 | G102: =G95-G99 -> 0 | H102: =H95-H99 -> 0 | I102: =I95-I99 -> 0 | J102: =J95-J99 -> 0 | K102: =SUM(G102:J102) -> 0 | L102: =L95-L99 -> 0 | M102: =M95-M99 -> 0 | N102: =N95-N99 -> 0 | O102: =O95-O99 -> 0 | P102: =SUM(L102:O102) -> 0 | Q102: =Q95-Q99 -> 0 | R102: =R95-R99 -> 0 | S102: =S95-S99 -> 0 | T102: =T95-T99 -> 0 | U102: =SUM(Q102:T102) -> 0 | V102: =V95-V99 -> 0 | W102: =W95-W99 -> 0 | X102: =X95-X99 -> 0 | Y102: =Y95-Y99 -> 0 | Z102: =SUM(V102:Y102) -> 0 | AA102: =AA95-AA99 -> 0 | AB102: =AB95-AB99 -> 0 | AC102: =AC95-AC99 -> 0 | AD102: =AD95-AD99 -> 0 | AE102: =SUM(AA102:AD102) -> 0 | AF102: =AF95-AF99 -> 0 | AG102: =AG95-AG99 -> 0 | AH102: =AH95-AH99 -> 0 | AI102: =AI95-AI99 -> 0 | AJ102: =SUM(AF102:AI102) -> 0 | AK102: =AK95-AK99 -> -766.165 | AL102: =AL95-AL99 -> -1045.351 | AM102: =AM95-AM99 -> -1353.653 | AN102: =AN95-AN99 -> -2114.608 | AO102: =SUM(AK102:AN102) -> -5279.777 | AP102: =AP95-AP99 -> -560.905 | AQ102: =AQ95-AQ99 -> -1107.788 | AR102: =AR95-AR99 -> -3741.392 | AS102: =AS95-AS99 -> -3259.349 | AT102: =SUM(AP102:AS102) -> -8669.434 | AU102: =AU95-AU99 -> -3465 | AV102: =AV95-AV99 -> -5215 | AW102: =AW95-AW99 -> -7768 | AX102: =AX95-AX99 -> -10241 | AY102: =SUM(AU102:AX102) -> -26689 | AZ102: =AZ95-AZ99 -> -4959 | BA102: =BA95-BA99 -> -5719 | BB102: =BB95-BB99 -> -6639 | BC102: =BC95-BC99 -> -6166 | BD102: =SUM(AZ102:BC102) -> -23483 | BE102: =BE95-BE99 -> -7256 | BF102: =BF95-BF99 -> -9300 | BG102: =BG95-BG99 -> -11427 | BH102: =BH95-BH99 -> -21731 | BI102: =SUM(BE102:BH102) -> -49714 | BJ102: =BJ95-BJ99 -> -17062 | BK102: =BK95-BK99 -> -22214 | BL102: =BL95-BL99 -> -22860 | BM102: =BM95-BM99 -> -26332 | BN102: =SUM(BJ102:BM102) -> -88468 | BO102: =BO95-BO99 -> -25672 | BP102: =BP95-BP99 -> -26026 | BQ102: =BQ95-BQ99 -> -23214 | BR102: =BR95-BR99 -> -25215 | BS102: =SUM(BO102:BR102) -> -100127 | BT102: =BT95-BT99 -> -24806 | BU102: =BU95-BU99 -> -31099 | BV102: =BV95-BV99 -> -39673 | BW102: =BW95-BW99 -> -41587 | BX102: =SUM(BT102:BW102) -> -137165 | BY102: =BY95-BY99 -> -51332 | BZ102: =BZ95-BZ99 -> -50846 | CA102: =CA95-CA99 -> -56062 | CB102: =CB95-CB99 -> -59596 | CC102: =SUM(BY102:CB102) -> -217836 | CD102: =CD95-CD99 -> -59802 | CE102: =CE95-CE99 -> -70288 | CF102: =-(AVERAGE('BS & FCF'!CE28:CF28)+AVERAGE('BS & FCF'!CE31:CF31))*((1+CF103)^(1/4)-1) -> -51675.015 | CG102: =-(AVERAGE('BS & FCF'!CF28:CG28)+AVERAGE('BS & FCF'!CF31:CG31))*((1+CG103)^(1/4)-1) -> -51884.836 | CH102: =SUM(CD102:CG102) -> -233649.85 | CI102: =-(AVERAGE('BS & FCF'!CH28:CI28)+AVERAGE('BS & FCF'!CH31:CI31))*((1+CI103)^(1/4)-1) -> -54494.949 | CJ102: =-(AVERAGE('BS & FCF'!CI28:CJ28)+AVERAGE('BS & FCF'!CI31:CJ31))*((1+CJ103)^(1/4)-1) -> -56010.795 | CK102: =-(AVERAGE('BS & FCF'!CJ28:CK28)+AVERAGE('BS & FCF'!CJ31:CK31))*((1+CK103)^(1/4)-1) -> -55551.908 | CL102: =-(AVERAGE('BS & FCF'!CK28:CL28)+AVERAGE('BS & FCF'!CK31:CL31))*((1+CL103)^(1/4)-1) -> -55906.806 | CM102: =SUM(CI102:CL102) -> -221964.46 | CN102: =-(AVERAGE('BS & FCF'!CM28:CN28)+AVERAGE('BS & FCF'!CM31:CN31))*((1+CN103)^(1/4)-1) -> -50990.067 | CO102: =-(AVERAGE('BS & FCF'!CN28:CO28)+AVERAGE('BS & FCF'!CN31:CO31))*((1+CO103)^(1/4)-1) -> -53434.378 | CP102: =-(AVERAGE('BS & FCF'!CO28:CP28)+AVERAGE('BS & FCF'!CO31:CP31))*((1+CP103)^(1/4)-1) -> -54177.072 | CQ102: =-(AVERAGE('BS & FCF'!CP28:CQ28)+AVERAGE('BS & FCF'!CP31:CQ31))*((1+CQ103)^(1/4)-1) -> -54440.294 | CR102: =SUM(CN102:CQ102) -> -213041.81 | CS102: =-(AVERAGE('BS & FCF'!CR28:CS28)+AVERAGE('BS & FCF'!CR31:CS31))*((1+CS103)^(1/4)-1) -> -56174.196 | CT102: =-(AVERAGE('BS & FCF'!CS28:CT28)+AVERAGE('BS & FCF'!CS31:CT31))*((1+CT103)^(1/4)-1) -> -58349.531 | CU102: =-(AVERAGE('BS & FCF'!CT28:CU28)+AVERAGE('BS & FCF'!CT31:CU31))*((1+CU103)^(1/4)-1) -> -58977.094 | CV102: =-(AVERAGE('BS & FCF'!CU28:CV28)+AVERAGE('BS & FCF'!CU31:CV31))*((1+CV103)^(1/4)-1) -> -58944.368 | CW102: =SUM(CS102:CV102) -> -232445.19 | CX102: =-(AVERAGE('BS & FCF'!CW28:CX28)+AVERAGE('BS & FCF'!CW31:CX31))*((1+CX103)^(1/4)-1) -> -60342.356 | CY102: =-(AVERAGE('BS & FCF'!CX28:CY28)+AVERAGE('BS & FCF'!CX31:CY31))*((1+CY103)^(1/4)-1) -> -62295.093 | CZ102: =-(AVERAGE('BS & FCF'!CY28:CZ28)+AVERAGE('BS & FCF'!CY31:CZ31))*((1+CZ103)^(1/4)-1) -> -62707.126 | DA102: =-(AVERAGE('BS & FCF'!CZ28:DA28)+AVERAGE('BS & FCF'!CZ31:DA31))*((1+DA103)^(1/4)-1) -> -62481.123 | DB102: =SUM(CX102:DA102) -> -247825.7
A103: Financial expenses rate | B103: =-B102/AVERAGE('BS & FCF'!A28:B28)*4 -> #DIV/0! | C103: =-C102/AVERAGE('BS & FCF'!B28:C28)*4 -> #DIV/0! | D103: =-D102/AVERAGE('BS & FCF'!C28:D28)*4 -> #DIV/0! | E103: =-E102/AVERAGE('BS & FCF'!D28:E28)*4 -> #DIV/0! | F103: =-F102/AVERAGE('BS & FCF'!B28:E28) -> #DIV/0! | G103: =-G102/AVERAGE('BS & FCF'!F28:G28)*4 -> #DIV/0! | H103: =-H102/AVERAGE('BS & FCF'!G28:H28)*4 -> #DIV/0! | I103: =-I102/AVERAGE('BS & FCF'!H28:I28)*4 -> #DIV/0! | J103: =-J102/AVERAGE('BS & FCF'!I28:J28)*4 -> #DIV/0! | K103: =-K102/AVERAGE('BS & FCF'!G28:J28) -> #DIV/0! | L103: =-L102/AVERAGE('BS & FCF'!K28:L28)*4 -> #DIV/0! | M103: =-M102/AVERAGE('BS & FCF'!L28:M28)*4 -> #DIV/0! | N103: =-N102/AVERAGE('BS & FCF'!M28:N28)*4 -> #DIV/0! | O103: =-O102/AVERAGE('BS & FCF'!N28:O28)*4 -> #DIV/0! | P103: =-P102/AVERAGE('BS & FCF'!L28:O28) -> #DIV/0! | Q103: =-Q102/AVERAGE('BS & FCF'!P28:Q28)*4 -> #DIV/0! | R103: =-R102/AVERAGE('BS & FCF'!Q28:R28)*4 -> #DIV/0! | S103: =-S102/AVERAGE('BS & FCF'!R28:S28)*4 -> #DIV/0! | T103: =-T102/AVERAGE('BS & FCF'!S28:T28)*4 -> #DIV/0! | U103: =-U102/AVERAGE('BS & FCF'!Q28:T28) -> #DIV/0! | V103: =-V102/AVERAGE('BS & FCF'!U28:V28)*4 -> #DIV/0! | W103: =-W102/AVERAGE('BS & FCF'!V28:W28)*4 -> #DIV/0! | X103: =-X102/AVERAGE('BS & FCF'!W28:X28)*4 -> #DIV/0! | Y103: =-Y102/AVERAGE('BS & FCF'!X28:Y28)*4 -> #DIV/0! | Z103: =-Z102/AVERAGE('BS & FCF'!V28:Y28) -> #DIV/0! | AA103: =-AA102/AVERAGE('BS & FCF'!Z28:AA28)*4 -> #DIV/0! | AB103: =-AB102/AVERAGE('BS & FCF'!AA28:AB28)*4 -> #DIV/0! | AC103: =-AC102/AVERAGE('BS & FCF'!AB28:AC28)*4 -> #DIV/0! | AD103: =-AD102/AVERAGE('BS & FCF'!AC28:AD28)*4 -> #DIV/0! | AE103: =-AE102/AVERAGE('BS & FCF'!AA28:AD28) -> #DIV/0! | AF103: =-AF102/AVERAGE('BS & FCF'!AE28:AF28)*4 -> #DIV/0! | AG103: =-AG102/AVERAGE('BS & FCF'!AF28:AG28)*4 -> #DIV/0! | AH103: =-AH102/AVERAGE('BS & FCF'!AG28:AH28)*4 -> #DIV/0! | AI103: =-AI102/AVERAGE('BS & FCF'!AH28:AI28)*4 -> #DIV/0! | AJ103: =-AJ102/AVERAGE('BS & FCF'!AF28:AI28) -> #DIV/0! | AK103: =-AK102/AVERAGE('BS & FCF'!AJ28:AK28)*4 -> 0.031252428 | AL103: =-AL102/AVERAGE('BS & FCF'!AK28:AL28)*4 -> 0.02169971 | AM103: =-AM102/AVERAGE('BS & FCF'!AL28:AM28)*4 -> 0.028732125 | AN103: =-AN102/AVERAGE('BS & FCF'!AM28:AN28)*4 -> 0.04508747 | AO103: =-AO102/AVERAGE('BS & FCF'!AK28:AN28) -> 0.027766781 | AP103: =-AP102/AVERAGE('BS & FCF'!AO28:AP28)*4 -> 0.013194544 | AQ103: =-AQ102/AVERAGE('BS & FCF'!AP28:AQ28)*4 -> 0.031529696 | AR103: =-AR102/AVERAGE('BS & FCF'!AQ28:AR28)*4 -> 0.085599462 | AS103: =-AS102/AVERAGE('BS & FCF'!AR28:AS28)*4 -> 0.059436092 | AT103: =-AT102/AVERAGE('BS & FCF'!AP28:AS28) -> 0.048178176 | AU103: =-AU102/AVERAGE('BS & FCF'!AT28:AU28)*4 -> 0.06378499 | AV103: =-AV102/AVERAGE('BS & FCF'!AU28:AV28)*4 -> 0.094991974 | AW103: =-AW102/AVERAGE('BS & FCF'!AV28:AW28)*4 -> 0.14433799 | AX103: =-AX102/AVERAGE('BS & FCF'!AW28:AX28)*4 -> 0.16540919 | AY103: =-AY102/AVERAGE('BS & FCF'!AU28:AX28) -> 0.11423863 | AZ103: =-AZ102/AVERAGE('BS & FCF'!AY28:AZ28)*4 -> 0.068130181 | BA103: =-BA102/AVERAGE('BS & FCF'!AZ28:BA28)*4 -> 0.072492541 | BB103: =-BB102/AVERAGE('BS & FCF'!BA28:BB28)*4 -> 0.082730518 | BC103: =-BC102/AVERAGE('BS & FCF'!BB28:BC28)*4 -> 0.084625876 | BD103: =-BD102/AVERAGE('BS & FCF'!AZ28:BC28) -> 0.077372568 | BE103: =-BE102/AVERAGE('BS & FCF'!BD28:BE28)*4 -> 0.10412347 | BF103: =-BF102/AVERAGE('BS & FCF'!BE28:BF28)*4 -> 0.13500664 | BG103: =-BG102/AVERAGE('BS & FCF'!BF28:BG28)*4 -> 0.13840026 | BH103: =-BH102/AVERAGE('BS & FCF'!BG28:BH28)*4 -> 0.22246792 | BI103: =-BI102/AVERAGE('BS & FCF'!BE28:BH28) -> 0.14923124 | BJ103: =-BJ102/AVERAGE('BS & FCF'!BI28:BJ28)*4 -> 0.17452723 | BK103: =-BK102/AVERAGE('BS & FCF'!BJ28:BK28)*4 -> 0.22499918 | BL103: =-BL102/AVERAGE('BS & FCF'!BK28:BL28)*4 -> 0.21389649 | BM103: =-BM102/AVERAGE('BS & FCF'!BL28:BM28)*4 -> 0.22481748 | BN103: =-BN102/AVERAGE('BS & FCF'!BJ28:BM28) -> 0.20492425 | BO103: =-BO102/AVERAGE('BS & FCF'!BN28:BO28)*4 -> 0.21493974 | BP103: =-BP102/AVERAGE('BS & FCF'!BO28:BP28)*4 -> 0.2137387 | BQ103: =-BQ102/AVERAGE('BS & FCF'!BP28:BQ28)*4 -> 0.16214772 | BR103: =-BR102/AVERAGE('BS & FCF'!BQ28:BR28)*4 -> 0.16021336 | BS103: =-BS102/AVERAGE('BS & FCF'!BO28:BR28) -> 0.17934305 | BT103: =-BT102/AVERAGE('BS & FCF'!BS28:BT28)*4 -> 0.16329916 | BU103: =-BU102/AVERAGE('BS & FCF'!BT28:BU28)*4 -> 0.14785918 | BV103: =-BV102/AVERAGE('BS & FCF'!BU28:BV28)*4 -> 0.1453714 | BW103: =-BW102/AVERAGE('BS & FCF'!BV28:BW28)*4 -> 0.15926798 | BX103: =-BX102/AVERAGE('BS & FCF'!BT28:BW28) -> 0.14547393 | BY103: =-BY102/AVERAGE('BS & FCF'!BX28:BY28)*4 -> 0.18097006 | BZ103: =-BZ102/AVERAGE('BS & FCF'!BY28:BZ28)*4 -> 0.15730089 | CA103: =-CA102/AVERAGE('BS & FCF'!BZ28:CA28)*4 -> 0.17078418 | CB103: =-CB102/AVERAGE('BS & FCF'!CA28:CB28)*4 -> 0.17040373 | CC103: =-CC102/AVERAGE('BS & FCF'!BY28:CB28) -> 0.16184566 | CD103: =-CD102/AVERAGE('BS & FCF'!CC28:CD28)*4 -> 0.16933263 | CE103: =-CE102/AVERAGE('BS & FCF'!CD28:CE28)*4 -> 0.20875782 | CF103: =CF104*Macro!CF12 -> 0.16195833 | CG103: =CG104*Macro!CG12 -> 0.161 | CH103: =-CH102/AVERAGE('BS & FCF'!CD28:CG28) -> 0.17235534 | CI103: =CI104*Macro!CI12 -> 0.161 | CJ103: =CJ104*Macro!CJ12 -> 0.15333333 | CK103: =CK104*Macro!CK12 -> 0.14566667 | CL103: =CL104*Macro!CL12 -> 0.14375 | CM103: =-CM102/AVERAGE('BS & FCF'!CI28:CL28) -> 0.13960673 | CN103: =CN104*Macro!CN12 -> 0.125 | CO103: =CO104*Macro!CO12 -> 0.125 | CP103: =CP104*Macro!CP12 -> 0.125 | CQ103: =CQ104*Macro!CQ12 -> 0.125 | CR103: =-CR102/AVERAGE('BS & FCF'!CN28:CQ28) -> 0.1180342 | CS103: =CS104*Macro!CS12 -> 0.125 | CT103: =CT104*Macro!CT12 -> 0.125 | CU103: =CU104*Macro!CU12 -> 0.125 | CV103: =CV104*Macro!CV12 -> 0.125 | CW103: =-CW102/AVERAGE('BS & FCF'!CS28:CV28) -> 0.11844252 | CX103: =CX104*Macro!CX12 -> 0.125 | CY103: =CY104*Macro!CY12 -> 0.125 | CZ103: =CZ104*Macro!CZ12 -> 0.125 | DA103: =DA104*Macro!DA12 -> 0.125 | DB103: =-DB102/AVERAGE('BS & FCF'!CX28:DA28) -> 0.11870719
A104: % of CDI | B104: =B103/Macro!B12 -> #DIV/0! | C104: =C103/Macro!C12 -> #DIV/0! | D104: =D103/Macro!D12 -> #DIV/0! | E104: =E103/Macro!E12 -> #DIV/0! | F104: =F103/Macro!F12 -> #DIV/0! | G104: =G103/Macro!G12 -> #DIV/0! | H104: =H103/Macro!H12 -> #DIV/0! | I104: =I103/Macro!I12 -> #DIV/0! | ... CE104: =CE103/Macro!CE12 -> 1.4480311 | CF104: 1.15 | CG104: =CF104 -> 1.15 | CH104: =CH103/Macro!CH12 -> 1.2007338 | CI104: =CG104 -> 1.15 | CJ104: =CI104 -> 1.15 | CK104: =CJ104 -> 1.15 | CL104: =CK104 -> 1.15 | CM104: =CM103/Macro!CM12 -> 1.0636703 | CN104: 1 | CO104: =CN104 -> 1 | CP104: =CO104 -> 1 | CQ104: =CP104 -> 1 | CR104: =CR103/Macro!CR12 -> 0.9442736 | CS104: =CQ104 -> 1 | CT104: =CS104 -> 1 | CU104: =CT104 -> 1 | CV104: =CU104 -> 1 | CW104: =CW103/Macro!CW12 -> 0.94754016 | CX104: =CV104 -> 1 | CY104: =CX104 -> 1 | CZ104: =CY104 -> 1 | DA104: =CZ104 -> 1 | DB104: =DB103/Macro!DB12 -> 0.94965753
...

Sheet BS & FCF
A2: =Valuation!$A$2 -> CURY3 | TP R$44/sh
A3: Balance sheet (R$000') | B3: =Macro!B$3 -> 1Q10 | C3: =Macro!C$3 -> 2Q10 | D3: =Macro!D$3 -> 3Q10 | E3: =Macro!E$3 -> 4Q10 | F3: =Macro!F$3 -> 2010 | G3: =Macro!G$3 -> 1Q11 | H3: =Macro!H$3 -> 2Q11 | I3: =Macro!I$3 -> 3Q11 | ... DB3: =Macro!DB$3 -> 2030E
A4: Total assets | B4: =B5+B20 -> 0 | C4: =C5+C20 -> 0 | D4: =D5+D20 -> 0 | E4: =E5+E20 -> 0 | F4: =F5+F20 -> 0 | G4: =G5+G20 -> 0 | H4: =H5+H20 -> 0 | I4: =I5+I20 -> 0 | ... DB4: =DB5+DB20 -> 9118805.1
A5: Current assets | B5: =SUM(B6:B8)+B12+SUM(B16:B19) -> 0 | C5: =SUM(C6:C8)+C12+SUM(C16:C19) -> 0 | D5: =SUM(D6:D8)+D12+SUM(D16:D19) -> 0 | E5: =SUM(E6:E8)+E12+SUM(E16:E19) -> 0 | F5: =SUM(F6:F8)+F12+SUM(F16:F19) -> 0 | G5: =SUM(G6:G8)+G12+SUM(G16:G19) -> 0 | H5: =SUM(H6:H8)+H12+SUM(H16:H19) -> 0 | I5: =SUM(I6:I8)+I12+SUM(I16:I19) -> 0 | ... DB5: =SUM(DB6:DB8)+DB12+SUM(DB16:DB19) -> 9023820.4
A6: Cash and equivalents | F6: =E6 -> 0 | K6: =J6 -> 0 | P6: =O6 -> 0 | U6: =T6 -> 0 | Z6: =Y6 -> 0 | AE6: =AD6 -> 0 | AJ6: =AI6 -> 0 | AK6: =142500+591 -> 143091 | AL6: 119847 | AM6: 123876 | AN6: =143946+54560 -> 198506 | AO6: =AN6 -> 198506 | AP6: 143831 | AQ6: 145875 | AR6: 203590 | AS6: =171395+79566 -> 250961 | AT6: =AS6 -> 250961 | AU6: 239346 | AV6: 269315 | AW6: =236221+46693 -> 282914 | AX6: =249496+64847 -> 314343 | AY6: =AX6 -> 314343 | AZ6: =254528+71000 -> 325528 | BA6: =358082+67765 -> 425847 | BB6: =529672+80177 -> 609849 | BC6: =291125+139773 -> 430898 | BD6: =BC6 -> 430898 | BE6: =329971+106673 -> 436644 | BF6: =390596+101391 -> 491987 | BG6: =414633+140294 -> 554927 | BH6: =375963+218524 -> 594487 | BI6: =BH6 -> 594487 | BJ6: =360921+241647 -> 602568 | BK6: =454074+225903 -> 679977 | BL6: =394522+240386 -> 634908 | BM6: =562264+227162 -> 789426 | BN6: =BM6 -> 789426 | BO6: =470159+259664 -> 729823 | BP6: =556696+278694 -> 835390 | BQ6: =730072+379003 -> 1109075 | BR6: =643630+348639 -> 992269 | BS6: =BR6 -> 992269 | BT6: =647595+364073 -> 1011668 | BU6: =889522+668498 -> 1558020 | BV6: =760259+664956 -> 1425215 | BW6: =975224+441012 -> 1416236 | BX6: =BW6 -> 1416236 | BY6: =1031724+512082 -> 1543806 | BZ6: =1035262+495613 -> 1530875 | CA6: =1287134+486069 -> 1773203 | CB6: =1355394+435543 -> 1790937 | CC6: =CB6 -> 1790937 | CD6: =1397709+359601 -> 1757310 | CE6: =1375239+258467 -> 1633706 | CF6: =CF88 -> 1751397 | CG6: =CG88 -> 1872524 | CH6: =CG6 -> 1872524 | CI6: =CI88 -> 2277922.1 | CJ6: =CJ88 -> 2131009.5 | CK6: =CK88 -> 2156367.3 | CL6: =CL88 -> 2185896.3 | CM6: =CL6 -> 2185896.3 | CN6: =CN88 -> 2698568.7 | CO6: =CO88 -> 2377558.3 | CP6: =CP88 -> 2372447.8 | CQ6: =CQ88 -> 2363477.7 | CR6: =CQ6 -> 2363477.7 | CS6: =CS88 -> 2917468.4 | CT6: =CT88 -> 2529513.6 | CU6: =CU88 -> 2517040.8 | CV6: =CV88 -> 2513932.1 | CW6: =CV6 -> 2513932.1 | CX6: =CX88 -> 3102924.8 | CY6: =CY88 -> 2691940.3 | CZ6: =CZ88 -> 2663510.2 | DA6: =DA88 -> 2638844.7 | DB6: =DA6 -> 2638844.7
A7: Receivables from related parties | F7: =E7 -> 0 | K7: =J7 -> 0 | P7: =O7 -> 0 | U7: =T7 -> 0 | Z7: =Y7 -> 0 | AE7: =AD7 -> 0 | AJ7: =AI7 -> 0 | AK7: 6612 | AL7: 0 | AM7: 17783 | AN7: 15827 | AO7: =AN7 -> 15827 | AP7: 848 | AQ7: 1649 | AR7: 0 | AS7: 16864 | AT7: =AS7 -> 16864 | AU7: 0 | AV7: 9167 | AW7: 30287 | AX7: =35414 -> 35414 | AY7: =AX7 -> 35414 | AZ7: 41381 | BA7: 41232 | BB7: =32688 -> 32688 | BC7: 12206 | BD7: =BC7 -> 12206 | BE7: 12223 | BF7: 4771 | BG7: 4788 | BH7: 4321 | BI7: =BH7 -> 4321 | BJ7: 4445 | BK7: 4724 | BL7: 4355 | BM7: 5073 | BN7: =BM7 -> 5073 | BO7: 4990 | BP7: 9220 | BQ7: 9055 | BR7: 12877 | BS7: =BR7 -> 12877 | BT7: 17035 | BU7: 20868 | BV7: 18436 | BW7: 19811 | BX7: =BW7 -> 19811 | BY7: 15765 | BZ7: 19451 | CA7: 12336 | CB7: 11893 | CC7: =CB7 -> 11893 | CD7: 17865 | CE7: 18291 | CF7: =CE7 -> 18291 | CG7: =CF7 -> 18291 | CH7: =CG7 -> 18291 | CI7: =CH7 -> 18291 | CJ7: =CI7 -> 18291 | CK7: =CJ7 -> 18291 | CL7: =CK7 -> 18291 | CM7: =CL7 -> 18291 | ... DB7: =DA7 -> 18291
A8: Accounts receivables from clients | B8: =B9+B10 -> 0 | C8: =C9+C10 -> 0 | D8: =D9+D10 -> 0 | E8: =E9+E10 -> 0 | F8: =F9+F10 -> 0 | G8: =G9+G10 -> 0 | H8: =H9+H10 -> 0 | I8: =I9+I10 -> 0 | ... AT8: =AT9+AT10 -> 557065 | AU8: =AU9+AU10+AU11 -> 543697 | AV8: =AV9+AV10+AV11 -> 592779 | AW8: =AW9+AW10+AW11 -> 685769 | AX8: =AX9+AX10+AX11 -> 659335 | AY8: =AY9+AY10+AY11 -> 659335 | AZ8: =AZ9+AZ10+AZ11 -> 605454 | BA8: =BA9+BA10+BA11 -> 685673 | BB8: =BB9+BB10+BB11 -> 831054 | ... DB8: =DB9+DB10+DB11 -> 4408886.4
A9: Perfomed contracts | F9: =E9 -> 0 | K9: =J9 -> 0 | P9: =O9 -> 0 | U9: =T9 -> 0 | Z9: =Y9 -> 0 | AE9: =AD9 -> 0 | AJ9: =AI9 -> 0 | AK9: 0 | AL9: 0 | AM9: 0 | AN9: 0 | AO9: =AN9 -> 0 | AP9: 0 | AQ9: 0 | AR9: 0 | AS9: 0 | AT9: =AS9 -> 0 | AU9: 0 | AV9: 0 | AW9: 0 | AX9: 0 | AY9: =AX9 -> 0 | AZ9: 0 | BA9: 0 | BB9: 0 | BC9: 0 | BD9: =BC9 -> 0 | BE9: 0 | BF9: 0 | BG9: 0 | BH9: 0 | BI9: =BH9 -> 0 | BJ9: 0 | BK9: 0 | BL9: 0 | BM9: 0 | BN9: =BM9 -> 0 | BO9: 0 | BP9: 0 | BQ9: 0 | BR9: 0 | BS9: =BR9 -> 0 | BT9: 0 | BU9: 0 | BV9: 0 | BW9: 0 | BX9: =BW9 -> 0 | BY9: 0 | BZ9: 0 | CA9: 0 | CB9: 0 | CC9: =CB9 -> 0 | CD9: 0 | CE9: 0 | CF9: =CE9 -> 0 | CG9: =CF9 -> 0 | CH9: =CG9 -> 0 | CI9: =CG9 -> 0 | CJ9: =CI9 -> 0 | CK9: =CJ9 -> 0 | CL9: =CK9 -> 0 | CM9: =CL9 -> 0 | CN9: =CL9 -> 0 | CO9: =CN9 -> 0 | CP9: =CO9 -> 0 | CQ9: =CP9 -> 0 | CR9: =CQ9 -> 0 | CS9: =CQ9 -> 0 | CT9: =CS9 -> 0 | CU9: =CT9 -> 0 | CV9: =CU9 -> 0 | CW9: =CV9 -> 0 | CX9: =CV9 -> 0 | CY9: =CX9 -> 0 | CZ9: =CY9 -> 0 | DA9: =CZ9 -> 0 | DB9: =DA9 -> 0
A10: Under-construction contracts | F10: =E10 -> 0 | K10: =J10 -> 0 | P10: =O10 -> 0 | U10: =T10 -> 0 | Z10: =Y10 -> 0 | AE10: =AD10 -> 0 | AJ10: =AI10 -> 0 | AK10: =642834+160043 -> 802877 | AL10: =646570+178988 -> 825558 | AM10: =705210+178357 -> 883567 | AN10: =680292+85006 -> 765298 | AO10: =AN10 -> 765298 | AP10: =583693+97078 -> 680771 | AQ10: =654913+105260 -> 760173 | AR10: =641647+93309 -> 734956 | AS10: =417334+139731 -> 557065 | AT10: =AS10 -> 557065 | AU10: =457533+86164 -> 543697 | AV10: =504111+88668 -> 592779 | AW10: =581653+104116 -> 685769 | AX10: =533437+125898-AX11 -> 556863 | AY10: =AX10 -> 556863 | AZ10: =448111+157343-AZ11 -> 527013 | BA10: =528330+157343-BA11 -> 594707 | BB10: =647241+183813-BB11 -> 745284 | BC10: =627243+172079-BC11 -> 713804 | BD10: =BC10 -> 713804 | BE10: =770187+167826-BE11 -> 866972 | BF10: =835343+213781-BF11 -> 974152 | BG10: =700282+406000-BG11 -> 1025135 | BH10: =731349+546316-BH11 -> 1186992 | BI10: =BH10 -> 1186992 | BJ10: =996524+634055-BJ11 -> 1549111 | BK10: =1004386+552406-BK11 -> 1482423 | BL10: =870147+529554-BL11 -> 1335180 | BM10: =681536+497726-BM11 -> 1128332 | BN10: =BM10 -> 1128332 | BO10: =677724+372912-BO11 -> 998907 | BP10: =678261+407428-BP11 -> 1032846 | BQ10: =489221+591170-BQ11 -> 1080391 | BR10: =481218+609583-BR11 -> 1090801 | BS10: =BR10 -> 1090801 | BT10: =649909+635299-BT11 -> 1285208 | BU10: =494497+884755-BU11 -> 1379252 | BV10: =371958+1082272-BV11 -> 1454230 | BW10: =345783+1091454-BW11 -> 1437237 | BX10: =BW10 -> 1437237 | BY10: =602208+1294500-BY11 -> 1896708 | BZ10: =552497+1581210-BZ11 -> 2133707 | CA10: =475943-CA9-CA11+1722835 -> 2198778 | CB10: =286215+1871728-CB11 -> 2157943 | CC10: =CB10 -> 2157943 | CD10: =536930+2012450-CD11 -> 2549380 | CE10: =580014+2142326-CE11 -> 2722340 | CF10: =CF99 -> 2749247.1 | CG10: =CG99 -> 2808598.5 | CH10: =CG10 -> 2808598.5 | CI10: =CI99 -> 2968201.5 | CJ10: =CJ99 -> 3156901.1 | CK10: =CK99 -> 3330522 | CL10: =CL99 -> 3446827.2 | CM10: =CL10 -> 3446827.2 | CN10: =CN99 -> 3564094.9 | CO10: =CO99 -> 3644230.1 | CP10: =CP99 -> 3723636.3 | CQ10: =CQ99 -> 3825212.2 | CR10: =CQ10 -> 3825212.2 | CS10: =CS99 -> 3916353.3 | CT10: =CT99 -> 4000898.7 | CU10: =CU99 -> 4078653.8 | CV10: =CV99 -> 4149887.9 | CW10: =CV10 -> 4149887.9 | CX10: =CX99 -> 4217937.6 | CY10: =CY99 -> 4284847 | CZ10: =CZ99 -> 4348767.5 | DA10: =DA99 -> 4408886.4 | DB10: =DA10 -> 4408886.4
A11: Client financing / other | F11: =E11 -> 0 | K11: =J11 -> 0 | P11: =O11 -> 0 | U11: =T11 -> 0 | Z11: =Y11 -> 0 | AE11: =AD11 -> 0 | AJ11: =AI11 -> 0 | AO11: =AN11 -> 0 | AT11: =AS11 -> 0 | AX11: =95525+6947 -> 102472 | AY11: =AX11 -> 102472 | AZ11: =77017+1424 -> 78441 | BA11: =89542+1424 -> 90966 | BB11: =84346+1424 -> 85770 | BC11: 85518 | BD11: =BC11 -> 85518 | BE11: 71041 | BF11: 74972 | BG11: 81147 | BH11: 90673 | BI11: =BH11 -> 90673 | BJ11: 81468 | BK11: 74369 | BL11: 64521 | BM11: 50930 | BN11: =BM11 -> 50930 | BO11: 51729 | BP11: 52843 | BQ11: 0 | BR11: 0 | BS11: =BR11 -> 0 | BT11: 0 | BU11: 0 | BV11: 0 | BW11: 0 | BX11: =BW11 -> 0 | BY11: 0 | BZ11: 0 | CA11: 0 | CB11: 0 | CC11: =CB11 -> 0 | CD11: 0 | CE11: 0 | CF11: =CE11-CE11/(4*2.5)+Operating!CF49*0%*60% -> 0 | CG11: =CF11-CF11/(4*2.5)+Operating!CG49*0%*60% -> 0 | CH11: =CG11 -> 0 | CI11: =CH11-CH11/(4*2.5)+Operating!CI49*0%*60% -> 0 | CJ11: =CI11-CI11/(4*2.5)+Operating!CJ49*0%*60% -> 0 | CK11: =CJ11-CJ11/(4*2.5)+Operating!CK49*0%*60% -> 0 | CL11: =CK11-CK11/(4*2.5)+Operating!CL49*0%*60% -> 0 | CM11: =CL11 -> 0 | CN11: =CM11-CM11/(4*2.5)+Operating!CN49*0%*60% -> 0 | CO11: =CN11-CN11/(4*2.5)+Operating!CO49*0%*60% -> 0 | CP11: =CO11-CO11/(4*2.5)+Operating!CP49*0%*60% -> 0 | CQ11: =CP11-CP11/(4*2.5)+Operating!CQ49*0%*60% -> 0 | CR11: =CQ11 -> 0 | CS11: =CR11-CR11/(4*2.5)+Operating!CS49*0%*60% -> 0 | CT11: =CS11-CS11/(4*2.5)+Operating!CT49*0%*60% -> 0 | CU11: =CT11-CT11/(4*2.5)+Operating!CU49*0%*60% -> 0 | CV11: =CU11-CU11/(4*2.5)+Operating!CV49*0%*60% -> 0 | CW11: =CV11 -> 0 | CX11: =CW11-CW11/(4*2.5)+Operating!CX49*0%*60% -> 0 | CY11: =CX11-CX11/(4*2.5)+Operating!CY49*0%*60% -> 0 | CZ11: =CY11-CY11/(4*2.5)+Operating!CZ49*0%*60% -> 0 | DA11: =CZ11-CZ11/(4*2.5)+Operating!DA49*0%*60% -> 0 | DB11: =DA11 -> 0
