Workbook
Name _1_0BS_minor: #REF!
Name _10_0IS_straightpref: #REF!
Name _106J–Ï__íÇ: #REF!,#REF!,#REF!,#REF!,#REF!,#REF!,#REF!,#REF!,#REF!,#REF!,#REF!,#REF!
Name _107_0: #REF!,#REF!,#REF!,#REF!,#REF!,#REF!,#REF!,#REF!,#REF!,#REF!,#REF!,#REF!,#REF!,#REF!
Name _108_0_0BS_minor: #REF!
Name _109_0_0CF_minor: #REF!
Name _11_0Interc_Rev_LD_: #REF!
Name _110_0_0IS_convpref: #REF!
Name _111_0_0IS_intconv: #REF!
Name _112_0_0IS_intexist: #REF!
Name _113_0_0IS_minor: #REF!
Name _114_0_0IS_straightpref: #REF!
Name _115_0_0IS_synerg: #REF!
Name _116_0IS_synerg: #REF!
Name _117_0s: #REF!
Name _118_0Sfu: #REF!
Name _119_1: #REF!
Name _12_0Interc_Rev_Loc_: #REF!
Name _120_10: #REF!
Name _121_11: #REF!
Name _122_12: #REF!
Name _123_13: #REF!
Name _124_14: #REF!
Name _125_15: #REF!
Name _126_16: #REF!
Name _127_17: #REF!
Name _128_18: #REF!
Name _129_2: #REF!
Name _13_0OutGoingTraf: #REF!
Name _130_3: #REF!
Name _131_4: #REF!
Name _132_5: #REF!
Name _133_6: #REF!
Name _134p0t: #REF!,#REF!,#REF!,#REF!,#REF!
Name _135ÿ_0CAPEX: #REF!
Name _136ÿ_0CAPEX_: #REF!
Name _137ÿ_0CAPEX_billing_VMS_: #REF!
Name _138ÿ_0CAPEX_Civil_Wo: #REF!
Name _139ÿ_0CAPEX_computer_softw: #REF!
Name _14_0Perc_Reg_of: #REF!
Name _140ÿ_0CAPEX_Equipm: #REF!
Name _141ÿ_0CAPEX_Gateway_Equipm: #REF!
Name _142ÿ_0CAPEX_Licence_: #REF!
Name _143ÿ_0CAPEX_Microw: #REF!
Name _144ÿ_0CAPEX_office_furnit: #REF!
Name _145ÿ_0CAPEX_Subscri: #REF!
Name _146ÿ_0Cum._Invest_bill: #REF!
Name _147ÿ_0Depr_base_bill: #REF!
Name _148ÿ_0Depr_base_equipm: #REF!
Name _149ÿ_0Depr_bill: #REF!
Name _15_0BS_minor: #REF!
Name _150ÿ_0Depr_civil_wo: #REF!
Name _151ÿ_0Depr_computer_softw: #REF!
Name _152ÿ_0Depr_equipm: #REF!
Name _153ÿ_0Depr_lice: #REF!
Name _154ÿ_0Depr_office_furnit: #REF!
Name _155ÿ_0GSM_In: #REF!
Name _156ÿ_0Invest: #REF!
Name _157ÿ_0Invest_: #REF!
Name _158ÿ_0Invest_Gatew: #REF!

Sheet Macro
A2: =DCF!$A$2 -> Cury - TP: R$48
A3: Status | B3: =B4&RIGHT(B5,2)&B6 -> 1Q04 | C3: =C4&RIGHT(C5,2)&C6 -> 2Q04 | D3: =D4&RIGHT(D5,2)&D6 -> 3Q04 | E3: =E4&RIGHT(E5,2)&E6 -> 4Q04 | F3: =F4&RIGHT(F5,2)&F6 -> 2004 | G3: =G4&RIGHT(G5,2)&G6 -> 1Q05 | H3: =H4&RIGHT(H5,2)&H6 -> 2Q05 | I3: =I4&RIGHT(I5,2)&I6 -> 3Q05 | ... EF3: =EF4&RIGHT(EF5,2)&EF6 -> 2030E
A4: Quarter | B4: 1Q | C4: 2Q | D4: 3Q | E4: 4Q | F4: 20 | G4: 1Q | H4: 2Q | I4: 3Q | J4: 4Q | K4: 20 | L4: 1Q | M4: 2Q | N4: 3Q | O4: 4Q | P4: 20 | Q4: 1Q | R4: 2Q | S4: 3Q | T4: 4Q | U4: 20 | V4: 1Q | W4: 2Q | X4: 3Q | Y4: 4Q | Z4: 20 | AA4: 1Q | AB4: 2Q | AC4: 3Q | AD4: 4Q | AE4: 20 | AF4: 1Q | AG4: 2Q | AH4: 3Q | AI4: 4Q | AJ4: 20 | AK4: 1Q | AL4: 2Q | AM4: 3Q | AN4: 4Q | AO4: 20 | AP4: 1Q | AQ4: 2Q | AR4: 3Q | AS4: 4Q | AT4: 20 | AU4: 1Q | AV4: 2Q | AW4: 3Q | AX4: 4Q | AY4: 20 | AZ4: 1Q | BA4: 2Q | BB4: 3Q | BC4: 4Q | BD4: 20 | BE4: 1Q | BF4: 2Q | BG4: 3Q | BH4: 4Q | BI4: 20 | BJ4: 1Q | BK4: 2Q | BL4: 3Q | BM4: 4Q | BN4: 20 | BO4: 1Q | BP4: 2Q | BQ4: 3Q | BR4: 4Q | BS4: 20 | BT4: 1Q | BU4: 2Q | BV4: 3Q | BW4: 4Q | BX4: 20 | BY4: 1Q | BZ4: 2Q | CA4: 3Q | CB4: 4Q | CC4: 20 | CD4: 1Q | CE4: 2Q | CF4: 3Q | CG4: 4Q | CH4: 20 | CI4: 1Q | CJ4: 2Q | CK4: 3Q | CL4: 4Q | CM4: 20 | CN4: 1Q | CO4: 2Q | CP4: 3Q | CQ4: 4Q | CR4: 20 | CS4: 1Q | CT4: 2Q | CU4: 3Q | CV4: 4Q | CW4: 20 | CX4: 1Q | CY4: 2Q | CZ4: 3Q | DA4: 4Q | DB4: 20 | DC4: 1Q | DD4: 2Q | DE4: 3Q | DF4: 4Q | DG4: 20 | DH4: 1Q | DI4: 2Q | DJ4: 3Q | DK4: 4Q | DL4: 20 | DM4: 1Q | DN4: 2Q | DO4: 3Q | DP4: 4Q | DQ4: 20 | DR4: 1Q | DS4: 2Q | DT4: 3Q | DU4: 4Q | DV4: 20 | DW4: 1Q | DX4: 2Q | DY4: 3Q | DZ4: 4Q | EA4: 20 | EB4: 1Q | EC4: 2Q | ED4: 3Q | EE4: 4Q | EF4: 20
A5: Year | B5: 2004 | C5: 2004 | D5: 2004 | E5: 2004 | F5: =E5 -> 2004 | G5: =B5+1 -> 2005 | H5: =C5+1 -> 2005 | I5: =D5+1 -> 2005 | J5: =E5+1 -> 2005 | K5: =J5 -> 2005 | L5: =G5+1 -> 2006 | M5: =H5+1 -> 2006 | N5: =I5+1 -> 2006 | O5: =J5+1 -> 2006 | P5: =O5 -> 2006 | Q5: =L5+1 -> 2007 | R5: =M5+1 -> 2007 | S5: =N5+1 -> 2007 | T5: =O5+1 -> 2007 | U5: =T5 -> 2007 | V5: =Q5+1 -> 2008 | W5: =R5+1 -> 2008 | X5: =S5+1 -> 2008 | Y5: =T5+1 -> 2008 | Z5: =Y5 -> 2008 | AA5: =V5+1 -> 2009 | AB5: =W5+1 -> 2009 | AC5: =X5+1 -> 2009 | AD5: =Y5+1 -> 2009 | AE5: =AD5 -> 2009 | AF5: =AA5+1 -> 2010 | AG5: =AB5+1 -> 2010 | AH5: =AC5+1 -> 2010 | AI5: =AD5+1 -> 2010 | AJ5: =AI5 -> 2010 | AK5: =AF5+1 -> 2011 | AL5: =AG5+1 -> 2011 | AM5: =AH5+1 -> 2011 | AN5: =AI5+1 -> 2011 | AO5: =AN5 -> 2011 | AP5: =AK5+1 -> 2012 | AQ5: =AL5+1 -> 2012 | AR5: =AM5+1 -> 2012 | AS5: =AN5+1 -> 2012 | AT5: =AO5+1 -> 2012 | AU5: =AP5+1 -> 2013 | AV5: =AQ5+1 -> 2013 | AW5: =AR5+1 -> 2013 | ... EF5: =EA5+1 -> 2030
A6: Actual/Estimate | DJ6: E | DK6: E | DL6: E | DM6: E | DN6: E | DO6: E | DP6: E | DQ6: E | DR6: E | DS6: E | DT6: E | DU6: E | DV6: E | DW6: E | DX6: E | DY6: E | DZ6: E | EA6: E | EB6: E | EC6: E | ED6: E | EE6: E | EF6: E
A7: Days in Quarter | B7: 91 | C7: 91 | D7: 92 | E7: 92 | F7: =SUM(B7:E7) -> 366 | G7: 90 | H7: 91 | I7: 92 | J7: 92 | K7: =SUM(G7:J7) -> 365 | L7: 90 | M7: 91 | N7: 92 | O7: 92 | P7: =SUM(L7:O7) -> 365 | Q7: 90 | R7: 91 | S7: 92 | T7: 92 | U7: =SUM(Q7:T7) -> 365 | V7: 91 | W7: 91 | X7: 92 | Y7: 92 | Z7: =SUM(V7:Y7) -> 366 | AA7: 90 | AB7: 91 | AC7: 92 | AD7: 92 | AE7: =SUM(AA7:AD7) -> 365 | AF7: 90 | AG7: 91 | AH7: 92 | AI7: 92 | AJ7: =SUM(AF7:AI7) -> 365 | AK7: 90 | AL7: 91 | AM7: 92 | AN7: 92 | AO7: =SUM(AK7:AN7) -> 365 | AP7: 90 | AQ7: 91 | AR7: 92 | AS7: 92 | AT7: 366 | AU7: 90 | AV7: 91 | AW7: 92 | AX7: 92 | AY7: =SUM(AU7:AX7) -> 365 | AZ7: 90 | BA7: 91 | BB7: 92 | BC7: 92 | BD7: =SUM(AZ7:BC7) -> 365 | BE7: 90 | BF7: 91 | BG7: 92 | BH7: 92 | BI7: =SUM(BE7:BH7) -> 365 | BJ7: 90 | BK7: 91 | BL7: 92 | BM7: 92 | BN7: =SUM(BJ7:BM7) -> 365 | BO7: 90 | BP7: 91 | BQ7: 92 | BR7: 92 | BS7: =SUM(BO7:BR7) -> 365 | BT7: 90 | BU7: 91 | BV7: 92 | BW7: 92 | BX7: =SUM(BT7:BW7) -> 365 | BY7: 90 | BZ7: 91 | CA7: 92 | CB7: 92 | CC7: =SUM(BY7:CB7) -> 365 | CD7: 90 | CE7: 91 | CF7: 92 | CG7: 92 | CH7: =SUM(CD7:CG7) -> 365 | CI7: 90 | CJ7: 91 | CK7: 92 | CL7: 92 | CM7: =SUM(CI7:CL7) -> 365 | CN7: 90 | CO7: 91 | CP7: 92 | CQ7: 92 | CR7: =SUM(CN7:CQ7) -> 365 | CS7: 90 | CT7: 91 | CU7: 92 | CV7: 92 | CW7: =SUM(CS7:CV7) -> 365 | CX7: 90 | CY7: 91 | CZ7: 92 | DA7: 92 | DB7: =SUM(CX7:DA7) -> 365 | DC7: 90 | DD7: 91 | DE7: 92 | DF7: 92 | DG7: =SUM(DC7:DF7) -> 365 | DH7: 90 | DI7: 91 | DJ7: 92 | DK7: 92 | DL7: =SUM(DH7:DK7) -> 365 | DM7: 90 | DN7: 91 | DO7: 92 | DP7: 92 | DQ7: =SUM(DM7:DP7) -> 365 | DR7: 90 | DS7: 91 | DT7: 92 | DU7: 92 | DV7: =SUM(DR7:DU7) -> 365 | DW7: 90 | DX7: 91 | DY7: 92 | DZ7: 92 | EA7: =SUM(DW7:DZ7) -> 365 | EB7: 90 | EC7: 91 | ED7: 92 | EE7: 92 | EF7: =SUM(EB7:EE7) -> 365
B9: =B$3 -> 1Q04 | C9: =C$3 -> 2Q04 | D9: =D$3 -> 3Q04 | E9: =E$3 -> 4Q04 | F9: =F$3 -> 2004 | G9: =G$3 -> 1Q05 | H9: =H$3 -> 2Q05 | I9: =I$3 -> 3Q05 | ... EF9: =EF$3 -> 2030E
A10: GDP Growth | B10: 0.018625076 | C10: 0.034978624 | D10: 0.046182359 | E10: 0.05690445 | F10: 0.05690445 | G10: 0.050839899 | H10: 0.040117662 | I10: 0.035368516 | J10: 0.031478279 | K10: 0.031478279 | L10: 0.035123174 | M10: 0.03287402 | N10: 0.035871317 | O10: 0.039296141 | P10: 0.039296141 | Q10: 0.041838309 | R10: 0.05276138 | S10: 0.0558906 | T10: 0.060872371 | U10: 0.060872371 | V10: 0.063938236 | W10: 0.063785439 | X10: 0.066447177 | Y10: 0.051439409 | Z10: 0.051439409 | AA10: 0.029907003 | AB10: 0.0094328172 | AC10: -0.010336182 | AD10: -0.0017527142 | AE10: -0.0017527142 | AF10: 0.092714294 | AG10: 0.091562714 | AH10: 0.067385174 | AI10: 0.050367589 | AJ10: 0.075 | AK10: 0.04235654 | AL10: 0.03314358 | AM10: 0.021219664 | AN10: 0.013664596 | AO10: 0.027325092 | AP10: 0.007973 | AQ10: 0.005509 | AR10: 0.009444 | AS10: 0.01825 | AT10: 0.01 | AU10: 0.0189 | AV10: 0.0346 | AW10: 0.0243 | AX10: 0.0217 | AY10: 0.025 | AZ10: 0.0191 | BA10: 0.004 | BB10: 0.011 | BC10: 0.01 | BD10: 0.0014458389 | BE10: -0.0081656208 | BF10: -0.017777081 | BG10: -0.02738854 | BH10: -0.037 | BI10: -0.037 | BJ10: -0.03475 | BK10: -0.0325 | BL10: -0.03025 | BM10: -0.028 | BN10: -0.028 | BO10: 0.005 | BP10: 0.005 | BQ10: 0.005 | BR10: 0.005 | BS10: 0.01 | BT10: 0.0032837896 | BU10: 0.0032837896 | BV10: 0.0032837896 | BW10: 0.0032837896 | BX10: 0.0132 | BY10: 0.0027387285 | BZ10: 0.0027387285 | CA10: 0.0027387285 | CB10: 0.0027387285 | CC10: 0.011 | CD10: -0.01 | CE10: -0.01 | CF10: -0.01 | CG10: -0.01 | CH10: -0.041 | CI10: 0.03 | CJ10: 0.03 | CK10: 0.03 | CL10: 0.03 | CM10: 0.046 | CN10: 0.02 | CO10: 0.02 | CP10: 0.02 | CQ10: 0.02 | CR10: 0.03 | CS10: 0.02 | CT10: 0.02 | CU10: 0.02 | CV10: 0.02 | CW10: 0.029 | CX10: 0.02 | CY10: 0.02 | CZ10: 0.02 | DA10: 0.02 | DB10: 0.034 | DC10: 0.02 | DD10: 0.02 | DE10: 0.02 | DF10: 0.02 | DG10: 0.02 | DH10: 0.02 | DI10: 0.02 | DJ10: 0.02 | DK10: 0.02 | DL10: 0.02 | DM10: 0.02 | DN10: 0.02 | DO10: 0.02 | DP10: 0.02 | DQ10: 0.02 | DR10: 0.02 | DS10: 0.02 | DT10: 0.02 | DU10: 0.02 | DV10: 0.02 | DW10: 0.02 | DX10: 0.02 | DY10: 0.02 | DZ10: 0.02 | EA10: 0.02 | EB10: 0.02 | EC10: 0.02 | ED10: 0.02 | EE10: 0.02 | EF10: 0.02
A11: R$/US$ EoP | B11: 2.9086 | C11: 3.1075 | D11: 2.8586 | E11: 2.6544 | F11: 2.6544 | G11: 2.6662 | H11: 2.3504 | I11: 2.2222 | J11: 2.3407 | K11: 2.3407 | L11: 2.1724 | M11: 2.1643 | N11: 2.1742 | O11: 2.138 | P11: 2.138 | Q11: 2.0504 | R11: 1.9262 | S11: 1.8389 | T11: 1.7713 | U11: 1.7713 | V11: 1.7491 | W11: 1.5919 | X11: 1.9143 | Y11: 2.337 | Z11: 2.337 | AA11: 2.3152 | AB11: 1.9516 | AC11: 1.7781 | AD11: 1.7412 | AE11: 1.7412 | AF11: 1.781 | AG11: 1.8015 | AH11: 1.6942 | AI11: 1.7161 | AJ11: 1.6662 | AK11: 1.6318 | AL11: 1.5633 | AM11: 1.8793 | AN11: 1.8668 | AO11: 1.8758 | AP11: 1.82 | AQ11: 2.02 | AR11: 2.03 | AS11: 2.04 | AT11: 2.04 | AU11: 2.0138 | AV11: 2.2156 | AW11: 2.23 | AX11: 2.3426 | AY11: 2.34 | AZ11: 2.263 | BA11: 2.29 | BB11: 2.34 | BC11: 2.4 | BD11: 2.6562 | BE11: 3.208 | BF11: 3.1026 | BG11: 3.9729 | BH11: 3.9048 | BI11: 3.8 | BJ11: 3.5589 | BK11: 3.2098 | BL11: 3.2462 | BM11: 3.2591 | BN11: 3.2591 | BO11: 3.2 | BP11: 3.12 | BQ11: 3.31 | BR11: 3.308 | BS11: 3.308 | BT11: 3.3238 | BU11: 3.8558 | BV11: 4.0039 | BW11: 3.88 | BX11: 3.88 | BY11: 3.9017478 | BZ11: 3.9236175 | CA11: 3.9456098 | CB11: 3.9677253 | CC11: 4.0307 | CD11: 5 | CE11: 5.0084136 | CF11: 5.0168413 | CG11: 5.0252832 | CH11: 4.8 | CI11: 4.872642 | CJ11: 4.9463833 | CK11: 5.0212406 | CL11: 5.0972308 | CM11: 5.5805 | CN11: 5.6316783 | CO11: 5.683326 | CP11: 5.7354473 | CQ11: 5.7880467 | CR11: 5.2177 | CS11: 5.2508591 | CT11: 5.284229 | CU11: 5.3178109 | CV11: 5.3516063 | CW11: 4.8513 | CX11: 4.8845909 | CY11: 4.9181102 | CZ11: 4.9518595 | DA11: 4.9858404 | DB11: 6.1923 | DC11: 5.9623333 | DD11: 5.7323667 | DE11: 5.6173833 | DF11: 5.5024 | DG11: 5.5024 | DH11: 5.5291054 | DI11: 5.5559404 | DJ11: 5.5829056 | DK11: 5.6100017 | DL11: 5.6100017 | DM11: 5.6372293 | DN11: 5.6645891 | DO11: 5.6920817 | DP11: 5.7197077 | DQ11: 5.7197077 | DR11: 5.7474677 | DS11: 5.7753625 | DT11: 5.8033927 | DU11: 5.8315589 | DV11: 5.8315589 | DW11: 5.8598619 | DX11: 5.8883021 | DY11: 5.9168805 | DZ11: 5.9455975 | EA11: 5.9455975 | EB11: 5.9744539 | EC11: 6.0034503 | ED11: 6.0325875 | EE11: 6.0618661 | EF11: 6.0618661
A12: Sequential Change | B12: 0.0067146615 | C12: 0.068383415 | D12: -0.080096541 | E12: -0.071433569 | F12: -0.081268171 | G12: 0.0044454491 | H12: -0.11844573 | I12: -0.054543907 | J12: 0.053325533 | K12: -0.11818113 | L12: -0.071901568 | M12: -0.0037285951 | N12: 0.0045742272 | O12: -0.016649802 | P12: -0.086598026 | Q12: -0.040972872 | R12: -0.060573547 | S12: -0.045322396 | T12: -0.036761107 | U12: -0.17151543 | V12: -0.012533168 | W12: -0.089874793 | X12: 0.20252528 | Y12: 0.22081178 | Z12: 0.31936995 | AA12: -0.0093281985 | AB12: -0.15704907 | AC12: -0.088901414 | AD12: -0.020752489 | AE12: -0.25494223 | AF12: -0.0069287358 | AG12: -0.0069770782 | AH12: -0.0070260998 | AI12: -0.0070758152 | AJ12: -0.027714943 | AK12: -0.049123011 | AL12: -0.041978184 | AM12: 0.20213651 | AN12: -0.0066514128 | AO12: 0.12579522 | AP12: -0.025069638 | AQ12: 0.10989011 | AR12: 0.004950495 | AS12: 0.0049261084 | AT12: 0.087535985 | AU12: -0.012843137 | AV12: 0.10020856 | AW12: 0.0064993681 | AX12: 0.050493274 | AY12: 0.14705882 | AZ12: -0.033979339 | BA12: 0.011931065 | BB12: 0.021834061 | BC12: 0.025641026 | BD12: 0.13512821 | BE12: 0.33666667 | BF12: -0.032855362 | BG12: 0.28050667 | BH12: -0.017141131 | BI12: 0.43061515 | BJ12: -0.088583282 | BK12: -0.098092107 | BL12: 0.01134027 | BM12: 0.0039738771 | BN12: -0.14234209 | BO12: -0.018133841 | BP12: -0.025 | BQ12: 0.060897436 | BR12: -0.00060422961 | BS12: 0.015004142 | BT12: 0.0047762999 | BU12: 0.16005777 | BV12: 0.038409669 | BW12: -0.030944829 | BX12: 0.17291415 | BY12: 0.0056051018 | BZ12: 0.0056051018 | CA12: 0.0056051018 | CB12: 0.0056051018 | CC12: 0.038840206 | CD12: 0.0056051018 | CE12: 0.0056051018 | CF12: 0.0056051018 | CG12: 0.0056051018 | CH12: 0.19086015 | CI12: 0.0056051018 | CJ12: 0.0056051018 | CK12: 0.0056051018 | CL12: 0.0056051018 | CM12: 0.16260417 | CN12: 0.0056051018 | CO12: 0.0056051018 | CP12: 0.0056051018 | CQ12: 0.0056051018 | CR12: -0.065012096 | CS12: 0.0056051018 | CT12: 0.0056051018 | CU12: 0.0056051018 | CV12: 0.0056051018 | CW12: -0.070222512 | CX12: 0.0056051018 | CY12: 0.0056051018 | CZ12: 0.0056051018 | DA12: 0.0056051018 | DB12: 0.27642075 | DC12: 0.0056051018 | DD12: 0.0056051018 | DE12: 0.0056051018 | DF12: 0.0056051018 | DG12: -0.11141256 | DH12: 0.0056051018 | DI12: 0.0056051018 | DJ12: 0.0056051018 | DK12: 0.0056051018 | DL12: 0.019555417 | DM12: 0.0056051018 | DN12: 0.0056051018 | DO12: 0.0056051018 | DP12: 0.0056051018 | DQ12: 0.019555417 | DR12: 0.0056051018 | DS12: 0.0056051018 | DT12: 0.0056051018 | DU12: 0.0056051018 | DV12: 0.019555417 | DW12: 0.0056051018 | DX12: 0.0056051018 | DY12: 0.0056051018 | DZ12: 0.0056051018 | EA12: 0.019555417 | EB12: 0.0056051018 | EC12: 0.0056051018 | ED12: 0.0056051018 | EE12: 0.0056051018 | EF12: 0.019555417
A13: R$/US$ Average | B13: 2.8958667 | C13: 3.0451667 | D13: 2.9769333 | E13: 2.7857 | F13: 2.9259167 | G13: 2.6651667 | H13: 2.4818333 | I13: 2.3428333 | J13: 2.2509333 | K13: 2.4351917 | L13: 2.1959333 | M13: 2.1852333 | N13: 2.1713 | O13: 2.1520333 | P13: 2.176125 | Q13: 2.1078167 | R13: 1.9818333 | S13: 1.9161333 | T13: 1.7856333 | U13: 1.9478542 | V13: 1.7365333 | W13: 1.6561 | X13: 1.6677667 | Y13: 2.2778667 | Z13: 1.8345667 | AA13: 2.3113 | AB13: 2.0748 | AC13: 1.8659333 | AD13: 1.7383667 | AE13: 1.9976 | AF13: 1.8416333 | AG13: 1.8131905 | AH13: 1.7595636 | AI13: 1.71333 | AJ13: 1.7593 | AK13: 1.6668306 | AL13: 1.5953516 | AM13: 1.6363954 | AN13: 1.8029258 | AO13: 1.6746 | AP13: 1.7687873 | AQ13: 1.9633 | AR13: 2.0279 | AS13: 2.06 | AT13: 1.9549968 | AU13: 1.9957333 | AV13: 2.07 | AW13: 2.2883 | AX13: 2.2765 | AY13: 2.1576333 | AZ13: 2.3639965 | BA13: 2.268832 | BB13: 2.33 | BC13: 2.38 | BD13: 2.3357071 | BE13: 2.8691 | BF13: 3.0709 | BG13: 3.5399 | BH13: 3.8471 | BI13: 3.33175 | BJ13: 3.67945 | BK13: 3.38435 | BL13: 3.228 | BM13: 3.25265 | BN13: 3.3861125 | BO13: 3.22955 | BP13: 3.16 | BQ13: 3.215 | BR13: 3.309 | BS13: 3.2283875 | BT13: 3.3159 | BU13: 3.5898 | BV13: 3.92985 | BW13: 3.94195 | BX13: 3.694375 | BY13: 3.8908739 | BZ13: 3.9126826 | CA13: 3.9346136 | CB13: 3.9566675 | CC13: 3.9237094 | CD13: 4.51535 | CE13: 5.0042068 | CF13: 5.0126274 | CG13: 5.0210622 | CH13: 4.8883116 | CI13: 4.836321 | CJ13: 4.9095126 | CK13: 4.983812 | CL13: 5.0592357 | CM13: 4.9472203 | CN13: 5.6060892 | CO13: 5.6575022 | CP13: 5.7093867 | CQ13: 5.761747 | CR13: 5.6836813 | CS13: 5.2342796 | CT13: 5.2675441 | CU13: 5.3010199 | CV13: 5.3347086 | CW13: 5.284388 | CX13: 4.8679454 | CY13: 4.9013505 | CZ13: 4.9349848 | DA13: 4.96885 | DB13: 4.9182827 | DC13: 6.0773167 | DD13: 5.84735 | DE13: 5.674875 | DF13: 5.5598917 | DG13: 5.7898583 | DH13: 5.5157527 | DI13: 5.5425229 | DJ13: 5.569423 | DK13: 5.5964537 | DL13: 5.5560381 | DM13: 5.6236155 | DN13: 5.6509092 | DO13: 5.6783354 | DP13: 5.7058947 | DQ13: 5.6646887 | DR13: 5.7335877 | DS13: 5.7614151 | DT13: 5.7893776 | DU13: 5.8174758 | DV13: 5.7754641 | DW13: 5.8457104 | DX13: 5.874082 | DY13: 5.9025913 | DZ13: 5.931239 | EA13: 5.8884057 | EB13: 5.9600257 | EC13: 5.9889521 | ED13: 6.0180189 | EE13: 6.0472268 | EF13: 6.0035559
A14: Sequential Change | B14: -0.0014941498 | C14: 0.051556241 | D14: -0.022407093 | E14: -0.064238366 | F14: -0.049497285 | G14: -0.043268598 | H14: -0.068788694 | I14: -0.056006984 | J14: -0.039226008 | K14: -0.16771667 | L14: -0.024434309 | M14: -0.0048726434 | N14: -0.0063761307 | O14: -0.0088733324 | P14: -0.10638451 | Q14: -0.02054646 | R14: -0.059769588 | S14: -0.033151123 | T14: -0.068105908 | U14: -0.10489785 | V14: -0.027497247 | W14: -0.046318335 | X14: 0.0070446632 | Y14: 0.36581856 | Z14: -0.058160155 | AA14: 0.014677476 | AB14: -0.10232337 | AC14: -0.10066834 | AD14: -0.068366144 | AE14: 0.088867489 | AF14: -0.04434007 | AG14: -0.006952823 | AH14: -0.0070015032 | AI14: -0.0070508699 | AJ14: -0.15792685 | AK14: -0.027139754 | AL14: -0.0428832 | AM14: 0.025727101 | AN14: 0.10176662 | AO14: -0.048144148 | AP14: -0.018935058 | AQ14: 0.10996952 | AR14: 0.032903784 | AS14: 0.015829183 | AT14: 0.16744108 | AU14: -0.031197411 | AV14: 0.03721272 | AW14: 0.10545894 | AX14: -0.0051566665 | AY14: 0.10365056 | AZ14: 0.038434655 | BA14: -0.040255779 | BB14: 0.02696014 | BC14: 0.021459227 | BD14: 0.082531995 | BE14: 0.2055042 | BF14: 0.070335645 | BG14: 0.15272396 | BH14: 0.086782112 | BI14: 0.42644169 | BJ14: -0.043578286 | BK14: -0.080202198 | BL14: -0.046197941 | BM14: 0.0076363073 | BN14: 0.016316499 | BO14: -0.0071019015 | BP14: -0.021535508 | BQ14: 0.017405063 | BR14: 0.029237947 | BS14: -0.046579963 | BT14: 0.027107186 | BU14: 0.082602009 | BV14: 0.094726726 | BW14: 0.0030789979 | BX14: 0.14434063 | BY14: 0.0030789979 | BZ14: 0.0030789979 | CA14: 0.0030789979 | CB14: 0.0030789979 | CC14: 0.06207665 | CD14: 0.0030789979 | CE14: 0.0030789979 | CF14: 0.0030789979 | CG14: 0.0030789979 | CH14: 0.24583935 | CI14: 0.0030789979 | CJ14: 0.0030789979 | CK14: 0.0030789979 | CL14: 0.0030789979 | CM14: 0.012050932 | CN14: 0.0030789979 | CO14: 0.0030789979 | CP14: 0.0030789979 | CQ14: 0.0030789979 | CR14: 0.14886358 | CS14: 0.0030789979 | CT14: 0.0030789979 | CU14: 0.0030789979 | CV14: 0.0030789979 | CW14: -0.07025257 | CX14: 0.0030789979 | CY14: 0.0030789979 | CZ14: 0.0030789979 | DA14: 0.0030789979 | DB14: -0.069280557 | DC14: 0.0030789979 | DD14: 0.0030789979 | DE14: 0.0030789979 | DF14: 0.0030789979 | DG14: 0.17721138 | DH14: 0.0030789979 | DI14: 0.0030789979 | DJ14: 0.0030789979 | DK14: 0.0030789979 | DL14: -0.040384455 | DM14: 0.0030789979 | DN14: 0.0030789979 | DO14: 0.0030789979 | DP14: 0.0030789979 | DQ14: 0.019555417 | DR14: 0.0030789979 | DS14: 0.0030789979 | DT14: 0.0030789979 | DU14: 0.0030789979 | DV14: 0.019555417 | DW14: 0.0030789979 | DX14: 0.0030789979 | DY14: 0.0030789979 | DZ14: 0.0030789979 | EA14: 0.019555417 | EB14: 0.0030789979 | EC14: 0.0030789979 | ED14: 0.0030789979 | EE14: 0.0030789979 | EF14: 0.019555417
A15: IGP-M | B15: 0.027238816 | C15: 0.039508457 | D15: 0.032535493 | E15: 0.019621757 | F15: 0.12419987 | G15: 0.015470449 | H15: 0.0019530032 | I15: -0.015125547 | J15: 0.0099229976 | K15: 0.012007603 | L15: 0.0069795279 | M15: 0.0070809203 | N15: 0.0084226293 | O15: 0.015474403 | P15: 0.03847626 | Q15: 0.011139726 | R15: 0.0034022404 | S15: 0.025690334 | T15: 0.035379965 | U15: 0.077462737 | V15: 0.023778077 | W15: 0.04336869 | X15: 0.015459458 | Y15: 0.012319512 | Z15: 0.098054313 | AA15: -0.0091980353 | AB15: -0.0031967511 | AC15: -0.003717635 | AD15: -0.0011034013 | AE15: -0.017122754 | AF15: 0.027745179 | AG15: 0.028359009 | AH15: 0.020817483 | AI15: 0.031817201 | AJ15: 0.113 | AK15: 0.024312626 | AL15: 0.0069680368 | AM15: 0.0097144444 | AN15: 0.0091198891 | AO15: 0.05096813 | AP15: 0.0061573961 | AQ15: 0.025570914 | AR15: 0.037862169 | AS15: 0.0066992596 | AT15: 0.0782 | AU15: 0.0084 | AV15: 0.009 | AW15: 0.0192 | AX15: 0.0176 | AY15: 0.055 | AZ15: 0.025462165 | BA15: 0 | BB15: 0.014 | BC15: 0.012 | BD15: 0.0369 | BE15: 0.020221661 | BF15: 0.022654151 | BG15: 0.019311654 | BH15: 0.039455778 | BI15: 0.107 | BJ15: 0.029665632 | BK15: 0.028562255 | BL15: 0.0051997258 | BM15: 0.0067134119 | BN15: 0.071729083 | BO15: -0.0013025427 | BP15: -0.0013025427 | BQ15: -0.0013025427 | BR15: -0.0013025427 | BS15: -0.0052 | BT15: 0.018244601 | BU15: 0.018244601 | BV15: 0.018244601 | BW15: 0.018244601 | BX15: 0.075 | BY15: 0.017813112 | BZ15: 0.017813112 | CA15: 0.017813112 | CB15: 0.017813112 | CC15: 0.073179 | CD15: 0.053413777 | CE15: 0.053413777 | CF15: 0.053413777 | CG15: 0.053413777 | CH15: 0.231391 | CI15: 0.041760503 | CJ15: 0.041760503 | CK15: 0.041760503 | CL15: 0.041760503 | CM15: 0.1778 | CN15: 0.013355073 | CO15: 0.013355073 | CP15: 0.013355073 | CQ15: 0.013355073 | CR15: 0.0545 | CS15: -0.0080466017 | CT15: -0.0080466017 | CU15: -0.0080466017 | CV15: -0.0080466017 | CW15: -0.0318 | CX15: 0.015963658 | CY15: 0.015963658 | CZ15: 0.015963658 | DA15: 0.015963658 | DB15: 0.0654 | DC15: -0.0026353997 | DD15: -0.0026353997 | DE15: -0.0026353997 | DF15: -0.0026353997 | DG15: -0.0105 | DH15: 0.01106499 | DI15: 0.01106499 | DJ15: 0.01106499 | DK15: 0.01106499 | DL15: 0.045 | DM15: 0.01106499 | DN15: 0.01106499 | DO15: 0.01106499 | DP15: 0.01106499 | DQ15: 0.045 | DR15: 0.01106499 | DS15: 0.01106499 | DT15: 0.01106499 | DU15: 0.01106499 | DV15: 0.045 | DW15: 0.01106499 | DX15: 0.01106499 | DY15: 0.01106499 | DZ15: 0.01106499 | EA15: 0.045 | EB15: 0.01106499 | EC15: 0.01106499 | ED15: 0.01106499 | EE15: 0.01106499 | EF15: 0.045
A16: IPCA | B16: 0.018510968 | C16: 0.015981484 | D16: 0.019415797 | E16: 0.020027801 | F16: 0.076006441 | G16: 0.017905799 | H16: 0.013439901 | I16: 0.0077189649 | J16: 0.016688199 | K16: 0.056897333 | L16: 0.014367294 | M16: 0.00099558559 | N16: 0.004505992 | O16: 0.011240999 | P16: 0.03141775 | Q16: 0.012551992 | R16: 0.0081218596 | S16: 0.0089240803 | T16: 0.014261804 | U16: 0.044573304 | V16: 0.015176027 | W16: 0.020942932 | X16: 0.010735939 | Y16: 0.010938925 | Z16: 0.059023134 | AA16: 0.012347053 | AB16: 0.013156841 | AC16: 0.0063129686 | AD16: 0.010637052 | AE16: 0.043120283 | AF16: 0.020638364 | AG16: 0.01002451 | AH16: 0.0050022902 | AI16: 0.022262182 | AJ16: 0.0591 | AK16: 0.02439696 | AL16: 0.013956003 | AM16: 0.010634041 | AN16: 0.014569972 | AO16: 0.065033527 | AP16: 0.01224539 | AQ16: 0.0108289 | AR16: 0.01416561 | AS16: 0.01992 | AT16: 0.0584 | AU16: 0.019420463 | AV16: 0.011844323 | AW16: 0.0062 | AX16: 0.0204 | AY16: 0.059 | AZ16: 0.021752379 | BA16: 0.0154 | BB16: 0.0066 | BC16: 0.0191 | BD16: 0.0641 | BE16: 0.038277997 | BF16: 0.022567505 | BG16: 0.013859074 | BH16: 0.028159295 | BI16: 0.107 | BJ16: 0.026208101 | BK16: 0.017496397 | BL16: 0.010430578 | BM16: 0.007417894 | BN16: 0.062880551 | BO16: 0.0072947902 | BP16: 0.0072947902 | BQ16: 0.0072947902 | BR16: 0.0072947902 | BS16: 0.0295 | BT16: 0.0092459757 | BU16: 0.0092459757 | BV16: 0.0092459757 | BW16: 0.0092459757 | BX16: 0.0375 | BY16: 0.010605102 | BZ16: 0.010605102 | CA16: 0.010605102 | CB16: 0.010605102 | CC16: 0.0431 | CD16: 0.0066827131 | CE16: 0.0066827131 | CF16: 0.0066827131 | CG16: 0.0066827131 | CH16: 0.027 | CI16: 0.020133746 | CJ16: 0.020133746 | CK16: 0.020133746 | CL16: 0.020133746 | CM16: 0.083 | CN16: 0.014170922 | CO16: 0.014170922 | CP16: 0.014170922 | CQ16: 0.014170922 | CR16: 0.0579 | CS16: 0.011355123 | CT16: 0.011355123 | CU16: 0.011355123 | CV16: 0.011355123 | CW16: 0.0462 | CX16: 0.011862256 | CY16: 0.011862256 | CZ16: 0.011862256 | DA16: 0.011862256 | DB16: 0.0483 | DC16: 0.010483974 | DD16: 0.010483974 | DE16: 0.010483974 | DF16: 0.010483974 | DG16: 0.0426 | DH16: 0.0098534065 | DI16: 0.0098534065 | DJ16: 0.0098534065 | DK16: 0.0098534065 | DL16: 0.04 | DM16: 0.0098534065 | DN16: 0.0098534065 | DO16: 0.0098534065 | DP16: 0.0098534065 | DQ16: 0.04 | DR16: 0.0098534065 | DS16: 0.0098534065 | DT16: 0.0098534065 | DU16: 0.0098534065 | DV16: 0.04 | DW16: 0.0098534065 | DX16: 0.0098534065 | DY16: 0.0098534065 | DZ16: 0.0098534065 | EA16: 0.04 | EB16: 0.0098534065 | EC16: 0.0098534065 | ED16: 0.0098534065 | EE16: 0.0098534065 | EF16: 0.04
A17: CDI | B17: 0.15891187 | C17: 0.15435042 | D17: 0.16350861 | E17: 0.16948771 | F17: 0.16155114 | G17: 0.1778254 | H17: 0.19514372 | I17: 0.20317559 | J17: 0.1838907 | K17: 0.18996837 | L17: 0.17179576 | M17: 0.15115659 | N17: 0.14797492 | O17: 0.13084663 | P17: 0.15035162 | Q17: 0.12681933 | R17: 0.1205915 | S17: 0.11615637 | T17: 0.10910245 | U17: 0.11814874 | V17: 0.10734371 | W17: 0.11439214 | X17: 0.13443413 | Y17: 0.1393809 | Z17: 0.12380815 | AA17: 0.12058908 | AB17: 0.098592428 | AC17: 0.08990374 | AD17: 0.086015281 | AE17: 0.098694035 | AF17: 0.0875 | AG17: 0.0975 | AH17: 0.1075 | AI17: 0.1075 | AJ17: 0.1 | AK17: 0.11333333 | AL17: 0.12012097 | AM17: 0.12280769 | AN17: 0.11415385 | AO17: 0.11708333 | AP17: 0.1025 | AQ17: 0.086666667 | AR17: 0.076666667 | AS17: 0.0725 | AT17: 0.08458 | AU17: 0.0725 | AV17: 0.078333333 | AW17: 0.088333333 | AX17: 0.098333333 | AY17: 0.0844 | AZ17: 0.10666667 | BA17: 0.11 | BB17: 0.11 | BC17: 0.11 | BD17: 0.11020833 | BE17: 0.1225 | BF17: 0.1325 | BG17: 0.14 | BH17: 0.1425 | BI17: 0.13583333 | BJ17: 0.1425 | BK17: 0.1425 | BL17: 0.1425 | BM17: 0.14 | BN17: 0.14 | BO17: 0.13 | BP17: 0.1125 | BQ17: 0.095 | BR17: 0.07875 | BS17: 0.095625 | BT17: 0.069166667 | BU17: 0.0675 | BV17: 0.065833333 | BW17: 0.065 | BX17: 0.06625 | BY17: 0.0625 | BZ17: 0.0575 | CA17: 0.0525 | CB17: 0.0475 | CC17: 0.0525 | CD17: 0.04125 | CE17: 0.03375 | CF17: 0.02625 | CG17: 0.0225 | CH17: 0.028125 | CI17: 0.031875 | CJ17: 0.050625 | CK17: 0.069375 | CL17: 0.088125 | CM17: 0.069375 | CN17: 0.1075 | CO17: 0.125 | CP17: 0.135 | CQ17: 0.1375 | CR17: 0.13125 | CS17: 0.135 | CT17: 0.13 | CU17: 0.125 | CV17: 0.12 | CW17: 0.125 | CX17: 0.114375 | CY17: 0.108125 | CZ17: 0.10625 | DA17: 0.115 | DB17: 0.1115625 | DC17: 0.1325 | DD17: 0.14625 | DE17: 0.15 | DF17: 0.15 | DG17: 0.148125 | DH17: 0.1475 | DI17: 0.1425 | DJ17: 0.1375 | DK17: 0.1325 | DL17: 0.1375 | DM17: 0.13 | DN17: 0.13 | DO17: 0.13 | DP17: 0.13 | DQ17: 0.13 | DR17: 0.13 | DS17: 0.13 | DT17: 0.13 | DU17: 0.13 | DV17: 0.13 | DW17: 0.13 | DX17: 0.13 | DY17: 0.13 | DZ17: 0.13 | EA17: 0.13 | EB17: 0.13 | EC17: 0.13 | ED17: 0.13 | EE17: 0.13 | EF17: 0.13
A18: INCC (lag) | U18: =U15 -> 0.077462737 | V18: =V15 -> 0.023778077 | W18: =W15 -> 0.04336869 | X18: =X15 -> 0.015459458 | Y18: =Y15 -> 0.012319512 | Z18: =Z15 -> 0.098054313 | AA18: 0.007 | AB18: 0.008 | AC18: 0.015 | AD18: 0.005 | AE18: =AE19 -> 0.035 | AF18: 0.010336071 | AG18: 0.01967952 | AH18: 0.033810947 | AI18: 0.0054064582 | AJ18: =(1+AF18)*(1+AG18)*(1+AH18)*(1+AI18)-1 -> 0.070809838 | AK18: 0.014508921 | AL18: 0.0177 | AM18: 0.0376 | AN18: 0.005 | AO18: =(1+AK18)*(1+AL18)*(1+AM18)*(1+AN18)-1 -> 0.076642873 | AP18: 0.017256562 | AQ18: 0.015616554 | AR18: 0.0329 | AS18: 0.0069 | AT18: =(1+AP18)*(1+AQ18)*(1+AR18)*(1+AS18)-1 -> 0.074496214 | AU18: 0.0114 | AV18: 0.0184 | AW18: 0.035 | AX18: =AW15 -> 0.0192 | AY18: =(1+AU18)*(1+AV18)*(1+AW18)*(1+AX18)-1 -> 0.086528456 | AZ18: =AX15 -> 0.0176 | BA18: =AZ15*0.8 -> 0.020369732 | BB18: 0.02 | BC18: =BB15 -> 0.014 | BD18: =(1+AZ18)*(1+BA18)*(1+BB18)*(1+BC18)-1 -> 0.073922131 | BE18: =BC15 -> 0.012 | BF18: =BE15 -> 0.020221661 | BG18: =BF15*1.5 -> 0.033981227 | BH18: =BG15 -> 0.019311654 | BI18: =(1+BE18)*(1+BF18)*(1+BG18)*(1+BH18)-1 -> 0.088164857 | BJ18: =BH15 -> 0.039455778 | BK18: =BJ15 -> 0.029665632 | BL18: =BK15*1.5 -> 0.042843382 | BM18: =BL15 -> 0.0051997258 | BN18: =(1+BJ18)*(1+BK18)*(1+BL18)*(1+BM18)-1 -> 0.12195047 | BO18: =BM15 -> 0.0067134119 | BP18: =BO15 -> -0.0013025427 | BQ18: =BP15*1.5 -> -0.0019538141 | BR18: =BQ15 -> -0.0013025427 | BS18: =(1+BO18)*(1+BP18)*(1+BQ18)*(1+BR18)-1 -> 0.0021307353 | BT18: =BR15 -> -0.0013025427 | BU18: =BT15 -> 0.018244601 | BV18: =BU15*1.5 -> 0.027366902 | BW18: =BV15 -> 0.018244601 | BX18: =(1+BT18)*(1+BU18)*(1+BV18)*(1+BW18)-1 -> 0.063809211 | BY18: =BW15 -> 0.018244601 | BZ18: =BY15 -> 0.017813112 | CA18: =BZ15*1.5 -> 0.026719668 | CB18: =CA15 -> 0.017813112 | CC18: =(1+BY18)*(1+BZ18)*(1+CA18)*(1+CB18)-1 -> 0.083028987 | CD18: =CB15 -> 0.017813112 | CE18: =CD15 -> 0.053413777 | CF18: =CE15*1.5 -> 0.080120665 | CG18: =CF15 -> 0.053413777 | CH18: =(1+CD18)*(1+CE18)*(1+CF18)*(1+CG18)-1 -> 0.21993953 | CI18: =CG15 -> 0.053413777 | CJ18: =CI15 -> 0.041760503 | CK18: =CJ15*1.5 -> 0.062640754 | CL18: =CK15 -> 0.041760503 | CM18: =(1+CI18)*(1+CJ18)*(1+CK18)*(1+CL18)-1 -> 0.21484602 | CN18: =CL15 -> 0.041760503 | CO18: =CN15 -> 0.013355073 | CP18: =CO15*1.5 -> 0.02003261 | CQ18: =CP15 -> 0.013355073 | CR18: =(1+CN18)*(1+CO18)*(1+CP18)*(1+CQ18)-1 -> 0.091202207 | CS18: =CQ15 -> 0.013355073 | CT18: =CS15 -> -0.0080466017 | CU18: =CT15*1.5 -> -0.012069903 | CV18: =CU15 -> -0.0080466017 | CW18: =(1+CS18)*(1+CT18)*(1+CU18)*(1+CV18)-1 -> -0.014922495 | CX18: =CV15 -> -0.0080466017 | CY18: =CX15 -> 0.015963658 | CZ18: =CY15*1.5 -> 0.023945487 | DA18: =CZ15 -> 0.015963658 | DB18: =(1+CX18)*(1+CY18)*(1+CZ18)*(1+DA18)-1 -> 0.04839382 | DC18: =DA15 -> 0.015963658 | DD18: =DC15 -> -0.0026353997 | DE18: =DD15*1.5 -> -0.0039530996 | DF18: =DE15 -> -0.0026353997 | DG18: =(1+DC18)*(1+DD18)*(1+DE18)*(1+DF18)-1 -> 0.0066207088 | DH18: =DF15 -> -0.0026353997 | DI18: =DH15 -> 0.01106499 | DJ18: =DI15*1.5 -> 0.016597486 | DK18: =DJ15 -> 0.01106499 | DL18: =(1+DH18)*(1+DI18)*(1+DJ18)*(1+DK18)-1 -> 0.036480477 | DM18: =DK15 -> 0.01106499 | DN18: =DM15 -> 0.01106499 | DO18: =DN15*1.5 -> 0.016597486 | DP18: =DO15 -> 0.01106499 | DQ18: =(1+DM18)*(1+DN18)*(1+DO18)*(1+DP18)-1 -> 0.050718186 | DR18: =DP15 -> 0.01106499 | DS18: =DR15 -> 0.01106499 | DT18: =DS15*1.5 -> 0.016597486 | DU18: =DT15 -> 0.01106499 | DV18: =(1+DR18)*(1+DS18)*(1+DT18)*(1+DU18)-1 -> 0.050718186 | DW18: =DU15 -> 0.01106499 | DX18: =DW15 -> 0.01106499 | DY18: =DX15*1.5 -> 0.016597486 | DZ18: =DY15 -> 0.01106499 | EA18: =(1+DW18)*(1+DX18)*(1+DY18)*(1+DZ18)-1 -> 0.050718186 | EB18: =DZ15 -> 0.01106499 | EC18: =EB15 -> 0.01106499 | ED18: =EC15*1.5 -> 0.016597486 | EE18: =ED15 -> 0.01106499 | EF18: =(1+EB18)*(1+EC18)*(1+ED18)*(1+EE18)-1 -> 0.050718186
B19: =#REF!+#REF!+#REF!+B15 -> #REF! | C19: =#REF!+#REF!+B15+C15 -> #REF! | D19: =#REF!+B15+C15+D15 -> #REF! | E19: =B15+C15+D15+E15 -> 0.11890452 | F19: =F15 -> 0.12419987 | G19: =C15+D15+E15+G15 -> 0.10713616 | H19: =D15+E15+G15+H15 -> 0.069580702 | I19: =E15+G15+H15+I15 -> 0.021919662 | J19: =G15+H15+I15+J15 -> 0.012220903 | K19: =K15 -> 0.012007603 | L19: =H15+I15+J15+L15 -> 0.0037299816 | M19: =I15+J15+L15+M15 -> 0.0088578987 | N19: =J15+L15+M15+N15 -> 0.032406075 | O19: =L15+M15+N15+O15 -> 0.03795748 | P19: =P15 -> 0.03847626 | Q19: =M15+N15+O15+Q15 -> 0.042117678 | R19: =N15+O15+Q15+R15 -> 0.038438998 | S19: =O15+Q15+R15+S15 -> 0.055706703 | T19: =Q15+R15+S15+T15 -> 0.075612265 | U19: =U15 -> 0.077462737 | V19: =R15+S15+T15+V15 -> 0.088250617 | W19: =S15+T15+V15+W15 -> 0.12821707 | X19: =T15+V15+W15+X15 -> 0.11798619 | Y19: =V15+W15+X15+Y15 -> 0.094925737 | Z19: =Z15 -> 0.098054313 | AA19: =W15+X15+Y15+AA15 -> 0.061949624 | AB19: 0.05 | AC19: 0.04 | AD19: 0.035 | AE19: =AD19 -> 0.035 | AF19: =AB15+AC15+AD15+AF15 -> 0.019727391 | AG19: =AC15+AD15+AF15+AG15 -> 0.051283151 | AH19: =AD15+AF15+AG15+AH15 -> 0.075818269 | AI19: =AF15+AG15+AH15+AI15 -> 0.10873887 | AJ19: =AJ15 -> 0.113 | AK19: =AG15+AH15+AI15+AK15 -> 0.10530632 | AL19: =AH15+AI15+AK15+AL15 -> 0.083915347 | AM19: =AI15+AK15+AL15+AM15 -> 0.072812308 | AN19: =AK15+AL15+AM15+AN15 -> 0.050114997 | AO19: =AO15 -> 0.05096813 | AP19: =AL15+AM15+AN15+AP15 -> 0.031959766 | AQ19: =AM15+AN15+AP15+AQ15 -> 0.050562644 | AR19: =AN15+AP15+AQ15+AR15 -> 0.078710368 | AS19: =AP15+AQ15+AR15+AS15 -> 0.076289739 | AT19: =AT15 -> 0.0782 | AU19: =AQ15+AR15+AS15+AU15 -> 0.078532343 | AV19: =AR15+AS15+AU15+AV15 -> 0.061961428 | AW19: =AS15+AU15+AV15+AW15 -> 0.04329926 | AX19: =AU15+AV15+AW15+AX15 -> 0.0542 | AY19: =AY15 -> 0.055 | AZ19: =AV15+AW15+AX15+AZ15 -> 0.071262165 | BA19: =AW15+AX15+AZ15+BA15 -> 0.062262165 | BB19: =AX15+AZ15+BA15+BB15 -> 0.057062165 | BC19: =AZ15+BA15+BB15+BC15 -> 0.051462165 | BD19: =BD15 -> 0.0369 | BE19: =BA15+BB15+BC15+BE15 -> 0.046221661 | BF19: =BB15+BC15+BE15+BF15 -> 0.068875812 | BG19: =BC15+BE15+BF15+BG15 -> 0.074187466 | BH19: =BE15+BF15+BG15+BH15 -> 0.10164324 | BI19: =BI15 -> 0.107 | BJ19: =BF15+BG15+BH15+BJ15 -> 0.11108721 | BK19: =BG15+BH15+BJ15+BK15 -> 0.11699532 | BL19: =BH15+BJ15+BK15+BL15 -> 0.10288339 | BM19: =BJ15+BK15+BL15+BM15 -> 0.070141024 | BN19: =BN15 -> 0.071729083 | BO19: =BK15+BL15+BM15+BO15 -> 0.03917285 | BP19: =BL15+BM15+BO15+BP15 -> 0.0093080523 | BQ19: =BM15+BO15+BP15+BQ15 -> 0.0028057838 | BR19: =BO15+BP15+BQ15+BR15 -> -0.0052101709 | BS19: =BS15 -> -0.0052 | BT19: =BP15+BQ15+BR15+BT15 -> 0.014336973 | BU19: =BQ15+BR15+BT15+BU15 -> 0.033884117 | BV19: =BR15+BT15+BU15+BV15 -> 0.053431261 | BW19: =BT15+BU15+BV15+BW15 -> 0.072978404 | BX19: =BX15 -> 0.075 | BY19: =BU15+BV15+BW15+BY15 -> 0.072546915 | BZ19: =BV15+BW15+BY15+BZ15 -> 0.072115427 | CA19: =BW15+BY15+BZ15+CA15 -> 0.071683938 | CB19: =BY15+BZ15+CA15+CB15 -> 0.071252449 | CC19: =CC15 -> 0.073179 | CD19: =BZ15+CA15+CB15+CD15 -> 0.10685311 | CE19: =CA15+CB15+CD15+CE15 -> 0.14245378 | CF19: =CB15+CD15+CE15+CF15 -> 0.17805444 | CG19: =CD15+CE15+CF15+CG15 -> 0.21365511 | CH19: =CH15 -> 0.231391 | CI19: =CE15+CF15+CG15+CI15 -> 0.20200183 | CJ19: =CF15+CG15+CI15+CJ15 -> 0.19034856 | CK19: =CG15+CI15+CJ15+CK15 -> 0.17869528 | CL19: =CI15+CJ15+CK15+CL15 -> 0.16704201 | CM19: =CM15 -> 0.1778 | CN19: =CJ15+CK15+CL15+CN15 -> 0.13863658 | CO19: =CK15+CL15+CN15+CO15 -> 0.11023115 | CP19: =CL15+CN15+CO15+CP15 -> 0.081825722 | CQ19: =CN15+CO15+CP15+CQ15 -> 0.053420292 | CR19: =CR15 -> 0.0545 | CS19: =CO15+CP15+CQ15+CS15 -> 0.032018618 | CT19: =CP15+CQ15+CS15+CT15 -> 0.010616943 | CU19: =CQ15+CS15+CT15+CU15 -> -0.010784732 | CV19: =CS15+CT15+CU15+CV15 -> -0.032186407 | CW19: =CW15 -> -0.0318 | CX19: =CT15+CU15+CV15+CX15 -> -0.0081761472 | CY19: =CU15+CV15+CX15+CY15 -> 0.015834113 | CZ19: =CV15+CX15+CY15+CZ15 -> 0.039844372 | DA19: =CX15+CY15+CZ15+DA15 -> 0.063854632 | DB19: =DB15 -> 0.0654 | DC19: =CY15+CZ15+DA15+DC15 -> 0.045255574 | DD19: =CZ15+DA15+DC15+DD15 -> 0.026656517 | DE19: =DA15+DC15+DD15+DE15 -> 0.0080574589 | DF19: =DC15+DD15+DE15+DF15 -> -0.010541599 | DG19: =DG15 -> -0.0105 | DH19: =DD15+DE15+DF15+DH15 -> 0.0031587914 | DI19: =DE15+DF15+DH15+DI15 -> 0.016859182 | DJ19: =DF15+DH15+DI15+DJ15 -> 0.030559572 | DK19: =DH15+DI15+DJ15+DK15 -> 0.044259962 | DL19: =DL15 -> 0.045 | DM19: =DI15+DJ15+DK15+DM15 -> 0.044259962 | DN19: =DJ15+DK15+DM15+DN15 -> 0.044259962 | DO19: =DK15+DM15+DN15+DO15 -> 0.044259962 | DP19: =DM15+DN15+DO15+DP15 -> 0.044259962 | DQ19: =DQ15 -> 0.045 | DR19: =DN15+DO15+DP15+DR15 -> 0.044259962 | DS19: =DO15+DP15+DR15+DS15 -> 0.044259962 | DT19: =DP15+DR15+DS15+DT15 -> 0.044259962 | DU19: =DR15+DS15+DT15+DU15 -> 0.044259962 | DV19: =DV15 -> 0.045 | DW19: =DS15+DT15+DU15+DW15 -> 0.044259962 | DX19: =DT15+DU15+DW15+DX15 -> 0.044259962 | DY19: =DU15+DW15+DX15+DY15 -> 0.044259962 | DZ19: =DW15+DX15+DY15+DZ15 -> 0.044259962 | EA19: =EA15 -> 0.045 | EB19: =DX15+DY15+DZ15+EB15 -> 0.044259962 | EC19: =DY15+DZ15+EB15+EC15 -> 0.044259962 | ED19: =DZ15+EB15+EC15+ED15 -> 0.044259962 | EE19: =EB15+EC15+ED15+EE15 -> 0.044259962 | EF19: =EF15 -> 0.045

Sheet Income Statement
BH1: =BH14/BH5 -> -0.03132943 | BM1: =BM14/BM5 -> -0.028155458 | BR1: =BR14/BR5 -> -0.02431711 | BW1: =BW14/BW5 -> -0.014585466
A2: =DCF!$A$2 -> Cury - TP: R$48 | AI2: =AI16/AI11 -> 0.33979978 | AJ2: =AJ16/AJ11 -> 0.33979978 | AN2: =AN16/AN11 -> 0.30448685 | AO2: =AO16/AO11 -> 0.30448685 | AS2: =AS16/AS11 -> 0.39647812 | AT2: =AT16/AT11 -> 0.39647812 | AX2: =AX16/AX11 -> 0.34601825 | AY2: =AY16/AY11 -> 0.34601825 | BC2: =(BC5*(1-2.08%)+BC13+BC14)/(BC5*(1-2.08%)) -> 0.36837541 | BD2: =(BD5+BD9+BD13)/(BD5+BD9) -> 0.3844607 | BH2: =(BH5*(1-2.08%)+BH13+BH14)/(BH5*(1-2.08%)) -> 0.36049391 | BI2: =(BI5+BI9+BI13)/(BI5+BI9) -> 0.38988821 | BM2: =(BM5*(1-2.08%)+BM13+BM14)/(BM5*(1-2.08%)) -> 0.33464547 | BN2: =(BN5+BN9+BN13)/(BN5+BN9) -> 0.36168617 | BR2: =(BR5*(1-2.08%)+BR13+BR14)/(BR5*(1-2.08%)) -> 0.35324277 | BS2: =(BS5+BS9+BS13)/(BS5+BS9) -> 0.37600902 | BW2: =(BW5*(1-2.08%)+BW13+BW14)/(BW5*(1-2.08%)) -> 0.38265246 | BX2: =(BX5+BX9+BX13)/(BX5+BX9) -> 0.39516181 | CB2: =(CB11+CB13)/(CB11) -> 0.41366816 | CC2: =CC16/CC11 -> 0.34915435 | CD2: =CD16/CD11 -> 0.34374299 | CE2: =CE16/CE11 -> 0.35363763 | CF2: =CF16/CF11 -> 0.37851223 | CG2: =CG16/CG11 -> 0.40499044 | CH2: =CH16/CH11 -> 0.37424368 | CI2: =CI16/CI11 -> 0.35469191 | CJ2: =CJ16/CJ11 -> 0.36096309 | ... EF2: =EF16/EF11 -> 0.37216648
B3: =Macro!B$9 -> 1Q04 | C3: =Macro!C$9 -> 2Q04 | D3: =Macro!D$9 -> 3Q04 | E3: =Macro!E$9 -> 4Q04 | F3: =Macro!F$9 -> 2004 | G3: =Macro!G$9 -> 1Q05 | H3: =Macro!H$9 -> 2Q05 | I3: =Macro!I$9 -> 3Q05 | ... EF3: =Macro!EF$9 -> 2030E
A4: Gross Revenues | B4: =B5+B7 -> 0 | C4: =C5+C7 -> 0 | D4: =D5+D7 -> 0 | E4: =E5+E7 -> 0 | F4: =SUM(B4:E4) -> 0 | G4: =G5+G7 -> 0 | H4: =H5+H7 -> 0 | I4: =I5+I7 -> 0 | J4: =J5+J7 -> 0 | K4: =SUM(G4:J4) -> 0 | L4: =L5+L7 -> 0 | M4: =M5+M7 -> 0 | N4: =N5+N7 -> 0 | O4: =O5+O7 -> 0 | P4: =SUM(L4:O4) -> 0 | Q4: =Q5+Q7 -> 0 | R4: =R5+R7 -> 0 | S4: =S5+S7 -> 0 | T4: =T5+T7 -> 0 | U4: =SUM(Q4:T4) -> 0 | V4: =V5+V7 -> 0 | W4: =W5+W7 -> 0 | X4: =X5+X7 -> 0 | Y4: =Y5+Y7 -> 0 | Z4: =SUM(V4:Y4) -> 0 | AA4: =AA5+AA7 -> 0 | AB4: =AB5+AB7 -> 0 | AC4: =AC5+AC7 -> 0 | AD4: =AD5+AD7 -> 0 | AE4: =SUM(AA4:AD4) -> 0 | AF4: =AF5+AF6+AF7 -> 0 | AG4: =AG5+AG6+AG7 -> 0 | AH4: =AH5+AH6+AH7 -> 0 | AI4: =AI5+AI6+AI7 -> 244646.21 | AJ4: =SUM(AF4:AI4) -> 244646.21 | AK4: =AK5+AK6+AK7 -> 0 | AL4: =AL5+AL6+AL7 -> 0 | AM4: =AM5+AM6+AM7 -> 0 | AN4: =AN5+AN6+AN7 -> 433385.81 | AO4: =SUM(AK4:AN4) -> 433385.81 | AP4: =AP5+AP6+AP7 -> 0 | AQ4: =AQ5+AQ6+AQ7 -> 0 | AR4: =AR5+AR6+AR7 -> 0 | AS4: =AS5+AS6+AS7 -> 494249.75 | AT4: =SUM(AP4:AS4) -> 494249.75 | AU4: =AU5+AU6+AU7 -> 0 | AV4: =AV5+AV6+AV7 -> 0 | AW4: =AW5+AW6+AW7 -> 0 | AX4: =AX5+AX6+AX7 -> 753085.35 | AY4: =SUM(AU4:AX4) -> 753085.35 | AZ4: =AZ5+AZ6+AZ7 -> 0 | BA4: =BA5+BA6+BA7 -> 0 | BB4: =BB5+BB6+BB7 -> 0 | BC4: =BC5+BC6+BC7 -> 912966 | BD4: =SUM(AZ4:BC4) -> 912966 | BE4: =BE5+BE6+BE7 -> 0 | BF4: =BF5+BF6+BF7 -> 0 | BG4: =BG5+BG6+BG7 -> 0 | BH4: =BH5+BH6+BH7 -> 871724 | BI4: =SUM(BE4:BH4) -> 871724 | BJ4: =BJ5+BJ6+BJ7 -> 0 | BK4: =BK5+BK6+BK7 -> 0 | BL4: =BL5+BL6+BL7 -> 0 | BM4: =BM5+BM6+BM7 -> 821810 | BN4: =SUM(BJ4:BM4) -> 821810 | BO4: =BO5+BO6+BO7 -> 0 | BP4: =BP5+BP6+BP7 -> 0 | BQ4: =BQ5+BQ6+BQ7 -> 0 | BR4: =BR5+BR6+BR7 -> 831922 | BS4: =SUM(BO4:BR4) -> 831922 | BT4: =BT5+BT6+BT7 -> 0 | BU4: =BU5+BU6+BU7 -> 0 | BV4: =BV5+BV6+BV7 -> 0 | BW4: =BW5+BW6+BW7 -> 942945 | BX4: =SUM(BT4:BW4) -> 942945 | BY4: =BY5+BY6+BY7 -> 193287 | BZ4: =BZ5+BZ6+BZ7 -> 273610 | CA4: =CA5+CA6+CA7 -> 268175 | CB4: =CB5+CB6+CB7 -> 308715 | CC4: =SUM(BY4:CB4) -> 1043787 | CD4: =CD5+CD6+CD7 -> 233098 | CE4: =CE5+CE6+CE7 -> 252454 | CF4: =CF5+CF6+CF7 -> 334505 | CG4: =CG5+CG6+CG7 -> 353014 | CH4: =SUM(CD4:CG4) -> 1173071 | CI4: =CI5+CI6+CI7 -> 346976 | CJ4: =CJ5+CJ6+CJ7 -> 462074 | CK4: =CK5+CK6+CK7 -> 466696 | CL4: =CL5+CL6+CL7 -> 502424 | CM4: =SUM(CI4:CL4) -> 1778170 | CN4: =CN5+CN6+CN7 -> 458170 | CO4: =CO5+CO6+CO7 -> 616407 | CP4: =CP5+CP6+CP7 -> 640437 | CQ4: =CQ5+CQ6+CQ7 -> 593421 | CR4: =SUM(CN4:CQ4) -> 2308435 | CS4: =CS5+CS6+CS7 -> 607423 | CT4: =CT5+CT6+CT7 -> 743352 | CU4: =CU5+CU6+CU7 -> 768155 | CV4: =CV5+CV6+CV7 -> 829075 | CW4: =SUM(CS4:CV4) -> 2948005 | CX4: =CX5+CX6+CX7 -> 854925 | CY4: =CY5+CY6+CY7 -> 1017876 | CZ4: =CZ5+CZ6+CZ7 -> 1078346 | DA4: =DA5+DA6+DA7 -> 1056476 | DB4: =SUM(CX4:DA4) -> 4007623 | DC4: =DC5+DC6+DC7 -> 1244407 | DD4: =DD5+DD6+DD7 -> 1375487 | DE4: =DE5+DE6+DE7 -> 1449421 | DF4: =DF5+DF6+DF7 -> 1453820 | DG4: =SUM(DC4:DF4) -> 5523135 | DH4: =DH5+DH6+DH7 -> 1644474 | DI4: =DI5+DI6+DI7 -> 1725754 | DJ4: =DJ5+DJ6+DJ7 -> 1717525.6 | DK4: =DK5+DK6+DK7 -> 1859826.6 | DL4: =SUM(DH4:DK4) -> 6947580.2 | DM4: =DM5+DM6+DM7 -> 1899921.8 | DN4: =DN5+DN6+DN7 -> 1962486 | DO4: =DO5+DO6+DO7 -> 2015562.5 | DP4: =DP5+DP6+DP7 -> 2064555.3 | DQ4: =SUM(DM4:DP4) -> 7942525.6 | DR4: =DR5+DR6+DR7 -> 2110530.9 | DS4: =DS5+DS6+DS7 -> 2154229.7 | DT4: =DT5+DT6+DT7 -> 2196132.6 | DU4: =DU5+DU6+DU7 -> 2236572.1 | DV4: =SUM(DR4:DU4) -> 8697465.4 | DW4: =DW5+DW6+DW7 -> 2275792.6 | DX4: =DX5+DX6+DX7 -> 2313983.1 | DY4: =DY5+DY6+DY7 -> 2351297.5 | DZ4: =DZ5+DZ6+DZ7 -> 2387865.2 | EA4: =SUM(DW4:DZ4) -> 9328938.3 | EB4: =EB5+EB6+EB7 -> 2423798.2 | EC4: =EC5+EC6+EC7 -> 2459194.6 | ED4: =ED5+ED6+ED7 -> 2494142.1 | EE4: =EE5+EE6+EE7 -> 2528718.8 | EF4: =SUM(EB4:EE4) -> 9905853.6
A5: Development Sales | F5: =SUM(B5:E5) -> 0 | K5: =SUM(G5:J5) -> 0 | P5: =SUM(L5:O5) -> 0 | U5: =SUM(Q5:T5) -> 0 | Z5: =SUM(V5:Y5) -> 0 | AE5: =SUM(AA5:AD5) -> 0 | AI5: =AI11/(1-AI10) -> 244646.21 | AJ5: =SUM(AF5:AI5) -> 244646.21 | AN5: =AN11/(1-AN10) -> 433385.81 | AO5: =SUM(AK5:AN5) -> 433385.81 | AS5: =AS11/(1-AS10) -> 494249.75 | AT5: =SUM(AP5:AS5) -> 494249.75 | AX5: =AX11/(1-AX10) -> 753085.35 | AY5: =SUM(AU5:AX5) -> 753085.35 | BC5: =472254-3130 -> 469124 | BD5: =SUM(AZ5:BC5) -> 469124 | BH5: =458609-5776 -> 452833 | BI5: =SUM(BE5:BH5) -> 452833 | BM5: =565504-8596 -> 556908 | BN5: =SUM(BJ5:BM5) -> 556908 | BR5: =738498-9135 -> 729363 | BS5: =SUM(BO5:BR5) -> 729363 | BW5: =930049-9955 -> 920094 | BX5: =SUM(BT5:BW5) -> 920094 | BY5: =193732-2076 -> 191656 | BZ5: =248291-3205 -> 245086 | CA5: =268629-1695 -> 266934 | CB5: =1063367-24443-8342+100-SUM(BY5:CA5) -> 327006 | CC5: =SUM(BY5:CB5) -> 1030682 | CD5: =234242-1985 -> 232257 | CE5: =263860-11578-507 -> 251775 | CF5: =830029-8974-3617-SUM(CD5:CE5) -> 333406 | CG5: =1183813-16767-4243-SUM(CD5:CF5) -> 345365 | CH5: =SUM(CD5:CG5) -> 1162803 | CI5: =348556-1130-1564 -> 345862 | CJ5: =467360-4492-2158 -> 460710 | CK5: =1290410-12155-6059-SUM(CI5:CJ5) -> 465624 | CL5: =1795292-13083-8289-SUM(CI5:CK5) -> 501724 | CM5: =SUM(CI5:CL5) -> 1773920 | CN5: =459417-740-1572 -> 457105 | CO5: =619527-4298-578 -> 614651 | CP5: =1720898-8316-1765-SUM(CN5:CO5) -> 639061 | CQ5: =2318165-11358-3745-SUM(CN5:CP5) -> 592245 | CR5: =SUM(CN5:CQ5) -> 2303062 | CS5: =608998-1086-2065 -> 605847 | CT5: =743265-382-704 -> 742179 | CU5: =767232-2543+1829 -> 766518 | CV5: =2950126-1185-6289-SUM(CS5:CU5) -> 828108 | CW5: =SUM(CS5:CV5) -> 2942652 | CX5: =851906-1722+2980 -> 853164 | CY5: =1016524+2082-1667 -> 1016939 | CZ5: =1084539-6033-160 -> 1078346 | DA5: =4016820+2114-14025-SUM(CX5:CZ5) -> 1056460 | DB5: =SUM(CX5:DA5) -> 4004909 | DC5: =1246115-6033-2089 -> 1237993 | DD5: =1393733-4822-13805 -> 1375106 | DE5: =1461895-11780-3018 -> 1447097 | DF5: =5567252-11984-42968-SUM(DC5:DE5) -> 1452104 | DG5: =SUM(DC5:DF5) -> 5512300 | DH5: =1660432-17750+353 -> 1643035 | DI5: =1742831-3187-14445 -> 1725199 | DJ5: =Forecasts!DJ36 -> 1714097.4 | DK5: =Forecasts!DK36 -> 1856114.4 | DL5: =SUM(DH5:DK5) -> 6938445.8 | DM5: =Forecasts!DM36 -> 1896129.5 | DN5: =Forecasts!DN36 -> 1958568.9 | DO5: =Forecasts!DO36 -> 2011539.4 | DP5: =Forecasts!DP36 -> 2060434.4 | DQ5: =SUM(DM5:DP5) -> 7926672.2 | DR5: =Forecasts!DR36 -> 2106318.3 | DS5: =Forecasts!DS36 -> 2149929.9 | DT5: =Forecasts!DT36 -> 2191749.1 | DU5: =Forecasts!DU36 -> 2232107.9 | DV5: =SUM(DR5:DU5) -> 8680105.1 | DW5: =Forecasts!DW36 -> 2271250.1 | DX5: =Forecasts!DX36 -> 2309364.4 | DY5: =Forecasts!DY36 -> 2346604.3 | DZ5: =Forecasts!DZ36 -> 2383099 | EA5: =SUM(DW5:DZ5) -> 9310317.7 | EB5: =Forecasts!EB36 -> 2418960.3 | EC5: =Forecasts!EC36 -> 2454286.1 | ED5: =Forecasts!ED36 -> 2489163.7 | EE5: =Forecasts!EE36 -> 2523671.4 | EF5: =SUM(EB5:EE5) -> 9886081.5
A6: INCC | F6: =SUM(B6:E6) -> 0 | K6: =SUM(G6:J6) -> 0 | P6: =SUM(L6:O6) -> 0 | U6: =SUM(Q6:T6) -> 0 | Z6: =SUM(V6:Y6) -> 0 | AE6: =SUM(AA6:AD6) -> 0 | AJ6: =SUM(AF6:AI6) -> 0 | AO6: =SUM(AK6:AN6) -> 0 | AT6: =SUM(AP6:AS6) -> 0 | AY6: =SUM(AU6:AX6) -> 0 | BD6: =SUM(AZ6:BC6) -> 0 | BI6: =SUM(BE6:BH6) -> 0 | BN6: =SUM(BJ6:BM6) -> 0 | BS6: =SUM(BO6:BR6) -> 0 | BX6: =SUM(BT6:BW6) -> 0 | CC6: =SUM(BY6:CB6) -> 0 | CH6: =SUM(CD6:CG6) -> 0 | CM6: =SUM(CI6:CL6) -> 0 | CR6: =SUM(CN6:CQ6) -> 0 | CW6: =SUM(CS6:CV6) -> 0 | DB6: =SUM(CX6:DA6) -> 0 | DG6: =SUM(DC6:DF6) -> 0 | DJ6: =AVERAGE(DE6/Macro!DE18,DF6/Macro!DF18,DH6/Macro!DH18,DI6/Macro!DI18)*'Balance Sheet'!DJ9/'Balance Sheet'!DE9*Macro!DJ18*0.95 -> 0 | DK6: =AVERAGE(DF6/Macro!DF18,DH6/Macro!DH18,DI6/Macro!DI18,DJ6/Macro!DJ18)*'Balance Sheet'!DK9/'Balance Sheet'!DF9*Macro!DK18*0.95 -> 0 | DL6: =SUM(DH6:DK6) -> 0 | DM6: =AVERAGE(DH6/Macro!DH18,DI6/Macro!DI18,DJ6/Macro!DJ18,DK6/Macro!DK18)*'Balance Sheet'!DM9/'Balance Sheet'!DH9*Macro!DM18*0.95 -> 0 | DN6: =AVERAGE(DI6/Macro!DI18,DJ6/Macro!DJ18,DK6/Macro!DK18,DM6/Macro!DM18)*'Balance Sheet'!DN9/'Balance Sheet'!DI9*Macro!DN18*0.95 -> 0 | DO6: =AVERAGE(DJ6/Macro!DJ18,DK6/Macro!DK18,DM6/Macro!DM18,DN6/Macro!DN18)*'Balance Sheet'!DO9/'Balance Sheet'!DJ9*Macro!DO18*0.95 -> 0 | DP6: =AVERAGE(DK6/Macro!DK18,DM6/Macro!DM18,DN6/Macro!DN18,DO6/Macro!DO18)*'Balance Sheet'!DP9/'Balance Sheet'!DK9*Macro!DP18*0.95 -> 0 | DQ6: =SUM(DM6:DP6) -> 0 | DR6: =AVERAGE(DM6/Macro!DM18,DN6/Macro!DN18,DO6/Macro!DO18,DP6/Macro!DP18)*'Balance Sheet'!DR9/'Balance Sheet'!DM9*Macro!DR18*0.95 -> 0 | DS6: =AVERAGE(DN6/Macro!DN18,DO6/Macro!DO18,DP6/Macro!DP18,DR6/Macro!DR18)*'Balance Sheet'!DS9/'Balance Sheet'!DN9*Macro!DS18*0.95 -> 0 | DT6: =AVERAGE(DO6/Macro!DO18,DP6/Macro!DP18,DR6/Macro!DR18,DS6/Macro!DS18)*'Balance Sheet'!DT9/'Balance Sheet'!DO9*Macro!DT18*0.95 -> 0 | DU6: =AVERAGE(DP6/Macro!DP18,DR6/Macro!DR18,DS6/Macro!DS18,DT6/Macro!DT18)*'Balance Sheet'!DU9/'Balance Sheet'!DP9*Macro!DU18*0.95 -> 0 | DV6: =SUM(DR6:DU6) -> 0 | DW6: =AVERAGE(DR6/Macro!DR18,DS6/Macro!DS18,DT6/Macro!DT18,DU6/Macro!DU18)*'Balance Sheet'!DW9/'Balance Sheet'!DR9*Macro!DW18*0.95 -> 0 | DX6: =AVERAGE(DS6/Macro!DS18,DT6/Macro!DT18,DU6/Macro!DU18,DW6/Macro!DW18)*'Balance Sheet'!DX9/'Balance Sheet'!DS9*Macro!DX18*0.95 -> 0 | DY6: =AVERAGE(DT6/Macro!DT18,DU6/Macro!DU18,DW6/Macro!DW18,DX6/Macro!DX18)*'Balance Sheet'!DY9/'Balance Sheet'!DT9*Macro!DY18*0.95 -> 0 | DZ6: =AVERAGE(DU6/Macro!DU18,DW6/Macro!DW18,DX6/Macro!DX18,DY6/Macro!DY18)*'Balance Sheet'!DZ9/'Balance Sheet'!DU9*Macro!DZ18*0.95 -> 0 | EA6: =SUM(DW6:DZ6) -> 0 | EB6: =AVERAGE(DW6/Macro!DW18,DX6/Macro!DX18,DY6/Macro!DY18,DZ6/Macro!DZ18)*'Balance Sheet'!EB9/'Balance Sheet'!DW9*Macro!EB18*0.95 -> 0 | EC6: =AVERAGE(DX6/Macro!DX18,DY6/Macro!DY18,DZ6/Macro!DZ18,EB6/Macro!EB18)*'Balance Sheet'!EC9/'Balance Sheet'!DX9*Macro!EC18*0.95 -> 0 | ED6: =AVERAGE(DY6/Macro!DY18,DZ6/Macro!DZ18,EB6/Macro!EB18,EC6/Macro!EC18)*'Balance Sheet'!ED9/'Balance Sheet'!DY9*Macro!ED18*0.95 -> 0 | EE6: =AVERAGE(DZ6/Macro!DZ18,EB6/Macro!EB18,EC6/Macro!EC18,ED6/Macro!ED18)*'Balance Sheet'!EE9/'Balance Sheet'!DZ9*Macro!EE18*0.95 -> 0 | EF6: =SUM(EB6:EE6) -> 0
A7: Services | F7: =SUM(B7:E7) -> 0 | K7: =SUM(G7:J7) -> 0 | P7: =SUM(L7:O7) -> 0 | U7: =SUM(Q7:T7) -> 0 | Z7: =SUM(V7:Y7) -> 0 | AE7: =SUM(AA7:AD7) -> 0 | AJ7: =SUM(AF7:AI7) -> 0 | AO7: =SUM(AK7:AN7) -> 0 | AT7: =SUM(AP7:AS7) -> 0 | AY7: =SUM(AU7:AX7) -> 0 | BC7: 443842 | BD7: =SUM(AZ7:BC7) -> 443842 | BH7: 418891 | BI7: =SUM(BE7:BH7) -> 418891 | BM7: 264902 | BN7: =SUM(BJ7:BM7) -> 264902 | BR7: =102559 -> 102559 | BS7: =SUM(BO7:BR7) -> 102559 | BW7: =22851 -> 22851 | BX7: =SUM(BT7:BW7) -> 22851 | BY7: 1631 | BZ7: 28524 | CA7: 1241 | CB7: =13105-SUM(BY7:CA7) -> -18291 | CC7: =SUM(BY7:CB7) -> 13105 | CD7: 841 | CE7: 679 | CF7: =2619-SUM(CD7:CE7) -> 1099 | CG7: =10268-SUM(CD7:CF7) -> 7649 | CH7: =SUM(CD7:CG7) -> 10268 | CI7: 1114 | CJ7: 1364 | CK7: =3550-SUM(CI7:CJ7) -> 1072 | CL7: =4250-SUM(CI7:CK7) -> 700 | CM7: =SUM(CI7:CL7) -> 4250 | CN7: 1065 | CO7: 1756 | CP7: =4197-SUM(CN7:CO7) -> 1376 | CQ7: =5373-SUM(CN7:CP7) -> 1176 | CR7: =SUM(CN7:CQ7) -> 5373 | CS7: 1576 | CT7: 1173 | CU7: 1637 | CV7: =5353-SUM(CS7:CU7) -> 967 | CW7: =SUM(CS7:CV7) -> 5353 | CX7: 1761 | CY7: 937 | CZ7: 0 | DA7: =2714-SUM(CX7:CZ7) -> 16 | DB7: =SUM(CX7:DA7) -> 2714 | DC7: 6414 | DD7: 381 | DE7: 2324 | DF7: =10835-SUM(DC7:DE7) -> 1716 | DG7: =SUM(DC7:DF7) -> 10835 | DH7: 1439 | DI7: 555 | DJ7: =Forecasts!DJ42 -> 3428.1948 | DK7: =Forecasts!DK42 -> 3712.2288 | DL7: =SUM(DH7:DK7) -> 9134.4236 | DM7: =Forecasts!DM42 -> 3792.259 | DN7: =Forecasts!DN42 -> 3917.1378 | DO7: =Forecasts!DO42 -> 4023.0789 | DP7: =Forecasts!DP42 -> 4120.8688 | DQ7: =SUM(DM7:DP7) -> 15853.344 | DR7: =Forecasts!DR42 -> 4212.6366 | DS7: =Forecasts!DS42 -> 4299.8597 | DT7: =Forecasts!DT42 -> 4383.4981 | DU7: =Forecasts!DU42 -> 4464.2159 | DV7: =SUM(DR7:DU7) -> 17360.21 | DW7: =Forecasts!DW42 -> 4542.5001 | DX7: =Forecasts!DX42 -> 4618.7287 | DY7: =Forecasts!DY42 -> 4693.2085 | DZ7: =Forecasts!DZ42 -> 4766.1981 | EA7: =SUM(DW7:DZ7) -> 18620.635 | EB7: =Forecasts!EB42 -> 4837.9205 | EC7: =Forecasts!EC42 -> 4908.5721 | ED7: =Forecasts!ED42 -> 4978.3275 | EE7: =Forecasts!EE42 -> 5047.3428 | EF7: =SUM(EB7:EE7) -> 19772.163
A8: Deductions | B8: =B9 -> 0 | C8: =C9 -> 0 | D8: =D9 -> 0 | E8: =E9 -> 0 | F8: =SUM(B8:E8) -> 0 | G8: =G9 -> 0 | H8: =H9 -> 0 | I8: =I9 -> 0 | J8: =J9 -> 0 | K8: =SUM(G8:J8) -> 0 | L8: =L9 -> 0 | M8: =M9 -> 0 | N8: =N9 -> 0 | O8: =O9 -> 0 | P8: =SUM(L8:O8) -> 0 | Q8: =Q9 -> 0 | R8: =R9 -> 0 | S8: =S9 -> 0 | T8: =T9 -> 0 | U8: =SUM(Q8:T8) -> 0 | V8: =V9 -> 0 | W8: =W9 -> 0 | X8: =X9 -> 0 | Y8: =Y9 -> 0 | Z8: =SUM(V8:Y8) -> 0 | AA8: =AA9 -> 0 | AB8: =AB9 -> 0 | AC8: =AC9 -> 0 | AD8: =AD9 -> 0 | AE8: =SUM(AA8:AD8) -> 0 | AF8: =AF9 -> 0 | AG8: =AG9 -> 0 | AH8: =AH9 -> 0 | AI8: =AI9 -> -5088.6411 | AJ8: =SUM(AF8:AI8) -> -5088.6411 | AK8: =AK9 -> 0 | AL8: =AL9 -> 0 | AM8: =AM9 -> 0 | AN8: =AN9 -> -9014.4249 | AO8: =SUM(AK8:AN8) -> -9014.4249 | AP8: =AP9 -> 0 | AQ8: =AQ9 -> 0 | AR8: =AR9 -> 0 | AS8: =AS9 -> -10280.395 | AT8: =SUM(AP8:AS8) -> -10280.395 | AU8: =AU9 -> 0 | AV8: =AV9 -> 0 | AW8: =AW9 -> 0 | AX8: =AX9 -> -15664.175 | AY8: =SUM(AU8:AX8) -> -15664.175 | AZ8: =AZ9 -> 0 | BA8: =BA9 -> 0 | BB8: =BB9 -> 0 | BC8: =BC9 -> -13595 | BD8: =SUM(AZ8:BC8) -> -13595 | BE8: =BE9 -> 0 | BF8: =BF9 -> 0 | BG8: =BG9 -> 0 | BH8: =BH9 -> -11309 | BI8: =SUM(BE8:BH8) -> -11309 | BJ8: =BJ9 -> 0 | BK8: =BK9 -> 0 | BL8: =BL9 -> 0 | BM8: =BM9 -> -13047 | BN8: =SUM(BJ8:BM8) -> -13047 | BO8: =BO9 -> 0 | BP8: =BP9 -> 0 | BQ8: =BQ9 -> 0 | BR8: =BR9 -> -17537 | BS8: =SUM(BO8:BR8) -> -17537 | BT8: =BT9 -> 0 | BU8: =BU9 -> 0 | BV8: =BV9 -> 0 | BW8: =BW9 -> -22692 | BX8: =SUM(BT8:BW8) -> -22692 | BY8: =BY9 -> -4917 | BZ8: =BZ9 -> -5877 | CA8: =CA9 -> -6651 | CB8: =CB9 -> -7065 | CC8: =SUM(BY8:CB8) -> -24510 | CD8: =CD9 -> -5777 | CE8: =CE9 -> -6250 | CF8: =CF9 -> -8608 | CG8: =CG9 -> -7754 | CH8: =SUM(CD8:CG8) -> -28389 | CI8: =CI9 -> -7690 | CJ8: =CJ9 -> -10737 | CK8: =CK9 -> -10247 | CL8: =CL9 -> -11201 | CM8: =SUM(CI8:CL8) -> -39875 | CN8: =CN9 -> -10796 | CO8: =CO9 -> -13624 | CP8: =CP9 -> -13778 | CQ8: =CQ9 -> -12943 | CR8: =SUM(CN8:CQ8) -> -51141 | CS8: =CS9 -> -12467 | CT8: =CT9 -> -15606 | CU8: =CU9 -> -16281 | CV8: =CV9 -> -17479 | CW8: =SUM(CS8:CV8) -> -61833 | CX8: =CX9 -> -17543 | CY8: =CY9 -> -19791 | CZ8: =CZ9 -> -22474 | DA8: =DA9 -> -21505 | DB8: =SUM(CX8:DA8) -> -81313 | DC8: =DC9 -> -28223 | DD8: =DD9 -> -28888 | DE8: =DE9 -> -32495 | DF8: =DF9 -> -34105 | DG8: =SUM(DC8:DF8) -> -123711 | DH8: =DH9 -> -31903 | DI8: =DI9 -> -35160 | DJ8: =DJ9 -> -35724.533 | DK8: =DK9 -> -38684.394 | DL8: =SUM(DH8:DK8) -> -141471.93 | DM8: =DM9 -> -39518.372 | DN8: =DN9 -> -40819.71 | DO8: =DO9 -> -41923.7 | DP8: =DP9 -> -42942.749 | DQ8: =SUM(DM8:DP8) -> -165204.53 | DR8: =DR9 -> -43899.044 | DS8: =DS9 -> -44807.978 | DT8: =DT9 -> -45679.557 | DU8: =DU9 -> -46520.701 | DV8: =SUM(DR8:DU8) -> -180907.28 | DW8: =DW9 -> -47336.485 | DX8: =DX9 -> -48130.848 | DY8: =DY9 -> -48906.987 | DZ8: =DZ9 -> -49667.597 | EA8: =SUM(DW8:DZ8) -> -194041.92 | EB8: =EB9 -> -50415.002 | EC8: =EC9 -> -51151.249 | ED8: =ED9 -> -51878.155 | EE8: =EE9 -> -52597.35 | EF8: =SUM(EB8:EE8) -> -206041.76
A9: Taxes and other deductions | F9: =SUM(B9:E9) -> 0 | K9: =SUM(G9:J9) -> 0 | P9: =SUM(L9:O9) -> 0 | U9: =SUM(Q9:T9) -> 0 | Z9: =SUM(V9:Y9) -> 0 | AE9: =SUM(AA9:AD9) -> 0 | AI9: =-AI10*AI5 -> -5088.6411 | AJ9: =SUM(AF9:AI9) -> -5088.6411 | AN9: =-AN10*AN5 -> -9014.4249 | AO9: =SUM(AK9:AN9) -> -9014.4249 | AS9: =-AS10*AS5 -> -10280.395 | AT9: =SUM(AP9:AS9) -> -10280.395 | AX9: =-AX10*AX5 -> -15664.175 | AY9: =SUM(AU9:AX9) -> -15664.175 | BC9: -13595 | BD9: =SUM(AZ9:BC9) -> -13595 | BH9: -11309 | BI9: =SUM(BE9:BH9) -> -11309 | BM9: -13047 | BN9: =SUM(BJ9:BM9) -> -13047 | BR9: =-17537 -> -17537 | BS9: =SUM(BO9:BR9) -> -17537 | BW9: =-22692 -> -22692 | BX9: =SUM(BT9:BW9) -> -22692 | BY9: -4917 | BZ9: -5877 | CA9: -6651 | CB9: =-24510-SUM(BY9:CA9) -> -7065 | CC9: =SUM(BY9:CB9) -> -24510 | CD9: -5777 | CE9: -6250 | CF9: =-20635-SUM(CD9:CE9) -> -8608 | CG9: =-28389-SUM(CD9:CF9) -> -7754 | CH9: =SUM(CD9:CG9) -> -28389 | CI9: -7690 | CJ9: -10737 | CK9: =-28674-SUM(CI9:CJ9) -> -10247 | CL9: =-39875-SUM(CI9:CK9) -> -11201 | CM9: =SUM(CI9:CL9) -> -39875 | CN9: -10796 | CO9: -13624 | CP9: =-38198-SUM(CN9:CO9) -> -13778 | CQ9: =-51141-SUM(CN9:CP9) -> -12943 | CR9: =SUM(CN9:CQ9) -> -51141 | CS9: -12467 | CT9: -15606 | CU9: -16281 | CV9: =-61833-SUM(CS9:CU9) -> -17479 | CW9: =SUM(CS9:CV9) -> -61833 | CX9: -17543 | CY9: -19791 | CZ9: -22474 | DA9: =-81313-SUM(CX9:CZ9) -> -21505 | DB9: =SUM(CX9:DA9) -> -81313 | DC9: -28223 | DD9: -28888 | DE9: -32495 | DF9: =-123711-SUM(DC9:DE9) -> -34105 | DG9: =SUM(DC9:DF9) -> -123711 | DH9: -31903 | DI9: -35160 | DJ9: =-DJ10*DJ$4 -> -35724.533 | DK9: =-DK10*DK$4 -> -38684.394 | DL9: =SUM(DH9:DK9) -> -141471.93 | DM9: =-DM10*DM$4 -> -39518.372 | DN9: =-DN10*DN$4 -> -40819.71 | DO9: =-DO10*DO$4 -> -41923.7 | DP9: =-DP10*DP$4 -> -42942.749 | DQ9: =SUM(DM9:DP9) -> -165204.53 | DR9: =-DR10*DR$4 -> -43899.044 | DS9: =-DS10*DS$4 -> -44807.978 | DT9: =-DT10*DT$4 -> -45679.557 | DU9: =-DU10*DU$4 -> -46520.701 | DV9: =SUM(DR9:DU9) -> -180907.28 | DW9: =-DW10*DW$4 -> -47336.485 | DX9: =-DX10*DX$4 -> -48130.848 | DY9: =-DY10*DY$4 -> -48906.987 | DZ9: =-DZ10*DZ$4 -> -49667.597 | EA9: =SUM(DW9:DZ9) -> -194041.92 | EB9: =-EB10*EB$4 -> -50415.002 | EC9: =-EC10*EC$4 -> -51151.249 | ED9: =-ED10*ED$4 -> -51878.155 | EE9: =-EE10*EE$4 -> -52597.35 | EF9: =SUM(EB9:EE9) -> -206041.76
A10: % of Gross revenues | B10: =-B9/B$4 -> #DIV/0! | C10: =-C9/C$4 -> #DIV/0! | D10: =-D9/D$4 -> #DIV/0! | E10: =-E9/E$4 -> #DIV/0! | F10: =-F9/F$4 -> #DIV/0! | G10: =-G9/G$4 -> #DIV/0! | H10: =-H9/H$4 -> #DIV/0! | I10: =-I9/I$4 -> #DIV/0! | ... AH10: =-AH9/AH$4 -> #DIV/0! | AI10: 0.0208 | AJ10: =-AJ9/AJ$4 -> 0.0208 | AK10: =-AK9/AK$4 -> #DIV/0! | AL10: =-AL9/AL$4 -> #DIV/0! | AM10: =-AM9/AM$4 -> #DIV/0! | AN10: 0.0208 | AO10: =-AO9/AO$4 -> 0.0208 | AP10: =-AP9/AP$4 -> #DIV/0! | AQ10: =-AQ9/AQ$4 -> #DIV/0! | AR10: =-AR9/AR$4 -> #DIV/0! | AS10: 0.0208 | AT10: =-AT9/AT$4 -> 0.0208 | AU10: =-AU9/AU$4 -> #DIV/0! | AV10: =-AV9/AV$4 -> #DIV/0! | AW10: =-AW9/AW$4 -> #DIV/0! | AX10: 0.0208 | AY10: =-AY9/AY$4 -> 0.0208 | AZ10: =-AZ9/AZ$4 -> #DIV/0! | BA10: =-BA9/BA$4 -> #DIV/0! | BB10: =-BB9/BB$4 -> #DIV/0! | BC10: =-BC9/BC$4 -> 0.014891026 | BD10: =-BD9/BD$4 -> 0.014891026 | BE10: =-BE9/BE$4 -> #DIV/0! | BF10: =-BF9/BF$4 -> #DIV/0! | ... DI10: =-DI9/DI$4 -> 0.020373703 | DJ10: =0.37%+1.71% -> 0.0208 | DK10: =0.37%+1.71% -> 0.0208 | DL10: =-DL9/DL$4 -> 0.020362763 | DM10: =0.37%+1.71% -> 0.0208 | DN10: =0.37%+1.71% -> 0.0208 | DO10: =0.37%+1.71% -> 0.0208 | DP10: =0.37%+1.71% -> 0.0208 | DQ10: =-DQ9/DQ$4 -> 0.0208 | DR10: =0.37%+1.71% -> 0.0208 | DS10: =DR10 -> 0.0208 | DT10: =DS10 -> 0.0208 | DU10: =DT10 -> 0.0208 | DV10: =-DV9/DV$4 -> 0.0208 | DW10: =DU10 -> 0.0208 | DX10: =DW10 -> 0.0208 | DY10: =DX10 -> 0.0208 | DZ10: =DY10 -> 0.0208 | EA10: =-EA9/EA$4 -> 0.0208 | EB10: =DZ10 -> 0.0208 | EC10: =EB10 -> 0.0208 | ED10: =EC10 -> 0.0208 | EE10: =ED10 -> 0.0208 | EF10: =-EF9/EF$4 -> 0.0208
A11: Net Revenues | B11: =B4+B8 -> 0 | C11: =C4+C8 -> 0 | D11: =D4+D8 -> 0 | E11: =E4+E8 -> 0 | F11: =SUM(B11:E11) -> 0 | G11: =G4+G8 -> 0 | H11: =H4+H8 -> 0 | I11: =I4+I8 -> 0 | J11: =J4+J8 -> 0 | K11: =SUM(G11:J11) -> 0 | L11: =L4+L8 -> 0 | M11: =M4+M8 -> 0 | N11: =N4+N8 -> 0 | O11: =O4+O8 -> 0 | P11: =SUM(L11:O11) -> 0 | Q11: =Q4+Q8 -> 0 | R11: =R4+R8 -> 0 | S11: =S4+S8 -> 0 | T11: =T4+T8 -> 0 | U11: =SUM(Q11:T11) -> 0 | V11: =V4+V8 -> 0 | W11: =W4+W8 -> 0 | X11: =X4+X8 -> 0 | Y11: =Y4+Y8 -> 0 | Z11: =SUM(V11:Y11) -> 0 | AA11: =AA4+AA8 -> 0 | AB11: =AB4+AB8 -> 0 | AC11: =AC4+AC8 -> 0 | AD11: =AD4+AD8 -> 0 | AE11: =SUM(AA11:AD11) -> 0 | AF11: =AF4+AF8 -> 0 | AG11: =AG4+AG8 -> 0 | AH11: =AH4+AH8 -> 0 | AI11: =239557.567 -> 239557.57 | AJ11: =SUM(AF11:AI11) -> 239557.57 | AK11: =AK4+AK8 -> 0 | AL11: =AL4+AL8 -> 0 | AM11: =AM4+AM8 -> 0 | AN11: =424371.389 -> 424371.39 | AO11: =SUM(AK11:AN11) -> 424371.39 | AP11: =AP4+AP8 -> 0 | AQ11: =AQ4+AQ8 -> 0 | AR11: =AR4+AR8 -> 0 | AS11: =483969.357 -> 483969.36 | AT11: =SUM(AP11:AS11) -> 483969.36 | AU11: =AU4+AU8 -> 0 | AV11: =AV4+AV8 -> 0 | AW11: =AW4+AW8 -> 0 | AX11: =737421.178 -> 737421.18 | AY11: =SUM(AU11:AX11) -> 737421.18 | AZ11: =AZ4+AZ8 -> 0 | BA11: =BA4+BA8 -> 0 | BB11: =BB4+BB8 -> 0 | BC11: =BC4+BC8 -> 899371 | BD11: =SUM(AZ11:BC11) -> 899371 | BE11: =BE4+BE8 -> 0 | BF11: =BF4+BF8 -> 0 | BG11: =BG4+BG8 -> 0 | BH11: =BH4+BH8 -> 860415 | BI11: =SUM(BE11:BH11) -> 860415 | BJ11: =BJ4+BJ8 -> 0 | BK11: =BK4+BK8 -> 0 | BL11: =BL4+BL8 -> 0 | BM11: =BM4+BM8 -> 808763 | BN11: =SUM(BJ11:BM11) -> 808763 | BO11: =BO4+BO8 -> 0 | BP11: =BP4+BP8 -> 0 | BQ11: =BQ4+BQ8 -> 0 | BR11: =BR4+BR8 -> 814385 | BS11: =SUM(BO11:BR11) -> 814385 | BT11: =BT4+BT8 -> 0 | BU11: =BU4+BU8 -> 0 | BV11: =BV4+BV8 -> 0 | BW11: =BW4+BW8 -> 920253 | BX11: =SUM(BT11:BW11) -> 920253 | BY11: =BY4+BY8 -> 188370 | BZ11: =BZ4+BZ8 -> 267733 | CA11: =CA4+CA8 -> 261524 | CB11: =CB4+CB8 -> 301650 | CC11: =SUM(BY11:CB11) -> 1019277 | CD11: =CD4+CD8 -> 227321 | CE11: =CE4+CE8 -> 246204 | CF11: =CF4+CF8 -> 325897 | CG11: =CG4+CG8 -> 345260 | CH11: =SUM(CD11:CG11) -> 1144682 | CI11: =CI4+CI8 -> 339286 | CJ11: =CJ4+CJ8 -> 451337 | CK11: =CK4+CK8 -> 456449 | CL11: =CL4+CL8 -> 491223 | CM11: =SUM(CI11:CL11) -> 1738295 | CN11: =CN4+CN8 -> 447374 | CO11: =CO4+CO8 -> 602783 | CP11: =CP4+CP8 -> 626659 | CQ11: =CQ4+CQ8 -> 580478 | CR11: =SUM(CN11:CQ11) -> 2257294 | CS11: =CS4+CS8 -> 594956 | CT11: =CT4+CT8 -> 727746 | CU11: =CU4+CU8 -> 751874 | CV11: =CV4+CV8 -> 811596 | CW11: =SUM(CS11:CV11) -> 2886172 | CX11: =CX4+CX8 -> 837382 | CY11: =CY4+CY8 -> 998085 | CZ11: =CZ4+CZ8 -> 1055872 | DA11: =DA4+DA8 -> 1034971 | DB11: =SUM(CX11:DA11) -> 3926310 | DC11: =DC4+DC8 -> 1216184 | DD11: =DD4+DD8 -> 1346599 | DE11: =DE4+DE8 -> 1416926 | DF11: =DF4+DF8 -> 1419715 | DG11: =SUM(DC11:DF11) -> 5399424 | DH11: =DH4+DH8 -> 1612571 | DI11: =DI4+DI8 -> 1690594 | DJ11: =DJ4+DJ8 -> 1681801.1 | DK11: =DK4+DK8 -> 1821142.2 | DL11: =SUM(DH11:DK11) -> 6806108.3 | DM11: =DM4+DM8 -> 1860403.4 | DN11: =DN4+DN8 -> 1921666.3 | DO11: =DO4+DO8 -> 1973638.8 | DP11: =DP4+DP8 -> 2021612.5 | DQ11: =SUM(DM11:DP11) -> 7777321 | DR11: =DR4+DR8 -> 2066631.9 | DS11: =DS4+DS8 -> 2109421.7 | DT11: =DT4+DT8 -> 2150453 | DU11: =DU4+DU8 -> 2190051.4 | DV11: =SUM(DR11:DU11) -> 8516558.1 | DW11: =DW4+DW8 -> 2228456.1 | DX11: =DX4+DX8 -> 2265852.2 | DY11: =DY4+DY8 -> 2302390.5 | DZ11: =DZ4+DZ8 -> 2338197.6 | EA11: =SUM(DW11:DZ11) -> 9134896.4 | EB11: =EB4+EB8 -> 2373383.2 | EC11: =EC4+EC8 -> 2408043.4 | ED11: =ED4+ED8 -> 2442263.9 | EE11: =EE4+EE8 -> 2476121.4 | EF11: =SUM(EB11:EE11) -> 9699811.9
A12: Operating Costs | B12: =B13+B15 -> 0 | C12: =C13+C15 -> 0 | D12: =D13+D15 -> 0 | E12: =E13+E15 -> 0 | F12: =SUM(B12:E12) -> 0 | G12: =G13+G15 -> 0 | H12: =H13+H15 -> 0 | I12: =I13+I15 -> 0 | J12: =J13+J15 -> 0 | K12: =SUM(G12:J12) -> 0 | L12: =L13+L15 -> 0 | M12: =M13+M15 -> 0 | N12: =N13+N15 -> 0 | O12: =O13+O15 -> 0 | P12: =SUM(L12:O12) -> 0 | Q12: =Q13+Q15 -> 0 | R12: =R13+R15 -> 0 | S12: =S13+S15 -> 0 | T12: =T13+T15 -> 0 | U12: =SUM(Q12:T12) -> 0 | V12: =V13+V15 -> 0 | W12: =W13+W15 -> 0 | X12: =X13+X15 -> 0 | Y12: =Y13+Y15 -> 0 | Z12: =SUM(V12:Y12) -> 0 | AA12: =AA13+AA15 -> 0 | AB12: =AB13+AB15 -> 0 | AC12: =AC13+AC15 -> 0 | AD12: =AD13+AD15 -> 0 | AE12: =SUM(AA12:AD12) -> 0 | AF12: =AF13+AF14+AF15 -> 0 | AG12: =AG13+AG14+AG15 -> 0 | AH12: =AH13+AH14+AH15 -> 0 | AI12: =AI13+AI14+AI15 -> -158155.96 | AJ12: =SUM(AF12:AI12) -> -158155.96 | AK12: =AK13+AK14+AK15 -> 0 | AL12: =AL13+AL14+AL15 -> 0 | AM12: =AM13+AM14+AM15 -> 0 | AN12: =AN13+AN14+AN15 -> -295155.88 | AO12: =SUM(AK12:AN12) -> -295155.88 | AP12: =AP13+AP14+AP15 -> 0 | AQ12: =AQ13+AQ14+AQ15 -> 0 | AR12: =AR13+AR14+AR15 -> 0 | AS12: =AS13+AS14+AS15 -> -292086.1 | AT12: =SUM(AP12:AS12) -> -292086.1 | AU12: =AU13+AU14+AU15 -> 0 | AV12: =AV13+AV14+AV15 -> 0 | AW12: =AW13+AW14+AW15 -> 0 | AX12: =AX13+AX14+AX15 -> -482259.99 | AY12: =SUM(AU12:AX12) -> -482259.99 | AZ12: =AZ13+AZ14+AZ15 -> 0 | BA12: =BA13+BA14+BA15 -> 0 | BB12: =BB13+BB14+BB15 -> 0 | BC12: =BC13+BC14+BC15 -> -641536 | BD12: =SUM(AZ12:BC12) -> -641536 | BE12: =BE13+BE14+BE15 -> 0 | BF12: =BF13+BF14+BF15 -> 0 | BG12: =BG13+BG14+BG15 -> 0 | BH12: =BH13+BH14+BH15 -> -612678 | BI12: =SUM(BE12:BH12) -> -612678 | BJ12: =BJ13+BJ14+BJ15 -> 0 | BK12: =BK13+BK14+BK15 -> 0 | BL12: =BL13+BL14+BL15 -> 0 | BM12: =BM13+BM14+BM15 -> -604986 | BN12: =SUM(BJ12:BM12) -> -604986 | BO12: =BO13+BO14+BO15 -> 0 | BP12: =BP13+BP14+BP15 -> 0 | BQ12: =BQ13+BQ14+BQ15 -> 0 | BR12: =BR13+BR14+BR15 -> -570540 | BS12: =SUM(BO12:BR12) -> -570540 | BT12: =BT13+BT14+BT15 -> 0 | BU12: =BU13+BU14+BU15 -> 0 | BV12: =BV13+BV14+BV15 -> 0 | BW12: =BW13+BW14+BW15 -> -605526 | BX12: =SUM(BT12:BW12) -> -605526 | BY12: =BY13+BY14+BY15 -> -133039 | BZ12: =BZ13+BZ14+BZ15 -> -166982 | CA12: =CA13+CA14+CA15 -> -180689 | CB12: =CB13+CB14+CB15 -> -182682 | CC12: =SUM(BY12:CB12) -> -663392 | CD12: =CD13+CD14+CD15 -> -149181 | CE12: =CE13+CE14+CE15 -> -159137 | CF12: =CF13+CF14+CF15 -> -202541 | CG12: =CG13+CG14+CG15 -> -205433 | CH12: =SUM(CD12:CG12) -> -716292 | CI12: =CI13+CI14+CI15 -> -218944 | CJ12: =CJ13+CJ14+CJ15 -> -288421 | CK12: =CK13+CK14+CK15 -> -281478 | CL12: =CL13+CL14+CL15 -> -304781 | CM12: =SUM(CI12:CL12) -> -1093624 | CN12: =CN13+CN14+CN15 -> -281465 | CO12: =CO13+CO14+CO15 -> -387286 | CP12: =CP13+CP14+CP15 -> -392916 | CQ12: =CQ13+CQ14+CQ15 -> -358735 | CR12: =SUM(CN12:CQ12) -> -1420402 | CS12: =CS13+CS14+CS15 -> -371794 | CT12: =CT13+CT14+CT15 -> -453192 | CU12: =CU13+CU14+CU15 -> -467971 | CV12: =CV13+CV14+CV15 -> -497862 | CW12: =SUM(CS12:CV12) -> -1790819 | CX12: =CX13+CX14+CX15 -> -520773 | CY12: =CY13+CY14+CY15 -> -615554 | CZ12: =CZ13+CZ14+CZ15 -> -646426 | DA12: =DA13+DA14+DA15 -> -630617 | DB12: =SUM(CX12:DA12) -> -2413370 | DC12: =DC13+DC14+DC15 -> -741296 | DD12: =DD13+DD14+DD15 -> -813823 | DE12: =DE13+DE14+DE15 -> -850699 | DF12: =DF13+DF14+DF15 -> -847019 | DG12: =SUM(DC12:DF12) -> -3252837 | DH12: =DH13+DH14+DH15 -> -982915 | DI12: =DI13+DI14+DI15 -> -1022232 | DJ12: =DJ13+DJ14+DJ15 -> -1005791.1 | DK12: =DK13+DK14+DK15 -> -1085146.1 | DL12: =SUM(DH12:DK12) -> -4096084.2 | DM12: =DM13+DM14+DM15 -> -1119854.2 | DN12: =DN13+DN14+DN15 -> -1165086.6 | DO12: =DO13+DO14+DO15 -> -1207492.2 | DP12: =DP13+DP14+DP15 -> -1241866.1 | DQ12: =SUM(DM12:DP12) -> -4734299.2 | DR12: =DR13+DR14+DR15 -> -1278692.2 | DS12: =DS13+DS14+DS15 -> -1307440.5 | DT12: =DT13+DT14+DT15 -> -1335252.3 | DU12: =DU13+DU14+DU15 -> -1362230.9 | DV12: =SUM(DR12:DU12) -> -5283615.9 | DW12: =DW13+DW14+DW15 -> -1388464.5 | DX12: =DX13+DX14+DX15 -> -1414031.8 | DY12: =DY13+DY14+DY15 -> -1439005.6 | DZ12: =DZ13+DZ14+DZ15 -> -1463453.2 | EA12: =SUM(DW12:DZ12) -> -5704955.2 | EB12: =EB13+EB14+EB15 -> -1487437.4 | EC12: =EC13+EC14+EC15 -> -1511016.2 | ED12: =ED13+ED14+ED15 -> -1534243.8 | EE12: =EE13+EE14+EE15 -> -1557169.7 | EF12: =SUM(EB12:EE12) -> -6089867.1
A13: Development Sales | F13: =SUM(B13:E13) -> 0 | K13: =SUM(G13:J13) -> 0 | P13: =SUM(L13:O13) -> 0 | U13: =SUM(Q13:T13) -> 0 | Z13: =SUM(V13:Y13) -> 0 | AE13: =SUM(AA13:AD13) -> 0 | AI13: =-115953.993-SUM(AF13:AH13)-SUM(AF14:AI14) -> -115953.99 | AJ13: =SUM(AF13:AI13) -> -115953.99 | AN13: =-234604.5-SUM(AK13:AM13)-SUM(AK14:AN14) -> -234604.5 | AO13: =SUM(AK13:AN13) -> -234604.5 | AS13: =-234631.021-SUM(AP13:AR13)-SUM(AP14:AS14) -> -234631.02 | AT13: =SUM(AP13:AS13) -> -234631.02 | AX13: =-286918.331-SUM(AU13:AW13)-SUM(AU14:AX14) -> -286918.33 | AY13: =SUM(AU13:AX13) -> -286918.33 | BC13: =-290147-SUM(AZ13:BB13)-SUM(AZ14:BC14) -> -280396 | BD13: =SUM(AZ13:BC13) -> -280396 | BH13: =-283566-SUM(BE13:BG13)-SUM(BE14:BH14) -> -269379 | BI13: =SUM(BE13:BH13) -> -269379 | BM13: =-362834-SUM(BJ13:BL13)-SUM(BJ14:BM14) -> -347154 | BN13: =SUM(BJ13:BM13) -> -347154 | BR13: =-461909-SUM(BO13:BQ13)-SUM(BO14:BR14) -> -444173 | BS13: =SUM(BO13:BR13) -> -444173 | BW13: =-556203-SUM(BT13:BV13)-SUM(BT14:BW14) -> -542783 | BX13: =SUM(BT13:BW13) -> -542783 | BY13: =-124775-BY14 -> -122991 | BZ13: =-158457-BZ14 -> -156928 | CA13: =-180689-CA14-CA15 -> -171768 | CB13: =-634880-SUM(BY13:CA13)-SUM(BY14:CB14) -> -176867 | CC13: =SUM(BY13:CB13) -> -628554 | CD13: =-139488-CD14 -> -138123 | CE13: =-149870-CE14 -> -148184 | CF13: =-202541-CF14-CF15 -> -196526 | CG13: =-682997-SUM(CD13:CF13)-SUM(CD14:CG14) -> -195949 | CH13: =SUM(CD13:CG13) -> -678782 | CI13: =-213294-CI14+1020-122 -> -212274 | CJ13: =-283327+2687 -> -280640 | CK13: =-275625-5853-CK14-CK15 -> -271663 | CL13: =-1082692-SUM(CI13:CK13)-SUM(CI14:CL14) -> -316781 | CM13: =SUM(CI13:CL13) -> -1081358 | CN13: =-279593-CN14+604-607 -> -278989 | CO13: =-388579+2608 -> -385971 | CP13: =-391796-1120-CP14-CP15 -> -383036 | CQ13: =-1415751-SUM(CN13:CP13)-SUM(CN14:CQ14) -> -364471 | CR13: =SUM(CN13:CQ13) -> -1412467 | CS13: =-371450-CS14+1477-1299 -> -369973 | CT13: =-452163+725 -> -451438 | CU13: =-463481-2863 -> -466344 | CV13: =-1789464-SUM(CS13:CU13)-SUM(CS14:CV14) -> -495745 | CW13: =SUM(CS13:CV13) -> -1783500 | CX13: =-515984-CX14-2219-1856 -> -518203 | CY13: =-611200-1474 -> -612674 | CZ13: =-643412+660 -> -642752 | DA13: =-2410748-SUM(CX13:CZ13)-SUM(CX14:DA14) -> -628758 | DB13: =SUM(CX13:DA13) -> -2402387 | DC13: =-740484-DC14+1505-1711 -> -738979 | DD13: =-812123+2758 -> -809365 | DE13: =-848164+1716 -> -846448 | DF13: =-3248989-SUM(DC13:DE13)-SUM(DC14:DF14) -> -841641 | DG13: =SUM(DC13:DF13) -> -3236433 | DH13: =-977668-DH14-206-4243 -> -977874 | DI13: =-1017806+1812 -> -1015994 | DJ13: =-(1-DJ71)*DJ5 -> -1005988.6 | DK13: =-(1-DK71)*DK5 -> -1083785.9 | DL13: =SUM(DH13:DK13) -> -4083642.5 | DM13: =-(1-DM71)*DM5 -> -1118698.9 | DN13: =-(1-DN71)*DN5 -> -1158696.5 | DO13: =-(1-DO71)*DO5 -> -1197756.1 | DP13: =-(1-DP71)*DP5 -> -1229834.5 | DQ13: =SUM(DM13:DP13) -> -4704986 | DR13: =-(1-DR71)*DR5 -> -1265042.8 | DS13: =-(1-DS71)*DS5 -> -1294202.4 | DT13: =-(1-DT71)*DT5 -> -1322155.2 | DU13: =-(1-DU71)*DU5 -> -1349109 | DV13: =SUM(DR13:DU13) -> -5230509.4 | DW13: =-(1-DW71)*DW5 -> -1375217.4 | DX13: =-(1-DX71)*DX5 -> -1400599.9 | DY13: =-(1-DY71)*DY5 -> -1425354.7 | DZ13: =-(1-DZ71)*DZ5 -> -1449564.7 | EA13: =SUM(DW13:DZ13) -> -5650736.7 | EB13: =-(1-EB71)*EB5 -> -1473302.2 | EC13: =-(1-EC71)*EC5 -> -1496631.3 | ED13: =-(1-ED71)*ED5 -> -1519609.1 | EE13: =-(1-EE71)*EE5 -> -1542287.5 | EF13: =SUM(EB13:EE13) -> -6031830.1
A14: Capitalized Interest | AJ14: =SUM(AF14:AI14) -> 0 | AO14: =SUM(AK14:AN14) -> 0 | AT14: =SUM(AP14:AS14) -> 0 | AY14: =SUM(AU14:AX14) -> 0 | BC14: -9751 | BD14: =SUM(AZ14:BC14) -> -9751 | BH14: -14187 | BI14: =SUM(BE14:BH14) -> -14187 | BM14: -15680 | BN14: =SUM(BJ14:BM14) -> -15680 | BR14: =-17736 -> -17736 | BS14: =SUM(BO14:BR14) -> -17736 | BW14: =-13420 -> -13420 | BX14: =SUM(BT14:BW14) -> -13420 | BY14: -1784 | BZ14: -1529 | CA14: -1146 | CB14: =-6326-SUM(BY14:CA14) -> -1867 | CC14: =SUM(BY14:CB14) -> -6326 | CD14: -1365 | CE14: -1686 | CF14: -409 | CG14: =-4215-SUM(CD14:CF14) -> -755 | CH14: =SUM(CD14:CG14) -> -4215 | CI14: -122 | CJ14: -142 | CK14: -339 | CL14: =-1334-SUM(CI14:CK14) -> -731 | CM14: =SUM(CI14:CL14) -> -1334 | CN14: -607 | CO14: -564 | CP14: -1100 | CQ14: =-3284-SUM(CN14:CP14) -> -1013 | CR14: =SUM(CN14:CQ14) -> -3284 | CS14: -1299 | CT14: -1415 | CU14: -1489 | CV14: =-5964-SUM(CS14:CU14) -> -1761 | CW14: =SUM(CS14:CV14) -> -5964 | CX14: -1856 | CY14: -2127 | CZ14: -2041 | DA14: =-8361-SUM(CX14:CZ14) -> -2337 | DB14: =SUM(CX14:DA14) -> -8361 | DC14: -1711 | DD14: -3457 | DE14: -3061 | DF14: =-12556-SUM(DC14:DE14) -> -4327 | DG14: =SUM(DC14:DF14) -> -12556 | DH14: -4243 | DI14: -5275 | DJ14: =-'Balance Sheet'!DI133/(Forecasts!DI24)*Forecasts!DJ21+0.1%*Forecasts!DJ40 -> 883.1273 | DK14: =-'Balance Sheet'!DJ133/(Forecasts!DJ24)*Forecasts!DK21+0.6%*Forecasts!DK40 -> -617.70213 | DL14: =SUM(DH14:DK14) -> -9252.5748 | DM14: =-'Balance Sheet'!DL133/(Forecasts!DL24)*Forecasts!DM21+1.2%*Forecasts!DM40 -> -17.590617 | DN14: =-'Balance Sheet'!DM133/(Forecasts!DM24)*Forecasts!DN21+1.2%*Forecasts!DN40 -> -5214.9784 | DO14: =-'Balance Sheet'!DN133/(Forecasts!DN24)*Forecasts!DO21+1.2%*Forecasts!DO40 -> -8529.2455 | DP14: =-'Balance Sheet'!DO133/(Forecasts!DO24)*Forecasts!DP21+1.2%*Forecasts!DP40 -> -10795.302 | DQ14: =SUM(DM14:DP14) -> -24557.116 | DR14: =-'Balance Sheet'!DQ133/(Forecasts!DQ24)*Forecasts!DR21+1.2%*Forecasts!DR40 -> -12385.645 | DS14: =-'Balance Sheet'!DR133/(Forecasts!DR24)*Forecasts!DS21+1.2%*Forecasts!DS40 -> -11948.083 | DT14: =-'Balance Sheet'!DS133/(Forecasts!DS24)*Forecasts!DT21+1.2%*Forecasts!DT40 -> -11782.036 | DU14: =-'Balance Sheet'!DT133/(Forecasts!DT24)*Forecasts!DU21+1.2%*Forecasts!DU40 -> -11782.634 | DV14: =SUM(DR14:DU14) -> -47898.399 | DW14: =-'Balance Sheet'!DV133/(Forecasts!DV24)*Forecasts!DW21+1.2%*Forecasts!DW40 -> -11884.346 | DX14: =-'Balance Sheet'!DW133/(Forecasts!DW24)*Forecasts!DX21+1.2%*Forecasts!DX40 -> -12046.278 | DY14: =-'Balance Sheet'!DX133/(Forecasts!DX24)*Forecasts!DY21+1.2%*Forecasts!DY40 -> -12242.981 | DZ14: =-'Balance Sheet'!DY133/(Forecasts!DY24)*Forecasts!DZ21+1.2%*Forecasts!DZ40 -> -12458.705 | EA14: =SUM(DW14:DZ14) -> -48632.31 | EB14: =-'Balance Sheet'!EA133/(Forecasts!EA24)*Forecasts!EB21+1.2%*Forecasts!EB40 -> -12683.79 | EC14: =-'Balance Sheet'!EB133/(Forecasts!EB24)*Forecasts!EC21+1.2%*Forecasts!EC40 -> -12912.406 | ED14: =-'Balance Sheet'!EC133/(Forecasts!EC24)*Forecasts!ED21+1.2%*Forecasts!ED40 -> -13141.127 | EE14: =-'Balance Sheet'!ED133/(Forecasts!ED24)*Forecasts!EE21+1.2%*Forecasts!EE40 -> -13368.027 | EF14: =SUM(EB14:EE14) -> -52105.349
A15: Services | F15: =SUM(B15:E15) -> 0 | K15: =SUM(G15:J15) -> 0 | P15: =SUM(L15:O15) -> 0 | U15: =SUM(Q15:T15) -> 0 | Z15: =SUM(V15:Y15) -> 0 | AE15: =SUM(AA15:AD15) -> 0 | AI15: -42201.965 | AJ15: =SUM(AF15:AI15) -> -42201.965 | AN15: -60551.383 | AO15: =SUM(AK15:AN15) -> -60551.383 | AS15: -57455.075 | AT15: =SUM(AP15:AS15) -> -57455.075 | AX15: -195341.66 | AY15: =SUM(AU15:AX15) -> -195341.66 | BC15: -351389 | BD15: =SUM(AZ15:BC15) -> -351389 | BH15: -329112 | BI15: =SUM(BE15:BH15) -> -329112 | BM15: -242152 | BN15: =SUM(BJ15:BM15) -> -242152 | BR15: -108631 | BS15: =SUM(BO15:BR15) -> -108631 | BW15: -49323 | BX15: =SUM(BT15:BW15) -> -49323 | BY15: -8264 | BZ15: -8525 | CA15: -7775 | CB15: =-28512-SUM(BY15:CA15) -> -3948 | CC15: =SUM(BY15:CB15) -> -28512 | CD15: -9693 | CE15: -9267 | CF15: -5606 | CG15: =-33295-SUM(CD15:CF15) -> -8729 | CH15: =SUM(CD15:CG15) -> -33295 | CI15: -6548 | CJ15: -7639 | CK15: -9476 | CL15: =-10932-SUM(CI15:CK15) -> 12731 | CM15: =SUM(CI15:CL15) -> -10932 | CN15: -1869 | CO15: -751 | CP15: -8780 | CQ15: =-4651-SUM(CN15:CP15) -> 6749 | CR15: =SUM(CN15:CQ15) -> -4651 | CS15: -522 | CT15: -339 | CU15: -138 | CV15: =-1355-SUM(CS15:CU15) -> -356 | CW15: =SUM(CS15:CV15) -> -1355 | CX15: -714 | CY15: -753 | CZ15: -1633 | DA15: =-2622-SUM(CX15:CZ15) -> 478 | DB15: =SUM(CX15:DA15) -> -2622 | DC15: -606 | DD15: -1001 | DE15: -1190 | DF15: =-3848-SUM(DC15:DE15) -> -1051 | DG15: =SUM(DC15:DF15) -> -3848 | DH15: -798 | DI15: -963 | DJ15: =-(1-DJ72)*DJ7 -> -685.63896 | DK15: =-(1-DK72)*DK7 -> -742.44576 | DL15: =SUM(DH15:DK15) -> -3189.0847 | DM15: =-(1-DM72)*DM7 -> -1137.6777 | DN15: =-(1-DN72)*DN7 -> -1175.1413 | DO15: =-(1-DO72)*DO7 -> -1206.9237 | DP15: =-(1-DP72)*DP7 -> -1236.2606 | DQ15: =SUM(DM15:DP15) -> -4756.0033 | DR15: =-(1-DR72)*DR7 -> -1263.791 | DS15: =-(1-DS72)*DS7 -> -1289.9579 | DT15: =-(1-DT72)*DT7 -> -1315.0494 | DU15: =-(1-DU72)*DU7 -> -1339.2648 | DV15: =SUM(DR15:DU15) -> -5208.0631 | DW15: =-(1-DW72)*DW7 -> -1362.75 | DX15: =-(1-DX72)*DX7 -> -1385.6186 | DY15: =-(1-DY72)*DY7 -> -1407.9626 | DZ15: =-(1-DZ72)*DZ7 -> -1429.8594 | EA15: =SUM(DW15:DZ15) -> -5586.1906 | EB15: =-(1-EB72)*EB7 -> -1451.3762 | EC15: =-(1-EC72)*EC7 -> -1472.5716 | ED15: =-(1-ED72)*ED7 -> -1493.4982 | EE15: =-(1-EE72)*EE7 -> -1514.2029 | EF15: =SUM(EB15:EE15) -> -5931.6489
A16: Gross Profit | B16: =+B11+B12 -> 0 | C16: =+C11+C12 -> 0 | D16: =+D11+D12 -> 0 | E16: =+E11+E12 -> 0 | F16: =SUM(B16:E16) -> 0 | G16: =+G11+G12 -> 0 | H16: =+H11+H12 -> 0 | I16: =+I11+I12 -> 0 | J16: =+J11+J12 -> 0 | K16: =SUM(G16:J16) -> 0 | L16: =+L11+L12 -> 0 | M16: =+M11+M12 -> 0 | N16: =+N11+N12 -> 0 | O16: =+O11+O12 -> 0 | P16: =SUM(L16:O16) -> 0 | Q16: =+Q11+Q12 -> 0 | R16: =+R11+R12 -> 0 | S16: =+S11+S12 -> 0 | T16: =+T11+T12 -> 0 | U16: =SUM(Q16:T16) -> 0 | V16: =+V11+V12 -> 0 | W16: =+W11+W12 -> 0 | X16: =+X11+X12 -> 0 | Y16: =+Y11+Y12 -> 0 | Z16: =SUM(V16:Y16) -> 0 | AA16: =+AA11+AA12 -> 0 | AB16: =+AB11+AB12 -> 0 | AC16: =+AC11+AC12 -> 0 | AD16: =+AD11+AD12 -> 0 | AE16: =SUM(AA16:AD16) -> 0 | AF16: =+AF11+AF12 -> 0 | AG16: =+AG11+AG12 -> 0 | AH16: =+AH11+AH12 -> 0 | AI16: =+AI11+AI12 -> 81401.609 | AJ16: =SUM(AF16:AI16) -> 81401.609 | AK16: =+AK11+AK12 -> 0 | AL16: =+AL11+AL12 -> 0 | AM16: =+AM11+AM12 -> 0 | AN16: =+AN11+AN12 -> 129215.51 | AO16: =SUM(AK16:AN16) -> 129215.51 | AP16: =+AP11+AP12 -> 0 | AQ16: =+AQ11+AQ12 -> 0 | AR16: =+AR11+AR12 -> 0 | AS16: =+AS11+AS12 -> 191883.26 | AT16: =SUM(AP16:AS16) -> 191883.26 | AU16: =+AU11+AU12 -> 0 | AV16: =+AV11+AV12 -> 0 | AW16: =+AW11+AW12 -> 0 | AX16: =+AX11+AX12 -> 255161.18 | AY16: =SUM(AU16:AX16) -> 255161.18 | AZ16: =+AZ11+AZ12 -> 0 | BA16: =+BA11+BA12 -> 0 | BB16: =+BB11+BB12 -> 0 | BC16: =+BC11+BC12 -> 257835 | BD16: =SUM(AZ16:BC16) -> 257835 | BE16: =+BE11+BE12 -> 0 | BF16: =+BF11+BF12 -> 0 | BG16: =+BG11+BG12 -> 0 | BH16: =+BH11+BH12 -> 247737 | BI16: =SUM(BE16:BH16) -> 247737 | BJ16: =+BJ11+BJ12 -> 0 | BK16: =+BK11+BK12 -> 0 | BL16: =+BL11+BL12 -> 0 | BM16: =+BM11+BM12 -> 203777 | BN16: =SUM(BJ16:BM16) -> 203777 | BO16: =+BO11+BO12 -> 0 | BP16: =+BP11+BP12 -> 0 | BQ16: =+BQ11+BQ12 -> 0 | BR16: =+BR11+BR12 -> 243845 | BS16: =SUM(BO16:BR16) -> 243845 | BT16: =+BT11+BT12 -> 0 | BU16: =+BU11+BU12 -> 0 | BV16: =+BV11+BV12 -> 0 | BW16: =+BW11+BW12 -> 314727 | BX16: =SUM(BT16:BW16) -> 314727 | BY16: =+BY11+BY12 -> 55331 | BZ16: =+BZ11+BZ12 -> 100751 | CA16: =+CA11+CA12 -> 80835 | CB16: =+CB11+CB12 -> 118968 | CC16: =SUM(BY16:CB16) -> 355885 | CD16: =+CD11+CD12 -> 78140 | CE16: =+CE11+CE12 -> 87067 | CF16: =+CF11+CF12 -> 123356 | CG16: =+CG11+CG12 -> 139827 | CH16: =SUM(CD16:CG16) -> 428390 | CI16: =+CI11+CI12 -> 120342 | CJ16: =+CJ11+CJ12 -> 162916 | CK16: =+CK11+CK12 -> 174971 | CL16: =+CL11+CL12 -> 186442 | CM16: =SUM(CI16:CL16) -> 644671 | CN16: =+CN11+CN12 -> 165909 | CO16: =+CO11+CO12 -> 215497 | CP16: =+CP11+CP12 -> 233743 | CQ16: =+CQ11+CQ12 -> 221743 | CR16: =SUM(CN16:CQ16) -> 836892 | CS16: =+CS11+CS12 -> 223162 | CT16: =+CT11+CT12 -> 274554 | CU16: =+CU11+CU12 -> 283903 | CV16: =+CV11+CV12 -> 313734 | CW16: =SUM(CS16:CV16) -> 1095353 | CX16: =+CX11+CX12 -> 316609 | CY16: =+CY11+CY12 -> 382531 | CZ16: =+CZ11+CZ12 -> 409446 | DA16: =+DA11+DA12 -> 404354 | DB16: =SUM(CX16:DA16) -> 1512940 | DC16: =+DC11+DC12 -> 474888 | DD16: =+DD11+DD12 -> 532776 | DE16: =+DE11+DE12 -> 566227 | DF16: =+DF11+DF12 -> 572696 | DG16: =SUM(DC16:DF16) -> 2146587 | DH16: =+DH11+DH12 -> 629656 | DI16: =+DI11+DI12 -> 668362 | DJ16: =+DJ11+DJ12 -> 676010.01 | DK16: =+DK11+DK12 -> 735996.15 | DL16: =SUM(DH16:DK16) -> 2710024.2 | DM16: =+DM11+DM12 -> 740549.19 | DN16: =+DN11+DN12 -> 756579.69 | DO16: =+DO11+DO12 -> 766146.58 | DP16: =+DP11+DP12 -> 779746.43 | DQ16: =SUM(DM16:DP16) -> 3043021.9 | DR16: =+DR11+DR12 -> 787939.65 | DS16: =+DS11+DS12 -> 801981.27 | DT16: =+DT11+DT12 -> 815200.74 | DU16: =+DU11+DU12 -> 827820.51 | DV16: =SUM(DR16:DU16) -> 3232942.2 | DW16: =+DW11+DW12 -> 839991.59 | DX16: =+DX11+DX12 -> 851820.39 | DY16: =+DY11+DY12 -> 863384.87 | DZ16: =+DZ11+DZ12 -> 874744.41 | EA16: =SUM(DW16:DZ16) -> 3429941.3 | EB16: =+EB11+EB12 -> 885945.82 | EC16: =+EC11+EC12 -> 897027.16 | ED16: =+ED11+ED12 -> 908020.13 | EE16: =+EE11+EE12 -> 918951.7 | EF16: =SUM(EB16:EE16) -> 3609944.8
A17: Operating (Expenses) Income | B17: =B18+B21+B23+B32+B36+B29 -> 0 | C17: =C18+C21+C23+C32+C36+C29 -> 0 | D17: =D18+D21+D23+D32+D36+D29 -> 0 | E17: =E18+E21+E23+E32+E36+E29 -> 0 | F17: =SUM(B17:E17) -> 0 | G17: =G18+G21+G23+G32+G36+G29 -> 0 | H17: =H18+H21+H23+H32+H36+H29 -> 0 | I17: =I18+I21+I23+I32+I36+I29 -> 0 | J17: =J18+J21+J23+J32+J36+J29 -> 0 | K17: =SUM(G17:J17) -> 0 | L17: =L18+L21+L23+L32+L36+L29 -> 0 | M17: =M18+M21+M23+M32+M36+M29 -> 0 | N17: =N18+N21+N23+N32+N36+N29 -> 0 | O17: =O18+O21+O23+O32+O36+O29 -> 0 | P17: =SUM(L17:O17) -> 0 | Q17: =Q18+Q21+Q23+Q32+Q36+Q29 -> 0 | R17: =R18+R21+R23+R32+R36+R29 -> 0 | S17: =S18+S21+S23+S32+S36+S29 -> 0 | T17: =T18+T21+T23+T32+T36+T29 -> 0 | U17: =SUM(Q17:T17) -> 0 | V17: =V18+V21+V23+V32+V36+V29 -> 0 | W17: =W18+W21+W23+W32+W36+W29 -> 0 | X17: =X18+X21+X23+X32+X36+X29 -> 0 | Y17: =Y18+Y21+Y23+Y32+Y36+Y29 -> 0 | Z17: =SUM(V17:Y17) -> 0 | AA17: =AA18+AA21+AA23+AA32+AA36+AA29 -> 0 | AB17: =AB18+AB21+AB23+AB32+AB36+AB29 -> 0 | AC17: =AC18+AC21+AC23+AC32+AC36+AC29 -> 0 | AD17: =AD18+AD21+AD23+AD32+AD36+AD29 -> 0 | AE17: =SUM(AA17:AD17) -> 0 | AF17: =AF18+AF21+AF23+AF32+AF36+AF29 -> 0 | AG17: =AG18+AG21+AG23+AG32+AG36+AG29 -> 0 | AH17: =AH18+AH21+AH23+AH32+AH36+AH29 -> 0 | AI17: =AI18+AI21+AI23+AI32+AI36+AI29 -> -23329.799 | AJ17: =SUM(AF17:AI17) -> -23329.799 | AK17: =AK18+AK21+AK23+AK32+AK36+AK29 -> 0 | AL17: =AL18+AL21+AL23+AL32+AL36+AL29 -> 0 | AM17: =AM18+AM21+AM23+AM32+AM36+AM29 -> 0 | AN17: =AN18+AN21+AN23+AN32+AN36+AN29 -> -27444.689 | AO17: =SUM(AK17:AN17) -> -27444.689 | AP17: =AP18+AP21+AP23+AP32+AP36+AP29 -> 0 | AQ17: =AQ18+AQ21+AQ23+AQ32+AQ36+AQ29 -> 0 | AR17: =AR18+AR21+AR23+AR32+AR36+AR29 -> 0 | AS17: =AS18+AS21+AS23+AS32+AS36+AS29 -> -56921.447 | AT17: =SUM(AP17:AS17) -> -56921.447 | AU17: =AU18+AU21+AU23+AU32+AU36+AU29 -> 0 | AV17: =AV18+AV21+AV23+AV32+AV36+AV29 -> 0 | AW17: =AW18+AW21+AW23+AW32+AW36+AW29 -> 0 | AX17: =AX18+AX21+AX23+AX32+AX36+AX29 -> -69870.619 | AY17: =SUM(AU17:AX17) -> -69870.619 | AZ17: =AZ18+AZ21+AZ23+AZ32+AZ36+AZ29 -> 0 | BA17: =BA18+BA21+BA23+BA32+BA36+BA29 -> 0 | BB17: =BB18+BB21+BB23+BB32+BB36+BB29 -> 0 | BC17: =BC18+BC21+BC23+BC32+BC36+BC29 -> -73241 | BD17: =SUM(AZ17:BC17) -> -73241 | BE17: =BE18+BE21+BE23+BE32+BE36+BE29 -> 0 | BF17: =BF18+BF21+BF23+BF32+BF36+BF29 -> 0 | BG17: =BG18+BG21+BG23+BG32+BG36+BG29 -> 0 | BH17: =BH18+BH21+BH23+BH32+BH36+BH29 -> -75968 | BI17: =SUM(BE17:BH17) -> -75968 | BJ17: =BJ18+BJ21+BJ23+BJ32+BJ36+BJ29 -> 0 | BK17: =BK18+BK21+BK23+BK32+BK36+BK29 -> 0 | BL17: =BL18+BL21+BL23+BL32+BL36+BL29 -> 0 | BM17: =BM18+BM21+BM23+BM32+BM36+BM29 -> -80668 | BN17: =SUM(BJ17:BM17) -> -80668 | BO17: =BO18+BO21+BO23+BO32+BO36+BO29 -> 0 | BP17: =BP18+BP21+BP23+BP32+BP36+BP29 -> 0 | BQ17: =BQ18+BQ21+BQ23+BQ32+BQ36+BQ29 -> 0 | BR17: =BR18+BR21+BR23+BR32+BR36+BR29 -> -101249 | BS17: =SUM(BO17:BR17) -> -101249 | BT17: =BT18+BT21+BT23+BT32+BT36+BT29 -> 0 | BU17: =BU18+BU21+BU23+BU32+BU36+BU29 -> 0 | BV17: =BV18+BV21+BV23+BV32+BV36+BV29 -> 0 | BW17: =BW18+BW21+BW23+BW32+BW36+BW29 -> -120266 | BX17: =SUM(BT17:BW17) -> -120266 | BY17: =BY18+BY21+BY23+BY32+BY36+BY29 -> -27074 | BZ17: =BZ18+BZ21+BZ23+BZ32+BZ36+BZ29 -> -21483 | CA17: =CA18+CA21+CA23+CA32+CA36+CA29 -> -35652 | CB17: =CB18+CB21+CB23+CB32+CB36+CB29 -> -45581 | CC17: =SUM(BY17:CB17) -> -129790 | CD17: =CD18+CD21+CD23+CD32+CD36+CD29 -> -54985 | CE17: =CE18+CE21+CE23+CE32+CE36+CE29 -> -41183 | CF17: =CF18+CF21+CF23+CF32+CF36+CF29 -> -57238 | CG17: =CG18+CG21+CG23+CG32+CG36+CG29 -> -58772 | CH17: =SUM(CD17:CG17) -> -212178 | CI17: =CI18+CI21+CI23+CI32+CI36+CI29 -> -61395 | CJ17: =CJ18+CJ21+CJ23+CJ32+CJ36+CJ29 -> -77551 | CK17: =CK18+CK21+CK23+CK32+CK36+CK29 -> -89995 | CL17: =CL18+CL21+CL23+CL32+CL36+CL29 -> -64089 | CM17: =SUM(CI17:CL17) -> -293030 | CN17: =CN18+CN21+CN23+CN32+CN36+CN29 -> -90921 | CO17: =CO18+CO21+CO23+CO32+CO36+CO29 -> -108110 | CP17: =CP18+CP21+CP23+CP32+CP36+CP29 -> -123338 | CQ17: =CQ18+CQ21+CQ23+CQ32+CQ36+CQ29 -> -109519 | CR17: =SUM(CN17:CQ17) -> -431888 | CS17: =CS18+CS21+CS23+CS32+CS36+CS29 -> -113770 | CT17: =CT18+CT21+CT23+CT32+CT36+CT29 -> -132289 | CU17: =CU18+CU21+CU23+CU32+CU36+CU29 -> -151884 | CV17: =CV18+CV21+CV23+CV32+CV36+CV29 -> -129381 | CW17: =SUM(CS17:CV17) -> -527324 | CX17: =CX18+CX21+CX23+CX32+CX36+CX29 -> -142353 | CY17: =CY18+CY21+CY23+CY32+CY36+CY29 -> -186341 | CZ17: =CZ18+CZ21+CZ23+CZ32+CZ36+CZ29 -> -205856 | DA17: =DA18+DA21+DA23+DA32+DA36+DA29 -> -189794 | DB17: =SUM(CX17:DA17) -> -724344 | DC17: =DC18+DC21+DC23+DC32+DC36+DC29 -> -210221 | DD17: =DD18+DD21+DD23+DD32+DD36+DD29 -> -234180 | DE17: =DE18+DE21+DE23+DE32+DE36+DE29 -> -246254 | DF17: =DF18+DF21+DF23+DF32+DF36+DF29 -> -235686 | DG17: =SUM(DC17:DF17) -> -926341 | DH17: =DH18+DH21+DH23+DH32+DH36+DH29 -> -237220 | DI17: =DI18+DI21+DI23+DI32+DI36+DI29 -> -312057 | DJ17: =DJ18+DJ21+DJ23+DJ32+DJ36+DJ29 -> -291971.16 | DK17: =DK18+DK21+DK23+DK32+DK36+DK29 -> -291279.92 | DL17: =SUM(DH17:DK17) -> -1132528.1 | DM17: =DM18+DM21+DM23+DM32+DM36+DM29 -> -296128.76 | DN17: =DN18+DN21+DN23+DN32+DN36+DN29 -> -297883.5 | DO17: =DO18+DO21+DO23+DO32+DO36+DO29 -> -301478.02 | DP17: =DP18+DP21+DP23+DP32+DP36+DP29 -> -300878.53 | DQ17: =SUM(DM17:DP17) -> -1196368.8 | DR17: =DR18+DR21+DR23+DR32+DR36+DR29 -> -291747.21 | DS17: =DS18+DS21+DS23+DS32+DS36+DS29 -> -306989.04 | DT17: =DT18+DT21+DT23+DT32+DT36+DT29 -> -303975.78 | DU17: =DU18+DU21+DU23+DU32+DU36+DU29 -> -296690.63 | DV17: =SUM(DR17:DU17) -> -1199402.7 | DW17: =DW18+DW21+DW23+DW32+DW36+DW29 -> -311551.43 | DX17: =DX18+DX21+DX23+DX32+DX36+DX29 -> -326486.49 | DY17: =DY18+DY21+DY23+DY32+DY36+DY29 -> -318750.66 | DZ17: =DZ18+DZ21+DZ23+DZ32+DZ36+DZ29 -> -310443.77 | EA17: =SUM(DW17:DZ17) -> -1267232.3 | EB17: =EB18+EB21+EB23+EB32+EB36+EB29 -> -325551.28 | EC17: =EC18+EC21+EC23+EC32+EC36+EC29 -> -340870.47 | ED17: =ED18+ED21+ED23+ED32+ED36+ED29 -> -332506.21 | EE17: =EE18+EE21+EE23+EE32+EE36+EE29 -> -323751.11 | EF17: =SUM(EB17:EE17) -> -1322679.1
A18: Selling Expenses | F18: =SUM(B18:E18) -> 0 | K18: =SUM(G18:J18) -> 0 | P18: =SUM(L18:O18) -> 0 | U18: =SUM(Q18:T18) -> 0 | Z18: =SUM(V18:Y18) -> 0 | AE18: =SUM(AA18:AD18) -> 0 | AI18: =-8042.308-SUM(AF18:AH18) -> -8042.308 | AJ18: =SUM(AF18:AI18) -> -8042.308 | AN18: =-11911.677-SUM(AK18:AM18) -> -11911.677 | AO18: =SUM(AK18:AN18) -> -11911.677 | AS18: =-28990.812-SUM(AP18:AR18) -> -28990.812 | AT18: =SUM(AP18:AS18) -> -28990.812 | AX18: =-20516.139-SUM(AU18:AW18) -> -20516.139 | AY18: =SUM(AU18:AX18) -> -20516.139 | BC18: =-19009-SUM(AZ18:BB18) -> -19009 | BD18: =SUM(AZ18:BC18) -> -19009 | BH18: =-18855-SUM(BE18:BG18) -> -18855 | BI18: =SUM(BE18:BH18) -> -18855 | BM18: =-26206-SUM(BJ18:BL18) -> -26206 | BN18: =SUM(BJ18:BM18) -> -26206 | BR18: =-43270-SUM(BO18:BQ18) -> -43270 | BS18: =SUM(BO18:BR18) -> -43270 | BW18: =-45831-SUM(BT18:BV18) -> -45831 | BX18: =SUM(BT18:BW18) -> -45831 | BY18: -14144 | BZ18: -20312 | CA18: -26575 | CB18: =-100668-SUM(BY18:CA18) -> -39637 | CC18: =SUM(BY18:CB18) -> -100668 | CD18: -22046 | CE18: -26343 | CF18: -27428 | CG18: =-102804-SUM(CD18:CF18) -> -26987 | CH18: =SUM(CD18:CG18) -> -102804 | CI18: -30360 | CJ18: -38953 | CK18: -47954 | CL18: =-164226-SUM(CI18:CK18) -> -46959 | CM18: =SUM(CI18:CL18) -> -164226 | CN18: -44417 | CO18: -53835 | CP18: -59384 | CQ18: =-212188-SUM(CN18:CP18) -> -54552 | CR18: =SUM(CN18:CQ18) -> -212188 | CS18: -62031 | CT18: -66728 | CU18: -80995 | CV18: =-285230-SUM(CS18:CU18) -> -75476 | CW18: =SUM(CS18:CV18) -> -285230 | CX18: -76092 | CY18: -97945 | CZ18: -113852 | DA18: =-391872-SUM(CX18:CZ18) -> -103983 | DB18: =SUM(CX18:DA18) -> -391872 | DC18: -106236 | DD18: -124747 | DE18: -134823 | DF18: =-494891-SUM(DC18:DE18) -> -129085 | DG18: =SUM(DC18:DF18) -> -494891 | DH18: -119070 | DI18: -166790 | DJ18: =-DJ20*(Forecasts!DJ15+Forecasts!DJ17) -> -152375.29 | DK18: =-DK20*(Forecasts!DK15+Forecasts!DK17) -> -156660 | DL18: =SUM(DH18:DK18) -> -594895.29 | DM18: =-DM20*(Forecasts!DM15+Forecasts!DM17) -> -163478.51 | DN18: =-DN20*(Forecasts!DN15+Forecasts!DN17) -> -167046.26 | DO18: =-DO20*(Forecasts!DO15+Forecasts!DO17) -> -169973.45 | DP18: =-DP20*(Forecasts!DP15+Forecasts!DP17) -> -172628.25 | DQ18: =SUM(DM18:DP18) -> -673126.48 | DR18: =-DR20*(Forecasts!DR15+Forecasts!DR17) -> -175123.46 | DS18: =-DS20*(Forecasts!DS15+Forecasts!DS17) -> -177526.36 | DT18: =-DT20*(Forecasts!DT15+Forecasts!DT17) -> -179875.6 | DU18: =-DU20*(Forecasts!DU15+Forecasts!DU17) -> -182193.92 | DV18: =SUM(DR18:DU18) -> -714719.34 | DW18: =-DW20*(Forecasts!DW15+Forecasts!DW17) -> -184495.15 | DX18: =-DX20*(Forecasts!DX15+Forecasts!DX17) -> -186788.04 | DY18: =-DY20*(Forecasts!DY15+Forecasts!DY17) -> -189078.44 | DZ18: =-DZ20*(Forecasts!DZ15+Forecasts!DZ17) -> -191370.5 | EA18: =SUM(DW18:DZ18) -> -751732.14 | EB18: =-EB20*(Forecasts!EB15+Forecasts!EB17) -> -193667.39 | EC18: =-EC20*(Forecasts!EC15+Forecasts!EC17) -> -195971.6 | ED18: =-ED20*(Forecasts!ED15+Forecasts!ED17) -> -198285.24 | EE18: =-EE20*(Forecasts!EE15+Forecasts!EE17) -> -200610.11 | EF18: =SUM(EB18:EE18) -> -788534.33
A19: % of revenues | B19: =-B18/B11 -> #DIV/0! | C19: =-C18/C11 -> #DIV/0! | D19: =-D18/D11 -> #DIV/0! | E19: =-E18/E11 -> #DIV/0! | F19: =-F18/F11 -> #DIV/0! | G19: =-G18/G11 -> #DIV/0! | H19: =-H18/H11 -> #DIV/0! | I19: =-I18/I11 -> #DIV/0! | ... EF19: =-EF18/EF11 -> 0.081293776
A20: % of sales | B20: =-B18/Forecasts!B10 -> #DIV/0! | C20: =-C18/Forecasts!C10 -> #DIV/0! | D20: =-D18/Forecasts!D10 -> #DIV/0! | E20: =-E18/Forecasts!E10 -> #DIV/0! | F20: =-F18/Forecasts!F10 -> #DIV/0! | G20: =-G18/Forecasts!G10 -> #DIV/0! | H20: =-H18/Forecasts!H10 -> #DIV/0! | I20: =-I18/Forecasts!I10 -> #DIV/0! | ... AE20: =-AE18/Forecasts!AE10 -> #DIV/0! | AF20: =-AF18/(Forecasts!AF15+Forecasts!AF17) -> #DIV/0! | AG20: =-AG18/(Forecasts!AG15+Forecasts!AG17) -> #DIV/0! | AH20: =-AH18/(Forecasts!AH15+Forecasts!AH17) -> #DIV/0! | AI20: =-AI18/(Forecasts!AI15+Forecasts!AI17) -> #DIV/0! | AJ20: =-AJ18/Forecasts!AJ10 -> #DIV/0! | AK20: =-AK18/(Forecasts!AK15+Forecasts!AK17) -> #DIV/0! | AL20: =-AL18/(Forecasts!AL15+Forecasts!AL17) -> #DIV/0! | AM20: =-AM18/(Forecasts!AM15+Forecasts!AM17) -> #DIV/0! | AN20: =-AN18/(Forecasts!AN15+Forecasts!AN17) -> #DIV/0! | AO20: =-AO18/Forecasts!AO10 -> #DIV/0! | AP20: =-AP18/(Forecasts!AP15+Forecasts!AP17) -> #DIV/0! | AQ20: =-AQ18/(Forecasts!AQ15+Forecasts!AQ17) -> #DIV/0! | AR20: =-AR18/(Forecasts!AR15+Forecasts!AR17) -> #DIV/0! | AS20: =-AS18/(Forecasts!AS15+Forecasts!AS17) -> #DIV/0! | AT20: =-AT18/Forecasts!AT10 -> #DIV/0! | AU20: =-AU18/(Forecasts!AU15+Forecasts!AU17) -> #DIV/0! | AV20: =-AV18/(Forecasts!AV15+Forecasts!AV17) -> #DIV/0! | AW20: =-AW18/(Forecasts!AW15+Forecasts!AW17) -> #DIV/0! | AX20: =-AX18/(Forecasts!AX15+Forecasts!AX17) -> #DIV/0! | AY20: =-AY18/(Forecasts!AY15+Forecasts!AY17) -> #DIV/0! | AZ20: =-AZ18/(Forecasts!AZ15+Forecasts!AZ17) -> #DIV/0! | BA20: =-BA18/(Forecasts!BA15+Forecasts!BA17) -> #DIV/0! | BB20: =-BB18/(Forecasts!BB15+Forecasts!BB17) -> #DIV/0! | ... DI20: =-DI18/(Forecasts!DI15+Forecasts!DI17) -> 0.075242216 | DJ20: 0.065 | DK20: 0.065 | DL20: =-DL18/(Forecasts!DL15+Forecasts!DL17) -> 0.062587507 | DM20: 0.065 | DN20: =DM20 -> 0.065 | DO20: =DN20 -> 0.065 | DP20: =DO20 -> 0.065 | DQ20: =-DQ18/(Forecasts!DQ15+Forecasts!DQ17) -> 0.065 | DR20: =DP20 -> 0.065 | DS20: =DR20 -> 0.065 | DT20: =DS20 -> 0.065 | DU20: =DT20 -> 0.065 | DV20: =-DV18/(Forecasts!DV15+Forecasts!DV17) -> 0.065 | DW20: =DU20 -> 0.065 | DX20: =DW20 -> 0.065 | DY20: =DX20 -> 0.065 | DZ20: =DY20 -> 0.065 | EA20: =-EA18/(Forecasts!EA15+Forecasts!EA17) -> 0.065 | EB20: =DZ20 -> 0.065 | EC20: =EB20 -> 0.065 | ED20: =EC20 -> 0.065 | EE20: =ED20 -> 0.065 | EF20: =-EF18/(Forecasts!EF15+Forecasts!EF17) -> 0.065
A21: G&A Expenses | F21: =SUM(B21:E21) -> 0 | K21: =SUM(G21:J21) -> 0 | P21: =SUM(L21:O21) -> 0 | U21: =SUM(Q21:T21) -> 0 | Z21: =SUM(V21:Y21) -> 0 | AE21: =SUM(AA21:AD21) -> 0 | AI21: =-17940.809-SUM(AF21:AH21) -> -17940.809 | AJ21: =SUM(AF21:AI21) -> -17940.809 | AN21: =-24844.193-SUM(AK21:AM21) -> -24844.193 | AO21: =SUM(AK21:AN21) -> -24844.193 | AS21: =-45247.462-SUM(AP21:AR21) -> -45247.462 | AT21: =SUM(AP21:AS21) -> -45247.462 | AX21: =-51886.296-SUM(AU21:AW21) -> -51886.296 | AY21: =SUM(AU21:AX21) -> -51886.296 | BC21: =-59532-SUM(AZ21:BB21)-SUM(AZ34:BC34) -> -54590 | BD21: =SUM(AZ21:BC21) -> -54590 | BH21: =-65477-SUM(BE21:BG21)-SUM(BE34:BH34) -> -62109 | BI21: =SUM(BE21:BH21) -> -62109 | BM21: =-62654-SUM(BJ21:BL21)-SUM(BJ34:BM34) -> -56880 | BN21: =SUM(BJ21:BM21) -> -56880 | BR21: =-103345-SUM(BO21:BQ21)-SUM(BO34:BR34) -> -95874 | BS21: =SUM(BO21:BR21) -> -95874 | BW21: =-85835-SUM(BT21:BV21)-SUM(BT34:BW34) -> -82117 | BX21: =SUM(BT21:BW21) -> -82117 | BY21: =-26240-BY34 -> -24386 | BZ21: =-27173-BZ34 -> -26994 | CA21: =-24843-CA34 -> -24444 | CB21: =-96843-SUM(BY21:CA21)-SUM(BY34:CB34) -> -19864 | CC21: =SUM(BY21:CB21) -> -95688 | CD21: =-28376-CD34 -> -25451 | CE21: =-14508-CE34 -> -14201 | CF21: =-25631-CF34 -> -25266 | CG21: =-96892-SUM(CD21:CF21)-SUM(CD34:CG34) -> -30415 | CH21: =SUM(CD21:CG21) -> -95333 | CI21: =-20615-CI34 -> -20280 | CJ21: =-24043-CJ34 -> -23688 | CK21: =-31117-CK34 -> -30752 | CL21: =-102464-SUM(CI21:CK21)-SUM(CI34:CL34) -> -26306 | CM21: =SUM(CI21:CL21) -> -101026 | CN21: =-22810-CN34 -> -22356 | CO21: =-34143-CO34 -> -33684 | CP21: =-49409-CP34 -> -48993 | CQ21: =-136568-SUM(CN21:CP21)-SUM(CN34:CQ34) -> -29683 | CR21: =SUM(CN21:CQ21) -> -134716 | CS21: =-33375-CS34 -> -32599 | CT21: =-42088-CT34 -> -41367 | CU21: =-54245-CU34 -> -53549 | CV21: =-165783-SUM(CS21:CU21)-SUM(CS34:CV34) -> -35293 | CW21: =SUM(CS21:CV21) -> -162808 | CX21: =-41298-CX34 -> -40769 | CY21: =-62203-CY34 -> -61475 | CZ21: =-68034-CZ34 -> -67309 | DA21: =-224429-SUM(CX21:CZ21)-SUM(CX34:DA34) -> -52203 | DB21: =SUM(CX21:DA21) -> -221756 | DC21: =-50355-DC34 -> -50151 | DD21: =-64402-DD34 -> -64176 | DE21: =-66007-DE34 -> -65788 | DF21: =-239339-SUM(DC21:DE21)-SUM(DC34:DF34) -> -58359 | DG21: =SUM(DC21:DF21) -> -238474 | DH21: =-64932-DH34 -> -64720 | DI21: =-78364-DI34 -> -78166 | DJ21: =DI21*(1+Macro!DJ15) -> -79030.906 | DK21: =DH21*1.05 -> -67956 | DL21: =SUM(DH21:DK21) -> -289872.91 | DM21: =DL21/4*(1+Macro!DM15)*1.05 -> -76933.591 | DN21: =DM21*(1+Macro!DN15) -> -77784.861 | DO21: =DN21*(1+Macro!DO15) -> -78645.549 | DP21: =DO21*(1+Macro!DP15) -> -79515.762 | DQ21: =SUM(DM21:DP21) -> -312879.76 | DR21: =DP21*(1+Macro!DR15) -> -80395.603 | DS21: =DR21*(1+Macro!DS15) -> -81285.179 | DT21: =DS21*(1+Macro!DT15) -> -82184.599 | DU21: =DT21*(1+Macro!DU15) -> -83093.971 | DV21: =SUM(DR21:DU21) -> -326959.35 | DW21: =DU21*(1+Macro!DW15) -> -84013.405 | DX21: =DW21*(1+Macro!DX15) -> -84943.012 | DY21: =DX21*(1+Macro!DY15) -> -85882.906 | DZ21: =DY21*(1+Macro!DZ15) -> -86833.199 | EA21: =SUM(DW21:DZ21) -> -341672.52 | EB21: =DZ21*(1+Macro!EB15) -> -87794.008 | EC21: =EB21*(1+Macro!EC15) -> -88765.448 | ED21: =EC21*(1+Macro!ED15) -> -89747.637 | EE21: =ED21*(1+Macro!EE15) -> -90740.693 | EF21: =SUM(EB21:EE21) -> -357047.79
A22: % of revenues | B22: =-B21/B11 -> #DIV/0! | C22: =-C21/C11 -> #DIV/0! | D22: =-D21/D11 -> #DIV/0! | E22: =-E21/E11 -> #DIV/0! | F22: =-F21/F11 -> #DIV/0! | G22: =-G21/G11 -> #DIV/0! | H22: =-H21/H11 -> #DIV/0! | I22: =-I21/I11 -> #DIV/0! | ... EF22: =-EF21/EF11 -> 0.036809764
A23: Net Financial Result | B23: =B24+B26+B28 -> 0 | C23: =C24+C26+C28 -> 0 | D23: =D24+D26+D28 -> 0 | E23: =E24+E26+E28 -> 0 | F23: =SUM(B23:E23) -> 0 | G23: =G24+G26+G28 -> 0 | H23: =H24+H26+H28 -> 0 | I23: =I24+I26+I28 -> 0 | J23: =J24+J26+J28 -> 0 | K23: =SUM(G23:J23) -> 0 | L23: =L24+L26+L28 -> 0 | M23: =M24+M26+M28 -> 0 | N23: =N24+N26+N28 -> 0 | O23: =O24+O26+O28 -> 0 | P23: =SUM(L23:O23) -> 0 | Q23: =Q24+Q26+Q28 -> 0 | R23: =R24+R26+R28 -> 0 | S23: =S24+S26+S28 -> 0 | T23: =T24+T26+T28 -> 0 | U23: =SUM(Q23:T23) -> 0 | V23: =V24+V26+V28 -> 0 | W23: =W24+W26+W28 -> 0 | X23: =X24+X26+X28 -> 0 | Y23: =Y24+Y26+Y28 -> 0 | Z23: =SUM(V23:Y23) -> 0 | AA23: =AA24+AA26+AA28 -> 0 | AB23: =AB24+AB26+AB28 -> 0 | AC23: =AC24+AC26+AC28 -> 0 | AD23: =AD24+AD26+AD28 -> 0 | AE23: =SUM(AA23:AD23) -> 0 | AF23: =AF24+AF26+AF28 -> 0 | AG23: =AG24+AG26+AG28 -> 0 | AH23: =AH24+AH26+AH28 -> 0 | AI23: =AI24+AI26+AI28 -> 2743.208 | AJ23: =SUM(AF23:AI23) -> 2743.208 | AK23: =AK24+AK26+AK28 -> 0 | AL23: =AL24+AL26+AL28 -> 0 | AM23: =AM24+AM26+AM28 -> 0 | AN23: =AN24+AN26+AN28 -> 9159.674 | AO23: =SUM(AK23:AN23) -> 9159.674 | AP23: =AP24+AP26+AP28 -> 0 | AQ23: =AQ24+AQ26+AQ28 -> 0 | AR23: =AR24+AR26+AR28 -> 0 | AS23: =AS24+AS26+AS28 -> 9700.656 | AT23: =SUM(AP23:AS23) -> 9700.656 | AU23: =AU24+AU26+AU28 -> 0 | AV23: =AV24+AV26+AV28 -> 0 | AW23: =AW24+AW26+AW28 -> 0 | AX23: =AX24+AX26+AX28 -> 2482.247 | AY23: =SUM(AU23:AX23) -> 2482.247 | AZ23: =AZ24+AZ26+AZ28 -> 0 | BA23: =BA24+BA26+BA28 -> 0 | BB23: =BB24+BB26+BB28 -> 0 | BC23: =BC24+BC26+BC28 -> 6338 | BD23: =SUM(AZ23:BC23) -> 6338 | BE23: =BE24+BE26+BE28 -> 0 | BF23: =BF24+BF26+BF28 -> 0 | BG23: =BG24+BG26+BG28 -> 0 | BH23: =BH24+BH26+BH28 -> 9721 | BI23: =SUM(BE23:BH23) -> 9721 | BJ23: =BJ24+BJ26+BJ28 -> 0 | BK23: =BK24+BK26+BK28 -> 0 | BL23: =BL24+BL26+BL28 -> 0 | BM23: =BM24+BM26+BM28 -> 10613 | BN23: =SUM(BJ23:BM23) -> 10613 | BO23: =BO24+BO26+BO28 -> 0 | BP23: =BP24+BP26+BP28 -> 0 | BQ23: =BQ24+BQ26+BQ28 -> 0 | BR23: =BR24+BR26+BR28 -> 15057 | BS23: =SUM(BO23:BR23) -> 15057 | BT23: =BT24+BT26+BT28 -> 0 | BU23: =BU24+BU26+BU28 -> 0 | BV23: =BV24+BV26+BV28 -> 0 | BW23: =BW24+BW26+BW28 -> 2463 | BX23: =SUM(BT23:BW23) -> 2463 | BY23: =BY24+BY26+BY28 -> -453 | BZ23: =BZ24+BZ26+BZ28 -> 262 | CA23: =CA24+CA26+CA28 -> -4443 | CB23: =CB24+CB26+CB28 -> -6780 | CC23: =SUM(BY23:CB23) -> -11414 | CD23: =CD24+CD26+CD28 -> -2175 | CE23: =CE24+CE26+CE28 -> -2892 | CF23: =CF24+CF26+CF28 -> -1211 | CG23: =CG24+CG26+CG28 -> -2532 | CH23: =SUM(CD23:CG23) -> -8810 | CI23: =CI24+CI26+CI28 -> -5034 | CJ23: =CJ24+CJ26+CJ28 -> -5376 | CK23: =CK24+CK26+CK28 -> -1071 | CL23: =CL24+CL26+CL28 -> -13246 | CM23: =SUM(CI23:CL23) -> -24727 | CN23: =CN24+CN26+CN28 -> -4085 | CO23: =CO24+CO26+CO28 -> -4609 | CP23: =CP24+CP26+CP28 -> -4065 | CQ23: =CQ24+CQ26+CQ28 -> -11678 | CR23: =SUM(CN23:CQ23) -> -24437 | CS23: =CS24+CS26+CS28 -> -5444 | CT23: =CT24+CT26+CT28 -> -5601 | CU23: =CU24+CU26+CU28 -> -3546 | CV23: =CV24+CV26+CV28 -> 680 | CW23: =SUM(CS23:CV23) -> -13911 | CX23: =CX24+CX26+CX28 -> -4917 | CY23: =CY24+CY26+CY28 -> -5749 | CZ23: =CZ24+CZ26+CZ28 -> -7613 | DA23: =DA24+DA26+DA28 -> -12805 | DB23: =SUM(CX23:DA23) -> -31084 | DC23: =DC24+DC26+DC28 -> -14580 | DD23: =DD24+DD26+DD28 -> -15628 | DE23: =DE24+DE26+DE28 -> -8694 | DF23: =DF24+DF26+DF28 -> -8912 | DG23: =SUM(DC23:DF23) -> -47814 | DH23: =DH24+DH26+DH28 -> -10709 | DI23: =DI24+DI26+DI28 -> -22120 | DJ23: =DJ24+DJ26+DJ28 -> -13696.499 | DK23: =DK24+DK26+DK28 -> -15906.934 | DL23: =SUM(DH23:DK23) -> -62432.433 | DM23: =DM24+DM26+DM28 -> -8616.9056 | DN23: =DN24+DN26+DN28 -> -4409.3655 | DO23: =DO24+DO26+DO28 -> -2909.8427 | DP23: =DP24+DP26+DP28 -> 2418.5152 | DQ23: =SUM(DM23:DP23) -> -13517.599 | DR23: =DR24+DR26+DR28 -> 16053.071 | DS23: =DS24+DS26+DS28 -> 5174.6692 | DT23: =DT24+DT26+DT28 -> 12462.297 | DU23: =DU24+DU26+DU28 -> 23963.922 | DV23: =SUM(DR23:DU23) -> 57653.96 | DW23: =DW24+DW26+DW28 -> 13281.704 | DX23: =DX24+DX26+DX28 -> 2500.9096 | DY23: =DY24+DY26+DY28 -> 14376.482 | DZ23: =DZ24+DZ26+DZ28 -> 26816.086 | EA23: =SUM(DW23:DZ23) -> 56975.182 | EB23: =EB24+EB26+EB28 -> 15840.303 | EC23: =EC24+EC26+EC28 -> 4656.9204 | ED23: =ED24+ED26+ED28 -> 17165.47 | EE23: =EE24+EE26+EE28 -> 30077.209 | EF23: =SUM(EB23:EE23) -> 67739.903
A24: Financial Income | F24: =SUM(B24:E24) -> 0 | K24: =SUM(G24:J24) -> 0 | P24: =SUM(L24:O24) -> 0 | U24: =SUM(Q24:T24) -> 0 | Z24: =SUM(V24:Y24) -> 0 | AE24: =SUM(AA24:AD24) -> 0 | AI24: =5819.99-SUM(AF24:AH24) -> 5819.99 | AJ24: =SUM(AF24:AI24) -> 5819.99 | AN24: =13919.218-SUM(AK24:AM24) -> 13919.218 | AO24: =SUM(AK24:AN24) -> 13919.218 | AS24: =15502.979-SUM(AP24:AR24) -> 15502.979 | AT24: =SUM(AP24:AS24) -> 15502.979 | AX24: =11239.451-SUM(AU24:AW24) -> 11239.451 | AY24: =SUM(AU24:AX24) -> 11239.451 | BC24: =7965-SUM(AZ24:BB24) -> 7965 | BD24: =SUM(AZ24:BC24) -> 7965 | BH24: =14892-SUM(BE24:BG24) -> 14892 | BI24: =SUM(BE24:BH24) -> 14892 | BM24: =14875-SUM(BJ24:BL24) -> 14875 | BN24: =SUM(BJ24:BM24) -> 14875 | BR24: =20337-SUM(BO24:BQ24) -> 20337 | BS24: =SUM(BO24:BR24) -> 20337 | BW24: =11132-SUM(BT24:BV24) -> 11132 | BX24: =SUM(BT24:BW24) -> 11132 | BY24: 3012 | BZ24: 5477 | CA24: 3325 | CB24: =15275-SUM(BY24:CA24) -> 3461 | CC24: =SUM(BY24:CB24) -> 15275 | CD24: 2784 | CE24: 2827 | CF24: 5428 | CG24: =14673-SUM(CD24:CF24) -> 3634 | CH24: =SUM(CD24:CG24) -> 14673 | CI24: 2222 | CJ24: 3924 | CK24: 10356 | CL24: =24987-SUM(CI24:CK24) -> 8485 | CM24: =SUM(CI24:CL24) -> 24987 | CN24: 12977 | CO24: 17605 | CP24: 18795 | CQ24: =64031-SUM(CN24:CP24) -> 14654 | CR24: =SUM(CN24:CQ24) -> 64031 | CS24: 20228 | CT24: 20425 | CU24: 19668 | CV24: =86216-SUM(CS24:CU24) -> 25895 | CW24: =SUM(CS24:CV24) -> 86216 | CX24: 19889 | CY24: 25350 | CZ24: 32060 | DA24: =106081-SUM(CX24:CZ24) -> 28782 | DB24: =SUM(CX24:DA24) -> 106081 | DC24: 36752 | DD24: 35218 | DE24: 47368 | DF24: =170022-SUM(DC24:DE24) -> 50684 | DG24: =SUM(DC24:DF24) -> 170022 | DH24: 49093 | DI24: 48168 | DJ24: =DJ25*(AVERAGE('Balance Sheet'!DI6:DJ6))/4 -> 48582.506 | DK24: =DK25*(AVERAGE('Balance Sheet'!DJ6:DK6))/4 -> 46159.245 | DL24: =SUM(DH24:DK24) -> 192002.75 | DM24: =DM25*(AVERAGE('Balance Sheet'!DL6:DM6))/4 -> 52914.23 | DN24: =DN25*(AVERAGE('Balance Sheet'!DM6:DN6))/4 -> 57914.003 | DO24: =DO25*(AVERAGE('Balance Sheet'!DN6:DO6))/4 -> 61174.243 | DP24: =DP25*(AVERAGE('Balance Sheet'!DO6:DP6))/4 -> 68056.794 | DQ24: =SUM(DM24:DP24) -> 240059.27 | DR24: =DR25*(AVERAGE('Balance Sheet'!DQ6:DR6))/4 -> 65532.66 | DS24: =DS25*(AVERAGE('Balance Sheet'!DR6:DS6))/4 -> 55660.28 | DT24: =DT25*(AVERAGE('Balance Sheet'!DS6:DT6))/4 -> 63909.754 | DU24: =DU25*(AVERAGE('Balance Sheet'!DT6:DU6))/4 -> 76338.643 | DV24: =SUM(DR24:DU24) -> 261441.34 | DW24: =DW25*(AVERAGE('Balance Sheet'!DV6:DW6))/4 -> 66555.738 | DX24: =DX25*(AVERAGE('Balance Sheet'!DW6:DX6))/4 -> 56651.169 | DY24: =DY25*(AVERAGE('Balance Sheet'!DX6:DY6))/4 -> 69383.65 | DZ24: =DZ25*(AVERAGE('Balance Sheet'!DY6:DZ6))/4 -> 82663.909 | EA24: =SUM(DW24:DZ24) -> 275254.46 | EB24: =EB25*(AVERAGE('Balance Sheet'!EA6:EB6))/4 -> 72515.107 | EC24: =EC25*(AVERAGE('Balance Sheet'!EB6:EC6))/4 -> 62147.263 | ED24: =ED25*(AVERAGE('Balance Sheet'!EC6:ED6))/4 -> 75461.868 | EE24: =EE25*(AVERAGE('Balance Sheet'!ED6:EE6))/4 -> 89171.926 | EF24: =SUM(EB24:EE24) -> 299296.16
A25: Avg rate (%) | B25: =(1+(B24+B28+B30)/(AVERAGE('Balance Sheet'!A6:B6)+AVERAGE('Balance Sheet'!A8:B8)*10%+AVERAGE('Balance Sheet'!A7:B7)))^4-1 -> #DIV/0! | C25: =(1+(C24+C28+C30)/(AVERAGE('Balance Sheet'!B6:C6)+AVERAGE('Balance Sheet'!B8:C8)*10%+AVERAGE('Balance Sheet'!B7:C7)))^4-1 -> #DIV/0! | D25: =(1+(D24+D28+D30)/(AVERAGE('Balance Sheet'!C6:D6)+AVERAGE('Balance Sheet'!C8:D8)*10%+AVERAGE('Balance Sheet'!C7:D7)))^4-1 -> #DIV/0! | E25: =(1+(E24+E28+E30)/(AVERAGE('Balance Sheet'!D6:E6)+AVERAGE('Balance Sheet'!D8:E8)*10%+AVERAGE('Balance Sheet'!D7:E7)))^4-1 -> #DIV/0! | F25: =(1+(F24+F28+F30)/(AVERAGE('Balance Sheet'!E6:F6)+AVERAGE('Balance Sheet'!E8:F8)*10%+AVERAGE('Balance Sheet'!E7:F7)))^4-1 -> #DIV/0! | G25: =(1+(G24+G28+G30)/(AVERAGE('Balance Sheet'!F6:G6)+AVERAGE('Balance Sheet'!F8:G8)*10%+AVERAGE('Balance Sheet'!F7:G7)))^4-1 -> #DIV/0! | H25: =(1+(H24+H28+H30)/(AVERAGE('Balance Sheet'!G6:H6)+AVERAGE('Balance Sheet'!G8:H8)*10%+AVERAGE('Balance Sheet'!G7:H7)))^4-1 -> #DIV/0! | I25: =(1+(I24+I28+I30)/(AVERAGE('Balance Sheet'!H6:I6)+AVERAGE('Balance Sheet'!H8:I8)*10%+AVERAGE('Balance Sheet'!H7:I7)))^4-1 -> #DIV/0! | ... AE25: =(1+(AE24+AE28+AE30)/(AVERAGE('Balance Sheet'!AD6:AE6)+AVERAGE('Balance Sheet'!AD8:AE8)*10%+AVERAGE('Balance Sheet'!AD7:AE7)))^4-1 -> #DIV/0! | AF25: =(1+(AF24)/(AVERAGE('Balance Sheet'!AE6:AF6)))^4-1 -> #DIV/0! | AG25: =(1+(AG24)/(AVERAGE('Balance Sheet'!AF6:AG6)))^4-1 -> #DIV/0! | AH25: =(1+(AH24)/(AVERAGE('Balance Sheet'!AG6:AH6)))^4-1 -> #DIV/0! | AI25: =(1+(AI24)/(AVERAGE('Balance Sheet'!AH6:AI6)))^4-1 -> 1.5421085 | AJ25: =((AJ24)/(AVERAGE('Balance Sheet'!AI6:AJ6))) -> 0.26269517 | AK25: =(1+(AK24)/(AVERAGE('Balance Sheet'!AJ6:AK6)))^4-1 -> 0 | AL25: =(1+(AL24)/(AVERAGE('Balance Sheet'!AK6:AL6)))^4-1 -> #DIV/0! | AM25: =(1+(AM24)/(AVERAGE('Balance Sheet'!AL6:AM6)))^4-1 -> #DIV/0! | AN25: =(1+(AN24)/(AVERAGE('Balance Sheet'!AM6:AN6)))^4-1 -> 1.6571302 | AO25: =((AO24)/(AVERAGE('Balance Sheet'!AN6:AO6))) -> 0.27674218 | AP25: =(1+(AP24)/(AVERAGE('Balance Sheet'!AO6:AP6)))^4-1 -> 0 | AQ25: =(1+(AQ24)/(AVERAGE('Balance Sheet'!AP6:AQ6)))^4-1 -> #DIV/0! | AR25: =(1+(AR24)/(AVERAGE('Balance Sheet'!AQ6:AR6)))^4-1 -> #DIV/0! | AS25: =(1+(AS24)/(AVERAGE('Balance Sheet'!AR6:AS6)))^4-1 -> 1.0086625 | AT25: =((AT24)/(AVERAGE('Balance Sheet'!AS6:AT6))) -> 0.19049272 | AU25: =(1+(AU24)/(AVERAGE('Balance Sheet'!AT6:AU6)))^4-1 -> 0 | AV25: =(1+(AV24)/(AVERAGE('Balance Sheet'!AU6:AV6)))^4-1 -> #DIV/0! | AW25: =(1+(AW24)/(AVERAGE('Balance Sheet'!AV6:AW6)))^4-1 -> #DIV/0! | AX25: =(1+(AX24)/(AVERAGE('Balance Sheet'!AW6:AX6)))^4-1 -> 0.63568201 | AY25: =((AY24)/(AVERAGE('Balance Sheet'!AX6:AY6))) -> 0.13090134 | AZ25: =(1+(AZ24)/(AVERAGE('Balance Sheet'!AY6:AZ6)))^4-1 -> 0 | BA25: =(1+(BA24)/(AVERAGE('Balance Sheet'!AZ6:BA6)))^4-1 -> #DIV/0! | BB25: =(1+(BB24)/(AVERAGE('Balance Sheet'!BA6:BB6)))^4-1 -> #DIV/0! | BC25: =(1+(BC24)/(AVERAGE('Balance Sheet'!BB6:BC6)))^4-1 -> 0.24370116 | BD25: =((BD24)/(AVERAGE('Balance Sheet'!BC6:BD6))) -> 0.056036696 | BE25: =(1+(BE24)/(AVERAGE('Balance Sheet'!BD6:BE6)))^4-1 -> 0 | BF25: =(1+(BF24)/(AVERAGE('Balance Sheet'!BE6:BF6)))^4-1 -> #DIV/0! | BG25: =(1+(BG24)/(AVERAGE('Balance Sheet'!BF6:BG6)))^4-1 -> #DIV/0! | BH25: =(1+(BH24)/(AVERAGE('Balance Sheet'!BG6:BH6)))^4-1 -> 0.45156713 | BI25: =((BI24)/(AVERAGE('Balance Sheet'!BH6:BI6))) -> 0.097638373 | BJ25: =(1+(BJ24)/(AVERAGE('Balance Sheet'!BI6:BJ6)))^4-1 -> 0 | BK25: =(1+(BK24)/(AVERAGE('Balance Sheet'!BJ6:BK6)))^4-1 -> #DIV/0! | BL25: =(1+(BL24)/(AVERAGE('Balance Sheet'!BK6:BL6)))^4-1 -> #DIV/0! | BM25: =(1+(BM24)/(AVERAGE('Balance Sheet'!BL6:BM6)))^4-1 -> 0.42180976 | BN25: =((BN24)/(AVERAGE('Balance Sheet'!BM6:BN6))) -> 0.09196916 | BO25: =(1+(BO24)/(AVERAGE('Balance Sheet'!BN6:BO6)))^4-1 -> 0 | BP25: =(1+(BP24)/(AVERAGE('Balance Sheet'!BO6:BP6)))^4-1 -> #DIV/0! | BQ25: =(1+(BQ24)/(AVERAGE('Balance Sheet'!BP6:BQ6)))^4-1 -> #DIV/0! | BR25: =(1+(BR24)/(AVERAGE('Balance Sheet'!BQ6:BR6)))^4-1 -> 0.47718907 | BS25: =((BS24)/(AVERAGE('Balance Sheet'!BR6:BS6))) -> 0.1024503 | BT25: =(1+(BT24)/(AVERAGE('Balance Sheet'!BS6:BT6)))^4-1 -> 0 | BU25: =(1+(BU24)/(AVERAGE('Balance Sheet'!BT6:BU6)))^4-1 -> #DIV/0! | BV25: =(1+(BV24)/(AVERAGE('Balance Sheet'!BU6:BV6)))^4-1 -> #DIV/0! | BW25: =(1+(BW24)/(AVERAGE('Balance Sheet'!BV6:BW6)))^4-1 -> 0.18958846 | BX25: =((BX24)/(AVERAGE('Balance Sheet'!BW6:BX6))) -> 0.04435749 | BY25: =(1+(BY24)/(AVERAGE('Balance Sheet'!BX6:BY6)))^4-1 -> 0.048878664 | BZ25: =(1+(BZ24)/(AVERAGE('Balance Sheet'!BY6:BZ6)))^4-1 -> #DIV/0! | CA25: =(1+(CA24)/(AVERAGE('Balance Sheet'!BZ6:CA6)))^4-1 -> #DIV/0! | CB25: =(1+(CB24)/(AVERAGE('Balance Sheet'!CA6:CB6)))^4-1 -> 0.044773773 | CC25: =((CC24)/(AVERAGE('Balance Sheet'!CB6:CC6))) -> 0.048593415 | CD25: =(1+(CD24)/(AVERAGE('Balance Sheet'!CC6:CD6)))^4-1 -> 0.03526398 | CE25: =(1+(CE24)/(AVERAGE('Balance Sheet'!CD6:CE6)))^4-1 -> 0.030440934 | CF25: =(1+(CF24)/(AVERAGE('Balance Sheet'!CE6:CF6)))^4-1 -> 0.042591193 | CG25: =(1+(CG24)/(AVERAGE('Balance Sheet'!CF6:CG6)))^4-1 -> 0.028227758 | CH25: =((CH24)/(AVERAGE('Balance Sheet'!CG6:CH6))) -> 0.034052142 | CI25: =(1+(CI24)/(AVERAGE('Balance Sheet'!CH6:CI6)))^4-1 -> 0.020648054 | CJ25: =(1+(CJ24)/(AVERAGE('Balance Sheet'!CI6:CJ6)))^4-1 -> 0.034235552 | CK25: =(1+(CK24)/(AVERAGE('Balance Sheet'!CJ6:CK6)))^4-1 -> 0.081514974 | CL25: =(1+(CL24)/(AVERAGE('Balance Sheet'!CK6:CL6)))^4-1 -> 0.060376962 | CM25: =((CM24)/(AVERAGE('Balance Sheet'!CL6:CM6))) -> 0.042031197 | CN25: =(1+(CN24)/(AVERAGE('Balance Sheet'!CM6:CN6)))^4-1 -> 0.0895877 | CO25: =(1+(CO24)/(AVERAGE('Balance Sheet'!CN6:CO6)))^4-1 -> 0.11441832 | CP25: =(1+(CP24)/(AVERAGE('Balance Sheet'!CO6:CP6)))^4-1 -> 0.11934999 | CQ25: =(1+(CQ24)/(AVERAGE('Balance Sheet'!CP6:CQ6)))^4-1 -> 0.084881953 | CR25: =((CR24)/(AVERAGE('Balance Sheet'!CQ6:CR6))) -> 0.081110832 | CS25: =(1+(CS24)/(AVERAGE('Balance Sheet'!CR6:CS6)))^4-1 -> 0.11084642 | CT25: =(1+(CT24)/(AVERAGE('Balance Sheet'!CS6:CT6)))^4-1 -> 0.10855316 | CU25: =(1+(CU24)/(AVERAGE('Balance Sheet'!CT6:CU6)))^4-1 -> 0.083407651 | CV25: =(1+(CV24)/(AVERAGE('Balance Sheet'!CU6:CV6)))^4-1 -> 0.10228937 | CW25: =((CW24)/(AVERAGE('Balance Sheet'!CV6:CW6))) -> 0.086887729 | CX25: =(1+(CX24)/(AVERAGE('Balance Sheet'!CW6:CX6)))^4-1 -> 0.081795259 | CY25: =(1+(CY24)/(AVERAGE('Balance Sheet'!CX6:CY6)))^4-1 -> 0.081286602 | CZ25: =(1+(CZ24)/(AVERAGE('Balance Sheet'!CY6:CZ6)))^4-1 -> 0.088785523 | DA25: =(1+(DA24)/(AVERAGE('Balance Sheet'!CZ6:DA6)))^4-1 -> 0.083530561 | DB25: =((DB24)/(AVERAGE('Balance Sheet'!DA6:DB6))) -> 0.074903477 | DC25: =(1+(DC24)/(AVERAGE('Balance Sheet'!DB6:DC6)))^4-1 -> 0.10308974 | DD25: =(1+(DD24)/(AVERAGE('Balance Sheet'!DC6:DD6)))^4-1 -> 0.094830702 | DE25: =(1+(DE24)/(AVERAGE('Balance Sheet'!DD6:DE6)))^4-1 -> 0.1197174 | DF25: =(1+(DF24)/(AVERAGE('Balance Sheet'!DE6:DF6)))^4-1 -> 0.11871038 | DG25: =((DG24)/(AVERAGE('Balance Sheet'!DF6:DG6))) -> 0.094934663 | DH25: =(1+(DH24)/(AVERAGE('Balance Sheet'!DG6:DH6)))^4-1 -> 0.11536645 | DI25: =(1+(DI24)/(AVERAGE('Balance Sheet'!DH6:DI6)))^4-1 -> 0.1185716 | DJ25: =Macro!DJ17*0.85 -> 0.116875 | DK25: =Macro!DK17*0.8 -> 0.106 | DL25: =((DL24)/(AVERAGE('Balance Sheet'!DK6:DL6))) -> 0.10714505 | DM25: =Macro!DM17*0.85 -> 0.1105 | DN25: =Macro!DN17*0.85 -> 0.1105 | DO25: =Macro!DO17*0.85 -> 0.1105 | DP25: =Macro!DP17*0.85 -> 0.1105 | DQ25: =((DQ24)/(AVERAGE('Balance Sheet'!DP6:DQ6))) -> 0.090511633 | DR25: =Macro!DR17*0.9 -> 0.117 | DS25: =Macro!DS17*0.9 -> 0.117 | DT25: =Macro!DT17*0.9 -> 0.117 | DU25: =Macro!DU17*0.9 -> 0.117 | DV25: =((DV24)/(AVERAGE('Balance Sheet'!DU6:DV6))) -> 0.092478443 | DW25: =Macro!DW17*0.9 -> 0.117 | DX25: =Macro!DX17*0.9 -> 0.117 | DY25: =Macro!DY17*0.9 -> 0.117 | DZ25: =Macro!DZ17*0.9 -> 0.117 | EA25: =((EA24)/(AVERAGE('Balance Sheet'!DZ6:EA6))) -> 0.090015154 | EB25: =Macro!EB17*0.9 -> 0.117 | EC25: =Macro!EC17*0.9 -> 0.117 | ED25: =Macro!ED17*0.9 -> 0.117 | EE25: =Macro!EE17*0.9 -> 0.117 | EF25: =((EF24)/(AVERAGE('Balance Sheet'!EE6:EF6))) -> 0.091071255
A26: Financial Expenses | F26: =SUM(B26:E26) -> 0 | K26: =SUM(G26:J26) -> 0 | P26: =SUM(L26:O26) -> 0 | U26: =SUM(Q26:T26) -> 0 | Z26: =SUM(V26:Y26) -> 0 | AE26: =SUM(AA26:AD26) -> 0 | AI26: =-3076.782-SUM(AF26:AH26) -> -3076.782 | AJ26: =SUM(AF26:AI26) -> -3076.782 | AN26: =-4759.544-SUM(AK26:AM26) -> -4759.544 | AO26: =SUM(AK26:AN26) -> -4759.544 | AS26: =-5802.323-SUM(AP26:AR26) -> -5802.323 | AT26: =SUM(AP26:AS26) -> -5802.323 | AX26: =-8757.204-SUM(AU26:AW26) -> -8757.204 | AY26: =SUM(AU26:AX26) -> -8757.204 | BC26: =-1627-SUM(AZ26:BB26) -> -1627 | BD26: =SUM(AZ26:BC26) -> -1627 | BH26: =-5171-SUM(BE26:BG26) -> -5171 | BI26: =SUM(BE26:BH26) -> -5171 | BM26: =-4262-SUM(BJ26:BL26) -> -4262 | BN26: =SUM(BJ26:BM26) -> -4262 | BR26: =-5280-SUM(BO26:BQ26) -> -5280 | BS26: =SUM(BO26:BR26) -> -5280 | BW26: =-8669-SUM(BT26:BV26) -> -8669 | BX26: =SUM(BT26:BW26) -> -8669 | BY26: -3465 | BZ26: -5215 | CA26: -7768 | CB26: =-26689-SUM(BY26:CA26) -> -10241 | CC26: =SUM(BY26:CB26) -> -26689 | CD26: -4959 | CE26: -5719 | CF26: -6639 | CG26: =-23483-SUM(CD26:CF26) -> -6166 | CH26: =SUM(CD26:CG26) -> -23483 | CI26: -7256 | CJ26: -9300 | CK26: -11427 | CL26: =-49714-SUM(CI26:CK26) -> -21731 | CM26: =SUM(CI26:CL26) -> -49714 | CN26: -17062 | CO26: -22214 | CP26: -22860 | CQ26: =-88468-SUM(CN26:CP26) -> -26332 | CR26: =SUM(CN26:CQ26) -> -88468 | CS26: -25672 | CT26: -26026 | CU26: -23214 | CV26: =-100127-SUM(CS26:CU26) -> -25215 | CW26: =SUM(CS26:CV26) -> -100127 | CX26: -24806 | CY26: -31099 | CZ26: -39673 | DA26: =-137165-SUM(CX26:CZ26) -> -41587 | DB26: =SUM(CX26:DA26) -> -137165 | DC26: -51332 | DD26: -50846 | DE26: -56062 | DF26: =-217836-SUM(DC26:DE26) -> -59596 | DG26: =SUM(DC26:DF26) -> -217836 | DH26: -59802 | DI26: -70288 | DJ26: =DJ85+DJ84 -> -62279.005 | DK26: =DK85+DK84 -> -62066.179 | DL26: =SUM(DH26:DK26) -> -254435.18 | DM26: =DM85+DM84 -> -61531.135 | DN26: =DN85+DN84 -> -62323.368 | DO26: =DO85+DO84 -> -64084.086 | DP26: =DP85+DP84 -> -65638.278 | DQ26: =SUM(DM26:DP26) -> -253576.87 | DR26: =DR85+DR84 -> -49479.589 | DS26: =DS85+DS84 -> -50485.611 | DT26: =DT85+DT84 -> -51447.457 | DU26: =DU85+DU84 -> -52374.721 | DV26: =SUM(DR26:DU26) -> -203787.38 | DW26: =DW85+DW84 -> -53274.034 | DX26: =DX85+DX84 -> -54150.259 | DY26: =DY85+DY84 -> -55007.168 | DZ26: =DZ85+DZ84 -> -55847.823 | EA26: =SUM(DW26:DZ26) -> -218279.28 | EB26: =EB85+EB84 -> -56674.804 | EC26: =EC85+EC84 -> -57490.342 | ED26: =ED85+ED84 -> -58296.398 | EE26: =EE85+EE84 -> -59094.716 | EF26: =SUM(EB26:EE26) -> -231556.26
A27: Avg rate (%) | B27: =(1-B26/'Balance Sheet'!B50)^4-1 -> #DIV/0! | C27: =(1-C26/'Balance Sheet'!C50)^4-1 -> #DIV/0! | D27: =(1-D26/'Balance Sheet'!D50)^4-1 -> #DIV/0! | E27: =(1-E26/'Balance Sheet'!E50)^4-1 -> #DIV/0! | F27: =-F26/AVERAGE('Balance Sheet'!B50:E50) -> #DIV/0! | G27: =(1-G26/'Balance Sheet'!G50)^4-1 -> #DIV/0! | H27: =(1-H26/'Balance Sheet'!H50)^4-1 -> #DIV/0! | I27: =(1-I26/'Balance Sheet'!I50)^4-1 -> #DIV/0! | J27: =(1-J26/'Balance Sheet'!J50)^4-1 -> #DIV/0! | K27: =-K26/AVERAGE('Balance Sheet'!G50:J50) -> #DIV/0! | L27: =(1-L26/'Balance Sheet'!L50)^4-1 -> #DIV/0! | M27: =(1-M26/'Balance Sheet'!M50)^4-1 -> #DIV/0! | N27: =(1-N26/'Balance Sheet'!N50)^4-1 -> #DIV/0! | O27: =(1-O26/'Balance Sheet'!O50)^4-1 -> #DIV/0! | P27: =-P26/AVERAGE('Balance Sheet'!L50:O50) -> #DIV/0! | Q27: =(1-Q26/'Balance Sheet'!Q50)^4-1 -> #DIV/0! | R27: =(1-R26/'Balance Sheet'!R50)^4-1 -> #DIV/0! | S27: =(1-S26/'Balance Sheet'!S50)^4-1 -> #DIV/0! | T27: =(1-T26/'Balance Sheet'!T50)^4-1 -> #DIV/0! | U27: =-U26/AVERAGE('Balance Sheet'!Q50:T50) -> #DIV/0! | V27: =(1-V26/'Balance Sheet'!V50)^4-1 -> #DIV/0! | W27: =(1-W26/'Balance Sheet'!W50)^4-1 -> #DIV/0! | X27: =(1-X26/'Balance Sheet'!X50)^4-1 -> #DIV/0! | Y27: =(1-Y26/'Balance Sheet'!Y50)^4-1 -> #DIV/0! | Z27: =-Z26/AVERAGE('Balance Sheet'!V50:Y50) -> #DIV/0! | AA27: =(1-AA26/'Balance Sheet'!AA50)^4-1 -> #DIV/0! | AB27: =(1-AB26/'Balance Sheet'!AB50)^4-1 -> #DIV/0! | AC27: =(1-AC26/'Balance Sheet'!AC50)^4-1 -> #DIV/0! | AD27: =(1-AD26/'Balance Sheet'!AD50)^4-1 -> #DIV/0! | AE27: =-AE26/AVERAGE('Balance Sheet'!AA50:AD50) -> #DIV/0! | AF27: =(1-AF26/AVERAGE('Balance Sheet'!AE50:AF50))^4-1 -> #DIV/0! | AG27: =(1-AG26/AVERAGE('Balance Sheet'!AF50:AG50))^4-1 -> #DIV/0! | AH27: =(1-AH26/AVERAGE('Balance Sheet'!AG50:AH50))^4-1 -> #DIV/0! | AI27: =(1-AI26/AVERAGE('Balance Sheet'!AH50:AI50))^4-1 -> 0.28166186 | AJ27: =-AJ26/AVERAGE('Balance Sheet'!AF50:AI50) -> 0.12800851 | AK27: =(1-AK26/AVERAGE('Balance Sheet'!AJ50:AK50))^4-1 -> 0 | AL27: =(1-AL26/AVERAGE('Balance Sheet'!AK50:AL50))^4-1 -> #DIV/0! | AM27: =(1-AM26/AVERAGE('Balance Sheet'!AL50:AM50))^4-1 -> #DIV/0! | AN27: =(1-AN26/AVERAGE('Balance Sheet'!AM50:AN50))^4-1 -> 0.27338366 | AO27: =-AO26/AVERAGE('Balance Sheet'!AK50:AN50) -> 0.12456398 | AP27: =(1-AP26/AVERAGE('Balance Sheet'!AO50:AP50))^4-1 -> 0 | AQ27: =(1-AQ26/AVERAGE('Balance Sheet'!AP50:AQ50))^4-1 -> #DIV/0! | AR27: =(1-AR26/AVERAGE('Balance Sheet'!AQ50:AR50))^4-1 -> #DIV/0! | AS27: =(1-AS26/AVERAGE('Balance Sheet'!AR50:AS50))^4-1 -> 0.51124933 | AT27: =-AT26/AVERAGE('Balance Sheet'!AP50:AS50) -> 0.21750203 | AU27: =(1-AU26/AVERAGE('Balance Sheet'!AT50:AU50))^4-1 -> 0 | AV27: =(1-AV26/AVERAGE('Balance Sheet'!AU50:AV50))^4-1 -> #DIV/0! | AW27: =(1-AW26/AVERAGE('Balance Sheet'!AV50:AW50))^4-1 -> #DIV/0! | AX27: =(1-AX26/AVERAGE('Balance Sheet'!AW50:AX50))^4-1 -> 0.8414597 | AY27: =-AY26/AVERAGE('Balance Sheet'!AU50:AX50) -> 0.32981024 | AZ27: =(1-AZ26/AVERAGE('Balance Sheet'!AY50:AZ50))^4-1 -> 0 | BA27: =(1-BA26/AVERAGE('Balance Sheet'!AZ50:BA50))^4-1 -> #DIV/0! | BB27: =(1-BB26/AVERAGE('Balance Sheet'!BA50:BB50))^4-1 -> #DIV/0! | BC27: =(1-BC26/AVERAGE('Balance Sheet'!BB50:BC50))^4-1 -> 0.088644708 | BD27: =-BD26/AVERAGE('Balance Sheet'!AZ50:BC50) -> 0.042920833 | BE27: =(1-BE26/AVERAGE('Balance Sheet'!BD50:BE50))^4-1 -> 0 | BF27: =(1-BF26/AVERAGE('Balance Sheet'!BE50:BF50))^4-1 -> #DIV/0! | BG27: =(1-BG26/AVERAGE('Balance Sheet'!BF50:BG50))^4-1 -> #DIV/0! | BH27: =(1-BH26/AVERAGE('Balance Sheet'!BG50:BH50))^4-1 -> 0.24195531 | BI27: =-BI26/AVERAGE('Balance Sheet'!BE50:BH50) -> 0.11133179 | BJ27: =(1-BJ26/AVERAGE('Balance Sheet'!BI50:BJ50))^4-1 -> 0 | BK27: =(1-BK26/AVERAGE('Balance Sheet'!BJ50:BK50))^4-1 -> #DIV/0! | BL27: =(1-BL26/AVERAGE('Balance Sheet'!BK50:BL50))^4-1 -> #DIV/0! | BM27: =(1-BM26/AVERAGE('Balance Sheet'!BL50:BM50))^4-1 -> 0.16759439 | BN27: =-BN26/AVERAGE('Balance Sheet'!BJ50:BM50) -> 0.07899285 | BO27: =(1-BO26/AVERAGE('Balance Sheet'!BN50:BO50))^4-1 -> 0 | BP27: =(1-BP26/AVERAGE('Balance Sheet'!BO50:BP50))^4-1 -> #DIV/0! | BQ27: =(1-BQ26/AVERAGE('Balance Sheet'!BP50:BQ50))^4-1 -> #DIV/0! | BR27: =(1-BR26/AVERAGE('Balance Sheet'!BQ50:BR50))^4-1 -> 0.20494919 | BS27: =-BS26/AVERAGE('Balance Sheet'!BO50:BR50) -> 0.09542528 | BT27: =(1-BT26/AVERAGE('Balance Sheet'!BS50:BT50))^4-1 -> 0 | BU27: =(1-BU26/AVERAGE('Balance Sheet'!BT50:BU50))^4-1 -> #DIV/0! | BV27: =(1-BV26/AVERAGE('Balance Sheet'!BU50:BV50))^4-1 -> #DIV/0! | BW27: =(1-BW26/AVERAGE('Balance Sheet'!BV50:BW50))^4-1 -> 0.25807628 | BX27: =-BX26/AVERAGE('Balance Sheet'!BT50:BW50) -> 0.11815013 | BY27: =(1-BY26/AVERAGE('Balance Sheet'!BX50:BY50))^4-1 -> 0.09784745 | BZ27: =(1-BZ26/AVERAGE('Balance Sheet'!BY50:BZ50))^4-1 -> #DIV/0! | CA27: =(1-CA26/AVERAGE('Balance Sheet'!BZ50:CA50))^4-1 -> #DIV/0! | CB27: =(1-CB26/AVERAGE('Balance Sheet'!CA50:CB50))^4-1 -> 0.28240291 | CC27: =-CC26/AVERAGE('Balance Sheet'!BY50:CB50) -> 0.33440357 | CD27: =(1-CD26/AVERAGE('Balance Sheet'!CC50:CD50))^4-1 -> 0.063219089 | CE27: =(1-CE26/AVERAGE('Balance Sheet'!CD50:CE50))^4-1 -> 0.069023308 | CF27: =(1-CF26/AVERAGE('Balance Sheet'!CE50:CF50))^4-1 -> 0.081578566 | CG27: =(1-CG26/AVERAGE('Balance Sheet'!CF50:CG50))^4-1 -> 0.085063737 | CH27: =-CH26/AVERAGE('Balance Sheet'!CD50:CG50) -> 0.073508133 | CI27: =(1-CI26/AVERAGE('Balance Sheet'!CH50:CI50))^4-1 -> 0.1066184 | CJ27: =(1-CJ26/AVERAGE('Balance Sheet'!CI50:CJ50))^4-1 -> 0.14159629 | CK27: =(1-CK26/AVERAGE('Balance Sheet'!CJ50:CK50))^4-1 -> 0.14540451 | CL27: =(1-CL26/AVERAGE('Balance Sheet'!CK50:CL50))^4-1 -> 0.24147356 | CM27: =-CM26/AVERAGE('Balance Sheet'!CI50:CL50) -> 0.14898125 | CN27: =(1-CN26/AVERAGE('Balance Sheet'!CM50:CN50))^4-1 -> 0.18628551 | CO27: =(1-CO26/AVERAGE('Balance Sheet'!CN50:CO50))^4-1 -> 0.24470533 | CP27: =(1-CP26/AVERAGE('Balance Sheet'!CO50:CP50))^4-1 -> 0.23167319 | CQ27: =(1-CQ26/AVERAGE('Balance Sheet'!CP50:CQ50))^4-1 -> 0.24449123 | CR27: =-CR26/AVERAGE('Balance Sheet'!CN50:CQ50) -> 0.20492425 | CS27: =(1-CS26/AVERAGE('Balance Sheet'!CR50:CS50))^4-1 -> 0.23289337 | CT27: =(1-CT26/AVERAGE('Balance Sheet'!CS50:CT50))^4-1 -> 0.23148872 | CU27: =(1-CU26/AVERAGE('Balance Sheet'!CT50:CU50))^4-1 -> 0.17227632 | CV27: =(1-CV26/AVERAGE('Balance Sheet'!CU50:CV50))^4-1 -> 0.17009858 | CW27: =-CW26/AVERAGE('Balance Sheet'!CS50:CV50) -> 0.17934305 | CX27: =(1-CX26/AVERAGE('Balance Sheet'!CW50:CX50))^4-1 -> 0.17357409 | CY27: =(1-CY26/AVERAGE('Balance Sheet'!CX50:CY50))^4-1 -> 0.15626146 | CZ27: =(1-CZ26/AVERAGE('Balance Sheet'!CY50:CZ50))^4-1 -> 0.15348997 | DA27: =(1-DA26/AVERAGE('Balance Sheet'!CZ50:DA50))^4-1 -> 0.16903536 | DB27: =-DB26/AVERAGE('Balance Sheet'!CX50:DA50) -> 0.14547393 | DC27: =(1-DC26/AVERAGE('Balance Sheet'!DB50:DC50))^4-1 -> 0.19362599 | DD27: =(1-DD26/AVERAGE('Balance Sheet'!DC50:DD50))^4-1 -> 0.16682539 | DE27: =(1-DE26/AVERAGE('Balance Sheet'!DD50:DE50))^4-1 -> 0.18203655 | DF27: =(1-DF26/AVERAGE('Balance Sheet'!DE50:DF50))^4-1 -> 0.18160532 | DG27: =-DG26/AVERAGE('Balance Sheet'!DC50:DF50) -> 0.16184566 | DH27: =(1-DH26/AVERAGE('Balance Sheet'!DG50:DH50))^4-1 -> 0.18039188 | DI27: =(1-DI26/AVERAGE('Balance Sheet'!DH50:DI50))^4-1 -> 0.22567627 | DJ27: =(1-DJ26/AVERAGE('Balance Sheet'!DI50:DJ50))^4-1 -> 0.19468256 | DK27: =(1-DK26/AVERAGE('Balance Sheet'!DJ50:DK50))^4-1 -> 0.1877088 | DL27: =-DL26/AVERAGE('Balance Sheet'!DH50:DK50) -> 0.18442975 | DM27: =(1-DM26/AVERAGE('Balance Sheet'!DL50:DM50))^4-1 -> 0.18421919 | DN27: =(1-DN26/AVERAGE('Balance Sheet'!DM50:DN50))^4-1 -> 0.18421919 | DO27: =(1-DO26/AVERAGE('Balance Sheet'!DN50:DO50))^4-1 -> 0.18421919 | DP27: =(1-DP26/AVERAGE('Balance Sheet'!DO50:DP50))^4-1 -> 0.18421919 | DQ27: =-DQ26/AVERAGE('Balance Sheet'!DM50:DP50) -> 0.17112473 | DR27: =(1-DR26/AVERAGE('Balance Sheet'!DQ50:DR50))^4-1 -> 0.13360497 | DS27: =(1-DS26/AVERAGE('Balance Sheet'!DR50:DS50))^4-1 -> 0.13360497 | DT27: =(1-DT26/AVERAGE('Balance Sheet'!DS50:DT50))^4-1 -> 0.13360497 | DU27: =(1-DU26/AVERAGE('Balance Sheet'!DT50:DU50))^4-1 -> 0.13360497 | DV27: =-DV26/AVERAGE('Balance Sheet'!DR50:DU50) -> 0.12619207 | DW27: =(1-DW26/AVERAGE('Balance Sheet'!DV50:DW50))^4-1 -> 0.13360497 | DX27: =(1-DX26/AVERAGE('Balance Sheet'!DW50:DX50))^4-1 -> 0.13360497 | DY27: =(1-DY26/AVERAGE('Balance Sheet'!DX50:DY50))^4-1 -> 0.13360497 | DZ27: =(1-DZ26/AVERAGE('Balance Sheet'!DY50:DZ50))^4-1 -> 0.13360497 | EA27: =-EA26/AVERAGE('Balance Sheet'!DW50:DZ50) -> 0.12639506 | EB27: =(1-EB26/AVERAGE('Balance Sheet'!EA50:EB50))^4-1 -> 0.13360497 | EC27: =(1-EC26/AVERAGE('Balance Sheet'!EB50:EC50))^4-1 -> 0.13360497 | ED27: =(1-ED26/AVERAGE('Balance Sheet'!EC50:ED50))^4-1 -> 0.13360497 | EE27: =(1-EE26/AVERAGE('Balance Sheet'!ED50:EE50))^4-1 -> 0.13360497 | EF27: =-EF26/AVERAGE('Balance Sheet'!EB50:EE50) -> 0.12650752
A28: Monetary Variation (when applicable) | F28: =SUM(B28:E28) -> 0 | K28: =SUM(G28:J28) -> 0 | P28: =SUM(L28:O28) -> 0 | U28: =SUM(Q28:T28) -> 0 | Z28: =SUM(V28:Y28) -> 0 | AE28: =SUM(AA28:AD28) -> 0 | AF28: 0 | AG28: 0 | AH28: 0 | AI28: 0 | AJ28: =SUM(AF28:AI28) -> 0 | AK28: 0 | AL28: 0 | AM28: 0 | AN28: 0 | AO28: =SUM(AK28:AN28) -> 0 | AP28: 0 | AQ28: 0 | AR28: 0 | AS28: 0 | AT28: =SUM(AP28:AS28) -> 0 | AU28: 0 | AV28: 0 | AW28: 0 | AX28: 0 | AY28: =SUM(AU28:AX28) -> 0 | AZ28: 0 | BA28: 0 | BB28: 0 | BC28: 0 | BD28: =SUM(AZ28:BC28) -> 0 | BE28: 0 | BF28: 0 | BG28: 0 | BH28: 0 | BI28: =SUM(BE28:BH28) -> 0 | BJ28: 0 | BK28: 0 | BL28: 0 | BM28: 0 | BN28: =SUM(BJ28:BM28) -> 0 | BO28: 0 | BP28: 0 | BQ28: 0 | BR28: 0 | BS28: =SUM(BO28:BR28) -> 0 | BT28: 0 | BU28: 0 | BV28: 0 | BW28: 0 | BX28: =SUM(BT28:BW28) -> 0 | BY28: 0 | BZ28: 0 | CA28: 0 | CB28: 0 | CC28: =SUM(BY28:CB28) -> 0 | CD28: 0 | CE28: 0 | CF28: 0 | CG28: 0 | CH28: =SUM(CD28:CG28) -> 0 | CI28: 0 | CJ28: 0 | CK28: 0 | CL28: 0 | CM28: =SUM(CI28:CL28) -> 0 | CN28: =CL28 -> 0 | CO28: =CM28 -> 0 | CP28: =CN28 -> 0 | CQ28: =CO28 -> 0 | CR28: =SUM(CN28:CQ28) -> 0 | CS28: =CQ28 -> 0 | CT28: =CR28 -> 0 | CU28: =CS28 -> 0 | CV28: =CT28 -> 0 | CW28: =SUM(CS28:CV28) -> 0 | CX28: =CV28 -> 0 | CY28: =CW28 -> 0 | CZ28: =CX28 -> 0 | DA28: =CY28 -> 0 | DB28: =SUM(CX28:DA28) -> 0 | DC28: =DA28 -> 0 | DD28: =DB28 -> 0 | DE28: =DC28 -> 0 | DF28: =DD28 -> 0 | DG28: =SUM(DC28:DF28) -> 0 | DH28: =DF28 -> 0 | DI28: =DG28 -> 0 | DJ28: =DI28 -> 0 | DK28: =DJ28 -> 0 | DL28: =SUM(DH28:DK28) -> 0 | DM28: =DK28 -> 0 | DN28: =DM28 -> 0 | DO28: =DN28 -> 0 | DP28: =DO28 -> 0 | DQ28: =SUM(DM28:DP28) -> 0 | DR28: =DP28 -> 0 | DS28: =DR28 -> 0 | DT28: =DS28 -> 0 | DU28: =DT28 -> 0 | DV28: =SUM(DR28:DU28) -> 0 | DW28: =DU28 -> 0 | DX28: =DW28 -> 0 | DY28: =DX28 -> 0 | DZ28: =DY28 -> 0 | EA28: =SUM(DW28:DZ28) -> 0 | EB28: =DZ28 -> 0 | EC28: =EB28 -> 0 | ED28: =EC28 -> 0 | EE28: =ED28 -> 0 | EF28: =SUM(EB28:EE28) -> 0
A29: Other Operating Income | B29: =+B30+B31 -> 0 | C29: =+C30+C31 -> 0 | D29: =+D30+D31 -> 0 | E29: =+E30+E31 -> 0 | F29: =SUM(B29:E29) -> 0 | G29: =+G30+G31 -> 0 | H29: =+H30+H31 -> 0 | I29: =+I30+I31 -> 0 | J29: =+J30+J31 -> 0 | K29: =SUM(G29:J29) -> 0 | L29: =+L30+L31 -> 0 | M29: =+M30+M31 -> 0 | N29: =+N30+N31 -> 0 | O29: =+O30+O31 -> 0 | P29: =SUM(L29:O29) -> 0 | Q29: =+Q30+Q31 -> 0 | R29: =+R30+R31 -> 0 | S29: =+S30+S31 -> 0 | T29: =+T30+T31 -> 0 | U29: =SUM(Q29:T29) -> 0 | V29: =+V30+V31 -> 0 | W29: =+W30+W31 -> 0 | X29: =+X30+X31 -> 0 | Y29: =+Y30+Y31 -> 0 | Z29: =SUM(V29:Y29) -> 0 | AA29: =+AA30+AA31 -> 0 | AB29: =+AB30+AB31 -> 0 | AC29: =+AC30+AC31 -> 0 | AD29: =+AD30+AD31 -> 0 | AE29: =SUM(AA29:AD29) -> 0 | AF29: =+AF30+AF31 -> 0 | AG29: =+AG30+AG31 -> 0 | AH29: =+AH30+AH31 -> 0 | AI29: =+AI30+AI31 -> 0 | AJ29: =SUM(AF29:AI29) -> 0 | AK29: =+AK30+AK31 -> 0 | AL29: =+AL30+AL31 -> 0 | AM29: =+AM30+AM31 -> 0 | AN29: =+AN30+AN31 -> 0 | AO29: =SUM(AK29:AN29) -> 0 | AP29: =+AP30+AP31 -> 0 | AQ29: =+AQ30+AQ31 -> 0 | AR29: =+AR30+AR31 -> 0 | AS29: =+AS30+AS31 -> 0 | AT29: =SUM(AP29:AS29) -> 0 | AU29: =+AU30+AU31 -> 0 | AV29: =+AV30+AV31 -> 0 | AW29: =+AW30+AW31 -> 0 | AX29: =+AX30+AX31 -> 0 | AY29: =SUM(AU29:AX29) -> 0 | AZ29: =+AZ30+AZ31 -> 0 | BA29: =+BA30+BA31 -> 0 | BB29: =+BB30+BB31 -> 0 | BC29: =+BC30+BC31 -> 0 | BD29: =SUM(AZ29:BC29) -> 0 | BE29: =+BE30+BE31 -> 0 | BF29: =+BF30+BF31 -> 0 | BG29: =+BG30+BG31 -> 0 | BH29: =+BH30+BH31 -> 0 | BI29: =SUM(BE29:BH29) -> 0 | BJ29: =+BJ30+BJ31 -> 0 | BK29: =+BK30+BK31 -> 0 | BL29: =+BL30+BL31 -> 0 | BM29: =+BM30+BM31 -> 0 | BN29: =SUM(BJ29:BM29) -> 0 | BO29: =+BO30+BO31 -> 0 | BP29: =+BP30+BP31 -> 0 | BQ29: =+BQ30+BQ31 -> 0 | BR29: =+BR30+BR31 -> 0 | BS29: =SUM(BO29:BR29) -> 0 | BT29: =+BT30+BT31 -> 0 | BU29: =+BU30+BU31 -> 0 | BV29: =+BV30+BV31 -> 0 | BW29: =+BW30+BW31 -> 0 | BX29: =SUM(BT29:BW29) -> 0 | BY29: =+BY30+BY31 -> 0 | BZ29: =+BZ30+BZ31 -> 0 | CA29: =+CA30+CA31 -> 0 | CB29: =+CB30+CB31 -> 0 | CC29: =SUM(BY29:CB29) -> 0 | CD29: =+CD30+CD31 -> 0 | CE29: =+CE30+CE31 -> 0 | CF29: =+CF30+CF31 -> 0 | CG29: =+CG30+CG31 -> 0 | CH29: =SUM(CD29:CG29) -> 0 | CI29: =+CI30+CI31 -> 0 | CJ29: =+CJ30+CJ31 -> 0 | CK29: =+CK30+CK31 -> 0 | CL29: =+CL30+CL31 -> 0 | CM29: =SUM(CI29:CL29) -> 0 | CN29: =+CN30+CN31 -> 0 | CO29: =+CO30+CO31 -> 0 | CP29: =+CP30+CP31 -> 0 | CQ29: =+CQ30+CQ31 -> 0 | CR29: =SUM(CN29:CQ29) -> 0 | CS29: =+CS30+CS31 -> 0 | CT29: =+CT30+CT31 -> 0 | CU29: =+CU30+CU31 -> 0 | CV29: =+CV30+CV31 -> 0 | CW29: =SUM(CS29:CV29) -> 0 | CX29: =+CX30+CX31 -> 0 | CY29: =+CY30+CY31 -> 0 | CZ29: =+CZ30+CZ31 -> 0 | DA29: =+DA30+DA31 -> 0 | DB29: =SUM(CX29:DA29) -> 0 | DC29: =+DC30+DC31 -> 0 | DD29: =+DD30+DD31 -> 0 | DE29: =+DE30+DE31 -> 0 | DF29: =+DF30+DF31 -> 0 | DG29: =SUM(DC29:DF29) -> 0 | DH29: =+DH30+DH31 -> 0 | DI29: =+DI30+DI31 -> 0 | DJ29: =+DJ30+DJ31 -> 0 | DK29: =+DK30+DK31 -> 0 | DL29: =SUM(DH29:DK29) -> 0 | DM29: =+DM30+DM31 -> 0 | DN29: =+DN30+DN31 -> 0 | DO29: =+DO30+DO31 -> 0 | DP29: =+DP30+DP31 -> 0 | DQ29: =SUM(DM29:DP29) -> 0 | DR29: =+DR30+DR31 -> 0 | DS29: =+DS30+DS31 -> 0 | DT29: =+DT30+DT31 -> 0 | DU29: =+DU30+DU31 -> 0 | DV29: =SUM(DR29:DU29) -> 0 | DW29: =+DW30+DW31 -> 0 | DX29: =+DX30+DX31 -> 0 | DY29: =+DY30+DY31 -> 0 | DZ29: =+DZ30+DZ31 -> 0 | EA29: =SUM(DW29:DZ29) -> 0 | EB29: =+EB30+EB31 -> 0 | EC29: =+EC30+EC31 -> 0 | ED29: =+ED30+ED31 -> 0 | EE29: =+EE30+EE31 -> 0 | EF29: =SUM(EB29:EE29) -> 0
A30: Client Financing (when applicable) | F30: =SUM(B30:E30) -> 0 | K30: =SUM(G30:J30) -> 0 | P30: =SUM(L30:O30) -> 0 | U30: =SUM(Q30:T30) -> 0 | Z30: =SUM(V30:Y30) -> 0 | AE30: =SUM(AA30:AD30) -> 0 | AI30: 0 | AJ30: =SUM(AF30:AI30) -> 0 | AN30: 0 | AO30: =SUM(AK30:AN30) -> 0 | AS30: 0 | AT30: =SUM(AP30:AS30) -> 0 | AX30: 0 | AY30: =SUM(AU30:AX30) -> 0 | BC30: 0 | BD30: =SUM(AZ30:BC30) -> 0 | BH30: 0 | BI30: =SUM(BE30:BH30) -> 0 | BM30: 0 | BN30: =SUM(BJ30:BM30) -> 0 | BR30: 0 | BS30: =SUM(BO30:BR30) -> 0 | BT30: 0 | BU30: 0 | BV30: 0 | BW30: 0 | BX30: =SUM(BT30:BW30) -> 0 | BY30: 0 | BZ30: 0 | CA30: 0 | CB30: 0 | CC30: =SUM(BY30:CB30) -> 0 | CD30: 0 | CE30: 0 | CF30: =0%*'Balance Sheet'!CF9 -> 0 | CG30: 0 | CH30: =SUM(CD30:CG30) -> 0 | CI30: 0 | CJ30: 0 | CK30: =0%*'Balance Sheet'!CK9 -> 0 | CL30: 0 | CM30: =SUM(CI30:CL30) -> 0 | CN30: =0%*'Balance Sheet'!CN9 -> 0 | CO30: 0 | CP30: 0 | CQ30: 0 | CR30: =SUM(CN30:CQ30) -> 0 | CS30: =0%*'Balance Sheet'!CS9 -> 0 | CT30: 0 | CU30: 0 | CV30: 0 | CW30: =SUM(CS30:CV30) -> 0 | CX30: =0%*'Balance Sheet'!CX9 -> 0 | CY30: 0 | CZ30: 0 | DA30: 0 | DB30: =SUM(CX30:DA30) -> 0 | DC30: =0%*'Balance Sheet'!DC9 -> 0 | DD30: 0 | DE30: 0 | DF30: 0 | DG30: =SUM(DC30:DF30) -> 0 | DH30: =0%*'Balance Sheet'!DH9 -> 0 | DI30: 0 | DJ30: =0%*'Balance Sheet'!DJ9 -> 0 | DK30: =0%*'Balance Sheet'!DK9 -> 0 | DL30: =SUM(DH30:DK30) -> 0 | DM30: =0%*'Balance Sheet'!DM9 -> 0 | DN30: =0%*'Balance Sheet'!DN9 -> 0 | DO30: =0%*'Balance Sheet'!DO9 -> 0 | DP30: =0%*'Balance Sheet'!DP9 -> 0 | DQ30: =SUM(DM30:DP30) -> 0 | DR30: =0%*'Balance Sheet'!DR9 -> 0 | DS30: =0%*'Balance Sheet'!DS9 -> 0 | DT30: =0%*'Balance Sheet'!DT9 -> 0 | DU30: =0%*'Balance Sheet'!DU9 -> 0 | DV30: =SUM(DR30:DU30) -> 0 | DW30: =0%*'Balance Sheet'!DW9 -> 0 | DX30: =0%*'Balance Sheet'!DX9 -> 0 | DY30: =0%*'Balance Sheet'!DY9 -> 0 | DZ30: =0%*'Balance Sheet'!DZ9 -> 0 | EA30: =SUM(DW30:DZ30) -> 0 | EB30: =0%*'Balance Sheet'!EB9 -> 0 | EC30: =0%*'Balance Sheet'!EC9 -> 0 | ED30: =0%*'Balance Sheet'!ED9 -> 0 | EE30: =0%*'Balance Sheet'!EE9 -> 0 | EF30: =SUM(EB30:EE30) -> 0
A31: Extraordinary items | F31: =SUM(B31:E31) -> 0 | K31: =SUM(G31:J31) -> 0 | P31: =SUM(L31:O31) -> 0 | U31: =SUM(Q31:T31) -> 0 | Z31: =SUM(V31:Y31) -> 0 | AE31: =SUM(AA31:AD31) -> 0 | AI31: 0 | AJ31: =SUM(AF31:AI31) -> 0 | AN31: 0 | AO31: =SUM(AK31:AN31) -> 0 | AS31: 0 | AT31: =SUM(AP31:AS31) -> 0 | AX31: 0 | AY31: =SUM(AU31:AX31) -> 0 | BC31: 0 | BD31: =SUM(AZ31:BC31) -> 0 | BH31: 0 | BI31: =SUM(BE31:BH31) -> 0 | BM31: 0 | BN31: =SUM(BJ31:BM31) -> 0 | BR31: 0 | BS31: =SUM(BO31:BR31) -> 0 | BT31: 0 | BU31: 0 | BV31: 0 | BW31: 0 | BX31: =SUM(BT31:BW31) -> 0 | BY31: 0 | BZ31: 0 | CA31: 0 | CB31: 0 | CC31: =SUM(BY31:CB31) -> 0 | CD31: 0 | CE31: 0 | CF31: =CE31 -> 0 | CG31: 0 | CH31: =SUM(CD31:CG31) -> 0 | CI31: 0 | CJ31: 0 | CK31: =CJ31 -> 0 | CL31: 0 | CM31: =SUM(CI31:CL31) -> 0 | CN31: =CL31 -> 0 | CO31: 0 | CP31: 0 | CQ31: 0 | CR31: =SUM(CN31:CQ31) -> 0 | CS31: =CQ31 -> 0 | CT31: 0 | CU31: 0 | CV31: 0 | CW31: =SUM(CS31:CV31) -> 0 | CX31: =CV31 -> 0 | CY31: 0 | CZ31: 0 | DA31: 0 | DB31: =SUM(CX31:DA31) -> 0 | DC31: =DA31 -> 0 | DD31: 0 | DE31: 0 | DF31: 0 | DG31: =SUM(DC31:DF31) -> 0 | DH31: =DF31 -> 0 | DI31: 0 | DJ31: =DI31 -> 0 | DK31: =DJ31 -> 0 | DL31: =SUM(DH31:DK31) -> 0 | DM31: =DK31 -> 0 | DN31: =DM31 -> 0 | DO31: =DN31 -> 0 | DP31: =DO31 -> 0 | DQ31: =SUM(DM31:DP31) -> 0 | DR31: =DP31 -> 0 | DS31: =DR31 -> 0 | DT31: =DS31 -> 0 | DU31: =DT31 -> 0 | DV31: =SUM(DR31:DU31) -> 0 | DW31: =DU31 -> 0 | DX31: =DW31 -> 0 | DY31: =DX31 -> 0 | DZ31: =DY31 -> 0 | EA31: =SUM(DW31:DZ31) -> 0 | EB31: =DZ31 -> 0 | EC31: =EB31 -> 0 | ED31: =EC31 -> 0 | EE31: =ED31 -> 0 | EF31: =SUM(EB31:EE31) -> 0
A32: Other Operating Expenses | B32: =B33+B34+B35 -> 0 | C32: =C33+C34+C35 -> 0 | D32: =D33+D34+D35 -> 0 | E32: =E33+E34+E35 -> 0 | F32: =SUM(B32:E32) -> 0 | G32: =G33+G34+G35 -> 0 | H32: =H33+H34+H35 -> 0 | I32: =I33+I34+I35 -> 0 | J32: =J33+J34+J35 -> 0 | K32: =SUM(G32:J32) -> 0 | L32: =L33+L34+L35 -> 0 | M32: =M33+M34+M35 -> 0 | N32: =N33+N34+N35 -> 0 | O32: =O33+O34+O35 -> 0 | P32: =SUM(L32:O32) -> 0 | Q32: =Q33+Q34+Q35 -> 0 | R32: =R33+R34+R35 -> 0 | S32: =S33+S34+S35 -> 0 | T32: =T33+T34+T35 -> 0 | U32: =SUM(Q32:T32) -> 0 | V32: =V33+V34+V35 -> 0 | W32: =W33+W34+W35 -> 0 | X32: =X33+X34+X35 -> 0 | Y32: =Y33+Y34+Y35 -> 0 | Z32: =SUM(V32:Y32) -> 0 | AA32: =AA33+AA34+AA35 -> 0 | AB32: =AB33+AB34+AB35 -> 0 | AC32: =AC33+AC34+AC35 -> 0 | AD32: =AD33+AD34+AD35 -> 0 | AE32: =SUM(AA32:AD32) -> 0 | AF32: =AF33+AF34+AF35 -> 0 | AG32: =AG33+AG34+AG35 -> 0 | AH32: =AH33+AH34+AH35 -> 0 | AI32: =AI33+AI34+AI35 -> -89.89 | AJ32: =SUM(AF32:AI32) -> -89.89 | AK32: =AK33+AK34+AK35 -> 0 | AL32: =AL33+AL34+AL35 -> 0 | AM32: =AM33+AM34+AM35 -> 0 | AN32: =AN33+AN34+AN35 -> 151.507 | AO32: =SUM(AK32:AN32) -> 151.507 | AP32: =AP33+AP34+AP35 -> 0 | AQ32: =AQ33+AQ34+AQ35 -> 0 | AR32: =AR33+AR34+AR35 -> 0 | AS32: =AS33+AS34+AS35 -> -5220.239 | AT32: =SUM(AP32:AS32) -> -5220.239 | AU32: =AU33+AU34+AU35 -> 0 | AV32: =AV33+AV34+AV35 -> 0 | AW32: =AW33+AW34+AW35 -> 0 | AX32: =AX33+AX34+AX35 -> -2946.043 | AY32: =SUM(AU32:AX32) -> -2946.043 | AZ32: =AZ33+AZ34+AZ35 -> 0 | BA32: =BA33+BA34+BA35 -> 0 | BB32: =BB33+BB34+BB35 -> 0 | BC32: =BC33+BC34+BC35 -> -13514 | BD32: =SUM(AZ32:BC32) -> -13514 | BE32: =BE33+BE34+BE35 -> 0 | BF32: =BF33+BF34+BF35 -> 0 | BG32: =BG33+BG34+BG35 -> 0 | BH32: =BH33+BH34+BH35 -> -12889 | BI32: =SUM(BE32:BH32) -> -12889 | BJ32: =BJ33+BJ34+BJ35 -> 0 | BK32: =BK33+BK34+BK35 -> 0 | BL32: =BL33+BL34+BL35 -> 0 | BM32: =BM33+BM34+BM35 -> -7840 | BN32: =SUM(BJ32:BM32) -> -7840 | BO32: =BO33+BO34+BO35 -> 0 | BP32: =BP33+BP34+BP35 -> 0 | BQ32: =BQ33+BQ34+BQ35 -> 0 | BR32: =BR33+BR34+BR35 -> 21796 | BS32: =SUM(BO32:BR32) -> 21796 | BT32: =BT33+BT34+BT35 -> 0 | BU32: =BU33+BU34+BU35 -> 0 | BV32: =BV33+BV34+BV35 -> 0 | BW32: =BW33+BW34+BW35 -> 5717 | BX32: =SUM(BT32:BW32) -> 5717 | BY32: =BY33+BY34+BY35 -> 12268 | BZ32: =BZ33+BZ34+BZ35 -> 26623 | CA32: =CA33+CA34+CA35 -> 18961 | CB32: =CB33+CB34+CB35 -> 18642 | CC32: =SUM(BY32:CB32) -> 76494 | CD32: =CD33+CD34+CD35 -> -6104 | CE32: =CE33+CE34+CE35 -> 2058 | CF32: =CF33+CF34+CF35 -> -3669 | CG32: =CG33+CG34+CG35 -> 124 | CH32: =SUM(CD32:CG32) -> -7591 | CI32: =CI33+CI34+CI35 -> -6859 | CJ32: =CJ33+CJ34+CJ35 -> -11260 | CK32: =CK33+CK34+CK35 -> -9272 | CL32: =CL33+CL34+CL35 -> 23413 | CM32: =SUM(CI32:CL32) -> -3978 | CN32: =CN33+CN34+CN35 -> -19752 | CO32: =CO33+CO34+CO35 -> -15841 | CP32: =CP33+CP34+CP35 -> -11872 | CQ32: =CQ33+CQ34+CQ35 -> -13461 | CR32: =SUM(CN32:CQ32) -> -60926 | CS32: =CS33+CS34+CS35 -> -13586 | CT32: =CT33+CT34+CT35 -> -19289 | CU32: =CU33+CU34+CU35 -> -13499 | CV32: =CV33+CV34+CV35 -> -20648 | CW32: =SUM(CS32:CV32) -> -67022 | CX32: =CX33+CX34+CX35 -> -21874 | CY32: =CY33+CY34+CY35 -> -23978 | CZ32: =CZ33+CZ34+CZ35 -> -20472 | DA32: =DA33+DA34+DA35 -> -21847 | DB32: =SUM(CX32:DA32) -> -88171 | DC32: =DC33+DC34+DC35 -> -39942 | DD32: =DD33+DD34+DD35 -> -30720 | DE32: =DE33+DE34+DE35 -> -39423 | DF32: =DF33+DF34+DF35 -> -42467 | DG32: =SUM(DC32:DF32) -> -152552 | DH32: =DH33+DH34+DH35 -> -45003 | DI32: =DI33+DI34+DI35 -> -45995 | DJ32: =DJ33+DJ34+DJ35 -> -48011.128 | DK32: =DK33+DK34+DK35 -> -51921.071 | DL32: =SUM(DH32:DK32) -> -190930.2 | DM32: =DM33+DM34+DM35 -> -48285.66 | DN32: =DN33+DN34+DN35 -> -49851.167 | DO32: =DO33+DO34+DO35 -> -51179.974 | DP32: =DP33+DP34+DP35 -> -52406.916 | DQ32: =SUM(DM32:DP32) -> -201723.72 | DR32: =DR33+DR34+DR35 -> -53558.605 | DS32: =DS33+DS34+DS35 -> -54653.508 | DT32: =DT33+DT34+DT35 -> -55703.627 | DU32: =DU33+DU34+DU35 -> -56717.26 | DV32: =SUM(DR32:DU32) -> -220633 | DW32: =DW33+DW34+DW35 -> -57700.5 | DX32: =DX33+DX34+DX35 -> -58658.067 | DY32: =DY33+DY34+DY35 -> -59593.799 | DZ32: =DZ33+DZ34+DZ35 -> -60510.926 | EA32: =SUM(DW32:DZ32) -> -236463.29 | EB32: =EB33+EB34+EB35 -> -61412.239 | EC32: =EC33+EC34+EC35 -> -62300.192 | ED32: =ED33+ED34+ED35 -> -63176.965 | EE32: =EE33+EE34+EE35 -> -64044.514 | EF32: =SUM(EB32:EE32) -> -250933.91
A33: Expenses | F33: =SUM(B33:E33) -> 0 | K33: =SUM(G33:J33) -> 0 | P33: =SUM(L33:O33) -> 0 | U33: =SUM(Q33:T33) -> 0 | Z33: =SUM(V33:Y33) -> 0 | AE33: =SUM(AA33:AD33) -> 0 | AI33: =-89.89-SUM(AF33:AH33) -> -89.89 | AJ33: =SUM(AF33:AI33) -> -89.89 | AN33: =151.507-SUM(AK33:AM33) -> 151.507 | AO33: =SUM(AK33:AN33) -> 151.507 | AS33: =-5220.239-SUM(AP33:AR33) -> -5220.239 | AT33: =SUM(AP33:AS33) -> -5220.239 | AX33: =-2946.043-SUM(AU33:AW33) -> -2946.043 | AY33: =SUM(AU33:AX33) -> -2946.043 | BC33: =-8572-SUM(AZ33:BB33) -> -8572 | BD33: =SUM(AZ33:BC33) -> -8572 | BH33: =-9521-SUM(BE33:BG33) -> -9521 | BI33: =SUM(BE33:BH33) -> -9521 | BM33: =-2066-SUM(BJ33:BL33) -> -2066 | BN33: =SUM(BJ33:BM33) -> -2066 | BR33: =71520-42253-SUM(BO33:BQ33) -> 29267 | BS33: =SUM(BO33:BR33) -> 29267 | BW33: =38408-28973-SUM(BT33:BV33) -> 9435 | BX33: =SUM(BT33:BW33) -> 9435 | BY33: =23718-9596 -> 14122 | BZ33: =28892-2090 -> 26802 | CA33: =20410-1050 -> 19360 | CB33: =120320-42671-SUM(BY33:CA33) -> 17365 | CC33: =SUM(BY33:CB33) -> 77649 | CD33: =1328-4507 -> -3179 | CE33: =9179-6814 -> 2365 | CF33: =2943-6247 -> -3304 | CG33: =11840-17872-SUM(CD33:CF33) -> -1914 | CH33: =SUM(CD33:CG33) -> -6032 | CI33: =0-6524 -> -6524 | CJ33: =0-10905 -> -10905 | CK33: -8907 | CL33: =40444-42984-SUM(CI33:CK33) -> 23796 | CM33: =SUM(CI33:CL33) -> -2540 | CN33: =0-19298 -> -19298 | CO33: =0-15382 -> -15382 | CP33: -11456 | CQ33: =2756-61830-SUM(CN33:CP33) -> -12938 | CR33: =SUM(CN33:CQ33) -> -59074 | CS33: =-12810 -> -12810 | CT33: =0-18568 -> -18568 | CU33: -12803 | CV33: =0-64047-SUM(CS33:CU33) -> -19866 | CW33: =SUM(CS33:CV33) -> -64047 | CX33: -21345 | CY33: =0-23250 -> -23250 | CZ33: -19747 | DA33: =2965-88463-SUM(CX33:CZ33) -> -21156 | DB33: =SUM(CX33:DA33) -> -85498 | DC33: -39738 | DD33: =0-30494 -> -30494 | DE33: -39204 | DF33: =-151687-SUM(DC33:DE33) -> -42251 | DG33: =SUM(DC33:DF33) -> -151687 | DH33: -44791 | DI33: =-45797 -> -45797 | DJ33: =-2.75%*DJ5 -> -47137.679 | DK33: =-2.75%*DK5 -> -51043.146 | DL33: =SUM(DH33:DK33) -> -188768.82 | DM33: =-2.5%*DM5 -> -47403.237 | DN33: =-2.5%*DN5 -> -48964.223 | DO33: =-2.5%*DO5 -> -50288.486 | DP33: =-2.5%*DP5 -> -51510.86 | DQ33: =SUM(DM33:DP33) -> -198166.81 | DR33: =-2.5%*DR5 -> -52657.958 | DS33: =-2.5%*DS5 -> -53748.246 | DT33: =-2.5%*DT5 -> -54793.726 | DU33: =-2.5%*DU5 -> -55802.698 | DV33: =SUM(DR33:DU33) -> -217002.63 | DW33: =-2.5%*DW5 -> -56781.252 | DX33: =-2.5%*DX5 -> -57734.109 | DY33: =-2.5%*DY5 -> -58665.107 | DZ33: =-2.5%*DZ5 -> -59577.476 | EA33: =SUM(DW33:DZ33) -> -232757.94 | EB33: =-2.5%*EB5 -> -60474.006 | EC33: =-2.5%*EC5 -> -61357.152 | ED33: =-2.5%*ED5 -> -62229.093 | EE33: =-2.5%*EE5 -> -63091.786 | EF33: =SUM(EB33:EE33) -> -247152.04
A34: Depreciation | F34: =SUM(B34:E34) -> 0 | K34: =SUM(G34:J34) -> 0 | P34: =SUM(L34:O34) -> 0 | U34: =SUM(Q34:T34) -> 0 | Z34: =SUM(V34:Y34) -> 0 | AE34: =SUM(AA34:AD34) -> 0 | AJ34: =SUM(AF34:AI34) -> 0 | AO34: =SUM(AK34:AN34) -> 0 | AT34: =SUM(AP34:AS34) -> 0 | AY34: =SUM(AU34:AX34) -> 0 | BC34: -4942 | BD34: =SUM(AZ34:BC34) -> -4942 | BH34: -3368 | BI34: =SUM(BE34:BH34) -> -3368 | BM34: -5774 | BN34: =SUM(BJ34:BM34) -> -5774 | BR34: =-7471 -> -7471 | BS34: =SUM(BO34:BR34) -> -7471 | BW34: =-3718 -> -3718 | BX34: =SUM(BT34:BW34) -> -3718 | BY34: -1854 | BZ34: -179 | CA34: -399 | CB34: =-1155-SUM(BY34:CA34) -> 1277 | CC34: =SUM(BY34:CB34) -> -1155 | CD34: -2925 | CE34: -307 | CF34: -365 | CG34: =-1559-SUM(CD34:CF34) -> 2038 | CH34: =SUM(CD34:CG34) -> -1559 | CI34: -335 | CJ34: -355 | CK34: -365 | CL34: =-1438-SUM(CI34:CK34) -> -383 | CM34: =SUM(CI34:CL34) -> -1438 | CN34: -454 | CO34: -459 | CP34: -416 | CQ34: =-1852-SUM(CN34:CP34) -> -523 | CR34: =SUM(CN34:CQ34) -> -1852 | CS34: -776 | CT34: -721 | CU34: -696 | CV34: =-2975-SUM(CS34:CU34) -> -782 | CW34: =SUM(CS34:CV34) -> -2975 | CX34: -529 | CY34: -728 | CZ34: -725 | DA34: =-2673-SUM(CX34:CZ34) -> -691 | DB34: =SUM(CX34:DA34) -> -2673 | DC34: -204 | DD34: -226 | DE34: -219 | DF34: =-865-SUM(DC34:DE34) -> -216 | DG34: =SUM(DC34:DF34) -> -865 | DH34: -212 | DI34: -198 | DJ34: =DJ68*DI34/DI68 -> -873.44929 | DK34: =DK68*DJ34/DJ68 -> -877.92456 | DL34: =SUM(DH34:DK34) -> -2161.3739 | DM34: =DM68*DK34/DK68 -> -882.42276 | DN34: =DN68*DM34/DM68 -> -886.944 | DO34: =DO68*DN34/DN68 -> -891.48841 | DP34: =DP68*DO34/DO68 -> -896.0561 | DQ34: =SUM(DM34:DP34) -> -3556.9113 | DR34: =DR68*DP34/DP68 -> -900.6472 | DS34: =DS68*DR34/DR68 -> -905.26182 | DT34: =DT68*DS34/DS68 -> -909.90008 | DU34: =DU68*DT34/DT68 -> -914.56211 | DV34: =SUM(DR34:DU34) -> -3630.3712 | DW34: =DW68*DU34/DU68 -> -919.24803 | DX34: =DX68*DW34/DW68 -> -923.95795 | DY34: =DY68*DX34/DX68 -> -928.69201 | DZ34: =DZ68*DY34/DY68 -> -933.45032 | EA34: =SUM(DW34:DZ34) -> -3705.3483 | EB34: =EB68*DZ34/DZ68 -> -938.23301 | EC34: =EC68*EB34/EB68 -> -943.04021 | ED34: =ED68*EC34/EC68 -> -947.87204 | EE34: =EE68*ED34/ED68 -> -952.72862 | EF34: =SUM(EB34:EE34) -> -3781.8739
A35: Extraordinary items | F35: =SUM(B35:E35) -> 0 | K35: =SUM(G35:J35) -> 0 | P35: =SUM(L35:O35) -> 0 | U35: =SUM(Q35:T35) -> 0 | Z35: =SUM(V35:Y35) -> 0 | AE35: =SUM(AA35:AD35) -> 0 | AI35: 0 | AJ35: =SUM(AF35:AI35) -> 0 | AN35: 0 | AO35: =SUM(AK35:AN35) -> 0 | AS35: 0 | AT35: =SUM(AP35:AS35) -> 0 | AX35: 0 | AY35: =SUM(AU35:AX35) -> 0 | BC35: 0 | BD35: =SUM(AZ35:BC35) -> 0 | BH35: 0 | BI35: =SUM(BE35:BH35) -> 0 | BM35: 0 | BN35: =SUM(BJ35:BM35) -> 0 | BR35: 0 | BS35: =SUM(BO35:BR35) -> 0 | BT35: 0 | BU35: 0 | BV35: 0 | BW35: 0 | BX35: =SUM(BT35:BW35) -> 0 | BY35: 0 | BZ35: 0 | CA35: 0 | CB35: 0 | CC35: =SUM(BY35:CB35) -> 0 | CD35: 0 | CE35: 0 | CF35: 0 | CG35: 0 | CH35: =SUM(CD35:CG35) -> 0 | CI35: 0 | CJ35: 0 | CK35: 0 | CL35: 0 | CM35: =SUM(CI35:CL35) -> 0 | CN35: 0 | CO35: 0 | CP35: 0 | CQ35: 0 | CR35: =SUM(CN35:CQ35) -> 0 | CS35: 0 | CT35: 0 | CU35: 0 | CV35: 0 | CW35: =SUM(CS35:CV35) -> 0 | CX35: 0 | CY35: 0 | CZ35: 0 | DA35: 0 | DB35: =SUM(CX35:DA35) -> 0 | DC35: 0 | DD35: 0 | DE35: 0 | DF35: 0 | DG35: =SUM(DC35:DF35) -> 0 | DH35: 0 | DI35: 0 | DJ35: =DI35 -> 0 | DK35: =DJ35 -> 0 | DL35: =SUM(DH35:DK35) -> 0 | DM35: =DK35 -> 0 | DN35: =DM35 -> 0 | DO35: =DN35 -> 0 | DP35: =DO35 -> 0 | DQ35: =SUM(DM35:DP35) -> 0 | DR35: =DP35 -> 0 | DS35: =DR35 -> 0 | DT35: =DS35 -> 0 | DU35: =DT35 -> 0 | DV35: =SUM(DR35:DU35) -> 0 | DW35: =DU35 -> 0 | DX35: =DW35 -> 0 | DY35: =DX35 -> 0 | DZ35: =DY35 -> 0 | EA35: =SUM(DW35:DZ35) -> 0 | EB35: =DZ35 -> 0 | EC35: =EB35 -> 0 | ED35: =EC35 -> 0 | EE35: =ED35 -> 0 | EF35: =SUM(EB35:EE35) -> 0
A36: Equity Income | F36: =SUM(B36:E36) -> 0 | K36: =SUM(G36:J36) -> 0 | P36: =SUM(L36:O36) -> 0 | U36: =SUM(Q36:T36) -> 0 | Z36: =SUM(V36:Y36) -> 0 | AE36: =SUM(AA36:AD36) -> 0 | AI36: 0 | AJ36: =SUM(AF36:AI36) -> 0 | AN36: 0 | AO36: =SUM(AK36:AN36) -> 0 | AS36: =12836.41-SUM(AP36:AR36) -> 12836.41 | AT36: =SUM(AP36:AS36) -> 12836.41 | AX36: =2995.612-SUM(AU36:AW36) -> 2995.612 | AY36: =SUM(AU36:AX36) -> 2995.612 | BC36: =7534-SUM(AZ36:BB36) -> 7534 | BD36: =SUM(AZ36:BC36) -> 7534 | BH36: =8164-SUM(BE36:BG36) -> 8164 | BI36: =SUM(BE36:BH36) -> 8164 | BM36: =-355-SUM(BJ36:BL36) -> -355 | BN36: =SUM(BJ36:BM36) -> -355 | BR36: 1042 | BS36: =SUM(BO36:BR36) -> 1042 | BW36: -498 | BX36: =SUM(BT36:BW36) -> -498 | BY36: -359 | BZ36: -1062 | CA36: 849 | CB36: =1486-SUM(BY36:CA36) -> 2058 | CC36: =SUM(BY36:CB36) -> 1486 | CD36: 791 | CE36: 195 | CF36: 336 | CG36: =2360-SUM(CD36:CF36) -> 1038 | CH36: =SUM(CD36:CG36) -> 2360 | CI36: 1138 | CJ36: 1726 | CK36: -946 | CL36: =927-SUM(CI36:CK36) -> -991 | CM36: =SUM(CI36:CL36) -> 927 | CN36: -311 | CO36: -141 | CP36: 976 | CQ36: =379-SUM(CN36:CP36) -> -145 | CR36: =SUM(CN36:CQ36) -> 379 | CS36: -110 | CT36: 696 | CU36: -295 | CV36: =1647-SUM(CS36:CU36) -> 1356 | CW36: =SUM(CS36:CV36) -> 1647 | CX36: 1299 | CY36: 2806 | CZ36: 3390 | DA36: =8539-SUM(CX36:CZ36) -> 1044 | DB36: =SUM(CX36:DA36) -> 8539 | DC36: 688 | DD36: 1091 | DE36: 2474 | DF36: =7390-SUM(DC36:DE36) -> 3137 | DG36: =SUM(DC36:DF36) -> 7390 | DH36: 2282 | DI36: 1014 | DJ36: =15%*('Balance Sheet'!DI20-'Balance Sheet'!DI136)/4 -> 1142.6625 | DK36: =15%*('Balance Sheet'!DJ20-'Balance Sheet'!DJ136)/4 -> 1164.0874 | DL36: =SUM(DH36:DK36) -> 5602.7499 | DM36: =15%*('Balance Sheet'!DL20-'Balance Sheet'!DL136)/4 -> 1185.9141 | DN36: =15%*('Balance Sheet'!DM20-'Balance Sheet'!DM136)/4 -> 1208.1499 | DO36: =15%*('Balance Sheet'!DN20-'Balance Sheet'!DN136)/4 -> 1230.8028 | DP36: =15%*('Balance Sheet'!DO20-'Balance Sheet'!DO136)/4 -> 1253.8803 | DQ36: =SUM(DM36:DP36) -> 4878.7471 | DR36: =15%*('Balance Sheet'!DQ20-'Balance Sheet'!DQ136)/4 -> 1277.3906 | DS36: =15%*('Balance Sheet'!DR20-'Balance Sheet'!DR136)/4 -> 1301.3416 | DT36: =15%*('Balance Sheet'!DS20-'Balance Sheet'!DS136)/4 -> 1325.7418 | DU36: =15%*('Balance Sheet'!DT20-'Balance Sheet'!DT136)/4 -> 1350.5995 | DV36: =SUM(DR36:DU36) -> 5255.0735 | DW36: =15%*('Balance Sheet'!DV20-'Balance Sheet'!DV136)/4 -> 1375.9232 | DX36: =15%*('Balance Sheet'!DW20-'Balance Sheet'!DW136)/4 -> 1401.7218 | DY36: =15%*('Balance Sheet'!DX20-'Balance Sheet'!DX136)/4 -> 1428.004 | DZ36: =15%*('Balance Sheet'!DY20-'Balance Sheet'!DY136)/4 -> 1454.7791 | EA36: =SUM(DW36:DZ36) -> 5660.4281 | EB36: =15%*('Balance Sheet'!EA20-'Balance Sheet'!EA136)/4 -> 1482.0562 | EC36: =15%*('Balance Sheet'!EB20-'Balance Sheet'!EB136)/4 -> 1509.8448 | ED36: =15%*('Balance Sheet'!EC20-'Balance Sheet'!EC136)/4 -> 1538.1544 | EE36: =15%*('Balance Sheet'!ED20-'Balance Sheet'!ED136)/4 -> 1566.9948 | EF36: =SUM(EB36:EE36) -> 6097.0501
A37: Operating Income | B37: =B16+B17 -> 0 | C37: =C16+C17 -> 0 | D37: =D16+D17 -> 0 | E37: =E16+E17 -> 0 | F37: =SUM(B37:E37) -> 0 | G37: =G16+G17 -> 0 | H37: =H16+H17 -> 0 | I37: =I16+I17 -> 0 | J37: =J16+J17 -> 0 | K37: =SUM(G37:J37) -> 0 | L37: =L16+L17 -> 0 | M37: =M16+M17 -> 0 | N37: =N16+N17 -> 0 | O37: =O16+O17 -> 0 | P37: =SUM(L37:O37) -> 0 | Q37: =Q16+Q17 -> 0 | R37: =R16+R17 -> 0 | S37: =S16+S17 -> 0 | T37: =T16+T17 -> 0 | U37: =SUM(Q37:T37) -> 0 | V37: =V16+V17 -> 0 | W37: =W16+W17 -> 0 | X37: =X16+X17 -> 0 | Y37: =Y16+Y17 -> 0 | Z37: =SUM(V37:Y37) -> 0 | AA37: =AA16+AA17 -> 0 | AB37: =AB16+AB17 -> 0 | AC37: =AC16+AC17 -> 0 | AD37: =AD16+AD17 -> 0 | AE37: =SUM(AA37:AD37) -> 0 | AF37: =AF16+AF17 -> 0 | AG37: =AG16+AG17 -> 0 | AH37: =AH16+AH17 -> 0 | AI37: =AI16+AI17 -> 58071.81 | AJ37: =SUM(AF37:AI37) -> 58071.81 | AK37: =AK16+AK17 -> 0 | AL37: =AL16+AL17 -> 0 | AM37: =AM16+AM17 -> 0 | AN37: =AN16+AN17 -> 101770.82 | AO37: =SUM(AK37:AN37) -> 101770.82 | AP37: =AP16+AP17 -> 0 | AQ37: =AQ16+AQ17 -> 0 | AR37: =AR16+AR17 -> 0 | AS37: =AS16+AS17 -> 134961.81 | AT37: =SUM(AP37:AS37) -> 134961.81 | AU37: =AU16+AU17 -> 0 | AV37: =AV16+AV17 -> 0 | AW37: =AW16+AW17 -> 0 | AX37: =AX16+AX17 -> 185290.56 | AY37: =SUM(AU37:AX37) -> 185290.56 | AZ37: =AZ16+AZ17 -> 0 | BA37: =BA16+BA17 -> 0 | BB37: =BB16+BB17 -> 0 | BC37: =BC16+BC17 -> 184594 | BD37: =SUM(AZ37:BC37) -> 184594 | BE37: =BE16+BE17 -> 0 | BF37: =BF16+BF17 -> 0 | BG37: =BG16+BG17 -> 0 | BH37: =BH16+BH17 -> 171769 | BI37: =SUM(BE37:BH37) -> 171769 | BJ37: =BJ16+BJ17 -> 0 | BK37: =BK16+BK17 -> 0 | BL37: =BL16+BL17 -> 0 | BM37: =BM16+BM17 -> 123109 | BN37: =SUM(BJ37:BM37) -> 123109 | BO37: =BO16+BO17 -> 0 | BP37: =BP16+BP17 -> 0 | BQ37: =BQ16+BQ17 -> 0 | BR37: =BR16+BR17 -> 142596 | BS37: =SUM(BO37:BR37) -> 142596 | BT37: =BT16+BT17 -> 0 | BU37: =BU16+BU17 -> 0 | BV37: =BV16+BV17 -> 0 | BW37: =BW16+BW17 -> 194461 | BX37: =SUM(BT37:BW37) -> 194461 | BY37: =BY16+BY17 -> 28257 | BZ37: =BZ16+BZ17 -> 79268 | CA37: =CA16+CA17 -> 45183 | CB37: =CB16+CB17 -> 73387 | CC37: =SUM(BY37:CB37) -> 226095 | CD37: =CD16+CD17 -> 23155 | CE37: =CE16+CE17 -> 45884 | CF37: =CF16+CF17 -> 66118 | CG37: =CG16+CG17 -> 81055 | CH37: =SUM(CD37:CG37) -> 216212 | CI37: =CI16+CI17 -> 58947 | CJ37: =CJ16+CJ17 -> 85365 | CK37: =CK16+CK17 -> 84976 | CL37: =CL16+CL17 -> 122353 | CM37: =SUM(CI37:CL37) -> 351641 | CN37: =CN16+CN17 -> 74988 | CO37: =CO16+CO17 -> 107387 | CP37: =CP16+CP17 -> 110405 | CQ37: =CQ16+CQ17 -> 112224 | CR37: =SUM(CN37:CQ37) -> 405004 | CS37: =CS16+CS17 -> 109392 | CT37: =CT16+CT17 -> 142265 | CU37: =CU16+CU17 -> 132019 | CV37: =CV16+CV17 -> 184353 | CW37: =SUM(CS37:CV37) -> 568029 | CX37: =CX16+CX17 -> 174256 | CY37: =CY16+CY17 -> 196190 | CZ37: =CZ16+CZ17 -> 203590 | DA37: =DA16+DA17 -> 214560 | DB37: =SUM(CX37:DA37) -> 788596 | DC37: =DC16+DC17 -> 264667 | DD37: =DD16+DD17 -> 298596 | DE37: =DE16+DE17 -> 319973 | DF37: =DF16+DF17 -> 337010 | DG37: =SUM(DC37:DF37) -> 1220246 | DH37: =DH16+DH17 -> 392436 | DI37: =DI16+DI17 -> 356305 | DJ37: =DJ16+DJ17 -> 384038.84 | DK37: =DK16+DK17 -> 444716.23 | DL37: =SUM(DH37:DK37) -> 1577496.1 | DM37: =DM16+DM17 -> 444420.43 | DN37: =DN16+DN17 -> 458696.19 | DO37: =DO16+DO17 -> 464668.56 | DP37: =DP16+DP17 -> 478867.89 | DQ37: =SUM(DM37:DP37) -> 1846653.1 | DR37: =DR16+DR17 -> 496192.45 | DS37: =DS16+DS17 -> 494992.24 | DT37: =DT16+DT17 -> 511224.95 | DU37: =DU16+DU17 -> 531129.87 | DV37: =SUM(DR37:DU37) -> 2033539.5 | DW37: =DW16+DW17 -> 528440.16 | DX37: =DX16+DX17 -> 525333.9 | DY37: =DY16+DY17 -> 544634.22 | DZ37: =DZ16+DZ17 -> 564300.64 | EA37: =SUM(DW37:DZ37) -> 2162708.9 | EB37: =EB16+EB17 -> 560394.54 | EC37: =EC16+EC17 -> 556156.68 | ED37: =ED16+ED17 -> 575513.92 | EE37: =EE16+EE17 -> 595200.58 | EF37: =SUM(EB37:EE37) -> 2287265.7
A38: Non-operating Expenses | B38: 0 | C38: 0 | D38: 0 | E38: 0 | F38: 0 | G38: 0 | H38: 0 | I38: 0 | J38: 0 | K38: 0 | L38: 0 | M38: 0 | N38: 0 | O38: 0 | P38: 0 | Q38: 0 | R38: 0 | S38: 0 | T38: 0 | U38: 0 | V38: 0 | W38: 0 | X38: 0 | Y38: 0 | Z38: 0 | AA38: 0 | AB38: 0 | AC38: 0 | AD38: 0 | AE38: 0 | AF38: =AD38 -> 0 | AG38: =AF38 -> 0 | AH38: =AG38 -> 0 | AI38: =AH38 -> 0 | AJ38: =SUM(AF38:AI38) -> 0 | AK38: =AI38 -> 0 | AL38: =AK38 -> 0 | AM38: =AL38 -> 0 | AN38: =AM38 -> 0 | AO38: =SUM(AK38:AN38) -> 0 | AP38: =AN38 -> 0 | AQ38: =AP38 -> 0 | AR38: =AQ38 -> 0 | AS38: =AR38 -> 0 | AT38: =SUM(AP38:AS38) -> 0 | AU38: =AS38 -> 0 | AV38: =AU38 -> 0 | AW38: =AV38 -> 0 | AX38: =AW38 -> 0 | AY38: =SUM(AU38:AX38) -> 0 | AZ38: =AX38 -> 0 | BA38: =AZ38 -> 0 | BB38: =BA38 -> 0 | BC38: =BB38 -> 0 | BD38: =SUM(AZ38:BC38) -> 0 | BE38: =BC38 -> 0 | BF38: =BE38 -> 0 | BG38: =BF38 -> 0 | BH38: =BG38 -> 0 | BI38: =SUM(BE38:BH38) -> 0 | BJ38: =BH38 -> 0 | BK38: =BJ38 -> 0 | BL38: =BK38 -> 0 | BM38: =BL38 -> 0 | BN38: =SUM(BJ38:BM38) -> 0 | BO38: =BM38 -> 0 | BP38: =BO38 -> 0 | BQ38: =BP38 -> 0 | BR38: =BQ38 -> 0 | BS38: =SUM(BO38:BR38) -> 0 | BT38: =BR38 -> 0 | BU38: =BT38 -> 0 | BV38: =BU38 -> 0 | BW38: =BV38 -> 0 | BX38: =SUM(BT38:BW38) -> 0 | BY38: =BW38 -> 0 | BZ38: =BY38 -> 0 | CA38: =BZ38 -> 0 | CB38: =CA38 -> 0 | CC38: =SUM(BY38:CB38) -> 0 | CD38: =CB38 -> 0 | CE38: =CD38 -> 0 | CF38: =CE38 -> 0 | CG38: =CF38 -> 0 | CH38: =SUM(CD38:CG38) -> 0 | CI38: =CG38 -> 0 | CJ38: =CI38 -> 0 | CK38: =CJ38 -> 0 | CL38: =CK38 -> 0 | CM38: =SUM(CI38:CL38) -> 0 | CN38: =CL38 -> 0 | CO38: =CN38 -> 0 | CP38: =CO38 -> 0 | CQ38: =CP38 -> 0 | CR38: =SUM(CN38:CQ38) -> 0 | CS38: =CQ38 -> 0 | CT38: =CS38 -> 0 | CU38: =CT38 -> 0 | CV38: =CU38 -> 0 | CW38: =SUM(CS38:CV38) -> 0 | CX38: =CV38 -> 0 | CY38: =CX38 -> 0 | CZ38: =CY38 -> 0 | DA38: =CZ38 -> 0 | DB38: =SUM(CX38:DA38) -> 0 | DC38: =DA38 -> 0 | DD38: =DC38 -> 0 | DE38: =DD38 -> 0 | DF38: =DE38 -> 0 | DG38: =SUM(DC38:DF38) -> 0 | DH38: =DF38 -> 0 | DI38: =DH38 -> 0 | DJ38: =DI38 -> 0 | DK38: =DJ38 -> 0 | DL38: =SUM(DH38:DK38) -> 0 | DM38: =DK38 -> 0 | DN38: =DM38 -> 0 | DO38: =DN38 -> 0 | DP38: =DO38 -> 0 | DQ38: =SUM(DM38:DP38) -> 0 | DR38: =DP38 -> 0 | DS38: =DR38 -> 0 | DT38: =DS38 -> 0 | DU38: =DT38 -> 0 | DV38: =SUM(DR38:DU38) -> 0 | DW38: =DU38 -> 0 | DX38: =DW38 -> 0 | DY38: =DX38 -> 0 | DZ38: =DY38 -> 0 | EA38: =SUM(DW38:DZ38) -> 0 | EB38: =DZ38 -> 0 | EC38: =EB38 -> 0 | ED38: =EC38 -> 0 | EE38: =ED38 -> 0 | EF38: =SUM(EB38:EE38) -> 0
A39: Income Before Taxes on Income | B39: =B37+B38 -> 0 | C39: =C37+C38 -> 0 | D39: =D37+D38 -> 0 | E39: =E37+E38 -> 0 | F39: =SUM(B39:E39) -> 0 | G39: =G37+G38 -> 0 | H39: =H37+H38 -> 0 | I39: =I37+I38 -> 0 | J39: =J37+J38 -> 0 | K39: =SUM(G39:J39) -> 0 | L39: =L37+L38 -> 0 | M39: =M37+M38 -> 0 | N39: =N37+N38 -> 0 | O39: =O37+O38 -> 0 | P39: =SUM(L39:O39) -> 0 | Q39: =Q37+Q38 -> 0 | R39: =R37+R38 -> 0 | S39: =S37+S38 -> 0 | T39: =T37+T38 -> 0 | U39: =SUM(Q39:T39) -> 0 | V39: =V37+V38 -> 0 | W39: =W37+W38 -> 0 | X39: =X37+X38 -> 0 | Y39: =Y37+Y38 -> 0 | Z39: =SUM(V39:Y39) -> 0 | AA39: =AA37+AA38 -> 0 | AB39: =AB37+AB38 -> 0 | AC39: =AC37+AC38 -> 0 | AD39: =AD37+AD38 -> 0 | AE39: =SUM(AA39:AD39) -> 0 | AF39: =AF37+AF38 -> 0 | AG39: =AG37+AG38 -> 0 | AH39: =AH37+AH38 -> 0 | AI39: =AI37+AI38 -> 58071.81 | AJ39: =SUM(AF39:AI39) -> 58071.81 | AK39: =AK37+AK38 -> 0 | AL39: =AL37+AL38 -> 0 | AM39: =AM37+AM38 -> 0 | AN39: =AN37+AN38 -> 101770.82 | AO39: =SUM(AK39:AN39) -> 101770.82 | AP39: =AP37+AP38 -> 0 | AQ39: =AQ37+AQ38 -> 0 | AR39: =AR37+AR38 -> 0 | AS39: =AS37+AS38 -> 134961.81 | AT39: =SUM(AP39:AS39) -> 134961.81 | AU39: =AU37+AU38 -> 0 | AV39: =AV37+AV38 -> 0 | AW39: =AW37+AW38 -> 0 | AX39: =AX37+AX38 -> 185290.56 | AY39: =SUM(AU39:AX39) -> 185290.56 | AZ39: =AZ37+AZ38 -> 0 | BA39: =BA37+BA38 -> 0 | BB39: =BB37+BB38 -> 0 | BC39: =BC37+BC38 -> 184594 | BD39: =SUM(AZ39:BC39) -> 184594 | BE39: =BE37+BE38 -> 0 | BF39: =BF37+BF38 -> 0 | BG39: =BG37+BG38 -> 0 | BH39: =BH37+BH38 -> 171769 | BI39: =SUM(BE39:BH39) -> 171769 | BJ39: =BJ37+BJ38 -> 0 | BK39: =BK37+BK38 -> 0 | BL39: =BL37+BL38 -> 0 | BM39: =BM37+BM38 -> 123109 | BN39: =SUM(BJ39:BM39) -> 123109 | BO39: =BO37+BO38 -> 0 | BP39: =BP37+BP38 -> 0 | BQ39: =BQ37+BQ38 -> 0 | BR39: =BR37+BR38 -> 142596 | BS39: =SUM(BO39:BR39) -> 142596 | BT39: =BT37+BT38 -> 0 | BU39: =BU37+BU38 -> 0 | BV39: =BV37+BV38 -> 0 | BW39: =BW37+BW38 -> 194461 | BX39: =SUM(BT39:BW39) -> 194461 | BY39: =BY37+BY38 -> 28257 | BZ39: =BZ37+BZ38 -> 79268 | CA39: =CA37+CA38 -> 45183 | CB39: =CB37+CB38 -> 73387 | CC39: =SUM(BY39:CB39) -> 226095 | CD39: =CD37+CD38 -> 23155 | CE39: =CE37+CE38 -> 45884 | CF39: =CF37+CF38 -> 66118 | CG39: =CG37+CG38 -> 81055 | CH39: =SUM(CD39:CG39) -> 216212 | CI39: =CI37+CI38 -> 58947 | CJ39: =CJ37+CJ38 -> 85365 | CK39: =CK37+CK38 -> 84976 | CL39: =CL37+CL38 -> 122353 | CM39: =SUM(CI39:CL39) -> 351641 | CN39: =CN37+CN38 -> 74988 | CO39: =CO37+CO38 -> 107387 | CP39: =CP37+CP38 -> 110405 | CQ39: =CQ37+CQ38 -> 112224 | CR39: =SUM(CN39:CQ39) -> 405004 | CS39: =CS37+CS38 -> 109392 | CT39: =CT37+CT38 -> 142265 | CU39: =CU37+CU38 -> 132019 | CV39: =CV37+CV38 -> 184353 | CW39: =SUM(CS39:CV39) -> 568029 | CX39: =CX37+CX38 -> 174256 | CY39: =CY37+CY38 -> 196190 | CZ39: =CZ37+CZ38 -> 203590 | DA39: =DA37+DA38 -> 214560 | DB39: =SUM(CX39:DA39) -> 788596 | DC39: =DC37+DC38 -> 264667 | DD39: =DD37+DD38 -> 298596 | DE39: =DE37+DE38 -> 319973 | DF39: =DF37+DF38 -> 337010 | DG39: =SUM(DC39:DF39) -> 1220246 | DH39: =DH37+DH38 -> 392436 | DI39: =DI37+DI38 -> 356305 | DJ39: =DJ37+DJ38 -> 384038.84 | DK39: =DK37+DK38 -> 444716.23 | DL39: =SUM(DH39:DK39) -> 1577496.1 | DM39: =DM37+DM38 -> 444420.43 | DN39: =DN37+DN38 -> 458696.19 | DO39: =DO37+DO38 -> 464668.56 | DP39: =DP37+DP38 -> 478867.89 | DQ39: =SUM(DM39:DP39) -> 1846653.1 | DR39: =DR37+DR38 -> 496192.45 | DS39: =DS37+DS38 -> 494992.24 | DT39: =DT37+DT38 -> 511224.95 | DU39: =DU37+DU38 -> 531129.87 | DV39: =SUM(DR39:DU39) -> 2033539.5 | DW39: =DW37+DW38 -> 528440.16 | DX39: =DX37+DX38 -> 525333.9 | DY39: =DY37+DY38 -> 544634.22 | DZ39: =DZ37+DZ38 -> 564300.64 | EA39: =SUM(DW39:DZ39) -> 2162708.9 | EB39: =EB37+EB38 -> 560394.54 | EC39: =EC37+EC38 -> 556156.68 | ED39: =ED37+ED38 -> 575513.92 | EE39: =EE37+EE38 -> 595200.58 | EF39: =SUM(EB39:EE39) -> 2287265.7
A40: Income Tax and Social Contribution | F40: =SUM(B40:E40) -> 0 | K40: =SUM(G40:J40) -> 0 | P40: =SUM(L40:O40) -> 0 | U40: =SUM(Q40:T40) -> 0 | Z40: =SUM(V40:Y40) -> 0 | AE40: =SUM(AA40:AD40) -> 0 | AI40: =-2746.112-SUM(AF40:AH40) -> -2746.112 | AJ40: =SUM(AF40:AI40) -> -2746.112 | AN40: =-9523.458-SUM(AK40:AM40) -> -9523.458 | AO40: =SUM(AK40:AN40) -> -9523.458 | AS40: =-11627.113-SUM(AP40:AR40) -> -11627.113 | AT40: =SUM(AP40:AS40) -> -11627.113 | AX40: =-13554.618-SUM(AU40:AW40) -> -13554.618 | AY40: =SUM(AU40:AX40) -> -13554.618 | BC40: =-11220-SUM(AZ40:BB40) -> -11220 | BD40: =SUM(AZ40:BC40) -> -11220 | BH40: =-10765-SUM(BE40:BG40) -> -10765 | BI40: =SUM(BE40:BH40) -> -10765 | BM40: =-11226-SUM(BJ40:BL40) -> -11226 | BN40: =SUM(BJ40:BM40) -> -11226 | BR40: =-13399-SUM(BO40:BQ40) -> -13399 | BS40: =SUM(BO40:BR40) -> -13399 | BW40: =-17745-SUM(BT40:BV40) -> -17745 | BX40: =SUM(BT40:BW40) -> -17745 | BY40: -4567 | BZ40: -5053 | CA40: -5661 | CB40: =-21283-SUM(BY40:CA40) -> -6002 | CC40: =SUM(BY40:CB40) -> -21283 | CD40: -7071 | CE40: -5058 | CF40: -5901 | CG40: =-24650-SUM(CD40:CF40) -> -6620 | CH40: =SUM(CD40:CG40) -> -24650 | CI40: -5387 | CJ40: -6221 | CK40: -9486 | CL40: =-31893-SUM(CI40:CK40) -> -10799 | CM40: =SUM(CI40:CL40) -> -31893 | CN40: -9507 | CO40: -12324 | CP40: -13899 | CQ40: =-50756-SUM(CN40:CP40) -> -15026 | CR40: =SUM(CN40:CQ40) -> -50756 | CS40: -13709 | CT40: -15906 | CU40: -18328 | CV40: =-67835-SUM(CS40:CU40) -> -19892 | CW40: =SUM(CS40:CV40) -> -67835 | CX40: -17229 | CY40: -19957 | CZ40: -21440 | DA40: =-86551-SUM(CX40:CZ40) -> -27925 | DB40: =SUM(CX40:DA40) -> -86551 | DC40: -22310 | DD40: -28545 | DE40: -37023 | DF40: =-127835-SUM(DC40:DE40) -> -39957 | DG40: =SUM(DC40:DF40) -> -127835 | DH40: -37247 | DI40: -42103 | DJ40: =-DJ41*(DJ4+'Balance Sheet'!DJ63) -> -31145.688 | DK40: =-DK41*(DK4+'Balance Sheet'!DK63) -> -33179.116 | DL40: =SUM(DH40:DK40) -> -143674.8 | DM40: =-DM41*(DM4+'Balance Sheet'!DM63) -> -37252.486 | DN40: =-DN41*(DN4+'Balance Sheet'!DN63) -> -35840.421 | DO40: =-DO41*(DO4+'Balance Sheet'!DO63) -> -37138.419 | DP40: =-DP41*(DP4+'Balance Sheet'!DP63) -> -38199.136 | DQ40: =SUM(DM40:DP40) -> -148430.46 | DR40: =-DR41*(DR4+'Balance Sheet'!DR63) -> -39170.567 | DS40: =-DS41*(DS4+'Balance Sheet'!DS63) -> -40076.522 | DT40: =-DT41*(DT4+'Balance Sheet'!DT63) -> -40933.854 | DU40: =-DU41*(DU4+'Balance Sheet'!DU63) -> -41753.312 | DV40: =SUM(DR40:DU40) -> -161934.26 | DW40: =-DW41*(DW4+'Balance Sheet'!DW63) -> -42542.187 | DX40: =-DX41*(DX4+'Balance Sheet'!DX63) -> -43305.722 | DY40: =-DY41*(DY4+'Balance Sheet'!DY63) -> -44047.915 | DZ40: =-DZ41*(DZ4+'Balance Sheet'!DZ63) -> -44771.967 | EA40: =SUM(DW40:DZ40) -> -174667.79 | EB40: =-EB41*(EB4+'Balance Sheet'!EB63) -> -45480.542 | EC40: =-EC41*(EC4+'Balance Sheet'!EC63) -> -46175.926 | ED40: =-ED41*(ED4+'Balance Sheet'!ED63) -> -46860.118 | EE40: =-EE41*(EE4+'Balance Sheet'!EE63) -> -47534.889 | EF40: =SUM(EB40:EE40) -> -186051.47
A41: Cash tax rate (% of collection) | B41: =-B40/#REF! -> #REF! | C41: =-C40/#REF! -> #REF! | D41: =-D40/#REF! -> #REF! | E41: =-E40/#REF! -> #REF! | F41: =-F40/#REF! -> #REF! | G41: =-G40/#REF! -> #REF! | H41: =-H40/#REF! -> #REF! | I41: =-I40/#REF! -> #REF! | ... AE41: =-AE40/#REF! -> #REF! | AF41: =-AF40/(AF4+'Balance Sheet'!AF63) -> #DIV/0! | AG41: =-AG40/(AG4+'Balance Sheet'!AG63) -> #DIV/0! | AH41: =-AH40/(AH4+'Balance Sheet'!AH63) -> #DIV/0! | AI41: =-AI40/(AI4+'Balance Sheet'!AI63) -> 0.26107833 | AJ41: =-AJ40/(AJ4+'Balance Sheet'!AJ63) -> 0.26107833 | AK41: =-AK40/(AK4+'Balance Sheet'!AK63) -> 0 | AL41: =-AL40/(AL4+'Balance Sheet'!AL63) -> #DIV/0! | AM41: =-AM40/(AM4+'Balance Sheet'!AM63) -> #DIV/0! | ... DI41: =-DI40/(DI4+'Balance Sheet'!DI63) -> 0.02711435 | DJ41: =1.26%+0.66% -> 0.0192 | DK41: =1.26%+0.66% -> 0.0192 | DL41: =-DL40/(DL4+'Balance Sheet'!DL63) -> 0.023338679 | DM41: =1.26%+0.66% -> 0.0192 | DN41: =1.26%+0.66% -> 0.0192 | DO41: =1.26%+0.66% -> 0.0192 | DP41: =1.26%+0.66% -> 0.0192 | DQ41: =-DQ40/(DQ4+'Balance Sheet'!DQ63) -> 0.0192 | DR41: =1.26%+0.66% -> 0.0192 | DS41: =DR41 -> 0.0192 | DT41: =DS41 -> 0.0192 | DU41: =DT41 -> 0.0192 | DV41: =-DV40/(DV4+'Balance Sheet'!DV63) -> 0.0192 | DW41: 0.0192 | DX41: =DW41 -> 0.0192 | DY41: =DX41 -> 0.0192 | DZ41: =DY41 -> 0.0192 | EA41: =-EA40/(EA4+'Balance Sheet'!EA63) -> 0.0192 | EB41: 0.0192 | EC41: =EB41 -> 0.0192 | ED41: =EC41 -> 0.0192 | EE41: =ED41 -> 0.0192 | EF41: =-EF40/(EF4+'Balance Sheet'!EF63) -> 0.0192
A42: Deffered Taxes | F42: =SUM(B42:E42) -> 0 | K42: =SUM(G42:J42) -> 0 | P42: =SUM(L42:O42) -> 0 | U42: =SUM(Q42:T42) -> 0 | Z42: =SUM(V42:Y42) -> 0 | AE42: =SUM(AA42:AD42) -> 0 | AI42: =-3227.931-SUM(AF42:AH42) -> -3227.931 | AJ42: =SUM(AF42:AI42) -> -3227.931 | AN42: =-2244.486-SUM(AK42:AM42) -> -2244.486 | AO42: =SUM(AK42:AN42) -> -2244.486 | AS42: 0 | AT42: =SUM(AP42:AS42) -> 0 | AX42: 0 | AY42: =SUM(AU42:AX42) -> 0 | BC42: =-585-SUM(AZ42:BB42) -> -585 | BD42: =SUM(AZ42:BC42) -> -585 | BH42: =325-SUM(BE42:BG42) -> 325 | BI42: =SUM(BE42:BH42) -> 325 | BM42: =-87-SUM(BJ42:BL42) -> -87 | BN42: =SUM(BJ42:BM42) -> -87 | BR42: =-420-SUM(BO42:BQ42) -> -420 | BS42: =SUM(BO42:BR42) -> -420 | BW42: =-705-SUM(BT42:BV42) -> -705 | BX42: =SUM(BT42:BW42) -> -705 | BY42: -184 | BZ42: -481 | CA42: 782 | CB42: =-756-SUM(BY42:CA42) -> -873 | CC42: =SUM(BY42:CB42) -> -756 | CD42: -666 | CE42: 186 | CF42: -1002 | CG42: =-1564-SUM(CD42:CF42) -> -82 | CH42: =SUM(CD42:CG42) -> -1564 | CI42: -1492 | CJ42: -2193 | CK42: -843 | CL42: =-4439-SUM(CI42:CK42) -> 89 | CM42: =SUM(CI42:CL42) -> -4439 | CN42: -2130 | CO42: -2124 | CP42: -1635 | CQ42: =-5808-SUM(CN42:CP42) -> 81 | CR42: =SUM(CN42:CQ42) -> -5808 | CS42: -1627 | CT42: -2289 | CU42: -800 | CV42: =-4583-SUM(CS42:CU42) -> 133 | CW42: =SUM(CS42:CV42) -> -4583 | CX42: -2957 | CY42: -951 | CZ42: -1562 | DA42: =-3233-SUM(CX42:CZ42) -> 2237 | DB42: =SUM(CX42:DA42) -> -3233 | DC42: -8693 | DD42: -2894 | DE42: 260 | DF42: =-11191-SUM(DC42:DE42) -> 136 | DG42: =SUM(DC42:DF42) -> -11191 | DH42: -4033 | DI42: -3011 | DJ42: =-DJ43*DJ11-DJ40 -> -1144.8929 | DK42: =-DK43*DK11-DK40 -> -1786.8155 | DL42: =SUM(DH42:DK42) -> -9975.7084 | DM42: =-DM43*DM11-DM40 -> 1532.7411 | DN42: =-DN43*DN11-DN40 -> -1055.5729 | DO42: =-DO43*DO11-DO40 -> -755.44589 | DP42: =-DP43*DP11-DP40 -> -615.82407 | DQ42: =SUM(DM42:DP42) -> -894.10176 | DR42: =-DR43*DR11-DR40 -> -508.76533 | DS42: =-DS43*DS11-DS40 -> -424.37552 | DT42: =-DT43*DT11-DT40 -> -354.84319 | DU42: =-DU43*DU11-DU40 -> -295.6755 | DV42: =SUM(DR42:DU42) -> -1583.6595 | DW42: =-DW43*DW11-DW40 -> -244.17018 | DX42: =-DX43*DX11-DX40 -> -198.64066 | DY42: =-DY43*DY11-DY40 -> -157.98187 | DZ42: =-DZ43*DZ11-DZ40 -> -121.4278 | EA42: =SUM(DW42:DZ42) -> -722.2205 | EB42: =-EB43*EB11-EB40 -> -88.415349 | EC42: =-EC43*EC11-EC40 -> -58.507499 | ED42: =-ED43*ED11-ED40 -> -31.349287 | EE42: =-EE43*EE11-EE40 -> -6.6422569 | EF42: =SUM(EB42:EE42) -> -184.91439
A43: Total tax rate (% of revenues) | B43: =-(B40+B42)/B11 -> #DIV/0! | C43: =-(C40+C42)/C11 -> #DIV/0! | D43: =-(D40+D42)/D11 -> #DIV/0! | E43: =-(E40+E42)/E11 -> #DIV/0! | F43: =-(F40+F42)/F11 -> #DIV/0! | G43: =-(G40+G42)/G11 -> #DIV/0! | H43: =-(H40+H42)/H11 -> #DIV/0! | I43: =-(I40+I42)/I11 -> #DIV/0! | ... DI43: =-(DI40+DI42)/DI11 -> 0.026685295 | DJ43: =1.26%+0.66% -> 0.0192 | DK43: =1.26%+0.66% -> 0.0192 | DL43: =-(DL40+DL42)/DL11 -> 0.022575384 | DM43: =1.26%+0.66% -> 0.0192 | DN43: =1.26%+0.66% -> 0.0192 | DO43: =1.26%+0.66% -> 0.0192 | DP43: =1.26%+0.66% -> 0.0192 | DQ43: =-(DQ40+DQ42)/DQ11 -> 0.0192 | DR43: =1.26%+0.66% -> 0.0192 | DS43: =DR43 -> 0.0192 | DT43: =DS43 -> 0.0192 | DU43: =DT43 -> 0.0192 | DV43: =-(DV40+DV42)/DV11 -> 0.0192 | DW43: 0.0192 | DX43: =DW43 -> 0.0192 | DY43: =DX43 -> 0.0192 | DZ43: =DY43 -> 0.0192 | EA43: =-(EA40+EA42)/EA11 -> 0.0192 | EB43: 0.0192 | EC43: =EB43 -> 0.0192 | ED43: =EC43 -> 0.0192 | EE43: =ED43 -> 0.0192 | EF43: =-(EF40+EF42)/EF11 -> 0.0192
A44: Employee compensation | F44: =SUM(B44:E44) -> 0 | K44: =SUM(G44:J44) -> 0 | P44: =SUM(L44:O44) -> 0 | U44: =SUM(Q44:T44) -> 0 | Z44: =SUM(V44:Y44) -> 0 | AE44: =SUM(AA44:AD44) -> 0 | AI44: 0 | AJ44: =SUM(AF44:AI44) -> 0 | AN44: 0 | AO44: =SUM(AK44:AN44) -> 0 | AS44: 0 | AT44: =SUM(AP44:AS44) -> 0 | AX44: 0 | AY44: =SUM(AU44:AX44) -> 0 | BC44: 0 | BD44: =SUM(AZ44:BC44) -> 0 | BH44: 0 | BI44: =SUM(BE44:BH44) -> 0 | BM44: 0 | BN44: =SUM(BJ44:BM44) -> 0 | BR44: 0 | BS44: =SUM(BO44:BR44) -> 0 | BT44: 0 | BU44: 0 | BV44: 0 | BW44: 0 | BX44: =SUM(BT44:BW44) -> 0 | BY44: 0 | BZ44: 0 | CA44: 0 | CB44: 0 | CC44: =SUM(BY44:CB44) -> 0 | CD44: 0 | CE44: 0 | CF44: 0 | CG44: 0 | CH44: =SUM(CD44:CG44) -> 0 | CI44: 0 | CJ44: 0 | CK44: 0 | CL44: 0 | CM44: =SUM(CI44:CL44) -> 0 | CN44: 0 | CO44: 0 | CP44: 0 | CQ44: 0 | CR44: =SUM(CN44:CQ44) -> 0 | CS44: 0 | CT44: 0 | CU44: 0 | CV44: 0 | CW44: =SUM(CS44:CV44) -> 0 | CX44: 0 | CY44: 0 | CZ44: 0 | DA44: 0 | DB44: =SUM(CX44:DA44) -> 0 | DC44: 0 | DD44: 0 | DE44: 0 | DF44: 0 | DG44: =SUM(DC44:DF44) -> 0 | DH44: 0 | DI44: 0 | DJ44: =DI44 -> 0 | DK44: =DJ44 -> 0 | DL44: =SUM(DH44:DK44) -> 0 | DM44: =DK44 -> 0 | DN44: =DM44 -> 0 | DO44: =DN44 -> 0 | DP44: =DO44 -> 0 | DQ44: =SUM(DM44:DP44) -> 0 | DR44: =DP44 -> 0 | DS44: =DR44 -> 0 | DT44: =DS44 -> 0 | DU44: =DT44 -> 0 | DV44: =SUM(DR44:DU44) -> 0 | DW44: =DU44 -> 0 | DX44: =DW44 -> 0 | DY44: =DX44 -> 0 | DZ44: =DY44 -> 0 | EA44: =SUM(DW44:DZ44) -> 0 | EB44: =DZ44 -> 0 | EC44: =EB44 -> 0 | ED44: =EC44 -> 0 | EE44: =ED44 -> 0 | EF44: =SUM(EB44:EE44) -> 0
A45: Majority Earnings | B45: =+B39+B40+B42+B44 -> 0 | C45: =+C39+C40+C42+C44 -> 0 | D45: =+D39+D40+D42+D44 -> 0 | E45: =+E39+E40+E42+E44 -> 0 | F45: =SUM(B45:E45) -> 0 | G45: =+G39+G40+G42+G44 -> 0 | H45: =+H39+H40+H42+H44 -> 0 | I45: =+I39+I40+I42+I44 -> 0 | J45: =+J39+J40+J42+J44 -> 0 | K45: =SUM(G45:J45) -> 0 | L45: =+L39+L40+L42+L44 -> 0 | M45: =+M39+M40+M42+M44 -> 0 | N45: =+N39+N40+N42+N44 -> 0 | O45: =+O39+O40+O42+O44 -> 0 | P45: =SUM(L45:O45) -> 0 | Q45: =+Q39+Q40+Q42+Q44 -> 0 | R45: =+R39+R40+R42+R44 -> 0 | S45: =+S39+S40+S42+S44 -> 0 | T45: =+T39+T40+T42+T44 -> 0 | U45: =SUM(Q45:T45) -> 0 | V45: =+V39+V40+V42+V44 -> 0 | W45: =+W39+W40+W42+W44 -> 0 | X45: =+X39+X40+X42+X44 -> 0 | Y45: =+Y39+Y40+Y42+Y44 -> 0 | Z45: =SUM(V45:Y45) -> 0 | AA45: =+AA39+AA40+AA42+AA44 -> 0 | AB45: =+AB39+AB40+AB42+AB44 -> 0 | AC45: =+AC39+AC40+AC42+AC44 -> 0 | AD45: =+AD39+AD40+AD42+AD44 -> 0 | AE45: =SUM(AA45:AD45) -> 0 | AF45: =+AF39+AF40+AF42+AF44 -> 0 | AG45: =+AG39+AG40+AG42+AG44 -> 0 | AH45: =+AH39+AH40+AH42+AH44 -> 0 | AI45: =+AI39+AI40+AI42+AI44 -> 52097.767 | AJ45: =SUM(AF45:AI45) -> 52097.767 | AK45: =+AK39+AK40+AK42+AK44 -> 0 | AL45: =+AL39+AL40+AL42+AL44 -> 0 | AM45: =+AM39+AM40+AM42+AM44 -> 0 | AN45: =+AN39+AN40+AN42+AN44 -> 90002.873 | AO45: =SUM(AK45:AN45) -> 90002.873 | AP45: =+AP39+AP40+AP42+AP44 -> 0 | AQ45: =+AQ39+AQ40+AQ42+AQ44 -> 0 | AR45: =+AR39+AR40+AR42+AR44 -> 0 | AS45: =+AS39+AS40+AS42+AS44 -> 123334.7 | AT45: =SUM(AP45:AS45) -> 123334.7 | AU45: =+AU39+AU40+AU42+AU44 -> 0 | AV45: =+AV39+AV40+AV42+AV44 -> 0 | AW45: =+AW39+AW40+AW42+AW44 -> 0 | AX45: =+AX39+AX40+AX42+AX44 -> 171735.95 | AY45: =SUM(AU45:AX45) -> 171735.95 | AZ45: =+AZ39+AZ40+AZ42+AZ44 -> 0 | BA45: =+BA39+BA40+BA42+BA44 -> 0 | BB45: =+BB39+BB40+BB42+BB44 -> 0 | BC45: =+BC39+BC40+BC42+BC44 -> 172789 | BD45: =SUM(AZ45:BC45) -> 172789 | BE45: =+BE39+BE40+BE42+BE44 -> 0 | BF45: =+BF39+BF40+BF42+BF44 -> 0 | BG45: =+BG39+BG40+BG42+BG44 -> 0 | BH45: =+BH39+BH40+BH42+BH44 -> 161329 | BI45: =SUM(BE45:BH45) -> 161329 | BJ45: =+BJ39+BJ40+BJ42+BJ44 -> 0 | BK45: =+BK39+BK40+BK42+BK44 -> 0 | BL45: =+BL39+BL40+BL42+BL44 -> 0 | BM45: =+BM39+BM40+BM42+BM44 -> 111796 | BN45: =SUM(BJ45:BM45) -> 111796 | BO45: =+BO39+BO40+BO42+BO44 -> 0 | BP45: =+BP39+BP40+BP42+BP44 -> 0 | BQ45: =+BQ39+BQ40+BQ42+BQ44 -> 0 | BR45: =+BR39+BR40+BR42+BR44 -> 128777 | BS45: =SUM(BO45:BR45) -> 128777 | BT45: =+BT39+BT40+BT42+BT44 -> 0 | BU45: =+BU39+BU40+BU42+BU44 -> 0 | BV45: =+BV39+BV40+BV42+BV44 -> 0 | BW45: =+BW39+BW40+BW42+BW44 -> 176011 | BX45: =SUM(BT45:BW45) -> 176011 | BY45: =+BY39+BY40+BY42+BY44 -> 23506 | BZ45: =+BZ39+BZ40+BZ42+BZ44 -> 73734 | CA45: =+CA39+CA40+CA42+CA44 -> 40304 | CB45: =+CB39+CB40+CB42+CB44 -> 66512 | CC45: =SUM(BY45:CB45) -> 204056 | CD45: =+CD39+CD40+CD42+CD44 -> 15418 | CE45: =+CE39+CE40+CE42+CE44 -> 41012 | CF45: =+CF39+CF40+CF42+CF44 -> 59215 | CG45: =+CG39+CG40+CG42+CG44 -> 74353 | CH45: =SUM(CD45:CG45) -> 189998 | CI45: =+CI39+CI40+CI42+CI44 -> 52068 | CJ45: =+CJ39+CJ40+CJ42+CJ44 -> 76951 | CK45: =+CK39+CK40+CK42+CK44 -> 74647 | CL45: =+CL39+CL40+CL42+CL44 -> 111643 | CM45: =SUM(CI45:CL45) -> 315309 | CN45: =+CN39+CN40+CN42+CN44 -> 63351 | CO45: =+CO39+CO40+CO42+CO44 -> 92939 | CP45: =+CP39+CP40+CP42+CP44 -> 94871 | CQ45: =+CQ39+CQ40+CQ42+CQ44 -> 97279 | CR45: =SUM(CN45:CQ45) -> 348440 | CS45: =+CS39+CS40+CS42+CS44 -> 94056 | CT45: =+CT39+CT40+CT42+CT44 -> 124070 | CU45: =+CU39+CU40+CU42+CU44 -> 112891 | CV45: =+CV39+CV40+CV42+CV44 -> 164594 | CW45: =SUM(CS45:CV45) -> 495611 | CX45: =+CX39+CX40+CX42+CX44 -> 154070 | CY45: =+CY39+CY40+CY42+CY44 -> 175282 | CZ45: =+CZ39+CZ40+CZ42+CZ44 -> 180588 | DA45: =+DA39+DA40+DA42+DA44 -> 188872 | DB45: =SUM(CX45:DA45) -> 698812 | DC45: =+DC39+DC40+DC42+DC44 -> 233664 | DD45: =+DD39+DD40+DD42+DD44 -> 267157 | DE45: =+DE39+DE40+DE42+DE44 -> 283210 | DF45: =+DF39+DF40+DF42+DF44 -> 297189 | DG45: =SUM(DC45:DF45) -> 1081220 | DH45: =+DH39+DH40+DH42+DH44 -> 351156 | DI45: =+DI39+DI40+DI42+DI44 -> 311191 | DJ45: =+DJ39+DJ40+DJ42+DJ44 -> 351748.26 | DK45: =+DK39+DK40+DK42+DK44 -> 409750.3 | DL45: =SUM(DH45:DK45) -> 1423845.6 | DM45: =+DM39+DM40+DM42+DM44 -> 408700.69 | DN45: =+DN39+DN40+DN42+DN44 -> 421800.19 | DO45: =+DO39+DO40+DO42+DO44 -> 426774.69 | DP45: =+DP39+DP40+DP42+DP44 -> 440052.93 | DQ45: =SUM(DM45:DP45) -> 1697328.5 | DR45: =+DR39+DR40+DR42+DR44 -> 456513.11 | DS45: =+DS39+DS40+DS42+DS44 -> 454491.34 | DT45: =+DT39+DT40+DT42+DT44 -> 469936.25 | DU45: =+DU39+DU40+DU42+DU44 -> 489080.89 | DV45: =SUM(DR45:DU45) -> 1870021.6 | DW45: =+DW39+DW40+DW42+DW44 -> 485653.8 | DX45: =+DX39+DX40+DX42+DX44 -> 481829.54 | DY45: =+DY39+DY40+DY42+DY44 -> 500428.32 | DZ45: =+DZ39+DZ40+DZ42+DZ44 -> 519407.25 | EA45: =SUM(DW45:DZ45) -> 1987318.9 | EB45: =+EB39+EB40+EB42+EB44 -> 514825.59 | EC45: =+EC39+EC40+EC42+EC44 -> 509922.25 | ED45: =+ED39+ED40+ED42+ED44 -> 528622.45 | EE45: =+EE39+EE40+EE42+EE44 -> 547659.05 | EF45: =SUM(EB45:EE45) -> 2101029.3
A46: Minority Interest | F46: =SUM(B46:E46) -> 0 | K46: =SUM(G46:J46) -> 0 | P46: =SUM(L46:O46) -> 0 | U46: =SUM(Q46:T46) -> 0 | Z46: =SUM(V46:Y46) -> 0 | AE46: =SUM(AA46:AD46) -> 0 | AI46: 0 | AJ46: =SUM(AF46:AI46) -> 0 | AN46: 0 | AO46: =SUM(AK46:AN46) -> 0 | AS46: =-43253.514-SUM(AP46:AR46) -> -43253.514 | AT46: =SUM(AP46:AS46) -> -43253.514 | AX46: =-66655.695-SUM(AU46:AW46) -> -66655.695 | AY46: =SUM(AU46:AX46) -> -66655.695 | BC46: =-38258-SUM(AZ46:BB46) -> -38258 | BD46: =SUM(AZ46:BC46) -> -38258 | BH46: =-30221-SUM(BE46:BG46) -> -30221 | BI46: =SUM(BE46:BH46) -> -30221 | BM46: =-20810-SUM(BJ46:BL46) -> -20810 | BN46: =SUM(BJ46:BM46) -> -20810 | BR46: -15943 | BS46: =SUM(BO46:BR46) -> -15943 | BW46: -45012 | BX46: =SUM(BT46:BW46) -> -45012 | BY46: -5130 | BZ46: -12661 | CA46: -9996 | CB46: =-43928-SUM(BY46:CA46) -> -16141 | CC46: =SUM(BY46:CB46) -> -43928 | CD46: -8918 | CE46: -4023 | CF46: -9861 | CG46: =-29186-SUM(CD46:CF46) -> -6384 | CH46: =SUM(CD46:CG46) -> -29186 | CI46: -2075 | CJ46: 1652 | CK46: -7242 | CL46: =-15560-SUM(CI46:CK46) -> -7895 | CM46: =SUM(CI46:CL46) -> -15560 | CN46: -1448 | CO46: -6614 | CP46: -4999 | CQ46: =-18555-SUM(CN46:CP46) -> -5494 | CR46: =SUM(CN46:CQ46) -> -18555 | CS46: -2207 | CT46: -2697 | CU46: -4671 | CV46: =-13846-SUM(CS46:CU46) -> -4271 | CW46: =SUM(CS46:CV46) -> -13846 | CX46: -12829 | CY46: -3035 | CZ46: -10017 | DA46: =-48969-SUM(CX46:CZ46) -> -23088 | DB46: =SUM(CX46:DA46) -> -48969 | DC46: -20189 | DD46: -30426 | DE46: -27957 | DF46: =-105684-SUM(DC46:DE46) -> -27112 | DG46: =SUM(DC46:DF46) -> -105684 | DH46: -48319 | DI46: -40740 | DJ46: =-45%*'Balance Sheet'!DI42/4 -> -44304.412 | DK46: =-45%*'Balance Sheet'!DJ42/4 -> -46796.536 | DL46: =SUM(DH46:DK46) -> -180159.95 | DM46: =-35%*'Balance Sheet'!DL42/4 -> -38444.654 | DN46: =-35%*'Balance Sheet'!DM42/4 -> -40126.608 | DO46: =-35%*'Balance Sheet'!DN42/4 -> -41882.147 | DP46: =-35%*'Balance Sheet'!DO42/4 -> -43714.491 | DQ46: =SUM(DM46:DP46) -> -164167.9 | DR46: =-30%*'Balance Sheet'!DQ42/4 -> -39108.857 | DS46: =-30%*'Balance Sheet'!DR42/4 -> -40575.439 | DT46: =-30%*'Balance Sheet'!DS42/4 -> -42097.018 | DU46: =-30%*'Balance Sheet'!DT42/4 -> -43675.656 | DV46: =SUM(DR46:DU46) -> -165456.97 | DW46: =-30%*'Balance Sheet'!DV42/4 -> -45313.493 | DX46: =-30%*'Balance Sheet'!DW42/4 -> -47012.749 | DY46: =-30%*'Balance Sheet'!DX42/4 -> -48775.727 | DZ46: =-30%*'Balance Sheet'!DY42/4 -> -50604.817 | EA46: =SUM(DW46:DZ46) -> -191706.79 | EB46: =-30%*'Balance Sheet'!EA42/4 -> -52502.498 | EC46: =-30%*'Balance Sheet'!EB42/4 -> -54471.341 | ED46: =-30%*'Balance Sheet'!EC42/4 -> -56514.017 | EE46: =-30%*'Balance Sheet'!ED42/4 -> -58633.292 | EF46: =SUM(EB46:EE46) -> -222121.15
A47: As % of majority earnings | B47: =-B46/B45 -> #DIV/0! | C47: =-C46/C45 -> #DIV/0! | D47: =-D46/D45 -> #DIV/0! | E47: =-E46/E45 -> #DIV/0! | F47: =-F46/F45 -> #DIV/0! | G47: =-G46/G45 -> #DIV/0! | H47: =-H46/H45 -> #DIV/0! | I47: =-I46/I45 -> #DIV/0! | ... EF47: =-EF46/EF45 -> 0.10572016
A48: Net Earnings | B48: =+B45+B46 -> 0 | C48: =+C45+C46 -> 0 | D48: =+D45+D46 -> 0 | E48: =+E45+E46 -> 0 | F48: =SUM(B48:E48) -> 0 | G48: =+G45+G46 -> 0 | H48: =+H45+H46 -> 0 | I48: =+I45+I46 -> 0 | J48: =+J45+J46 -> 0 | K48: =SUM(G48:J48) -> 0 | L48: =+L45+L46 -> 0 | M48: =+M45+M46 -> 0 | N48: =+N45+N46 -> 0 | O48: =+O45+O46 -> 0 | P48: =SUM(L48:O48) -> 0 | Q48: =+Q45+Q46 -> 0 | R48: =+R45+R46 -> 0 | S48: =+S45+S46 -> 0 | T48: =+T45+T46 -> 0 | U48: =SUM(Q48:T48) -> 0 | V48: =+V45+V46 -> 0 | W48: =+W45+W46 -> 0 | X48: =+X45+X46 -> 0 | Y48: =+Y45+Y46 -> 0 | Z48: =SUM(V48:Y48) -> 0 | AA48: =+AA45+AA46 -> 0 | AB48: =+AB45+AB46 -> 0 | AC48: =+AC45+AC46 -> 0 | AD48: =+AD45+AD46 -> 0 | AE48: =SUM(AA48:AD48) -> 0 | AF48: =+AF45+AF46 -> 0 | AG48: =+AG45+AG46 -> 0 | AH48: =+AH45+AH46 -> 0 | AI48: =+AI45+AI46 -> 52097.767 | AJ48: =SUM(AF48:AI48) -> 52097.767 | AK48: =+AK45+AK46 -> 0 | AL48: =+AL45+AL46 -> 0 | AM48: =+AM45+AM46 -> 0 | AN48: =+AN45+AN46 -> 90002.873 | AO48: =SUM(AK48:AN48) -> 90002.873 | AP48: =+AP45+AP46 -> 0 | AQ48: =+AQ45+AQ46 -> 0 | AR48: =+AR45+AR46 -> 0 | AS48: =+AS45+AS46 -> 80081.187 | AT48: =SUM(AP48:AS48) -> 80081.187 | AU48: =+AU45+AU46 -> 0 | AV48: =+AV45+AV46 -> 0 | AW48: =+AW45+AW46 -> 0 | AX48: =+AX45+AX46 -> 105080.25 | AY48: =SUM(AU48:AX48) -> 105080.25 | AZ48: =+AZ45+AZ46 -> 0 | BA48: =+BA45+BA46 -> 0 | BB48: =+BB45+BB46 -> 0 | BC48: =+BC45+BC46 -> 134531 | BD48: =SUM(AZ48:BC48) -> 134531 | BE48: =+BE45+BE46 -> 0 | BF48: =+BF45+BF46 -> 0 | BG48: =+BG45+BG46 -> 0 | BH48: =+BH45+BH46 -> 131108 | BI48: =SUM(BE48:BH48) -> 131108 | BJ48: =+BJ45+BJ46 -> 0 | BK48: =+BK45+BK46 -> 0 | BL48: =+BL45+BL46 -> 0 | BM48: =+BM45+BM46 -> 90986 | BN48: =SUM(BJ48:BM48) -> 90986 | BO48: =+BO45+BO46 -> 0 | BP48: =+BP45+BP46 -> 0 | BQ48: =+BQ45+BQ46 -> 0 | BR48: =+BR45+BR46 -> 112834 | BS48: =SUM(BO48:BR48) -> 112834 | BT48: =+BT45+BT46 -> 0 | BU48: =+BU45+BU46 -> 0 | BV48: =+BV45+BV46 -> 0 | BW48: =+BW45+BW46 -> 130999 | BX48: =SUM(BT48:BW48) -> 130999 | BY48: =+BY45+BY46 -> 18376 | BZ48: =+BZ45+BZ46 -> 61073 | CA48: =+CA45+CA46 -> 30308 | CB48: =+CB45+CB46 -> 50371 | CC48: =SUM(BY48:CB48) -> 160128 | CD48: =+CD45+CD46 -> 6500 | CE48: =+CE45+CE46 -> 36989 | CF48: =+CF45+CF46 -> 49354 | CG48: =+CG45+CG46 -> 67969 | CH48: =SUM(CD48:CG48) -> 160812 | CI48: =+CI45+CI46 -> 49993 | CJ48: =+CJ45+CJ46 -> 78603 | CK48: =+CK45+CK46 -> 67405 | CL48: =+CL45+CL46 -> 103748 | CM48: =SUM(CI48:CL48) -> 299749 | CN48: =+CN45+CN46 -> 61903 | CO48: =+CO45+CO46 -> 86325 | CP48: =+CP45+CP46 -> 89872 | CQ48: =+CQ45+CQ46 -> 91785 | CR48: =SUM(CN48:CQ48) -> 329885 | CS48: =+CS45+CS46 -> 91849 | CT48: =+CT45+CT46 -> 121373 | CU48: =+CU45+CU46 -> 108220 | CV48: =+CV45+CV46 -> 160323 | CW48: =SUM(CS48:CV48) -> 481765 | CX48: =+CX45+CX46 -> 141241 | CY48: =+CY45+CY46 -> 172247 | CZ48: =+CZ45+CZ46 -> 170571 | DA48: =+DA45+DA46 -> 165784 | DB48: =SUM(CX48:DA48) -> 649843 | DC48: =+DC45+DC46 -> 213475 | DD48: =+DD45+DD46 -> 236731 | DE48: =+DE45+DE46 -> 255253 | DF48: =+DF45+DF46 -> 270077 | DG48: =SUM(DC48:DF48) -> 975536 | DH48: =+DH45+DH46 -> 302837 | DI48: =+DI45+DI46 -> 270451 | DJ48: =+DJ45+DJ46 -> 307443.85 | DK48: =+DK45+DK46 -> 362953.77 | DL48: =SUM(DH48:DK48) -> 1243685.6 | DM48: =+DM45+DM46 -> 370256.03 | DN48: =+DN45+DN46 -> 381673.58 | DO48: =+DO45+DO46 -> 384892.55 | DP48: =+DP45+DP46 -> 396338.44 | DQ48: =SUM(DM48:DP48) -> 1533160.6 | DR48: =+DR45+DR46 -> 417404.26 | DS48: =+DS45+DS46 -> 413915.9 | DT48: =+DT45+DT46 -> 427839.24 | DU48: =+DU45+DU46 -> 445405.23 | DV48: =SUM(DR48:DU48) -> 1704564.6 | DW48: =+DW45+DW46 -> 440340.31 | DX48: =+DX45+DX46 -> 434816.79 | DY48: =+DY45+DY46 -> 451652.59 | DZ48: =+DZ45+DZ46 -> 468802.43 | EA48: =SUM(DW48:DZ48) -> 1795612.1 | EB48: =+EB45+EB46 -> 462323.09 | EC48: =+EC45+EC46 -> 455450.91 | ED48: =+ED45+ED46 -> 472108.44 | EE48: =+EE45+EE46 -> 489025.76 | EF48: =SUM(EB48:EE48) -> 1878908.2
DB49: =DB48/CW48-1 -> 0.34887964 | DG49: =DG48/DB48-1 -> 0.50118721 | DL49: =DL48/DG48-1 -> 0.27487414 | DQ49: =DQ48/DL48-1 -> 0.23275576 | DV49: =DV48/DQ48-1 -> 0.11179782 | EA49: =EA48/DV48-1 -> 0.053413935 | EF49: =EF48/EA48-1 -> 0.046388675
A50: Dividends Declared | F50: =SUM(B50:E50) -> 0 | K50: =SUM(G50:J50) -> 0 | P50: =SUM(L50:O50) -> 0 | U50: =SUM(Q50:T50) -> 0 | Z50: =SUM(V50:Y50) -> 0 | AE50: =SUM(AA50:AD50) -> 0 | AF50: 0 | AG50: 0 | AH50: 0 | AI50: 0 | AJ50: =SUM(AF50:AI50) -> 0 | AK50: 0 | AL50: 0 | AM50: 0 | AN50: 0 | AO50: =SUM(AK50:AN50) -> 0 | AP50: 0 | AQ50: 0 | AR50: 0 | AS50: 0 | AT50: =SUM(AP50:AS50) -> 0 | AU50: 0 | AV50: 0 | AW50: 0 | AX50: 0 | AY50: =SUM(AU50:AX50) -> 0 | AZ50: 0 | BA50: 0 | BB50: 0 | BC50: 0 | BD50: =SUM(AZ50:BC50) -> 0 | BE50: 0 | BF50: 0 | BG50: 0 | BH50: 80000 | BI50: =SUM(BE50:BH50) -> 80000 | BJ50: 0 | BK50: 0 | BL50: 0 | BM50: 69000 | BN50: =SUM(BJ50:BM50) -> 69000 | BO50: 0 | BP50: 0 | BQ50: 0 | BR50: 69000 | BS50: =SUM(BO50:BR50) -> 69000 | BT50: 0 | BU50: 0 | BV50: 0 | BW50: 141000 | BX50: =SUM(BT50:BW50) -> 141000 | BY50: 0 | BZ50: 0 | CA50: 0 | CB50: 134000 | CC50: =SUM(BY50:CB50) -> 134000 | CD50: 0 | CE50: 0 | CF50: 0 | CG50: 38193 | CH50: =SUM(CD50:CG50) -> 38193 | CI50: 0 | CJ50: 115000 | CK50: 0 | CL50: 50000 | CM50: =SUM(CI50:CL50) -> 165000 | CN50: 0 | CO50: 150000 | CP50: 0 | CQ50: 0 | CR50: =SUM(CN50:CQ50) -> 150000 | CS50: 60000 | CT50: 18300 | CU50: 150000 | CV50: 100000 | CW50: =SUM(CS50:CV50) -> 328300 | CX50: 0 | CY50: 118500 | CZ50: 265000 | DA50: 100000 | DB50: =SUM(CX50:DA50) -> 483500 | DC50: 175000 | DD50: 154337.62 | DE50: 0 | DF50: =200000+250000+573000 -> 1023000 | DG50: =SUM(DC50:DF50) -> 1352337.6 | DH50: 140000 | DI50: 160000 | DJ50: 190000 | DK50: =(DG48*0.8-DI50-DH50)/2.2 -> 218376.73 | DL50: =SUM(DH50:DK50) -> 708376.73 | DM50: =+DL48*80%/4 -> 248737.12 | DN50: =+DL48*80%/4 -> 248737.12 | DO50: =+DL48*80%/4 -> 248737.12 | DP50: =+DL48*80%/4 -> 248737.12 | DQ50: =SUM(DM50:DP50) -> 994948.49 | DR50: =DQ48*0.8 -> 1226528.5 | DS50: 0 | DT50: 0 | DU50: 0 | DV50: =SUM(DR50:DU50) -> 1226528.5 | DW50: =DV48*0.9 -> 1534108.2 | DX50: 0 | DY50: 0 | DZ50: 0 | EA50: =SUM(DW50:DZ50) -> 1534108.2 | EB50: =EA48*0.9 -> 1616050.9 | EC50: 0 | ED50: 0 | EE50: 0 | EF50: =SUM(EB50:EE50) -> 1616050.9
A51: Payout (%) | B51: =-SUM(B50:B50)/SUM(B$11:B$11) -> #DIV/0! | C51: =-SUM(B50:C50)/SUM(B$11:C$11) -> #DIV/0! | D51: =-SUM(B50:D50)/SUM(B$11:D$11) -> #DIV/0! | E51: =-SUM(B50:E50)/SUM(B$11:E$11) -> #DIV/0! | F51: =+F50/F48 -> #DIV/0! | G51: =-SUM(G50:G50)/SUM(G$11:G$11) -> #DIV/0! | H51: =-SUM(G50:H50)/SUM(G$11:H$11) -> #DIV/0! | I51: =-SUM(G50:I50)/SUM(G$11:I$11) -> #DIV/0! | J51: =-SUM(G50:J50)/SUM(G$11:J$11) -> #DIV/0! | K51: =+K50/K48 -> #DIV/0! | L51: =-SUM(L50:L50)/SUM(L$11:L$11) -> #DIV/0! | M51: =-SUM(L50:M50)/SUM(L$11:M$11) -> #DIV/0! | N51: =-SUM(L50:N50)/SUM(L$11:N$11) -> #DIV/0! | O51: =-SUM(L50:O50)/SUM(L$11:O$11) -> #DIV/0! | P51: =+P50/P48 -> #DIV/0! | Q51: =-SUM(Q50:Q50)/SUM(Q$11:Q$11) -> #DIV/0! | R51: =-SUM(Q50:R50)/SUM(Q$11:R$11) -> #DIV/0! | S51: =-SUM(Q50:S50)/SUM(Q$11:S$11) -> #DIV/0! | T51: =-SUM(Q50:T50)/SUM(Q$11:T$11) -> #DIV/0! | U51: =+U50/U48 -> #DIV/0! | V51: =-SUM(V50:V50)/SUM(V$11:V$11) -> #DIV/0! | W51: =-SUM(V50:W50)/SUM(V$11:W$11) -> #DIV/0! | X51: =-SUM(V50:X50)/SUM(V$11:X$11) -> #DIV/0! | Y51: =-SUM(V50:Y50)/SUM(V$11:Y$11) -> #DIV/0! | Z51: =+Z50/Z48 -> #DIV/0! | AA51: =-SUM(AA50:AA50)/SUM(AA$11:AA$11) -> #DIV/0! | AB51: =-SUM(AA50:AB50)/SUM(AA$11:AB$11) -> #DIV/0! | AC51: =-SUM(AA50:AC50)/SUM(AA$11:AC$11) -> #DIV/0! | AD51: =-SUM(AA50:AD50)/SUM(AA$11:AD$11) -> #DIV/0! | AE51: =+AE50/AE48 -> #DIV/0! | AF51: =AF50/AF48 -> #DIV/0! | AG51: =AG50/AG48 -> #DIV/0! | AH51: =AH50/AH48 -> #DIV/0! | AI51: =AI50/AI48 -> 0 | AJ51: =+AJ50/AJ48 -> 0 | AK51: =AK50/AK48 -> #DIV/0! | AL51: =AL50/AL48 -> #DIV/0! | AM51: =AM50/AM48 -> #DIV/0! | AN51: =AN50/AN48 -> 0 | AO51: =+AO50/AO48 -> 0 | AP51: =AP50/AP48 -> #DIV/0! | AQ51: =AQ50/AQ48 -> #DIV/0! | AR51: =AR50/AR48 -> #DIV/0! | AS51: =AS50/AS48 -> 0 | AT51: =+AT50/AT48 -> 0 | AU51: =AU50/AU48 -> #DIV/0! | AV51: =AV50/AV48 -> #DIV/0! | AW51: =AW50/AW48 -> #DIV/0! | AX51: =AX50/AX48 -> 0 | AY51: =+AY50/AY48 -> 0 | AZ51: =AZ50/AZ48 -> #DIV/0! | BA51: =BA50/BA48 -> #DIV/0! | BB51: =BB50/BB48 -> #DIV/0! | BC51: =BC50/BC48 -> 0 | BD51: =+BD50/BD48 -> 0 | BE51: =BE50/BE48 -> #DIV/0! | BF51: =BF50/BF48 -> #DIV/0! | BG51: =BG50/BG48 -> #DIV/0! | BH51: =BH50/BH48 -> 0.61018397 | BI51: =+BI50/BI48 -> 0.61018397 | BJ51: =BJ50/BJ48 -> #DIV/0! | BK51: =BK50/BK48 -> #DIV/0! | BL51: =BL50/BL48 -> #DIV/0! | BM51: =BM50/BM48 -> 0.75835843 | BN51: =+BN50/BN48 -> 0.75835843 | BO51: =BO50/BO48 -> #DIV/0! | BP51: =BP50/BP48 -> #DIV/0! | BQ51: =BQ50/BQ48 -> #DIV/0! | BR51: =BR50/BR48 -> 0.6115178 | BS51: =+BS50/BS48 -> 0.6115178 | BT51: =BT50/BT48 -> #DIV/0! | BU51: =BU50/BU48 -> #DIV/0! | BV51: =BV50/BV48 -> #DIV/0! | BW51: =BW50/BW48 -> 1.0763441 | BX51: =+BX50/BX48 -> 1.0763441 | BY51: =BY50/BY48 -> 0 | BZ51: =BZ50/BZ48 -> 0 | CA51: =CA50/CA48 -> 0 | CB51: =CB50/CB48 -> 2.6602609 | CC51: =+CC50/CC48 -> 0.83683054 | CD51: =CD50/CD48 -> 0 | CE51: =CE50/CE48 -> 0 | CF51: =CF50/CF48 -> 0 | CG51: =CG50/CG48 -> 0.56191793 | CH51: =+CH50/CH48 -> 0.23750093 | CI51: =CI50/CI48 -> 0 | CJ51: =CJ50/CJ48 -> 1.4630485 | CK51: =CK50/CK48 -> 0 | CL51: =CL50/CM48 -> 0.16680623 | CM51: =+CM50/CM48 -> 0.55046055 | CN51: =CN50/CN48 -> 0 | CO51: =CO50/CO48 -> 1.7376195 | CP51: =CP50/CP48 -> 0 | CQ51: =CQ50/CR48 -> 0 | CR51: =+CR50/CR48 -> 0.45470391 | CS51: =CS50/CS48 -> 0.65324609 | CT51: =CT50/CT48 -> 0.15077488 | CU51: =CU50/CU48 -> 1.3860654 | CV51: =CV50/CW48 -> 0.20757008 | CW51: =+CW50/CW48 -> 0.68145258 | CX51: =CX50/CX48 -> 0 | CY51: =CY50/CY48 -> 0.68796554 | CZ51: =CZ50/CZ48 -> 1.5536052 | DA51: =DA50/DB48 -> 0.15388332 | DB51: =+DB50/DB48 -> 0.74402586 | DC51: =DC50/DC48 -> 0.81976812 | DD51: =DD50/DD48 -> 0.65195355 | DE51: =DE50/DE48 -> 0 | DF51: =DF50/DG48 -> 1.0486543 | DG51: =+DG50/DG48 -> 1.3862509 | DH51: =DH49/DH48 -> 0 | DI51: =DI50/DI48 -> 0.59160439 | DJ51: =DJ50/DJ48 -> 0.61799902 | DK51: =DK50/DL48 -> 0.17558837 | DL51: =+DL50/DL48 -> 0.56957861 | DM51: =DM50/DM48 -> 0.67179762 | DN51: =DN50/DN48 -> 0.65170118 | DO51: =DO50/DO48 -> 0.64625082 | DP51: =DP50/DQ48 -> 0.16223814 | DQ51: =+DQ50/DQ48 -> 0.64895255 | DR51: =DR50/DR48 -> 2.9384666 | DS51: =DS50/DS48 -> 0 | DT51: =DT50/DT48 -> 0 | DU51: =DU50/DV48 -> 0 | DV51: =+DV50/DV48 -> 0.71955529 | DW51: =DW50/DW48 -> 3.4839149 | DX51: =DX50/DX48 -> 0 | DY51: =DY50/DY48 -> 0 | DZ51: =DZ50/EA48 -> 0 | EA51: =+EA50/EA48 -> 0.854365 | EB51: =EB50/EB48 -> 3.4955012 | EC51: =EC50/EC48 -> 0 | ED51: =ED50/ED48 -> 0 | EE51: =EE50/EF48 -> 0 | EF51: =+EF50/EF48 -> 0.86010105
A52: Summary | B52: =Macro!B$9 -> 1Q04 | C52: =Macro!C$9 -> 2Q04 | D52: =Macro!D$9 -> 3Q04 | E52: =Macro!E$9 -> 4Q04 | F52: =Macro!F$9 -> 2004 | G52: =Macro!G$9 -> 1Q05 | H52: =Macro!H$9 -> 2Q05 | I52: =Macro!I$9 -> 3Q05 | ... EF52: =Macro!EF$9 -> 2030E
A53: Net Revenues | B53: =B11 -> 0 | C53: =C11 -> 0 | D53: =D11 -> 0 | E53: =E11 -> 0 | F53: =F11 -> 0 | G53: =G11 -> 0 | H53: =H11 -> 0 | I53: =I11 -> 0 | ... EF53: =EF11 -> 9699811.9
A54: COGS | B54: =B13+B15 -> 0 | C54: =C13+C15 -> 0 | D54: =D13+D15 -> 0 | E54: =E13+E15 -> 0 | F54: =F13+F15 -> 0 | G54: =G13+G15 -> 0 | H54: =H13+H15 -> 0 | I54: =I13+I15 -> 0 | ... EF54: =EF13+EF15 -> -6037761.7
A55: Gross Profit | B55: =B53+B54 -> 0 | C55: =C53+C54 -> 0 | D55: =D53+D54 -> 0 | E55: =E53+E54 -> 0 | F55: =F53+F54 -> 0 | G55: =G53+G54 -> 0 | H55: =H53+H54 -> 0 | I55: =I53+I54 -> 0 | ... EF55: =EF53+EF54 -> 3662050.2
A56: Operating Expenses | B56: =B18+B21+B33+B34+B44 -> 0 | C56: =C18+C21+C33+C34+C44 -> 0 | D56: =D18+D21+D33+D34+D44 -> 0 | E56: =E18+E21+E33+E34+E44 -> 0 | F56: =F18+F21+F33+F34+F44 -> 0 | G56: =G18+G21+G33+G34+G44 -> 0 | H56: =H18+H21+H33+H34+H44 -> 0 | I56: =I18+I21+I33+I34+I44 -> 0 | ... EF56: =EF18+EF21+EF33+EF34+EF44 -> -1396516
A57: EBIT | B57: =B55+B56 -> 0 | C57: =C55+C56 -> 0 | D57: =D55+D56 -> 0 | E57: =E55+E56 -> 0 | F57: =F55+F56 -> 0 | G57: =G55+G56 -> 0 | H57: =H55+H56 -> 0 | I57: =I55+I56 -> 0 | ... EF57: =EF55+EF56 -> 2265534.1
A58: EBITDA | B58: =B57+B68 -> 0 | C58: =C57+C68 -> 0 | D58: =D57+D68 -> 0 | E58: =E57+E68 -> 0 | F58: =F57+F68 -> 0 | G58: =G57+G68 -> 0 | H58: =H57+H68 -> 0 | I58: =I57+I68 -> 0 | ... EF58: =EF57+EF68 -> 2269316
A59: Net Financial Result | B59: =B60+B61 -> 0 | C59: =C60+C61 -> 0 | D59: =D60+D61 -> 0 | E59: =E60+E61 -> 0 | F59: =F60+F61 -> 0 | G59: =G60+G61 -> 0 | H59: =H60+H61 -> 0 | I59: =I60+I61 -> 0 | ... EF59: =EF60+EF61 -> 15634.553
A60: Interest Income | B60: =B24+B30+B28 -> 0 | C60: =C24+C30+C28 -> 0 | D60: =D24+D30+D28 -> 0 | E60: =E24+E30+E28 -> 0 | F60: =F24+F30+F28 -> 0 | G60: =G24+G30+G28 -> 0 | H60: =H24+H30+H28 -> 0 | I60: =I24+I30+I28 -> 0 | ... EF60: =EF24+EF30+EF28 -> 299296.16
A61: Interest Expense | B61: =B26+B14 -> 0 | C61: =C26+C14 -> 0 | D61: =D26+D14 -> 0 | E61: =E26+E14 -> 0 | F61: =F26+F14 -> 0 | G61: =G26+G14 -> 0 | H61: =H26+H14 -> 0 | I61: =I26+I14 -> 0 | ... EF61: =EF26+EF14 -> -283661.61
A62: Other Income | B62: =B31+B38+B35 -> 0 | C62: =C31+C38+C35 -> 0 | D62: =D31+D38+D35 -> 0 | E62: =E31+E38+E35 -> 0 | F62: =F31+F38+F35 -> 0 | G62: =G31+G38+G35 -> 0 | H62: =H31+H38+H35 -> 0 | I62: =I31+I38+I35 -> 0 | ... AE62: =AE31+AE38+AE35 -> 0 | AF62: =AF31+AF38+AF35+AF36 -> 0 | AG62: =AG31+AG38+AG35+AG36 -> 0 | AH62: =AH31+AH38+AH35+AH36 -> 0 | AI62: =AI31+AI38+AI35+AI36 -> 0 | AJ62: =AJ31+AJ38+AJ35+AJ36 -> 0 | AK62: =AK31+AK38+AK35+AK36 -> 0 | AL62: =AL31+AL38+AL35+AL36 -> 0 | AM62: =AM31+AM38+AM35+AM36 -> 0 | ... EF62: =EF31+EF38+EF35+EF36 -> 6097.0501
A63: EBT | B63: =B39 -> 0 | C63: =C39 -> 0 | D63: =D39 -> 0 | E63: =E39 -> 0 | F63: =F39 -> 0 | G63: =G39 -> 0 | H63: =H39 -> 0 | I63: =I39 -> 0 | ... EF63: =EF39 -> 2287265.7
A64: Taxes | B64: =B40+B42 -> 0 | C64: =C40+C42 -> 0 | D64: =D40+D42 -> 0 | E64: =E40+E42 -> 0 | F64: =F40+F42 -> 0 | G64: =G40+G42 -> 0 | H64: =H40+H42 -> 0 | I64: =I40+I42 -> 0 | ... EF64: =EF40+EF42 -> -186236.39
A65: Minorities | B65: =B46 -> 0 | C65: =C46 -> 0 | D65: =D46 -> 0 | E65: =E46 -> 0 | F65: =F46 -> 0 | G65: =G46 -> 0 | H65: =H46 -> 0 | I65: =I46 -> 0 | ... EF65: =EF46 -> -222121.15
A66: Net Income (reported) | B66: =B48 -> 0 | C66: =C48 -> 0 | D66: =D48 -> 0 | E66: =E48 -> 0 | F66: =F48 -> 0 | G66: =G48 -> 0 | H66: =H48 -> 0 | I66: =I48 -> 0 | ... EF66: =EF48 -> 1878908.2
A67: Net Income (adjusted) | B67: =B66-B35-B31-B38 -> 0 | C67: =C66-C35-C31-C38 -> 0 | D67: =D66-D35-D31-D38 -> 0 | E67: =E66-E35-E31-E38 -> 0 | F67: =F66-F35-F31-F38 -> 0 | G67: =G66-G35-G31-G38 -> 0 | H67: =H66-H35-H31-H38 -> 0 | I67: =I66-I35-I31-I38 -> 0 | ... EF67: =EF66-EF35-EF31-EF38 -> 1878908.2
A68: Depreciation&Amortization | B68: =-B34 -> 0 | C68: =-C34 -> 0 | D68: =-D34 -> 0 | E68: =-E34 -> 0 | F68: =-F34 -> 0 | G68: =-G34 -> 0 | H68: =-H34 -> 0 | I68: =-I34 -> 0 | ... AE68: =-AE34 -> 0 | AJ68: =SUM(AF68:AI68) -> 0 | AO68: =SUM(AK68:AN68) -> 0 | AT68: =SUM(AP68:AS68) -> 0 | AY68: =SUM(AU68:AX68) -> 0 | BC68: =-BC34 -> 4942 | BD68: =SUM(AZ68:BC68) -> 4942 | BH68: =-BH34 -> 3368 | BI68: =SUM(BE68:BH68) -> 3368 | BM68: =-BM34 -> 5774 | BN68: =SUM(BJ68:BM68) -> 5774 | BR68: =-BR34 -> 7471 | BS68: =SUM(BO68:BR68) -> 7471 | BW68: =-BW34 -> 3718 | BX68: =SUM(BT68:BW68) -> 3718 | BY68: =-BY34 -> 1854 | BZ68: =-BZ34 -> 179 | CA68: =-CA34 -> 399 | CB68: =-CB34 -> -1277 | CC68: =SUM(BY68:CB68) -> 1155 | CD68: =-CD34 -> 2925 | CE68: =-CE34 -> 307 | CF68: =-CF34 -> 365 | CG68: =-CG34 -> -2038 | CH68: =SUM(CD68:CG68) -> 1559 | CI68: =-CI34 -> 335 | CJ68: =-CJ34 -> 355 | CK68: =-CK34 -> 365 | CL68: =-CL34 -> 383 | CM68: =SUM(CI68:CL68) -> 1438 | CN68: =-CN34 -> 454 | CO68: =-CO34 -> 459 | CP68: =-CP34 -> 416 | CQ68: =-CQ34 -> 523 | CR68: =SUM(CN68:CQ68) -> 1852 | CS68: =-CS34 -> 776 | CT68: =-CT34 -> 721 | CU68: =-CU34 -> 696 | CV68: =-CV34 -> 782 | CW68: =SUM(CS68:CV68) -> 2975 | CX68: =-CX34 -> 529 | CY68: =-CY34 -> 728 | CZ68: =-CZ34 -> 725 | DA68: =-DA34 -> 691 | DB68: =SUM(CX68:DA68) -> 2673 | DC68: =-DC34 -> 204 | DD68: =-DD34 -> 226 | DE68: =-DE34 -> 219 | DF68: =-DF34 -> 216 | DG68: =SUM(DC68:DF68) -> 865 | DH68: =-DH34 -> 212 | DI68: =-DI34 -> 198 | DJ68: ='Balance Sheet'!DJ92+'Balance Sheet'!DJ94 -> 873.44929 | DK68: ='Balance Sheet'!DK92+'Balance Sheet'!DK94 -> 877.92456 | DL68: =SUM(DH68:DK68) -> 2161.3739 | DM68: ='Balance Sheet'!DM92+'Balance Sheet'!DM94 -> 882.42276 | DN68: ='Balance Sheet'!DN92+'Balance Sheet'!DN94 -> 886.944 | DO68: ='Balance Sheet'!DO92+'Balance Sheet'!DO94 -> 891.48841 | DP68: ='Balance Sheet'!DP92+'Balance Sheet'!DP94 -> 896.0561 | DQ68: =SUM(DM68:DP68) -> 3556.9113 | DR68: ='Balance Sheet'!DR92+'Balance Sheet'!DR94 -> 900.6472 | DS68: ='Balance Sheet'!DS92+'Balance Sheet'!DS94 -> 905.26182 | DT68: ='Balance Sheet'!DT92+'Balance Sheet'!DT94 -> 909.90008 | DU68: ='Balance Sheet'!DU92+'Balance Sheet'!DU94 -> 914.56211 | DV68: =SUM(DR68:DU68) -> 3630.3712 | DW68: ='Balance Sheet'!DW92+'Balance Sheet'!DW94 -> 919.24803 | DX68: ='Balance Sheet'!DX92+'Balance Sheet'!DX94 -> 923.95795 | DY68: ='Balance Sheet'!DY92+'Balance Sheet'!DY94 -> 928.69201 | DZ68: ='Balance Sheet'!DZ92+'Balance Sheet'!DZ94 -> 933.45032 | EA68: =SUM(DW68:DZ68) -> 3705.3483 | EB68: ='Balance Sheet'!EB92+'Balance Sheet'!EB94 -> 938.23301 | EC68: ='Balance Sheet'!EC92+'Balance Sheet'!EC94 -> 943.04021 | ED68: ='Balance Sheet'!ED92+'Balance Sheet'!ED94 -> 947.87204 | EE68: ='Balance Sheet'!EE92+'Balance Sheet'!EE94 -> 952.72862 | EF68: =SUM(EB68:EE68) -> 3781.8739
A69: Margins (%) | AJ69: =AJ67/AE67-1 -> #DIV/0! | AO69: =AO67/AJ67-1 -> 0.7275764 | AT69: =AT67/AO67-1 -> -0.11023744 | AY69: =AY67/AT67-1 -> 0.3121715 | BD69: =BD67/AY67-1 -> 0.28026912 | BI69: =BI67/BD67-1 -> -0.02544395 | BN69: =BN67/BI67-1 -> -0.30602252 | BS69: =BS67/BN67-1 -> 0.24012485 | BX69: =BX67/BS67-1 -> 0.16098871 | CC69: =CC67/BX67-1 -> 0.22236048 | CH69: =CH67/CC67-1 -> 0.0042715827 | CM69: =CM67/CH67-1 -> 0.86397159 | CR69: =CR67/CM67-1 -> 0.10053745 | CW69: =CW67/CR67-1 -> 0.46040287 | DB69: =DB67/CW67-1 -> 0.34887964 | DF69: =DG73+DG29/DG11 -> 0.23596795 | DG69: =DG67/DB67-1 -> 0.50118721 | DJ69: =DK69-DL14/DL11 -> 0.24316279 | DK69: =DL73+DL29/DL11 -> 0.24180334 | DL69: =DL67/DG67-1 -> 0.27487414 | DO69: =DP69-DQ14/DQ11 -> 0.24532394 | DP69: =DQ73+DQ29/DQ11 -> 0.24216641 | DQ69: =DQ67/DL67-1 -> 0.23275576 | DT69: =DU69-DV14/DV11 -> 0.2430627 | DU69: =DV73+DV29/DV11 -> 0.23743856 | DV69: =DV67/DQ67-1 -> 0.11179782 | DY69: =DZ69-EA14/EA11 -> 0.2409489 | DZ69: =EA73+EA29/EA11 -> 0.23562511 | EA69: =EA67/DV67-1 -> 0.053413935 | ED69: =EE69-EF14/EF11 -> 0.23932643 | EE69: =EF73+EF29/EF11 -> 0.23395464 | EF69: =EF67/EA67-1 -> 0.046388675
A70: Gross Margin | B70: =B55/B$53 -> #DIV/0! | C70: =C55/C$53 -> #DIV/0! | D70: =D55/D$53 -> #DIV/0! | E70: =E55/E$53 -> #DIV/0! | F70: =F55/F$53 -> #DIV/0! | G70: =G55/G$53 -> #DIV/0! | H70: =H55/H$53 -> #DIV/0! | I70: =I55/I$53 -> #DIV/0! | ... EF70: =EF55/EF$53 -> 0.37753827
A71: Development & Sales | B71: =(1+B13/B5) -> #DIV/0! | C71: =(1+C13/C5) -> #DIV/0! | D71: =(1+D13/D5) -> #DIV/0! | E71: =(1+E13/E5) -> #DIV/0! | F71: =(1+F13/F5) -> #DIV/0! | G71: =(1+G13/G5) -> #DIV/0! | H71: =(1+H13/H5) -> #DIV/0! | I71: =(1+I13/I5) -> #DIV/0! | ... DI71: =(1+DI13/DI5) -> 0.41108591 | DJ71: =('Balance Sheet'!DJ118*Forecasts!DJ38+'Balance Sheet'!DI110*Forecasts!DJ40)/DJ5-0.5% -> 0.41310888 | DK71: =('Balance Sheet'!DK118*Forecasts!DK38+'Balance Sheet'!DJ110*Forecasts!DK40)/DK5 -> 0.4160996 | DL71: =(1+DL13/DL5) -> 0.41144709 | DM71: =('Balance Sheet'!DM118*Forecasts!DM38+'Balance Sheet'!DL110*Forecasts!DM40)/DM5 -> 0.41000922 | DN71: =('Balance Sheet'!DN118*Forecasts!DN38+'Balance Sheet'!DM110*Forecasts!DN40)/DN5 -> 0.40839634 | DO71: =('Balance Sheet'!DO118*Forecasts!DO38+'Balance Sheet'!DN110*Forecasts!DO40)/DO5 -> 0.4045575 | DP71: =('Balance Sheet'!DP118*Forecasts!DP38+'Balance Sheet'!DO110*Forecasts!DP40)/DP5 -> 0.40311882 | DQ71: =(1+DQ13/DQ5) -> 0.40643616 | DR71: =('Balance Sheet'!DR118*Forecasts!DR38+'Balance Sheet'!DQ110*Forecasts!DR40)/DR5 -> 0.39940568 | DS71: =('Balance Sheet'!DS118*Forecasts!DS38+'Balance Sheet'!DR110*Forecasts!DS40)/DS5 -> 0.39802575 | DT71: =('Balance Sheet'!DT118*Forecasts!DT38+'Balance Sheet'!DS110*Forecasts!DT40)/DT5 -> 0.39675796 | DU71: =('Balance Sheet'!DU118*Forecasts!DU38+'Balance Sheet'!DT110*Forecasts!DU40)/DU5 -> 0.39558969 | DV71: =(1+DV13/DV5) -> 0.39741405 | DW71: =('Balance Sheet'!DW118*Forecasts!DW38+'Balance Sheet'!DV110*Forecasts!DW40)/DW5 -> 0.3945108 | DX71: =('Balance Sheet'!DX118*Forecasts!DX38+'Balance Sheet'!DW110*Forecasts!DX40)/DX5 -> 0.39351279 | DY71: =('Balance Sheet'!DY118*Forecasts!DY38+'Balance Sheet'!DX110*Forecasts!DY40)/DY5 -> 0.39258839 | DZ71: =('Balance Sheet'!DZ118*Forecasts!DZ38+'Balance Sheet'!DY110*Forecasts!DZ40)/DZ5 -> 0.39173125 | EA71: =(1+EA13/EA5) -> 0.39306726 | EB71: =('Balance Sheet'!EB118*Forecasts!EB38+'Balance Sheet'!EA110*Forecasts!EB40)/EB5 -> 0.39093576 | EC71: =('Balance Sheet'!EC118*Forecasts!EC38+'Balance Sheet'!EB110*Forecasts!EC40)/EC5 -> 0.3901969 | ED71: =('Balance Sheet'!ED118*Forecasts!ED38+'Balance Sheet'!EC110*Forecasts!ED40)/ED5 -> 0.38951017 | EE71: =('Balance Sheet'!EE118*Forecasts!EE38+'Balance Sheet'!ED110*Forecasts!EE40)/EE5 -> 0.38887152 | EF71: =(1+EF13/EF5) -> 0.38986644
A72: Rental & Services | B72: =(1+B15/B7) -> #DIV/0! | C72: =(1+C15/C7) -> #DIV/0! | D72: =(1+D15/D7) -> #DIV/0! | E72: =(1+E15/E7) -> #DIV/0! | F72: =(1+F15/F7) -> #DIV/0! | G72: =(1+G15/G7) -> #DIV/0! | H72: =(1+H15/H7) -> #DIV/0! | I72: =(1+I15/I7) -> #DIV/0! | ... DI72: =(1+DI15/DI7) -> -0.73513514 | DJ72: 0.8 | DK72: 0.8 | DL72: =(1+DL15/DL7) -> 0.65087182 | DM72: 0.7 | DN72: =DM72 -> 0.7 | DO72: =DN72 -> 0.7 | DP72: =DO72 -> 0.7 | DQ72: =(1+DQ15/DQ7) -> 0.7 | DR72: =DP72 -> 0.7 | DS72: =DR72 -> 0.7 | DT72: =DS72 -> 0.7 | DU72: =DT72 -> 0.7 | DV72: =(1+DV15/DV7) -> 0.7 | DW72: =DU72 -> 0.7 | DX72: =DW72 -> 0.7 | DY72: =DX72 -> 0.7 | DZ72: =DY72 -> 0.7 | EA72: =(1+EA15/EA7) -> 0.7 | EB72: =DZ72 -> 0.7 | EC72: =EB72 -> 0.7 | ED72: =EC72 -> 0.7 | EE72: =ED72 -> 0.7 | EF72: =(1+EF15/EF7) -> 0.7
A73: EBITDA Margin | B73: =B58/B$53 -> #DIV/0! | C73: =C58/C$53 -> #DIV/0! | D73: =D58/D$53 -> #DIV/0! | E73: =E58/E$53 -> #DIV/0! | F73: =F58/F$53 -> #DIV/0! | G73: =G58/G$53 -> #DIV/0! | H73: =H58/H$53 -> #DIV/0! | I73: =I58/I$53 -> #DIV/0! | ... EF73: =EF58/EF$53 -> 0.23395464
A74: EBIT Margin | B74: =B57/B53 -> #DIV/0! | C74: =C57/C53 -> #DIV/0! | D74: =D57/D53 -> #DIV/0! | E74: =E57/E53 -> #DIV/0! | F74: =F57/F53 -> #DIV/0! | G74: =G57/G53 -> #DIV/0! | H74: =H57/H53 -> #DIV/0! | I74: =I57/I53 -> #DIV/0! | ... EF74: =EF57/EF53 -> 0.23356475
A75: Net Margin | B75: =B66/B$53 -> #DIV/0! | C75: =C66/C$53 -> #DIV/0! | D75: =D66/D$53 -> #DIV/0! | E75: =E66/E$53 -> #DIV/0! | F75: =F66/F$53 -> #DIV/0! | G75: =G66/G$53 -> #DIV/0! | H75: =H66/H$53 -> #DIV/0! | I75: =I66/I$53 -> #DIV/0! | ... EF75: =EF66/EF$53 -> 0.19370563
CR76: =(135800*4/CR78)/12.28 -> 0.15259374 | CZ76: =DA76/21.49*4 -> 0.13301885 | DA76: =-'Balance Sheet'!DA49/'Income Statement'!DA78 -> 0.71464377
A77: Per share data | B77: =Macro!B$9 -> 1Q04 | C77: =Macro!C$9 -> 2Q04 | D77: =Macro!D$9 -> 3Q04 | E77: =Macro!E$9 -> 4Q04 | F77: =Macro!F$9 -> 2004 | G77: =Macro!G$9 -> 1Q05 | H77: =Macro!H$9 -> 2Q05 | I77: =Macro!I$9 -> 3Q05 | ... EF77: =Macro!EF$9 -> 2030E
A78: Shares Outstanding (ex-treasury) | F78: =E78 -> 0 | K78: =J78 -> 0 | P78: =O78 -> 0 | U78: =T78 -> 0 | Z78: =Y78 -> 0 | AE78: =AD78 -> 0 | AF78: 273693.27 | AG78: 273693.27 | AH78: 273693.27 | AI78: 273693.27 | AJ78: =AI78 -> 273693.27 | AK78: =AI78 -> 273693.27 | AL78: =AK78 -> 273693.27 | AM78: =AL78 -> 273693.27 | AN78: 273693.27 | AO78: =AN78 -> 273693.27 | AP78: =AN78 -> 273693.27 | AQ78: =AP78 -> 273693.27 | AR78: =AQ78 -> 273693.27 | AS78: 273693.27 | AT78: =AS78 -> 273693.27 | AU78: =AS78 -> 273693.27 | AV78: =AU78 -> 273693.27 | AW78: =AV78 -> 273693.27 | AX78: 273693.27 | AY78: =AX78 -> 273693.27 | AZ78: =AX78 -> 273693.27 | BA78: =AZ78 -> 273693.27 | BB78: =BA78 -> 273693.27 | BC78: 273693.27 | BD78: =BC78 -> 273693.27 | BE78: =BC78 -> 273693.27 | BF78: =BE78 -> 273693.27 | BG78: =BF78 -> 273693.27 | BH78: 273693.27 | BI78: =BH78 -> 273693.27 | BJ78: =BH78 -> 273693.27 | BK78: =BJ78 -> 273693.27 | BL78: =BK78 -> 273693.27 | BM78: 273693.27 | BN78: =BM78 -> 273693.27 | BO78: =BM78 -> 273693.27 | BP78: =BO78 -> 273693.27 | BQ78: =BP78 -> 273693.27 | BR78: 273693.27 | BS78: =BR78 -> 273693.27 | BT78: =BR78 -> 273693.27 | BU78: =BT78 -> 273693.27 | BV78: =BU78 -> 273693.27 | BW78: 273693.27 | BX78: =BW78 -> 273693.27 | BY78: =BW78 -> 273693.27 | BZ78: =BY78 -> 273693.27 | CA78: =BZ78 -> 273693.27 | CB78: 273693.27 | CC78: =CB78 -> 273693.27 | CD78: 273693.27 | CE78: 273693.27 | CF78: 291875.09 | CG78: 291875.09 | CH78: =CG78 -> 291875.09 | CI78: 291875.09 | CJ78: 291875.09 | CK78: 291875.09 | CL78: =291785.088-18.6 -> 291766.49 | CM78: =CL78 -> 291766.49 | CN78: 291875.09 | CO78: =291875.088-1990.8 -> 289884.29 | CP78: =291875.088-1990.8 -> 289884.29 | CQ78: =291875.088-1990.8 -> 289884.29 | CR78: =CQ78 -> 289884.29 | CS78: =291875.088-1990.8 -> 289884.29 | CT78: =291875.088-1990.8 -> 289884.29 | CU78: =291875.088-1990.8 -> 289884.29 | CV78: =291875.088-1990.8 -> 289884.29 | CW78: =CV78 -> 289884.29 | CX78: =291875.088-1990.8 -> 289884.29 | CY78: =291875.088-1990.8 -> 289884.29 | CZ78: =291875.088-1990.8 -> 289884.29 | DA78: =291875.088-1990.8 -> 289884.29 | DB78: =DA78 -> 289884.29 | DC78: =291875.088-1990.8 -> 289884.29 | DD78: =291875.088 -> 291875.09 | DE78: =291875.088 -> 291875.09 | DF78: =308047.594-0 -> 308047.59 | DG78: =DF78 -> 308047.59 | DH78: =308047.594-0 -> 308047.59 | DI78: =308047.594-0 -> 308047.59 | DJ78: =DI78+('Balance Sheet'!DJ44+'Balance Sheet'!DJ45-'Balance Sheet'!DI44-'Balance Sheet'!DI45)/DCF!$B$13 -> 308047.59 | DK78: =DJ78+('Balance Sheet'!DK44+'Balance Sheet'!DK45-'Balance Sheet'!DJ44-'Balance Sheet'!DJ45)/DCF!$B$13 -> 308047.59 | DL78: =DK78 -> 308047.59 | DM78: =DL78+('Balance Sheet'!DM44+'Balance Sheet'!DM45-'Balance Sheet'!DL44-'Balance Sheet'!DL45)/DCF!$B$13 -> 308047.59 | DN78: =DM78+('Balance Sheet'!DN44+'Balance Sheet'!DN45-'Balance Sheet'!DM44-'Balance Sheet'!DM45)/DCF!$B$13 -> 308047.59 | DO78: =DN78+('Balance Sheet'!DO44+'Balance Sheet'!DO45-'Balance Sheet'!DN44-'Balance Sheet'!DN45)/DCF!$B$13 -> 308047.59 | DP78: =DO78+('Balance Sheet'!DP44+'Balance Sheet'!DP45-'Balance Sheet'!DO44-'Balance Sheet'!DO45)/DCF!$B$13 -> 308047.59 | DQ78: =DP78 -> 308047.59 | DR78: =DQ78+('Balance Sheet'!DR44+'Balance Sheet'!DR45-'Balance Sheet'!DQ44-'Balance Sheet'!DQ45)/DCF!$B$13 -> 308047.59 | DS78: =DR78+('Balance Sheet'!DS44+'Balance Sheet'!DS45-'Balance Sheet'!DR44-'Balance Sheet'!DR45)/DCF!$B$13 -> 308047.59 | DT78: =DS78+('Balance Sheet'!DT44+'Balance Sheet'!DT45-'Balance Sheet'!DS44-'Balance Sheet'!DS45)/DCF!$B$13 -> 308047.59 | DU78: =DT78+('Balance Sheet'!DU44+'Balance Sheet'!DU45-'Balance Sheet'!DT44-'Balance Sheet'!DT45)/DCF!$B$13 -> 308047.59 | DV78: =DU78 -> 308047.59 | DW78: =DV78+('Balance Sheet'!DW44+'Balance Sheet'!DW45-'Balance Sheet'!DV44-'Balance Sheet'!DV45)/DCF!$B$13 -> 308047.59 | DX78: =DW78+('Balance Sheet'!DX44+'Balance Sheet'!DX45-'Balance Sheet'!DW44-'Balance Sheet'!DW45)/DCF!$B$13 -> 308047.59 | DY78: =DX78+('Balance Sheet'!DY44+'Balance Sheet'!DY45-'Balance Sheet'!DX44-'Balance Sheet'!DX45)/DCF!$B$13 -> 308047.59 | DZ78: =DY78+('Balance Sheet'!DZ44+'Balance Sheet'!DZ45-'Balance Sheet'!DY44-'Balance Sheet'!DY45)/DCF!$B$13 -> 308047.59 | EA78: =DZ78 -> 308047.59 | EB78: =EA78+('Balance Sheet'!EB44+'Balance Sheet'!EB45-'Balance Sheet'!EA44-'Balance Sheet'!EA45)/DCF!$B$13 -> 308047.59 | EC78: =EB78+('Balance Sheet'!EC44+'Balance Sheet'!EC45-'Balance Sheet'!EB44-'Balance Sheet'!EB45)/DCF!$B$13 -> 308047.59 | ED78: =EC78+('Balance Sheet'!ED44+'Balance Sheet'!ED45-'Balance Sheet'!EC44-'Balance Sheet'!EC45)/DCF!$B$13 -> 308047.59 | EE78: =ED78+('Balance Sheet'!EE44+'Balance Sheet'!EE45-'Balance Sheet'!ED44-'Balance Sheet'!ED45)/DCF!$B$13 -> 308047.59 | EF78: =EE78 -> 308047.59
