Workbook
Name _1_0BS_minor: #REF!
Name _1_0BS_minor: #REF!
Name _10_0Interc_Rev_Loc_: #REF!
Name _10_0IS_straightpref: #REF!
Name _10_0IS_straightpref: #REF!
Name _105J–Ï__íÇ: #REF!,#REF!,#REF!,#REF!,#REF!,#REF!,#REF!,#REF!,#REF!,#REF!,#REF!,#REF!
Name _106_0: #REF!,#REF!,#REF!,#REF!,#REF!,#REF!,#REF!,#REF!,#REF!,#REF!,#REF!,#REF!,#REF!,#REF!
Name _106J–Ï__íÇ: #REF!,#REF!,#REF!,#REF!,#REF!,#REF!,#REF!,#REF!,#REF!,#REF!,#REF!,#REF!
Name _106J–Ï__íÇ: #REF!,#REF!,#REF!,#REF!,#REF!,#REF!,#REF!,#REF!,#REF!,#REF!,#REF!,#REF!
Name _107_0: #REF!,#REF!,#REF!,#REF!,#REF!,#REF!,#REF!,#REF!,#REF!,#REF!,#REF!,#REF!,#REF!,#REF!
Name _107_0: #REF!,#REF!,#REF!,#REF!,#REF!,#REF!,#REF!,#REF!,#REF!,#REF!,#REF!,#REF!,#REF!,#REF!
Name _107_0_0BS_minor: #REF!
Name _108_0_0BS_minor: #REF!
Name _108_0_0CF_minor: #REF!
Name _109_0_0CF_minor: #REF!
Name _109_0_0IS_convpref: #REF!
Name _11_0Interc_Rev_LD_: #REF!
Name _11_0OutGoingTraf: #REF!
Name _110_0_0IS_convpref: #REF!
Name _110_0_0IS_intconv: #REF!
Name _111_0_0IS_intconv: #REF!
Name _111_0_0IS_intexist: #REF!
Name _112_0_0IS_intexist: #REF!
Name _112_0_0IS_minor: #REF!
Name _113_0_0IS_minor: #REF!
Name _113_0_0IS_straightpref: #REF!
Name _114_0_0IS_straightpref: #REF!
Name _114_0_0IS_synerg: #REF!
Name _115_0_0IS_synerg: #REF!
Name _115_0IS_synerg: #REF!
Name _116_0IS_synerg: #REF!
Name _116_0s: #REF!
Name _117_0s: #REF!
Name _117_0Sfu: #REF!
Name _118_0Sfu: #REF!
Name _118_1: #REF!
Name _119_1: #REF!
Name _119_1: #REF!
Name _119_10: #REF!
Name _12_0Interc_Rev_Loc_: #REF!
Name _12_0Interc_Rev_Loc_: #REF!
Name _12_0Perc_Reg_of: #REF!
Name _120_10: #REF!
Name _120_10: #REF!
Name _120_11: #REF!
Name _121_11: #REF!
Name _121_11: #REF!
Name _121_12: #REF!
Name _122_12: #REF!
Name _122_13: #REF!
Name _123_13: #REF!
Name _123_14: #REF!
Name _124_14: #REF!
Name _124_15: #REF!
Name _125_15: #REF!
Name _125_16: #REF!
Name _126_16: #REF!
Name _126_17: #REF!
Name _127_17: #REF!
Name _127_18: #REF!

Sheet Macro
A2: =DCF!$A$2 -> Cyrela - TP: R$35
A3: Status | B3: =B4&RIGHT(B5,2)&B6 -> 1Q04 | C3: =C4&RIGHT(C5,2)&C6 -> 2Q04 | D3: =D4&RIGHT(D5,2)&D6 -> 3Q04 | E3: =E4&RIGHT(E5,2)&E6 -> 4Q04 | F3: =F4&RIGHT(F5,2)&F6 -> 2004 | G3: =G4&RIGHT(G5,2)&G6 -> 1Q05 | H3: =H4&RIGHT(H5,2)&H6 -> 2Q05 | I3: =I4&RIGHT(I5,2)&I6 -> 3Q05 | ... EF3: =EF4&RIGHT(EF5,2)&EF6 -> 2030E
A4: Quarter | B4: 1Q | C4: 2Q | D4: 3Q | E4: 4Q | F4: 20 | G4: 1Q | H4: 2Q | I4: 3Q | J4: 4Q | K4: 20 | L4: 1Q | M4: 2Q | N4: 3Q | O4: 4Q | P4: 20 | Q4: 1Q | R4: 2Q | S4: 3Q | T4: 4Q | U4: 20 | V4: 1Q | W4: 2Q | X4: 3Q | Y4: 4Q | Z4: 20 | AA4: 1Q | AB4: 2Q | AC4: 3Q | AD4: 4Q | AE4: 20 | AF4: 1Q | AG4: 2Q | AH4: 3Q | AI4: 4Q | AJ4: 20 | AK4: 1Q | AL4: 2Q | AM4: 3Q | AN4: 4Q | AO4: 20 | AP4: 1Q | AQ4: 2Q | AR4: 3Q | AS4: 4Q | AT4: 20 | AU4: 1Q | AV4: 2Q | AW4: 3Q | AX4: 4Q | AY4: 20 | AZ4: 1Q | BA4: 2Q | BB4: 3Q | BC4: 4Q | BD4: 20 | BE4: 1Q | BF4: 2Q | BG4: 3Q | BH4: 4Q | BI4: 20 | BJ4: 1Q | BK4: 2Q | BL4: 3Q | BM4: 4Q | BN4: 20 | BO4: 1Q | BP4: 2Q | BQ4: 3Q | BR4: 4Q | BS4: 20 | BT4: 1Q | BU4: 2Q | BV4: 3Q | BW4: 4Q | BX4: 20 | BY4: 1Q | BZ4: 2Q | CA4: 3Q | CB4: 4Q | CC4: 20 | CD4: 1Q | CE4: 2Q | CF4: 3Q | CG4: 4Q | CH4: 20 | CI4: 1Q | CJ4: 2Q | CK4: 3Q | CL4: 4Q | CM4: 20 | CN4: 1Q | CO4: 2Q | CP4: 3Q | CQ4: 4Q | CR4: 20 | CS4: 1Q | CT4: 2Q | CU4: 3Q | CV4: 4Q | CW4: 20 | CX4: 1Q | CY4: 2Q | CZ4: 3Q | DA4: 4Q | DB4: 20 | DC4: 1Q | DD4: 2Q | DE4: 3Q | DF4: 4Q | DG4: 20 | DH4: 1Q | DI4: 2Q | DJ4: 3Q | DK4: 4Q | DL4: 20 | DM4: 1Q | DN4: 2Q | DO4: 3Q | DP4: 4Q | DQ4: 20 | DR4: 1Q | DS4: 2Q | DT4: 3Q | DU4: 4Q | DV4: 20 | DW4: 1Q | DX4: 2Q | DY4: 3Q | DZ4: 4Q | EA4: 20 | EB4: 1Q | EC4: 2Q | ED4: 3Q | EE4: 4Q | EF4: 20
A5: Year | B5: 2004 | C5: 2004 | D5: 2004 | E5: 2004 | F5: =E5 -> 2004 | G5: =B5+1 -> 2005 | H5: =C5+1 -> 2005 | I5: =D5+1 -> 2005 | J5: =E5+1 -> 2005 | K5: =J5 -> 2005 | L5: =G5+1 -> 2006 | M5: =H5+1 -> 2006 | N5: =I5+1 -> 2006 | O5: =J5+1 -> 2006 | P5: =O5 -> 2006 | Q5: =L5+1 -> 2007 | R5: =M5+1 -> 2007 | S5: =N5+1 -> 2007 | T5: =O5+1 -> 2007 | U5: =T5 -> 2007 | V5: =Q5+1 -> 2008 | W5: =R5+1 -> 2008 | X5: =S5+1 -> 2008 | Y5: =T5+1 -> 2008 | Z5: =Y5 -> 2008 | AA5: =V5+1 -> 2009 | AB5: =W5+1 -> 2009 | AC5: =X5+1 -> 2009 | AD5: =Y5+1 -> 2009 | AE5: =AD5 -> 2009 | AF5: =AA5+1 -> 2010 | AG5: =AB5+1 -> 2010 | AH5: =AC5+1 -> 2010 | AI5: =AD5+1 -> 2010 | AJ5: =AI5 -> 2010 | AK5: =AF5+1 -> 2011 | AL5: =AG5+1 -> 2011 | AM5: =AH5+1 -> 2011 | AN5: =AI5+1 -> 2011 | AO5: =AN5 -> 2011 | AP5: =AK5+1 -> 2012 | AQ5: =AL5+1 -> 2012 | AR5: =AM5+1 -> 2012 | AS5: =AN5+1 -> 2012 | AT5: =AO5+1 -> 2012 | AU5: =AP5+1 -> 2013 | AV5: =AQ5+1 -> 2013 | AW5: =AR5+1 -> 2013 | ... EF5: =EA5+1 -> 2030
A6: Actual/Estimate | DJ6: E | DK6: E | DL6: E | DM6: E | DN6: E | DO6: E | DP6: E | DQ6: E | DR6: E | DS6: E | DT6: E | DU6: E | DV6: E | DW6: E | DX6: E | DY6: E | DZ6: E | EA6: E | EB6: E | EC6: E | ED6: E | EE6: E | EF6: E
A7: Days in Quarter | B7: 91 | C7: 91 | D7: 92 | E7: 92 | F7: =SUM(B7:E7) -> 366 | G7: 90 | H7: 91 | I7: 92 | J7: 92 | K7: =SUM(G7:J7) -> 365 | L7: 90 | M7: 91 | N7: 92 | O7: 92 | P7: =SUM(L7:O7) -> 365 | Q7: 90 | R7: 91 | S7: 92 | T7: 92 | U7: =SUM(Q7:T7) -> 365 | V7: 91 | W7: 91 | X7: 92 | Y7: 92 | Z7: =SUM(V7:Y7) -> 366 | AA7: 90 | AB7: 91 | AC7: 92 | AD7: 92 | AE7: =SUM(AA7:AD7) -> 365 | AF7: 90 | AG7: 91 | AH7: 92 | AI7: 92 | AJ7: =SUM(AF7:AI7) -> 365 | AK7: 90 | AL7: 91 | AM7: 92 | AN7: 92 | AO7: =SUM(AK7:AN7) -> 365 | AP7: 90 | AQ7: 91 | AR7: 92 | AS7: 92 | AT7: 366 | AU7: 90 | AV7: 91 | AW7: 92 | AX7: 92 | AY7: =SUM(AU7:AX7) -> 365 | AZ7: 90 | BA7: 91 | BB7: 92 | BC7: 92 | BD7: =SUM(AZ7:BC7) -> 365 | BE7: 90 | BF7: 91 | BG7: 92 | BH7: 92 | BI7: =SUM(BE7:BH7) -> 365 | BJ7: 90 | BK7: 91 | BL7: 92 | BM7: 92 | BN7: =SUM(BJ7:BM7) -> 365 | BO7: 90 | BP7: 91 | BQ7: 92 | BR7: 92 | BS7: =SUM(BO7:BR7) -> 365 | BT7: 90 | BU7: 91 | BV7: 92 | BW7: 92 | BX7: =SUM(BT7:BW7) -> 365 | BY7: 90 | BZ7: 91 | CA7: 92 | CB7: 92 | CC7: =SUM(BY7:CB7) -> 365 | CD7: 90 | CE7: 91 | CF7: 92 | CG7: 92 | CH7: =SUM(CD7:CG7) -> 365 | CI7: 90 | CJ7: 91 | CK7: 92 | CL7: 92 | CM7: =SUM(CI7:CL7) -> 365 | CN7: 90 | CO7: 91 | CP7: 92 | CQ7: 92 | CR7: =SUM(CN7:CQ7) -> 365 | CS7: 90 | CT7: 91 | CU7: 92 | CV7: 92 | CW7: =SUM(CS7:CV7) -> 365 | CX7: 90 | CY7: 91 | CZ7: 92 | DA7: 92 | DB7: =SUM(CX7:DA7) -> 365 | DC7: 90 | DD7: 91 | DE7: 92 | DF7: 92 | DG7: =SUM(DC7:DF7) -> 365 | DH7: 90 | DI7: 91 | DJ7: 92 | DK7: 92 | DL7: =SUM(DH7:DK7) -> 365 | DM7: 90 | DN7: 91 | DO7: 92 | DP7: 92 | DQ7: =SUM(DM7:DP7) -> 365 | DR7: 90 | DS7: 91 | DT7: 92 | DU7: 92 | DV7: =SUM(DR7:DU7) -> 365 | DW7: 90 | DX7: 91 | DY7: 92 | DZ7: 92 | EA7: =SUM(DW7:DZ7) -> 365 | EB7: 90 | EC7: 91 | ED7: 92 | EE7: 92 | EF7: =SUM(EB7:EE7) -> 365
A9: Macro variables | B9: =B$3 -> 1Q04 | C9: =C$3 -> 2Q04 | D9: =D$3 -> 3Q04 | E9: =E$3 -> 4Q04 | F9: =F$3 -> 2004 | G9: =G$3 -> 1Q05 | H9: =H$3 -> 2Q05 | I9: =I$3 -> 3Q05 | ... EF9: =EF$3 -> 2030E
A10: GDP Growth | B10: 0.018625076 | C10: 0.034978624 | D10: 0.046182359 | E10: 0.05690445 | F10: 0.05690445 | G10: 0.050839899 | H10: 0.040117662 | I10: 0.035368516 | J10: 0.031478279 | K10: 0.031478279 | L10: 0.035123174 | M10: 0.03287402 | N10: 0.035871317 | O10: 0.039296141 | P10: 0.039296141 | Q10: 0.041838309 | R10: 0.05276138 | S10: 0.0558906 | T10: 0.060872371 | U10: 0.060872371 | V10: 0.063938236 | W10: 0.063785439 | X10: 0.066447177 | Y10: 0.051439409 | Z10: 0.051439409 | AA10: 0.029907003 | AB10: 0.0094328172 | AC10: -0.010336182 | AD10: -0.0017527142 | AE10: -0.0017527142 | AF10: 0.092714294 | AG10: 0.091562714 | AH10: 0.067385174 | AI10: 0.050367589 | AJ10: 0.075 | AK10: 0.04235654 | AL10: 0.03314358 | AM10: 0.021219664 | AN10: 0.013664596 | AO10: 0.027325092 | AP10: 0.007973 | AQ10: 0.005509 | AR10: 0.009444 | AS10: 0.01825 | AT10: 0.01 | AU10: 0.0189 | AV10: 0.0346 | AW10: 0.0243 | AX10: 0.0217 | AY10: 0.025 | AZ10: 0.0191 | BA10: 0.004 | BB10: 0.011 | BC10: 0.01 | BD10: 0.0014458389 | BE10: -0.0081656208 | BF10: -0.017777081 | BG10: -0.02738854 | BH10: -0.037 | BI10: -0.037 | BJ10: -0.03475 | BK10: -0.0325 | BL10: -0.03025 | BM10: -0.028 | BN10: -0.028 | BO10: 0.005 | BP10: 0.005 | BQ10: 0.005 | BR10: 0.005 | BS10: 0.01 | BT10: 0.0032837896 | BU10: 0.0032837896 | BV10: 0.0032837896 | BW10: 0.0032837896 | BX10: 0.0132 | BY10: 0.0027387285 | BZ10: 0.0027387285 | CA10: 0.0027387285 | CB10: 0.0027387285 | CC10: 0.011 | CD10: -0.01 | CE10: -0.01 | CF10: -0.01 | CG10: -0.01 | CH10: -0.041 | CI10: 0.03 | CJ10: 0.03 | CK10: 0.03 | CL10: 0.03 | CM10: 0.046 | CN10: 0.02 | CO10: 0.02 | CP10: 0.02 | CQ10: 0.02 | CR10: 0.03 | CS10: 0.02 | CT10: 0.02 | CU10: 0.02 | CV10: 0.02 | CW10: 0.029 | CX10: 0.02 | CY10: 0.02 | CZ10: 0.02 | DA10: 0.02 | DB10: 0.034 | DC10: 0.02 | DD10: 0.02 | DE10: 0.02 | DF10: 0.02 | DG10: 0.02 | DH10: 0.02 | DI10: 0.02 | DJ10: 0.02 | DK10: 0.02 | DL10: 0.02 | DM10: 0.02 | DN10: 0.02 | DO10: 0.02 | DP10: 0.02 | DQ10: 0.02 | DR10: 0.02 | DS10: 0.02 | DT10: 0.02 | DU10: 0.02 | DV10: 0.02 | DW10: 0.02 | DX10: 0.02 | DY10: 0.02 | DZ10: 0.02 | EA10: 0.02 | EB10: 0.02 | EC10: 0.02 | ED10: 0.02 | EE10: 0.02 | EF10: 0.02
A11: R$/US$ EoP | B11: 2.9086 | C11: 3.1075 | D11: 2.8586 | E11: 2.6544 | F11: 2.6544 | G11: 2.6662 | H11: 2.3504 | I11: 2.2222 | J11: 2.3407 | K11: 2.3407 | L11: 2.1724 | M11: 2.1643 | N11: 2.1742 | O11: 2.138 | P11: 2.138 | Q11: 2.0504 | R11: 1.9262 | S11: 1.8389 | T11: 1.7713 | U11: 1.7713 | V11: 1.7491 | W11: 1.5919 | X11: 1.9143 | Y11: 2.337 | Z11: 2.337 | AA11: 2.3152 | AB11: 1.9516 | AC11: 1.7781 | AD11: 1.7412 | AE11: 1.7412 | AF11: 1.781 | AG11: 1.8015 | AH11: 1.6942 | AI11: 1.7161 | AJ11: 1.6662 | AK11: 1.6318 | AL11: 1.5633 | AM11: 1.8793 | AN11: 1.8668 | AO11: 1.8758 | AP11: 1.82 | AQ11: 2.02 | AR11: 2.03 | AS11: 2.04 | AT11: 2.04 | AU11: 2.0138 | AV11: 2.2156 | AW11: 2.23 | AX11: 2.3426 | AY11: 2.34 | AZ11: 2.263 | BA11: 2.29 | BB11: 2.34 | BC11: 2.4 | BD11: 2.6562 | BE11: 3.208 | BF11: 3.1026 | BG11: 3.9729 | BH11: 3.9048 | BI11: 3.8 | BJ11: 3.5589 | BK11: 3.2098 | BL11: 3.2462 | BM11: 3.2591 | BN11: 3.2591 | BO11: 3.2 | BP11: 3.12 | BQ11: 3.31 | BR11: 3.308 | BS11: 3.308 | BT11: 3.3238 | BU11: 3.8558 | BV11: 4.0039 | BW11: 3.88 | BX11: 3.88 | BY11: 3.9017478 | BZ11: 3.9236175 | CA11: 3.9456098 | CB11: 3.9677253 | CC11: 4.0307 | CD11: 5 | CE11: 5.0084136 | CF11: 5.0168413 | CG11: 5.0252832 | CH11: 4.8 | CI11: 4.872642 | CJ11: 4.9463833 | CK11: 5.0212406 | CL11: 5.0972308 | CM11: 5.5805 | CN11: 5.6316783 | CO11: 5.683326 | CP11: 5.7354473 | CQ11: 5.7880467 | CR11: 5.2177 | CS11: 5.2508591 | CT11: 5.284229 | CU11: 5.3178109 | CV11: 5.3516063 | CW11: 4.8513 | CX11: 4.8845909 | CY11: 4.9181102 | CZ11: 4.9518595 | DA11: 4.9858404 | DB11: 6.1923 | DC11: 5.9623333 | DD11: 5.7323667 | DE11: 5.6173833 | DF11: 5.5024 | DG11: 5.5024 | DH11: 5.5291054 | DI11: 5.5559404 | DJ11: 5.5829056 | DK11: 5.6100017 | DL11: 5.6100017 | DM11: 5.6372293 | DN11: 5.6645891 | DO11: 5.6920817 | DP11: 5.7197077 | DQ11: 5.7197077 | DR11: 5.7474677 | DS11: 5.7753625 | DT11: 5.8033927 | DU11: 5.8315589 | DV11: 5.8315589 | DW11: 5.8598619 | DX11: 5.8883021 | DY11: 5.9168805 | DZ11: 5.9455975 | EA11: 5.9455975 | EB11: 5.9744539 | EC11: 6.0034503 | ED11: 6.0325875 | EE11: 6.0618661 | EF11: 6.0618661
A12: Sequential Change | B12: 0.0067146615 | C12: 0.068383415 | D12: -0.080096541 | E12: -0.071433569 | F12: -0.081268171 | G12: 0.0044454491 | H12: -0.11844573 | I12: -0.054543907 | J12: 0.053325533 | K12: -0.11818113 | L12: -0.071901568 | M12: -0.0037285951 | N12: 0.0045742272 | O12: -0.016649802 | P12: -0.086598026 | Q12: -0.040972872 | R12: -0.060573547 | S12: -0.045322396 | T12: -0.036761107 | U12: -0.17151543 | V12: -0.012533168 | W12: -0.089874793 | X12: 0.20252528 | Y12: 0.22081178 | Z12: 0.31936995 | AA12: -0.0093281985 | AB12: -0.15704907 | AC12: -0.088901414 | AD12: -0.020752489 | AE12: -0.25494223 | AF12: -0.0069287358 | AG12: -0.0069770782 | AH12: -0.0070260998 | AI12: -0.0070758152 | AJ12: -0.027714943 | AK12: -0.049123011 | AL12: -0.041978184 | AM12: 0.20213651 | AN12: -0.0066514128 | AO12: 0.12579522 | AP12: -0.025069638 | AQ12: 0.10989011 | AR12: 0.004950495 | AS12: 0.0049261084 | AT12: 0.087535985 | AU12: -0.012843137 | AV12: 0.10020856 | AW12: 0.0064993681 | AX12: 0.050493274 | AY12: 0.14705882 | AZ12: -0.033979339 | BA12: 0.011931065 | BB12: 0.021834061 | BC12: 0.025641026 | BD12: 0.13512821 | BE12: 0.33666667 | BF12: -0.032855362 | BG12: 0.28050667 | BH12: -0.017141131 | BI12: 0.43061515 | BJ12: -0.088583282 | BK12: -0.098092107 | BL12: 0.01134027 | BM12: 0.0039738771 | BN12: -0.14234209 | BO12: -0.018133841 | BP12: -0.025 | BQ12: 0.060897436 | BR12: -0.00060422961 | BS12: 0.015004142 | BT12: 0.0047762999 | BU12: 0.16005777 | BV12: 0.038409669 | BW12: -0.030944829 | BX12: 0.17291415 | BY12: 0.0056051018 | BZ12: 0.0056051018 | CA12: 0.0056051018 | CB12: 0.0056051018 | CC12: 0.038840206 | CD12: 0.0056051018 | CE12: 0.0056051018 | CF12: 0.0056051018 | CG12: 0.0056051018 | CH12: 0.19086015 | CI12: 0.0056051018 | CJ12: 0.0056051018 | CK12: 0.0056051018 | CL12: 0.0056051018 | CM12: 0.16260417 | CN12: 0.0056051018 | CO12: 0.0056051018 | CP12: 0.0056051018 | CQ12: 0.0056051018 | CR12: -0.065012096 | CS12: 0.0056051018 | CT12: 0.0056051018 | CU12: 0.0056051018 | CV12: 0.0056051018 | CW12: -0.070222512 | CX12: 0.0056051018 | CY12: 0.0056051018 | CZ12: 0.0056051018 | DA12: 0.0056051018 | DB12: 0.27642075 | DC12: 0.0056051018 | DD12: 0.0056051018 | DE12: 0.0056051018 | DF12: 0.0056051018 | DG12: -0.11141256 | DH12: 0.0056051018 | DI12: 0.0056051018 | DJ12: 0.0056051018 | DK12: 0.0056051018 | DL12: 0.019555417 | DM12: 0.0056051018 | DN12: 0.0056051018 | DO12: 0.0056051018 | DP12: 0.0056051018 | DQ12: 0.019555417 | DR12: 0.0056051018 | DS12: 0.0056051018 | DT12: 0.0056051018 | DU12: 0.0056051018 | DV12: 0.019555417 | DW12: 0.0056051018 | DX12: 0.0056051018 | DY12: 0.0056051018 | DZ12: 0.0056051018 | EA12: 0.019555417 | EB12: 0.0056051018 | EC12: 0.0056051018 | ED12: 0.0056051018 | EE12: 0.0056051018 | EF12: 0.019555417
A13: R$/US$ Average | B13: 2.8958667 | C13: 3.0451667 | D13: 2.9769333 | E13: 2.7857 | F13: 2.9259167 | G13: 2.6651667 | H13: 2.4818333 | I13: 2.3428333 | J13: 2.2509333 | K13: 2.4351917 | L13: 2.1959333 | M13: 2.1852333 | N13: 2.1713 | O13: 2.1520333 | P13: 2.176125 | Q13: 2.1078167 | R13: 1.9818333 | S13: 1.9161333 | T13: 1.7856333 | U13: 1.9478542 | V13: 1.7365333 | W13: 1.6561 | X13: 1.6677667 | Y13: 2.2778667 | Z13: 1.8345667 | AA13: 2.3113 | AB13: 2.0748 | AC13: 1.8659333 | AD13: 1.7383667 | AE13: 1.9976 | AF13: 1.8416333 | AG13: 1.8131905 | AH13: 1.7595636 | AI13: 1.71333 | AJ13: 1.7593 | AK13: 1.6668306 | AL13: 1.5953516 | AM13: 1.6363954 | AN13: 1.8029258 | AO13: 1.6746 | AP13: 1.7687873 | AQ13: 1.9633 | AR13: 2.0279 | AS13: 2.06 | AT13: 1.9549968 | AU13: 1.9957333 | AV13: 2.07 | AW13: 2.2883 | AX13: 2.2765 | AY13: 2.1576333 | AZ13: 2.3639965 | BA13: 2.268832 | BB13: 2.33 | BC13: 2.38 | BD13: 2.3357071 | BE13: 2.8691 | BF13: 3.0709 | BG13: 3.5399 | BH13: 3.8471 | BI13: 3.33175 | BJ13: 3.67945 | BK13: 3.38435 | BL13: 3.228 | BM13: 3.25265 | BN13: 3.3861125 | BO13: 3.22955 | BP13: 3.16 | BQ13: 3.215 | BR13: 3.309 | BS13: 3.2283875 | BT13: 3.3159 | BU13: 3.5898 | BV13: 3.92985 | BW13: 3.94195 | BX13: 3.694375 | BY13: 3.8908739 | BZ13: 3.9126826 | CA13: 3.9346136 | CB13: 3.9566675 | CC13: 3.9237094 | CD13: 4.51535 | CE13: 5.0042068 | CF13: 5.0126274 | CG13: 5.0210622 | CH13: 4.8883116 | CI13: 4.836321 | CJ13: 4.9095126 | CK13: 4.983812 | CL13: 5.0592357 | CM13: 4.9472203 | CN13: 5.6060892 | CO13: 5.6575022 | CP13: 5.7093867 | CQ13: 5.761747 | CR13: 5.6836813 | CS13: 5.2342796 | CT13: 5.2675441 | CU13: 5.3010199 | CV13: 5.3347086 | CW13: 5.284388 | CX13: 4.8679454 | CY13: 4.9013505 | CZ13: 4.9349848 | DA13: 4.96885 | DB13: 4.9182827 | DC13: 6.0773167 | DD13: 5.84735 | DE13: 5.674875 | DF13: 5.5598917 | DG13: 5.7898583 | DH13: 5.5157527 | DI13: 5.5425229 | DJ13: 5.569423 | DK13: 5.5964537 | DL13: 5.5560381 | DM13: 5.6236155 | DN13: 5.6509092 | DO13: 5.6783354 | DP13: 5.7058947 | DQ13: 5.6646887 | DR13: 5.7335877 | DS13: 5.7614151 | DT13: 5.7893776 | DU13: 5.8174758 | DV13: 5.7754641 | DW13: 5.8457104 | DX13: 5.874082 | DY13: 5.9025913 | DZ13: 5.931239 | EA13: 5.8884057 | EB13: 5.9600257 | EC13: 5.9889521 | ED13: 6.0180189 | EE13: 6.0472268 | EF13: 6.0035559
A14: Sequential Change | B14: -0.0014941498 | C14: 0.051556241 | D14: -0.022407093 | E14: -0.064238366 | F14: -0.049497285 | G14: -0.043268598 | H14: -0.068788694 | I14: -0.056006984 | J14: -0.039226008 | K14: -0.16771667 | L14: -0.024434309 | M14: -0.0048726434 | N14: -0.0063761307 | O14: -0.0088733324 | P14: -0.10638451 | Q14: -0.02054646 | R14: -0.059769588 | S14: -0.033151123 | T14: -0.068105908 | U14: -0.10489785 | V14: -0.027497247 | W14: -0.046318335 | X14: 0.0070446632 | Y14: 0.36581856 | Z14: -0.058160155 | AA14: 0.014677476 | AB14: -0.10232337 | AC14: -0.10066834 | AD14: -0.068366144 | AE14: 0.088867489 | AF14: -0.04434007 | AG14: -0.006952823 | AH14: -0.0070015032 | AI14: -0.0070508699 | AJ14: -0.15792685 | AK14: -0.027139754 | AL14: -0.0428832 | AM14: 0.025727101 | AN14: 0.10176662 | AO14: -0.048144148 | AP14: -0.018935058 | AQ14: 0.10996952 | AR14: 0.032903784 | AS14: 0.015829183 | AT14: 0.16744108 | AU14: -0.031197411 | AV14: 0.03721272 | AW14: 0.10545894 | AX14: -0.0051566665 | AY14: 0.10365056 | AZ14: 0.038434655 | BA14: -0.040255779 | BB14: 0.02696014 | BC14: 0.021459227 | BD14: 0.082531995 | BE14: 0.2055042 | BF14: 0.070335645 | BG14: 0.15272396 | BH14: 0.086782112 | BI14: 0.42644169 | BJ14: -0.043578286 | BK14: -0.080202198 | BL14: -0.046197941 | BM14: 0.0076363073 | BN14: 0.016316499 | BO14: -0.0071019015 | BP14: -0.021535508 | BQ14: 0.017405063 | BR14: 0.029237947 | BS14: -0.046579963 | BT14: 0.027107186 | BU14: 0.082602009 | BV14: 0.094726726 | BW14: 0.0030789979 | BX14: 0.14434063 | BY14: 0.0030789979 | BZ14: 0.0030789979 | CA14: 0.0030789979 | CB14: 0.0030789979 | CC14: 0.06207665 | CD14: 0.0030789979 | CE14: 0.0030789979 | CF14: 0.0030789979 | CG14: 0.0030789979 | CH14: 0.24583935 | CI14: 0.0030789979 | CJ14: 0.0030789979 | CK14: 0.0030789979 | CL14: 0.0030789979 | CM14: 0.012050932 | CN14: 0.0030789979 | CO14: 0.0030789979 | CP14: 0.0030789979 | CQ14: 0.0030789979 | CR14: 0.14886358 | CS14: 0.0030789979 | CT14: 0.0030789979 | CU14: 0.0030789979 | CV14: 0.0030789979 | CW14: -0.07025257 | CX14: 0.0030789979 | CY14: 0.0030789979 | CZ14: 0.0030789979 | DA14: 0.0030789979 | DB14: -0.069280557 | DC14: 0.0030789979 | DD14: 0.0030789979 | DE14: 0.0030789979 | DF14: 0.0030789979 | DG14: 0.17721138 | DH14: 0.0030789979 | DI14: 0.0030789979 | DJ14: 0.0030789979 | DK14: 0.0030789979 | DL14: -0.040384455 | DM14: 0.0030789979 | DN14: 0.0030789979 | DO14: 0.0030789979 | DP14: 0.0030789979 | DQ14: 0.019555417 | DR14: 0.0030789979 | DS14: 0.0030789979 | DT14: 0.0030789979 | DU14: 0.0030789979 | DV14: 0.019555417 | DW14: 0.0030789979 | DX14: 0.0030789979 | DY14: 0.0030789979 | DZ14: 0.0030789979 | EA14: 0.019555417 | EB14: 0.0030789979 | EC14: 0.0030789979 | ED14: 0.0030789979 | EE14: 0.0030789979 | EF14: 0.019555417
A15: IGP-M | B15: 0.027238816 | C15: 0.039508457 | D15: 0.032535493 | E15: 0.019621757 | F15: 0.12419987 | G15: 0.015470449 | H15: 0.0019530032 | I15: -0.015125547 | J15: 0.0099229976 | K15: 0.012007603 | L15: 0.0069795279 | M15: 0.0070809203 | N15: 0.0084226293 | O15: 0.015474403 | P15: 0.03847626 | Q15: 0.011139726 | R15: 0.0034022404 | S15: 0.025690334 | T15: 0.035379965 | U15: 0.077462737 | V15: 0.023778077 | W15: 0.04336869 | X15: 0.015459458 | Y15: 0.012319512 | Z15: 0.098054313 | AA15: -0.0091980353 | AB15: -0.0031967511 | AC15: -0.003717635 | AD15: -0.0011034013 | AE15: -0.017122754 | AF15: 0.027745179 | AG15: 0.028359009 | AH15: 0.020817483 | AI15: 0.031817201 | AJ15: 0.113 | AK15: 0.024312626 | AL15: 0.0069680368 | AM15: 0.0097144444 | AN15: 0.0091198891 | AO15: 0.05096813 | AP15: 0.0061573961 | AQ15: 0.025570914 | AR15: 0.037862169 | AS15: 0.0066992596 | AT15: 0.0782 | AU15: 0.0084 | AV15: 0.009 | AW15: 0.0192 | AX15: 0.0176 | AY15: 0.055 | AZ15: 0.025462165 | BA15: 0 | BB15: 0.014 | BC15: 0.012 | BD15: 0.0369 | BE15: 0.020221661 | BF15: 0.022654151 | BG15: 0.019311654 | BH15: 0.039455778 | BI15: 0.107 | BJ15: 0.029665632 | BK15: 0.028562255 | BL15: 0.0051997258 | BM15: 0.0067134119 | BN15: 0.071729083 | BO15: -0.0013025427 | BP15: -0.0013025427 | BQ15: -0.0013025427 | BR15: -0.0013025427 | BS15: -0.0052 | BT15: 0.018244601 | BU15: 0.018244601 | BV15: 0.018244601 | BW15: 0.018244601 | BX15: 0.075 | BY15: 0.017813112 | BZ15: 0.017813112 | CA15: 0.017813112 | CB15: 0.017813112 | CC15: 0.073179 | CD15: 0.053413777 | CE15: 0.053413777 | CF15: 0.053413777 | CG15: 0.053413777 | CH15: 0.231391 | CI15: 0.041760503 | CJ15: 0.041760503 | CK15: 0.041760503 | CL15: 0.041760503 | CM15: 0.1778 | CN15: 0.013355073 | CO15: 0.013355073 | CP15: 0.013355073 | CQ15: 0.013355073 | CR15: 0.0545 | CS15: -0.0080466017 | CT15: -0.0080466017 | CU15: -0.0080466017 | CV15: -0.0080466017 | CW15: -0.0318 | CX15: 0.015963658 | CY15: 0.015963658 | CZ15: 0.015963658 | DA15: 0.015963658 | DB15: 0.0654 | DC15: -0.0026353997 | DD15: -0.0026353997 | DE15: -0.0026353997 | DF15: -0.0026353997 | DG15: -0.0105 | DH15: 0.01106499 | DI15: 0.01106499 | DJ15: 0.01106499 | DK15: 0.01106499 | DL15: 0.045 | DM15: 0.01106499 | DN15: 0.01106499 | DO15: 0.01106499 | DP15: 0.01106499 | DQ15: 0.045 | DR15: 0.01106499 | DS15: 0.01106499 | DT15: 0.01106499 | DU15: 0.01106499 | DV15: 0.045 | DW15: 0.01106499 | DX15: 0.01106499 | DY15: 0.01106499 | DZ15: 0.01106499 | EA15: 0.045 | EB15: 0.01106499 | EC15: 0.01106499 | ED15: 0.01106499 | EE15: 0.01106499 | EF15: 0.045
A16: IPCA | B16: 0.018510968 | C16: 0.015981484 | D16: 0.019415797 | E16: 0.020027801 | F16: 0.076006441 | G16: 0.017905799 | H16: 0.013439901 | I16: 0.0077189649 | J16: 0.016688199 | K16: 0.056897333 | L16: 0.014367294 | M16: 0.00099558559 | N16: 0.004505992 | O16: 0.011240999 | P16: 0.03141775 | Q16: 0.012551992 | R16: 0.0081218596 | S16: 0.0089240803 | T16: 0.014261804 | U16: 0.044573304 | V16: 0.015176027 | W16: 0.020942932 | X16: 0.010735939 | Y16: 0.010938925 | Z16: 0.059023134 | AA16: 0.012347053 | AB16: 0.013156841 | AC16: 0.0063129686 | AD16: 0.010637052 | AE16: 0.043120283 | AF16: 0.020638364 | AG16: 0.01002451 | AH16: 0.0050022902 | AI16: 0.022262182 | AJ16: 0.0591 | AK16: 0.02439696 | AL16: 0.013956003 | AM16: 0.010634041 | AN16: 0.014569972 | AO16: 0.065033527 | AP16: 0.01224539 | AQ16: 0.0108289 | AR16: 0.01416561 | AS16: 0.01992 | AT16: 0.0584 | AU16: 0.019420463 | AV16: 0.011844323 | AW16: 0.0062 | AX16: 0.0204 | AY16: 0.059 | AZ16: 0.021752379 | BA16: 0.0154 | BB16: 0.0066 | BC16: 0.0191 | BD16: 0.0641 | BE16: 0.038277997 | BF16: 0.022567505 | BG16: 0.013859074 | BH16: 0.028159295 | BI16: 0.107 | BJ16: 0.026208101 | BK16: 0.017496397 | BL16: 0.010430578 | BM16: 0.007417894 | BN16: 0.062880551 | BO16: 0.0072947902 | BP16: 0.0072947902 | BQ16: 0.0072947902 | BR16: 0.0072947902 | BS16: 0.0295 | BT16: 0.0092459757 | BU16: 0.0092459757 | BV16: 0.0092459757 | BW16: 0.0092459757 | BX16: 0.0375 | BY16: 0.010605102 | BZ16: 0.010605102 | CA16: 0.010605102 | CB16: 0.010605102 | CC16: 0.0431 | CD16: 0.0066827131 | CE16: 0.0066827131 | CF16: 0.0066827131 | CG16: 0.0066827131 | CH16: 0.027 | CI16: 0.020133746 | CJ16: 0.020133746 | CK16: 0.020133746 | CL16: 0.020133746 | CM16: 0.083 | CN16: 0.014170922 | CO16: 0.014170922 | CP16: 0.014170922 | CQ16: 0.014170922 | CR16: 0.0579 | CS16: 0.011355123 | CT16: 0.011355123 | CU16: 0.011355123 | CV16: 0.011355123 | CW16: 0.0462 | CX16: 0.011862256 | CY16: 0.011862256 | CZ16: 0.011862256 | DA16: 0.011862256 | DB16: 0.0483 | DC16: 0.010483974 | DD16: 0.010483974 | DE16: 0.010483974 | DF16: 0.010483974 | DG16: 0.0426 | DH16: 0.0098534065 | DI16: 0.0098534065 | DJ16: 0.0098534065 | DK16: 0.0098534065 | DL16: 0.04 | DM16: 0.0098534065 | DN16: 0.0098534065 | DO16: 0.0098534065 | DP16: 0.0098534065 | DQ16: 0.04 | DR16: 0.0098534065 | DS16: 0.0098534065 | DT16: 0.0098534065 | DU16: 0.0098534065 | DV16: 0.04 | DW16: 0.0098534065 | DX16: 0.0098534065 | DY16: 0.0098534065 | DZ16: 0.0098534065 | EA16: 0.04 | EB16: 0.0098534065 | EC16: 0.0098534065 | ED16: 0.0098534065 | EE16: 0.0098534065 | EF16: 0.04
A17: CDI | B17: 0.15891187 | C17: 0.15435042 | D17: 0.16350861 | E17: 0.16948771 | F17: 0.16155114 | G17: 0.1778254 | H17: 0.19514372 | I17: 0.20317559 | J17: 0.1838907 | K17: 0.18996837 | L17: 0.17179576 | M17: 0.15115659 | N17: 0.14797492 | O17: 0.13084663 | P17: 0.15035162 | Q17: 0.12681933 | R17: 0.1205915 | S17: 0.11615637 | T17: 0.10910245 | U17: 0.11814874 | V17: 0.10734371 | W17: 0.11439214 | X17: 0.13443413 | Y17: 0.1393809 | Z17: 0.12380815 | AA17: 0.12058908 | AB17: 0.098592428 | AC17: 0.08990374 | AD17: 0.086015281 | AE17: 0.098694035 | AF17: 0.0875 | AG17: 0.0975 | AH17: 0.1075 | AI17: 0.1075 | AJ17: 0.1 | AK17: 0.11333333 | AL17: 0.12012097 | AM17: 0.12280769 | AN17: 0.11415385 | AO17: 0.11708333 | AP17: 0.1025 | AQ17: 0.086666667 | AR17: 0.076666667 | AS17: 0.0725 | AT17: 0.08458 | AU17: 0.0725 | AV17: 0.078333333 | AW17: 0.088333333 | AX17: 0.098333333 | AY17: 0.0844 | AZ17: 0.10666667 | BA17: 0.11 | BB17: 0.11 | BC17: 0.11 | BD17: 0.11020833 | BE17: 0.1225 | BF17: 0.1325 | BG17: 0.14 | BH17: 0.1425 | BI17: 0.13583333 | BJ17: 0.1425 | BK17: 0.1425 | BL17: 0.1425 | BM17: 0.14 | BN17: 0.14 | BO17: 0.13 | BP17: 0.1125 | BQ17: 0.095 | BR17: 0.07875 | BS17: 0.095625 | BT17: 0.069166667 | BU17: 0.0675 | BV17: 0.065833333 | BW17: 0.065 | BX17: 0.06625 | BY17: 0.0625 | BZ17: 0.0575 | CA17: 0.0525 | CB17: 0.0475 | CC17: 0.0525 | CD17: 0.04125 | CE17: 0.03375 | CF17: 0.02625 | CG17: 0.0225 | CH17: 0.028125 | CI17: 0.031875 | CJ17: 0.050625 | CK17: 0.069375 | CL17: 0.088125 | CM17: 0.069375 | CN17: 0.1075 | CO17: 0.125 | CP17: 0.135 | CQ17: 0.1375 | CR17: 0.13125 | CS17: 0.135 | CT17: 0.13 | CU17: 0.125 | CV17: 0.12 | CW17: 0.125 | CX17: 0.114375 | CY17: 0.108125 | CZ17: 0.10625 | DA17: 0.115 | DB17: 0.1115625 | DC17: 0.1325 | DD17: 0.14625 | DE17: 0.15 | DF17: 0.15 | DG17: 0.148125 | DH17: 0.1475 | DI17: 0.1425 | DJ17: 0.1375 | DK17: 0.1325 | DL17: 0.1375 | DM17: 0.13 | DN17: 0.13 | DO17: 0.13 | DP17: 0.13 | DQ17: 0.13 | DR17: 0.13 | DS17: 0.13 | DT17: 0.13 | DU17: 0.13 | DV17: 0.13 | DW17: 0.13 | DX17: 0.13 | DY17: 0.13 | DZ17: 0.13 | EA17: 0.13 | EB17: 0.13 | EC17: 0.13 | ED17: 0.13 | EE17: 0.13 | EF17: 0.13
B19: =#REF!+#REF!+#REF!+B15 -> #REF! | C19: =#REF!+#REF!+B15+C15 -> #REF! | D19: =#REF!+B15+C15+D15 -> #REF! | E19: =B15+C15+D15+E15 -> 0.11890452 | F19: =F15 -> 0.12419987 | G19: =C15+D15+E15+G15 -> 0.10713616 | H19: =D15+E15+G15+H15 -> 0.069580702 | I19: =E15+G15+H15+I15 -> 0.021919662 | J19: =G15+H15+I15+J15 -> 0.012220903 | K19: =K15 -> 0.012007603 | L19: =H15+I15+J15+L15 -> 0.0037299816 | M19: =I15+J15+L15+M15 -> 0.0088578987 | N19: =J15+L15+M15+N15 -> 0.032406075 | O19: =L15+M15+N15+O15 -> 0.03795748 | P19: =P15 -> 0.03847626 | Q19: =M15+N15+O15+Q15 -> 0.042117678 | R19: =N15+O15+Q15+R15 -> 0.038438998 | S19: =O15+Q15+R15+S15 -> 0.055706703 | T19: =Q15+R15+S15+T15 -> 0.075612265 | U19: =U15 -> 0.077462737 | V19: =R15+S15+T15+V15 -> 0.088250617 | W19: =S15+T15+V15+W15 -> 0.12821707 | X19: =T15+V15+W15+X15 -> 0.11798619 | Y19: =V15+W15+X15+Y15 -> 0.094925737 | Z19: =Z15 -> 0.098054313 | AA19: =W15+X15+Y15+AA15 -> 0.061949624 | AB19: =X15+Y15+AA15+AB15 -> 0.015384183 | AC19: =Y15+AA15+AB15+AC15 -> -0.0037929098 | AD19: =AA15+AB15+AC15+AD15 -> -0.017215823 | AE19: =AE15 -> -0.017122754 | AF19: =AB15+AC15+AD15+AF15 -> 0.019727391 | AG19: =AC15+AD15+AF15+AG15 -> 0.051283151 | AH19: =AD15+AF15+AG15+AH15 -> 0.075818269 | AI19: =AF15+AG15+AH15+AI15 -> 0.10873887 | AJ19: =AJ15 -> 0.113 | AK19: =AG15+AH15+AI15+AK15 -> 0.10530632 | AL19: =AH15+AI15+AK15+AL15 -> 0.083915347 | AM19: =AI15+AK15+AL15+AM15 -> 0.072812308 | AN19: =AK15+AL15+AM15+AN15 -> 0.050114997 | AO19: =AO15 -> 0.05096813 | AP19: =AL15+AM15+AN15+AP15 -> 0.031959766 | AQ19: =AM15+AN15+AP15+AQ15 -> 0.050562644 | AR19: =AN15+AP15+AQ15+AR15 -> 0.078710368 | AS19: =AP15+AQ15+AR15+AS15 -> 0.076289739 | AT19: =AT15 -> 0.0782 | AU19: =AQ15+AR15+AS15+AU15 -> 0.078532343 | AV19: =AR15+AS15+AU15+AV15 -> 0.061961428 | AW19: =AS15+AU15+AV15+AW15 -> 0.04329926 | AX19: =AU15+AV15+AW15+AX15 -> 0.0542 | AY19: =AY15 -> 0.055 | AZ19: =AV15+AW15+AX15+AZ15 -> 0.071262165 | BA19: =AW15+AX15+AZ15+BA15 -> 0.062262165 | BB19: =AX15+AZ15+BA15+BB15 -> 0.057062165 | BC19: =AZ15+BA15+BB15+BC15 -> 0.051462165 | BD19: =BD15 -> 0.0369 | BE19: =BA15+BB15+BC15+BE15 -> 0.046221661 | BF19: =BB15+BC15+BE15+BF15 -> 0.068875812 | BG19: =BC15+BE15+BF15+BG15 -> 0.074187466 | BH19: =BE15+BF15+BG15+BH15 -> 0.10164324 | BI19: =BI15 -> 0.107 | BJ19: =BF15+BG15+BH15+BJ15 -> 0.11108721 | BK19: =BG15+BH15+BJ15+BK15 -> 0.11699532 | BL19: =BH15+BJ15+BK15+BL15 -> 0.10288339 | BM19: =BJ15+BK15+BL15+BM15 -> 0.070141024 | BN19: =BN15 -> 0.071729083 | BO19: =BK15+BL15+BM15+BO15 -> 0.03917285 | BP19: =BL15+BM15+BO15+BP15 -> 0.0093080523 | BQ19: =BM15+BO15+BP15+BQ15 -> 0.0028057838 | BR19: =BO15+BP15+BQ15+BR15 -> -0.0052101709 | BS19: =BS15 -> -0.0052 | BT19: =BP15+BQ15+BR15+BT15 -> 0.014336973 | BU19: =BQ15+BR15+BT15+BU15 -> 0.033884117 | BV19: =BR15+BT15+BU15+BV15 -> 0.053431261 | BW19: =BT15+BU15+BV15+BW15 -> 0.072978404 | BX19: =BX15 -> 0.075 | BY19: =BU15+BV15+BW15+BY15 -> 0.072546915 | BZ19: =BV15+BW15+BY15+BZ15 -> 0.072115427 | CA19: =BW15+BY15+BZ15+CA15 -> 0.071683938 | CB19: =BY15+BZ15+CA15+CB15 -> 0.071252449 | CC19: =CC15 -> 0.073179 | CD19: =BZ15+CA15+CB15+CD15 -> 0.10685311 | CE19: =CA15+CB15+CD15+CE15 -> 0.14245378 | CF19: =CB15+CD15+CE15+CF15 -> 0.17805444 | CG19: =CD15+CE15+CF15+CG15 -> 0.21365511 | CH19: =CH15 -> 0.231391 | CI19: =CE15+CF15+CG15+CI15 -> 0.20200183 | CJ19: =CF15+CG15+CI15+CJ15 -> 0.19034856 | CK19: =CG15+CI15+CJ15+CK15 -> 0.17869528 | CL19: =CI15+CJ15+CK15+CL15 -> 0.16704201 | CM19: =CM15 -> 0.1778 | CN19: =CJ15+CK15+CL15+CN15 -> 0.13863658 | CO19: =CK15+CL15+CN15+CO15 -> 0.11023115 | CP19: =CL15+CN15+CO15+CP15 -> 0.081825722 | CQ19: =CN15+CO15+CP15+CQ15 -> 0.053420292 | CR19: =CR15 -> 0.0545 | CS19: =CO15+CP15+CQ15+CS15 -> 0.032018618 | CT19: =CP15+CQ15+CS15+CT15 -> 0.010616943 | CU19: =CQ15+CS15+CT15+CU15 -> -0.010784732 | CV19: =CS15+CT15+CU15+CV15 -> -0.032186407 | CW19: =CW15 -> -0.0318 | CX19: =CT15+CU15+CV15+CX15 -> -0.0081761472 | CY19: =CU15+CV15+CX15+CY15 -> 0.015834113 | CZ19: =CV15+CX15+CY15+CZ15 -> 0.039844372 | DA19: =CX15+CY15+CZ15+DA15 -> 0.063854632 | DB19: =DB15 -> 0.0654 | DC19: =CY15+CZ15+DA15+DC15 -> 0.045255574 | DD19: =CZ15+DA15+DC15+DD15 -> 0.026656517 | DE19: =DA15+DC15+DD15+DE15 -> 0.0080574589 | DF19: =DC15+DD15+DE15+DF15 -> -0.010541599 | DG19: =DG15 -> -0.0105 | DH19: =DD15+DE15+DF15+DH15 -> 0.0031587914 | DI19: =DE15+DF15+DH15+DI15 -> 0.016859182 | DJ19: =DF15+DH15+DI15+DJ15 -> 0.030559572 | DK19: =DH15+DI15+DJ15+DK15 -> 0.044259962 | DL19: =DL15 -> 0.045 | DM19: =DI15+DJ15+DK15+DM15 -> 0.044259962 | DN19: =DJ15+DK15+DM15+DN15 -> 0.044259962 | DO19: =DK15+DM15+DN15+DO15 -> 0.044259962 | DP19: =DM15+DN15+DO15+DP15 -> 0.044259962 | DQ19: =DQ15 -> 0.045 | DR19: =DN15+DO15+DP15+DR15 -> 0.044259962 | DS19: =DO15+DP15+DR15+DS15 -> 0.044259962 | DT19: =DP15+DR15+DS15+DT15 -> 0.044259962 | DU19: =DR15+DS15+DT15+DU15 -> 0.044259962 | DV19: =DV15 -> 0.045 | DW19: =DS15+DT15+DU15+DW15 -> 0.044259962 | DX19: =DT15+DU15+DW15+DX15 -> 0.044259962 | DY19: =DU15+DW15+DX15+DY15 -> 0.044259962 | DZ19: =DW15+DX15+DY15+DZ15 -> 0.044259962 | EA19: =EA15 -> 0.045 | EB19: =DX15+DY15+DZ15+EB15 -> 0.044259962 | EC19: =DY15+DZ15+EB15+EC15 -> 0.044259962 | ED19: =DZ15+EB15+EC15+ED15 -> 0.044259962 | EE19: =EB15+EC15+ED15+EE15 -> 0.044259962 | EF19: =EF15 -> 0.045

Sheet Income Statement
BS1: =48+16-31 -> 33 | DB1: =DB10/CW10-1 -> 0.27395993 | DG1: =DG10/DB10-1 -> 0.18301068
A2: =DCF!$A$2 -> Cyrela - TP: R$35 | U2: =U15/U10 -> 0.38877 | Z2: =Z15/Z10 -> 0.38019401 | AE2: =AE15/AE10 -> 0.34474421 | AJ2: =AJ15/AJ10 -> 0.31423252 | AK2: =AK15/AK10 -> 0.27375823 | AL2: =AL15/AL10 -> 0.27659298 | AM2: =AM15/AM10 -> 0.28594539 | AN2: =AN15/AN10 -> 0.29054933 | AO2: =AO15/AO10 -> 0.2829365 | AT2: =AT15/AT10 -> 0.32290354 | AW2: =AW15/AW10 -> 0.32790753 | AX2: =AX15/AX10 -> 0.32903727 | AY2: =AY15/AY10 -> 0.32749956 | AZ2: =AZ15/AZ10 -> 0.3327259 | BA2: =BA15/BA10 -> 0.33390389 | BB2: =BB15/BB10 -> 0.29914618 | BC2: =BC15/BC10 -> 0.32329024 | BD2: =BD15/BD10 -> 0.32120479 | ... EF2: =EF15/EF10 -> 0.32784266
B3: =Macro!B$3 -> 1Q04 | C3: =Macro!C$3 -> 2Q04 | D3: =Macro!D$3 -> 3Q04 | E3: =Macro!E$3 -> 4Q04 | F3: =Macro!F$3 -> 2004 | G3: =Macro!G$3 -> 1Q05 | H3: =Macro!H$3 -> 2Q05 | I3: =Macro!I$3 -> 3Q05 | ... EF3: =Macro!EF$3 -> 2030E
A4: Gross Revenues | B4: =B5+B6 -> 116483.5 | C4: =C5+C6 -> 116483.5 | D4: =D5+D6 -> 127779 | E4: =E5+E6 -> 196256 | F4: =SUM(B4:E4) -> 557002 | G4: =G5+G6 -> 178056 | H4: =H5+H6 -> 154333 | I4: =I5+I6 -> 263879 | J4: =J5+J6 -> 128931 | K4: =SUM(G4:J4) -> 725199 | L4: =L5+L6 -> 241448 | M4: =M5+M6 -> 275347 | N4: =N5+N6 -> 237808 | O4: =O5+O6 -> 402165 | P4: =SUM(L4:O4) -> 1156768 | Q4: =Q5+Q6 -> 299261 | R4: =R5+R6 -> 387298 | S4: =S5+S6 -> 431668 | T4: =T5+T6 -> 961212 | U4: =SUM(Q4:T4) -> 2079439 | V4: =V5+V6 -> 572579 | W4: =W5+W6 -> 830119 | X4: =X5+X6 -> 773992 | Y4: =Y5+Y6 -> 790759 | Z4: =SUM(V4:Y4) -> 2967449 | AA4: =AA5+AA6 -> 698996 | AB4: =AB5+AB6 -> 909715 | AC4: =AC5+AC6 -> 1396986 | AD4: =AD5+AD6 -> 1228296 | AE4: =SUM(AA4:AD4) -> 4233993 | AF4: =AF5+AF6 -> 1170169 | AG4: =AG5+AG6 -> 1234539 | AH4: =AH5+AH6 -> 1203539 | AI4: =AI5+AI6 -> 1445304 | AJ4: =SUM(AF4:AI4) -> 5053551 | AK4: =AK5+AK6 -> 1248883 | AL4: =AL5+AL6 -> 1438136 | AM4: =AM5+AM6 -> 1619390 | AN4: =AN5+AN6 -> 2069350 | AO4: =SUM(AK4:AN4) -> 6375759 | AP4: =AP5+AP6 -> 1522642 | AQ4: =AQ5+AQ6 -> 1438939 | AR4: =AR5+AR6 -> 1409120 | AS4: =AS5+AS6 -> 1432050 | AT4: =SUM(AP4:AS4) -> 5802751 | AU4: =AU5+AU6 -> 1250942 | AV4: =AV5+AV6 -> 1410150 | AW4: =AW5+AW6 -> 1435138 | AX4: =AX5+AX6 -> 1436106 | AY4: =SUM(AU4:AX4) -> 5532336 | AZ4: =AZ5+AZ6 -> 1351067 | BA4: =BA5+BA6 -> 1397217 | BB4: =BB5+BB6 -> 1628377 | BC4: =BC5+BC6 -> 1569902 | BD4: =SUM(AZ4:BC4) -> 5946563 | BE4: =BE5+BE6 -> 1068010 | BF4: =BF5+BF6 -> 1165862 | BG4: =BG5+BG6 -> 1172876 | BH4: =BH5+BH6 -> 1059054 | BI4: =SUM(BE4:BH4) -> 4465802 | BJ4: =BJ5+BJ6 -> 833226 | BK4: =BK5+BK6 -> 662190 | BL4: =BL5+BL6 -> 847384 | BM4: =BM5+BM6 -> 947904 | BN4: =SUM(BJ4:BM4) -> 3290704 | BO4: =BO5+BO6 -> 712412 | BP4: =BP5+BP6 -> 591107 | BQ4: =BQ5+BQ6 -> 614497 | BR4: =BR5+BR6 -> 831905 | BS4: =SUM(BO4:BR4) -> 2749921 | BT4: =BT5+BT6 -> 464152 | BU4: =BU5+BU6 -> 657521 | BV4: =BV5+BV6 -> 744589 | BW4: =BW5+BW6 -> 1111066 | BX4: =SUM(BT4:BW4) -> 2977328 | BY4: =BY5+BY6 -> 847909 | BZ4: =BZ5+BZ6 -> 959639 | CA4: =CA5+CA6 -> 959878 | CB4: =CB5+CB6 -> 1265292 | CC4: =SUM(BY4:CB4) -> 4032718 | CD4: =CD5+CD6 -> 785189 | CE4: =CE5+CE6 -> 860738 | CF4: =CF5+CF6 -> 1192465 | CG4: =CG5+CG6 -> 1087405 | CH4: =SUM(CD4:CG4) -> 3925797 | CI4: =CI5+CI6 -> 1030234 | CJ4: =CJ5+CJ6 -> 1213954 | CK4: =CK5+CK6 -> 1321796 | CL4: =CL5+CL6 -> 1351676 | CM4: =SUM(CI4:CL4) -> 4917660 | CN4: =CN5+CN6 -> 1259101 | CO4: =CO5+CO6 -> 1284091 | CP4: =CP5+CP6 -> 1600107 | CQ4: =CQ5+CQ6 -> 1412549 | CR4: =SUM(CN4:CQ4) -> 5555848 | CS4: =CS5+CS6 -> 1317322 | CT4: =CT5+CT6 -> 1678440 | CU4: =CU5+CU6 -> 1672991 | CV4: =CV5+CV6 -> 1760921 | CW4: =SUM(CS4:CV4) -> 6429674 | CX4: =CX5+CX6 -> 1614575 | CY4: =CY5+CY6 -> 1909290 | CZ4: =CZ5+CZ6 -> 2086805 | DA4: =DA5+DA6 -> 2574979 | DB4: =SUM(CX4:DA4) -> 8185649 | DC4: =DC5+DC6 -> 2003367 | DD4: =DD5+DD6 -> 2167903 | DE4: =DE5+DE6 -> 2191373 | DF4: =DF5+DF6 -> 3317082 | DG4: =SUM(DC4:DF4) -> 9679725 | DH4: =DH5+DH6 -> 2081306 | DI4: =DI5+DI6 -> 2548922 | DJ4: =DJ5+DJ6 -> 2779665.8 | DK4: =DK5+DK6 -> 3085867.8 | DL4: =SUM(DH4:DK4) -> 10495762 | DM4: =DM5+DM6 -> 2904177.2 | DN4: =DN5+DN6 -> 3030696.4 | DO4: =DO5+DO6 -> 3135918.4 | DP4: =DP5+DP6 -> 3413246 | DQ4: =SUM(DM4:DP4) -> 12484038 | DR4: =DR5+DR6 -> 3232579.8 | DS4: =DS5+DS6 -> 3342174.3 | DT4: =DT5+DT6 -> 3438345.6 | DU4: =DU5+DU6 -> 3716019 | DV4: =SUM(DR4:DU4) -> 13729119 | DW4: =DW5+DW6 -> 3508456.3 | DX4: =DX5+DX6 -> 3616040.7 | DY4: =DY5+DY6 -> 3707760.8 | DZ4: =DZ5+DZ6 -> 3991703.6 | EA4: =SUM(DW4:DZ4) -> 14823961 | EB4: =EB5+EB6 -> 3765591.1 | EC4: =EC5+EC6 -> 3873478.4 | ED4: =ED5+ED6 -> 3962578.6 | EE4: =EE5+EE6 -> 4251973.9 | EF4: =SUM(EB4:EE4) -> 15853622
A5: Development Sales | B5: =(482261+31373-SUM(D5:E5))/2 -> 105655 | C5: =B5 -> 105655 | D5: 113887 | E5: 188437 | F5: =SUM(B5:E5) -> 513634 | G5: 167756 | H5: 143200 | I5: 245810 | J5: 114407 | K5: =SUM(G5:J5) -> 671173 | L5: 227048 | M5: =481169-L5 -> 254121 | N5: =698102-SUM(L5:M5) -> 216933 | O5: =1082508-SUM(L5:N5) -> 384406 | P5: =SUM(L5:O5) -> 1082508 | Q5: 293395 | R5: =668065-Q5 -> 374670 | S5: 418305 | T5: =2021962+8363-SUM(Q5:S5) -> 943955 | U5: =SUM(Q5:T5) -> 2030325 | V5: =559757+3794 -> 563551 | W5: =818418+4241 -> 822659 | X5: =761546+4301 -> 765847 | Y5: =2907848+22974-SUM(V5:X5) -> 778765 | Z5: =SUM(V5:Y5) -> 2930822 | AA5: =685017+5225 -> 690242 | AB5: =887540+13379 -> 900919 | AC5: =1370602+13033 -> 1383635 | AD5: =1201078+16442 -> 1217520 | AE5: =SUM(AA5:AD5) -> 4192316 | AF5: =1140556+18091 -> 1158647 | AG5: =1191445+26952-AG34 -> 1218397 | AH5: =1171767+13862 -> 1185629 | AI5: =1407331+6543 -> 1413874 | AJ5: =SUM(AF5:AI5) -> 4976547 | AK5: =1216842+8949 -> 1225791 | AL5: =2625160+13076-AK5 -> 1412445 | AM5: =4207472+17666-AK5-AL5 -> 1586902 | AN5: =6240161+26490-AK5-AL5-AM5 -> 2041513 | AO5: =SUM(AK5:AN5) -> 6266651 | AP5: =2915251+4573-AQ5 -> 1505576 | AQ5: =1411422+2826 -> 1414248 | AR5: =1409120-AR6 -> 1394730 | AS5: =5701885+14069-AP5-AQ5-AR5 -> 1401400 | AT5: =SUM(AP5:AS5) -> 5715954 | AU5: =2603392+20342-AV5 -> 1233951 | AV5: =1382665+7118 -> 1389783 | AW5: =1435138-AW6 -> 1414214 | AX5: =5532336-SUM(AU5:AW5)-SUM(AU6:AX6) -> 1410416 | AY5: =SUM(AU5:AX5) -> 5448364 | AZ5: =1317983+17433 -> 1335416 | BA5: =1366342+14295 -> 1380637 | BB5: =1628377-BB6 -> 1607593 | BC5: =5946563-SUM(AZ5:BB5)-SUM(AZ6:BC6) -> 1558582 | BD5: =SUM(AZ5:BC5) -> 5882228 | BE5: =1031782+22263 -> 1054045 | BF5: =1141593+15312 -> 1156905 | BG5: =1172876-BG6 -> 1164221 | BH5: =4465802-SUM(BE5:BG5)-SUM(BE6:BH6) -> 1046063 | BI5: =SUM(BE5:BH5) -> 4421234 | BJ5: =799333+20950 -> 820283 | BK5: =614249+21481 -> 635730 | BL5: =847384-BL6 -> 839121 | BM5: =3290704-SUM(BJ5:BL5)-SUM(BJ6:BM6) -> 942441 | BN5: =SUM(BJ5:BM5) -> 3237575 | BO5: =678581+16224 -> 694805 | BP5: =573917+11356 -> 585273 | BQ5: =614497-BQ6 -> 608783 | BR5: =2671670+44168-SUM(BO5:BQ5) -> 826977 | BS5: =SUM(BO5:BR5) -> 2715838 | BT5: =445472+14559 -> 460031 | BU5: =638476+14319 -> 652795 | BV5: =728261+9518 -> 737779 | BW5: =3156039+51958-SUM(BT5:BV5)-254000 -> 1103392 | BX5: =SUM(BT5:BW5) -> 2953997 | BY5: =845764+11907-14195 -> 843476 | BZ5: =953167+9105-6610 -> 955662 | CA5: =901500+8113+41796 -> 951409 | CB5: =3867086+34904+105628-SUM(BY5:CA5) -> 1257071 | CC5: =SUM(BY5:CB5) -> 4007618 | CD5: =724852+9374+39479 -> 773705 | CE5: =826804+3845+16608 -> 847257 | CF5: =1153156+14847+6784 -> 1174787 | CG5: =3765116+41562+48464-SUM(CD5:CF5) -> 1059393 | CH5: =SUM(CD5:CG5) -> 3855142 | CI5: =1057818+20802-45161-24355 -> 1009104 | CJ5: =1193319+15809-12203-7752 -> 1189173 | CK5: =1288055+11945+2193-5203 -> 1296990 | CL5: =4851226+51769-62954-35986-SUM(CI5:CK5) -> 1308788 | CM5: =SUM(CI5:CL5) -> 4804055 | CN5: =1270338+6461-43143+5545 -> 1239201 | CO5: =1219902+10977+30436-6907 -> 1254408 | CP5: =1549256+2670+8131+9798 -> 1569855 | CQ5: =5440721+23045-15086+6545-SUM(CN5:CP5) -> 1391761 | CR5: =SUM(CN5:CQ5) -> 5455225 | CS5: =1323506+633-18150-4887 -> 1301102 | CT5: =2967331+1814-2630-7413-CS5 -> 1658000 | CU5: =4598860+2811+12432-3586-SUM(CS5:CT5) -> 1651415 | CV5: =6373445+3955-30135-3508-SUM(CS5:CU5) -> 1733240 | CW5: =SUM(CS5:CV5) -> 6343757 | CX5: =1644948+2568-46749-5947 -> 1594820 | CY5: =3509983+3638-29563-3531-CX5 -> 1885707 | CZ5: =5585280+2631-45676-236-SUM(CX5:CY5) -> 2061472 | DA5: =8201507+3951-109456-5895-SUM(CX5:CZ5) -> 2548108 | DB5: =SUM(CX5:DA5) -> 8090107 | DC5: =2074898+285-99013-914 -> 1975256 | DD5: =4146252+272-28621-1012-DC5 -> 2141635 | DE5: =6199476+66785+24246-10557-SUM(DC5:DD5) -> 2163059 | DF5: =9498874+90734-12130-9388-SUM(DC5:DE5) -> 3288140 | DG5: =SUM(DC5:DF5) -> 9568090 | DH5: =2110359+10713-68796-2191 -> 2050085 | DI5: =4601478+13577-56471-3916-DH5 -> 2504583 | DJ5: =Forecasts!DJ36 -> 2746705.3 | DK5: =Forecasts!DK36 -> 3049276.4 | DL5: =SUM(DH5:DK5) -> 10350650 | DM5: =Forecasts!DM36 -> 2875422.9 | DN5: =Forecasts!DN36 -> 3000689.5 | DO5: =Forecasts!DO36 -> 3104869.7 | DP5: =Forecasts!DP36 -> 3379451.4 | DQ5: =SUM(DM5:DP5) -> 12360434 | DR5: =Forecasts!DR36 -> 3200574.1 | DS5: =Forecasts!DS36 -> 3309083.4 | DT5: =Forecasts!DT36 -> 3404302.6 | DU5: =Forecasts!DU36 -> 3679226.7 | DV5: =SUM(DR5:DU5) -> 13593187 | DW5: =Forecasts!DW36 -> 3473719.1 | DX5: =Forecasts!DX36 -> 3580238.3 | DY5: =Forecasts!DY36 -> 3671050.3 | DZ5: =Forecasts!DZ36 -> 3952181.8 | EA5: =SUM(DW5:DZ5) -> 14677190 | EB5: =Forecasts!EB36 -> 3728308.1 | EC5: =Forecasts!EC36 -> 3835127.2 | ED5: =Forecasts!ED36 -> 3923345.2 | EE5: =Forecasts!EE36 -> 4209875.1 | EF5: =SUM(EB5:EE5) -> 15696656
A6: Services | B6: =(21672+14671+7025-SUM(D6:E6))/2 -> 10828.5 | C6: =B6 -> 10828.5 | D6: 13892 | E6: 7819 | F6: =SUM(B6:E6) -> 43368 | G6: 10300 | H6: 11133 | I6: 18069 | J6: 14524 | K6: =SUM(G6:J6) -> 54026 | L6: 14400 | M6: 21226 | N6: =40123+16378-SUM(L6:M6) -> 20875 | O6: =52423+21837-SUM(L6:N6) -> 17759 | P6: =SUM(L6:O6) -> 74260 | Q6: 5866 | R6: =18494-Q6 -> 12628 | S6: 13363 | T6: =16559+698 -> 17257 | U6: =SUM(Q6:T6) -> 49114 | V6: 9028 | W6: 7460 | X6: 8145 | Y6: =11994 -> 11994 | Z6: =SUM(V6:Y6) -> 36627 | AA6: 8754 | AB6: 8796 | AC6: 13351 | AD6: 10776 | AE6: =SUM(AA6:AD6) -> 41677 | AF6: 11522 | AG6: 16142 | AH6: 17910 | AI6: 31430 | AJ6: =SUM(AF6:AI6) -> 77004 | AK6: 23092 | AL6: =48783-AK6 -> 25691 | AM6: =81271-AK6-AL6 -> 32488 | AN6: =109108-AK6-AL6-AM6 -> 27837 | AO6: =SUM(AK6:AN6) -> 109108 | AP6: =41757-AQ6 -> 17066 | AQ6: 24691 | AR6: 14390 | AS6: =86797-AP6-AQ6-AR6 -> 30650 | AT6: =SUM(AP6:AS6) -> 86797 | AU6: =37358-AV6 -> 16991 | AV6: 20367 | AW6: 20924 | AX6: =83972-SUM(AU6:AW6) -> 25690 | AY6: =SUM(AU6:AX6) -> 83972 | AZ6: 15651 | BA6: 16580 | BB6: 20784 | BC6: =64335-SUM(AZ6:BB6) -> 11320 | BD6: =SUM(AZ6:BC6) -> 64335 | BE6: 13965 | BF6: 8957 | BG6: 8655 | BH6: =44568-SUM(BE6:BG6) -> 12991 | BI6: =SUM(BE6:BH6) -> 44568 | BJ6: 12943 | BK6: 26460 | BL6: 8263 | BM6: =53129-SUM(BJ6:BL6) -> 5463 | BN6: =SUM(BJ6:BM6) -> 53129 | BO6: 17607 | BP6: 5834 | BQ6: 5714 | BR6: =34083-SUM(BO6:BQ6) -> 4928 | BS6: =SUM(BO6:BR6) -> 34083 | BT6: 4121 | BU6: 4726 | BV6: 6810 | BW6: =23331-SUM(BT6:BV6) -> 7674 | BX6: =SUM(BT6:BW6) -> 23331 | BY6: 4433 | BZ6: 3977 | CA6: 8469 | CB6: =25100-SUM(BY6:CA6) -> 8221 | CC6: =SUM(BY6:CB6) -> 25100 | CD6: 11484 | CE6: 13481 | CF6: 17678 | CG6: =70655-SUM(CD6:CF6) -> 28012 | CH6: =SUM(CD6:CG6) -> 70655 | CI6: 21130 | CJ6: 24781 | CK6: 24806 | CL6: =113605-SUM(CI6:CK6) -> 42888 | CM6: =SUM(CI6:CL6) -> 113605 | CN6: 19900 | CO6: 29683 | CP6: 30252 | CQ6: =100623-SUM(CN6:CP6) -> 20788 | CR6: =SUM(CN6:CQ6) -> 100623 | CS6: 16220 | CT6: =36660-CS6 -> 20440 | CU6: =58236-SUM(CS6:CT6) -> 21576 | CV6: =85917-SUM(CS6:CU6) -> 27681 | CW6: =SUM(CS6:CV6) -> 85917 | CX6: 19755 | CY6: =43338-CX6 -> 23583 | CZ6: =68671-SUM(CX6:CY6) -> 25333 | DA6: =95542-SUM(CX6:CZ6) -> 26871 | DB6: =SUM(CX6:DA6) -> 95542 | DC6: 28111 | DD6: =54379-DC6 -> 26268 | DE6: =82693-SUM(DC6:DD6) -> 28314 | DF6: =111635-SUM(DC6:DE6) -> 28942 | DG6: =SUM(DC6:DF6) -> 111635 | DH6: 31221 | DI6: =75560-DH6 -> 44339 | DJ6: =Forecasts!DJ42 -> 32960.464 | DK6: =Forecasts!DK42 -> 36591.317 | DL6: =SUM(DH6:DK6) -> 145111.78 | DM6: =Forecasts!DM42 -> 28754.229 | DN6: =Forecasts!DN42 -> 30006.895 | DO6: =Forecasts!DO42 -> 31048.697 | DP6: =Forecasts!DP42 -> 33794.514 | DQ6: =SUM(DM6:DP6) -> 123604.34 | DR6: =Forecasts!DR42 -> 32005.741 | DS6: =Forecasts!DS42 -> 33090.834 | DT6: =Forecasts!DT42 -> 34043.026 | DU6: =Forecasts!DU42 -> 36792.267 | DV6: =SUM(DR6:DU6) -> 135931.87 | DW6: =Forecasts!DW42 -> 34737.191 | DX6: =Forecasts!DX42 -> 35802.383 | DY6: =Forecasts!DY42 -> 36710.503 | DZ6: =Forecasts!DZ42 -> 39521.818 | EA6: =SUM(DW6:DZ6) -> 146771.9 | EB6: =Forecasts!EB42 -> 37283.081 | EC6: =Forecasts!EC42 -> 38351.272 | ED6: =Forecasts!ED42 -> 39233.452 | EE6: =Forecasts!EE42 -> 42098.751 | EF6: =SUM(EB6:EE6) -> 156966.56
A7: Deductions | B7: =B8 -> -6878 | C7: =C8 -> -6878 | D7: =D8 -> -5069 | E7: =E8 -> -13740 | F7: =SUM(B7:E7) -> -32565 | G7: =G8 -> -7917 | H7: =H8 -> -11628 | I7: =I8 -> -10928 | J7: =J8 -> -5878 | K7: =SUM(G7:J7) -> -36351 | L7: =L8 -> -10369 | M7: =M8 -> -13345 | N7: =N8 -> -4993 | O7: =O8 -> -11380 | P7: =SUM(L7:O7) -> -40087 | Q7: =Q8 -> -11770 | R7: =R8 -> -16002 | S7: =S8 -> -16844 | T7: =T8 -> -36284 | U7: =SUM(Q7:T7) -> -80900 | V7: =V8 -> -21734 | W7: =W8 -> -35238 | X7: =X8 -> -23275 | Y7: =Y8 -> -39761 | Z7: =SUM(V7:Y7) -> -120008 | AA7: =AA8 -> -27542 | AB7: =AB8 -> -34115 | AC7: =AC8 -> -48118 | AD7: =AD8 -> -36393 | AE7: =SUM(AA7:AD7) -> -146168 | AF7: =AF8 -> -37721 | AG7: =AG8 -> -28704 | AH7: =AH8 -> -40990 | AI7: =AI8 -> -56031 | AJ7: =SUM(AF7:AI7) -> -163446 | AK7: =AK8 -> -48141 | AL7: =AL8 -> -55252 | AM7: =AM8 -> -59788 | AN7: =AN8 -> -85797 | AO7: =SUM(AK7:AN7) -> -248978 | AP7: =AP8 -> -56299 | AQ7: =AQ8 -> -53676 | AR7: =AR8 -> -59168 | AS7: =AS8 -> -929 | AT7: =SUM(AP7:AS7) -> -170072 | AU7: =AU8 -> -35572 | AV7: =AV8 -> -37731 | AW7: =AW8 -> -40690 | AX7: =AX8 -> -46461 | AY7: =SUM(AU7:AX7) -> -160454 | AZ7: =AZ8 -> -35705 | BA7: =BA8 -> -38886 | BB7: =BB8 -> -14681 | BC7: =BC8 -> -39364 | BD7: =SUM(AZ7:BC7) -> -128636 | BE7: =BE8 -> -32796 | BF7: =BF8 -> -28179 | BG7: =BG8 -> -35143 | BH7: =BH8 -> -28500 | BI7: =SUM(BE7:BH7) -> -124618 | BJ7: =BJ8 -> -22520 | BK7: =BK8 -> -21157 | BL7: =BL8 -> -22577 | BM7: =BM8 -> -29140 | BN7: =SUM(BJ7:BM7) -> -95394 | BO7: =BO8 -> -20025 | BP7: =BP8 -> -16351 | BQ7: =BQ8 -> -16670 | BR7: =BR8 -> -23105 | BS7: =SUM(BO7:BR7) -> -76151 | BT7: =BT8 -> -13530 | BU7: =BU8 -> -17982 | BV7: =BV8 -> -19764 | BW7: =BW8 -> -33895 | BX7: =SUM(BT7:BW7) -> -85171 | BY7: =BY8 -> -21673 | BZ7: =BZ8 -> -23017 | CA7: =CA8 -> -25119 | CB7: =CB8 -> -32086 | CC7: =SUM(BY7:CB7) -> -101895 | CD7: =CD8 -> -20434 | CE7: =CE8 -> -21930 | CF7: =CF8 -> -28962 | CG7: =CG8 -> -30775 | CH7: =SUM(CD7:CG7) -> -102101 | CI7: =CI8 -> -26502 | CJ7: =CJ8 -> -31935 | CK7: =CK8 -> -33457 | CL7: =CL8 -> -34933 | CM7: =SUM(CI7:CL7) -> -126827 | CN7: =CN8 -> -27449 | CO7: =CO8 -> -34008 | CP7: =CP8 -> -40463 | CQ7: =CQ8 -> -41633 | CR7: =SUM(CN7:CQ7) -> -143553 | CS7: =CS8 -> -33896 | CT7: =CT8 -> -45385 | CU7: =CU8 -> -47004 | CV7: =CV8 -> -50690 | CW7: =SUM(CS7:CV7) -> -176975 | CX7: =CX8 -> -41664 | CY7: =CY8 -> -52433 | CZ7: =CZ8 -> -57154 | DA7: =DA8 -> -68710 | DB7: =SUM(CX7:DA7) -> -219961 | DC7: =DC8 -> -50623 | DD7: =DD8 -> -60773 | DE7: =DE8 -> -62927 | DF7: =DF8 -> -81908 | DG7: =SUM(DC7:DF7) -> -256231 | DH7: =DH8 -> -56273 | DI7: =DI8 -> -68051 | DJ7: =DJ8 -> -70932.519 | DK7: =DK8 -> -75834.244 | DL7: =SUM(DH7:DK7) -> -271090.76 | DM7: =DM8 -> -60406.885 | DN7: =DN8 -> -63038.485 | DO7: =DO8 -> -65227.103 | DP7: =DP8 -> -70995.516 | DQ7: =SUM(DM7:DP7) -> -259667.99 | DR7: =DR8 -> -67237.66 | DS7: =DS8 -> -69517.225 | DT7: =DT8 -> -71517.589 | DU7: =DU8 -> -77293.195 | DV7: =SUM(DR7:DU7) -> -285565.67 | DW7: =DW8 -> -72975.892 | DX7: =DX8 -> -75213.646 | DY7: =DY8 -> -77121.426 | DZ7: =DZ8 -> -83027.435 | EA7: =SUM(DW7:DZ7) -> -308338.4 | EB7: =EB8 -> -78324.296 | EC7: =EC8 -> -80568.351 | ED7: =ED8 -> -82421.635 | EE7: =EE8 -> -88441.057 | EF7: =SUM(EB7:EE7) -> -329755.34
A8: Taxes and other deductions | B8: =(-18825-SUM(D8))/2 -> -6878 | C8: =B8 -> -6878 | D8: -5069 | E8: -13740 | F8: =SUM(B8:E8) -> -32565 | G8: =-7917 -> -7917 | H8: =-11628 -> -11628 | I8: =-10928 -> -10928 | J8: =-5878 -> -5878 | K8: =SUM(G8:J8) -> -36351 | L8: =-10369 -> -10369 | M8: =-13345 -> -13345 | N8: =-28707-L8-M8 -> -4993 | O8: =-40087-SUM(L8:N8) -> -11380 | P8: =SUM(L8:O8) -> -40087 | Q8: -11770 | R8: =-27772-Q8 -> -16002 | S8: -16844 | T8: =-80900-SUM(Q8:S8) -> -36284 | U8: =SUM(Q8:T8) -> -80900 | V8: -21734 | W8: -35238 | X8: -23275 | Y8: =-120008-SUM(V8:X8) -> -39761 | Z8: =SUM(V8:Y8) -> -120008 | AA8: -27542 | AB8: -34115 | AC8: -48118 | AD8: -36393 | AE8: =SUM(AA8:AD8) -> -146168 | AF8: -37721 | AG8: -28704 | AH8: -40990 | AI8: -56031 | AJ8: =SUM(AF8:AI8) -> -163446 | AK8: -48141 | AL8: =-103393-AK8 -> -55252 | AM8: =-163181-AK8-AL8 -> -59788 | AN8: =-248978-AK8-AL8-AM8 -> -85797 | AO8: =SUM(AK8:AN8) -> -248978 | AP8: =-109975-AQ8 -> -56299 | AQ8: -53676 | AR8: -59168 | AS8: =-170072-AP8-AQ8-AR8 -> -929 | AT8: =SUM(AP8:AS8) -> -170072 | AU8: =-73303-AV8 -> -35572 | AV8: -37731 | AW8: -40690 | AX8: =-160454-SUM(AU8:AW8) -> -46461 | AY8: =SUM(AU8:AX8) -> -160454 | AZ8: -35705 | BA8: -38886 | BB8: -14681 | BC8: =-128636-SUM(AZ8:BB8) -> -39364 | BD8: =SUM(AZ8:BC8) -> -128636 | BE8: -32796 | BF8: -28179 | BG8: -35143 | BH8: =-124618-SUM(BE8:BG8) -> -28500 | BI8: =SUM(BE8:BH8) -> -124618 | BJ8: -22520 | BK8: -21157 | BL8: -22577 | BM8: =-95394-SUM(BJ8:BL8) -> -29140 | BN8: =SUM(BJ8:BM8) -> -95394 | BO8: -20025 | BP8: -16351 | BQ8: -16670 | BR8: =-76151-SUM(BO8:BQ8) -> -23105 | BS8: =SUM(BO8:BR8) -> -76151 | BT8: -13530 | BU8: -17982 | BV8: -19764 | BW8: =-85171-SUM(BT8:BV8) -> -33895 | BX8: =SUM(BT8:BW8) -> -85171 | BY8: -21673 | BZ8: -23017 | CA8: -25119 | CB8: =-101895-SUM(BY8:CA8) -> -32086 | CC8: =SUM(BY8:CB8) -> -101895 | CD8: -20434 | CE8: -21930 | CF8: -28962 | CG8: =-102101-SUM(CD8:CF8) -> -30775 | CH8: =SUM(CD8:CG8) -> -102101 | CI8: -26502 | CJ8: -31935 | CK8: -33457 | CL8: =-126827-SUM(CI8:CK8) -> -34933 | CM8: =SUM(CI8:CL8) -> -126827 | CN8: -27449 | CO8: -34008 | CP8: -40463 | CQ8: =-143553-SUM(CN8:CP8) -> -41633 | CR8: =SUM(CN8:CQ8) -> -143553 | CS8: -33896 | CT8: =-79281-CS8 -> -45385 | CU8: =-126285-SUM(CS8:CT8) -> -47004 | CV8: =-176975-SUM(CS8:CU8) -> -50690 | CW8: =SUM(CS8:CV8) -> -176975 | CX8: -41664 | CY8: =-94097-CX8 -> -52433 | CZ8: =-151251-SUM(CX8:CY8) -> -57154 | DA8: =-219961-SUM(CX8:CZ8) -> -68710 | DB8: =SUM(CX8:DA8) -> -219961 | DC8: -50623 | DD8: =-111396-DC8 -> -60773 | DE8: =-174323-SUM(DC8:DD8) -> -62927 | DF8: =-256231-SUM(DC8:DE8) -> -81908 | DG8: =SUM(DC8:DF8) -> -256231 | DH8: -56273 | DI8: =-124324-DH8 -> -68051 | DJ8: =-DJ9*DJ$4 -> -70932.519 | DK8: =-DK9*DK$4 -> -75834.244 | DL8: =SUM(DH8:DK8) -> -271090.76 | DM8: =-DM9*DM$4 -> -60406.885 | DN8: =-DN9*DN$4 -> -63038.485 | DO8: =-DO9*DO$4 -> -65227.103 | DP8: =-DP9*DP$4 -> -70995.516 | DQ8: =SUM(DM8:DP8) -> -259667.99 | DR8: =-DR9*DR$4 -> -67237.66 | DS8: =-DS9*DS$4 -> -69517.225 | DT8: =-DT9*DT$4 -> -71517.589 | DU8: =-DU9*DU$4 -> -77293.195 | DV8: =SUM(DR8:DU8) -> -285565.67 | DW8: =-DW9*DW$4 -> -72975.892 | DX8: =-DX9*DX$4 -> -75213.646 | DY8: =-DY9*DY$4 -> -77121.426 | DZ8: =-DZ9*DZ$4 -> -83027.435 | EA8: =SUM(DW8:DZ8) -> -308338.4 | EB8: =-EB9*EB$4 -> -78324.296 | EC8: =-EC9*EC$4 -> -80568.351 | ED8: =-ED9*ED$4 -> -82421.635 | EE8: =-EE9*EE$4 -> -88441.057 | EF8: =SUM(EB8:EE8) -> -329755.34
A9: % of Gross Revenues | B9: =-B8/B$4 -> 0.059046989 | C9: =-C8/C$4 -> 0.059046989 | D9: =-D8/D$4 -> 0.039670055 | E9: =-E8/E$4 -> 0.070010598 | F9: =-F8/F$4 -> 0.058464781 | G9: =-G8/G$4 -> 0.04446354 | H9: =-H8/H$4 -> 0.075343575 | I9: =-I8/I$4 -> 0.04141292 | ... DI9: =-DI8/DI$4 -> 0.026697953 | DJ9: =DI9*80%+20%*2.08% -> 0.025518362 | DK9: =DJ9*80%+20%*2.08% -> 0.02457469 | DL9: =-DL8/DL$4 -> 0.025828594 | DM9: 0.0208 | DN9: =DM9 -> 0.0208 | DO9: =DN9 -> 0.0208 | DP9: =DO9 -> 0.0208 | DQ9: =-DQ8/DQ$4 -> 0.0208 | DR9: =DP9 -> 0.0208 | DS9: =DR9 -> 0.0208 | DT9: =DS9 -> 0.0208 | DU9: =DT9 -> 0.0208 | DV9: =-DV8/DV$4 -> 0.0208 | DW9: =DU9 -> 0.0208 | DX9: =DW9 -> 0.0208 | DY9: =DX9 -> 0.0208 | DZ9: =DY9 -> 0.0208 | EA9: =-EA8/EA$4 -> 0.0208 | EB9: =DZ9 -> 0.0208 | EC9: =EB9 -> 0.0208 | ED9: =EC9 -> 0.0208 | EE9: =ED9 -> 0.0208 | EF9: =-EF8/EF$4 -> 0.0208
A10: Net Revenues | B10: =B4+B7 -> 109605.5 | C10: =C4+C7 -> 109605.5 | D10: =D4+D7 -> 122710 | E10: =E4+E7 -> 182516 | F10: =SUM(B10:E10) -> 524437 | G10: =G4+G7 -> 170139 | H10: =H4+H7 -> 142705 | I10: =I4+I7 -> 252951 | J10: =J4+J7 -> 123053 | K10: =SUM(G10:J10) -> 688848 | L10: =L4+L7 -> 231079 | M10: =M4+M7 -> 262002 | N10: =N4+N7 -> 232815 | O10: =O4+O7 -> 390785 | P10: =SUM(L10:O10) -> 1116681 | Q10: =Q4+Q7 -> 287491 | R10: =R4+R7 -> 371296 | S10: =S4+S7 -> 414824 | T10: =T4+T7 -> 924928 | U10: =SUM(Q10:T10) -> 1998539 | V10: =V4+V7 -> 550845 | W10: =W4+W7 -> 794881 | X10: =X4+X7 -> 750717 | Y10: =Y4+Y7 -> 750998 | Z10: =SUM(V10:Y10) -> 2847441 | AA10: =AA4+AA7 -> 671454 | AB10: =AB4+AB7 -> 875600 | AC10: =AC4+AC7 -> 1348868 | AD10: =AD4+AD7 -> 1191903 | AE10: =SUM(AA10:AD10) -> 4087825 | AF10: =AF4+AF7 -> 1132448 | AG10: =AG4+AG7 -> 1205835 | AH10: =AH4+AH7 -> 1162549 | AI10: =AI4+AI7 -> 1389273 | AJ10: =SUM(AF10:AI10) -> 4890105 | AK10: =AK4+AK7 -> 1200742 | AL10: =AL4+AL7 -> 1382884 | AM10: =AM4+AM7 -> 1559602 | AN10: =AN4+AN7 -> 1983553 | AO10: =SUM(AK10:AN10) -> 6126781 | AP10: =AP4+AP7 -> 1466343 | AQ10: =AQ4+AQ7 -> 1385263 | AR10: =AR4+AR7 -> 1349952 | AS10: =AS4+AS7 -> 1431121 | AT10: =SUM(AP10:AS10) -> 5632679 | AU10: =AU4+AU7 -> 1215370 | AV10: =AV4+AV7 -> 1372419 | AW10: =AW4+AW7 -> 1394448 | AX10: =AX4+AX7 -> 1389645 | AY10: =SUM(AU10:AX10) -> 5371882 | AZ10: =AZ4+AZ7 -> 1315362 | BA10: =BA4+BA7 -> 1358331 | BB10: =BB4+BB7 -> 1613696 | BC10: =BC4+BC7 -> 1530538 | BD10: =SUM(AZ10:BC10) -> 5817927 | BE10: =BE4+BE7 -> 1035214 | BF10: =BF4+BF7 -> 1137683 | BG10: =BG4+BG7 -> 1137733 | BH10: =BH4+BH7 -> 1030554 | BI10: =SUM(BE10:BH10) -> 4341184 | BJ10: =BJ4+BJ7 -> 810706 | BK10: =BK4+BK7 -> 641033 | BL10: =BL4+BL7 -> 824807 | BM10: =BM4+BM7 -> 918764 | BN10: =SUM(BJ10:BM10) -> 3195310 | BO10: =BO4+BO7 -> 692387 | BP10: =BP4+BP7 -> 574756 | BQ10: =BQ4+BQ7 -> 597827 | BR10: =BR4+BR7 -> 808800 | BS10: =SUM(BO10:BR10) -> 2673770 | BT10: =BT4+BT7 -> 450622 | BU10: =BU4+BU7 -> 639539 | BV10: =BV4+BV7 -> 724825 | BW10: =BW4+BW7 -> 1077171 | BX10: =SUM(BT10:BW10) -> 2892157 | BY10: =BY4+BY7 -> 826236 | BZ10: =BZ4+BZ7 -> 936622 | CA10: =CA4+CA7 -> 934759 | CB10: =CB4+CB7 -> 1233206 | CC10: =SUM(BY10:CB10) -> 3930823 | CD10: =CD4+CD7 -> 764755 | CE10: =CE4+CE7 -> 838808 | CF10: =CF4+CF7 -> 1163503 | CG10: =CG4+CG7 -> 1056630 | CH10: =SUM(CD10:CG10) -> 3823696 | CI10: =CI4+CI7 -> 1003732 | CJ10: =CJ4+CJ7 -> 1182019 | CK10: =CK4+CK7 -> 1288339 | CL10: =CL4+CL7 -> 1316743 | CM10: =SUM(CI10:CL10) -> 4790833 | CN10: =CN4+CN7 -> 1231652 | CO10: =CO4+CO7 -> 1250083 | CP10: =CP4+CP7 -> 1559644 | CQ10: =CQ4+CQ7 -> 1370916 | CR10: =SUM(CN10:CQ10) -> 5412295 | CS10: =CS4+CS7 -> 1283426 | CT10: =CT4+CT7 -> 1633055 | CU10: =CU4+CU7 -> 1625987 | CV10: =CV4+CV7 -> 1710231 | CW10: =SUM(CS10:CV10) -> 6252699 | CX10: =CX4+CX7 -> 1572911 | CY10: =CY4+CY7 -> 1856857 | CZ10: =CZ4+CZ7 -> 2029651 | DA10: =DA4+DA7 -> 2506269 | DB10: =SUM(CX10:DA10) -> 7965688 | DC10: =DC4+DC7 -> 1952744 | DD10: =DD4+DD7 -> 2107130 | DE10: =DE4+DE7 -> 2128446 | DF10: =DF4+DF7 -> 3235174 | DG10: =SUM(DC10:DF10) -> 9423494 | DH10: =DH4+DH7 -> 2025033 | DI10: =DI4+DI7 -> 2480871 | DJ10: =DJ4+DJ7 -> 2708733.3 | DK10: =DK4+DK7 -> 3010033.5 | DL10: =SUM(DH10:DK10) -> 10224671 | DM10: =DM4+DM7 -> 2843770.3 | DN10: =DN4+DN7 -> 2967657.9 | DO10: =DO4+DO7 -> 3070691.3 | DP10: =DP4+DP7 -> 3342250.4 | DQ10: =SUM(DM10:DP10) -> 12224370 | DR10: =DR4+DR7 -> 3165342.2 | DS10: =DS4+DS7 -> 3272657 | DT10: =DT4+DT7 -> 3366828 | DU10: =DU4+DU7 -> 3638725.8 | DV10: =SUM(DR10:DU10) -> 13443553 | DW10: =DW4+DW7 -> 3435480.4 | DX10: =DX4+DX7 -> 3540827 | DY10: =DY4+DY7 -> 3630639.4 | DZ10: =DZ4+DZ7 -> 3908676.2 | EA10: =SUM(DW10:DZ10) -> 14515623 | EB10: =EB4+EB7 -> 3687266.9 | EC10: =EC4+EC7 -> 3792910.1 | ED10: =ED4+ED7 -> 3880157 | EE10: =EE4+EE7 -> 4163532.8 | EF10: =SUM(EB10:EE10) -> 15523867
A11: Operating Costs | B11: =B12+B14 -> -64466.5 | C11: =C12+C14 -> -64466.5 | D11: =D12+D14 -> -69814 | E11: =E12+E14 -> -113127 | F11: =SUM(B11:E11) -> -311874 | G11: =G12+G14 -> -87174 | H11: =H12+H14 -> -72047 | I11: =I12+I14 -> -132097 | J11: =J12+J14 -> -78930 | K11: =SUM(G11:J11) -> -370248 | L11: =L12+L14 -> -127839 | M11: =M12+M14 -> -146442 | N11: =N12+N14 -> -133680 | O11: =O12+O14 -> -237213 | P11: =SUM(L11:O11) -> -645174 | Q11: =Q12+Q13+Q14 -> -175293 | R11: =R12+R13+R14 -> -214924 | S11: =S12+S13+S14 -> -234337 | T11: =T12+T13+T14 -> -597013 | U11: =SUM(Q11:T11) -> -1221567 | V11: =V12+V13+V14 -> -331341 | W11: =W12+W13+W14 -> -484092 | X11: =X12+X13+X14 -> -445046 | Y11: =Y12+Y13+Y14 -> -504382 | Z11: =SUM(V11:Y11) -> -1764861 | AA11: =AA12+AA13+AA14 -> -419369 | AB11: =AB12+AB13+AB14 -> -575732 | AC11: =AC12+AC13+AC14 -> -890296 | AD11: =AD12+AD13+AD14 -> -793174 | AE11: =SUM(AA11:AD11) -> -2678571 | AF11: =AF12+AF13+AF14 -> -737831 | AG11: =AG12+AG13+AG14 -> -812794 | AH11: =AH12+AH13+AH14 -> -753585 | AI11: =AI12+AI13+AI14 -> -1049265 | AJ11: =SUM(AF11:AI11) -> -3353475 | AK11: =AK12+AK13+AK14 -> -872029 | AL11: =AL12+AL13+AL14 -> -1000388 | AM11: =AM12+AM13+AM14 -> -1113641 | AN11: =AN12+AN13+AN14 -> -1407233 | AO11: =SUM(AK11:AN11) -> -4393291 | AP11: =AP12+AP13+AP14 -> -1006468 | AQ11: =AQ12+AQ13+AQ14 -> -973692 | AR11: =AR12+AR13+AR14 -> -921666 | AS11: =AS12+AS13+AS14 -> -912041 | AT11: =SUM(AP11:AS11) -> -3813867 | AU11: =AU12+AU13+AU14 -> -818350 | AV11: =AV12+AV13+AV14 -> -924645 | AW11: =AW12+AW13+AW14 -> -937198 | AX11: =AX12+AX13+AX14 -> -932400 | AY11: =SUM(AU11:AX11) -> -3612593 | AZ11: =AZ12+AZ13+AZ14 -> -877707 | BA11: =BA12+BA13+BA14 -> -904779 | BB11: =BB12+BB13+BB14 -> -1130965 | BC11: =BC12+BC13+BC14 -> -1035730 | BD11: =SUM(AZ11:BC11) -> -3949181 | BE11: =BE12+BE13+BE14 -> -674603 | BF11: =BF12+BF13+BF14 -> -738627 | BG11: =BG12+BG13+BG14 -> -743219 | BH11: =BH12+BH13+BH14 -> -681656 | BI11: =SUM(BE11:BH11) -> -2838105 | BJ11: =BJ12+BJ13+BJ14 -> -528445 | BK11: =BK12+BK13+BK14 -> -387103 | BL11: =BL12+BL13+BL14 -> -563386 | BM11: =BM12+BM13+BM14 -> -653853 | BN11: =SUM(BJ11:BM11) -> -2132787 | BO11: =BO12+BO13+BO14 -> -477370 | BP11: =BP12+BP13+BP14 -> -421167 | BQ11: =BQ12+BQ13+BQ14 -> -450495 | BR11: =BR12+BR13+BR14 -> -590225 | BS11: =SUM(BO11:BR11) -> -1939257 | BT11: =BT12+BT13+BT14 -> -325839 | BU11: =BU12+BU13+BU14 -> -468242 | BV11: =BV12+BV13+BV14 -> -520049 | BW11: =BW12+BW13+BW14 -> -763100 | BX11: =SUM(BT11:BW11) -> -2077230 | BY11: =BY12+BY13+BY14 -> -577347 | BZ11: =BZ12+BZ13+BZ14 -> -643662 | CA11: =CA12+CA13+CA14 -> -645832 | CB11: =CB12+CB13+CB14 -> -848268 | CC11: =SUM(BY11:CB11) -> -2715109 | CD11: =CD12+CD13+CD14 -> -503900 | CE11: =CE12+CE13+CE14 -> -563937 | CF11: =CF12+CF13+CF14 -> -784922 | CG11: =CG12+CG13+CG14 -> -720554 | CH11: =SUM(CD11:CG11) -> -2573313 | CI11: =CI12+CI13+CI14 -> -657192 | CJ11: =CJ12+CJ13+CJ14 -> -749735 | CK11: =CK12+CK13+CK14 -> -841443 | CL11: =CL12+CL13+CL14 -> -876643 | CM11: =SUM(CI11:CL11) -> -3125013 | CN11: =CN12+CN13+CN14 -> -848102 | CO11: =CO12+CO13+CO14 -> -858752 | CP11: =CP12+CP13+CP14 -> -1031260 | CQ11: =CQ12+CQ13+CQ14 -> -940219 | CR11: =SUM(CN11:CQ11) -> -3678333 | CS11: =CS12+CS13+CS14 -> -888959 | CT11: =CT12+CT13+CT14 -> -1105967 | CU11: =CU12+CU13+CU14 -> -1080523 | CV11: =CV12+CV13+CV14 -> -1133651 | CW11: =SUM(CS11:CV11) -> -4209100 | CX11: =CX12+CX13+CX14 -> -1079389 | CY11: =CY12+CY13+CY14 -> -1246830 | CZ11: =CZ12+CZ13+CZ14 -> -1353486 | DA11: =DA12+DA13+DA14 -> -1706118 | DB11: =SUM(CX11:DA11) -> -5385823 | DC11: =DC12+DC13+DC14 -> -1318405 | DD11: =DD12+DD13+DD14 -> -1417294 | DE11: =DE12+DE13+DE14 -> -1426032 | DF11: =DF12+DF13+DF14 -> -2191794 | DG11: =SUM(DC11:DF11) -> -6353525 | DH11: =DH12+DH13+DH14 -> -1359107 | DI11: =DI12+DI13+DI14 -> -1627952 | DJ11: =DJ12+DJ13+DJ14 -> -1809188.7 | DK11: =DK12+DK13+DK14 -> -2009620.2 | DL11: =SUM(DH11:DK11) -> -6805867.9 | DM11: =DM12+DM13+DM14 -> -1908132.4 | DN11: =DN12+DN13+DN14 -> -1992592.9 | DO11: =DO12+DO13+DO14 -> -2063564.2 | DP11: =DP12+DP13+DP14 -> -2248931.3 | DQ11: =SUM(DM11:DP11) -> -8213220.8 | DR11: =DR12+DR13+DR14 -> -2112861.3 | DS11: =DS12+DS13+DS14 -> -2186900.5 | DT11: =DT12+DT13+DT14 -> -2252333 | DU11: =DU12+DU13+DU14 -> -2438853.2 | DV11: =SUM(DR11:DU11) -> -8990947.9 | DW11: =DW12+DW13+DW14 -> -2301758.7 | DX11: =DX12+DX13+DX14 -> -2373919.7 | DY11: =DY12+DY13+DY14 -> -2435879.8 | DZ11: =DZ12+DZ13+DZ14 -> -2626631 | EA11: =SUM(DW11:DZ11) -> -9738189.2 | EB11: =EB12+EB13+EB14 -> -2476005.1 | EC11: =EC12+EC13+EC14 -> -2548062.8 | ED11: =ED12+ED13+ED14 -> -2607985.3 | EE11: =EE12+EE13+EE14 -> -2802427.8 | EF11: =SUM(EB11:EE11) -> -10434481
A12: Development Sales | B12: =(-186623-SUM(D12))/2 -> -61275.5 | C12: =B12 -> -61275.5 | D12: -64072 | E12: -116555 | F12: =SUM(B12:E12) -> -303178 | G12: -84233 | H12: -70640 | I12: -127457 | J12: -78478 | K12: =SUM(G12:J12) -> -360808 | L12: -123633 | M12: -144584 | N12: =-395386-L12-M12 -> -127169 | O12: =-629377-SUM(L12:N12) -> -233991 | P12: =SUM(L12:O12) -> -629377 | Q12: -170895 | R12: =-382018-Q12 -> -211123 | S12: -230348 | T12: =-1196492-5221-SUM(Q12:S12) -> -589347 | U12: =SUM(Q12:T12) -> -1201713 | V12: =-322348-2044-V13 -> -324392 | W12: =-476512-1933-W13 -> -478445 | X12: =-435700-2651-X13 -> -430268 | Y12: =-1723828-12725-SUM(V12:X13)-Y13 -> -487282 | Z12: =SUM(V12:Y12) -> -1720387 | AA12: =-410631-2752-AA13 -> -404214 | AB12: =-563157-6656-AB13 -> -558186 | AC12: =-872920-8462-AC13 -> -870439 | AD12: =-775381-10756-AD13 -> -777924 | AE12: =SUM(AA12:AD12) -> -2610763 | AF12: =-720668-8588-AF13 -> -719706 | AG12: =-788554-11417-AG13 -> -780649 | AH12: =-733569-6811-AH13 -> -723289 | AI12: =-1022857-6899-AI13 -> -979524 | AJ12: =SUM(AF12:AI12) -> -3203168 | AK12: =-872029-AK13-AK14 -> -814297 | AL12: =-1822675-11542-AK12-AK13-AL13 -> -938469 | AM12: =-2913877-14933-AK12-AL12-AK13-AL13-AM13 -> -1033848 | AN12: =-4307266-23111-AK12-AL12-AM12-SUM(AK13:AN13) -> -1351567 | AO12: =SUM(AK12:AN12) -> -4138181 | AP12: =-1948429-2281-AQ12-AP13-AQ13 -> -953589 | AQ12: =-954640-1681-AQ13 -> -920832 | AR12: =-921666-AR13-AR14 -> -869668 | AS12: =-3752076-7039-AP12-AQ12-AR12-SUM(AP13:AS13) -> -836719 | AT12: =SUM(AP12:AS12) -> -3580808 | AU12: =-1706950-9638-AV12-AU13-AV13 -> -776189 | AV12: =-906964-3456-AV13 -> -878136 | AW12: =-937198-AW13-AW14 -> -872421 | AX12: =-3612593-SUM(AU12:AW12)-SUM(AU13:AX13)-SUM(AU14:AX14) -> -840276 | AY12: =SUM(AU12:AX12) -> -3367022 | AZ12: =-860370-6154-AZ13 -> -817972 | BA12: =-888975-5318-BA13 -> -841556 | BB12: =-1130965-BB13-BB14 -> -1065415 | BC12: =-3949181-SUM(AZ12:BB12)-SUM(AZ13:BC13)-SUM(AZ14:BC14) -> -971255 | BD12: =SUM(AZ12:BC12) -> -3696198 | BE12: =-649099-14345-BE13 -> -619379 | BF12: =-723129-8237-BF13 -> -690531 | BG12: =-743219-BG13-BG14 -> -693061 | BH12: =-2838105-SUM(BE12:BG12)-SUM(BE13:BH13)-SUM(BE14:BH14) -> -628303 | BI12: =SUM(BE12:BH12) -> -2631274 | BJ12: =-508878-8982-BJ13 -> -467503 | BK12: =-355863-9166-BK13 -> -316982 | BL12: =-563386-BL13-BL14 -> -501053 | BM12: =-2132787-SUM(BJ12:BL12)-SUM(BJ13:BM13)-SUM(BJ14:BM14) -> -599914 | BN12: =SUM(BJ12:BM12) -> -1885452 | BO12: =-463095-6748-BO13 -> -424962 | BP12: =-410665-7135-BP13 -> -369701 | BQ12: =-450495-BQ13-BQ14 -> -407556 | BR12: =-1939257-SUM(BO12:BQ12)-SUM(BO13:BR13)-SUM(BO14:BR14) -> -545529 | BS12: =SUM(BO12:BR12) -> -1747748 | BT12: =-317073-6374-BT13 -> -297842 | BU12: =-458811-5796-BU13 -> -435627 | BV12: =-520049-BV13-BV14 -> -481284 | BW12: =-2311230-SUM(BT12:BV12)-SUM(BT13:BW13)-SUM(BT14:BW14)+167000+67000 -> -735041 | BX12: =SUM(BT12:BW12) -> -1949794 | BY12: =-577017-6070+10468-BY13 -> -548776 | BZ12: =-643682-5751+8996-BZ13 -> -622178 | CA12: =-608648-5030-30212-CA13 -> -623728 | CB12: =-2715109-SUM(BY12:CA12)-SUM(BY13:CB13)-SUM(BY14:CB14) -> -823979 | CC12: =SUM(BY12:CB12) -> -2618661 | CD12: =-469844-5517-24451-CD13 -> -488169 | CE12: =-535625-2042-12517-CE13 -> -533358 | CF12: =-756657-13129-6433-CF13 -> -757962 | CG12: =-2573313-SUM(CD12:CF12)-SUM(CD13:CG13)-SUM(CD14:CG14) -> -690696 | CH12: =SUM(CD12:CG12) -> -2470185 | CI12: =-668863-8491+32132-CI13 -> -636211 | CJ12: =-729733-9928+5283-CJ13 -> -724002 | CK12: =-812566-4618-2520-CK13 -> -808109 | CL12: =-3125013-SUM(CI12:CK12)-SUM(CI13:CL13)-SUM(CI14:CL14) -> -846902 | CM12: =SUM(CI12:CL12) -> -3015224 | CN12: =-852833-1569+23103-CN13 -> -815032 | CO12: =-815979-3365-16232-CO13 -> -816065 | CP12: =-1002666-736-5819-CP13 -> -986430 | CQ12: =-3678333-SUM(CN12:CP12)-SUM(CN13:CQ13)-SUM(CN14:CQ14) -> -902868 | CR12: =SUM(CN12:CQ12) -> -3520395 | CS12: =-888554-284+9962-CS13 -> -854201 | CT12: =-1979270-547+1850-SUM(CS13:CT13)-CS12 -> -1068710 | CU12: =-3045353-843-8169-SUM(CS13:CU13)-SUM(CS12:CT12) -> -1046397 | CV12: =-4209100-SUM(CS12:CU12)-SUM(CS13:CV13)-SUM(CS14:CV14) -> -1097346 | CW12: =SUM(CS12:CV12) -> -4066654 | CX12: =-1099469-734+32389-CX13 -> -1040695 | CY12: =-2326156-841+20515-SUM(CX13:CY13)-CX12 -> -1203470 | CZ12: =-3680152-480+29360-SUM(CX13:CZ13)-SUM(CX12:CY12) -> -1308936 | DA12: =-5385823-SUM(CX12:CZ12)-SUM(CX13:DA13)-SUM(CX14:DA14) -> -1662991 | DB12: =SUM(CX12:DA12) -> -5216092 | DC12: =-1371838+103+63476-DC13 -> -1271764 | DD12: =-2741584+532+19610-SUM(DC13:DD13)-DC12 -> -1367612 | DE12: =-4073434-55402-13316-SUM(DC13:DE13)-SUM(DC12:DD12) -> -1372087 | DF12: =-6353525-SUM(DC12:DE12)-SUM(DC13:DF13)-SUM(DC14:DF14) -> -2141389 | DG12: =SUM(DC12:DF12) -> -6152852 | DH12: =-1387597-7626+43725-DH13 -> -1286258 | DI12: =-2996523-10945+35263-SUM(DH13:DI13)-DH12 -> -1547952 | DJ12: =-(1-DJ71)*DJ5 -> -1755735.6 | DK12: =-(1-DK71)*DK5 -> -1949477.1 | DL12: =SUM(DH12:DK12) -> -6539422.6 | DM12: =-(1-DM71)*DM5 -> -1852418.9 | DN12: =-(1-DN71)*DN5 -> -1934687.4 | DO12: =-(1-DO71)*DO5 -> -2003196.5 | DP12: =-(1-DP71)*DP5 -> -2182436 | DQ12: =SUM(DM12:DP12) -> -7972738.8 | DR12: =-(1-DR71)*DR5 -> -2066866.6 | DS12: =-(1-DS71)*DS5 -> -2138152.7 | DT12: =-(1-DT71)*DT5 -> -2200739.3 | DU12: =-(1-DU71)*DU5 -> -2380093.9 | DV12: =SUM(DR12:DU12) -> -8785852.5 | DW12: =-(1-DW71)*DW5 -> -2247106.9 | DX12: =-(1-DX71)*DX5 -> -2316972.7 | DY12: =-(1-DY71)*DY5 -> -2376573.3 | DZ12: =-(1-DZ71)*DZ5 -> -2559844.3 | EA12: =SUM(DW12:DZ12) -> -9500497.2 | EB12: =-(1-EB71)*EB5 -> -2414809 | EC12: =-(1-EC71)*EC5 -> -2484749 | ED12: =-(1-ED71)*ED5 -> -2542551.9 | EE12: =-(1-EE71)*EE5 -> -2729226.5 | EF12: =SUM(EB12:EE12) -> -10171336
A13: Capitalized Interest | P13: =SUM(L13:O13) -> 0 | Q13: 0 | R13: 0 | S13: 0 | T13: 0 | U13: =SUM(Q13:T13) -> 0 | V13: 0 | W13: 0 | X13: =-16166/2 -> -8083 | Y13: =-16166-X13-W13-V13 -> -8083 | Z13: =SUM(V13:Y13) -> -16166 | AA13: -9169 | AB13: -11627 | AC13: =-31739-AA13-AB13 -> -10943 | AD13: =-39952-AC13-AB13-AA13 -> -8213 | AE13: =SUM(AA13:AD13) -> -39952 | AF13: -9550 | AG13: =-28872-AF13 -> -19322 | AH13: =-45963-AG13-AF13 -> -17091 | AI13: =-96195-AH13-AG13-AF13 -> -50232 | AJ13: =SUM(AF13:AI13) -> -96195 | AK13: -39087 | AL13: =-81451-AK13 -> -42364 | AM13: =-142196-AK13-AL13 -> -60745 | AN13: -50000 | AO13: =SUM(AK13:AN13) -> -192196 | AP13: =-76289-AQ13 -> -40800 | AQ13: -35489 | AR13: =-119322-AP13-AQ13 -> -43033 | AS13: =-178307-AP13-AQ13-AR13 -> -58985 | AT13: =SUM(AP13:AS13) -> -178307 | AU13: -29979 | AV13: =-62263-AU13 -> -32284 | AW13: =-112043-AU13-AV13 -> -49780 | AX13: =-186376-SUM(AU13:AW13) -> -74333 | AY13: =SUM(AU13:AX13) -> -186376 | AZ13: -48552 | BA13: =-101289-AZ13 -> -52737 | BB13: =-152526-AZ13-BA13 -> -51237 | BC13: =-207728-SUM(AZ13:BB13) -> -55202 | BD13: =SUM(AZ13:BC13) -> -207728 | BE13: -44065 | BF13: =-84900-BE13 -> -40835 | BG13: =-128001-BE13-BF13 -> -43101 | BH13: -43000 | BI13: =SUM(BE13:BH13) -> -171001 | BJ13: -50357 | BK13: =-98404-BJ13 -> -48047 | BL13: =-153560-BJ13-BK13 -> -55156 | BM13: =-202752-SUM(BJ13:BL13) -> -49192 | BN13: =SUM(BJ13:BM13) -> -202752 | BO13: -44881 | BP13: =-92980-BO13 -> -48099 | BQ13: =-132347-BO13-BP13 -> -39367 | BR13: =-173966-SUM(BO13:BQ13) -> -41619 | BS13: =SUM(BO13:BR13) -> -173966 | BT13: -25605 | BU13: =-54585-BT13 -> -28980 | BV13: =-87467-BT13-BU13 -> -32882 | BW13: -22250 | BX13: =SUM(BT13:BW13) -> -109717 | BY13: -23843 | BZ13: =-42102-BY13 -> -18259 | CA13: =-62264-BY13-BZ13 -> -20162 | CB13: =-81394-CA13-BZ13-BY13 -> -19130 | CC13: =SUM(BY13:CB13) -> -81394 | CD13: -11643 | CE13: =-28469-CD13 -> -16826 | CF13: =-46726-CD13-CE13 -> -18257 | CG13: =-67353-CF13-CE13-CD13 -> -20627 | CH13: =SUM(CD13:CG13) -> -67353 | CI13: -9011 | CJ13: =-19387-CI13 -> -10376 | CK13: =-30982-CI13-CJ13 -> -11595 | CL13: =-46249-CK13-CJ13-CI13 -> -15267 | CM13: =SUM(CI13:CL13) -> -46249 | CN13: -16267 | CO13: =-35778-CN13 -> -19511 | CP13: =-58569-CN13-CO13 -> -22791 | CQ13: =-82014-CP13-CO13-CN13 -> -23445 | CR13: =SUM(CN13:CQ13) -> -82014 | CS13: -24675 | CT13: =-55056-CS13 -> -30381 | CU13: =-85057-CS13-CT13 -> -30001 | CV13: =-114687-CU13-CT13-CS13 -> -29630 | CW13: =SUM(CS13:CV13) -> -114687 | CX13: -27119 | CY13: =-62317-CX13 -> -35198 | CZ13: =-98171-CX13-CY13 -> -35854 | DA13: =-133989-CZ13-CY13-CX13 -> -35818 | DB13: =SUM(CX13:DA13) -> -133989 | DC13: -36495 | DD13: =-82066-DC13 -> -45571 | DE13: =-130689-DC13-DD13 -> -48623 | DF13: =-178230-DE13-DD13-DC13 -> -47541 | DG13: =SUM(DC13:DF13) -> -178230 | DH13: -65240 | DI13: =-137995-DH13 -> -72755 | DJ13: =-('Balance Sheet'!DI133/(Forecasts!DI26+Forecasts!DI27))*Forecasts!DJ38-2%*Forecasts!DJ40 -> -45213.013 | DK13: =-('Balance Sheet'!DJ133/(Forecasts!DJ26+Forecasts!DJ27))*Forecasts!DK38-2%*Forecasts!DK40 -> -50995.302 | DL13: =SUM(DH13:DK13) -> -234203.32 | DM13: =-('Balance Sheet'!DL133/(Forecasts!DL26+Forecasts!DL27))*Forecasts!DM38-2%*Forecasts!DM40 -> -48524.95 | DN13: =-('Balance Sheet'!DM133/(Forecasts!DM26+Forecasts!DM27))*Forecasts!DN38-2%*Forecasts!DN40 -> -50403.716 | DO13: =-('Balance Sheet'!DN133/(Forecasts!DN26+Forecasts!DN27))*Forecasts!DO38-2%*Forecasts!DO40 -> -52605.523 | DP13: =-('Balance Sheet'!DO133/(Forecasts!DO26+Forecasts!DO27))*Forecasts!DP38-2%*Forecasts!DP40 -> -58046.732 | DQ13: =SUM(DM13:DP13) -> -209580.92 | DR13: =-('Balance Sheet'!DQ133/(Forecasts!DQ26+Forecasts!DQ27))*Forecasts!DR38-1%*Forecasts!DR40 -> -37993.341 | DS13: =-('Balance Sheet'!DR133/(Forecasts!DR26+Forecasts!DR27))*Forecasts!DS38-1%*Forecasts!DS40 -> -40475.077 | DT13: =-('Balance Sheet'!DS133/(Forecasts!DS26+Forecasts!DS27))*Forecasts!DT38-1%*Forecasts!DT40 -> -43082.917 | DU13: =-('Balance Sheet'!DT133/(Forecasts!DT26+Forecasts!DT27))*Forecasts!DU38-1%*Forecasts!DU40 -> -49561.148 | DV13: =SUM(DR13:DU13) -> -171112.48 | DW13: =-('Balance Sheet'!DV133/(Forecasts!DV26+Forecasts!DV27))*Forecasts!DW38-1%*Forecasts!DW40 -> -45967.496 | DX13: =-('Balance Sheet'!DW133/(Forecasts!DW26+Forecasts!DW27))*Forecasts!DX38-1%*Forecasts!DX40 -> -47996.427 | DY13: =-('Balance Sheet'!DX133/(Forecasts!DX26+Forecasts!DX27))*Forecasts!DY38-1%*Forecasts!DY40 -> -50128.854 | DZ13: =-('Balance Sheet'!DY133/(Forecasts!DY26+Forecasts!DY27))*Forecasts!DZ38-1%*Forecasts!DZ40 -> -56906.322 | EA13: =SUM(DW13:DZ13) -> -200999.1 | EB13: =-('Balance Sheet'!EA133/(Forecasts!EA26+Forecasts!EA27))*Forecasts!EB38-1%*Forecasts!EB40 -> -51875.341 | EC13: =-('Balance Sheet'!EB133/(Forecasts!EB26+Forecasts!EB27))*Forecasts!EC38-1%*Forecasts!EC40 -> -53725.986 | ED13: =-('Balance Sheet'!EC133/(Forecasts!EC26+Forecasts!EC27))*Forecasts!ED38-1%*Forecasts!ED40 -> -55624.983 | EE13: =-('Balance Sheet'!ED133/(Forecasts!ED26+Forecasts!ED27))*Forecasts!EE38-1%*Forecasts!EE40 -> -62676.55 | EF13: =SUM(EB13:EE13) -> -223902.86
A14: Services | B14: =(-12124-SUM(D14))/2 -> -3191 | C14: =B14 -> -3191 | D14: -5742 | E14: 3428 | F14: =SUM(B14:E14) -> -8696 | G14: -2941 | H14: -1407 | I14: -4640 | J14: -452 | K14: =SUM(G14:J14) -> -9440 | L14: -4206 | M14: -1858 | N14: =-12575-L14-M14 -> -6511 | O14: =-15797-SUM(L14:N14) -> -3222 | P14: =SUM(L14:O14) -> -15797 | Q14: -4398 | R14: =-8199-Q14 -> -3801 | S14: -3989 | T14: -7666 | U14: =SUM(Q14:T14) -> -19854 | V14: -6949 | W14: -5647 | X14: -6695 | Y14: -9017 | Z14: =SUM(V14:Y14) -> -28308 | AA14: -5986 | AB14: -5919 | AC14: -8914 | AD14: -7037 | AE14: =SUM(AA14:AD14) -> -27856 | AF14: -8575 | AG14: -12823 | AH14: -13205 | AI14: -19509 | AJ14: =SUM(AF14:AI14) -> -54112 | AK14: -18645 | AL14: =-38200-AK14 -> -19555 | AM14: =-57248-AK14-AL14 -> -19048 | AN14: =-62914-AK14-AL14-AM14 -> -5666 | AO14: =SUM(AK14:AN14) -> -62914 | AP14: =-29450-AQ14 -> -12079 | AQ14: -17371 | AR14: -8965 | AS14: =-54752-AP14-AQ14-AR14 -> -16337 | AT14: =SUM(AP14:AS14) -> -54752 | AU14: =-26407-AV14 -> -12182 | AV14: -14225 | AW14: -14997 | AX14: =-59195-SUM(AU14:AW14) -> -17791 | AY14: =SUM(AU14:AX14) -> -59195 | AZ14: -11183 | BA14: -10486 | BB14: -14313 | BC14: =-45255-SUM(AZ14:BB14) -> -9273 | BD14: =SUM(AZ14:BC14) -> -45255 | BE14: -11159 | BF14: -7261 | BG14: -7057 | BH14: =-35830-SUM(BE14:BG14) -> -10353 | BI14: =SUM(BE14:BH14) -> -35830 | BJ14: -10585 | BK14: -22074 | BL14: -7177 | BM14: =-44583-SUM(BJ14:BL14) -> -4747 | BN14: =SUM(BJ14:BM14) -> -44583 | BO14: -7527 | BP14: -3367 | BQ14: -3572 | BR14: =-17543-SUM(BO14:BQ14) -> -3077 | BS14: =SUM(BO14:BR14) -> -17543 | BT14: -2392 | BU14: -3635 | BV14: -5883 | BW14: =-17719-SUM(BT14:BV14) -> -5809 | BX14: =SUM(BT14:BW14) -> -17719 | BY14: -4728 | BZ14: -3225 | CA14: -1942 | CB14: =-15054-SUM(BY14:CA14) -> -5159 | CC14: =SUM(BY14:CB14) -> -15054 | CD14: -4088 | CE14: -13753 | CF14: -8703 | CG14: =-35775-SUM(CD14:CF14) -> -9231 | CH14: =SUM(CD14:CG14) -> -35775 | CI14: -11970 | CJ14: -15357 | CK14: -21739 | CL14: =-63540-SUM(CI14:CK14) -> -14474 | CM14: =SUM(CI14:CL14) -> -63540 | CN14: -16803 | CO14: -23176 | CP14: -22039 | CQ14: =-75924-SUM(CN14:CP14) -> -13906 | CR14: =SUM(CN14:CQ14) -> -75924 | CS14: -10083 | CT14: =-16959-CS14 -> -6876 | CU14: =-21084-SUM(CS14:CT14) -> -4125 | CV14: =-27759-SUM(CS14:CU14) -> -6675 | CW14: =SUM(CS14:CV14) -> -27759 | CX14: -11575 | CY14: =-19737-CX14 -> -8162 | CZ14: =-28433-SUM(CX14:CY14) -> -8696 | DA14: =-35742-SUM(CX14:CZ14) -> -7309 | DB14: =SUM(CX14:DA14) -> -35742 | DC14: -10146 | DD14: =-14257-DC14 -> -4111 | DE14: =-19579-SUM(DC14:DD14) -> -5322 | DF14: =-22443-SUM(DC14:DE14) -> -2864 | DG14: =SUM(DC14:DF14) -> -22443 | DH14: -7609 | DI14: =-14854-DH14 -> -7245 | DJ14: =-DJ6*(1-DJ72) -> -8240.116 | DK14: =-DK6*(1-DK72) -> -9147.8293 | DL14: =SUM(DH14:DK14) -> -32241.945 | DM14: =-DM6*(1-DM72) -> -7188.5573 | DN14: =-DN6*(1-DN72) -> -7501.7238 | DO14: =-DO6*(1-DO72) -> -7762.1743 | DP14: =-DP6*(1-DP72) -> -8448.6286 | DQ14: =SUM(DM14:DP14) -> -30901.084 | DR14: =-DR6*(1-DR72) -> -8001.4352 | DS14: =-DS6*(1-DS72) -> -8272.7086 | DT14: =-DT6*(1-DT72) -> -8510.7564 | DU14: =-DU6*(1-DU72) -> -9198.0669 | DV14: =SUM(DR14:DU14) -> -33982.967 | DW14: =-DW6*(1-DW72) -> -8684.2979 | DX14: =-DX6*(1-DX72) -> -8950.5957 | DY14: =-DY6*(1-DY72) -> -9177.6259 | DZ14: =-DZ6*(1-DZ72) -> -9880.4544 | EA14: =SUM(DW14:DZ14) -> -36692.974 | EB14: =-EB6*(1-EB72) -> -9320.7702 | EC14: =-EC6*(1-EC72) -> -9587.8179 | ED14: =-ED6*(1-ED72) -> -9808.3629 | EE14: =-EE6*(1-EE72) -> -10524.688 | EF14: =SUM(EB14:EE14) -> -39241.639
A15: Gross Profit | B15: =B10+B11 -> 45139 | C15: =C10+C11 -> 45139 | D15: =D10+D11 -> 52896 | E15: =E10+E11 -> 69389 | F15: =SUM(B15:E15) -> 212563 | G15: =G10+G11 -> 82965 | H15: =H10+H11 -> 70658 | I15: =I10+I11 -> 120854 | J15: =J10+J11 -> 44123 | K15: =SUM(G15:J15) -> 318600 | L15: =L10+L11 -> 103240 | M15: =M10+M11 -> 115560 | N15: =N10+N11 -> 99135 | O15: =O10+O11 -> 153572 | P15: =SUM(L15:O15) -> 471507 | Q15: =Q10+Q11 -> 112198 | R15: =R10+R11 -> 156372 | S15: =S10+S11 -> 180487 | T15: =T10+T11 -> 327915 | U15: =SUM(Q15:T15) -> 776972 | V15: =V10+V11 -> 219504 | W15: =W10+W11 -> 310789 | X15: =X10+X11 -> 305671 | Y15: =Y10+Y11 -> 246616 | Z15: =SUM(V15:Y15) -> 1082580 | AA15: =AA10+AA11 -> 252085 | AB15: =AB10+AB11 -> 299868 | AC15: =AC10+AC11 -> 458572 | AD15: =AD10+AD11 -> 398729 | AE15: =SUM(AA15:AD15) -> 1409254 | AF15: =AF10+AF11 -> 394617 | AG15: =AG10+AG11 -> 393041 | AH15: =AH10+AH11 -> 408964 | AI15: =AI10+AI11 -> 340008 | AJ15: =SUM(AF15:AI15) -> 1536630 | AK15: =AK10+AK11 -> 328713 | AL15: =AL10+AL11 -> 382496 | AM15: =AM10+AM11 -> 445961 | AN15: =AN10+AN11 -> 576320 | AO15: =SUM(AK15:AN15) -> 1733490 | AP15: =AP10+AP11 -> 459875 | AQ15: =AQ10+AQ11 -> 411571 | AR15: =AR10+AR11 -> 428286 | AS15: =AS10+AS11 -> 519080 | AT15: =SUM(AP15:AS15) -> 1818812 | AU15: =AU10+AU11 -> 397020 | AV15: =AV10+AV11 -> 447774 | AW15: =AW10+AW11 -> 457250 | AX15: =AX10+AX11 -> 457245 | AY15: =SUM(AU15:AX15) -> 1759289 | AZ15: =AZ10+AZ11 -> 437655 | BA15: =BA10+BA11 -> 453552 | BB15: =BB10+BB11 -> 482731 | BC15: =BC10+BC11 -> 494808 | BD15: =SUM(AZ15:BC15) -> 1868746 | BE15: =BE10+BE11 -> 360611 | BF15: =BF10+BF11 -> 399056 | BG15: =BG10+BG11 -> 394514 | BH15: =BH10+BH11 -> 348898 | BI15: =SUM(BE15:BH15) -> 1503079 | BJ15: =BJ10+BJ11 -> 282261 | BK15: =BK10+BK11 -> 253930 | BL15: =BL10+BL11 -> 261421 | BM15: =BM10+BM11 -> 264911 | BN15: =SUM(BJ15:BM15) -> 1062523 | BO15: =BO10+BO11 -> 215017 | BP15: =BP10+BP11 -> 153589 | BQ15: =BQ10+BQ11 -> 147332 | BR15: =BR10+BR11 -> 218575 | BS15: =SUM(BO15:BR15) -> 734513 | BT15: =BT10+BT11 -> 124783 | BU15: =BU10+BU11 -> 171297 | BV15: =BV10+BV11 -> 204776 | BW15: =BW10+BW11 -> 314071 | BX15: =SUM(BT15:BW15) -> 814927 | BY15: =BY10+BY11 -> 248889 | BZ15: =BZ10+BZ11 -> 292960 | CA15: =CA10+CA11 -> 288927 | CB15: =CB10+CB11 -> 384938 | CC15: =SUM(BY15:CB15) -> 1215714 | CD15: =CD10+CD11 -> 260855 | CE15: =CE10+CE11 -> 274871 | CF15: =CF10+CF11 -> 378581 | CG15: =CG10+CG11 -> 336076 | CH15: =SUM(CD15:CG15) -> 1250383 | CI15: =CI10+CI11 -> 346540 | CJ15: =CJ10+CJ11 -> 432284 | CK15: =CK10+CK11 -> 446896 | CL15: =CL10+CL11 -> 440100 | CM15: =SUM(CI15:CL15) -> 1665820 | CN15: =CN10+CN11 -> 383550 | CO15: =CO10+CO11 -> 391331 | CP15: =CP10+CP11 -> 528384 | CQ15: =CQ10+CQ11 -> 430697 | CR15: =SUM(CN15:CQ15) -> 1733962 | CS15: =CS10+CS11 -> 394467 | CT15: =CT10+CT11 -> 527088 | CU15: =CU10+CU11 -> 545464 | CV15: =CV10+CV11 -> 576580 | CW15: =SUM(CS15:CV15) -> 2043599 | CX15: =CX10+CX11 -> 493522 | CY15: =CY10+CY11 -> 610027 | CZ15: =CZ10+CZ11 -> 676165 | DA15: =DA10+DA11 -> 800151 | DB15: =SUM(CX15:DA15) -> 2579865 | DC15: =DC10+DC11 -> 634339 | DD15: =DD10+DD11 -> 689836 | DE15: =DE10+DE11 -> 702414 | DF15: =DF10+DF11 -> 1043380 | DG15: =SUM(DC15:DF15) -> 3069969 | DH15: =DH10+DH11 -> 665926 | DI15: =DI10+DI11 -> 852919 | DJ15: =DJ10+DJ11 -> 899544.58 | DK15: =DK10+DK11 -> 1000413.3 | DL15: =SUM(DH15:DK15) -> 3418802.9 | DM15: =DM10+DM11 -> 935637.86 | DN15: =DN10+DN11 -> 975065.06 | DO15: =DO10+DO11 -> 1007127.1 | DP15: =DP10+DP11 -> 1093319.1 | DQ15: =SUM(DM15:DP15) -> 4011149.2 | DR15: =DR10+DR11 -> 1052480.8 | DS15: =DS10+DS11 -> 1085756.6 | DT15: =DT10+DT11 -> 1114495.1 | DU15: =DU10+DU11 -> 1199872.7 | DV15: =SUM(DR15:DU15) -> 4452605.1 | DW15: =DW10+DW11 -> 1133721.8 | DX15: =DX10+DX11 -> 1166907.3 | DY15: =DY10+DY11 -> 1194759.6 | DZ15: =DZ10+DZ11 -> 1282045.1 | EA15: =SUM(DW15:DZ15) -> 4777433.8 | EB15: =EB10+EB11 -> 1211261.7 | EC15: =EC10+EC11 -> 1244847.3 | ED15: =ED10+ED11 -> 1272171.7 | EE15: =EE10+EE11 -> 1361105.1 | EF15: =SUM(EB15:EE15) -> 5089385.7
A16: Operating (Expenses) Income | B16: =B17+B20+B22+B31+B35+B28 -> -13312 | C16: =C17+C20+C22+C31+C35+C28 -> -13312 | D16: =D17+D20+D22+D31+D35+D28 -> -20313 | E16: =E17+E20+E22+E31+E35+E28 -> -18430 | F16: =SUM(B16:E16) -> -65367 | G16: =G17+G20+G22+G31+G35+G28 -> -31442 | H16: =H17+H20+H22+H31+H35+H28 -> -30388 | I16: =I17+I20+I22+I31+I35+I28 -> -64956 | J16: =J17+J20+J22+J31+J35+J28 -> -30148 | K16: =SUM(G16:J16) -> -156934 | L16: =L17+L20+L22+L31+L35+L28 -> -19465 | M16: =M17+M20+M22+M31+M35+M28 -> -16696 | N16: =N17+N20+N22+N31+N35+N28 -> -55005 | O16: =O17+O20+O22+O31+O35+O28 -> -51754 | P16: =SUM(L16:O16) -> -142920 | Q16: =Q17+Q20+Q22+Q31+Q35+Q28 -> -58156 | R16: =R17+R20+R22+R31+R35+R28 -> 67398 | S16: =S17+S20+S22+S31+S35+S28 -> -55336 | T16: =T17+T20+T22+T31+T35+T28 -> -193314 | U16: =SUM(Q16:T16) -> -239408 | V16: =V17+V20+V22+V31+V35+V28 -> -126028 | W16: =W17+W20+W22+W31+W35+W28 -> -161849 | X16: =X17+X20+X22+X31+X35+X28 -> -189157 | Y16: =Y17+Y20+Y22+Y31+Y35+Y28 -> -163553 | Z16: =SUM(V16:Y16) -> -640587 | AA16: =AA17+AA20+AA22+AA31+AA35+AA28 -> -101565 | AB16: =AB17+AB20+AB22+AB31+AB35+AB28 -> -96202 | AC16: =AC17+AC20+AC22+AC31+AC35+AC28 -> -90744 | AD16: =AD17+AD20+AD22+AD31+AD35+AD28 -> -148786 | AE16: =SUM(AA16:AD16) -> -437297 | AF16: =AF17+AF20+AF22+AF31+AF35+AF28 -> -178833 | AG16: =AG17+AG20+AG22+AG31+AG35+AG28 -> -156810 | AH16: =AH17+AH20+AH22+AH31+AH35+AH28 -> -173217 | AI16: =AI17+AI20+AI22+AI31+AI35+AI28 -> -199860 | AJ16: =SUM(AF16:AI16) -> -708720 | AK16: =AK17+AK20+AK22+AK31+AK35+AK28 -> -196754 | AL16: =AL17+AL20+AL22+AL31+AL35+AL28 -> -241502 | AM16: =AM17+AM20+AM22+AM31+AM35+AM28 -> -221026 | AN16: =AN17+AN20+AN22+AN31+AN35+AN28 -> -293810 | AO16: =SUM(AK16:AN16) -> -953092 | AP16: =AP17+AP20+AP22+AP31+AP35+AP28 -> -232954 | AQ16: =AQ17+AQ20+AQ22+AQ31+AQ35+AQ28 -> -180102 | AR16: =AR17+AR20+AR22+AR31+AR35+AR28 -> -214192 | AS16: =AS17+AS20+AS22+AS31+AS35+AS28 -> -203195 | AT16: =SUM(AP16:AS16) -> -830443 | AU16: =AU17+AU20+AU22+AU31+AU35+AU28 -> -161583 | AV16: =AV17+AV20+AV22+AV31+AV35+AV28 -> -189478 | AW16: =AW17+AW20+AW22+AW31+AW35+AW28 -> -196650 | AX16: =AX17+AX20+AX22+AX31+AX35+AX28 -> -187688 | AY16: =SUM(AU16:AX16) -> -735399 | AZ16: =AZ17+AZ20+AZ22+AZ31+AZ35+AZ28 -> -209059 | BA16: =BA17+BA20+BA22+BA31+BA35+BA28 -> -202724 | BB16: =BB17+BB20+BB22+BB31+BB35+BB28 -> -222391 | BC16: =BC17+BC20+BC22+BC31+BC35+BC28 -> -258165 | BD16: =SUM(AZ16:BC16) -> -892339 | BE16: =BE17+BE20+BE22+BE31+BE35+BE28 -> -219357 | BF16: =BF17+BF20+BF22+BF31+BF35+BF28 -> -190079 | BG16: =BG17+BG20+BG22+BG31+BG35+BG28 -> -196105 | BH16: =BH17+BH20+BH22+BH31+BH35+BH28 -> -207134 | BI16: =SUM(BE16:BH16) -> -812675 | BJ16: =BJ17+BJ20+BJ22+BJ31+BJ35+BJ28 -> -175144 | BK16: =BK17+BK20+BK22+BK31+BK35+BK28 -> -182593 | BL16: =BL17+BL20+BL22+BL31+BL35+BL28 -> -199948 | BM16: =BM17+BM20+BM22+BM31+BM35+BM28 -> -186495 | BN16: =SUM(BJ16:BM16) -> -744180 | BO16: =BO17+BO20+BO22+BO31+BO35+BO28 -> -165320 | BP16: =BP17+BP20+BP22+BP31+BP35+BP28 -> -273570 | BQ16: =BQ17+BQ20+BQ22+BQ31+BQ35+BQ28 -> -118881 | BR16: =BR17+BR20+BR22+BR31+BR35+BR28 -> -122112 | BS16: =SUM(BO16:BR16) -> -679883 | BT16: =BT17+BT20+BT22+BT31+BT35+BT28 -> -147683 | BU16: =BU17+BU20+BU22+BU31+BU35+BU28 -> -176235 | BV16: =BV17+BV20+BV22+BV31+BV35+BV28 -> -283464 | BW16: =BW17+BW20+BW22+BW31+BW35+BW28 -> -132985 | BX16: =SUM(BT16:BW16) -> -740367 | BY16: =BY17+BY20+BY22+BY31+BY35+BY28 -> -169377 | BZ16: =BZ17+BZ20+BZ22+BZ31+BZ35+BZ28 -> -131465 | CA16: =CA17+CA20+CA22+CA31+CA35+CA28 -> -145997 | CB16: =CB17+CB20+CB22+CB31+CB35+CB28 -> -148384 | CC16: =SUM(BY16:CB16) -> -595223 | CD16: =CD17+CD20+CD22+CD31+CD35+CD28 -> -195770 | CE16: =CE17+CE20+CE22+CE31+CE35+CE28 -> -165614 | CF16: =CF17+CF20+CF22+CF31+CF35+CF28 -> 1057582 | CG16: =CG17+CG20+CG22+CG31+CG35+CG28 -> -32202 | CH16: =SUM(CD16:CG16) -> 663996 | CI16: =CI17+CI20+CI22+CI31+CI35+CI28 -> -120500 | CJ16: =CJ17+CJ20+CJ22+CJ31+CJ35+CJ28 -> -120885 | CK16: =CK17+CK20+CK22+CK31+CK35+CK28 -> -154069 | CL16: =CL17+CL20+CL22+CL31+CL35+CL28 -> -164432 | CM16: =SUM(CI16:CL16) -> -559886 | CN16: =CN17+CN20+CN22+CN31+CN35+CN28 -> -186479 | CO16: =CO17+CO20+CO22+CO31+CO35+CO28 -> -199209 | CP16: =CP17+CP20+CP22+CP31+CP35+CP28 -> -186277 | CQ16: =CQ17+CQ20+CQ22+CQ31+CQ35+CQ28 -> -180381 | CR16: =SUM(CN16:CQ16) -> -752346 | CS16: =CS17+CS20+CS22+CS31+CS35+CS28 -> -171430 | CT16: =CT17+CT20+CT22+CT31+CT35+CT28 -> -179239 | CU16: =CU17+CU20+CU22+CU31+CU35+CU28 -> -199818 | CV16: =CV17+CV20+CV22+CV31+CV35+CV28 -> -230901 | CW16: =SUM(CS16:CV16) -> -781388 | CX16: =CX17+CX20+CX22+CX31+CX35+CX28 -> -141678 | CY16: =CY17+CY20+CY22+CY31+CY35+CY28 -> -90783 | CZ16: =CZ17+CZ20+CZ22+CZ31+CZ35+CZ28 -> -83457 | DA16: =DA17+DA20+DA22+DA31+DA35+DA28 -> -157465 | DB16: =SUM(CX16:DA16) -> -473383 | DC16: =DC17+DC20+DC22+DC31+DC35+DC28 -> -196376 | DD16: =DD17+DD20+DD22+DD31+DD35+DD28 -> -161100 | DE16: =DE17+DE20+DE22+DE31+DE35+DE28 -> 36389 | DF16: =DF17+DF20+DF22+DF31+DF35+DF28 -> -205022 | DG16: =SUM(DC16:DF16) -> -526109 | DH16: =DH17+DH20+DH22+DH31+DH35+DH28 -> -254645 | DI16: =DI17+DI20+DI22+DI31+DI35+DI28 -> -279216 | DJ16: =DJ17+DJ20+DJ22+DJ31+DJ35+DJ28 -> -213540.08 | DK16: =DK17+DK20+DK22+DK31+DK35+DK28 -> -223160.72 | DL16: =SUM(DH16:DK16) -> -970561.8 | DM16: =DM17+DM20+DM22+DM31+DM35+DM28 -> -238927.89 | DN16: =DN17+DN20+DN22+DN31+DN35+DN28 -> -259298.36 | DO16: =DO17+DO20+DO22+DO31+DO35+DO28 -> -294762.22 | DP16: =DP17+DP20+DP22+DP31+DP35+DP28 -> -340987.68 | DQ16: =SUM(DM16:DP16) -> -1133976.1 | DR16: =DR17+DR20+DR22+DR31+DR35+DR28 -> -265269.3 | DS16: =DS17+DS20+DS22+DS31+DS35+DS28 -> -337419.39 | DT16: =DT17+DT20+DT22+DT31+DT35+DT28 -> -367608.18 | DU16: =DU17+DU20+DU22+DU31+DU35+DU28 -> -386086.14 | DV16: =SUM(DR16:DU16) -> -1356383 | DW16: =DW17+DW20+DW22+DW31+DW35+DW28 -> -293053.64 | DX16: =DX17+DX20+DX22+DX31+DX35+DX28 -> -376568.59 | DY16: =DY17+DY20+DY22+DY31+DY35+DY28 -> -412290.04 | DZ16: =DZ17+DZ20+DZ22+DZ31+DZ35+DZ28 -> -419192.16 | EA16: =SUM(DW16:DZ16) -> -1501104.4 | EB16: =EB17+EB20+EB22+EB31+EB35+EB28 -> -304803.89 | EC16: =EC17+EC20+EC22+EC31+EC35+EC28 -> -383407.16 | ED16: =ED17+ED20+ED22+ED31+ED35+ED28 -> -417433.3 | EE16: =EE17+EE20+EE22+EE31+EE35+EE28 -> -425913.5 | EF16: =SUM(EB16:EE16) -> -1531557.9
A17: Selling Expenses | B17: =(-23743-SUM(D17))/2 -> -6079.5 | C17: =B17 -> -6079.5 | D17: -11584 | E17: -18592 | F17: =SUM(B17:E17) -> -42335 | G17: -20958 | H17: -26303 | I17: -19771 | J17: -27283 | K17: =SUM(G17:J17) -> -94315 | L17: -20214 | M17: =-47715-L17 -> -27501 | N17: =-81492-L17-M17 -> -33777 | O17: =-131233-SUM(L17:N17) -> -49741 | P17: =SUM(L17:O17) -> -131233 | Q17: -29530 | R17: =-72045-Q17 -> -42515 | S17: -44577 | T17: =-262987-SUM(Q17:S17) -> -146365 | U17: =SUM(Q17:T17) -> -262987 | V17: -69144 | W17: -107614 | X17: -91352 | Y17: =-366684-SUM(V17:X17) -> -98574 | Z17: =SUM(V17:Y17) -> -366684 | AA17: -52424 | AB17: -52750 | AC17: -95819 | AD17: -90298 | AE17: =SUM(AA17:AD17) -> -291291 | AF17: -94188 | AG17: -103019 | AH17: -103927 | AI17: -100686 | AJ17: =SUM(AF17:AI17) -> -401820 | AK17: -112616 | AL17: =-255554-AK17 -> -142938 | AM17: =-377323-AK17-AL17 -> -121769 | AN17: =-511246-AK17-AL17-AM17 -> -133923 | AO17: =SUM(AK17:AN17) -> -511246 | AP17: =-219037-AQ17 -> -109229 | AQ17: -109808 | AR17: -110247 | AS17: =-457139-AP17-AQ17-AR17 -> -127855 | AT17: =SUM(AP17:AS17) -> -457139 | AU17: =-195945-AV17 -> -92544 | AV17: -103401 | AW17: -113426 | AX17: =-431373-SUM(AU17:AW17) -> -122002 | AY17: =SUM(AU17:AX17) -> -431373 | AZ17: -105875 | BA17: -110796 | BB17: -118305 | BC17: =-466628-SUM(AZ17:BB17) -> -131652 | BD17: =SUM(AZ17:BC17) -> -466628 | BE17: -107499 | BF17: -114777 | BG17: -119917 | BH17: =-459538-SUM(BE17:BG17) -> -117345 | BI17: =SUM(BE17:BH17) -> -459538 | BJ17: -102376 | BK17: -94828 | BL17: -101971 | BM17: =-400579-SUM(BJ17:BL17) -> -101404 | BN17: =SUM(BJ17:BM17) -> -400579 | BO17: -87376 | BP17: -87704 | BQ17: -88456 | BR17: =-343283-SUM(BO17:BQ17) -> -79747 | BS17: =SUM(BO17:BR17) -> -343283 | BT17: -73073 | BU17: -84139 | BV17: -87973 | BW17: =-332795-SUM(BT17:BV17) -> -87610 | BX17: =SUM(BT17:BW17) -> -332795 | BY17: -87514 | BZ17: -98449 | CA17: -95474 | CB17: =-382005-SUM(BY17:CA17) -> -100568 | CC17: =SUM(BY17:CB17) -> -382005 | CD17: -90755 | CE17: -89321 | CF17: -71523 | CG17: =-326318-SUM(CD17:CF17) -> -74719 | CH17: =SUM(CD17:CG17) -> -326318 | CI17: -70578 | CJ17: -75141 | CK17: -94562 | CL17: =-347846-SUM(CI17:CK17) -> -107565 | CM17: =SUM(CI17:CL17) -> -347846 | CN17: -97954 | CO17: -108144 | CP17: -152389 | CQ17: =-514969-SUM(CN17:CP17) -> -156482 | CR17: =SUM(CN17:CQ17) -> -514969 | CS17: -142049 | CT17: -155437 | CU17: -155053 | CV17: =-628585-SUM(CS17:CU17) -> -176046 | CW17: =SUM(CS17:CV17) -> -628585 | CX17: -153798 | CY17: -147794 | CZ17: -170109 | DA17: =-659284-SUM(CX17:CZ17) -> -187583 | DB17: =SUM(CX17:DA17) -> -659284 | DC17: -200780 | DD17: -225655 | DE17: -237709 | DF17: =-938220-SUM(DC17:DE17) -> -274076 | DG17: =SUM(DC17:DF17) -> -938220 | DH17: -276768 | DI17: -293787 | DJ17: =-DJ19*(Forecasts!DJ15+Forecasts!DJ17) -> -251393.75 | DK17: =-DK19*(Forecasts!DK15+Forecasts!DK17) -> -275226.68 | DL17: =SUM(DH17:DK17) -> -1097175.4 | DM17: =-DM19*(Forecasts!DM15+Forecasts!DM17) -> -247670.79 | DN17: =-DN19*(Forecasts!DN15+Forecasts!DN17) -> -274528.43 | DO17: =-DO19*(Forecasts!DO15+Forecasts!DO17) -> -293758.67 | DP17: =-DP19*(Forecasts!DP15+Forecasts!DP17) -> -336125.43 | DQ17: =SUM(DM17:DP17) -> -1152083.3 | DR17: =-DR19*(Forecasts!DR15+Forecasts!DR17) -> -255624.76 | DS17: =-DS19*(Forecasts!DS15+Forecasts!DS17) -> -285071.47 | DT17: =-DT19*(Forecasts!DT15+Forecasts!DT17) -> -306545.88 | DU17: =-DU19*(Forecasts!DU15+Forecasts!DU17) -> -351882.1 | DV17: =SUM(DR17:DU17) -> -1199124.2 | DW17: =-DW19*(Forecasts!DW15+Forecasts!DW17) -> -268362.95 | DX17: =-DX19*(Forecasts!DX15+Forecasts!DX17) -> -299772.74 | DY17: =-DY19*(Forecasts!DY15+Forecasts!DY17) -> -322535 | DZ17: =-DZ19*(Forecasts!DZ15+Forecasts!DZ17) -> -370229.63 | EA17: =SUM(DW17:DZ17) -> -1260900.3 | EB17: =-EB19*(Forecasts!EB15+Forecasts!EB17) -> -282681.2 | EC17: =-EC19*(Forecasts!EC15+Forecasts!EC17) -> -315551.92 | ED17: =-ED19*(Forecasts!ED15+Forecasts!ED17) -> -339138.55 | EE17: =-EE19*(Forecasts!EE15+Forecasts!EE17) -> -388861.78 | EF17: =SUM(EB17:EE17) -> -1326233.4
A18: % of revenues | B18: =-B17/B10 -> 0.055467107 | C18: =-C17/C10 -> 0.055467107 | D18: =-D17/D10 -> 0.094401434 | E18: =-E17/E10 -> 0.10186504 | F18: =-F17/F10 -> 0.080724663 | G18: =-G17/G10 -> 0.12318163 | H18: =-H17/H10 -> 0.1843173 | I18: =-I17/I10 -> 0.078161383 | ... EF18: =-EF17/EF10 -> 0.085431901
A19: % of sales | B19: =-B17/Forecasts!B9 -> 0.03150185 | C19: =-C17/Forecasts!C9 -> 0.03150185 | D19: =-D17/Forecasts!D9 -> 0.06002425 | E19: =-E17/Forecasts!E9 -> 0.081495248 | F19: =-F17/Forecasts!F9 -> 0.052453098 | G19: =-G17/Forecasts!G9 -> 0.12354762 | H19: =-H17/Forecasts!H9 -> 0.11098078 | I19: =-I17/Forecasts!I9 -> 0.071948441 | ... AO19: =-AO17/Forecasts!AO9 -> 0.078677439 | AP19: =-AP17/(Forecasts!AP15+Forecasts!AP17) -> 0.074001207 | AQ19: =-AQ17/(Forecasts!AQ15+Forecasts!AQ17) -> 0.069820247 | AR19: =-AR17/(Forecasts!AR15+Forecasts!AR17) -> 0.054881493 | AS19: =-AS17/(Forecasts!AS15+Forecasts!AS17) -> 0.091306655 | AT19: =-AT17/(Forecasts!AT15+Forecasts!AT17) -> 0.07078791 | AU19: =-AU17/(Forecasts!AU15+Forecasts!AU17) -> 0.066539821 | AV19: =-AV17/(Forecasts!AV15+Forecasts!AV17) -> 0.053967567 | AW19: =-AW17/(Forecasts!AW15+Forecasts!AW17) -> 0.071505066 | ... DI19: =-DI17/(Forecasts!DI15+Forecasts!DI17) -> 0.074948296 | DJ19: 0.0575 | DK19: 0.055 | DL19: =-DL17/(Forecasts!DL15+Forecasts!DL17) -> 0.066166311 | DM19: 0.065 | DN19: 0.065 | DO19: 0.065 | DP19: 0.065 | DQ19: =-DQ17/(Forecasts!DQ15+Forecasts!DQ17) -> 0.065 | DR19: =DM19 -> 0.065 | DS19: =DN19 -> 0.065 | DT19: =DO19 -> 0.065 | DU19: =DP19 -> 0.065 | DV19: =-DV17/(Forecasts!DV15+Forecasts!DV17) -> 0.065 | DW19: =DR19 -> 0.065 | DX19: =DS19 -> 0.065 | DY19: =DT19 -> 0.065 | DZ19: =DU19 -> 0.065 | EA19: =-EA17/(Forecasts!EA15+Forecasts!EA17) -> 0.065 | EB19: =DW19 -> 0.065 | EC19: =DX19 -> 0.065 | ED19: =DY19 -> 0.065 | EE19: =DZ19 -> 0.065 | EF19: =-EF17/(Forecasts!EF15+Forecasts!EF17) -> 0.065
A20: G&A Expenses | B20: =(-27146-SUM(D20))/2 -> -8407.5 | C20: =B20 -> -8407.5 | D20: -10331 | E20: -5479 | F20: =SUM(B20:E20) -> -32625 | G20: -10997 | H20: -12345 | I20: -8780 | J20: -12722 | K20: =SUM(G20:J20) -> -44844 | L20: -17512 | M20: -14998 | N20: =-48254-L20-M20-1362 -> -17106 | O20: =-72949-SUM(L20:N20)-1797 -> -25130 | P20: =SUM(L20:O20) -> -74746 | Q20: =-24351-454 -> -24805 | R20: =-43826-Q20-876 -> -19897 | S20: =-29532-437 -> -29969 | T20: =-133653-3297-SUM(Q20:S20) -> -62279 | U20: =SUM(Q20:T20) -> -136950 | V20: =-43679-1891 -> -45570 | W20: =-52746-2123 -> -54869 | X20: =-61052-2768 -> -63820 | Y20: =-212648-SUM(V20:X20)-9394 -> -57783 | Z20: =SUM(V20:Y20) -> -222042 | AA20: =-43676-2268-AA33 -> -42957 | AB20: =-48572-2582-AB33 -> -47904 | AC20: =-64087-2797-AC33 -> -63580 | AD20: =-59431-1542-AD33 -> -34121 | AE20: =SUM(AA20:AD20) -> -188562 | AF20: =-73166-1227-AF33 -> -56073 | AG20: =-73035-1331-AG33 -> -63450 | AH20: =-79447-1247-AH33 -> -69372 | AI20: =-108018-1385-AI33 -> -90428 | AJ20: =SUM(AF20:AI20) -> -279323 | AK20: =-83303-1930-AK33 -> -81847 | AL20: =-101579-1927-AL33 -> -99975 | AM20: =-102443-AM33 -> -96569 | AN20: =-404033-AK20-AL20-AM20-SUM(AK33:AN33) -> -112306 | AO20: =SUM(AK20:AN20) -> -390697 | AP20: =-229623-3571-AP33-AQ20-AQ33-AP34 -> -107149 | AQ20: =-103506-1632-AQ33 -> -98867 | AR20: =-89636-AR33-2518 -> -89846 | AS20: =-397452-AP20-AQ20-AR20-SUM(AP33:AS33) -> -83181 | AT20: =SUM(AP20:AS20) -> -379043 | AU20: =-186579-3351-AU33-AV20-AV33 -> -84934 | AV20: =-97252-1586-AV33 -> -94225 | AW20: =-98777-AW33-1590 -> -98089 | AX20: =-401077-SUM(AU20:AW20)-SUM(AU33:AX33) -> -104248 | AY20: =SUM(AU20:AX20) -> -381496 | AZ20: =-105462-1375-AZ33 -> -102174 | BA20: =-114861-1552-BA33 -> -110181 | BB20: =-114766-BB33-1725 -> -111149 | BC20: =-467317-SUM(AZ20:BB20)-SUM(AZ33:BC33) -> -122209 | BD20: =SUM(AZ20:BC20) -> -445713 | BE20: =-103807-1725-BE33 -> -101107 | BF20: =-88399-1754-BF33 -> -84496 | BG20: =-113883-BG33-1702 -> -110889 | BH20: =-412408-SUM(BE20:BG20)-SUM(BE33:BH33) -> -94312 | BI20: =SUM(BE20:BH20) -> -390804 | BJ20: =-93379-1721-BJ33 -> -88100 | BK20: =-113954-BK33-1564 -> -107828 | BL20: =-111709-BL33-1684 -> -102140 | BM20: =-438601-SUM(BJ20:BL20)-SUM(BJ33:BM33) -> -83590 | BN20: =SUM(BJ20:BM20) -> -381658 | BO20: =-98009-1501-BO33 -> -78168 | BP20: =-102822-BP33-1517 -> -75678 | BQ20: =-92934-BQ33-1441 -> -83500 | BR20: =-391470-5761-SUM(BO20:BQ20)-SUM(BO33:BR33) -> -93350 | BS20: =SUM(BO20:BR20) -> -330696 | BT20: =-97415-1299-BT33 -> -82847 | BU20: =-82780-BU33-1327 -> -74523 | BV20: =-93939-BV33-1342 -> -84406 | BW20: =-364737-5261-SUM(BT20:BV20)-SUM(BT33:BW33) -> -66853 | BX20: =SUM(BT20:BW20) -> -308629 | BY20: =-78164-1268-BY33 -> -55073 | BZ20: =-94502-BZ33-1268 -> -103651 | CA20: =-103322-CA33-1260 -> -73044 | CB20: =-388305-5050-SUM(BY20:CA20)-SUM(BY33:CB33) -> -86909 | CC20: =SUM(BY20:CB20) -> -318677 | CD20: =-94234-1568-CD33 -> -78603 | CE20: =-95740-1458-CE33 -> -83473 | CF20: =-93025-CF33 -> -84062 | CG20: =-384720-5957-SUM(CD20:CF20)-SUM(CD33:CG33) -> -93376 | CH20: =SUM(CD20:CG20) -> -339514 | CI20: =-118255-1332-CI33 -> -108655 | CJ20: =-125166-CJ33 -> -114704 | CK20: =-122372-CK33 -> -111352 | CL20: =-501453-SUM(CI20:CK20)-SUM(CI33:CL33) -> -126719 | CM20: =SUM(CI20:CL20) -> -461430 | CN20: =-134623-1618-CN33 -> -127709 | CO20: =-142746-CO33 -> -133495 | CP20: =-151238-CP33 -> -128406 | CQ20: =-554805-SUM(CN20:CP20)-SUM(CN33:CQ33) -> -121721 | CR20: =SUM(CN20:CQ20) -> -511331 | CS20: =-111939-1826-CS33 -> -84481 | CT20: =-118608-CT33 -> -102537 | CU20: =-150553-CU33 -> -108251 | CV20: =-517647-SUM(CS20:CU20)-SUM(CS33:CV33) -> -155290 | CW20: =SUM(CS20:CV20) -> -450559 | CX20: =-105049-1827-CX33 -> -83238 | CY20: =-110024-CY33 -> -93659 | CZ20: =-125048-CZ33 -> -85049 | DA20: =-462436-SUM(CX20:CZ20)-SUM(CX33:DA33) -> -100431 | DB20: =SUM(CX20:DA20) -> -362377 | DC20: =-124568-2139-DC33 -> -96435 | DD20: =-126946-DD33 -> -103144 | DE20: =-131713-DE33 -> -103084 | DF20: =-524921-SUM(DC20:DE20)-SUM(DC33:DF33) -> -89683 | DG20: =SUM(DC20:DF20) -> -392346 | DH20: =-131579-2266-DH33 -> -79262 | DI20: =-134332-DI33 -> -93166 | DJ20: =DI20*(1+Macro!DJ15) -> -94196.881 | DK20: =DF20*(1+Macro!DL15) -> -93718.735 | DL20: =SUM(DH20:DK20) -> -360343.62 | DM20: =DJ20 -> -94196.881 | DN20: =DM20*(1+Macro!DN15) -> -95239.168 | DO20: =DN20*(1+Macro!DO15) -> -96292.989 | DP20: =DK20*(1+Macro!DQ15) -> -97936.078 | DQ20: =SUM(DM20:DP20) -> -383665.12 | DR20: =DO20 -> -96292.989 | DS20: =DR20*(1+Macro!DS15) -> -97358.47 | DT20: =DS20*(1+Macro!DT15) -> -98435.741 | DU20: =DP20*(1+Macro!DV15) -> -102343.2 | DV20: =SUM(DR20:DU20) -> -394430.4 | DW20: =DT20 -> -98435.741 | DX20: =DW20*(1+Macro!DX15) -> -99524.931 | DY20: =DX20*(1+Macro!DY15) -> -100626.17 | DZ20: =DU20*(1+Macro!EA15) -> -106948.65 | EA20: =SUM(DW20:DZ20) -> -405535.49 | EB20: =DY20 -> -100626.17 | EC20: =EB20*(1+Macro!EC15) -> -101739.6 | ED20: =EC20*(1+Macro!ED15) -> -102865.35 | EE20: =DZ20*(1+Macro!EF15) -> -111761.33 | EF20: =SUM(EB20:EE20) -> -416992.46
A21: % of revenues | B21: =-B20/B10 -> 0.076706917 | C21: =-C20/C10 -> 0.076706917 | D21: =-D20/D10 -> 0.084190368 | E21: =-E20/E10 -> 0.030019286 | F21: =-F20/F10 -> 0.06220957 | G21: =-G20/G10 -> 0.064635386 | H21: =-H20/H10 -> 0.08650713 | I21: =-I20/I10 -> 0.03471028 | ... N21: =-N20/N10 -> 0.073474647 | O21: 0.085 | P21: =-P20/P10 -> 0.066935857 | Q21: =-Q20/Q10 -> 0.086280962 | R21: =-R20/R10 -> 0.053587973 | S21: =-S20/S10 -> 0.072245097 | T21: =-T20/T10 -> 0.06733389 | U21: =-U20/U10 -> 0.068525058 | V21: =-V20/V10 -> 0.082727446 | W21: =-W20/W10 -> 0.069027943 | ... EF21: =-EF20/EF10 -> 0.026861378
A22: Net Financial Result | B22: =B23+B25+B27 -> -322.5 | C22: =C23+C25+C27 -> -322.5 | D22: =D23+D25+D27 -> 4723 | E22: =E23+E25+E27 -> 2765 | F22: =SUM(B22:E22) -> 6843 | G22: =G23+G25+G27 -> -1143 | H22: =H23+H25+H27 -> 7287 | I22: =I23+I25+I27 -> -8873 | J22: =J23+J25+J27 -> 9717 | K22: =SUM(G22:J22) -> 6988 | L22: =L23+L25+L27 -> 17909 | M22: =M23+M25+M27 -> 21099 | N22: =N23+N25+N27 -> 18095 | O22: =O23+O25+O27 -> 23740 | P22: =SUM(L22:O22) -> 80843 | Q22: =Q23+Q25+Q27 -> 485 | R22: =R23+R25+R27 -> 16529 | S22: =S23+S25+S27 -> 11403 | T22: =T23+T25+T27 -> 26777 | U22: =SUM(Q22:T22) -> 55194 | V22: =V23+V25+V27 -> 22 | W22: =W23+W25+W27 -> 8204 | X22: =X23+X25+X27 -> -28122 | Y22: =Y23+Y25+Y27 -> 9116 | Z22: =SUM(V22:Y22) -> -10780 | AA22: =AA23+AA25+AA27 -> -739 | AB22: =AB23+AB25+AB27 -> -5487 | AC22: =AC23+AC25+AC27 -> -12602 | AD22: =AD23+AD25+AD27 -> 4295 | AE22: =SUM(AA22:AD22) -> -14533 | AF22: =AF23+AF25+AF27 -> 5388 | AG22: =AG23+AG25+AG27 -> 20507 | AH22: =AH23+AH25+AH27 -> 22098 | AI22: =AI23+AI25+AI27 -> 17239 | AJ22: =SUM(AF22:AI22) -> 65232 | AK22: =AK23+AK25+AK27 -> 3210 | AL22: =AL23+AL25+AL27 -> 6573 | AM22: =AM23+AM25+AM27 -> 7204 | AN22: =AN23+AN25+AN27 -> 32632 | AO22: =SUM(AK22:AN22) -> 49619 | AP22: =AP23+AP25+AP27 -> 7372 | AQ22: =AQ23+AQ25+AQ27 -> 3487 | AR22: =AR23+AR25+AR27 -> 2574 | AS22: =AS23+AS25+AS27 -> -2842 | AT22: =SUM(AP22:AS22) -> 10591 | AU22: =AU23+AU25+AU27 -> 9802 | AV22: =AV23+AV25+AV27 -> 8806 | AW22: =AW23+AW25+AW27 -> 4964 | AX22: =AX23+AX25+AX27 -> 4306 | AY22: =SUM(AU22:AX22) -> 27878 | AZ22: =AZ23+AZ25+AZ27 -> 9440 | BA22: =BA23+BA25+BA27 -> 3202 | BB22: =BB23+BB25+BB27 -> 1584 | BC22: =BC23+BC25+BC27 -> 1918 | BD22: =SUM(AZ22:BC22) -> 16144 | BE22: =BE23+BE25+BE27 -> 6182 | BF22: =BF23+BF25+BF27 -> -10004 | BG22: =BG23+BG25+BG27 -> 5184 | BH22: =BH23+BH25+BH27 -> 16235 | BI22: =SUM(BE22:BH22) -> 17597 | BJ22: =BJ23+BJ25+BJ27 -> 20257 | BK22: =BK23+BK25+BK27 -> 25931 | BL22: =BL23+BL25+BL27 -> 18196 | BM22: =BM23+BM25+BM27 -> 14759 | BN22: =SUM(BJ22:BM22) -> 79143 | BO22: =BO23+BO25+BO27 -> 12967 | BP22: =BP23+BP25+BP27 -> 5208 | BQ22: =BQ23+BQ25+BQ27 -> 11674 | BR22: =BR23+BR25+BR27 -> 7963 | BS22: =SUM(BO22:BR22) -> 37812 | BT22: =BT23+BT25+BT27 -> 2760 | BU22: =BU23+BU25+BU27 -> 4473 | BV22: =BV23+BV25+BV27 -> -769 | BW22: =BW23+BW25+BW27 -> 15654 | BX22: =SUM(BT22:BW22) -> 22118 | BY22: =BY23+BY25+BY27 -> 1872 | BZ22: =BZ23+BZ25+BZ27 -> 17872 | CA22: =CA23+CA25+CA27 -> 9055 | CB22: =CB23+CB25+CB27 -> 1794 | CC22: =SUM(BY22:CB22) -> 30593 | CD22: =CD23+CD25+CD27 -> 3251 | CE22: =CE23+CE25+CE27 -> 6501 | CF22: =CF23+CF25+CF27 -> 24471 | CG22: =CG23+CG25+CG27 -> 50278 | CH22: =SUM(CD22:CG22) -> 84501 | CI22: =CI23+CI25+CI27 -> 10887 | CJ22: =CJ23+CJ25+CJ27 -> 9293 | CK22: =CK23+CK25+CK27 -> 8859 | CL22: =CL23+CL25+CL27 -> 13958 | CM22: =SUM(CI22:CL22) -> 42997 | CN22: =CN23+CN25+CN27 -> 9333 | CO22: =CO23+CO25+CO27 -> 25501 | CP22: =CP23+CP25+CP27 -> 7027 | CQ22: =CQ23+CQ25+CQ27 -> 26466 | CR22: =SUM(CN22:CQ22) -> 68327 | CS22: =CS23+CS25+CS27 -> 45587 | CT22: =CT23+CT25+CT27 -> 29183 | CU22: =CU23+CU25+CU27 -> 28081 | CV22: =CV23+CV25+CV27 -> 33921 | CW22: =SUM(CS22:CV22) -> 136772 | CX22: =CX23+CX25+CX27 -> 13135 | CY22: =CY23+CY25+CY27 -> 44695 | CZ22: =CZ23+CZ25+CZ27 -> 39210 | DA22: =DA23+DA25+DA27 -> 16645 | DB22: =SUM(CX22:DA22) -> 113685 | DC22: =DC23+DC25+DC27 -> 59001 | DD22: =DD23+DD25+DD27 -> 66436 | DE22: =DE23+DE25+DE27 -> 56503 | DF22: =DF23+DF25+DF27 -> 65739 | DG22: =SUM(DC22:DF22) -> 247679 | DH22: =DH23+DH25+DH27 -> 37699 | DI22: =DI23+DI25+DI27 -> 69311 | DJ22: =DJ23+DJ25+DJ27 -> 49433.595 | DK22: =DK23+DK25+DK27 -> 52198.181 | DL22: =SUM(DH22:DK22) -> 208641.78 | DM22: =DM23+DM25+DM27 -> 27900.045 | DN22: =DN23+DN25+DN27 -> 25908.024 | DO22: =DO23+DO25+DO27 -> 5388.9371 | DP22: =DP23+DP25+DP27 -> -171.38227 | DQ22: =SUM(DM22:DP22) -> 59025.623 | DR22: =DR23+DR25+DR27 -> -13663.267 | DS22: =DS23+DS25+DS27 -> -55671.251 | DT22: =DT23+DT25+DT27 -> -70549.486 | DU22: =DU23+DU25+DU27 -> -43829.43 | DV22: =SUM(DR22:DU22) -> -183713.43 | DW22: =DW23+DW25+DW27 -> -40227.564 | DX22: =DX23+DX25+DX27 -> -88336.8 | DY22: =DY23+DY25+DY27 -> -107536.36 | DZ22: =DZ23+DZ25+DZ27 -> -64408.887 | EA22: =SUM(DW22:DZ22) -> -300509.61 | EB22: =EB23+EB25+EB27 -> -45217.573 | EC22: =EC23+EC25+EC27 -> -86130.163 | ED22: =ED23+ED25+ED27 -> -102834.48 | EE22: =EE23+EE25+EE27 -> -56652.855 | EF22: =SUM(EB22:EE22) -> -290835.08
A23: Financial Income | B23: =(34575-SUM(D23))/2 -> 9849 | C23: =B23 -> 9849 | D23: 14877 | E23: 9124 | F23: =SUM(B23:E23) -> 43699 | G23: 11688 | H23: 19433 | I23: 5656 | J23: 21014 | K23: =SUM(G23:J23) -> 57791 | L23: 29751 | M23: 31770 | N23: =95612-L23-M23 -> 34091 | O23: =133293-SUM(L23:N23) -> 37681 | P23: =SUM(L23:O23) -> 133293 | Q23: =19763-Q27 -> 13408.333 | R23: =67756-Q23-Q27-R27 -> 41638.333 | S23: =44601-S27 -> 38246.333 | T23: =144188-SUM(Q23:S23) -> 50895 | U23: =SUM(Q23:T23) -> 144188 | V23: =37046-V27 -> 29500 | W23: =55234-W27 -> 45460 | X23: =20683-X27 -> -7416 | Y23: =190740-SUM(V23:X23)-SUM(V27:Y27) -> 41643 | Z23: =SUM(V23:Y23) -> 109187 | AA23: =55187-AA27 -> 29518 | AB23: =47545-AB27 -> 39177 | AC23: =10013+10725+3196 -> 23934 | AD23: =24316+9391+1720 -> 35427 | AE23: =SUM(AA23:AD23) -> 128056 | AF23: =57269-AF27 -> 30543 | AG23: =79023-AG27 -> 40313 | AH23: =82309-AH27 -> 40595 | AI23: =69011-AI27 -> 27223 | AJ23: =SUM(AF23:AI23) -> 138674 | AK23: =59606-AK27 -> 36957 | AL23: =135741-46605-AK23 -> 52179 | AM23: =101379-AM27 -> 57933 | AN23: =363335-AK23-AL23-AM23-SUM(AK27:AN27) -> 94930 | AO23: =SUM(AK23:AN23) -> 241999 | AP23: =156358-AQ23-AP27-AQ27 -> 60399 | AQ23: =78349-AQ27 -> 53870 | AR23: =47580-AR27 -> 44190 | AS23: =249302-AP23-AQ23-AR23-SUM(AP27:AS27) -> 49593 | AT23: =SUM(AP23:AS23) -> 208052 | AU23: =99206-AV23-AU27-AV27 -> 33764 | AV23: =48469-AV27 -> 32002 | AW23: =50340-AW27 -> 37130 | AX23: =207166-AU23-AV23-AW23-SUM(AU27:AX27) -> 41654 | AY23: =SUM(AU23:AX23) -> 144550 | AZ23: =69890-AZ27 -> 53994 | BA23: =72020-BA27 -> 58712 | BB23: =68287-BB27 -> 53481 | BC23: =278643-AZ23-BA23-BB23-SUM(AZ27:BC27) -> 57135 | BD23: =SUM(AZ23:BC23) -> 223322 | BE23: =70199-BE27 -> 57470 | BF23: =78523-BF27 -> 67812 | BG23: =92358-BG27 -> 83052 | BH23: =330885-BE23-BF23-BG23-SUM(BE27:BH27) -> 81409 | BI23: =SUM(BE23:BH23) -> 289743 | BJ23: =79540-BJ27 -> 75343 | BK23: =82849-BK27 -> 77531 | BL23: =72404-BL27 -> 66572 | BM23: =305693-BJ23-BK23-BL23-SUM(BJ27:BM27) -> 67118 | BN23: =SUM(BJ23:BM23) -> 286564 | BO23: =64967-BO27 -> 60573 | BP23: =49577-BP27 -> 45707 | BQ23: =53730-BQ27 -> 49917 | BR23: =205392-BO23-BP23-BQ23-SUM(BO27:BR27) -> 32244 | BS23: =SUM(BO23:BR23) -> 188441 | BT23: =31953-BT27 -> 29534 | BU23: =33070-BU27 -> 28664 | BV23: =49281-BV27 -> 42228 | BW23: =173006-BT23-BU23-BV23-SUM(BT27:BW27) -> 54212 | BX23: =SUM(BT23:BW23) -> 154638 | BY23: =40108-BY27 -> 36402 | BZ23: =49286-BZ27 -> 45795 | CA23: =47956-CA27 -> 43500 | CB23: =180522-BY23-BZ23-CA23-SUM(BY27:CB27) -> 40873 | CC23: =SUM(BY23:CB23) -> 166570 | CD23: =31141-CD27 -> 27505 | CE23: =42555-CE27 -> 34572 | CF23: =55454-CF27 -> 52179 | CG23: =202431-CD23-CE23-CF23-SUM(CD27:CG27) -> 71282 | CH23: =SUM(CD23:CG23) -> 185538 | CI23: =53921-CI27 -> 52590 | CJ23: =51865-CJ27 -> 48563 | CK23: =71473-CK27 -> 69268 | CL23: =271862-CI23-CJ23-CK23-SUM(CI27:CL27) -> 91837 | CM23: =SUM(CI23:CL23) -> 262258 | CN23: =95875-CN27 -> 87063 | CO23: =130109-CO27 -> 123190 | CP23: =130948-CP27 -> 127352 | CQ23: =572713-CN23-CO23-CP23-SUM(CN27:CQ27) -> 209350 | CR23: =SUM(CN23:CQ23) -> 546955 | CS23: =190820-CS27 -> 187928 | CT23: =178032-CT27 -> 175031 | CU23: =156108-CU27 -> 152003 | CV23: =694725-CS23-CT23-CU23-SUM(CS27:CV27) -> 167390 | CW23: =SUM(CS23:CV23) -> 682352 | CX23: =157466-CX27 -> 153718 | CY23: =182301-CY27 -> 178220 | CZ23: =169528-CZ27 -> 166458 | DA23: =683473-CX23-CY23-CZ23-SUM(CX27:DA27) -> 170531 | DB23: =SUM(CX23:DA23) -> 668927 | DC23: =211618-DC27 -> 207879 | DD23: =252543-DD27 -> 248937 | DE23: =246895-DE27 -> 238180 | DF23: =975978-DC23-DD23-DE23-SUM(DC27:DF27) -> 258155 | DG23: =SUM(DC23:DF23) -> 953151 | DH23: =260988-DH27 -> 258243 | DI23: =332564-DI27 -> 328877 | DJ23: =DJ24*(AVERAGE('Balance Sheet'!DI6:DJ6)+AVERAGE('Balance Sheet'!DI7:DJ7))/4 -> 282825.07 | DK23: =DK24*(AVERAGE('Balance Sheet'!DJ6:DK6)+AVERAGE('Balance Sheet'!DJ7:DK7))/4 -> 274608.24 | DL23: =SUM(DH23:DK23) -> 1144553.3 | DM23: =DM24*(AVERAGE('Balance Sheet'!DL6:DM6)+AVERAGE('Balance Sheet'!DL7:DM7))/4 -> 268974.96 | DN23: =DN24*(AVERAGE('Balance Sheet'!DM6:DN6)+AVERAGE('Balance Sheet'!DM7:DN7))/4 -> 272847.52 | DO23: =DO24*(AVERAGE('Balance Sheet'!DN6:DO6)+AVERAGE('Balance Sheet'!DN7:DO7))/4 -> 251203.19 | DP23: =DP24*(AVERAGE('Balance Sheet'!DO6:DP6)+AVERAGE('Balance Sheet'!DO7:DP7))/4 -> 244595.31 | DQ23: =SUM(DM23:DP23) -> 1037621 | DR23: =DR24*(AVERAGE('Balance Sheet'!DQ6:DR6)+AVERAGE('Balance Sheet'!DQ7:DR7))/4 -> 236726.79 | DS23: =DS24*(AVERAGE('Balance Sheet'!DR6:DS6)+AVERAGE('Balance Sheet'!DR7:DS7))/4 -> 200346.5 | DT23: =DT24*(AVERAGE('Balance Sheet'!DS6:DT6)+AVERAGE('Balance Sheet'!DS7:DT7))/4 -> 184691.85 | DU23: =DU24*(AVERAGE('Balance Sheet'!DT6:DU6)+AVERAGE('Balance Sheet'!DT7:DU7))/4 -> 210583.12 | DV23: =SUM(DR23:DU23) -> 832348.27 | DW23: =DW24*(AVERAGE('Balance Sheet'!DV6:DW6)+AVERAGE('Balance Sheet'!DV7:DW7))/4 -> 220126.41 | DX23: =DX24*(AVERAGE('Balance Sheet'!DW6:DX6)+AVERAGE('Balance Sheet'!DW7:DX7))/4 -> 178215.43 | DY23: =DY24*(AVERAGE('Balance Sheet'!DX6:DY6)+AVERAGE('Balance Sheet'!DX7:DY7))/4 -> 158819.35 | DZ23: =DZ24*(AVERAGE('Balance Sheet'!DY6:DZ6)+AVERAGE('Balance Sheet'!DY7:DZ7))/4 -> 202049.68 | EA23: =SUM(DW23:DZ23) -> 759210.86 | EB23: =EB24*(AVERAGE('Balance Sheet'!EA6:EB6)+AVERAGE('Balance Sheet'!EA7:EB7))/4 -> 228094.25 | EC23: =EC24*(AVERAGE('Balance Sheet'!EB6:EC6)+AVERAGE('Balance Sheet'!EB7:EC7))/4 -> 193920.99 | ED23: =ED24*(AVERAGE('Balance Sheet'!EC6:ED6)+AVERAGE('Balance Sheet'!EC7:ED7))/4 -> 177131.45 | EE23: =EE24*(AVERAGE('Balance Sheet'!ED6:EE6)+AVERAGE('Balance Sheet'!ED7:EE7))/4 -> 223345.67 | EF23: =SUM(EB23:EE23) -> 822492.35
A24: Avg rate (%) | B24: =(1+(B23+B27)/(AVERAGE('Balance Sheet'!B6:B6)+AVERAGE('Balance Sheet'!B9:B9)+AVERAGE('Balance Sheet'!B7:B7)))^4-1 -> #DIV/0! | C24: =(1+(C23+C27)/(AVERAGE('Balance Sheet'!B6:C6)+AVERAGE('Balance Sheet'!B9:C9)+AVERAGE('Balance Sheet'!B7:C7)))^4-1 -> #DIV/0! | D24: =(1+(D23+D27)/(AVERAGE('Balance Sheet'!C6:D6)+AVERAGE('Balance Sheet'!C9:D9)+AVERAGE('Balance Sheet'!C7:D7)))^4-1 -> #DIV/0! | E24: =(1+(E23+E27)/(AVERAGE('Balance Sheet'!D6:E6)+AVERAGE('Balance Sheet'!D9:E9)+AVERAGE('Balance Sheet'!D7:E7)))^4-1 -> #DIV/0! | F24: =(F23+F27)/(AVERAGE('Balance Sheet'!B6:E6)+AVERAGE('Balance Sheet'!B9:E9)+AVERAGE('Balance Sheet'!B7:E7)) -> #DIV/0! | G24: =(1+(G23+G27)/(AVERAGE('Balance Sheet'!F6:G6)+AVERAGE('Balance Sheet'!F9:G9)+AVERAGE('Balance Sheet'!F7:G7)))^4-1 -> 0.27716164 | H24: =(1+(H23+H27)/(AVERAGE('Balance Sheet'!G6:H6)+AVERAGE('Balance Sheet'!G9:H9)+AVERAGE('Balance Sheet'!G7:H7)))^4-1 -> #DIV/0! | I24: =(1+(I23+I27)/(AVERAGE('Balance Sheet'!H6:I6)+AVERAGE('Balance Sheet'!H9:I9)+AVERAGE('Balance Sheet'!H7:I7)))^4-1 -> #DIV/0! | J24: =(1+(J23+J27)/(AVERAGE('Balance Sheet'!I6:J6)+AVERAGE('Balance Sheet'!I9:J9)+AVERAGE('Balance Sheet'!I7:J7)))^4-1 -> #DIV/0! | K24: =(K23+K27)/(AVERAGE('Balance Sheet'!G6:J6)+AVERAGE('Balance Sheet'!G9:J9)+AVERAGE('Balance Sheet'!G7:J7)) -> #DIV/0! | L24: =(1+(L23+L27)/(AVERAGE('Balance Sheet'!K6:L6)+AVERAGE('Balance Sheet'!K9:L9)+AVERAGE('Balance Sheet'!K7:L7)))^4-1 -> 0.25772088 | M24: =(1+(M23+M27)/(AVERAGE('Balance Sheet'!L6:M6)+AVERAGE('Balance Sheet'!L9:M9)+AVERAGE('Balance Sheet'!L7:M7)))^4-1 -> #DIV/0! | N24: =(1+(N23+N27)/(AVERAGE('Balance Sheet'!M6:N6)+AVERAGE('Balance Sheet'!M9:N9)+AVERAGE('Balance Sheet'!M7:N7)))^4-1 -> #DIV/0! | O24: =(1+(O23+O27)/(AVERAGE('Balance Sheet'!N6:O6)+AVERAGE('Balance Sheet'!N9:O9)+AVERAGE('Balance Sheet'!N7:O7)))^4-1 -> #DIV/0! | P24: =(P23)/(AVERAGE('Balance Sheet'!L6:O6)+AVERAGE('Balance Sheet'!L7:O7)) -> 0.2254163 | Q24: =(1+(Q23)/(AVERAGE('Balance Sheet'!P6:Q6)+AVERAGE('Balance Sheet'!P7:Q7)))^4-1 -> 0.094577722 | R24: =(1+(R23)/(AVERAGE('Balance Sheet'!Q6:R6)+AVERAGE('Balance Sheet'!Q7:R7)))^4-1 -> 0.23879125 | S24: =(1+(S23)/(AVERAGE('Balance Sheet'!R6:S6)+AVERAGE('Balance Sheet'!R7:S7)))^4-1 -> 0.16289558 | T24: =(1+(T23)/(AVERAGE('Balance Sheet'!S6:T6)+AVERAGE('Balance Sheet'!S7:T7)))^4-1 -> 0.22840579 | U24: =(U23)/(AVERAGE('Balance Sheet'!Q6:T6)+AVERAGE('Balance Sheet'!Q7:T7)) -> 0.16751048 | V24: =(1+(V23)/(AVERAGE('Balance Sheet'!U6:V6)+AVERAGE('Balance Sheet'!U7:V7)))^4-1 -> 0.11010706 | W24: =(1+(W23)/(AVERAGE('Balance Sheet'!V6:W6)+AVERAGE('Balance Sheet'!V7:W7)))^4-1 -> 0.15327161 | X24: =(1+(X23)/(AVERAGE('Balance Sheet'!W6:X6)+AVERAGE('Balance Sheet'!W7:X7)))^4-1 -> -0.025796138 | Y24: =(1+(Y23)/(AVERAGE('Balance Sheet'!X6:Y6)+AVERAGE('Balance Sheet'!X7:Y7)))^4-1 -> 0.15870308 | Z24: =(Z23)/(AVERAGE('Balance Sheet'!V6:Y6)+AVERAGE('Balance Sheet'!V7:Y7)) -> 0.092426143 | AA24: =(1+(AA23)/(AVERAGE('Balance Sheet'!Z6:AA6)+AVERAGE('Balance Sheet'!Z7:AA7)))^4-1 -> 0.10833833 | AB24: =(1+(AB23)/(AVERAGE('Balance Sheet'!AA6:AB6)+AVERAGE('Balance Sheet'!AA7:AB7)))^4-1 -> 0.16811599 | AC24: =(1+(AC23)/(AVERAGE('Balance Sheet'!AB6:AC6)+AVERAGE('Balance Sheet'!AB7:AC7)))^4-1 -> 0.088847514 | AD24: =(1+(AD23)/(AVERAGE('Balance Sheet'!AC6:AD6)+AVERAGE('Balance Sheet'!AC7:AD7)))^4-1 -> 0.086894303 | AE24: =(AE23)/(AVERAGE('Balance Sheet'!AA6:AD6)+AVERAGE('Balance Sheet'!AA7:AD7)) -> 0.095849116 | AF24: =(1+(AF23)/(AVERAGE('Balance Sheet'!AE6:AF6)+AVERAGE('Balance Sheet'!AE7:AF7)))^4-1 -> 0.067201127 | AG24: =(1+(AG23)/(AVERAGE('Balance Sheet'!AF6:AG6)+AVERAGE('Balance Sheet'!AF7:AG7)))^4-1 -> 0.10646105 | AH24: =(1+(AH23)/(AVERAGE('Balance Sheet'!AG6:AH6)+AVERAGE('Balance Sheet'!AG7:AH7)))^4-1 -> 0.11790691 | AI24: =(1+(AI23)/(AVERAGE('Balance Sheet'!AH6:AI6)+AVERAGE('Balance Sheet'!AH7:AI7)))^4-1 -> 0.076027601 | AJ24: =(AJ23)/(AVERAGE('Balance Sheet'!AF6:AI6)+AVERAGE('Balance Sheet'!AF7:AI7)) -> 0.091043231 | AK24: =(1+(AK23)/(AVERAGE('Balance Sheet'!AJ6:AK6)+AVERAGE('Balance Sheet'!AJ7:AK7)))^4-1 -> 0.096930177 | AL24: =(1+(AL23)/(AVERAGE('Balance Sheet'!AK6:AL6)+AVERAGE('Balance Sheet'!AK7:AL7)))^4-1 -> 0.12077167 | AM24: =(1+(AM23)/(AVERAGE('Balance Sheet'!AL6:AM6)+AVERAGE('Balance Sheet'!AL7:AM7)))^4-1 -> 0.11709348 | AN24: =(1+(AN23)/(AVERAGE('Balance Sheet'!AM6:AN6)+AVERAGE('Balance Sheet'!AM7:AN7)))^4-1 -> 0.18121503 | AO24: =(AO23)/(AVERAGE('Balance Sheet'!AK6:AN6)+AVERAGE('Balance Sheet'!AK7:AN7)) -> 0.11987672 | AP24: =(1+(AP23)/(AVERAGE('Balance Sheet'!AO6:AP6)+AVERAGE('Balance Sheet'!AO7:AP7)))^4-1 -> 0.10909401 | AQ24: =(1+(AQ23)/(AVERAGE('Balance Sheet'!AP6:AQ6)+AVERAGE('Balance Sheet'!AP7:AQ7)))^4-1 -> 0.10044683 | AR24: =(1+(AR23)/(AVERAGE('Balance Sheet'!AQ6:AR6)+AVERAGE('Balance Sheet'!AQ7:AR7)))^4-1 -> 0.084433727 | AS24: =(1+(AS23)/(AVERAGE('Balance Sheet'!AR6:AS6)+AVERAGE('Balance Sheet'!AR7:AS7)))^4-1 -> 0.097201038 | AT24: =(AT23)/(AVERAGE('Balance Sheet'!AP6:AS6)+AVERAGE('Balance Sheet'!AP7:AS7)) -> 0.095916212 | AU24: =(1+(AU23)/(AVERAGE('Balance Sheet'!AT6:AU6)+AVERAGE('Balance Sheet'!AT7:AU7)))^4-1 -> 0.066730222 | AV24: =(1+(AV23)/(AVERAGE('Balance Sheet'!AU6:AV6)+AVERAGE('Balance Sheet'!AU7:AV7)))^4-1 -> 0.065937704 | AW24: =(1+(AW23)/(AVERAGE('Balance Sheet'!AV6:AW6)+AVERAGE('Balance Sheet'!AV7:AW7)))^4-1 -> 0.07959981 | AX24: =(1+(AX23)/(AVERAGE('Balance Sheet'!AW6:AX6)+AVERAGE('Balance Sheet'!AW7:AX7)))^4-1 -> 0.088130022 | AY24: =(AY23)/(AVERAGE('Balance Sheet'!AU6:AX6)+AVERAGE('Balance Sheet'!AU7:AX7)) -> 0.073363271 | AZ24: =(1+(AZ23)/(AVERAGE('Balance Sheet'!AY6:AZ6)+AVERAGE('Balance Sheet'!AY7:AZ7)))^4-1 -> 0.10325454 | BA24: =(1+(BA23)/(AVERAGE('Balance Sheet'!AZ6:BA6)+AVERAGE('Balance Sheet'!AZ7:BA7)))^4-1 -> 0.11309618 | BB24: =(1+(BB23)/(AVERAGE('Balance Sheet'!BA6:BB6)+AVERAGE('Balance Sheet'!BA7:BB7)))^4-1 -> 0.11478474 | BC24: =(1+(BC23)/(AVERAGE('Balance Sheet'!BB6:BC6)+AVERAGE('Balance Sheet'!BB7:BC7)))^4-1 -> 0.12274524 | BD24: =(BD23)/(AVERAGE('Balance Sheet'!AZ6:BC6)+AVERAGE('Balance Sheet'!AZ7:BC7)) -> 0.10872073 | BE24: =(1+(BE23)/(AVERAGE('Balance Sheet'!BD6:BE6)+AVERAGE('Balance Sheet'!BD7:BE7)))^4-1 -> 0.11495047 | BF24: =(1+(BF23)/(AVERAGE('Balance Sheet'!BE6:BF6)+AVERAGE('Balance Sheet'!BE7:BF7)))^4-1 -> 0.12122831 | BG24: =(1+(BG23)/(AVERAGE('Balance Sheet'!BF6:BG6)+AVERAGE('Balance Sheet'!BF7:BG7)))^4-1 -> 0.13469298 | BH24: =(1+(BH23)/(AVERAGE('Balance Sheet'!BG6:BH6)+AVERAGE('Balance Sheet'!BG7:BH7)))^4-1 -> 0.13189461 | BI24: =(BI23)/(AVERAGE('Balance Sheet'!BE6:BH6)+AVERAGE('Balance Sheet'!BE7:BH7)) -> 0.11767016 | BJ24: =(1+(BJ23)/(AVERAGE('Balance Sheet'!BI6:BJ6)+AVERAGE('Balance Sheet'!BI7:BJ7)))^4-1 -> 0.12914315 | BK24: =(1+(BK23)/(AVERAGE('Balance Sheet'!BJ6:BK6)+AVERAGE('Balance Sheet'!BJ7:BK7)))^4-1 -> 0.14150858 | BL24: =(1+(BL23)/(AVERAGE('Balance Sheet'!BK6:BL6)+AVERAGE('Balance Sheet'!BK7:BL7)))^4-1 -> 0.13769976 | BM24: =(1+(BM23)/(AVERAGE('Balance Sheet'!BL6:BM6)+AVERAGE('Balance Sheet'!BL7:BM7)))^4-1 -> 0.14382364 | BN24: =(BN23)/(AVERAGE('Balance Sheet'!BJ6:BM6)+AVERAGE('Balance Sheet'!BJ7:BM7)) -> 0.13424775 | BO24: =(1+(BO23)/(AVERAGE('Balance Sheet'!BN6:BO6)+AVERAGE('Balance Sheet'!BN7:BO7)))^4-1 -> 0.11644379 | BP24: =(1+(BP23)/(AVERAGE('Balance Sheet'!BO6:BP6)+AVERAGE('Balance Sheet'!BO7:BP7)))^4-1 -> 0.089224233 | BQ24: =(1+(BQ23)/(AVERAGE('Balance Sheet'!BP6:BQ6)+AVERAGE('Balance Sheet'!BP7:BQ7)))^4-1 -> 0.10834923 | BR24: =(1+(BR23)/(AVERAGE('Balance Sheet'!BQ6:BR6)+AVERAGE('Balance Sheet'!BQ7:BR7)))^4-1 -> 0.073354476 | BS24: =(BS23)/(AVERAGE('Balance Sheet'!BO6:BR6)+AVERAGE('Balance Sheet'!BO7:BR7)) -> 0.096086157 | BT24: =(1+(BT23)/(AVERAGE('Balance Sheet'!BS6:BT6)+AVERAGE('Balance Sheet'!BS7:BT7)))^4-1 -> 0.076063713 | BU24: =(1+(BU23)/(AVERAGE('Balance Sheet'!BT6:BU6)+AVERAGE('Balance Sheet'!BT7:BU7)))^4-1 -> 0.070298214 | BV24: =(1+(BV23)/(AVERAGE('Balance Sheet'!BU6:BV6)+AVERAGE('Balance Sheet'!BU7:BV7)))^4-1 -> 0.081817442 | BW24: =(1+(BW23)/(AVERAGE('Balance Sheet'!BV6:BW6)+AVERAGE('Balance Sheet'!BV7:BW7)))^4-1 -> 0.1066612 | BX24: =(BX23)/(AVERAGE('Balance Sheet'!BT6:BW6)+AVERAGE('Balance Sheet'!BT7:BW7)) -> 0.081688573 | BY24: =(1+(BY23)/(AVERAGE('Balance Sheet'!BX6:BY6)+AVERAGE('Balance Sheet'!BX7:BY7)))^4-1 -> 0.083220134 | BZ24: =(1+(BZ23)/(AVERAGE('Balance Sheet'!BY6:BZ6)+AVERAGE('Balance Sheet'!BY7:BZ7)))^4-1 -> 0.10479399 | CA24: =(1+(CA23)/(AVERAGE('Balance Sheet'!BZ6:CA6)+AVERAGE('Balance Sheet'!BZ7:CA7)))^4-1 -> 0.090584114 | CB24: =(1+(CB23)/(AVERAGE('Balance Sheet'!CA6:CB6)+AVERAGE('Balance Sheet'!CA7:CB7)))^4-1 -> 0.081340144 | CC24: =(CC23)/(AVERAGE('Balance Sheet'!BY6:CB6)+AVERAGE('Balance Sheet'!BY7:CB7)) -> 0.085738018 | CD24: =(1+(CD23)/(AVERAGE('Balance Sheet'!CC6:CD6)+AVERAGE('Balance Sheet'!CC7:CD7)))^4-1 -> 0.054413118 | CE24: =(1+(CE23)/(AVERAGE('Balance Sheet'!CD6:CE6)+AVERAGE('Balance Sheet'!CD7:CE7)))^4-1 -> 0.062143383 | CF24: =(1+(CF23)/(AVERAGE('Balance Sheet'!CE6:CF6)+AVERAGE('Balance Sheet'!CE7:CF7)))^4-1 -> 0.080331747 | CG24: =(1+(CG23)/(AVERAGE('Balance Sheet'!CF6:CG6)+AVERAGE('Balance Sheet'!CF7:CG7)))^4-1 -> 0.10432008 | CH24: =(CH23)/(AVERAGE('Balance Sheet'!CD6:CG6)+AVERAGE('Balance Sheet'!CD7:CG7)) -> 0.072554734 | CI24: =(1+(CI23)/(AVERAGE('Balance Sheet'!CH6:CI6)+AVERAGE('Balance Sheet'!CH7:CI7)))^4-1 -> 0.077085574 | CJ24: =(1+(CJ23)/(AVERAGE('Balance Sheet'!CI6:CJ6)+AVERAGE('Balance Sheet'!CI7:CJ7)))^4-1 -> 0.066096957 | CK24: =(1+(CK23)/(AVERAGE('Balance Sheet'!CJ6:CK6)+AVERAGE('Balance Sheet'!CJ7:CK7)))^4-1 -> 0.086436968 | CL24: =(1+(CL23)/(AVERAGE('Balance Sheet'!CK6:CL6)+AVERAGE('Balance Sheet'!CK7:CL7)))^4-1 -> 0.10488604 | CM24: =(CM23)/(AVERAGE('Balance Sheet'!CI6:CL6)+AVERAGE('Balance Sheet'!CI7:CL7)) -> 0.078898137 | CN24: =(1+(CN23)/(AVERAGE('Balance Sheet'!CM6:CN6)+AVERAGE('Balance Sheet'!CM7:CN7)))^4-1 -> 0.09474081 | CO24: =(1+(CO23)/(AVERAGE('Balance Sheet'!CN6:CO6)+AVERAGE('Balance Sheet'!CN7:CO7)))^4-1 -> 0.13041413 | CP24: =(1+(CP23)/(AVERAGE('Balance Sheet'!CO6:CP6)+AVERAGE('Balance Sheet'!CO7:CP7)))^4-1 -> 0.12435805 | CQ24: =(1+(CQ23)/(AVERAGE('Balance Sheet'!CP6:CQ6)+AVERAGE('Balance Sheet'!CP7:CQ7)))^4-1 -> 0.18715983 | CR24: =(CR23)/(AVERAGE('Balance Sheet'!CN6:CQ6)+AVERAGE('Balance Sheet'!CN7:CQ7)) -> 0.12522509 | CS24: =(1+(CS23)/(AVERAGE('Balance Sheet'!CR6:CS6)+AVERAGE('Balance Sheet'!CR7:CS7)))^4-1 -> 0.15805693 | CT24: =(1+(CT23)/(AVERAGE('Balance Sheet'!CS6:CT6)+AVERAGE('Balance Sheet'!CS7:CT7)))^4-1 -> 0.1468367 | CU24: =(1+(CU23)/(AVERAGE('Balance Sheet'!CT6:CU6)+AVERAGE('Balance Sheet'!CT7:CU7)))^4-1 -> 0.12431135 | CV24: =(1+(CV23)/(AVERAGE('Balance Sheet'!CU6:CV6)+AVERAGE('Balance Sheet'!CU7:CV7)))^4-1 -> 0.13892617 | CW24: =(CW23)/(AVERAGE('Balance Sheet'!CS6:CV6)+AVERAGE('Balance Sheet'!CS7:CV7)) -> 0.13529441 | CX24: =(1+(CX23)/(AVERAGE('Balance Sheet'!CW6:CX6)+AVERAGE('Balance Sheet'!CW7:CX7)))^4-1 -> 0.13136325 | CY24: =(1+(CY23)/(AVERAGE('Balance Sheet'!CX6:CY6)+AVERAGE('Balance Sheet'!CX7:CY7)))^4-1 -> 0.15184523 | CZ24: =(1+(CZ23)/(AVERAGE('Balance Sheet'!CY6:CZ6)+AVERAGE('Balance Sheet'!CY7:CZ7)))^4-1 -> 0.13320206 | DA24: =(1+(DA23)/(AVERAGE('Balance Sheet'!CZ6:DA6)+AVERAGE('Balance Sheet'!CZ7:DA7)))^4-1 -> 0.13133375 | DB24: =(DB23)/(AVERAGE('Balance Sheet'!CX6:DA6)+AVERAGE('Balance Sheet'!CX7:DA7)) -> 0.12867342 | DC24: =(1+(DC23)/(AVERAGE('Balance Sheet'!DB6:DC6)+AVERAGE('Balance Sheet'!DB7:DC7)))^4-1 -> 0.15592497 | DD24: =(1+(DD23)/(AVERAGE('Balance Sheet'!DC6:DD6)+AVERAGE('Balance Sheet'!DC7:DD7)))^4-1 -> 0.17631075 | DE24: =(1+(DE23)/(AVERAGE('Balance Sheet'!DD6:DE6)+AVERAGE('Balance Sheet'!DD7:DE7)))^4-1 -> 0.1477819 | DF24: =(1+(DF23)/(AVERAGE('Balance Sheet'!DE6:DF6)+AVERAGE('Balance Sheet'!DE7:DF7)))^4-1 -> 0.15026892 | DG24: =(DG23)/(AVERAGE('Balance Sheet'!DC6:DF6)+AVERAGE('Balance Sheet'!DC7:DF7)) -> 0.14380432 | DH24: =(1+(DH23)/(AVERAGE('Balance Sheet'!DG6:DH6)+AVERAGE('Balance Sheet'!DG7:DH7)))^4-1 -> 0.14878181 | DI24: =(1+(DI23)/(AVERAGE('Balance Sheet'!DH6:DI6)+AVERAGE('Balance Sheet'!DH7:DI7)))^4-1 -> 0.18190837 | DJ24: =Macro!DJ17 -> 0.1375 | DK24: =Macro!DK17 -> 0.1325 | DL24: =(DL23)/(AVERAGE('Balance Sheet'!DH6:DK6)+AVERAGE('Balance Sheet'!DH7:DK7)) -> 0.14308782 | DM24: =Macro!DM17 -> 0.13 | DN24: =Macro!DN17 -> 0.13 | DO24: =Macro!DO17 -> 0.13 | DP24: =Macro!DP17 -> 0.13 | DQ24: =(DQ23)/(AVERAGE('Balance Sheet'!DM6:DP6)+AVERAGE('Balance Sheet'!DM7:DP7)) -> 0.13034361 | DR24: =Macro!DR17 -> 0.13 | DS24: =Macro!DS17 -> 0.13 | DT24: =Macro!DT17 -> 0.13 | DU24: =Macro!DU17 -> 0.13 | DV24: =(DV23)/(AVERAGE('Balance Sheet'!DR6:DU6)+AVERAGE('Balance Sheet'!DR7:DU7)) -> 0.13165913 | DW24: =Macro!DW17 -> 0.13 | DX24: =Macro!DX17 -> 0.13 | DY24: =Macro!DY17 -> 0.13 | DZ24: =Macro!DZ17 -> 0.13 | EA24: =(EA23)/(AVERAGE('Balance Sheet'!DW6:DZ6)+AVERAGE('Balance Sheet'!DW7:DZ7)) -> 0.12977448 | EB24: =Macro!EB17 -> 0.13 | EC24: =Macro!EC17 -> 0.13 | ED24: =Macro!ED17 -> 0.13 | EE24: =Macro!EE17 -> 0.13 | EF24: =(EF23)/(AVERAGE('Balance Sheet'!EB6:EE6)+AVERAGE('Balance Sheet'!EB7:EE7)) -> 0.12812431
A25: Financial Expenses | B25: =(-30497-SUM(D25))/2 -> -10171.5 | C25: =B25 -> -10171.5 | D25: -10154 | E25: -6359 | F25: =SUM(B25:E25) -> -36856 | G25: -12831 | H25: -12146 | I25: -14529 | J25: -11297 | K25: =SUM(G25:J25) -> -50803 | L25: -11842 | M25: =-22513-L25 -> -10671 | N25: =-38509-L25-M25 -> -15996 | O25: =-84450-SUM(L25:N25)+32000 -> -13941 | P25: =SUM(L25:O25) -> -52450 | Q25: -19278 | R25: =-50742-Q25 -> -31464 | S25: -33198 | T25: =-116922-SUM(Q25:S25) -> -32982 | U25: =SUM(Q25:T25) -> -116922 | V25: -37024 | W25: -47030 | X25: -48805 | Y25: =-201520-SUM(V25:X25) -> -68661 | Z25: =SUM(V25:Y25) -> -201520 | AA25: -55926 | AB25: -53032 | AC25: -54285 | AD25: -62092 | AE25: =SUM(AA25:AD25) -> -225335 | AF25: -51881 | AG25: -58516 | AH25: -60211 | AI25: -51772 | AJ25: =SUM(AF25:AI25) -> -222380 | AK25: -56396 | AL25: =-125958-AK25 -> -69562 | AM25: =-220133-AK25-AL25 -> -94175 | AN25: =-313716-AK25-AL25-AM25 -> -93583 | AO25: =SUM(AK25:AN25) -> -313716 | AP25: =-145499-AQ25 -> -70637 | AQ25: -74862 | AR25: -45006 | AS25: =-238711-AP25-AQ25-AR25 -> -48206 | AT25: =SUM(AP25:AS25) -> -238711 | AU25: =-80598-AV25 -> -40935 | AV25: -39663 | AW25: -45376 | AX25: =-179288-AU25-AV25-AW25 -> -53314 | AY25: =SUM(AU25:AX25) -> -179288 | AZ25: -60450 | BA25: -68818 | BB25: -66703 | BC25: =-262499-AZ25-BA25-BB25 -> -66528 | BD25: =SUM(AZ25:BC25) -> -262499 | BE25: -64017 | BF25: -88527 | BG25: -87174 | BH25: =-313288-BE25-BF25-BG25 -> -73570 | BI25: =SUM(BE25:BH25) -> -313288 | BJ25: -59283 | BK25: -56918 | BL25: -54208 | BM25: =-226550-BJ25-BK25-BL25 -> -56141 | BN25: =SUM(BJ25:BM25) -> -226550 | BO25: -52000 | BP25: -44369 | BQ25: -42056 | BR25: =-167580-BO25-BP25-BQ25 -> -29155 | BS25: =SUM(BO25:BR25) -> -167580 | BT25: -29193 | BU25: -28597 | BV25: -50050 | BW25: =-150888-BT25-BU25-BV25 -> -43048 | BX25: =SUM(BT25:BW25) -> -150888 | BY25: -38236 | BZ25: -31414 | CA25: -38901 | CB25: =-149929-BY25-BZ25-CA25 -> -41378 | CC25: =SUM(BY25:CB25) -> -149929 | CD25: -27890 | CE25: -36054 | CF25: -30983 | CG25: =-117930-CD25-CE25-CF25 -> -23003 | CH25: =SUM(CD25:CG25) -> -117930 | CI25: -43034 | CJ25: -42572 | CK25: -62614 | CL25: =-228865-CI25-CJ25-CK25 -> -80645 | CM25: =SUM(CI25:CL25) -> -228865 | CN25: -86542 | CO25: -104608 | CP25: -123921 | CQ25: =-504386-CN25-CO25-CP25 -> -189315 | CR25: =SUM(CN25:CQ25) -> -504386 | CS25: -145233 | CT25: -148849 | CU25: -128027 | CV25: =-557953-CS25-CT25-CU25 -> -135844 | CW25: =SUM(CS25:CV25) -> -557953 | CX25: -144331 | CY25: -137606 | CZ25: -130318 | DA25: =-569788-CX25-CY25-CZ25 -> -157533 | DB25: =SUM(CX25:DA25) -> -569788 | DC25: -152617 | DD25: -186107 | DE25: -190392 | DF25: =-728299-DC25-DD25-DE25 -> -199183 | DG25: =SUM(DC25:DF25) -> -728299 | DH25: -223289 | DI25: -263253 | DJ25: =DJ85+DJ84 -> -242832.35 | DK25: =DK85+DK84 -> -234399.19 | DL25: =SUM(DH25:DK25) -> -963773.54 | DM25: =DM85+DM84 -> -247805.91 | DN25: =DN85+DN84 -> -254463.88 | DO25: =DO85+DO84 -> -254463.88 | DP25: =DP85+DP84 -> -254463.88 | DQ25: =SUM(DM25:DP25) -> -1011197.5 | DR25: =DR85+DR84 -> -261121.84 | DS25: =DS85+DS84 -> -267779.8 | DT25: =DT85+DT84 -> -267779.8 | DU25: =DU85+DU84 -> -267779.8 | DV25: =SUM(DR25:DU25) -> -1064461.3 | DW25: =DW85+DW84 -> -274437.77 | DX25: =DX85+DX84 -> -281095.73 | DY25: =DY85+DY84 -> -281095.73 | DZ25: =DZ85+DZ84 -> -281095.73 | EA25: =SUM(DW25:DZ25) -> -1117725 | EB25: =EB85+EB84 -> -287753.7 | EC25: =EC85+EC84 -> -294411.66 | ED25: =ED85+ED84 -> -294411.66 | EE25: =EE85+EE84 -> -294411.66 | EF25: =SUM(EB25:EE25) -> -1170988.7
A26: Avg rate (%) | B26: =(1-B25/'Balance Sheet'!B50)^4-1 -> 0.5613868 | C26: =(1-C25/'Balance Sheet'!C50)^4-1 -> 0.50940587 | D26: =(1-D25/'Balance Sheet'!D50)^4-1 -> 0.44933823 | E26: =(1-E25/'Balance Sheet'!E50)^4-1 -> 0.099488421 | F26: =-F25/AVERAGE('Balance Sheet'!B50:E50) -> 0.2682353 | G26: =(1-G25/'Balance Sheet'!G50)^4-1 -> 0.097220296 | H26: =(1-H25/'Balance Sheet'!H50)^4-1 -> 0.18389627 | I26: =(1-I25/'Balance Sheet'!I50)^4-1 -> 0.34548079 | J26: =(1-J25/'Balance Sheet'!J50)^4-1 -> 0.24081054 | K26: =-K25/AVERAGE('Balance Sheet'!G50:J50) -> 0.16642262 | L26: =(1-L25/'Balance Sheet'!L50)^4-1 -> 0.2204243 | M26: =(1-M25/'Balance Sheet'!M50)^4-1 -> 0.1768272 | N26: =(1-N25/AVERAGE('Balance Sheet'!M50:N50))^4-1 -> 0.33640485 | O26: =(1-O25/AVERAGE('Balance Sheet'!N50:O50))^4-1 -> 0.40132987 | P26: =-P25/AVERAGE('Balance Sheet'!L50:O50) -> 0.26044059 | Q26: =(1-Q25/'Balance Sheet'!Q50)^4-1 -> 0.31368084 | R26: =(1-R25/'Balance Sheet'!R50)^4-1 -> 0.19173331 | S26: =(1-S25/AVERAGE('Balance Sheet'!R50:S50))^4-1 -> 0.19659668 | T26: =(1-T25/AVERAGE('Balance Sheet'!S50:T50))^4-1 -> 0.17034023 | U26: =-U25/AVERAGE('Balance Sheet'!Q50:T50) -> 0.17852813 | V26: =(1-V25/AVERAGE('Balance Sheet'!U50:V50))^4-1 -> 0.1297291 | W26: =(1-W25/AVERAGE('Balance Sheet'!V50:W50))^4-1 -> 0.12339261 | X26: =(1-X25/AVERAGE('Balance Sheet'!W50:X50))^4-1 -> 0.11611256 | Y26: =(1-Y25/AVERAGE('Balance Sheet'!X50:Y50))^4-1 -> 0.1438906 | Z26: =-Z25/AVERAGE('Balance Sheet'!V50:Y50) -> 0.11188693 | AA26: =(1-AA25/AVERAGE('Balance Sheet'!Z50:AA50))^4-1 -> 0.10212294 | AB26: =(1-AB25/AVERAGE('Balance Sheet'!AA50:AB50))^4-1 -> 0.090260035 | AC26: =(1-AC25/AVERAGE('Balance Sheet'!AB50:AC50))^4-1 -> 0.08059382 | AD26: =(1-AD25/AVERAGE('Balance Sheet'!AC50:AD50))^4-1 -> 0.088781294 | AE26: =-AE25/AVERAGE('Balance Sheet'!AA50:AD50) -> 0.084755142 | AF26: =(1-AF25/AVERAGE('Balance Sheet'!AE50:AF50))^4-1 -> 0.077879878 | AG26: =(1-AG25/AVERAGE('Balance Sheet'!AF50:AG50))^4-1 -> 0.085444772 | AH26: =(1-AH25/AVERAGE('Balance Sheet'!AG50:AH50))^4-1 -> 0.082361158 | AI26: =(1-AI25/AVERAGE('Balance Sheet'!AH50:AI50))^4-1 -> 0.063527826 | AJ26: =-AJ25/AVERAGE('Balance Sheet'!AF50:AI50) -> 0.072176734 | AK26: =(1-AK25/AVERAGE('Balance Sheet'!AJ50:AK50))^4-1 -> 0.06267027 | AL26: =(1-AL25/AVERAGE('Balance Sheet'!AK50:AL50))^4-1 -> 0.070221048 | AM26: =(1-AM25/AVERAGE('Balance Sheet'!AL50:AM50))^4-1 -> 0.085316441 | AN26: =(1-AN25/AVERAGE('Balance Sheet'!AM50:AN50))^4-1 -> 0.080736668 | AO26: =-AO25/AVERAGE('Balance Sheet'!AK50:AN50) -> 0.070977382 | AP26: =(1-AP25/AVERAGE('Balance Sheet'!AO50:AP50))^4-1 -> 0.060217644 | AQ26: =(1-AQ25/AVERAGE('Balance Sheet'!AP50:AQ50))^4-1 -> 0.064702039 | AR26: =(1-AR25/AVERAGE('Balance Sheet'!AQ50:AR50))^4-1 -> 0.039800195 | AS26: =(1-AS25/AVERAGE('Balance Sheet'!AR50:AS50))^4-1 -> 0.044230908 | AT26: =-AT25/AVERAGE('Balance Sheet'!AP50:AS50) -> 0.052063033 | AU26: =(1-AU25/AVERAGE('Balance Sheet'!AT50:AU50))^4-1 -> 0.039291246 | AV26: =(1-AV25/AVERAGE('Balance Sheet'!AU50:AV50))^4-1 -> 0.039531971 | AW26: =(1-AW25/AVERAGE('Balance Sheet'!AV50:AW50))^4-1 -> 0.045197399 | AX26: =(1-AX25/AVERAGE('Balance Sheet'!AW50:AX50))^4-1 -> 0.050966129 | AY26: =-AY25/AVERAGE('Balance Sheet'!AU50:AX50) -> 0.043016986 | AZ26: =(1-AZ25/AVERAGE('Balance Sheet'!AY50:AZ50))^4-1 -> 0.053987202 | BA26: =(1-BA25/AVERAGE('Balance Sheet'!AZ50:BA50))^4-1 -> 0.061298172 | BB26: =(1-BB25/AVERAGE('Balance Sheet'!BA50:BB50))^4-1 -> 0.061955836 | BC26: =(1-BC25/AVERAGE('Balance Sheet'!BB50:BC50))^4-1 -> 0.0648581 | BD26: =-BD25/AVERAGE('Balance Sheet'!AZ50:BC50) -> 0.059698713 | BE26: =(1-BE25/AVERAGE('Balance Sheet'!BD50:BE50))^4-1 -> 0.065766147 | BF26: =(1-BF25/AVERAGE('Balance Sheet'!BE50:BF50))^4-1 -> 0.091182843 | BG26: =(1-BG25/AVERAGE('Balance Sheet'!BF50:BG50))^4-1 -> 0.087502827 | BH26: =(1-BH25/AVERAGE('Balance Sheet'!BG50:BH50))^4-1 -> 0.075367218 | BI26: =-BI25/AVERAGE('Balance Sheet'!BE50:BH50) -> 0.078056894 | BJ26: =(1-BJ25/AVERAGE('Balance Sheet'!BI50:BJ50))^4-1 -> 0.063051055 | BK26: =(1-BK25/AVERAGE('Balance Sheet'!BJ50:BK50))^4-1 -> 0.062394139 | BL26: =(1-BL25/AVERAGE('Balance Sheet'!BK50:BL50))^4-1 -> 0.061289797 | BM26: =(1-BM25/AVERAGE('Balance Sheet'!BL50:BM50))^4-1 -> 0.064948882 | BN26: =-BN25/AVERAGE('Balance Sheet'!BJ50:BM50) -> 0.062291287 | BO26: =(1-BO25/AVERAGE('Balance Sheet'!BN50:BO50))^4-1 -> 0.059735977 | BP26: =(1-BP25/AVERAGE('Balance Sheet'!BO50:BP50))^4-1 -> 0.051097861 | BQ26: =(1-BQ25/AVERAGE('Balance Sheet'!BP50:BQ50))^4-1 -> 0.052062408 | BR26: =(1-BR25/AVERAGE('Balance Sheet'!BQ50:BR50))^4-1 -> 0.041091596 | BS26: =-BS25/AVERAGE('Balance Sheet'!BO50:BR50) -> 0.052201257 | BT26: =(1-BT25/AVERAGE('Balance Sheet'!BS50:BT50))^4-1 -> 0.049609029 | BU26: =(1-BU25/AVERAGE('Balance Sheet'!BT50:BU50))^4-1 -> 0.051078586 | BV26: =(1-BV25/AVERAGE('Balance Sheet'!BU50:BV50))^4-1 -> 0.07721794 | BW26: =(1-BW25/AVERAGE('Balance Sheet'!BV50:BW50))^4-1 -> 0.06606308 | BX26: =-BX25/AVERAGE('Balance Sheet'!BT50:BW50) -> 0.0609391 | BY26: =(1-BY25/AVERAGE('Balance Sheet'!BX50:BY50))^4-1 -> 0.06862562 | BZ26: =(1-BZ25/AVERAGE('Balance Sheet'!BY50:BZ50))^4-1 -> 0.060622734 | CA26: =(1-CA25/AVERAGE('Balance Sheet'!BZ50:CA50))^4-1 -> 0.069888565 | CB26: =(1-CB25/AVERAGE('Balance Sheet'!CA50:CB50))^4-1 -> 0.066318503 | CC26: =-CC25/AVERAGE('Balance Sheet'!BY50:CB50) -> 0.064123638 | CD26: =(1-CD25/AVERAGE('Balance Sheet'!CC50:CD50))^4-1 -> 0.043502325 | CE26: =(1-CE25/AVERAGE('Balance Sheet'!CD50:CE50))^4-1 -> 0.052514927 | CF26: =(1-CF25/AVERAGE('Balance Sheet'!CE50:CF50))^4-1 -> 0.045630381 | CG26: =(1-CG25/AVERAGE('Balance Sheet'!CF50:CG50))^4-1 -> 0.035079575 | CH26: =-CH25/AVERAGE('Balance Sheet'!CD50:CG50) -> 0.043222323 | CI26: =(1-CI25/AVERAGE('Balance Sheet'!CH50:CI50))^4-1 -> 0.062729706 | CJ26: =(1-CJ25/AVERAGE('Balance Sheet'!CI50:CJ50))^4-1 -> 0.055537862 | CK26: =(1-CK25/AVERAGE('Balance Sheet'!CJ50:CK50))^4-1 -> 0.074470221 | CL26: =(1-CL25/AVERAGE('Balance Sheet'!CK50:CL50))^4-1 -> 0.092397662 | CM26: =-CM25/AVERAGE('Balance Sheet'!CI50:CL50) -> 0.06791998 | CN26: =(1-CN25/AVERAGE('Balance Sheet'!CM50:CN50))^4-1 -> 0.095347638 | CO26: =(1-CO25/AVERAGE('Balance Sheet'!CN50:CO50))^4-1 -> 0.11001777 | CP26: =(1-CP25/AVERAGE('Balance Sheet'!CO50:CP50))^4-1 -> 0.11908937 | CQ26: =(1-CQ25/AVERAGE('Balance Sheet'!CP50:CQ50))^4-1 -> 0.16680104 | CR26: =-CR25/AVERAGE('Balance Sheet'!CN50:CQ50) -> 0.11500482 | CS26: =(1-CS25/AVERAGE('Balance Sheet'!CR50:CS50))^4-1 -> 0.12160395 | CT26: =(1-CT25/AVERAGE('Balance Sheet'!CS50:CT50))^4-1 -> 0.12529839 | CU26: =(1-CU25/AVERAGE('Balance Sheet'!CT50:CU50))^4-1 -> 0.10535499 | CV26: =(1-CV25/AVERAGE('Balance Sheet'!CU50:CV50))^4-1 -> 0.11011659 | CW26: =-CW25/AVERAGE('Balance Sheet'!CS50:CV50) -> 0.11044755 | CX26: =(1-CX25/AVERAGE('Balance Sheet'!CW50:CX50))^4-1 -> 0.11776188 | CY26: =(1-CY25/AVERAGE('Balance Sheet'!CX50:CY50))^4-1 -> 0.11049727 | CZ26: =(1-CZ25/AVERAGE('Balance Sheet'!CY50:CZ50))^4-1 -> 0.099120583 | DA26: =(1-DA25/AVERAGE('Balance Sheet'!CZ50:DA50))^4-1 -> 0.11261643 | DB26: =-DB25/AVERAGE('Balance Sheet'!CX50:DA50) -> 0.10350685 | DC26: =(1-DC25/AVERAGE('Balance Sheet'!DB50:DC50))^4-1 -> 0.1030271 | DD26: =(1-DD25/AVERAGE('Balance Sheet'!DC50:DD50))^4-1 -> 0.11666546 | DE26: =(1-DE25/AVERAGE('Balance Sheet'!DD50:DE50))^4-1 -> 0.10668343 | DF26: =(1-DF25/AVERAGE('Balance Sheet'!DE50:DF50))^4-1 -> 0.099695683 | DG26: =-DG25/AVERAGE('Balance Sheet'!DC50:DF50) -> 0.09750878 | DH26: =(1-DH25/AVERAGE('Balance Sheet'!DG50:DH50))^4-1 -> 0.10438448 | DI26: =(1-DI25/AVERAGE('Balance Sheet'!DH50:DI50))^4-1 -> 0.12238386 | DJ26: =(1-DJ25/AVERAGE('Balance Sheet'!DI50:DJ50))^4-1 -> 0.11166437 | DK26: =(1-DK25/AVERAGE('Balance Sheet'!DJ50:DK50))^4-1 -> 0.10763667 | DL26: =-DL25/AVERAGE('Balance Sheet'!DH50:DK50) -> 0.1068223 | DM26: =(1-DM25/AVERAGE('Balance Sheet'!DL50:DM50))^4-1 -> 0.11085902 | DN26: =(1-DN25/AVERAGE('Balance Sheet'!DM50:DN50))^4-1 -> 0.11085902 | DO26: =(1-DO25/AVERAGE('Balance Sheet'!DN50:DO50))^4-1 -> 0.11085902 | DP26: =(1-DP25/AVERAGE('Balance Sheet'!DO50:DP50))^4-1 -> 0.11085902 | DQ26: =-DQ25/AVERAGE('Balance Sheet'!DM50:DP50) -> 0.10583061 | DR26: =(1-DR25/AVERAGE('Balance Sheet'!DQ50:DR50))^4-1 -> 0.11085902 | DS26: =(1-DS25/AVERAGE('Balance Sheet'!DR50:DS50))^4-1 -> 0.11085902 | DT26: =(1-DT25/AVERAGE('Balance Sheet'!DS50:DT50))^4-1 -> 0.11085902 | DU26: =(1-DU25/AVERAGE('Balance Sheet'!DT50:DU50))^4-1 -> 0.11085902 | DV26: =-DV25/AVERAGE('Balance Sheet'!DR50:DU50) -> 0.10586526 | DW26: =(1-DW25/AVERAGE('Balance Sheet'!DV50:DW50))^4-1 -> 0.11085902 | DX26: =(1-DX25/AVERAGE('Balance Sheet'!DW50:DX50))^4-1 -> 0.11085902 | DY26: =(1-DY25/AVERAGE('Balance Sheet'!DX50:DY50))^4-1 -> 0.11085902 | DZ26: =(1-DZ25/AVERAGE('Balance Sheet'!DY50:DZ50))^4-1 -> 0.11085902 | EA26: =-EA25/AVERAGE('Balance Sheet'!DW50:DZ50) -> 0.10589663 | EB26: =(1-EB25/AVERAGE('Balance Sheet'!EA50:EB50))^4-1 -> 0.11085902 | EC26: =(1-EC25/AVERAGE('Balance Sheet'!EB50:EC50))^4-1 -> 0.11085902 | ED26: =(1-ED25/AVERAGE('Balance Sheet'!EC50:ED50))^4-1 -> 0.11085902 | EE26: =(1-EE25/AVERAGE('Balance Sheet'!ED50:EE50))^4-1 -> 0.11085902 | EF26: =-EF25/AVERAGE('Balance Sheet'!EB50:EE50) -> 0.10592516
A27: Monetary Variation (when applicable) | F27: =SUM(B27:E27) -> 0 | G27: 0 | H27: 0 | I27: 0 | J27: 0 | K27: =SUM(G27:J27) -> 0 | L27: 0 | M27: 0 | N27: 0 | O27: 0 | P27: =SUM(L27:O27) -> 0 | Q27: =(27928-8864)/3 -> 6354.6667 | R27: =(27928-8864)/3 -> 6354.6667 | S27: =(27928-8864)/3 -> 6354.6667 | T27: 8864 | U27: =SUM(Q27:T27) -> 27928 | V27: =45419-X27-W27 -> 7546 | W27: 9774 | X27: 28099 | Y27: 36134 | Z27: =SUM(V27:Y27) -> 81553 | AA27: 25669 | AB27: 8368 | AC27: 17749 | AD27: 30960 | AE27: =SUM(AA27:AD27) -> 82746 | AF27: =26726 -> 26726 | AG27: 38710 | AH27: 41714 | AI27: 41788 | AJ27: =SUM(AF27:AI27) -> 148938 | AK27: 22649 | AL27: =46605-AK27 -> 23956 | AM27: =90051-AK27-AL27 -> 43446 | AN27: =121336-AK27-AL27-AM27 -> 31285 | AO27: =SUM(AK27:AN27) -> 121336 | AP27: =42089-AQ27 -> 17610 | AQ27: 24479 | AR27: =3390 -> 3390 | AS27: =41250-AP27-AQ27-AR27 -> -4229 | AT27: =SUM(AP27:AS27) -> 41250 | AU27: =21752+11688-AV27 -> 16973 | AV27: =9826+6641 -> 16467 | AW27: =7234+5976 -> 13210 | AX27: =37487+25129-AU27-AV27-AW27 -> 15966 | AY27: =SUM(AU27:AX27) -> 62616 | AZ27: =7112+8784 -> 15896 | BA27: =5703+7605 -> 13308 | BB27: =5905+8901 -> 14806 | BC27: =20945+34376-AZ27-BA27-BB27 -> 11311 | BD27: =SUM(AZ27:BC27) -> 55321 | BE27: =2363+10366 -> 12729 | BF27: =3311+7400 -> 10711 | BG27: =2107+7199 -> 9306 | BH27: =9928+31214-BE27-BF27-BG27 -> 8396 | BI27: =SUM(BE27:BH27) -> 41142 | BJ27: =2+4195 -> 4197 | BK27: =-1+5319 -> 5318 | BL27: =0+5832 -> 5832 | BM27: =0+19129-BJ27-BK27-BL27 -> 3782 | BN27: =SUM(BJ27:BM27) -> 19129 | BO27: =4394 -> 4394 | BP27: =3870 -> 3870 | BQ27: 3813 | BR27: =0+16951-BO27-BP27-BQ27 -> 4874 | BS27: =SUM(BO27:BR27) -> 16951 | BT27: 2419 | BU27: 4406 | BV27: 7053 | BW27: =18368-BT27-BU27-BV27 -> 4490 | BX27: =SUM(BT27:BW27) -> 18368 | BY27: 3706 | BZ27: 3491 | CA27: 4456 | CB27: =13952-BY27-BZ27-CA27 -> 2299 | CC27: =SUM(BY27:CB27) -> 13952 | CD27: 3636 | CE27: 7983 | CF27: 3275 | CG27: =16893-CD27-CE27-CF27 -> 1999 | CH27: =SUM(CD27:CG27) -> 16893 | CI27: 1331 | CJ27: 3302 | CK27: 2205 | CL27: =9604-CI27-CJ27-CK27 -> 2766 | CM27: =SUM(CI27:CL27) -> 9604 | CN27: 8812 | CO27: 6919 | CP27: 3596 | CQ27: =25758-CN27-CO27-CP27 -> 6431 | CR27: =SUM(CN27:CQ27) -> 25758 | CS27: 2892 | CT27: 3001 | CU27: 4105 | CV27: =12373-CS27-CT27-CU27 -> 2375 | CW27: =SUM(CS27:CV27) -> 12373 | CX27: 3748 | CY27: 4081 | CZ27: 3070 | DA27: =14546-CX27-CY27-CZ27 -> 3647 | DB27: =SUM(CX27:DA27) -> 14546 | DC27: 3739 | DD27: 3606 | DE27: 8715 | DF27: =22827-DC27-DD27-DE27 -> 6767 | DG27: =SUM(DC27:DF27) -> 22827 | DH27: 2745 | DI27: 3687 | DJ27: =AVERAGE('Balance Sheet'!DI9:DJ9)*0.5% -> 9440.8808 | DK27: =AVERAGE('Balance Sheet'!DJ9:DK9)*0.5% -> 11989.125 | DL27: =SUM(DH27:DK27) -> 27862.006 | DM27: =AVERAGE('Balance Sheet'!DL9:DM9)*0.25% -> 6730.9949 | DN27: =AVERAGE('Balance Sheet'!DM9:DN9)*0.25% -> 7524.3778 | DO27: =AVERAGE('Balance Sheet'!DN9:DO9)*0.25% -> 8649.6183 | DP27: =AVERAGE('Balance Sheet'!DO9:DP9)*0.25% -> 9697.1862 | DQ27: =SUM(DM27:DP27) -> 32602.177 | DR27: =AVERAGE('Balance Sheet'!DQ9:DR9)*0.25% -> 10731.779 | DS27: =AVERAGE('Balance Sheet'!DR9:DS9)*0.25% -> 11762.051 | DT27: =AVERAGE('Balance Sheet'!DS9:DT9)*0.25% -> 12538.464 | DU27: =AVERAGE('Balance Sheet'!DT9:DU9)*0.25% -> 13367.256 | DV27: =SUM(DR27:DU27) -> 48399.55 | DW27: =AVERAGE('Balance Sheet'!DV9:DW9)*0.25% -> 14083.799 | DX27: =AVERAGE('Balance Sheet'!DW9:DX9)*0.25% -> 14543.499 | DY27: =AVERAGE('Balance Sheet'!DX9:DY9)*0.25% -> 14740.026 | DZ27: =AVERAGE('Balance Sheet'!DY9:DZ9)*0.25% -> 14637.168 | EA27: =SUM(DW27:DZ27) -> 58004.491 | EB27: =AVERAGE('Balance Sheet'!EA9:EB9)*0.25% -> 14441.875 | EC27: =AVERAGE('Balance Sheet'!EB9:EC9)*0.25% -> 14360.512 | ED27: =AVERAGE('Balance Sheet'!EC9:ED9)*0.25% -> 14445.73 | EE27: =AVERAGE('Balance Sheet'!ED9:EE9)*0.25% -> 14413.139 | EF27: =SUM(EB27:EE27) -> 57661.256
A28: Other Operating Income | B28: =B29+B30 -> 0 | C28: =C29+C30 -> 0 | D28: =D29+D30 -> 0 | E28: =E29+E30 -> 0 | F28: =SUM(B28:E28) -> 0 | G28: =G29+G30 -> 0 | H28: =H29+H30 -> 0 | I28: =I29+I30 -> 0 | J28: =J29+J30 -> 0 | K28: =SUM(G28:J28) -> 0 | L28: =L29+L30 -> 0 | M28: =M29+M30 -> 0 | N28: =N29+N30 -> 0 | O28: =O29+O30 -> 0 | P28: =SUM(L28:O28) -> 0 | Q28: =Q29+Q30 -> 0 | R28: =R29+R30 -> 0 | S28: =S29+S30 -> 0 | T28: =T29+T30 -> 0 | U28: =SUM(Q28:T28) -> 0 | V28: =V29+V30 -> 0 | W28: =W29+W30 -> 0 | X28: =X29+X30 -> 0 | Y28: =Y29+Y30 -> 0 | Z28: =SUM(V28:Y28) -> 0 | AA28: =AA29+AA30 -> 0 | AB28: =AB29+AB30 -> 0 | AC28: =AC29+AC30 -> 80632 | AD28: =AD29+AD30 -> 0 | AE28: =SUM(AA28:AD28) -> 80632 | AF28: =AF29+AF30 -> 0 | AG28: =AG29+AG30 -> 0 | AH28: =AH29+AH30 -> 0 | AI28: =AI29+AI30 -> 0 | AJ28: =SUM(AF28:AI28) -> 0 | AK28: =AK29+AK30 -> 0 | AL28: =AL29+AL30 -> 0 | AM28: =AM29+AM30 -> 0 | AN28: =AN29+AN30 -> 0 | AO28: =SUM(AK28:AN28) -> 0 | AP28: =AP29+AP30 -> 0 | AQ28: =AQ29+AQ30 -> 0 | AR28: =AR29+AR30 -> 0 | AS28: =AS29+AS30 -> 0 | AT28: =SUM(AP28:AS28) -> 0 | AU28: =AU29+AU30 -> 0 | AV28: =AV29+AV30 -> 0 | AW28: =AW29+AW30 -> 0 | AX28: =AX29+AX30 -> 0 | AY28: =SUM(AU28:AX28) -> 0 | AZ28: =AZ29+AZ30 -> 0 | BA28: =BA29+BA30 -> 0 | BB28: =BB29+BB30 -> 0 | BC28: =BC29+BC30 -> 0 | BD28: =SUM(AZ28:BC28) -> 0 | BE28: =BE29+BE30 -> 0 | BF28: =BF29+BF30 -> 0 | BG28: =BG29+BG30 -> 0 | BH28: =BH29+BH30 -> 0 | BI28: =SUM(BE28:BH28) -> 0 | BJ28: =BJ29+BJ30 -> 0 | BK28: =BK29+BK30 -> 0 | BL28: =BL29+BL30 -> 0 | BM28: =BM29+BM30 -> 0 | BN28: =SUM(BJ28:BM28) -> 0 | BO28: =BO29+BO30 -> 0 | BP28: =BP29+BP30 -> 0 | BQ28: =BQ29+BQ30 -> 0 | BR28: =BR29+BR30 -> 0 | BS28: =SUM(BO28:BR28) -> 0 | BT28: =BT29+BT30 -> 0 | BU28: =BU29+BU30 -> 0 | BV28: =BV29+BV30 -> 0 | BW28: =BW29+BW30 -> 20000 | BX28: =SUM(BT28:BW28) -> 20000 | BY28: =BY29+BY30 -> 0 | BZ28: =BZ29+BZ30 -> 0 | CA28: =CA29+CA30 -> 0 | CB28: =CB29+CB30 -> 0 | CC28: =SUM(BY28:CB28) -> 0 | CD28: =CD29+CD30 -> 0 | CE28: =CE29+CE30 -> 0 | CF28: =CF29+CF30 -> 1153000 | CG28: =CG29+CG30 -> 0 | CH28: =SUM(CD28:CG28) -> 1153000 | CI28: =CI29+CI30 -> 0 | CJ28: =CJ29+CJ30 -> 0 | CK28: =CK29+CK30 -> 0 | CL28: =CL29+CL30 -> 0 | CM28: =SUM(CI28:CL28) -> 0 | CN28: =CN29+CN30 -> 0 | CO28: =CO29+CO30 -> 0 | CP28: =CP29+CP30 -> 0 | CQ28: =CQ29+CQ30 -> 0 | CR28: =SUM(CN28:CQ28) -> 0 | CS28: =CS29+CS30 -> 0 | CT28: =CT29+CT30 -> 0 | CU28: =CU29+CU30 -> 0 | CV28: =CV29+CV30 -> 0 | CW28: =SUM(CS28:CV28) -> 0 | CX28: =CX29+CX30 -> 0 | CY28: =CY29+CY30 -> 0 | CZ28: =CZ29+CZ30 -> 0 | DA28: =DA29+DA30 -> 0 | DB28: =SUM(CX28:DA28) -> 0 | DC28: =DC29+DC30 -> 0 | DD28: =DD29+DD30 -> 0 | DE28: =DE29+DE30 -> 0 | DF28: =DF29+DF30 -> 0 | DG28: =SUM(DC28:DF28) -> 0 | DH28: =DH29+DH30 -> 0 | DI28: =DI29+DI30 -> 0 | DJ28: =DJ29+DJ30 -> 0 | DK28: =DK29+DK30 -> 0 | DL28: =SUM(DH28:DK28) -> 0 | DM28: =DM29+DM30 -> 0 | DN28: =DN29+DN30 -> 0 | DO28: =DO29+DO30 -> 0 | DP28: =DP29+DP30 -> 0 | DQ28: =SUM(DM28:DP28) -> 0 | DR28: =DR29+DR30 -> 0 | DS28: =DS29+DS30 -> 0 | DT28: =DT29+DT30 -> 0 | DU28: =DU29+DU30 -> 0 | DV28: =SUM(DR28:DU28) -> 0 | DW28: =DW29+DW30 -> 0 | DX28: =DX29+DX30 -> 0 | DY28: =DY29+DY30 -> 0 | DZ28: =DZ29+DZ30 -> 0 | EA28: =SUM(DW28:DZ28) -> 0 | EB28: =EB29+EB30 -> 0 | EC28: =EC29+EC30 -> 0 | ED28: =ED29+ED30 -> 0 | EE28: =EE29+EE30 -> 0 | EF28: =SUM(EB28:EE28) -> 0
A29: Client Financing (when applicable) | B29: 0 | C29: 0 | D29: 0 | E29: 0 | F29: =SUM(B29:E29) -> 0 | G29: 0 | H29: 0 | I29: 0 | J29: 0 | K29: =SUM(G29:J29) -> 0 | L29: 0 | M29: 0 | N29: 0 | O29: 0 | P29: =SUM(L29:O29) -> 0 | Q29: 0 | R29: 0 | S29: 0 | T29: 0 | U29: =SUM(Q29:T29) -> 0 | V29: 0 | W29: 0 | X29: 0 | Y29: 0 | Z29: =SUM(V29:Y29) -> 0 | AA29: 0 | AB29: 0 | AC29: 0 | AD29: 0 | AE29: =SUM(AA29:AD29) -> 0 | AF29: 0 | AG29: 0 | AH29: 0 | AI29: 0 | AJ29: =SUM(AF29:AI29) -> 0 | AK29: 0 | AL29: 0 | AM29: 0 | AN29: 0 | AO29: =SUM(AK29:AN29) -> 0 | AP29: 0 | AQ29: 0 | AR29: 0 | AS29: 0 | AT29: =SUM(AP29:AS29) -> 0 | AU29: 0 | AV29: 0 | AW29: 0 | AX29: 0 | AY29: =SUM(AU29:AX29) -> 0 | AZ29: 0 | BA29: 0 | BB29: 0 | BC29: 0 | BD29: =SUM(AZ29:BC29) -> 0 | BE29: 0 | BF29: 0 | BG29: 0 | BH29: 0 | BI29: =SUM(BE29:BH29) -> 0 | BJ29: 0 | BK29: 0 | BL29: 0 | BM29: 0 | BN29: =SUM(BJ29:BM29) -> 0 | BO29: 0 | BP29: 0 | BQ29: 0 | BR29: 0 | BS29: =SUM(BO29:BR29) -> 0 | BT29: 0 | BU29: 0 | BV29: 0 | BW29: 0 | BX29: =SUM(BT29:BW29) -> 0 | BY29: 0 | BZ29: 0 | CA29: 0 | CB29: 0 | CC29: =SUM(BY29:CB29) -> 0 | CD29: 0 | CE29: 0 | CF29: 0 | CG29: 0 | CH29: =SUM(CD29:CG29) -> 0 | CI29: 0 | CJ29: 0 | CK29: 0 | CL29: 0 | CM29: =SUM(CI29:CL29) -> 0 | CN29: 0 | CO29: 0 | CP29: 0 | CQ29: 0 | CR29: =SUM(CN29:CQ29) -> 0 | CS29: 0 | CT29: 0 | CU29: 0 | CV29: 0 | CW29: =SUM(CS29:CV29) -> 0 | CX29: 0 | CY29: 0 | CZ29: 0 | DA29: 0 | DB29: =SUM(CX29:DA29) -> 0 | DC29: 0 | DD29: 0 | DE29: 0 | DF29: 0 | DG29: =SUM(DC29:DF29) -> 0 | DH29: 0 | DI29: 0 | DJ29: 0 | DK29: 0 | DL29: =SUM(DH29:DK29) -> 0 | DM29: 0 | DN29: 0 | DO29: 0 | DP29: 0 | DQ29: =SUM(DM29:DP29) -> 0 | DR29: 0 | DS29: 0 | DT29: 0 | DU29: 0 | DV29: =SUM(DR29:DU29) -> 0 | DW29: 0 | DX29: 0 | DY29: 0 | DZ29: 0 | EA29: =SUM(DW29:DZ29) -> 0 | EB29: 0 | EC29: 0 | ED29: 0 | EE29: 0 | EF29: =SUM(EB29:EE29) -> 0
A30: Extraordinary items | F30: =SUM(B30:E30) -> 0 | G30: 0 | H30: 0 | I30: 0 | J30: 0 | K30: =SUM(G30:J30) -> 0 | L30: 0 | M30: 0 | N30: 0 | O30: 0 | P30: =SUM(L30:O30) -> 0 | Q30: 0 | R30: 0 | S30: 0 | T30: 0 | U30: =SUM(Q30:T30) -> 0 | V30: 0 | W30: 0 | X30: 0 | Y30: 0 | Z30: =SUM(V30:Y30) -> 0 | AA30: 0 | AB30: 0 | AC30: 80632 | AD30: 0 | AE30: =SUM(AA30:AD30) -> 80632 | AF30: 0 | AG30: 0 | AH30: 0 | AI30: 0 | AJ30: =SUM(AF30:AI30) -> 0 | AK30: =AVERAGE(AF30:AI30) -> 0 | AL30: =AK30*AL12/AK12 -> 0 | AM30: =AL30*AM12/AL12 -> 0 | AN30: =AM30*AN12/AM12 -> 0 | AO30: =SUM(AK30:AN30) -> 0 | AP30: =AVERAGE(AK30:AN30) -> 0 | AQ30: =AP30*AQ12/AP12 -> 0 | AR30: =AQ30*AR12/AQ12 -> 0 | AS30: =AR30*AS12/AR12 -> 0 | AT30: =SUM(AP30:AS30) -> 0 | AU30: =AVERAGE(AP30:AS30) -> 0 | AV30: =AU30*AV12/AU12 -> 0 | AW30: =AV30*AW12/AV12 -> 0 | AX30: =AW30*AX12/AW12 -> 0 | AY30: =SUM(AU30:AX30) -> 0 | AZ30: =AVERAGE(AU30:AX30) -> 0 | BA30: =AZ30*BA12/AZ12 -> 0 | BB30: =BA30*BB12/BA12 -> 0 | BC30: =BB30*BC12/BB12 -> 0 | BD30: =SUM(AZ30:BC30) -> 0 | BE30: =AVERAGE(AZ30:BC30) -> 0 | BF30: =BE30*BF12/BE12 -> 0 | BG30: =BF30*BG12/BF12 -> 0 | BH30: =BG30*BH12/BG12 -> 0 | BI30: =SUM(BE30:BH30) -> 0 | BJ30: =AVERAGE(BE30:BH30) -> 0 | BK30: =BJ30*BK12/BJ12 -> 0 | BL30: =BK30*BL12/BK12 -> 0 | BM30: =BL30*BM12/BL12 -> 0 | BN30: =SUM(BJ30:BM30) -> 0 | BO30: =AVERAGE(BJ30:BM30) -> 0 | BP30: =BO30*BP12/BO12 -> 0 | BQ30: =BP30*BQ12/BP12 -> 0 | BR30: =BQ30*BR12/BQ12 -> 0 | BS30: =SUM(BO30:BR30) -> 0 | BT30: =AVERAGE(BO30:BR30) -> 0 | BU30: =BT30*BU12/BT12 -> 0 | BV30: =BU30*BV12/BU12 -> 0 | BW30: =254000-167000-67000 -> 20000 | BX30: =SUM(BT30:BW30) -> 20000 | BY30: 0 | BZ30: =BY30*BZ12/BY12 -> 0 | CA30: =BZ30*CA12/BZ12 -> 0 | CB30: =CA30*CB12/CA12 -> 0 | CC30: =SUM(BY30:CB30) -> 0 | CD30: 0 | CE30: 0 | CF30: =1403000-250000 -> 1153000 | CG30: 0 | CH30: =SUM(CD30:CG30) -> 1153000 | CI30: 0 | CJ30: 0 | CK30: 0 | CL30: 0 | CM30: =SUM(CI30:CL30) -> 0 | CN30: 0 | CO30: 0 | CP30: 0 | CQ30: 0 | CR30: =SUM(CN30:CQ30) -> 0 | CS30: 0 | CT30: 0 | CU30: 0 | CV30: 0 | CW30: =SUM(CS30:CV30) -> 0 | CX30: 0 | CY30: 0 | CZ30: 0 | DA30: 0 | DB30: =SUM(CX30:DA30) -> 0 | DC30: 0 | DD30: 0 | DE30: 0 | DF30: 0 | DG30: =SUM(DC30:DF30) -> 0 | DH30: 0 | DI30: 0 | DJ30: =DI30*DJ12/DI12 -> 0 | DK30: =DJ30*DK12/DJ12 -> 0 | DL30: =SUM(DH30:DK30) -> 0 | DM30: =AVERAGE(DH30:DK30) -> 0 | DN30: =DM30*DN12/DM12 -> 0 | DO30: =DN30*DO12/DN12 -> 0 | DP30: =DO30*DP12/DO12 -> 0 | DQ30: =SUM(DM30:DP30) -> 0 | DR30: =AVERAGE(DM30:DP30) -> 0 | DS30: =DR30*DS12/DR12 -> 0 | DT30: =DS30*DT12/DS12 -> 0 | DU30: =DT30*DU12/DT12 -> 0 | DV30: =SUM(DR30:DU30) -> 0 | DW30: =AVERAGE(DR30:DU30) -> 0 | DX30: =DW30*DX12/DW12 -> 0 | DY30: =DX30*DY12/DX12 -> 0 | DZ30: =DY30*DZ12/DY12 -> 0 | EA30: =SUM(DW30:DZ30) -> 0 | EB30: =AVERAGE(DW30:DZ30) -> 0 | EC30: =EB30*EC12/EB12 -> 0 | ED30: =EC30*ED12/EC12 -> 0 | EE30: =ED30*EE12/ED12 -> 0 | EF30: =SUM(EB30:EE30) -> 0
A31: Other Operating Expenses | B31: =B32+B33+B34 -> 1497.5 | C31: =C32+C33+C34 -> 1497.5 | D31: =D32+D33+D34 -> -3121 | E31: =E32+E33+E34 -> 2876 | F31: =SUM(B31:E31) -> 2750 | G31: =G32+G33+G34 -> 1656 | H31: =H32+H33+H34 -> 973 | I31: =I32+I33+I34 -> -27532 | J31: =J32+J33+J34 -> 140 | K31: =SUM(G31:J31) -> -24763 | L31: =L32+L33+L34 -> 629 | M31: =M32+M33+M34 -> 4704 | N31: =N32+N33+N34 -> -22217 | O31: =O32+O33+O34 -> -623 | P31: =SUM(L31:O31) -> -17507 | Q31: =Q32+Q33+Q34 -> -260 | R31: =R32+R33+R34 -> 113281 | S31: =S32+S33+S34 -> 139 | T31: =T32+T33+T34 -> 1147 | U31: =SUM(Q31:T31) -> 114307 | V31: =V32+V33+V34 -> 454 | W31: =W32+W33+W34 -> 1118 | X31: =X32+X33+X34 -> 1066 | Y31: =Y32+Y33+Y34 -> -964 | Z31: =SUM(V31:Y31) -> 1674 | AA31: =AA32+AA33+AA34 -> -2938 | AB31: =AB32+AB33+AB34 -> -1114 | AC31: =AC32+AC33+AC34 -> -16289 | AD31: =AD32+AD33+AD34 -> -33654 | AE31: =SUM(AA31:AD31) -> -53995 | AF31: =AF32+AF33+AF34 -> -18319 | AG31: =AG32+AG33+AG34 -> -10848 | AH31: =AH32+AH33+AH34 -> -11262 | AI31: =AI32+AI33+AI34 -> -19250 | AJ31: =SUM(AF31:AI31) -> -59679 | AK31: =AK32+AK33+AK34 -> -2558 | AL31: =AL32+AL33+AL34 -> -2360 | AM31: =AM32+AM33+AM34 -> -5676 | AN31: =AN32+AN33+AN34 -> -36765 | AO31: =SUM(AK31:AN31) -> -47359 | AP31: =AP32+AP33+AP34 -> -26056 | AQ31: =AQ32+AQ33+AQ34 -> -14249 | AR31: =AR32+AR33+AR34 -> -12641 | AS31: =AS32+AS33+AS34 -> -2202 | AT31: =SUM(AP31:AS31) -> -55148 | AU31: =AU32+AU33+AU34 -> -15625 | AV31: =AV32+AV33+AV34 -> -20556 | AW31: =AW32+AW33+AW34 -> -11063 | AX31: =AX32+AX33+AX34 -> -9794 | AY31: =SUM(AU31:AX31) -> -57038 | AZ31: =AZ32+AZ33+AZ34 -> -14758 | BA31: =BA32+BA33+BA34 -> -16717 | BB31: =BB32+BB33+BB34 -> -32302 | BC31: =BC32+BC33+BC34 -> -51022 | BD31: =SUM(AZ31:BC31) -> -114799 | BE31: =BE32+BE33+BE34 -> -28353 | BF31: =BF32+BF33+BF34 -> 3216 | BG31: =BG32+BG33+BG34 -> -1513 | BH31: =BH32+BH33+BH34 -> -26931 | BI31: =SUM(BE31:BH31) -> -53581 | BJ31: =BJ32+BJ33+BJ34 -> -11807 | BK31: =BK32+BK33+BK34 -> -18604 | BL31: =BL32+BL33+BL34 -> -19828 | BM31: =BM32+BM33+BM34 -> -50573 | BN31: =SUM(BJ31:BM31) -> -100812 | BO31: =BO32+BO33+BO34 -> -14495 | BP31: =BP32+BP33+BP34 -> -149746 | BQ31: =BQ32+BQ33+BQ34 -> 16317 | BR31: =BR32+BR33+BR34 -> -23157 | BS31: =SUM(BO31:BR31) -> -171081 | BT31: =BT32+BT33+BT34 -> -4672 | BU31: =BU32+BU33+BU34 -> -36070 | BV31: =BV32+BV33+BV34 -> -133002 | BW31: =BW32+BW33+BW34 -> -74971 | BX31: =SUM(BT31:BW31) -> -248715 | BY31: =BY32+BY33+BY34 -> -27820 | BZ31: =BZ32+BZ33+BZ34 -> 1272 | CA31: =CA32+CA33+CA34 -> -22314 | CB31: =CB32+CB33+CB34 -> 19528 | CC31: =SUM(BY31:CB31) -> -29334 | CD31: =CD32+CD33+CD34 -> -40355 | CE31: =CE32+CE33+CE34 -> -20788 | CF31: =CF32+CF33+CF34 -> -29104 | CG31: =CG32+CG33+CG34 -> 26862 | CH31: =SUM(CD31:CG31) -> -63385 | CI31: =CI32+CI33+CI34 -> -31171 | CJ31: =CJ32+CJ33+CJ34 -> -14738 | CK31: =CK32+CK33+CK34 -> -35335 | CL31: =CL32+CL33+CL34 -> -9530 | CM31: =SUM(CI31:CL31) -> -90774 | CN31: =CN32+CN33+CN34 -> -30483 | CO31: =CO32+CO33+CO34 -> -21795 | CP31: =CP32+CP33+CP34 -> 27790 | CQ31: =CQ32+CQ33+CQ34 -> 13030 | CR31: =SUM(CN31:CQ31) -> -11458 | CS31: =CS32+CS33+CS34 -> -37625 | CT31: =CT32+CT33+CT34 -> 16531 | CU31: =CU32+CU33+CU34 -> -54025 | CV31: =CV32+CV33+CV34 -> -25956 | CW31: =SUM(CS31:CV31) -> -101075 | CX31: =CX32+CX33+CX34 -> -18668 | CY31: =CY32+CY33+CY34 -> -10492 | CZ31: =CZ32+CZ33+CZ34 -> -3423 | DA31: =DA32+DA33+DA34 -> -33704 | DB31: =SUM(CX31:DA31) -> -66287 | DC31: =DC32+DC33+DC34 -> -70720 | DD31: =DD32+DD33+DD34 -> -38346 | DE31: =DE32+DE33+DE34 -> 188788 | DF31: =DF32+DF33+DF34 -> -71050 | DG31: =SUM(DC31:DF31) -> 8672 | DH31: =DH32+DH33+DH34 -> -64455 | DI31: =DI32+DI33+DI34 -> -68131 | DJ31: =DJ32+DJ33+DJ34 -> -70139.816 | DK31: =DK32+DK33+DK34 -> -73431.98 | DL31: =SUM(DH31:DK31) -> -276157.8 | DM31: =DM32+DM33+DM34 -> -86338.675 | DN31: =DN32+DN33+DN34 -> -88487.465 | DO31: =DO32+DO33+DO34 -> -90321.643 | DP31: =DP32+DP33+DP34 -> -94713.539 | DQ31: =SUM(DM31:DP31) -> -359861.32 | DR31: =DR32+DR33+DR34 -> -92305.255 | DS31: =DS32+DS33+DS34 -> -94209.488 | DT31: =DT32+DT33+DT34 -> -95916.094 | DU31: =DU32+DU33+DU34 -> -100320.01 | DV31: =SUM(DR31:DU31) -> -382750.85 | DW31: =DW32+DW33+DW34 -> -97519.206 | DX31: =DX32+DX33+DX34 -> -99400.559 | DY31: =DY32+DY33+DY34 -> -101048.08 | DZ31: =DZ32+DZ33+DZ34 -> -105552.17 | EA31: =SUM(DW31:DZ31) -> -403520.01 | EB31: =EB32+EB33+EB34 -> -102482.97 | EC31: =EC32+EC33+EC34 -> -104375.97 | ED31: =ED32+ED33+ED34 -> -105991.77 | EE31: =EE32+EE33+EE34 -> -110584.08 | EF31: =SUM(EB31:EE31) -> -423434.79
A32: Expenses | B32: =1497.5-B33 -> 2260.5 | C32: =+B32+B33-C33 -> 2741.5 | D32: =-3121-D33 -> -2098 | E32: =2876-E33 -> 3346 | F32: =SUM(B32:E32) -> 6250 | G32: =1656-G33 -> 2762 | H32: =973-H33 -> 1624 | I32: =-1806-I33 -> -789 | J32: =140-J33 -> 453 | K32: =SUM(G32:J32) -> 4050 | L32: =629-L33 -> 1423 | M32: =5818-M33 -> 7051 | N32: =3943-L32-M32-N33-M33-L33 -> -932 | O32: =3320-SUM(L32:N32)-SUM(L33:O33) -> 836 | P32: =SUM(L32:O32) -> 8378 | Q32: =-260-Q33 -> 4906 | R32: =127-Q32-R33-Q33 -> 9609 | S32: =139-S33 -> 1829 | T32: =1147-T33 -> 1152 | U32: =SUM(Q32:T32) -> 17496 | V32: =454-V33 -> 2276 | W32: =1118-W33 -> 13988 | X32: =1066-X33 -> 4929 | Y32: =-964-Y33 -> 2251 | Z32: =SUM(V32:Y32) -> 23444 | AA32: =49 -> 49 | AB32: =2136 -> 2136 | AC32: =-80632+67647 -> -12985 | AD32: =-6802 -> -6802 | AE32: =SUM(AA32:AD32) -> -17602 | AF32: =1 -> 1 | AG32: =68 -> 68 | AH32: 60 | AI32: -275 | AJ32: =SUM(AF32:AI32) -> -146 | AK32: 828 | AL32: 1171 | AM32: 198 | AN32: 0 | AO32: =SUM(AK32:AN32) -> 2197 | AP32: =-13127-AQ32 -> -5149 | AQ32: -7978 | AR32: -10333 | AS32: =-18739-AR32-AQ32-AP32 -> 4721 | AT32: =SUM(AP32:AS32) -> -18739 | AU32: =-19410-AV32 -> -9467 | AV32: =-15943-AV34 -> -9943 | AW32: -8785 | AX32: =-31457-AW32-AV32-AU32 -> -3262 | AY32: =SUM(AU32:AX32) -> -31457 | AZ32: -10095 | BA32: -10485 | BB32: -26960 | BC32: =-93195-BB32-BA32-AZ32 -> -45655 | BD32: =SUM(AZ32:BC32) -> -93195 | BE32: -23928 | BF32: 8873 | BG32: 3183 | BH32: =-31977-BG32-BF32-BE32 -> -20105 | BI32: =SUM(BE32:BH32) -> -31977 | BJ32: -4807 | BK32: -10914 | BL32: -8575 | BM32: =-43869-BL32-BK32-BJ32 -> -19573 | BN32: =SUM(BJ32:BM32) -> -43869 | BO32: 6847 | BP32: -121085 | BQ32: =12013+15179 -> 27192 | BR32: =89804-194350-BQ32-BP32-BO32 -> -17500 | BS32: =SUM(BO32:BR32) -> -104546 | BT32: =52786-41771+180 -> 11195 | BU32: =20547-47033 -> -26486 | BV32: =35318-157445 -> -122127 | BW32: =27831-263185-BV32-BU32-BT32+48008 -> -49928 | BX32: =SUM(BT32:BW32) -> -187346 | BY32: =6551-10012 -> -3461 | BZ32: =8726-15335 -> -6609 | CA32: =34431-25207 -> 9224 | CB32: =-24458+110587-46506+5721-CA32-BZ32-BY32 -> 46190 | CC32: =SUM(BY32:CB32) -> 45344 | CD32: =44875-68031 -> -23156 | CE32: =10194-17257 -> -7063 | CF32: =1367584-109725-(1403000-250000+375000-250000) -> -20141 | CG32: =1492096-226318-CF32-CE32-CD32-(1403000-250000+375000-250000) -> 38138 | CH32: =SUM(CD32:CG32) -> -12222 | CI32: =2155-22394 -> -20239 | CJ32: =5674-9950 -> -4276 | CK32: =47195-71510 -> -24315 | CL32: =79487-130238-CK32-CJ32-CI32 -> -1921 | CM32: =SUM(CI32:CL32) -> -50751 | CN32: =13339-35290 -> -21951 | CO32: =18890-31434 -> -12544 | CP32: =201308-150686 -> 50622 | CQ32: =325209-293193-CP32-CO32-CN32 -> 15889 | CR32: =SUM(CN32:CQ32) -> 32016 | CS32: =8303-16644 -> -8341 | CT32: =90079-57477 -> 32602 | CU32: =26088-37811 -> -11723 | CV32: =123166-157153-CU32-CT32-CS32 -> -46525 | CW32: =SUM(CS32:CV32) -> -33987 | CX32: =50588-45618 -> 4970 | CY32: =90642-84769 -> 5873 | CZ32: =111059-74483 -> 36576 | DA32: =405906-372134-CZ32-CY32-CX32 -> -13647 | DB32: =SUM(CX32:DA32) -> 33772 | DC32: =3278-43726 -> -40448 | DD32: =26238-40782 -> -14544 | DE32: =270767-53350-DE34 -> 4417 | DF32: =424091-282844-DE32-DD32-DC32-DE34 -> -21178 | DG32: =SUM(DC32:DF32) -> -71753 | DH32: =21481-31353 -> -9872 | DI32: =8744-35709 -> -26965 | DJ32: =-1%*DJ5 -> -27467.053 | DK32: =-1%*DK5 -> -30492.764 | DL32: =SUM(DH32:DK32) -> -94796.818 | DM32: =-1.5%*DM5 -> -43131.344 | DN32: =-1.5%*DN5 -> -45010.343 | DO32: =-1.5%*DO5 -> -46573.046 | DP32: =-1.5%*DP5 -> -50691.772 | DQ32: =SUM(DM32:DP32) -> -185406.5 | DR32: =-1.5%*DR5 -> -48008.611 | DS32: =-1.5%*DS5 -> -49636.251 | DT32: =-1.5%*DT5 -> -51064.539 | DU32: =-1.5%*DU5 -> -55188.401 | DV32: =SUM(DR32:DU32) -> -203897.8 | DW32: =-1.5%*DW5 -> -52105.787 | DX32: =-1.5%*DX5 -> -53703.574 | DY32: =-1.5%*DY5 -> -55065.755 | DZ32: =-1.5%*DZ5 -> -59282.727 | EA32: =SUM(DW32:DZ32) -> -220157.84 | EB32: =-1.5%*EB5 -> -55924.621 | EC32: =-1.5%*EC5 -> -57526.907 | ED32: =-1.5%*ED5 -> -58850.177 | EE32: =-1.5%*EE5 -> -63148.127 | EF32: =SUM(EB32:EE32) -> -235449.83
A33: Depreciation&Amortization | B33: =-3500-SUM(C33:E33) -> -763 | C33: -1244 | D33: -1023 | E33: -470 | F33: =SUM(B33:E33) -> -3500 | G33: -1106 | H33: -651 | I33: -1017 | J33: -313 | K33: =SUM(G33:J33) -> -3087 | L33: =-668-126 -> -794 | M33: =-1688-L33-339 -> -1233 | N33: =-2759-840-L33-M33 -> -1572 | O33: =-3564-1494-SUM(L33:N33) -> -1459 | P33: =SUM(L33:O33) -> -5058 | Q33: =-2252-2914 -> -5166 | R33: =-13846-542-Q33 -> -9222 | S33: =-1007-683 -> -1690 | T33: =-526+521 -> -5 | U33: =SUM(Q33:T33) -> -16083 | V33: =-785-1037 -> -1822 | W33: =-1321-11549 -> -12870 | X33: =-1277-2586 -> -3863 | Y33: =-17880-3890-V33-W33-X33 -> -3215 | Z33: =SUM(V33:Y33) -> -21770 | AA33: =-AA68 -> -2987 | AB33: =-AB68 -> -3250 | AC33: =-AC68 -> -3304 | AD33: =-AD68 -> -26852 | AE33: =SUM(AA33:AD33) -> -36393 | AF33: =-AF68 -> -18320 | AG33: =-AG68 -> -10916 | AH33: =-AH68 -> -11322 | AI33: =-AI68 -> -18975 | AJ33: =SUM(AF33:AI33) -> -59533 | AK33: =-741-2645 -> -3386 | AL33: =-1940-4977-AK33 -> -3531 | AM33: =-5926-6865-AK33-AL33 -> -5874 | AN33: =-6826-6510-AK33-AL33-AM33 -> -545 | AO33: =SUM(AK33:AN33) -> -13336 | AP33: =-4139-5039-AQ33 -> -2907 | AQ33: =-2562-3709 -> -6271 | AR33: -2308 | AS33: =-9228-9181-AP33-AQ33-AR33 -> -6923 | AT33: =SUM(AP33:AS33) -> -18409 | AU33: =-6024-4747-AV33 -> -6158 | AV33: =-2286-2327 -> -4613 | AW33: -2278 | AX33: =-10186-9395-SUM(AU33:AW33) -> -6532 | AY33: =SUM(AU33:AX33) -> -19581 | AZ33: =-2303-2360 -> -4663 | BA33: -6232 | BB33: -5342 | BC33: =-21604-SUM(AZ33:BB33) -> -5367 | BD33: =SUM(AZ33:BC33) -> -21604 | BE33: -4425 | BF33: -5657 | BG33: -4696 | BH33: =-21604-SUM(BE33:BG33) -> -6826 | BI33: =SUM(BE33:BH33) -> -21604 | BJ33: -7000 | BK33: -7690 | BL33: -11253 | BM33: -31000 | BN33: =SUM(BJ33:BM33) -> -56943 | BO33: =-BO68 -> -21342 | BP33: =-BP68 -> -28661 | BQ33: -10875 | BR33: =-55495-11040-SUM(BO33:BQ33) -> -5657 | BS33: =SUM(BO33:BR33) -> -66535 | BT33: =-BT68 -> -15867 | BU33: =-BU68 -> -9584 | BV33: -10875 | BW33: =-61369-SUM(BT33:BV33) -> -25043 | BX33: =SUM(BT33:BW33) -> -61369 | BY33: =-BY68 -> -24359 | BZ33: =-BZ68 -> 7881 | CA33: =-CA68 -> -31538 | CB33: =-74678-SUM(BY33:CA33) -> -26662 | CC33: =SUM(BY33:CB33) -> -74678 | CD33: =-CD68 -> -17199 | CE33: =-CE68 -> -13725 | CF33: =-CF68 -> -8963 | CG33: =-51163-SUM(CD33:CF33) -> -11276 | CH33: =SUM(CD33:CG33) -> -51163 | CI33: =-CI68 -> -10932 | CJ33: =-CJ68 -> -10462 | CK33: =-CK68 -> -11020 | CL33: =-40023-SUM(CI33:CK33) -> -7609 | CM33: =SUM(CI33:CL33) -> -40023 | CN33: =-CN68 -> -8532 | CO33: =-CO68 -> -9251 | CP33: =-CP68 -> -22832 | CQ33: =-43474-SUM(CN33:CP33) -> -2859 | CR33: =SUM(CN33:CQ33) -> -43474 | CS33: =-CS68 -> -29284 | CT33: =-CT68 -> -16071 | CU33: =-CU68 -> -42302 | CV33: =-67088-SUM(CS33:CU33) -> 20569 | CW33: =SUM(CS33:CV33) -> -67088 | CX33: =-CX68 -> -23638 | CY33: =-CY68 -> -16365 | CZ33: =-CZ68 -> -39999 | DA33: =-DA68 -> -20057 | DB33: =SUM(CX33:DA33) -> -100059 | DC33: =-DC68 -> -30272 | DD33: =-DD68 -> -23802 | DE33: =-DE68 -> -28629 | DF33: =-DF68 -> -49872 | DG33: =SUM(DC33:DF33) -> -132575 | DH33: =-DH68 -> -54583 | DI33: =-DI68 -> -41166 | DJ33: =DI33*DJ68/DI68 -> -42672.762 | DK33: =DJ33*DK68/DJ68 -> -42939.215 | DL33: =SUM(DH33:DK33) -> -181360.98 | DM33: =DL33*DM68/DL68 -> -43207.332 | DN33: =DM33*DN68/DM68 -> -43477.122 | DO33: =DN33*DO68/DN68 -> -43748.597 | DP33: =DO33*DP68/DO68 -> -44021.768 | DQ33: =SUM(DM33:DP33) -> -174454.82 | DR33: =DQ33*DR68/DQ68 -> -44296.644 | DS33: =DR33*DS68/DR68 -> -44573.236 | DT33: =DS33*DT68/DS68 -> -44851.556 | DU33: =DT33*DU68/DT68 -> -45131.613 | DV33: =SUM(DR33:DU33) -> -178853.05 | DW33: =DV33*DW68/DV68 -> -45413.419 | DX33: =DW33*DX68/DW68 -> -45696.985 | DY33: =DX33*DY68/DX68 -> -45982.321 | DZ33: =DY33*DZ68/DY68 -> -46269.439 | EA33: =SUM(DW33:DZ33) -> -183362.16 | EB33: =EA33*EB68/EA68 -> -46558.35 | EC33: =EB33*EC68/EB68 -> -46849.064 | ED33: =EC33*ED68/EC68 -> -47141.594 | EE33: =ED33*EE68/ED68 -> -47435.951 | EF33: =SUM(EB33:EE33) -> -187984.96
A34: Extraordinary items | F34: =SUM(B34:E34) -> 0 | G34: 0 | H34: 0 | I34: -25726 | J34: 0 | K34: =SUM(G34:J34) -> -25726 | L34: 0 | M34: -1114 | N34: =-20827-M34 -> -19713 | O34: 0 | P34: =SUM(L34:O34) -> -20827 | Q34: 0 | R34: 112894 | S34: 0 | T34: 0 | U34: =SUM(Q34:T34) -> 112894 | V34: 0 | W34: 0 | X34: 0 | Y34: 0 | Z34: =SUM(V34:Y34) -> 0 | AA34: 0 | AB34: 0 | AC34: 0 | AD34: 0 | AE34: =SUM(AA34:AD34) -> 0 | AF34: 0 | AH34: 0 | AI34: 0 | AJ34: =SUM(AF34:AI34) -> 0 | AK34: 0 | AL34: 0 | AM34: 0 | AN34: =-34023-AK32-AL32-AM32 -> -36220 | AO34: =SUM(AK34:AN34) -> -36220 | AP34: -18000 | AQ34: 0 | AR34: 0 | AS34: 0 | AT34: =SUM(AP34:AS34) -> -18000 | AU34: 0 | AV34: -6000 | AW34: 0 | AX34: 0 | AY34: =SUM(AU34:AX34) -> -6000 | AZ34: 0 | BA34: 0 | BB34: 0 | BC34: 0 | BD34: =SUM(AZ34:BC34) -> 0 | BE34: 0 | BF34: 0 | BG34: 0 | BH34: 0 | BI34: =SUM(BE34:BH34) -> 0 | BJ34: 0 | BK34: 0 | BL34: 0 | BM34: 0 | BN34: =SUM(BJ34:BM34) -> 0 | BO34: 0 | BP34: 0 | BQ34: 0 | BR34: 0 | BS34: =SUM(BO34:BR34) -> 0 | BT34: 0 | BU34: 0 | BV34: 0 | BW34: 0 | BX34: =SUM(BT34:BW34) -> 0 | BY34: 0 | BZ34: 0 | CA34: 0 | CB34: 0 | CC34: =SUM(BY34:CB34) -> 0 | CD34: 0 | CE34: 0 | CF34: 0 | CG34: 0 | CH34: =SUM(CD34:CG34) -> 0 | CI34: 0 | CJ34: 0 | CK34: 0 | CL34: 0 | CM34: =SUM(CI34:CL34) -> 0 | CN34: 0 | CO34: 0 | CP34: 0 | CQ34: 0 | CR34: =SUM(CN34:CQ34) -> 0 | CS34: 0 | CT34: 0 | CU34: 0 | CV34: 0 | CW34: =SUM(CS34:CV34) -> 0 | CX34: 0 | CY34: 0 | CZ34: 0 | DA34: 0 | DB34: =SUM(CX34:DA34) -> 0 | DC34: 0 | DD34: 0 | DE34: 213000 | DF34: 0 | DG34: =SUM(DC34:DF34) -> 213000 | DH34: 0 | DI34: 0 | DJ34: 0 | DK34: 0 | DL34: =SUM(DH34:DK34) -> 0 | DM34: 0 | DN34: 0 | DO34: 0 | DP34: 0 | DQ34: =SUM(DM34:DP34) -> 0 | DR34: 0 | DS34: 0 | DT34: 0 | DU34: 0 | DV34: =SUM(DR34:DU34) -> 0 | DW34: 0 | DX34: 0 | DY34: 0 | DZ34: 0 | EA34: =SUM(DW34:DZ34) -> 0 | EB34: 0 | EC34: 0 | ED34: 0 | EE34: 0 | EF34: =SUM(EB34:EE34) -> 0
A35: Equity Income | F35: =SUM(B35:E35) -> 0 | K35: =SUM(G35:J35) -> 0 | L35: -277 | N35: =M35*N$10/M$10 -> 0 | O35: =N35*O$10/N$10 -> 0 | P35: =SUM(L35:O35) -> -277 | Q35: -4046 | R35: 0 | S35: 7668 | T35: =103922-SUM(Q34:S35) -> -12594 | U35: =SUM(Q35:T35) -> -8972 | V35: -11790 | W35: -8688 | X35: -6929 | Y35: =-42755-SUM(V35:X35) -> -15348 | Z35: =SUM(V35:Y35) -> -42755 | AA35: -2507 | AB35: 11053 | AC35: 16914 | AD35: 4992 | AE35: =SUM(AA35:AD35) -> 30452 | AF35: =236-15877 -> -15641 | AG35: 0 | AH35: =167-10921 -> -10754 | AI35: =579-7314 -> -6735 | AJ35: =SUM(AF35:AI35) -> -33130 | AK35: =-3193+250 -> -2943 | AL35: =-3293+491 -> -2802 | AM35: =-4399+183 -> -4216 | AN35: =-54858+1449-AK35-AL35-AM35 -> -43448 | AO35: =SUM(AK35:AN35) -> -53409 | AP35: =41443-AQ35 -> 2108 | AQ35: =39335 -> 39335 | AR35: =9719-13751 -> -4032 | AS35: =-31731+64027-AR35-AQ35-AP35-AP34 -> 12885 | AT35: =SUM(AP35:AS35) -> 50296 | AU35: =25968+15648-AV35 -> 21718 | AV35: =12865+7033 -> 19898 | AW35: =23195-2231 -> 20964 | AX35: =90094+16536-SUM(AU35:AW35) -> 44050 | AY35: =SUM(AU35:AX35) -> 106630 | AZ35: =6853-2545 -> 4308 | BA35: =28886+2882 -> 31768 | BB35: =35253+2528 -> 37781 | BC35: =118221+436-SUM(AZ35:BB35) -> 44800 | BD35: =SUM(AZ35:BC35) -> 118657 | BE35: =8606+2814 -> 11420 | BF35: =22274-6292 -> 15982 | BG35: =28608+2422 -> 31030 | BH35: =73645+6-SUM(BE35:BG35) -> 15219 | BI35: =SUM(BE35:BH35) -> 73651 | BJ35: =6821+61 -> 6882 | BK35: =13992-1256 -> 12736 | BL35: =-1606+7401 -> 5795 | BM35: =49438+10288-SUM(BJ35:BL35) -> 34313 | BN35: =SUM(BJ35:BM35) -> 59726 | BO35: 1752 | BP35: =19303+15047 -> 34350 | BQ35: =25084 -> 25084 | BR35: =73690+53675-SUM(BO35:BQ35) -> 66179 | BS35: =SUM(BO35:BR35) -> 127365 | BT35: 10149 | BU35: 14024 | BV35: 22686 | BW35: =107654-SUM(BT35:BV35) -> 60795 | BX35: =SUM(BT35:BW35) -> 107654 | BY35: -842 | BZ35: 51491 | CA35: =86429-SUM(BY35:BZ35) -> 35780 | CB35: =104200-SUM(BY35:CA35) -> 17771 | CC35: =SUM(BY35:CB35) -> 104200 | CD35: 10692 | CE35: 21467 | CF35: =314800-250000 -> 64800 | CG35: =405712-SUM(CD35:CF35)-250000 -> 58753 | CH35: =SUM(CD35:CG35) -> 155712 | CI35: 79017 | CJ35: 74405 | CK35: 78321 | CL35: =297167-SUM(CI35:CK35) -> 65424 | CM35: =SUM(CI35:CL35) -> 297167 | CN35: 60334 | CO35: 38724 | CP35: 59701 | CQ35: =217085-SUM(CN35:CP35) -> 58326 | CR35: =SUM(CN35:CQ35) -> 217085 | CS35: 47138 | CT35: 33021 | CU35: 89430 | CV35: =262059-SUM(CS35:CU35) -> 92470 | CW35: =SUM(CS35:CV35) -> 262059 | CX35: 100891 | CY35: 116467 | CZ35: 135914 | DA35: =500880-SUM(CX35:CZ35) -> 147608 | DB35: =SUM(CX35:DA35) -> 500880 | DC35: 112558 | DD35: 139609 | DE35: 131891 | DF35: =548106-SUM(DC35:DE35) -> 164048 | DG35: =SUM(DC35:DF35) -> 548106 | DH35: 128141 | DI35: 106557 | DJ35: 152756.77 | DK35: 167018.49 | DL35: =SUM(DH35:DK35) -> 554473.27 | DM35: 161378.41 | DN35: 173048.68 | DO35: 180222.15 | DP35: 187958.75 | DQ35: =SUM(DM35:DP35) -> 702607.99 | DR35: 192616.97 | DS35: 194891.28 | DT35: 203839.02 | DU35: 212288.6 | DV35: =SUM(DR35:DU35) -> 803635.87 | DW35: 211491.82 | DX35: 210466.43 | DY35: 219455.58 | DZ35: 227947.18 | EA35: =SUM(DW35:DZ35) -> 869361.01 | EB35: 226204.03 | EC35: 224390.49 | ED35: 233396.85 | EE35: 241946.55 | EF35: =SUM(EB35:EE35) -> 925937.91
A36: Operating Income | B36: =B15+B16 -> 31827 | C36: =C15+C16 -> 31827 | D36: =D15+D16 -> 32583 | E36: =E15+E16 -> 50959 | F36: =SUM(B36:E36) -> 147196 | G36: =G15+G16 -> 51523 | H36: =H15+H16 -> 40270 | I36: =I15+I16 -> 55898 | J36: =J15+J16 -> 13975 | K36: =SUM(G36:J36) -> 161666 | L36: =L15+L16 -> 83775 | M36: =M15+M16 -> 98864 | N36: =N15+N16 -> 44130 | O36: =O15+O16 -> 101818 | P36: =SUM(L36:O36) -> 328587 | Q36: =Q15+Q16 -> 54042 | R36: =R15+R16 -> 223770 | S36: =S15+S16 -> 125151 | T36: =T15+T16 -> 134601 | U36: =SUM(Q36:T36) -> 537564 | V36: =V15+V16 -> 93476 | W36: =W15+W16 -> 148940 | X36: =X15+X16 -> 116514 | Y36: =Y15+Y16 -> 83063 | Z36: =SUM(V36:Y36) -> 441993 | AA36: =AA15+AA16 -> 150520 | AB36: =AB15+AB16 -> 203666 | AC36: =AC15+AC16 -> 367828 | AD36: =AD15+AD16 -> 249943 | AE36: =SUM(AA36:AD36) -> 971957 | AF36: =AF15+AF16 -> 215784 | AG36: =AG15+AG16 -> 236231 | AH36: =AH15+AH16 -> 235747 | AI36: =AI15+AI16 -> 140148 | AJ36: =SUM(AF36:AI36) -> 827910 | AK36: =AK15+AK16 -> 131959 | AL36: =AL15+AL16 -> 140994 | AM36: =AM15+AM16 -> 224935 | AN36: =AN15+AN16 -> 282510 | AO36: =SUM(AK36:AN36) -> 780398 | AP36: =AP15+AP16 -> 226921 | AQ36: =AQ15+AQ16 -> 231469 | AR36: =AR15+AR16 -> 214094 | AS36: =AS15+AS16 -> 315885 | AT36: =SUM(AP36:AS36) -> 988369 | AU36: =AU15+AU16 -> 235437 | AV36: =AV15+AV16 -> 258296 | AW36: =AW15+AW16 -> 260600 | AX36: =AX15+AX16 -> 269557 | AY36: =SUM(AU36:AX36) -> 1023890 | AZ36: =AZ15+AZ16 -> 228596 | BA36: =BA15+BA16 -> 250828 | BB36: =BB15+BB16 -> 260340 | BC36: =BC15+BC16 -> 236643 | BD36: =SUM(AZ36:BC36) -> 976407 | BE36: =BE15+BE16 -> 141254 | BF36: =BF15+BF16 -> 208977 | BG36: =BG15+BG16 -> 198409 | BH36: =BH15+BH16 -> 141764 | BI36: =SUM(BE36:BH36) -> 690404 | BJ36: =BJ15+BJ16 -> 107117 | BK36: =BK15+BK16 -> 71337 | BL36: =BL15+BL16 -> 61473 | BM36: =BM15+BM16 -> 78416 | BN36: =SUM(BJ36:BM36) -> 318343 | BO36: =BO15+BO16 -> 49697 | BP36: =BP15+BP16 -> -119981 | BQ36: =BQ15+BQ16 -> 28451 | BR36: =BR15+BR16 -> 96463 | BS36: =SUM(BO36:BR36) -> 54630 | BT36: =BT15+BT16 -> -22900 | BU36: =BU15+BU16 -> -4938 | BV36: =BV15+BV16 -> -78688 | BW36: =BW15+BW16 -> 181086 | BX36: =SUM(BT36:BW36) -> 74560 | BY36: =BY15+BY16 -> 79512 | BZ36: =BZ15+BZ16 -> 161495 | CA36: =CA15+CA16 -> 142930 | CB36: =CB15+CB16 -> 236554 | CC36: =SUM(BY36:CB36) -> 620491 | CD36: =CD15+CD16 -> 65085 | CE36: =CE15+CE16 -> 109257 | CF36: =CF15+CF16 -> 1436163 | CG36: =CG15+CG16 -> 303874 | CH36: =SUM(CD36:CG36) -> 1914379 | CI36: =CI15+CI16 -> 226040 | CJ36: =CJ15+CJ16 -> 311399 | CK36: =CK15+CK16 -> 292827 | CL36: =CL15+CL16 -> 275668 | CM36: =SUM(CI36:CL36) -> 1105934 | CN36: =CN15+CN16 -> 197071 | CO36: =CO15+CO16 -> 192122 | CP36: =CP15+CP16 -> 342107 | CQ36: =CQ15+CQ16 -> 250316 | CR36: =SUM(CN36:CQ36) -> 981616 | CS36: =CS15+CS16 -> 223037 | CT36: =CT15+CT16 -> 347849 | CU36: =CU15+CU16 -> 345646 | CV36: =CV15+CV16 -> 345679 | CW36: =SUM(CS36:CV36) -> 1262211 | CX36: =CX15+CX16 -> 351844 | CY36: =CY15+CY16 -> 519244 | CZ36: =CZ15+CZ16 -> 592708 | DA36: =DA15+DA16 -> 642686 | DB36: =SUM(CX36:DA36) -> 2106482 | DC36: =DC15+DC16 -> 437963 | DD36: =DD15+DD16 -> 528736 | DE36: =DE15+DE16 -> 738803 | DF36: =DF15+DF16 -> 838358 | DG36: =SUM(DC36:DF36) -> 2543860 | DH36: =DH15+DH16 -> 411281 | DI36: =DI15+DI16 -> 573703 | DJ36: =DJ15+DJ16 -> 686004.5 | DK36: =DK15+DK16 -> 777252.61 | DL36: =SUM(DH36:DK36) -> 2448241.1 | DM36: =DM15+DM16 -> 696709.97 | DN36: =DN15+DN16 -> 715766.7 | DO36: =DO15+DO16 -> 712364.93 | DP36: =DP15+DP16 -> 752331.42 | DQ36: =SUM(DM36:DP36) -> 2877173 | DR36: =DR15+DR16 -> 787211.52 | DS36: =DS15+DS16 -> 748337.19 | DT36: =DT15+DT16 -> 746886.89 | DU36: =DU15+DU16 -> 813786.51 | DV36: =SUM(DR36:DU36) -> 3096222.1 | DW36: =DW15+DW16 -> 840668.13 | DX36: =DX15+DX16 -> 790338.7 | DY36: =DY15+DY16 -> 782469.6 | DZ36: =DZ15+DZ16 -> 862852.95 | EA36: =SUM(DW36:DZ36) -> 3276329.4 | EB36: =EB15+EB16 -> 906457.81 | EC36: =EC15+EC16 -> 861440.12 | ED36: =ED15+ED16 -> 854738.41 | EE36: =EE15+EE16 -> 935191.55 | EF36: =SUM(EB36:EE36) -> 3557827.9
A37: Non-operating Expenses | B37: 0 | C37: 0 | D37: 0 | E37: 0 | F37: =SUM(B37:E37) -> 0 | G37: 0 | H37: 0 | I37: 0 | J37: 0 | K37: =SUM(G37:J37) -> 0 | L37: 0 | M37: 0 | N37: 0 | O37: 0 | P37: =SUM(L37:O37) -> 0 | Q37: 0 | R37: 0 | S37: 0 | T37: 0 | U37: =SUM(Q37:T37) -> 0 | V37: 0 | W37: 0 | X37: 0 | Y37: 0 | Z37: =SUM(V37:Y37) -> 0 | AA37: 0 | AB37: 0 | AC37: 0 | AD37: 0 | AE37: =SUM(AA37:AD37) -> 0 | AF37: 0 | AG37: 0 | AH37: 0 | AI37: 0 | AJ37: =SUM(AF37:AI37) -> 0 | AK37: 0 | AL37: 0 | AM37: 0 | AN37: 0 | AO37: =SUM(AK37:AN37) -> 0 | AP37: 0 | AQ37: 0 | AR37: 0 | AS37: 0 | AT37: =SUM(AP37:AS37) -> 0 | AU37: 0 | AV37: 0 | AW37: 0 | AX37: 0 | AY37: =SUM(AU37:AX37) -> 0 | AZ37: 0 | BA37: 0 | BB37: 0 | BC37: 0 | BD37: =SUM(AZ37:BC37) -> 0 | BE37: 0 | BF37: 0 | BG37: 0 | BH37: 0 | BI37: =SUM(BE37:BH37) -> 0 | BJ37: 0 | BK37: 0 | BL37: 0 | BM37: 0 | BN37: =SUM(BJ37:BM37) -> 0 | BO37: 0 | BP37: 0 | BQ37: 0 | BR37: 0 | BS37: =SUM(BO37:BR37) -> 0 | BT37: 0 | BU37: 0 | BV37: 0 | BW37: 0 | BX37: =SUM(BT37:BW37) -> 0 | BY37: 0 | BZ37: 0 | CA37: 0 | CB37: 0 | CC37: =SUM(BY37:CB37) -> 0 | CD37: 0 | CE37: 0 | CF37: 0 | CG37: 0 | CH37: =SUM(CD37:CG37) -> 0 | CI37: 0 | CJ37: 0 | CK37: 0 | CL37: 0 | CM37: =SUM(CI37:CL37) -> 0 | CN37: 0 | CO37: 0 | CP37: 0 | CQ37: 0 | CR37: =SUM(CN37:CQ37) -> 0 | CS37: 0 | CT37: 0 | CU37: 0 | CV37: 0 | CW37: =SUM(CS37:CV37) -> 0 | CX37: 0 | CY37: 0 | CZ37: 0 | DA37: 0 | DB37: =SUM(CX37:DA37) -> 0 | DC37: 0 | DD37: 0 | DE37: 0 | DF37: 0 | DG37: =SUM(DC37:DF37) -> 0 | DH37: 0 | DI37: 0 | DJ37: 0 | DK37: 0 | DL37: =SUM(DH37:DK37) -> 0 | DM37: 0 | DN37: 0 | DO37: 0 | DP37: 0 | DQ37: =SUM(DM37:DP37) -> 0 | DR37: 0 | DS37: 0 | DT37: 0 | DU37: 0 | DV37: =SUM(DR37:DU37) -> 0 | DW37: 0 | DX37: 0 | DY37: 0 | DZ37: 0 | EA37: =SUM(DW37:DZ37) -> 0 | EB37: 0 | EC37: 0 | ED37: 0 | EE37: 0 | EF37: =SUM(EB37:EE37) -> 0
A38: Income Before Taxes on Income | B38: =B36+B37 -> 31827 | C38: =C36+C37 -> 31827 | D38: =D36+D37 -> 32583 | E38: =E36+E37 -> 50959 | F38: =SUM(B38:E38) -> 147196 | G38: =G36+G37 -> 51523 | H38: =H36+H37 -> 40270 | I38: =I36+I37 -> 55898 | J38: =J36+J37 -> 13975 | K38: =SUM(G38:J38) -> 161666 | L38: =L36+L37 -> 83775 | M38: =M36+M37 -> 98864 | N38: =N36+N37 -> 44130 | O38: =O36+O37 -> 101818 | P38: =SUM(L38:O38) -> 328587 | Q38: =Q36+Q37 -> 54042 | R38: =R36+R37 -> 223770 | S38: =S36+S37 -> 125151 | T38: =T36+T37 -> 134601 | U38: =SUM(Q38:T38) -> 537564 | V38: =V36+V37 -> 93476 | W38: =W36+W37 -> 148940 | X38: =X36+X37 -> 116514 | Y38: =Y36+Y37 -> 83063 | Z38: =SUM(V38:Y38) -> 441993 | AA38: =AA36+AA37 -> 150520 | AB38: =AB36+AB37 -> 203666 | AC38: =AC36+AC37 -> 367828 | AD38: =AD36+AD37 -> 249943 | AE38: =SUM(AA38:AD38) -> 971957 | AF38: =AF36+AF37 -> 215784 | AG38: =AG36+AG37 -> 236231 | AH38: =AH36+AH37 -> 235747 | AI38: =AI36+AI37 -> 140148 | AJ38: =SUM(AF38:AI38) -> 827910 | AK38: =AK36+AK37 -> 131959 | AL38: =AL36+AL37 -> 140994 | AM38: =AM36+AM37 -> 224935 | AN38: =AN36+AN37 -> 282510 | AO38: =SUM(AK38:AN38) -> 780398 | AP38: =AP36+AP37 -> 226921 | AQ38: =AQ36+AQ37 -> 231469 | AR38: =AR36+AR37 -> 214094 | AS38: =AS36+AS37 -> 315885 | AT38: =SUM(AP38:AS38) -> 988369 | AU38: =AU36+AU37 -> 235437 | AV38: =AV36+AV37 -> 258296 | AW38: =AW36+AW37 -> 260600 | AX38: =AX36+AX37 -> 269557 | AY38: =SUM(AU38:AX38) -> 1023890 | AZ38: =AZ36+AZ37 -> 228596 | BA38: =BA36+BA37 -> 250828 | BB38: =BB36+BB37 -> 260340 | BC38: =BC36+BC37 -> 236643 | BD38: =SUM(AZ38:BC38) -> 976407 | BE38: =BE36+BE37 -> 141254 | BF38: =BF36+BF37 -> 208977 | BG38: =BG36+BG37 -> 198409 | BH38: =BH36+BH37 -> 141764 | BI38: =SUM(BE38:BH38) -> 690404 | BJ38: =BJ36+BJ37 -> 107117 | BK38: =BK36+BK37 -> 71337 | BL38: =BL36+BL37 -> 61473 | BM38: =BM36+BM37 -> 78416 | BN38: =SUM(BJ38:BM38) -> 318343 | BO38: =BO36+BO37 -> 49697 | BP38: =BP36+BP37 -> -119981 | BQ38: =BQ36+BQ37 -> 28451 | BR38: =BR36+BR37 -> 96463 | BS38: =SUM(BO38:BR38) -> 54630 | BT38: =BT36+BT37 -> -22900 | BU38: =BU36+BU37 -> -4938 | BV38: =BV36+BV37 -> -78688 | BW38: =BW36+BW37 -> 181086 | BX38: =SUM(BT38:BW38) -> 74560 | BY38: =BY36+BY37 -> 79512 | BZ38: =BZ36+BZ37 -> 161495 | CA38: =CA36+CA37 -> 142930 | CB38: =CB36+CB37 -> 236554 | CC38: =SUM(BY38:CB38) -> 620491 | CD38: =CD36+CD37 -> 65085 | CE38: =CE36+CE37 -> 109257 | CF38: =CF36+CF37 -> 1436163 | CG38: =CG36+CG37 -> 303874 | CH38: =SUM(CD38:CG38) -> 1914379 | CI38: =CI36+CI37 -> 226040 | CJ38: =CJ36+CJ37 -> 311399 | CK38: =CK36+CK37 -> 292827 | CL38: =CL36+CL37 -> 275668 | CM38: =SUM(CI38:CL38) -> 1105934 | CN38: =CN36+CN37 -> 197071 | CO38: =CO36+CO37 -> 192122 | CP38: =CP36+CP37 -> 342107 | CQ38: =CQ36+CQ37 -> 250316 | CR38: =SUM(CN38:CQ38) -> 981616 | CS38: =CS36+CS37 -> 223037 | CT38: =CT36+CT37 -> 347849 | CU38: =CU36+CU37 -> 345646 | CV38: =CV36+CV37 -> 345679 | CW38: =SUM(CS38:CV38) -> 1262211 | CX38: =CX36+CX37 -> 351844 | CY38: =CY36+CY37 -> 519244 | CZ38: =CZ36+CZ37 -> 592708 | DA38: =DA36+DA37 -> 642686 | DB38: =SUM(CX38:DA38) -> 2106482 | DC38: =DC36+DC37 -> 437963 | DD38: =DD36+DD37 -> 528736 | DE38: =DE36+DE37 -> 738803 | DF38: =DF36+DF37 -> 838358 | DG38: =SUM(DC38:DF38) -> 2543860 | DH38: =DH36+DH37 -> 411281 | DI38: =DI36+DI37 -> 573703 | DJ38: =DJ36+DJ37 -> 686004.5 | DK38: =DK36+DK37 -> 777252.61 | DL38: =SUM(DH38:DK38) -> 2448241.1 | DM38: =DM36+DM37 -> 696709.97 | DN38: =DN36+DN37 -> 715766.7 | DO38: =DO36+DO37 -> 712364.93 | DP38: =DP36+DP37 -> 752331.42 | DQ38: =SUM(DM38:DP38) -> 2877173 | DR38: =DR36+DR37 -> 787211.52 | DS38: =DS36+DS37 -> 748337.19 | DT38: =DT36+DT37 -> 746886.89 | DU38: =DU36+DU37 -> 813786.51 | DV38: =SUM(DR38:DU38) -> 3096222.1 | DW38: =DW36+DW37 -> 840668.13 | DX38: =DX36+DX37 -> 790338.7 | DY38: =DY36+DY37 -> 782469.6 | DZ38: =DZ36+DZ37 -> 862852.95 | EA38: =SUM(DW38:DZ38) -> 3276329.4 | EB38: =EB36+EB37 -> 906457.81 | EC38: =EC36+EC37 -> 861440.12 | ED38: =ED36+ED37 -> 854738.41 | EE38: =EE36+EE37 -> 935191.55 | EF38: =SUM(EB38:EE38) -> 3557827.9
A39: Income Tax and Social Contribution | B39: =(-4895-SUM(D39))/2 -> -821.5 | C39: =B39 -> -821.5 | D39: -3252 | E39: -28280 | F39: =SUM(B39:E39) -> -33175 | G39: 526 | H39: -3879 | I39: -4777 | J39: 13667 | K39: =SUM(G39:J39) -> 5537 | L39: -12684 | M39: -4719 | N39: =-24397-L39-M39 -> -6994 | O39: =-40860-SUM(L39:N39) -> -16463 | P39: =SUM(L39:O39) -> -40860 | Q39: -8089 | R39: =-16298-Q39 -> -8209 | S39: -8013 | T39: =-44989-SUM(Q39:S39) -> -20678 | U39: =SUM(Q39:T39) -> -44989 | V39: -15913 | W39: -16602 | X39: -24581 | Y39: =-76152-SUM(V39:X39) -> -19056 | Z39: =SUM(V39:Y39) -> -76152 | AA39: -14941 | AB39: -18704 | AC39: -30803 | AD39: -9446 | AE39: =SUM(AA39:AD39) -> -73894 | AF39: -23931 | AG39: -15687 | AH39: -29101 | AI39: -33848 | AJ39: =SUM(AF39:AI39) -> -102567 | AK39: -34565 | AL39: -39626 | AM39: -49893 | AN39: =-178073-AK39-AL39-AM39 -> -53989 | AO39: =SUM(AK39:AN39) -> -178073 | AP39: =-90450-AQ39 -> -42616 | AQ39: -47834 | AR39: -41335 | AS39: =-183130-AP39-AQ39-AR39 -> -51345 | AT39: =SUM(AP39:AS39) -> -183130 | AU39: =-65574-AV39 -> -29418 | AV39: =-33111-AV41 -> -36156 | AW39: -33193 | AX39: =-142835-SUM(AU39:AW39) -> -44068 | AY39: =SUM(AU39:AX39) -> -142835 | AZ39: -35647 | BA39: =-42613-BA41 -> -34983 | BB39: -36586 | BC39: =-139210-SUM(AZ39:BB39) -> -31994 | BD39: =SUM(AZ39:BC39) -> -139210 | BE39: -32913 | BF39: =-23918-BF41 -> -31110 | BG39: -29243 | BH39: =-118474-SUM(BE39:BG39) -> -25208 | BI39: =SUM(BE39:BH39) -> -118474 | BJ39: -20775 | BK39: -20557 | BL39: -17757 | BM39: =-83164-SUM(BJ39:BL39) -> -24075 | BN39: =SUM(BJ39:BM39) -> -83164 | BO39: -21610 | BP39: -19338 | BQ39: -20444 | BR39: =-82764-SUM(BO39:BQ39) -> -21372 | BS39: =SUM(BO39:BR39) -> -82764 | BT39: -14173 | BU39: -16481 | BV39: -18051 | BW39: =-67433-SUM(BT39:BV39) -> -18728 | BX39: =SUM(BT39:BW39) -> -67433 | BY39: -174 | BZ39: 401 | CA39: -21871 | CB39: =-83217-SUM(BY39:CA39) -> -61573 | CC39: =SUM(BY39:CB39) -> -83217 | CD39: -18306 | CE39: -13360 | CF39: =-129743-266545+375000 -> -21288 | CG39: =-197539-SUM(CD39:CF39)+(-266545+375000) -> -36130 | CH39: =SUM(CD39:CG39) -> -89084 | CI39: -17832 | CJ39: -24464 | CK39: -24110 | CL39: =-93019-SUM(CI39:CK39) -> -26613 | CM39: =SUM(CI39:CL39) -> -93019 | CN39: -25176 | CO39: -27899 | CP39: -35365 | CQ39: =-121158-SUM(CN39:CP39) -> -32718 | CR39: =SUM(CN39:CQ39) -> -121158 | CS39: -35951 | CT39: -33981 | CU39: -35936 | CV39: =-143963-SUM(CS39:CU39) -> -38095 | CW39: =SUM(CS39:CV39) -> -143963 | CX39: -34290 | CY39: -34111 | CZ39: -44362 | DA39: =-158483-SUM(CX39:CZ39) -> -45720 | DB39: =SUM(CX39:DA39) -> -158483 | DC39: -43072 | DD39: -43481 | DE39: -54825 | DF39: =-197741-SUM(DC39:DE39) -> -56363 | DG39: =SUM(DC39:DF39) -> -197741 | DH39: -46053 | DI39: -52535 | DJ39: =-DJ40*(DJ4+'Balance Sheet'!DJ63) -> -54805.347 | DK39: =-DK40*(DK4+'Balance Sheet'!DK63) -> -59978.541 | DL39: =SUM(DH39:DK39) -> -213371.89 | DM39: =-DM40*(DM4+'Balance Sheet'!DM63) -> -58047.047 | DN39: =-DN40*(DN4+'Balance Sheet'!DN63) -> -49773.141 | DO39: =-DO40*(DO4+'Balance Sheet'!DO63) -> -50836.055 | DP39: =-DP40*(DP4+'Balance Sheet'!DP63) -> -58751.366 | DQ39: =SUM(DM39:DP39) -> -217407.61 | DR39: =-DR40*(DR4+'Balance Sheet'!DR63) -> -52311.162 | DS39: =-DS40*(DS4+'Balance Sheet'!DS63) -> -56720.078 | DT39: =-DT40*(DT4+'Balance Sheet'!DT63) -> -59886.84 | DU39: =-DU40*(DU4+'Balance Sheet'!DU63) -> -62706.147 | DV39: =SUM(DR39:DU39) -> -231624.23 | DW39: =-DW40*(DW4+'Balance Sheet'!DW63) -> -62718.784 | DX39: =-DX40*(DX4+'Balance Sheet'!DX63) -> -64566.09 | DY39: =-DY40*(DY4+'Balance Sheet'!DY63) -> -70383.055 | DZ39: =-DZ40*(DZ4+'Balance Sheet'!DZ63) -> -76182.159 | EA39: =SUM(DW39:DZ39) -> -273850.09 | EB39: =-EB40*(EB4+'Balance Sheet'!EB63) -> -72784.24 | EC39: =-EC40*(EC4+'Balance Sheet'!EC63) -> -72074.652 | ED39: =-ED40*(ED4+'Balance Sheet'!ED63) -> -73872.765 | EE39: =-EE40*(EE4+'Balance Sheet'!EE63) -> -81033.549 | EF39: =SUM(EB39:EE39) -> -299765.21
A40: Cash Tax Rate (% of collection) | B40: =-B39/(B4+'Balance Sheet'!B63) -> #REF! | C40: =-C39/(C4+'Balance Sheet'!C63) -> 0.0044245524 | D40: =-D39/(D4+'Balance Sheet'!D63) -> 0.027347725 | E40: =-E39/(E4+'Balance Sheet'!E63) -> -0.49350831 | F40: =-F39/(F4+'Balance Sheet'!F63) -> #REF! | G40: =-G39/(G4+'Balance Sheet'!G63) -> -0.0028600324 | H40: =-H39/(H4+'Balance Sheet'!H63) -> 0.024214844 | I40: =-I39/(I4+'Balance Sheet'!I63) -> 0.023809642 | ... DI40: =-DI39/(DI4+'Balance Sheet'!DI63) -> 0.022490376 | DJ40: =DI40*80%+20%*1.92% -> 0.021832301 | DK40: =DJ40*80%+20%*1.92% -> 0.021305841 | DL40: =-DL39/(DL4+'Balance Sheet'!DL63) -> 0.022353045 | DM40: =DK40*80%+20%*1.92% -> 0.020884673 | DN40: =DM40*80%+20%*1.92% -> 0.020547738 | DO40: =DN40*80%+20%*1.92% -> 0.02027819 | DP40: =DO40*80%+20%*1.92% -> 0.020062552 | DQ40: =-DQ39/(DQ4+'Balance Sheet'!DQ63) -> 0.020438678 | DR40: =DP40*80%+20%*1.92% -> 0.019890042 | DS40: =DR40*80%+20%*1.92% -> 0.019752034 | DT40: =DS40*80%+20%*1.92% -> 0.019641627 | DU40: =DT40*80%+20%*1.92% -> 0.019553301 | DV40: =-DV39/(DV4+'Balance Sheet'!DV63) -> 0.019700068 | DW40: =DU40*80%+20%*1.92% -> 0.019482641 | DX40: =DW40*80%+20%*1.92% -> 0.019426113 | DY40: =DX40*80%+20%*1.92% -> 0.01938089 | DZ40: =DY40*80%+20%*1.92% -> 0.019344712 | EA40: =-EA39/(EA4+'Balance Sheet'!EA63) -> 0.019404656 | EB40: =DZ40*80%+20%*1.92% -> 0.01931577 | EC40: =EB40*80%+20%*1.92% -> 0.019292616 | ED40: =EC40*80%+20%*1.92% -> 0.019274093 | EE40: =ED40*80%+20%*1.92% -> 0.019259274 | EF40: =-EF39/(EF4+'Balance Sheet'!EF63) -> 0.019284636
A41: Deffered Taxes | B41: =(-11959-SUM(D41))/2 -> -4154 | C41: =B41 -> -4154 | D41: -3651 | E41: -1431 | F41: =SUM(B41:E41) -> -13390 | G41: -5285 | H41: -4070 | I41: -6872 | J41: -7085 | K41: =SUM(G41:J41) -> -23312 | L41: -4634 | M41: -11170 | N41: =-14295-L41-M41 -> 1509 | O41: =-17148-SUM(L41:N41) -> -2853 | P41: =SUM(L41:O41) -> -17148 | Q41: 6472 | R41: =3866-Q41 -> -2606 | S41: -14981 | T41: =-20538-SUM(Q41:S41) -> -9423 | U41: =SUM(Q41:T41) -> -20538 | V41: 1921 | W41: -19494 | X41: -11504 | Y41: =-36247-SUM(V41:X41) -> -7170 | Z41: =SUM(V41:Y41) -> -36247 | AA41: -13785 | AB41: -3286 | AC41: -17529 | AD41: -5633 | AE41: =SUM(AA41:AD41) -> -40233 | AF41: -593 | AG41: -19909 | AH41: -5466 | AI41: -395 | AJ41: =SUM(AF41:AI41) -> -26363 | AK41: -7319 | AL41: 4572 | AM41: 2519 | AN41: =-10139-AK41-AL41-AM41 -> -9911 | AO41: =SUM(AK41:AN41) -> -10139 | AP41: =-20103-AQ41 -> -6080 | AQ41: -14023 | AR41: -6910 | AS41: =30450-AP41-AQ41-AR41 -> 57463 | AT41: =SUM(AP41:AS41) -> 30450 | AU41: =5483-AV41 -> 2438 | AV41: 3045 | AW41: 687 | AX41: =6944-SUM(AU41:AW41) -> 774 | AY41: =SUM(AU41:AX41) -> 6944 | AZ41: -5605 | BA41: -7630 | BB41: 6039 | BC41: =-5811-SUM(AZ41:BB41) -> 1385 | BD41: =SUM(AZ41:BC41) -> -5811 | BE41: 9591 | BF41: 7192 | BG41: -140 | BH41: =21223-SUM(BE41:BG41) -> 4580 | BI41: =SUM(BE41:BH41) -> 21223 | BJ41: 2525 | BK41: 5723 | BL41: -741 | BM41: =9441-SUM(BJ41:BL41) -> 1934 | BN41: =SUM(BJ41:BM41) -> 9441 | BO41: 6159 | BP41: 4999 | BQ41: 6156 | BR41: =17595-SUM(BO41:BQ41) -> 281 | BS41: =SUM(BO41:BR41) -> 17595 | BT41: 2418 | BU41: 2288 | BV41: 2662 | BW41: =-1099-SUM(BT41:BV41) -> -8467 | BX41: =SUM(BT41:BW41) -> -1099 | BY41: -17937 | BZ41: -19605 | CA41: 202 | CB41: =-2956-SUM(BY41:CA41) -> 34384 | CC41: =SUM(BY41:CB41) -> -2956 | CD41: 1457 | CE41: -2972 | CF41: 0 | CG41: =-262343-SUM(CD41:CF41)+266545 -> 5717 | CH41: =SUM(CD41:CG41) -> 4202 | CI41: -15 | CJ41: 3417 | CK41: -2474 | CL41: =4399-SUM(CI41:CK41) -> 3471 | CM41: =SUM(CI41:CL41) -> 4399 | CN41: -1238 | CO41: -2609 | CP41: 2855 | CQ41: =-1867-SUM(CN41:CP41) -> -875 | CR41: =SUM(CN41:CQ41) -> -1867 | CS41: 3974 | CT41: -5843 | CU41: -5072 | CV41: =-12548-SUM(CS41:CU41) -> -5607 | CW41: =SUM(CS41:CV41) -> -12548 | CX41: -2751 | CY41: -7190 | CZ41: -7334 | DA41: =-26947-SUM(CX41:CZ41) -> -9672 | DB41: =SUM(CX41:DA41) -> -26947 | DC41: -1078 | DD41: -6252 | DE41: -1015 | DF41: =49710-SUM(DC41:DE41) -> 58055 | DG41: =SUM(DC41:DF41) -> 49710 | DH41: -5169 | DI41: -2441 | DJ41: =-DJ42*DJ10-DJ39 -> -10408.821 | DK41: =-DK42*DK10-DK39 -> -4941.7633 | DL41: =SUM(DH41:DK41) -> -22960.584 | DM41: =-DM42*DM10-DM39 -> -1940.5061 | DN41: =-DN42*DN10-DN39 -> -11703.374 | DO41: =-DO42*DO10-DO39 -> -11844.121 | DP41: =-DP42*DP10-DP39 -> -8661.5559 | DQ41: =SUM(DM41:DP41) -> -34149.557 | DR41: =-DR42*DR10-DR39 -> -10919.509 | DS41: =-DS42*DS10-DS39 -> -8146.4341 | DT41: =-DT42*DT10-DT39 -> -6428.2203 | DU41: =-DU42*DU10-DU39 -> -8602.9775 | DV41: =SUM(DR41:DU41) -> -34097.141 | DW41: =-DW42*DW10-DW39 -> -4334.3155 | DX41: =-DX42*DX10-DX39 -> -4318.0745 | DY41: =-DY42*DY10-DY39 -> -63.71868 | DZ41: =-DZ42*DZ10-DZ39 -> 499.53524 | EA41: =SUM(DW41:DZ41) -> -8216.5734 | EB41: =-EB42*EB10-EB39 -> 1508.7065 | EC41: =-EC42*EC10-EC39 -> -1144.2313 | ED41: =-ED42*ED10-ED39 -> -949.52612 | EE41: =-EE42*EE10-EE39 -> 816.20914 | EF41: =SUM(EB41:EE41) -> 231.15822
A42: Total Tax Rate (% of revenues) | B42: =-(B39+B41)/B10 -> 0.04539462 | C42: =-(C39+C41)/C10 -> 0.04539462 | D42: =-(D39+D41)/D10 -> 0.056254584 | E42: =-(E39+E41)/E10 -> 0.16278573 | F42: =-(F39+F41)/F10 -> 0.088790455 | G42: =-(G39+G41)/G10 -> 0.027971247 | H42: =-(H39+H41)/H10 -> 0.055702323 | I42: =-(I39+I41)/I10 -> 0.046052397 | ... DI42: =-(DI39+DI41)/DI10 -> 0.022159959 | DJ42: =DH42*80%+20%*1.92% -> 0.024075522 | DK42: =DI42*80%+20%*1.92% -> 0.021567967 | DL42: =-(DL39+DL41)/DL10 -> 0.023113944 | DM42: =DK42*80%+20%*1.92% -> 0.021094374 | DN42: =DM42*80%+20%*1.92% -> 0.020715499 | DO42: =DN42*80%+20%*1.92% -> 0.020412399 | DP42: =DO42*80%+20%*1.92% -> 0.020169919 | DQ42: =-(DQ39+DQ41)/DQ10 -> 0.020578334 | DR42: =DP42*80%+20%*1.92% -> 0.019975936 | DS42: =DR42*80%+20%*1.92% -> 0.019820748 | DT42: =DS42*80%+20%*1.92% -> 0.019696599 | DU42: =DT42*80%+20%*1.92% -> 0.019597279 | DV42: =-(DV39+DV41)/DV10 -> 0.01976571 | DW42: =DU42*80%+20%*1.92% -> 0.019517823 | DX42: =DW42*80%+20%*1.92% -> 0.019454259 | DY42: =DX42*80%+20%*1.92% -> 0.019403407 | DZ42: =DY42*80%+20%*1.92% -> 0.019362725 | EA42: =-(EA39+EA41)/EA10 -> 0.019431936 | EB42: =DZ42*80%+20%*1.92% -> 0.01933018 | EC42: =EB42*80%+20%*1.92% -> 0.019304144 | ED42: =EC42*80%+20%*1.92% -> 0.019283315 | EE42: =ED42*80%+20%*1.92% -> 0.019266652 | EF42: =-(EF39+EF41)/EF10 -> 0.019295067
A43: Employee compensation | B43: 0 | C43: 0 | D43: 0 | E43: 0 | F43: =SUM(B43:E43) -> 0 | G43: 0 | H43: 0 | I43: 0 | J43: 0 | K43: =SUM(G43:J43) -> 0 | L43: 0 | M43: -1500 | N43: -1500 | O43: =-4603-SUM(L43:N43) -> -1603 | P43: =SUM(L43:O43) -> -4603 | Q43: -1151 | R43: =-3000-Q43 -> -1849 | S43: -5000 | T43: 5000 | U43: =SUM(Q43:T43) -> -3000 | V43: -750 | W43: -750 | X43: -1570 | Y43: -985 | Z43: =SUM(V43:Y43) -> -4055 | AA43: -3000 | AB43: -3000 | AC43: -9800 | AD43: -15132 | AE43: =SUM(AA43:AD43) -> -30932 | AF43: -4987 | AG43: -3544 | AH43: -5038 | AI43: 0 | AJ43: =SUM(AF43:AI43) -> -13569 | AK43: 0 | AL43: 0 | AM43: 0 | AN43: =AM43*AN20/AM20 -> 0 | AO43: =SUM(AK43:AN43) -> 0 | AP43: 0 | AQ43: =AP43*AQ20/AP20 -> 0 | AR43: =AQ43*AR20/AQ20 -> 0 | AS43: =AR43*AS20/AR20 -> 0 | AT43: =SUM(AP43:AS43) -> 0 | AU43: 0 | AV43: =AU43*AV20/AU20 -> 0 | AW43: =AV43*AW20/AV20 -> 0 | AX43: =AW43*AX20/AW20 -> 0 | AY43: =SUM(AU43:AX43) -> 0 | AZ43: 0 | BA43: =AZ43*BA20/AZ20 -> 0 | BB43: =BA43*BB20/BA20 -> 0 | BC43: =BB43*BC20/BB20 -> 0 | BD43: =SUM(AZ43:BC43) -> 0 | BE43: 0 | BF43: =BE43*BF20/BE20 -> 0 | BG43: =BF43*BG20/BF20 -> 0 | BH43: =BG43*BH20/BG20 -> 0 | BI43: =SUM(BE43:BH43) -> 0 | BJ43: 0 | BK43: =BJ43*BK20/BJ20 -> 0 | BL43: =BK43*BL20/BK20 -> 0 | BM43: =BL43*BM20/BL20 -> 0 | BN43: =SUM(BJ43:BM43) -> 0 | BO43: 0 | BP43: =BO43*BP20/BO20 -> 0 | BQ43: =BP43*BQ20/BP20 -> 0 | BR43: =BQ43*BR20/BQ20 -> 0 | BS43: =SUM(BO43:BR43) -> 0 | BT43: 0 | BU43: =BT43*BU20/BT20 -> 0 | BV43: =BU43*BV20/BU20 -> 0 | BW43: =BV43*BW20/BV20 -> 0 | BX43: =SUM(BT43:BW43) -> 0 | BY43: 0 | BZ43: =BY43*BZ20/BY20 -> 0 | CA43: =BZ43*CA20/BZ20 -> 0 | CB43: =CA43*CB20/CA20 -> 0 | CC43: =SUM(BY43:CB43) -> 0 | CD43: 0 | CE43: =CD43*CE20/CD20 -> 0 | CF43: =CE43*CF20/CE20 -> 0 | CG43: =CF43*CG20/CF20 -> 0 | CH43: =SUM(CD43:CG43) -> 0 | CI43: 0 | CJ43: =CI43*CJ20/CI20 -> 0 | CK43: =CJ43*CK20/CJ20 -> 0 | CL43: =CK43*CL20/CK20 -> 0 | CM43: =SUM(CI43:CL43) -> 0 | CN43: 0 | CO43: =CN43*CO20/CN20 -> 0 | CP43: =CO43*CP20/CO20 -> 0 | CQ43: =CP43*CQ20/CP20 -> 0 | CR43: =SUM(CN43:CQ43) -> 0 | CS43: 0 | CT43: =CS43*CT20/CS20 -> 0 | CU43: =CT43*CU20/CT20 -> 0 | CV43: =CU43*CV20/CU20 -> 0 | CW43: =SUM(CS43:CV43) -> 0 | CX43: 0 | CY43: =CX43*CY20/CX20 -> 0 | CZ43: =CY43*CZ20/CY20 -> 0 | DA43: =CZ43*DA20/CZ20 -> 0 | DB43: =SUM(CX43:DA43) -> 0 | DC43: 0 | DD43: =DC43*DD20/DC20 -> 0 | DE43: =DD43*DE20/DD20 -> 0 | DF43: =DE43*DF20/DE20 -> 0 | DG43: =SUM(DC43:DF43) -> 0 | DH43: 0 | DI43: =DH43*DI20/DH20 -> 0 | DJ43: =DI43*DJ20/DI20 -> 0 | DK43: =DJ43*DK20/DJ20 -> 0 | DL43: =SUM(DH43:DK43) -> 0 | DM43: =DL43*DM20/DL20 -> 0 | DN43: =DM43*DN20/DM20 -> 0 | DO43: =DN43*DO20/DN20 -> 0 | DP43: =DO43*DP20/DO20 -> 0 | DQ43: =SUM(DM43:DP43) -> 0 | DR43: =DQ43*DR20/DQ20 -> 0 | DS43: =DR43*DS20/DR20 -> 0 | DT43: =DS43*DT20/DS20 -> 0 | DU43: =DT43*DU20/DT20 -> 0 | DV43: =SUM(DR43:DU43) -> 0 | DW43: =DV43*DW20/DV20 -> 0 | DX43: =DW43*DX20/DW20 -> 0 | DY43: =DX43*DY20/DX20 -> 0 | DZ43: =DY43*DZ20/DY20 -> 0 | EA43: =SUM(DW43:DZ43) -> 0 | EB43: =EA43*EB20/EA20 -> 0 | EC43: =EB43*EC20/EB20 -> 0 | ED43: =EC43*ED20/EC20 -> 0 | EE43: =ED43*EE20/ED20 -> 0 | EF43: =SUM(EB43:EE43) -> 0
A44: Majority Earnings | B44: =B38+B39+B41+B43 -> 26851.5 | C44: =C38+C39+C41+C43 -> 26851.5 | D44: =D38+D39+D41+D43 -> 25680 | E44: =E38+E39+E41+E43 -> 21248 | F44: =SUM(B44:E44) -> 100631 | G44: =G38+G39+G41+G43 -> 46764 | H44: =H38+H39+H41+H43 -> 32321 | I44: =I38+I39+I41+I43 -> 44249 | J44: =J38+J39+J41+J43 -> 20557 | K44: =SUM(G44:J44) -> 143891 | L44: =L38+L39+L41+L43 -> 66457 | M44: =M38+M39+M41+M43 -> 81475 | N44: =N38+N39+N41+N43 -> 37145 | O44: =O38+O39+O41+O43 -> 80899 | P44: =SUM(L44:O44) -> 265976 | Q44: =Q38+Q39+Q41+Q43 -> 51274 | R44: =R38+R39+R41+R43 -> 211106 | S44: =S38+S39+S41+S43 -> 97157 | T44: =T38+T39+T41+T43 -> 109500 | U44: =SUM(Q44:T44) -> 469037 | V44: =V38+V39+V41+V43 -> 78734 | W44: =W38+W39+W41+W43 -> 112094 | X44: =X38+X39+X41+X43 -> 78859 | Y44: =Y38+Y39+Y41+Y43 -> 55852 | Z44: =SUM(V44:Y44) -> 325539 | AA44: =AA38+AA39+AA41+AA43 -> 118794 | AB44: =AB38+AB39+AB41+AB43 -> 178676 | AC44: =AC38+AC39+AC41+AC43 -> 309696 | AD44: =AD38+AD39+AD41+AD43 -> 219732 | AE44: =SUM(AA44:AD44) -> 826898 | AF44: =AF38+AF39+AF41+AF43 -> 186273 | AG44: =AG38+AG39+AG41+AG43 -> 197091 | AH44: =AH38+AH39+AH41+AH43 -> 196142 | AI44: =AI38+AI39+AI41+AI43 -> 105905 | AJ44: =SUM(AF44:AI44) -> 685411 | AK44: =AK38+AK39+AK41+AK43 -> 90075 | AL44: =AL38+AL39+AL41+AL43 -> 105940 | AM44: =AM38+AM39+AM41+AM43 -> 177561 | AN44: =AN38+AN39+AN41+AN43 -> 218610 | AO44: =SUM(AK44:AN44) -> 592186 | AP44: =AP38+AP39+AP41+AP43 -> 178225 | AQ44: =AQ38+AQ39+AQ41+AQ43 -> 169612 | AR44: =AR38+AR39+AR41+AR43 -> 165849 | AS44: =AS38+AS39+AS41+AS43 -> 322003 | AT44: =SUM(AP44:AS44) -> 835689 | AU44: =AU38+AU39+AU41+AU43 -> 208457 | AV44: =AV38+AV39+AV41+AV43 -> 225185 | AW44: =AW38+AW39+AW41+AW43 -> 228094 | AX44: =AX38+AX39+AX41+AX43 -> 226263 | AY44: =SUM(AU44:AX44) -> 887999 | AZ44: =AZ38+AZ39+AZ41+AZ43 -> 187344 | BA44: =BA38+BA39+BA41+BA43 -> 208215 | BB44: =BB38+BB39+BB41+BB43 -> 229793 | BC44: =BC38+BC39+BC41+BC43 -> 206034 | BD44: =SUM(AZ44:BC44) -> 831386 | BE44: =BE38+BE39+BE41+BE43 -> 117932 | BF44: =BF38+BF39+BF41+BF43 -> 185059 | BG44: =BG38+BG39+BG41+BG43 -> 169026 | BH44: =BH38+BH39+BH41+BH43 -> 121136 | BI44: =SUM(BE44:BH44) -> 593153 | BJ44: =BJ38+BJ39+BJ41+BJ43 -> 88867 | BK44: =BK38+BK39+BK41+BK43 -> 56503 | BL44: =BL38+BL39+BL41+BL43 -> 42975 | BM44: =BM38+BM39+BM41+BM43 -> 56275 | BN44: =SUM(BJ44:BM44) -> 244620 | BO44: =BO38+BO39+BO41+BO43 -> 34246 | BP44: =BP38+BP39+BP41+BP43 -> -134320 | BQ44: =BQ38+BQ39+BQ41+BQ43 -> 14163 | BR44: =BR38+BR39+BR41+BR43 -> 75372 | BS44: =SUM(BO44:BR44) -> -10539 | BT44: =BT38+BT39+BT41+BT43 -> -34655 | BU44: =BU38+BU39+BU41+BU43 -> -19131 | BV44: =BV38+BV39+BV41+BV43 -> -94077 | BW44: =BW38+BW39+BW41+BW43 -> 153891 | BX44: =SUM(BT44:BW44) -> 6028 | BY44: =BY38+BY39+BY41+BY43 -> 61401 | BZ44: =BZ38+BZ39+BZ41+BZ43 -> 142291 | CA44: =CA38+CA39+CA41+CA43 -> 121261 | CB44: =CB38+CB39+CB41+CB43 -> 209365 | CC44: =SUM(BY44:CB44) -> 534318 | CD44: =CD38+CD39+CD41+CD43 -> 48236 | CE44: =CE38+CE39+CE41+CE43 -> 92925 | CF44: =CF38+CF39+CF41+CF43 -> 1414875 | CG44: =CG38+CG39+CG41+CG43 -> 273461 | CH44: =SUM(CD44:CG44) -> 1829497 | CI44: =CI38+CI39+CI41+CI43 -> 208193 | CJ44: =CJ38+CJ39+CJ41+CJ43 -> 290352 | CK44: =CK38+CK39+CK41+CK43 -> 266243 | CL44: =CL38+CL39+CL41+CL43 -> 252526 | CM44: =SUM(CI44:CL44) -> 1017314 | CN44: =CN38+CN39+CN41+CN43 -> 170657 | CO44: =CO38+CO39+CO41+CO43 -> 161614 | CP44: =CP38+CP39+CP41+CP43 -> 309597 | CQ44: =CQ38+CQ39+CQ41+CQ43 -> 216723 | CR44: =SUM(CN44:CQ44) -> 858591 | CS44: =CS38+CS39+CS41+CS43 -> 191060 | CT44: =CT38+CT39+CT41+CT43 -> 308025 | CU44: =CU38+CU39+CU41+CU43 -> 304638 | CV44: =CV38+CV39+CV41+CV43 -> 301977 | CW44: =SUM(CS44:CV44) -> 1105700 | CX44: =CX38+CX39+CX41+CX43 -> 314803 | CY44: =CY38+CY39+CY41+CY43 -> 477943 | CZ44: =CZ38+CZ39+CZ41+CZ43 -> 541012 | DA44: =DA38+DA39+DA41+DA43 -> 587294 | DB44: =SUM(CX44:DA44) -> 1921052 | DC44: =DC38+DC39+DC41+DC43 -> 393813 | DD44: =DD38+DD39+DD41+DD43 -> 479003 | DE44: =DE38+DE39+DE41+DE43 -> 682963 | DF44: =DF38+DF39+DF41+DF43 -> 840050 | DG44: =SUM(DC44:DF44) -> 2395829 | DH44: =DH38+DH39+DH41+DH43 -> 360059 | DI44: =DI38+DI39+DI41+DI43 -> 518727 | DJ44: =DJ38+DJ39+DJ41+DJ43 -> 620790.33 | DK44: =DK38+DK39+DK41+DK43 -> 712332.31 | DL44: =SUM(DH44:DK44) -> 2211908.6 | DM44: =DM38+DM39+DM41+DM43 -> 636722.42 | DN44: =DN38+DN39+DN41+DN43 -> 654290.19 | DO44: =DO38+DO39+DO41+DO43 -> 649684.75 | DP44: =DP38+DP39+DP41+DP43 -> 684918.5 | DQ44: =SUM(DM44:DP44) -> 2625615.9 | DR44: =DR38+DR39+DR41+DR43 -> 723980.85 | DS44: =DS38+DS39+DS41+DS43 -> 683470.68 | DT44: =DT38+DT39+DT41+DT43 -> 680571.83 | DU44: =DU38+DU39+DU41+DU43 -> 742477.38 | DV44: =SUM(DR44:DU44) -> 2830500.7 | DW44: =DW38+DW39+DW41+DW43 -> 773615.03 | DX44: =DX38+DX39+DX41+DX43 -> 721454.54 | DY44: =DY38+DY39+DY41+DY43 -> 712022.82 | DZ44: =DZ38+DZ39+DZ41+DZ43 -> 787170.33 | EA44: =SUM(DW44:DZ44) -> 2994262.7 | EB44: =EB38+EB39+EB41+EB43 -> 835182.28 | EC44: =EC38+EC39+EC41+EC43 -> 788221.24 | ED44: =ED38+ED39+ED41+ED43 -> 779916.12 | EE44: =EE38+EE39+EE41+EE43 -> 854974.21 | EF44: =SUM(EB44:EE44) -> 3258293.8
A45: Minority Interest | B45: =(-12945-SUM(D45))/2 -> -4600.5 | C45: =B45 -> -4600.5 | D45: -3744 | E45: -3153 | F45: =SUM(B45:E45) -> -16098 | G45: -6267 | H45: =-4088-G45 -> 2179 | I45: =-17842-G45-H45 -> -13754 | J45: =-16090-SUM(G45:I45) -> 1752 | K45: =SUM(G45:J45) -> -16090 | L45: -9044 | M45: -8517 | N45: =-23698-L45-M45 -> -6137 | O45: =-23970-SUM(L45:N45) -> -272 | P45: =SUM(L45:O45) -> -23970 | Q45: -7961 | R45: =-21610-Q45 -> -13649 | S45: -7144 | T45: =-54350-SUM(Q45:S45) -> -25596 | U45: =SUM(Q45:T45) -> -54350 | V45: -10224 | W45: -18067 | X45: -960 | Y45: =-47833-SUM(V45:X45) -> -18582 | Z45: =SUM(V45:Y45) -> -47833 | AA45: -18337 | AB45: -21605 | AC45: -45593 | AD45: -12014 | AE45: =SUM(AA45:AD45) -> -97549 | AF45: -12033 | AG45: -29297 | AH45: -20108 | AI45: -23379 | AJ45: =SUM(AF45:AI45) -> -84817 | AK45: -15894 | AL45: -10068 | AM45: -30808 | AN45: =-94015-AK45-AL45-AM45 -> -37245 | AO45: =SUM(AK45:AN45) -> -94015 | AP45: =-87186-AQ45 -> -60319 | AQ45: -26867 | AR45: -15454 | AS45: =-175541-AP45-AQ45-AR45 -> -72901 | AT45: =SUM(AP45:AS45) -> -175541 | AU45: =-77936-AV45 -> -35528 | AV45: -42408 | AW45: -53490 | AX45: =-175167-SUM(AU45:AW45) -> -43741 | AY45: =SUM(AU45:AX45) -> -175167 | AZ45: -23891 | BA45: -39321 | BB45: -50664 | BC45: =-169887-SUM(AZ45:BB45) -> -56011 | BD45: =SUM(AZ45:BC45) -> -169887 | BE45: -17391 | BF45: -67053 | BG45: -37794 | BH45: =-145353-SUM(BE45:BG45) -> -23115 | BI45: =SUM(BE45:BH45) -> -145353 | BJ45: -27595 | BK45: -11800 | BL45: -28531 | BM45: =-93268-SUM(BJ45:BL45) -> -25342 | BN45: =SUM(BJ45:BM45) -> -93268 | BO45: -30221 | BP45: -6708 | BQ45: -20926 | BR45: =-84465-SUM(BO45:BQ45) -> -26610 | BS45: =SUM(BO45:BR45) -> -84465 | BT45: -16629 | BU45: -9306 | BV45: -26676 | BW45: =-90391-SUM(BT45:BV45) -> -37780 | BX45: =SUM(BT45:BW45) -> -90391 | BY45: -12991 | BZ45: -28456 | CA45: -16878 | CB45: =-118475-SUM(BY45:CA45) -> -60150 | CC45: =SUM(BY45:CB45) -> -118475 | CD45: -20301 | CE45: -25114 | CF45: -11594 | CG45: =-69239-SUM(CD45:CF45) -> -12230 | CH45: =SUM(CD45:CG45) -> -69239 | CI45: -15908 | CJ45: -23378 | CK45: -28696 | CL45: =-102959-SUM(CI45:CK45) -> -34977 | CM45: =SUM(CI45:CL45) -> -102959 | CN45: -8906 | CO45: -10817 | CP45: -20969 | CQ45: =-49711-SUM(CN45:CP45) -> -9019 | CR45: =SUM(CN45:CQ45) -> -49711 | CS45: -27484 | CT45: -28640 | CU45: -53319 | CV45: =-163610-SUM(CS45:CU45) -> -54167 | CW45: =SUM(CS45:CV45) -> -163610 | CX45: -47545 | CY45: -65938 | CZ45: -67911 | DA45: =-272056-SUM(CX45:CZ45) -> -90662 | DB45: =SUM(CX45:DA45) -> -272056 | DC45: -66181 | DD45: -91196 | DE45: -73848 | DF45: =-389073-SUM(DC45:DE45) -> -157848 | DG45: =SUM(DC45:DF45) -> -389073 | DH45: -63283 | DI45: -67151 | DJ45: =-30%/4*'Balance Sheet'!DI42 -> -96260.25 | DK45: =-30%/4*'Balance Sheet'!DJ42 -> -95144.265 | DL45: =SUM(DH45:DK45) -> -321838.52 | DM45: =-30%/4*'Balance Sheet'!DL42 -> -99065.432 | DN45: =-30%/4*'Balance Sheet'!DM42 -> -98640.76 | DO45: =-30%/4*'Balance Sheet'!DN42 -> -102537.43 | DP45: =-30%/4*'Balance Sheet'!DO42 -> -107636.19 | DQ45: =SUM(DM45:DP45) -> -407879.81 | DR45: =-30%/4*'Balance Sheet'!DQ42 -> -112507.45 | DS45: =-30%/4*'Balance Sheet'!DR42 -> -115618.2 | DT45: =-30%/4*'Balance Sheet'!DS42 -> -118903.96 | DU45: =-30%/4*'Balance Sheet'!DT42 -> -122642.76 | DV45: =SUM(DR45:DU45) -> -469672.38 | DW45: =-30%/4*'Balance Sheet'!DV42 -> -127947.21 | DX45: =-30%/4*'Balance Sheet'!DW42 -> -128997.42 | DY45: =-30%/4*'Balance Sheet'!DX42 -> -131141.4 | DZ45: =-30%/4*'Balance Sheet'!DY42 -> -132802.36 | EA45: =SUM(DW45:DZ45) -> -520888.4 | EB45: =-30%/4*'Balance Sheet'!EA42 -> -135014.53 | EC45: =-30%/4*'Balance Sheet'!EB42 -> -133932.72 | ED45: =-30%/4*'Balance Sheet'!EC42 -> -134910.46 | EE45: =-30%/4*'Balance Sheet'!ED42 -> -136891.76 | EF45: =SUM(EB45:EE45) -> -540749.47
A46: As % of Majority Earnings | B46: =-B45/B44 -> 0.17133121 | C46: =-C45/C44 -> 0.17133121 | D46: =-D45/D44 -> 0.14579439 | E46: =-E45/E44 -> 0.14839044 | F46: =-F45/F44 -> 0.15997059 | G46: =-G45/G44 -> 0.13401334 | H46: =-H45/H44 -> -0.067417469 | I46: =-I45/I44 -> 0.31083188 | ... EF46: =-EF45/EF44 -> 0.16596093
A47: Net Earnings | B47: =B44+B45 -> 22251 | C47: =C44+C45 -> 22251 | D47: =D44+D45 -> 21936 | E47: =E44+E45 -> 18095 | F47: =SUM(B47:E47) -> 84533 | G47: =G44+G45 -> 40497 | H47: =H44+H45 -> 34500 | I47: =I44+I45 -> 30495 | J47: =J44+J45 -> 22309 | K47: =SUM(G47:J47) -> 127801 | L47: =L44+L45 -> 57413 | M47: =M44+M45 -> 72958 | N47: =N44+N45 -> 31008 | O47: =O44+O45 -> 80627 | P47: =SUM(L47:O47) -> 242006 | Q47: =Q44+Q45 -> 43313 | R47: =R44+R45 -> 197457 | S47: =S44+S45 -> 90013 | T47: =T44+T45 -> 83904 | U47: =SUM(Q47:T47) -> 414687 | V47: =V44+V45 -> 68510 | W47: =W44+W45 -> 94027 | X47: =X44+X45 -> 77899 | Y47: =Y44+Y45 -> 37270 | Z47: =SUM(V47:Y47) -> 277706 | AA47: =AA44+AA45 -> 100457 | AB47: =AB44+AB45 -> 157071 | AC47: =AC44+AC45 -> 264103 | AD47: =AD44+AD45 -> 207718 | AE47: =SUM(AA47:AD47) -> 729349 | AF47: =AF44+AF45 -> 174240 | AG47: =AG44+AG45 -> 167794 | AH47: =AH44+AH45 -> 176034 | AI47: =AI44+AI45 -> 82526 | AJ47: =SUM(AF47:AI47) -> 600594 | AK47: =AK44+AK45 -> 74181 | AL47: =AL44+AL45 -> 95872 | AM47: =AM44+AM45 -> 146753 | AN47: =AN44+AN45 -> 181365 | AO47: =SUM(AK47:AN47) -> 498171 | AP47: =AP44+AP45 -> 117906 | AQ47: =AQ44+AQ45 -> 142745 | AR47: =AR44+AR45 -> 150395 | AS47: =AS44+AS45 -> 249102 | AT47: =SUM(AP47:AS47) -> 660148 | AU47: =AU44+AU45 -> 172929 | AV47: =AV44+AV45 -> 182777 | AW47: =AW44+AW45 -> 174604 | AX47: =AX44+AX45 -> 182522 | AY47: =SUM(AU47:AX47) -> 712832 | AZ47: =AZ44+AZ45 -> 163453 | BA47: =BA44+BA45 -> 168894 | BB47: =BB44+BB45 -> 179129 | BC47: =BC44+BC45 -> 150023 | BD47: =SUM(AZ47:BC47) -> 661499 | BE47: =BE44+BE45 -> 100541 | BF47: =BF44+BF45 -> 118006 | BG47: =BG44+BG45 -> 131232 | BH47: =BH44+BH45 -> 98021 | BI47: =SUM(BE47:BH47) -> 447800 | BJ47: =BJ44+BJ45 -> 61272 | BK47: =BK44+BK45 -> 44703 | BL47: =BL44+BL45 -> 14444 | BM47: =BM44+BM45 -> 30933 | BN47: =SUM(BJ47:BM47) -> 151352 | BO47: =BO44+BO45 -> 4025 | BP47: =BP44+BP45 -> -141028 | BQ47: =BQ44+BQ45 -> -6763 | BR47: =BR44+BR45 -> 48762 | BS47: =SUM(BO47:BR47) -> -95004 | BT47: =BT44+BT45 -> -51284 | BU47: =BU44+BU45 -> -28437 | BV47: =BV44+BV45 -> -120753 | BW47: =BW44+BW45 -> 116111 | BX47: =SUM(BT47:BW47) -> -84363 | BY47: =BY44+BY45 -> 48410 | BZ47: =BZ44+BZ45 -> 113835 | CA47: =CA44+CA45 -> 104383 | CB47: =CB44+CB45 -> 149215 | CC47: =SUM(BY47:CB47) -> 415843 | CD47: =CD44+CD45 -> 27935 | CE47: =CE44+CE45 -> 67811 | CF47: =CF44+CF45 -> 1403281 | CG47: =CG44+CG45 -> 261231 | CH47: =SUM(CD47:CG47) -> 1760258 | CI47: =CI44+CI45 -> 192285 | CJ47: =CJ44+CJ45 -> 266974 | CK47: =CK44+CK45 -> 237547 | CL47: =CL44+CL45 -> 217549 | CM47: =SUM(CI47:CL47) -> 914355 | CN47: =CN44+CN45 -> 161751 | CO47: =CO44+CO45 -> 150797 | CP47: =CP44+CP45 -> 288628 | CQ47: =CQ44+CQ45 -> 207704 | CR47: =SUM(CN47:CQ47) -> 808880 | CS47: =CS44+CS45 -> 163576 | CT47: =CT44+CT45 -> 279385 | CU47: =CU44+CU45 -> 251319 | CV47: =CV44+CV45 -> 247810 | CW47: =SUM(CS47:CV47) -> 942090 | CX47: =CX44+CX45 -> 267258 | CY47: =CY44+CY45 -> 412005 | CZ47: =CZ44+CZ45 -> 473101 | DA47: =DA44+DA45 -> 496632 | DB47: =SUM(CX47:DA47) -> 1648996 | DC47: =DC44+DC45 -> 327632 | DD47: =DD44+DD45 -> 387807 | DE47: =DE44+DE45 -> 609115 | DF47: =DF44+DF45 -> 682202 | DG47: =SUM(DC47:DF47) -> 2006756 | DH47: =DH44+DH45 -> 296776 | DI47: =DI44+DI45 -> 451576 | DJ47: =DJ44+DJ45 -> 524530.08 | DK47: =DK44+DK45 -> 617188.04 | DL47: =SUM(DH47:DK47) -> 1890070.1 | DM47: =DM44+DM45 -> 537656.99 | DN47: =DN44+DN45 -> 555649.43 | DO47: =DO44+DO45 -> 547147.32 | DP47: =DP44+DP45 -> 577282.3 | DQ47: =SUM(DM47:DP47) -> 2217736 | DR47: =DR44+DR45 -> 611473.4 | DS47: =DS44+DS45 -> 567852.47 | DT47: =DT44+DT45 -> 561667.87 | DU47: =DU44+DU45 -> 619834.62 | DV47: =SUM(DR47:DU47) -> 2360828.4 | DW47: =DW44+DW45 -> 645667.83 | DX47: =DX44+DX45 -> 592457.12 | DY47: =DY44+DY45 -> 580881.42 | DZ47: =DZ44+DZ45 -> 654367.97 | EA47: =SUM(DW47:DZ47) -> 2473374.3 | EB47: =EB44+EB45 -> 700167.75 | EC47: =EC44+EC45 -> 654288.52 | ED47: =ED44+ED45 -> 645005.66 | EE47: =EE44+EE45 -> 718082.45 | EF47: =SUM(EB47:EE47) -> 2717544.4
