Workbook

Sheet Cover
B6: =Valuation!B5&" -"&" "&Valuation!B18&" Rating - TP R$"&Valuation!B16&"/sh" -> CYRE3 - Outperform Rating - TP R$35/sh
B8: Brazil - Homebuilders
B10: Itaú BBA - Real Estate
B11: Elvis Credendio
B12: Cel.: +55 11 3073-3032
B14: Daniel Gasparete
B15: Cel.: +55 11 3073-3906
B17: Mariangela Castro
B18: Cel.: +55 11 3073-3102
B20: Juliana Veiga
B21: Cel.: +55 11 3073-2025

Sheet Macro
A2: =Valuation!$A$2 -> CYRE3 | TP R$35/sh
A3: Macro variables | B3: =B5&RIGHT(B4,2)&B6 -> 1Q10 | C3: =C5&RIGHT(C4,2)&C6 -> 2Q10 | D3: =D5&RIGHT(D4,2)&D6 -> 3Q10 | E3: =E5&RIGHT(E4,2)&E6 -> 4Q10 | F3: =F4&F6 -> 2010 | G3: =G5&RIGHT(G4,2)&G6 -> 1Q11 | H3: =H5&RIGHT(H4,2)&H6 -> 2Q11 | I3: =I5&RIGHT(I4,2)&I6 -> 3Q11 | J3: =J5&RIGHT(J4,2)&J6 -> 4Q11 | K3: =K4&K6 -> 2011 | L3: =L5&RIGHT(L4,2)&L6 -> 1Q12 | M3: =M5&RIGHT(M4,2)&M6 -> 2Q12 | N3: =N5&RIGHT(N4,2)&N6 -> 3Q12 | O3: =O5&RIGHT(O4,2)&O6 -> 4Q12 | P3: =P4&P6 -> 2012 | Q3: =Q5&RIGHT(Q4,2)&Q6 -> 1Q13 | R3: =R5&RIGHT(R4,2)&R6 -> 2Q13 | S3: =S5&RIGHT(S4,2)&S6 -> 3Q13 | T3: =T5&RIGHT(T4,2)&T6 -> 4Q13 | U3: =U4&U6 -> 2013 | V3: =V5&RIGHT(V4,2)&V6 -> 1Q14 | W3: =W5&RIGHT(W4,2)&W6 -> 2Q14 | X3: =X5&RIGHT(X4,2)&X6 -> 3Q14 | Y3: =Y5&RIGHT(Y4,2)&Y6 -> 4Q14 | Z3: =Z4&Z6 -> 2014 | AA3: =AA5&RIGHT(AA4,2)&AA6 -> 1Q15 | AB3: =AB5&RIGHT(AB4,2)&AB6 -> 2Q15 | AC3: =AC5&RIGHT(AC4,2)&AC6 -> 3Q15 | AD3: =AD5&RIGHT(AD4,2)&AD6 -> 4Q15 | AE3: =AE4&AE6 -> 2015 | AF3: =AF5&RIGHT(AF4,2)&AF6 -> 1Q16 | AG3: =AG5&RIGHT(AG4,2)&AG6 -> 2Q16 | AH3: =AH5&RIGHT(AH4,2)&AH6 -> 3Q16 | AI3: =AI5&RIGHT(AI4,2)&AI6 -> 4Q16 | AJ3: =AJ4&AJ6 -> 2016 | AK3: =AK5&RIGHT(AK4,2)&AK6 -> 1Q17 | AL3: =AL5&RIGHT(AL4,2)&AL6 -> 2Q17 | AM3: =AM5&RIGHT(AM4,2)&AM6 -> 3Q17 | AN3: =AN5&RIGHT(AN4,2)&AN6 -> 4Q17 | AO3: =AO4&AO6 -> 2017 | AP3: =AP5&RIGHT(AP4,2)&AP6 -> 1Q18 | AQ3: =AQ5&RIGHT(AQ4,2)&AQ6 -> 2Q18 | AR3: =AR5&RIGHT(AR4,2)&AR6 -> 3Q18 | AS3: =AS5&RIGHT(AS4,2)&AS6 -> 4Q18 | AT3: =AT4&AT6 -> 2018 | AU3: =AU5&RIGHT(AU4,2)&AU6 -> 1Q19 | AV3: =AV5&RIGHT(AV4,2)&AV6 -> 2Q19 | AW3: =AW5&RIGHT(AW4,2)&AW6 -> 3Q19 | AX3: =AX5&RIGHT(AX4,2)&AX6 -> 4Q19 | AY3: =AY4&AY6 -> 2019 | AZ3: =AZ5&RIGHT(AZ4,2)&AZ6 -> 1Q20 | BA3: =BA5&RIGHT(BA4,2)&BA6 -> 2Q20 | BB3: =BB5&RIGHT(BB4,2)&BB6 -> 3Q20 | BC3: =BC5&RIGHT(BC4,2)&BC6 -> 4Q20 | BD3: =BD4&BD6 -> 2020 | BE3: =BE5&RIGHT(BE4,2)&BE6 -> 1Q21 | BF3: =BF5&RIGHT(BF4,2)&BF6 -> 2Q21 | BG3: =BG5&RIGHT(BG4,2)&BG6 -> 3Q21 | BH3: =BH5&RIGHT(BH4,2)&BH6 -> 4Q21 | BI3: =BI4&BI6 -> 2021 | BJ3: =BJ5&RIGHT(BJ4,2)&BJ6 -> 1Q22 | BK3: =BK5&RIGHT(BK4,2)&BK6 -> 2Q22 | BL3: =BL5&RIGHT(BL4,2)&BL6 -> 3Q22 | BM3: =BM5&RIGHT(BM4,2)&BM6 -> 4Q22 | BN3: =BN4&BN6 -> 2022 | BO3: =BO5&RIGHT(BO4,2)&BO6 -> 1Q23 | BP3: =BP5&RIGHT(BP4,2)&BP6 -> 2Q23 | BQ3: =BQ5&RIGHT(BQ4,2)&BQ6 -> 3Q23 | BR3: =BR5&RIGHT(BR4,2)&BR6 -> 4Q23 | BS3: =BS4&BS6 -> 2023 | BT3: =BT5&RIGHT(BT4,2)&BT6 -> 1Q24 | BU3: =BU5&RIGHT(BU4,2)&BU6 -> 2Q24 | BV3: =BV5&RIGHT(BV4,2)&BV6 -> 3Q24 | BW3: =BW5&RIGHT(BW4,2)&BW6 -> 4Q24 | BX3: =BX4&BX6 -> 2024 | BY3: =BY5&RIGHT(BY4,2)&BY6 -> 1Q25 | BZ3: =BZ5&RIGHT(BZ4,2)&BZ6 -> 2Q25 | CA3: =CA5&RIGHT(CA4,2)&CA6 -> 3Q25 | CB3: =CB5&RIGHT(CB4,2)&CB6 -> 4Q25 | CC3: =CC4&CC6 -> 2025 | CD3: =CD5&RIGHT(CD4,2)&CD6 -> 1Q26 | CE3: =CE5&RIGHT(CE4,2)&CE6 -> 2Q26 | CF3: =CF5&RIGHT(CF4,2)&CF6 -> 3Q26E | CG3: =CG5&RIGHT(CG4,2)&CG6 -> 4Q26E | CH3: =CH4&CH6 -> 2026E | CI3: =CI5&RIGHT(CI4,2)&CI6 -> 1Q27E | CJ3: =CJ5&RIGHT(CJ4,2)&CJ6 -> 2Q27E | CK3: =CK5&RIGHT(CK4,2)&CK6 -> 3Q27E | CL3: =CL5&RIGHT(CL4,2)&CL6 -> 4Q27E | CM3: =CM4&CM6 -> 2027E | CN3: =CN5&RIGHT(CN4,2)&CN6 -> 1Q28E | CO3: =CO5&RIGHT(CO4,2)&CO6 -> 2Q28E | CP3: =CP5&RIGHT(CP4,2)&CP6 -> 3Q28E | CQ3: =CQ5&RIGHT(CQ4,2)&CQ6 -> 4Q28E | CR3: =CR4&CR6 -> 2028E | CS3: =CS5&RIGHT(CS4,2)&CS6 -> 1Q29E | CT3: =CT5&RIGHT(CT4,2)&CT6 -> 2Q29E | CU3: =CU5&RIGHT(CU4,2)&CU6 -> 3Q29E | CV3: =CV5&RIGHT(CV4,2)&CV6 -> 4Q29E | CW3: =CW4&CW6 -> 2029E | CX3: =CX5&RIGHT(CX4,2)&CX6 -> 1Q30E | CY3: =CY5&RIGHT(CY4,2)&CY6 -> 2Q30E | CZ3: =CZ5&RIGHT(CZ4,2)&CZ6 -> 3Q30E | DA3: =DA5&RIGHT(DA4,2)&DA6 -> 4Q30E | DB3: =DB4&DB6 -> 2030E
A4: Year | B4: 2010 | C4: 2010 | D4: 2010 | E4: 2010 | F4: =E4 -> 2010 | G4: =B4+1 -> 2011 | H4: =C4+1 -> 2011 | I4: =D4+1 -> 2011 | J4: =E4+1 -> 2011 | K4: =J4 -> 2011 | L4: =G4+1 -> 2012 | M4: =H4+1 -> 2012 | N4: =I4+1 -> 2012 | O4: =J4+1 -> 2012 | P4: =O4 -> 2012 | Q4: =L4+1 -> 2013 | R4: =M4+1 -> 2013 | S4: =N4+1 -> 2013 | T4: =O4+1 -> 2013 | U4: =T4 -> 2013 | V4: =Q4+1 -> 2014 | W4: =R4+1 -> 2014 | X4: =S4+1 -> 2014 | Y4: =T4+1 -> 2014 | Z4: =Y4 -> 2014 | AA4: =V4+1 -> 2015 | AB4: =W4+1 -> 2015 | AC4: =X4+1 -> 2015 | AD4: =Y4+1 -> 2015 | AE4: =AD4 -> 2015 | AF4: =AA4+1 -> 2016 | AG4: =AB4+1 -> 2016 | AH4: =AC4+1 -> 2016 | AI4: =AD4+1 -> 2016 | AJ4: =AI4 -> 2016 | AK4: =AF4+1 -> 2017 | AL4: =AG4+1 -> 2017 | AM4: =AH4+1 -> 2017 | AN4: =AI4+1 -> 2017 | AO4: =AN4 -> 2017 | AP4: =AK4+1 -> 2018 | AQ4: =AL4+1 -> 2018 | AR4: =AM4+1 -> 2018 | AS4: =AN4+1 -> 2018 | AT4: =AS4 -> 2018 | AU4: =AP4+1 -> 2019 | AV4: =AQ4+1 -> 2019 | AW4: =AR4+1 -> 2019 | AX4: =AS4+1 -> 2019 | AY4: =AX4 -> 2019 | AZ4: =AU4+1 -> 2020 | BA4: =AV4+1 -> 2020 | BB4: =AW4+1 -> 2020 | BC4: =AX4+1 -> 2020 | BD4: =BC4 -> 2020 | BE4: =AZ4+1 -> 2021 | BF4: =BA4+1 -> 2021 | BG4: =BB4+1 -> 2021 | BH4: =BC4+1 -> 2021 | BI4: =BH4 -> 2021 | BJ4: =BE4+1 -> 2022 | BK4: =BF4+1 -> 2022 | BL4: =BG4+1 -> 2022 | BM4: =BH4+1 -> 2022 | BN4: =BM4 -> 2022 | BO4: =BJ4+1 -> 2023 | BP4: =BK4+1 -> 2023 | BQ4: =BL4+1 -> 2023 | BR4: =BM4+1 -> 2023 | BS4: =BR4 -> 2023 | BT4: =BO4+1 -> 2024 | BU4: =BP4+1 -> 2024 | BV4: =BQ4+1 -> 2024 | BW4: =BR4+1 -> 2024 | BX4: =BW4 -> 2024 | BY4: =BT4+1 -> 2025 | BZ4: =BU4+1 -> 2025 | CA4: =BV4+1 -> 2025 | CB4: =BW4+1 -> 2025 | CC4: =CB4 -> 2025 | CD4: =BY4+1 -> 2026 | CE4: =BZ4+1 -> 2026 | CF4: =CA4+1 -> 2026 | CG4: =CB4+1 -> 2026 | CH4: =CG4 -> 2026 | CI4: =CD4+1 -> 2027 | CJ4: =CE4+1 -> 2027 | CK4: =CF4+1 -> 2027 | CL4: =CG4+1 -> 2027 | CM4: =CL4 -> 2027 | CN4: =CI4+1 -> 2028 | CO4: =CJ4+1 -> 2028 | CP4: =CK4+1 -> 2028 | CQ4: =CL4+1 -> 2028 | CR4: =CQ4 -> 2028 | CS4: =CN4+1 -> 2029 | CT4: =CO4+1 -> 2029 | CU4: =CP4+1 -> 2029 | CV4: =CQ4+1 -> 2029 | CW4: =CV4 -> 2029 | CX4: =CS4+1 -> 2030 | CY4: =CT4+1 -> 2030 | CZ4: =CU4+1 -> 2030 | DA4: =CV4+1 -> 2030 | DB4: =DA4 -> 2030
A5: Quarter | B5: 1Q | C5: 2Q | D5: 3Q | E5: 4Q | G5: 1Q | H5: 2Q | I5: 3Q | J5: 4Q | K5: 20 | L5: 1Q | M5: 2Q | N5: 3Q | O5: 4Q | P5: 20 | Q5: 1Q | R5: 2Q | S5: 3Q | T5: 4Q | U5: 20 | V5: 1Q | W5: 2Q | X5: 3Q | Y5: 4Q | Z5: 20 | AA5: 1Q | AB5: 2Q | AC5: 3Q | AD5: 4Q | AE5: 20 | AF5: 1Q | AG5: 2Q | AH5: 3Q | AI5: 4Q | AJ5: 20 | AK5: 1Q | AL5: 2Q | AM5: 3Q | AN5: 4Q | AO5: 20 | AP5: 1Q | AQ5: 2Q | AR5: 3Q | AS5: 4Q | AT5: 20 | AU5: 1Q | AV5: 2Q | AW5: 3Q | AX5: 4Q | AY5: 20 | AZ5: 1Q | BA5: 2Q | BB5: 3Q | BC5: 4Q | BD5: 20 | BE5: 1Q | BF5: 2Q | BG5: 3Q | BH5: 4Q | BI5: 20 | BJ5: 1Q | BK5: 2Q | BL5: 3Q | BM5: 4Q | BN5: 20 | BO5: 1Q | BP5: 2Q | BQ5: 3Q | BR5: 4Q | BS5: 20 | BT5: 1Q | BU5: 2Q | BV5: 3Q | BW5: 4Q | BX5: 20 | BY5: 1Q | BZ5: 2Q | CA5: 3Q | CB5: 4Q | CC5: 20 | CD5: 1Q | CE5: 2Q | CF5: 3Q | CG5: 4Q | CH5: 20 | CI5: 1Q | CJ5: 2Q | CK5: 3Q | CL5: 4Q | CM5: 20 | CN5: 1Q | CO5: 2Q | CP5: 3Q | CQ5: 4Q | CR5: 20 | CS5: 1Q | CT5: 2Q | CU5: 3Q | CV5: 4Q | CW5: 20 | CX5: 1Q | CY5: 2Q | CZ5: 3Q | DA5: 4Q | DB5: 20
A6: Actual / estimate | CF6: E | CG6: E | CH6: E | CI6: E | CJ6: E | CK6: E | CL6: E | CM6: E | CN6: E | CO6: E | CP6: E | CQ6: E | CR6: E | CS6: E | CT6: E | CU6: E | CV6: E | CW6: E | CX6: E | CY6: E | CZ6: E | DA6: E | DB6: E
A7: GDP growth | B7: =[4]Macro_Model!B7 -> 0.091174884 | C7: =[4]Macro_Model!C7 -> 0.085075937 | D7: =[4]Macro_Model!D7 -> 0.06962323 | E7: =[4]Macro_Model!E7 -> 0.057675173 | F7: =[4]Macro_Model!F7 -> 0.075282491 | G7: =[4]Macro_Model!G7 -> 0.050185202 | H7: =[4]Macro_Model!H7 -> 0.047444346 | I7: =[4]Macro_Model!I7 -> 0.035981126 | ... DB7: =[4]Macro_Model!DB7 -> 0.018
A8: IGP-M | B8: =[4]Macro_Model!B8 -> 0.0277751 | C8: =[4]Macro_Model!C8 -> 0.028275291 | D8: =[4]Macro_Model!D8 -> 0.020898783 | E8: =[4]Macro_Model!E8 -> 0.031799424 | F8: =[4]Macro_Model!F8 -> 0.11323143 | G8: =[4]Macro_Model!G8 -> 0.024312626 | H8: =[4]Macro_Model!H8 -> 0.0069680368 | I8: =[4]Macro_Model!I8 -> 0.0097144444 | ... DB8: =[4]Macro_Model!DB8 -> 0.035
A9: IGP-M y/y | B9: =[4]Macro_Model!B9 -> 0 | C9: =[4]Macro_Model!C9 -> 0 | D9: =[4]Macro_Model!D9 -> 0 | E9: =[4]Macro_Model!E9 -> 0 | F9: =[4]Macro_Model!F9 -> 0.11323143 | G9: =[4]Macro_Model!G9 -> 0 | H9: =[4]Macro_Model!H9 -> 0 | I9: =[4]Macro_Model!I9 -> 0 | ... DB9: =[4]Macro_Model!DB9 -> 0.035
A10: IPCA q/q | B10: =[4]Macro_Model!B10 -> 0.020635673 | C10: =[4]Macro_Model!C10 -> 0.01002643 | D10: =[4]Macro_Model!D10 -> 0.0049988106 | E10: =[4]Macro_Model!E10 -> 0.02226281 | F10: =[4]Macro_Model!F10 -> 0.059086887 | G10: =[4]Macro_Model!G10 -> 0.02439696 | H10: =[4]Macro_Model!H10 -> 0.013956003 | I10: =[4]Macro_Model!I10 -> 0.010633971 | ... DB10: =[4]Macro_Model!DB10 -> 0.035
A11: IPCA y/y | B11: =[4]Macro_Model!B11 -> 0.048630627 | C11: =[4]Macro_Model!C11 -> 0.051065847 | D11: =[4]Macro_Model!D11 -> 0.045967658 | E11: =[4]Macro_Model!E11 -> 0.055795324 | F11: =[4]Macro_Model!F11 -> 0.059086887 | G11: =[4]Macro_Model!G11 -> 0.061020488 | H11: =[4]Macro_Model!H11 -> 0.065918631 | I11: =[4]Macro_Model!I11 -> 0.071362426 | ... DB11: =[4]Macro_Model!DB11 -> 0.035
A12: CDI rate | B12: =[4]Macro_Model!B12 -> 0.0875 | C12: =[4]Macro_Model!C12 -> 0.0975 | D12: =[4]Macro_Model!D12 -> 0.1075 | E12: =[4]Macro_Model!E12 -> 0.1075 | F12: =[4]Macro_Model!F12 -> 0.1 | G12: =[4]Macro_Model!G12 -> 0.11416667 | H12: =[4]Macro_Model!H12 -> 0.12083333 | I12: =[4]Macro_Model!I12 -> 0.12166667 | ... DB12: =[4]Macro_Model!DB12 -> 0.106

Sheet IS
A2: =Valuation!$A$2 -> CYRE3 | TP R$35/sh
A3: Income Statement (R$000') | B3: =Macro!B$3 -> 1Q10 | C3: =Macro!C$3 -> 2Q10 | D3: =Macro!D$3 -> 3Q10 | E3: =Macro!E$3 -> 4Q10 | F3: =Macro!F$3 -> 2010 | G3: =Macro!G$3 -> 1Q11 | H3: =Macro!H$3 -> 2Q11 | I3: =Macro!I$3 -> 3Q11 | ... DB3: =Macro!DB$3 -> 2030E
A4: Gross revenues | B4: =B5+B6 -> 1170169 | C4: =C5+C6 -> 1234539 | D4: =D5+D6 -> 1203539 | E4: =E5+E6 -> 1445304 | F4: =SUM(B4:E4) -> 5053551 | G4: =G5+G6 -> 1248883 | H4: =H5+H6 -> 1438136 | I4: =I5+I6 -> 1619390 | J4: =J5+J6 -> 2069350 | K4: =SUM(G4:J4) -> 6375759 | L4: =L5+L6 -> 1522642 | M4: =M5+M6 -> 1438939 | N4: =N5+N6 -> 1409120 | O4: =O5+O6 -> 1432050 | P4: =SUM(L4:O4) -> 5802751 | Q4: =Q5+Q6 -> 1250942 | R4: =R5+R6 -> 1410150 | S4: =S5+S6 -> 1435138 | T4: =T5+T6 -> 1436106 | U4: =SUM(Q4:T4) -> 5532336 | V4: =V5+V6 -> 1351067 | W4: =W5+W6 -> 1397217 | X4: =X5+X6 -> 1628377 | Y4: =Y5+Y6 -> 1569902 | Z4: =SUM(V4:Y4) -> 5946563 | AA4: =AA5+AA6 -> 1068010 | AB4: =AB5+AB6 -> 1165862 | AC4: =AC5+AC6 -> 1172876 | AD4: =AD5+AD6 -> 1059054 | AE4: =SUM(AA4:AD4) -> 4465802 | AF4: =AF5+AF6 -> 833226 | AG4: =AG5+AG6 -> 662190 | AH4: =AH5+AH6 -> 847384 | AI4: =AI5+AI6 -> 947904 | AJ4: =SUM(AF4:AI4) -> 3290704 | AK4: =AK5+AK6 -> 712412 | AL4: =AL5+AL6 -> 591107 | AM4: =AM5+AM6 -> 614497 | AN4: =AN5+AN6 -> 831905 | AO4: =SUM(AK4:AN4) -> 2749921 | AP4: =AP5+AP6 -> 464152 | AQ4: =AQ5+AQ6 -> 657521 | AR4: =AR5+AR6 -> 744589 | AS4: =AS5+AS6 -> 1111066 | AT4: =SUM(AP4:AS4) -> 2977328 | AU4: =AU5+AU6 -> 847909 | AV4: =AV5+AV6 -> 959639 | AW4: =AW5+AW6 -> 959878 | AX4: =AX5+AX6 -> 1265292 | AY4: =SUM(AU4:AX4) -> 4032718 | AZ4: =AZ5+AZ6 -> 785189 | BA4: =BA5+BA6 -> 860738 | BB4: =BB5+BB6 -> 1192465 | BC4: =BC5+BC6 -> 1087405 | BD4: =SUM(AZ4:BC4) -> 3925797 | BE4: =BE5+BE6 -> 1030234 | BF4: =BF5+BF6 -> 1213954 | BG4: =BG5+BG6 -> 1321796 | BH4: =BH5+BH6 -> 1351676 | BI4: =SUM(BE4:BH4) -> 4917660 | BJ4: =BJ5+BJ6 -> 1259101 | BK4: =BK5+BK6 -> 1284091 | BL4: =BL5+BL6 -> 1600107 | BM4: =BM5+BM6 -> 1412549 | BN4: =SUM(BJ4:BM4) -> 5555848 | BO4: =BO5+BO6 -> 1317322 | BP4: =BP5+BP6 -> 1678440 | BQ4: =BQ5+BQ6 -> 1672991 | BR4: =BR5+BR6 -> 1760921 | BS4: =SUM(BO4:BR4) -> 6429674 | BT4: =BT5+BT6 -> 1614575 | BU4: =BU5+BU6 -> 1909290 | BV4: =BV5+BV6 -> 2086805 | BW4: =BW5+BW6 -> 2574979 | BX4: =SUM(BT4:BW4) -> 8185649 | BY4: =BY5+BY6 -> 2003367 | BZ4: =BZ5+BZ6 -> 2167903 | CA4: =CA5+CA6 -> 2191373 | CB4: =CB5+CB6 -> 3317082 | CC4: =SUM(BY4:CB4) -> 9679725 | CD4: =CD5+CD6 -> 2081306 | CE4: =CE5+CE6 -> 2548922 | CF4: =CF5+CF6 -> 2725182.5 | CG4: =CG5+CG6 -> 2933473.8 | CH4: =SUM(CD4:CG4) -> 10288884 | CI4: =CI5+CI6 -> 2752041.2 | CJ4: =CJ5+CJ6 -> 2805655.7 | CK4: =CK5+CK6 -> 2948222.8 | CL4: =CL5+CL6 -> 3109438.2 | CM4: =SUM(CI4:CL4) -> 11615358 | CN4: =CN5+CN6 -> 3093368.1 | CO4: =CO5+CO6 -> 3128009.5 | CP4: =CP5+CP6 -> 3255981.1 | CQ4: =CQ5+CQ6 -> 3475613.2 | CR4: =SUM(CN4:CQ4) -> 12952972 | CS4: =CS5+CS6 -> 3391188.9 | CT4: =CT5+CT6 -> 3408720 | CU4: =CU5+CU6 -> 3525236 | CV4: =CV5+CV6 -> 3741182.3 | CW4: =SUM(CS4:CV4) -> 14066327 | CX4: =CX5+CX6 -> 3649385.9 | CY4: =CY5+CY6 -> 3657352 | CZ4: =CZ5+CZ6 -> 3772174 | DA4: =DA5+DA6 -> 3988590.2 | DB4: =SUM(CX4:DA4) -> 15067502
A5: Development revenues | B5: =1140556+18091 -> 1158647 | C5: =1191445+26952-C33 -> 1218397 | D5: =1171767+13862 -> 1185629 | E5: =1407331+6543 -> 1413874 | F5: =SUM(B5:E5) -> 4976547 | G5: =1216842+8949 -> 1225791 | H5: =2625160+13076-G5 -> 1412445 | I5: =4207472+17666-G5-H5 -> 1586902 | J5: =6240161+26490-G5-H5-I5 -> 2041513 | K5: =SUM(G5:J5) -> 6266651 | L5: =2915251+4573-M5 -> 1505576 | M5: =1411422+2826 -> 1414248 | N5: =1409120-N6 -> 1394730 | O5: =5701885+14069-L5-M5-N5 -> 1401400 | P5: =SUM(L5:O5) -> 5715954 | Q5: =2603392+20342-R5 -> 1233951 | R5: =1382665+7118 -> 1389783 | S5: =1435138-S6 -> 1414214 | T5: =5532336-SUM(Q5:S5)-SUM(Q6:T6) -> 1410416 | U5: =SUM(Q5:T5) -> 5448364 | V5: =1317983+17433 -> 1335416 | W5: =1366342+14295 -> 1380637 | X5: =1628377-X6 -> 1607593 | Y5: =5946563-SUM(V5:X5)-SUM(V6:Y6) -> 1558582 | Z5: =SUM(V5:Y5) -> 5882228 | AA5: =1031782+22263 -> 1054045 | AB5: =1141593+15312 -> 1156905 | AC5: =1172876-AC6 -> 1164221 | AD5: =4465802-SUM(AA5:AC5)-SUM(AA6:AD6) -> 1046063 | AE5: =SUM(AA5:AD5) -> 4421234 | AF5: =799333+20950 -> 820283 | AG5: =614249+21481 -> 635730 | AH5: =847384-AH6 -> 839121 | AI5: =3290704-SUM(AF5:AH5)-SUM(AF6:AI6) -> 942441 | AJ5: =SUM(AF5:AI5) -> 3237575 | AK5: =678581+16224 -> 694805 | AL5: =573917+11356 -> 585273 | AM5: =614497-AM6 -> 608783 | AN5: =2671670+44168-SUM(AK5:AM5) -> 826977 | AO5: =SUM(AK5:AN5) -> 2715838 | AP5: =445472+14559 -> 460031 | AQ5: =638476+14319 -> 652795 | AR5: =728261+9518 -> 737779 | AS5: =3156039+51958-SUM(AP5:AR5)-254000 -> 1103392 | AT5: =SUM(AP5:AS5) -> 2953997 | AU5: =845764+11907-14195 -> 843476 | AV5: =953167+9105-6610 -> 955662 | AW5: =901500+8113+41796 -> 951409 | AX5: =3867086+34904+105628-SUM(AU5:AW5) -> 1257071 | AY5: =SUM(AU5:AX5) -> 4007618 | AZ5: =724852+9374+39479 -> 773705 | BA5: =826804+3845+16608 -> 847257 | BB5: =1153156+14847+6784 -> 1174787 | BC5: =3765116+41562+48464-SUM(AZ5:BB5) -> 1059393 | BD5: =SUM(AZ5:BC5) -> 3855142 | BE5: =1057818+20802-45161-24355 -> 1009104 | BF5: =1193319+15809-12203-7752 -> 1189173 | BG5: =1288055+11945+2193-5203 -> 1296990 | BH5: =4851226+51769-62954-35986-SUM(BE5:BG5) -> 1308788 | BI5: =SUM(BE5:BH5) -> 4804055 | BJ5: =1270338+6461-43143+5545 -> 1239201 | BK5: =1219902+10977+30436-6907 -> 1254408 | BL5: =1549256+2670+8131+9798 -> 1569855 | BM5: =5440721+23045-15086+6545-SUM(BJ5:BL5) -> 1391761 | BN5: =SUM(BJ5:BM5) -> 5455225 | BO5: =1323506+633-18150-4887 -> 1301102 | BP5: =2967331+1814-2630-7413-BO5 -> 1658000 | BQ5: =4598860+2811+12432-3586-SUM(BO5:BP5) -> 1651415 | BR5: =6373445+3955-30135-3508-SUM(BO5:BQ5) -> 1733240 | BS5: =SUM(BO5:BR5) -> 6343757 | BT5: =1644948+2568-46749-5947 -> 1594820 | BU5: =3509983+3638-29563-3531-BT5 -> 1885707 | BV5: =5585280+2631-45676-236-SUM(BT5:BU5) -> 2061472 | BW5: =8201507+3951-109456-5895-SUM(BT5:BV5) -> 2548108 | BX5: =SUM(BT5:BW5) -> 8090107 | BY5: =2074898+285-99013-914 -> 1975256 | BZ5: =4146252+272-28621-1012-BY5 -> 2141635 | CA5: =6199476+66785+24246-10557-BZ5-BY5 -> 2163059 | CB5: =9498874+90734-12130-9388-SUM(BY5:CA5) -> 3288140 | CC5: =SUM(BY5:CB5) -> 9568090 | CD5: =2110359+10713-68796-2191 -> 2050085 | CE5: =4601478+13577-56471-3916-CD5 -> 2504583 | CF5: =Operating!CF35 -> 2677777.4 | CG5: =Operating!CG35 -> 2882445.5 | CH5: =SUM(CD5:CG5) -> 10114891 | CI5: =Operating!CI35 -> 2704168.9 | CJ5: =Operating!CJ35 -> 2756850.8 | CK5: =Operating!CK35 -> 2896937.9 | CL5: =Operating!CL35 -> 3055348.9 | CM5: =SUM(CI5:CL5) -> 11413306 | CN5: =Operating!CN35 -> 3039558.3 | CO5: =Operating!CO35 -> 3073597.2 | CP5: =Operating!CP35 -> 3199342.7 | CQ5: =Operating!CQ35 -> 3415154.2 | CR5: =SUM(CN5:CQ5) -> 12727652 | CS5: =Operating!CS35 -> 3332198.5 | CT5: =Operating!CT35 -> 3349424.6 | CU5: =Operating!CU35 -> 3463913.9 | CV5: =Operating!CV35 -> 3676103.7 | CW5: =SUM(CS5:CV5) -> 13821641 | CX5: =Operating!CX35 -> 3585904.1 | CY5: =Operating!CY35 -> 3593731.7 | CZ5: =Operating!CZ35 -> 3706556.3 | DA5: =Operating!DA35 -> 3919207.9 | DB5: =SUM(CX5:DA5) -> 14805400
A6: Service revenues | B6: 11522 | C6: 16142 | D6: 17910 | E6: 31430 | F6: =SUM(B6:E6) -> 77004 | G6: 23092 | H6: =48783-G6 -> 25691 | I6: =81271-G6-H6 -> 32488 | J6: =109108-G6-H6-I6 -> 27837 | K6: =SUM(G6:J6) -> 109108 | L6: =41757-M6 -> 17066 | M6: 24691 | N6: 14390 | O6: =86797-L6-M6-N6 -> 30650 | P6: =SUM(L6:O6) -> 86797 | Q6: =37358-R6 -> 16991 | R6: 20367 | S6: 20924 | T6: =83972-SUM(Q6:S6) -> 25690 | U6: =SUM(Q6:T6) -> 83972 | V6: 15651 | W6: 16580 | X6: 20784 | Y6: =64335-SUM(V6:X6) -> 11320 | Z6: =SUM(V6:Y6) -> 64335 | AA6: 13965 | AB6: 8957 | AC6: 8655 | AD6: =44568-SUM(AA6:AC6) -> 12991 | AE6: =SUM(AA6:AD6) -> 44568 | AF6: 12943 | AG6: 26460 | AH6: 8263 | AI6: =53129-SUM(AF6:AH6) -> 5463 | AJ6: =SUM(AF6:AI6) -> 53129 | AK6: 17607 | AL6: 5834 | AM6: 5714 | AN6: =34083-SUM(AK6:AM6) -> 4928 | AO6: =SUM(AK6:AN6) -> 34083 | AP6: 4121 | AQ6: 4726 | AR6: 6810 | AS6: =23331-SUM(AP6:AR6) -> 7674 | AT6: =SUM(AP6:AS6) -> 23331 | AU6: 4433 | AV6: 3977 | AW6: 8469 | AX6: =25100-SUM(AU6:AW6) -> 8221 | AY6: =SUM(AU6:AX6) -> 25100 | AZ6: 11484 | BA6: 13481 | BB6: 17678 | BC6: =70655-SUM(AZ6:BB6) -> 28012 | BD6: =SUM(AZ6:BC6) -> 70655 | BE6: 21130 | BF6: 24781 | BG6: 24806 | BH6: =113605-SUM(BE6:BG6) -> 42888 | BI6: =SUM(BE6:BH6) -> 113605 | BJ6: 19900 | BK6: 29683 | BL6: 30252 | BM6: =100623-SUM(BJ6:BL6) -> 20788 | BN6: =SUM(BJ6:BM6) -> 100623 | BO6: 16220 | BP6: =36660-BO6 -> 20440 | BQ6: =58236-SUM(BO6:BP6) -> 21576 | BR6: =85917-SUM(BO6:BQ6) -> 27681 | BS6: =SUM(BO6:BR6) -> 85917 | BT6: 19755 | BU6: =43338-BT6 -> 23583 | BV6: =68671-SUM(BT6:BU6) -> 25333 | BW6: =95542-SUM(BT6:BV6) -> 26871 | BX6: =SUM(BT6:BW6) -> 95542 | BY6: 28111 | BZ6: =54379-BY6 -> 26268 | CA6: =82693-BZ6-BY6 -> 28314 | CB6: =111635-SUM(BY6:CA6) -> 28942 | CC6: =SUM(BY6:CB6) -> 111635 | CD6: 31221 | CE6: =75560-CD6 -> 44339 | CF6: =Operating!CF41 -> 47405.086 | CG6: =Operating!CG41 -> 51028.355 | CH6: =SUM(CD6:CG6) -> 173993.44 | CI6: =Operating!CI41 -> 47872.298 | CJ6: =Operating!CJ41 -> 48804.934 | CK6: =Operating!CK41 -> 51284.917 | CL6: =Operating!CL41 -> 54089.289 | CM6: =SUM(CI6:CL6) -> 202051.44 | CN6: =Operating!CN41 -> 53809.746 | CO6: =Operating!CO41 -> 54412.342 | CP6: =Operating!CP41 -> 56638.433 | CQ6: =Operating!CQ41 -> 60458.975 | CR6: =SUM(CN6:CQ6) -> 225319.5 | CS6: =Operating!CS41 -> 58990.398 | CT6: =Operating!CT41 -> 59295.355 | CU6: =Operating!CU41 -> 61322.175 | CV6: =Operating!CV41 -> 65078.603 | CW6: =SUM(CS6:CV6) -> 244686.53 | CX6: =Operating!CX41 -> 63481.785 | CY6: =Operating!CY41 -> 63620.358 | CZ6: =Operating!CZ41 -> 65617.709 | DA6: =Operating!DA41 -> 69382.311 | DB6: =SUM(CX6:DA6) -> 262102.16
A7: Taxes and deductions | B7: -37721 | C7: -28704 | D7: -40990 | E7: -56031 | F7: =SUM(B7:E7) -> -163446 | G7: -48141 | H7: =-103393-G7 -> -55252 | I7: =-163181-G7-H7 -> -59788 | J7: =-248978-G7-H7-I7 -> -85797 | K7: =SUM(G7:J7) -> -248978 | L7: =-109975-M7 -> -56299 | M7: -53676 | N7: -59168 | O7: =-170072-L7-M7-N7 -> -929 | P7: =SUM(L7:O7) -> -170072 | Q7: =-73303-R7 -> -35572 | R7: -37731 | S7: -40690 | T7: =-160454-SUM(Q7:S7) -> -46461 | U7: =SUM(Q7:T7) -> -160454 | V7: -35705 | W7: -38886 | X7: -14681 | Y7: =-128636-SUM(V7:X7) -> -39364 | Z7: =SUM(V7:Y7) -> -128636 | AA7: -32796 | AB7: -28179 | AC7: -35143 | AD7: =-124618-SUM(AA7:AC7) -> -28500 | AE7: =SUM(AA7:AD7) -> -124618 | AF7: -22520 | AG7: -21157 | AH7: -22577 | AI7: =-95394-SUM(AF7:AH7) -> -29140 | AJ7: =SUM(AF7:AI7) -> -95394 | AK7: -20025 | AL7: -16351 | AM7: -16670 | AN7: =-76151-SUM(AK7:AM7) -> -23105 | AO7: =SUM(AK7:AN7) -> -76151 | AP7: -13530 | AQ7: -17982 | AR7: -19764 | AS7: =-85171-SUM(AP7:AR7) -> -33895 | AT7: =SUM(AP7:AS7) -> -85171 | AU7: -21673 | AV7: -23017 | AW7: -25119 | AX7: =-101895-SUM(AU7:AW7) -> -32086 | AY7: =SUM(AU7:AX7) -> -101895 | AZ7: -20434 | BA7: -21930 | BB7: -28962 | BC7: =-102101-SUM(AZ7:BB7) -> -30775 | BD7: =SUM(AZ7:BC7) -> -102101 | BE7: -26502 | BF7: -31935 | BG7: -33457 | BH7: =-126827-SUM(BE7:BG7) -> -34933 | BI7: =SUM(BE7:BH7) -> -126827 | BJ7: -27449 | BK7: -34008 | BL7: -40463 | BM7: =-143553-SUM(BJ7:BL7) -> -41633 | BN7: =SUM(BJ7:BM7) -> -143553 | BO7: -33896 | BP7: =-79281-BO7 -> -45385 | BQ7: =-126285-SUM(BO7:BP7) -> -47004 | BR7: =-176975-SUM(BO7:BQ7) -> -50690 | BS7: =SUM(BO7:BR7) -> -176975 | BT7: -41664 | BU7: =-94097-BT7 -> -52433 | BV7: =-151251-SUM(BT7:BU7) -> -57154 | BW7: =-219961-SUM(BT7:BV7) -> -68710 | BX7: =SUM(BT7:BW7) -> -219961 | BY7: -50623 | BZ7: =-111396-BY7 -> -60773 | CA7: =-174323-BZ7-BY7 -> -62927 | CB7: =-256231-SUM(BY7:CA7) -> -81908 | CC7: =SUM(BY7:CB7) -> -256231 | CD7: -56273 | CE7: =-124324-CD7 -> -68051 | CF7: =-CF8*CF$4 -> -68129.563 | CG7: =-CG8*CG$4 -> -73336.846 | CH7: =SUM(CD7:CG7) -> -265790.41 | CI7: =-CI8*CI$4 -> -57242.456 | CJ7: =-CJ8*CJ$4 -> -58357.639 | CK7: =-CK8*CK$4 -> -61323.035 | CL7: =-CL8*CL$4 -> -64676.314 | CM7: =SUM(CI7:CL7) -> -241599.44 | CN7: =-CN8*CN$4 -> -64342.056 | CO7: =-CO8*CO$4 -> -65062.598 | CP7: =-CP8*CP$4 -> -67724.408 | CQ7: =-CQ8*CQ$4 -> -72292.754 | CR7: =SUM(CN7:CQ7) -> -269421.82 | CS7: =-CS8*CS$4 -> -70536.729 | CT7: =-CT8*CT$4 -> -70901.376 | CU7: =-CU8*CU$4 -> -73324.91 | CV7: =-CV8*CV$4 -> -77816.592 | CW7: =SUM(CS7:CV7) -> -292579.61 | CX7: =-CX8*CX$4 -> -75907.226 | CY7: =-CY8*CY$4 -> -76072.922 | CZ7: =-CZ8*CZ$4 -> -78461.219 | DA7: =-DA8*DA$4 -> -82962.676 | DB7: =SUM(CX7:DA7) -> -313404.04
A8: % of gross revenues | B8: =-B7/B$4 -> 0.032235515 | C8: =-C7/C$4 -> 0.023250784 | D8: =-D7/D$4 -> 0.034057891 | E8: =-E7/E$4 -> 0.038767623 | F8: =-F7/F$4 -> 0.032342802 | G8: =-G7/G$4 -> 0.038547246 | H8: =-H7/H$4 -> 0.038419176 | I8: =-I7/I$4 -> 0.036920075 | ... CE8: =-CE7/CE$4 -> 0.026697953 | CF8: 0.025 | CG8: 0.025 | CH8: =-CH7/CH$4 -> 0.025832773 | CI8: 0.0208 | CJ8: 0.0208 | CK8: 0.0208 | CL8: 0.0208 | CM8: =-CM7/CM$4 -> 0.0208 | CN8: 0.0208 | CO8: 0.0208 | CP8: 0.0208 | CQ8: 0.0208 | CR8: =-CR7/CR$4 -> 0.0208 | CS8: 0.0208 | CT8: 0.0208 | CU8: 0.0208 | CV8: 0.0208 | CW8: =-CW7/CW$4 -> 0.0208 | CX8: 0.0208 | CY8: 0.0208 | CZ8: 0.0208 | DA8: 0.0208 | DB8: =-DB7/DB$4 -> 0.0208
A9: Net Revenues | B9: =B4+B7 -> 1132448 | C9: =C4+C7 -> 1205835 | D9: =D4+D7 -> 1162549 | E9: =E4+E7 -> 1389273 | F9: =SUM(B9:E9) -> 4890105 | G9: =G4+G7 -> 1200742 | H9: =H4+H7 -> 1382884 | I9: =I4+I7 -> 1559602 | J9: =J4+J7 -> 1983553 | K9: =SUM(G9:J9) -> 6126781 | L9: =L4+L7 -> 1466343 | M9: =M4+M7 -> 1385263 | N9: =N4+N7 -> 1349952 | O9: =O4+O7 -> 1431121 | P9: =SUM(L9:O9) -> 5632679 | Q9: =Q4+Q7 -> 1215370 | R9: =R4+R7 -> 1372419 | S9: =S4+S7 -> 1394448 | T9: =T4+T7 -> 1389645 | U9: =SUM(Q9:T9) -> 5371882 | V9: =V4+V7 -> 1315362 | W9: =W4+W7 -> 1358331 | X9: =X4+X7 -> 1613696 | Y9: =Y4+Y7 -> 1530538 | Z9: =SUM(V9:Y9) -> 5817927 | AA9: =AA4+AA7 -> 1035214 | AB9: =AB4+AB7 -> 1137683 | AC9: =AC4+AC7 -> 1137733 | AD9: =AD4+AD7 -> 1030554 | AE9: =SUM(AA9:AD9) -> 4341184 | AF9: =AF4+AF7 -> 810706 | AG9: =AG4+AG7 -> 641033 | AH9: =AH4+AH7 -> 824807 | AI9: =AI4+AI7 -> 918764 | AJ9: =SUM(AF9:AI9) -> 3195310 | AK9: =AK4+AK7 -> 692387 | AL9: =AL4+AL7 -> 574756 | AM9: =AM4+AM7 -> 597827 | AN9: =AN4+AN7 -> 808800 | AO9: =SUM(AK9:AN9) -> 2673770 | AP9: =AP4+AP7 -> 450622 | AQ9: =AQ4+AQ7 -> 639539 | AR9: =AR4+AR7 -> 724825 | AS9: =AS4+AS7 -> 1077171 | AT9: =SUM(AP9:AS9) -> 2892157 | AU9: =AU4+AU7 -> 826236 | AV9: =AV4+AV7 -> 936622 | AW9: =AW4+AW7 -> 934759 | AX9: =AX4+AX7 -> 1233206 | AY9: =SUM(AU9:AX9) -> 3930823 | AZ9: =AZ4+AZ7 -> 764755 | BA9: =BA4+BA7 -> 838808 | BB9: =BB4+BB7 -> 1163503 | BC9: =BC4+BC7 -> 1056630 | BD9: =SUM(AZ9:BC9) -> 3823696 | BE9: =BE4+BE7 -> 1003732 | BF9: =BF4+BF7 -> 1182019 | BG9: =BG4+BG7 -> 1288339 | BH9: =BH4+BH7 -> 1316743 | BI9: =SUM(BE9:BH9) -> 4790833 | BJ9: =BJ4+BJ7 -> 1231652 | BK9: =BK4+BK7 -> 1250083 | BL9: =BL4+BL7 -> 1559644 | BM9: =BM4+BM7 -> 1370916 | BN9: =SUM(BJ9:BM9) -> 5412295 | BO9: =BO4+BO7 -> 1283426 | BP9: =BP4+BP7 -> 1633055 | BQ9: =BQ4+BQ7 -> 1625987 | BR9: =BR4+BR7 -> 1710231 | BS9: =SUM(BO9:BR9) -> 6252699 | BT9: =BT4+BT7 -> 1572911 | BU9: =BU4+BU7 -> 1856857 | BV9: =BV4+BV7 -> 2029651 | BW9: =BW4+BW7 -> 2506269 | BX9: =SUM(BT9:BW9) -> 7965688 | BY9: =BY4+BY7 -> 1952744 | BZ9: =BZ4+BZ7 -> 2107130 | CA9: =CA4+CA7 -> 2128446 | CB9: =CB4+CB7 -> 3235174 | CC9: =SUM(BY9:CB9) -> 9423494 | CD9: =CD4+CD7 -> 2025033 | CE9: =CE4+CE7 -> 2480871 | CF9: =CF4+CF7 -> 2657052.9 | CG9: =CG4+CG7 -> 2860137 | CH9: =SUM(CD9:CG9) -> 10023094 | CI9: =CI4+CI7 -> 2694798.7 | CJ9: =CJ4+CJ7 -> 2747298.1 | CK9: =CK4+CK7 -> 2886899.8 | CL9: =CL4+CL7 -> 3044761.9 | CM9: =SUM(CI9:CL9) -> 11373758 | CN9: =CN4+CN7 -> 3029026 | CO9: =CO4+CO7 -> 3062946.9 | CP9: =CP4+CP7 -> 3188256.7 | CQ9: =CQ4+CQ7 -> 3403320.4 | CR9: =SUM(CN9:CQ9) -> 12683550 | CS9: =CS4+CS7 -> 3320652.2 | CT9: =CT4+CT7 -> 3337818.6 | CU9: =CU4+CU7 -> 3451911.1 | CV9: =CV4+CV7 -> 3663365.7 | CW9: =SUM(CS9:CV9) -> 13773748 | CX9: =CX4+CX7 -> 3573478.6 | CY9: =CY4+CY7 -> 3581279.1 | CZ9: =CZ4+CZ7 -> 3693712.8 | DA9: =DA4+DA7 -> 3905627.5 | DB9: =SUM(CX9:DA9) -> 14754098
A10: Operating Costs | B10: =B11+B13+B14 -> -737831 | C10: =C11+C13+C14 -> -812794 | D10: =D11+D13+D14 -> -753585 | E10: =E11+E13+E14 -> -1049265 | F10: =SUM(B10:E10) -> -3353475 | G10: =G11+G13+G14 -> -872029 | H10: =H11+H13+H14 -> -1000388 | I10: =I11+I13+I14 -> -1113641 | J10: =J11+J13+J14 -> -1407233 | K10: =SUM(G10:J10) -> -4393291 | L10: =L11+L13+L14 -> -1006468 | M10: =M11+M13+M14 -> -973692 | N10: =N11+N13+N14 -> -921666 | O10: =O11+O13+O14 -> -912041 | P10: =SUM(L10:O10) -> -3813867 | Q10: =Q11+Q13+Q14 -> -818350 | R10: =R11+R13+R14 -> -924645 | S10: =S11+S13+S14 -> -937198 | T10: =T11+T13+T14 -> -932400 | U10: =SUM(Q10:T10) -> -3612593 | V10: =V11+V13+V14 -> -877707 | W10: =W11+W13+W14 -> -904779 | X10: =X11+X13+X14 -> -1130965 | Y10: =Y11+Y13+Y14 -> -1035730 | Z10: =SUM(V10:Y10) -> -3949181 | AA10: =AA11+AA13+AA14 -> -674603 | AB10: =AB11+AB13+AB14 -> -738627 | AC10: =AC11+AC13+AC14 -> -743219 | AD10: =AD11+AD13+AD14 -> -681656 | AE10: =SUM(AA10:AD10) -> -2838105 | AF10: =AF11+AF13+AF14 -> -528445 | AG10: =AG11+AG13+AG14 -> -387103 | AH10: =AH11+AH13+AH14 -> -563386 | AI10: =AI11+AI13+AI14 -> -653853 | AJ10: =SUM(AF10:AI10) -> -2132787 | AK10: =AK11+AK13+AK14 -> -477370 | AL10: =AL11+AL13+AL14 -> -421167 | AM10: =AM11+AM13+AM14 -> -450495 | AN10: =AN11+AN13+AN14 -> -590225 | AO10: =SUM(AK10:AN10) -> -1939257 | AP10: =AP11+AP13+AP14 -> -325839 | AQ10: =AQ11+AQ13+AQ14 -> -468242 | AR10: =AR11+AR13+AR14 -> -520049 | AS10: =AS11+AS13+AS14 -> -763100 | AT10: =SUM(AP10:AS10) -> -2077230 | AU10: =AU11+AU13+AU14 -> -577347 | AV10: =AV11+AV13+AV14 -> -643662 | AW10: =AW11+AW13+AW14 -> -645832 | AX10: =AX11+AX13+AX14 -> -848268 | AY10: =SUM(AU10:AX10) -> -2715109 | AZ10: =AZ11+AZ13+AZ14 -> -503900 | BA10: =BA11+BA13+BA14 -> -563937 | BB10: =BB11+BB13+BB14 -> -784922 | BC10: =BC11+BC13+BC14 -> -720554 | BD10: =SUM(AZ10:BC10) -> -2573313 | BE10: =BE11+BE13+BE14 -> -657192 | BF10: =BF11+BF13+BF14 -> -749735 | BG10: =BG11+BG13+BG14 -> -841443 | BH10: =BH11+BH13+BH14 -> -876643 | BI10: =SUM(BE10:BH10) -> -3125013 | BJ10: =BJ11+BJ13+BJ14 -> -848102 | BK10: =BK11+BK13+BK14 -> -858752 | BL10: =BL11+BL13+BL14 -> -1031260 | BM10: =BM11+BM13+BM14 -> -940219 | BN10: =SUM(BJ10:BM10) -> -3678333 | BO10: =BO11+BO13+BO14 -> -888959 | BP10: =BP11+BP13+BP14 -> -1105967 | BQ10: =BQ11+BQ13+BQ14 -> -1080523 | BR10: =BR11+BR13+BR14 -> -1133651 | BS10: =SUM(BO10:BR10) -> -4209100 | BT10: =BT11+BT13+BT14 -> -1079389 | BU10: =BU11+BU13+BU14 -> -1246830 | BV10: =BV11+BV13+BV14 -> -1353486 | BW10: =BW11+BW13+BW14 -> -1706118 | BX10: =SUM(BT10:BW10) -> -5385823 | BY10: =BY11+BY13+BY14 -> -1318405 | BZ10: =BZ11+BZ13+BZ14 -> -1417294 | CA10: =CA11+CA13+CA14 -> -1426032 | CB10: =CB11+CB13+CB14 -> -2191794 | CC10: =SUM(BY10:CB10) -> -6353525 | CD10: =CD11+CD13+CD14 -> -1359107 | CE10: =CE11+CE13+CE14 -> -1627952 | CF10: =CF11+CF13+CF14 -> -1759307.7 | CG10: =CG11+CG13+CG14 -> -1894204.9 | CH10: =SUM(CD10:CG10) -> -6640571.6 | CI10: =CI11+CI13+CI14 -> -1774990.7 | CJ10: =CJ11+CJ13+CJ14 -> -1812335.4 | CK10: =CK11+CK13+CK14 -> -1907188.7 | CL10: =CL11+CL13+CL14 -> -2013734.1 | CM10: =SUM(CI10:CL10) -> -7508248.8 | CN10: =CN11+CN13+CN14 -> -2000760.8 | CO10: =CO11+CO13+CO14 -> -2025161 | CP10: =CP11+CP13+CP14 -> -2111089.2 | CQ10: =CQ11+CQ13+CQ14 -> -2258153.8 | CR10: =SUM(CN10:CQ10) -> -8395164.8 | CS10: =CS11+CS13+CS14 -> -2203657.9 | CT10: =CT11+CT13+CT14 -> -2214817.1 | CU10: =CU11+CU13+CU14 -> -2291616.2 | CV10: =CV11+CV13+CV14 -> -2435550 | CW10: =SUM(CS10:CV10) -> -9145641.2 | CX10: =CX11+CX13+CX14 -> -2372527.5 | CY10: =CY11+CY13+CY14 -> -2377266.4 | CZ10: =CZ11+CZ13+CZ14 -> -2452929.4 | DA10: =DA11+DA13+DA14 -> -2597143 | DB10: =SUM(CX10:DA10) -> -9799866.2
A11: Development costs | B11: =-720668-8588-B13 -> -719706 | C11: =-788554-11417-C13 -> -780649 | D11: =-733569-6811-D13 -> -723289 | E11: =-1022857-6899-E13 -> -979524 | F11: =SUM(B11:E11) -> -3203168 | G11: =-872029-G13-G14 -> -814297 | H11: =-1822675-11542-G11-G13-H13 -> -938469 | I11: =-2913877-14933-G11-H11-G13-H13-I13 -> -1033848 | J11: =-4307266-23111-G11-H11-I11-SUM(G13:J13) -> -1351567 | K11: =SUM(G11:J11) -> -4138181 | L11: =-1948429-2281-M11-L13-M13 -> -953589 | M11: =-954640-1681-M13 -> -920832 | N11: =-921666-N13-N14 -> -869668 | O11: =-3752076-7039-L11-M11-N11-SUM(L13:O13) -> -836719 | P11: =SUM(L11:O11) -> -3580808 | Q11: =-1706950-9638-R11-Q13-R13 -> -776189 | R11: =-906964-3456-R13 -> -878136 | S11: =-937198-S13-S14 -> -872421 | T11: =-3612593-SUM(Q11:S11)-SUM(Q13:T13)-SUM(Q14:T14) -> -840276 | U11: =SUM(Q11:T11) -> -3367022 | V11: =-860370-6154-V13 -> -817972 | W11: =-888975-5318-W13 -> -841556 | X11: =-1130965-X13-X14 -> -1065415 | Y11: =-3949181-SUM(V11:X11)-SUM(V13:Y13)-SUM(V14:Y14) -> -971255 | Z11: =SUM(V11:Y11) -> -3696198 | AA11: =-649099-14345-AA13 -> -619379 | AB11: =-723129-8237-AB13 -> -690531 | AC11: =-743219-AC13-AC14 -> -693061 | AD11: =-2838105-SUM(AA11:AC11)-SUM(AA13:AD13)-SUM(AA14:AD14) -> -628303 | AE11: =SUM(AA11:AD11) -> -2631274 | AF11: =-508878-8982-AF13 -> -467503 | AG11: =-355863-9166-AG13 -> -316982 | AH11: =-563386-AH13-AH14 -> -501053 | AI11: =-2132787-SUM(AF11:AH11)-SUM(AF13:AI13)-SUM(AF14:AI14) -> -599914 | AJ11: =SUM(AF11:AI11) -> -1885452 | AK11: =-463095-6748-AK13 -> -424962 | AL11: =-410665-7135-AL13 -> -369701 | AM11: =-450495-AM13-AM14 -> -407556 | AN11: =-1939257-SUM(AK11:AM11)-SUM(AK13:AN13)-SUM(AK14:AN14) -> -545529 | AO11: =SUM(AK11:AN11) -> -1747748 | AP11: =-317073-6374-AP13 -> -297842 | AQ11: =-458811-5796-AQ13 -> -435627 | AR11: =-520049-AR13-AR14 -> -481284 | AS11: =-2311230-SUM(AP11:AR11)-SUM(AP13:AS13)-SUM(AP14:AS14)+167000+67000 -> -735041 | AT11: =SUM(AP11:AS11) -> -1949794 | AU11: =-577017-6070+10468-AU13 -> -548776 | AV11: =-643682-5751+8996-AV13 -> -622178 | AW11: =-608648-5030-30212-AW13 -> -623728 | AX11: =-2715109-SUM(AU11:AW11)-SUM(AU13:AX13)-SUM(AU14:AX14) -> -823979 | AY11: =SUM(AU11:AX11) -> -2618661 | AZ11: =-469844-5517-24451-AZ13 -> -488169 | BA11: =-535625-2042-12517-BA13 -> -533358 | BB11: =-756657-13129-6433-BB13 -> -757962 | BC11: =-2573313-SUM(AZ11:BB11)-SUM(AZ13:BC13)-SUM(AZ14:BC14) -> -690696 | BD11: =SUM(AZ11:BC11) -> -2470185 | BE11: =-668863-8491+32132-BE13 -> -636211 | BF11: =-729733-9928+5283-BF13 -> -724002 | BG11: =-812566-4618-2520-BG13 -> -808109 | BH11: =-3125013-SUM(BE11:BG11)-SUM(BE13:BH13)-SUM(BE14:BH14) -> -846902 | BI11: =SUM(BE11:BH11) -> -3015224 | BJ11: =-852833-1569+23103-BJ13 -> -815032 | BK11: =-815979-3365-16232-BK13 -> -816065 | BL11: =-1002666-736-5819-BL13 -> -986430 | BM11: =-3678333-SUM(BJ11:BL11)-SUM(BJ13:BM13)-SUM(BJ14:BM14) -> -902868 | BN11: =SUM(BJ11:BM11) -> -3520395 | BO11: =-888554-284+9962-BO13 -> -854201 | BP11: =-1979270-547+1850-SUM(BO13:BP13)-BO11 -> -1068710 | BQ11: =-3045353-843-8169-SUM(BO13:BQ13)-SUM(BO11:BP11) -> -1046397 | BR11: =-4209100-SUM(BO11:BQ11)-SUM(BO13:BR13)-SUM(BO14:BR14) -> -1097346 | BS11: =SUM(BO11:BR11) -> -4066654 | BT11: =-1099469-734+32389-BT13 -> -1040695 | BU11: =-2326156-841+20515-SUM(BT13:BU13)-BT11 -> -1203470 | BV11: =-3680152-480+29360-SUM(BT13:BV13)-SUM(BT11:BU11) -> -1308936 | BW11: =-5385823-SUM(BT11:BV11)-SUM(BT13:BW13)-SUM(BT14:BW14) -> -1662991 | BX11: =SUM(BT11:BW11) -> -5216092 | BY11: =-1371838+103+63476-BY13 -> -1271764 | BZ11: =-2741584+532+19610-SUM(BY13:BZ13)-BY11 -> -1367612 | CA11: =-4073434-55402-13316-BZ11-BY11-CA13-BZ13-BY13 -> -1372087 | CB11: =-6353525-SUM(BY11:CA11)-SUM(BY13:CB13)-SUM(BY14:CB14) -> -2141389 | CC11: =SUM(BY11:CB11) -> -6152852 | CD11: =-1387597-7626+43725-CD13 -> -1286258 | CE11: =-2996523-10945+35263-SUM(CD13:CE13)-CD11 -> -1547952 | CF11: =-(1-CF12)*CF5 -> -1705336.8 | CG11: =-(1-CG12)*CG5 -> -1834948 | CH11: =SUM(CD11:CG11) -> -6374494.8 | CI11: =-(1-CI12)*CI5 -> -1726783.4 | CJ11: =-(1-CJ12)*CJ5 -> -1760741.4 | CK11: =-(1-CK12)*CK5 -> -1850633.8 | CL11: =-(1-CL12)*CL5 -> -1952239.7 | CM11: =SUM(CI11:CL11) -> -7290398.2 | CN11: =-(1-CN12)*CN5 -> -1948356.2 | CO11: =-(1-CO12)*CO5 -> -1971094.2 | CP11: =-(1-CP12)*CP5 -> -2052949.2 | CQ11: =-(1-CQ12)*CQ5 -> -2192848.5 | CR11: =SUM(CN11:CQ11) -> -8165248 | CS11: =-(1-CS12)*CS5 -> -2140428.7 | CT11: =-(1-CT12)*CT5 -> -2152106.9 | CU11: =-(1-CU12)*CU5 -> -2226492.9 | CV11: =-(1-CV12)*CV5 -> -2363859.1 | CW11: =SUM(CS11:CV11) -> -8882887.5 | CX11: =-(1-CX12)*CX5 -> -2306141.8 | CY11: =-(1-CY12)*CY5 -> -2311656.5 | CZ11: =-(1-CZ12)*CZ5 -> -2384865.1 | DA11: =-(1-DA12)*DA5 -> -2522426.7 | DB11: =SUM(CX11:DA11) -> -9525090.1
A12: Development gross margin (%) | B12: =(1+B11/B5) -> 0.37883928 | C12: =(1+C11/C5) -> 0.35928191 | D12: =(1+D11/D5) -> 0.38995335 | E12: =(1+E11/E5) -> 0.30720559 | F12: =(1+F11/F5) -> 0.35634728 | G12: =(1+G11/G5) -> 0.33569671 | H12: =(1+H11/H5) -> 0.3355713 | I12: =(1+I11/I5) -> 0.34851175 | ... CE12: =(1+CE11/CE5) -> 0.38195221 | CF12: =(IS!CF118*Operating!CF37+IS!CE110*Operating!CF39)/Operating!CF35 -> 0.36315214 | CG12: =(IS!CG118*Operating!CG37+IS!CF110*Operating!CG39)/Operating!CG35 -> 0.36340584 | CH12: =(1+CH11/CH5) -> 0.36979105 | CI12: =(IS!CI118*Operating!CI37+IS!CH110*Operating!CI39)/Operating!CI35 -> 0.36143655 | CJ12: =(IS!CJ118*Operating!CJ37+IS!CI110*Operating!CJ39)/Operating!CJ35 -> 0.36132149 | CK12: =(IS!CK118*Operating!CK37+IS!CJ110*Operating!CK39)/Operating!CK35 -> 0.36117589 | CL12: =(IS!CL118*Operating!CL37+IS!CK110*Operating!CL39)/Operating!CL35 -> 0.36104198 | CM12: =(1+CM11/CM5) -> 0.36123697 | CN12: =(IS!CN118*Operating!CN37+IS!CM110*Operating!CN39)/Operating!CN35 -> 0.35900024 | CO12: =(IS!CO118*Operating!CO37+IS!CN110*Operating!CO39)/Operating!CO35 -> 0.35870118 | CP12: =(IS!CP118*Operating!CP37+IS!CO110*Operating!CP39)/Operating!CP35 -> 0.35832158 | CQ12: =(IS!CQ118*Operating!CQ37+IS!CP110*Operating!CQ39)/Operating!CQ35 -> 0.35790646 | CR12: =(1+CR11/CR5) -> 0.35846394 | CS12: =(IS!CS118*Operating!CS37+IS!CR110*Operating!CS39)/Operating!CS35 -> 0.35765271 | CT12: =(IS!CT118*Operating!CT37+IS!CS110*Operating!CT39)/Operating!CT35 -> 0.35746968 | CU12: =(IS!CU118*Operating!CU37+IS!CT110*Operating!CU39)/Operating!CU35 -> 0.35723203 | CV12: =(IS!CV118*Operating!CV37+IS!CU110*Operating!CV39)/Operating!CV35 -> 0.35696616 | CW12: =(1+CW11/CW5) -> 0.35732033 | CX12: =(IS!CX118*Operating!CX37+IS!CW110*Operating!CX39)/Operating!CX35 -> 0.35688692 | CY12: =(IS!CY118*Operating!CY37+IS!CX110*Operating!CY39)/Operating!CY35 -> 0.35675318 | CZ12: =(IS!CZ118*Operating!CZ37+IS!CY110*Operating!CZ39)/Operating!CZ35 -> 0.35658199 | DA12: =(IS!DA118*Operating!DA37+IS!CZ110*Operating!DA39)/Operating!DA35 -> 0.35639373 | DB12: =(1+DB11/DB5) -> 0.35664756
A13: Capitalized interest expenses | B13: -9550 | C13: =-28872-B13 -> -19322 | D13: =-45963-C13-B13 -> -17091 | E13: =-96195-D13-C13-B13 -> -50232 | F13: =SUM(B13:E13) -> -96195 | G13: -39087 | H13: =-81451-G13 -> -42364 | I13: =-142196-G13-H13 -> -60745 | J13: -50000 | K13: =SUM(G13:J13) -> -192196 | L13: =-76289-M13 -> -40800 | M13: -35489 | N13: =-119322-L13-M13 -> -43033 | O13: =-178307-L13-M13-N13 -> -58985 | P13: =SUM(L13:O13) -> -178307 | Q13: -29979 | R13: =-62263-Q13 -> -32284 | S13: =-112043-Q13-R13 -> -49780 | T13: =-186376-SUM(Q13:S13) -> -74333 | U13: =SUM(Q13:T13) -> -186376 | V13: -48552 | W13: =-101289-V13 -> -52737 | X13: =-152526-V13-W13 -> -51237 | Y13: =-207728-SUM(V13:X13) -> -55202 | Z13: =SUM(V13:Y13) -> -207728 | AA13: -44065 | AB13: =-84900-AA13 -> -40835 | AC13: =-128001-AA13-AB13 -> -43101 | AD13: -43000 | AE13: =SUM(AA13:AD13) -> -171001 | AF13: -50357 | AG13: =-98404-AF13 -> -48047 | AH13: =-153560-AF13-AG13 -> -55156 | AI13: =-202752-SUM(AF13:AH13) -> -49192 | AJ13: =SUM(AF13:AI13) -> -202752 | AK13: -44881 | AL13: =-92980-AK13 -> -48099 | AM13: =-132347-AK13-AL13 -> -39367 | AN13: =-173966-SUM(AK13:AM13) -> -41619 | AO13: =SUM(AK13:AN13) -> -173966 | AP13: -25605 | AQ13: =-54585-AP13 -> -28980 | AR13: =-87467-AP13-AQ13 -> -32882 | AS13: -22250 | AT13: =SUM(AP13:AS13) -> -109717 | AU13: -23843 | AV13: =-42102-AU13 -> -18259 | AW13: =-62264-AU13-AV13 -> -20162 | AX13: =-81394-AW13-AV13-AU13 -> -19130 | AY13: =SUM(AU13:AX13) -> -81394 | AZ13: -11643 | BA13: =-28469-AZ13 -> -16826 | BB13: =-46726-AZ13-BA13 -> -18257 | BC13: =-67353-BB13-BA13-AZ13 -> -20627 | BD13: =SUM(AZ13:BC13) -> -67353 | BE13: -9011 | BF13: =-19387-BE13 -> -10376 | BG13: =-30982-BE13-BF13 -> -11595 | BH13: =-46249-BG13-BF13-BE13 -> -15267 | BI13: =SUM(BE13:BH13) -> -46249 | BJ13: -16267 | BK13: =-35778-BJ13 -> -19511 | BL13: =-58569-BJ13-BK13 -> -22791 | BM13: =-82014-BL13-BK13-BJ13 -> -23445 | BN13: =SUM(BJ13:BM13) -> -82014 | BO13: -24675 | BP13: =-55056-BO13 -> -30381 | BQ13: =-85057-BO13-BP13 -> -30001 | BR13: =-114687-BQ13-BP13-BO13 -> -29630 | BS13: =SUM(BO13:BR13) -> -114687 | BT13: -27119 | BU13: =-62317-BT13 -> -35198 | BV13: =-98171-BT13-BU13 -> -35854 | BW13: =-133989-BV13-BU13-BT13 -> -35818 | BX13: =SUM(BT13:BW13) -> -133989 | BY13: -36495 | BZ13: =-82066-BY13 -> -45571 | CA13: =-130689-BZ13-BY13 -> -48623 | CB13: =-178230-CA13-BZ13-BY13 -> -47541 | CC13: =SUM(BY13:CB13) -> -178230 | CD13: -65240 | CE13: =-137995-CD13 -> -72755 | CF13: =-('BS & FCF'!CE144/(Operating!CE26+Operating!CE27))*Operating!CF37-2%*Operating!CF39 -> -46224.914 | CG13: =-('BS & FCF'!CF144/(Operating!CF26+Operating!CF27))*Operating!CG37-2%*Operating!CG39 -> -50918.88 | CH13: =SUM(CD13:CG13) -> -235138.79 | CI13: =-('BS & FCF'!CH144/(Operating!CH26+Operating!CH27))*Operating!CI37-1.5%*Operating!CI39 -> -40384.913 | CJ13: =-('BS & FCF'!CI144/(Operating!CI26+Operating!CI27))*Operating!CJ37-1.5%*Operating!CJ39 -> -43619.307 | CK13: =-('BS & FCF'!CJ144/(Operating!CJ26+Operating!CJ27))*Operating!CK37-1.5%*Operating!CK39 -> -48174.93 | CL13: =-('BS & FCF'!CK144/(Operating!CK26+Operating!CK27))*Operating!CL37-1.5%*Operating!CL39 -> -52656.218 | CM13: =SUM(CI13:CL13) -> -184835.37 | CN13: =-('BS & FCF'!CM144/(Operating!CM26+Operating!CM27))*Operating!CN37-1%*Operating!CN39 -> -43612.154 | CO13: =-('BS & FCF'!CN144/(Operating!CN26+Operating!CN27))*Operating!CO37-1%*Operating!CO39 -> -45175.764 | CP13: =-('BS & FCF'!CO144/(Operating!CO26+Operating!CO27))*Operating!CP37-1%*Operating!CP39 -> -48885.282 | CQ13: =-('BS & FCF'!CP144/(Operating!CP26+Operating!CP27))*Operating!CQ37-1%*Operating!CQ39 -> -55426.339 | CR13: =SUM(CN13:CQ13) -> -193099.54 | CS13: =-('BS & FCF'!CR144/(Operating!CR26+Operating!CR27))*Operating!CS37-1%*Operating!CS39 -> -53590.166 | CT13: =-('BS & FCF'!CS144/(Operating!CS26+Operating!CS27))*Operating!CT37-1%*Operating!CT39 -> -53021.345 | CU13: =-('BS & FCF'!CT144/(Operating!CT26+Operating!CT27))*Operating!CU37-1%*Operating!CU39 -> -55103.295 | CV13: =-('BS & FCF'!CU144/(Operating!CU26+Operating!CU27))*Operating!CV37-1%*Operating!CV39 -> -61057.082 | CW13: =SUM(CS13:CV13) -> -222771.89 | CX13: =-('BS & FCF'!CW144/(Operating!CW26+Operating!CW27))*Operating!CX37-1%*Operating!CX39 -> -56012.706 | CY13: =-('BS & FCF'!CX144/(Operating!CX26+Operating!CX27))*Operating!CY37-1%*Operating!CY39 -> -55214.348 | CZ13: =-('BS & FCF'!CY144/(Operating!CY26+Operating!CY27))*Operating!CZ37-1%*Operating!CZ39 -> -57342.395 | DA13: =-('BS & FCF'!CZ144/(Operating!CZ26+Operating!CZ27))*Operating!DA37-1%*Operating!DA39 -> -63379.135 | DB13: =SUM(CX13:DA13) -> -231948.58
A14: Service costs | B14: -8575 | C14: -12823 | D14: -13205 | E14: -19509 | F14: =SUM(B14:E14) -> -54112 | G14: -18645 | H14: =-38200-G14 -> -19555 | I14: =-57248-G14-H14 -> -19048 | J14: =-62914-G14-H14-I14 -> -5666 | K14: =SUM(G14:J14) -> -62914 | L14: =-29450-M14 -> -12079 | M14: -17371 | N14: -8965 | O14: =-54752-L14-M14-N14 -> -16337 | P14: =SUM(L14:O14) -> -54752 | Q14: =-26407-R14 -> -12182 | R14: -14225 | S14: -14997 | T14: =-59195-SUM(Q14:S14) -> -17791 | U14: =SUM(Q14:T14) -> -59195 | V14: -11183 | W14: -10486 | X14: -14313 | Y14: =-45255-SUM(V14:X14) -> -9273 | Z14: =SUM(V14:Y14) -> -45255 | AA14: -11159 | AB14: -7261 | AC14: -7057 | AD14: =-35830-SUM(AA14:AC14) -> -10353 | AE14: =SUM(AA14:AD14) -> -35830 | AF14: -10585 | AG14: -22074 | AH14: -7177 | AI14: =-44583-SUM(AF14:AH14) -> -4747 | AJ14: =SUM(AF14:AI14) -> -44583 | AK14: -7527 | AL14: -3367 | AM14: -3572 | AN14: =-17543-SUM(AK14:AM14) -> -3077 | AO14: =SUM(AK14:AN14) -> -17543 | AP14: -2392 | AQ14: -3635 | AR14: -5883 | AS14: =-17719-SUM(AP14:AR14) -> -5809 | AT14: =SUM(AP14:AS14) -> -17719 | AU14: -4728 | AV14: -3225 | AW14: -1942 | AX14: =-15054-SUM(AU14:AW14) -> -5159 | AY14: =SUM(AU14:AX14) -> -15054 | AZ14: -4088 | BA14: -13753 | BB14: -8703 | BC14: =-35775-SUM(AZ14:BB14) -> -9231 | BD14: =SUM(AZ14:BC14) -> -35775 | BE14: -11970 | BF14: -15357 | BG14: -21739 | BH14: =-63540-SUM(BE14:BG14) -> -14474 | BI14: =SUM(BE14:BH14) -> -63540 | BJ14: -16803 | BK14: -23176 | BL14: -22039 | BM14: =-75924-SUM(BJ14:BL14) -> -13906 | BN14: =SUM(BJ14:BM14) -> -75924 | BO14: -10083 | BP14: =-16959-BO14 -> -6876 | BQ14: =-21084-SUM(BO14:BP14) -> -4125 | BR14: =-27759-SUM(BO14:BQ14) -> -6675 | BS14: =SUM(BO14:BR14) -> -27759 | BT14: -11575 | BU14: =-19737-BT14 -> -8162 | BV14: =-28433-SUM(BT14:BU14) -> -8696 | BW14: =-35742-SUM(BT14:BV14) -> -7309 | BX14: =SUM(BT14:BW14) -> -35742 | BY14: -10146 | BZ14: =-14257-BY14 -> -4111 | CA14: =-19579-BZ14-BY14 -> -5322 | CB14: =-22443-SUM(BY14:CA14) -> -2864 | CC14: =SUM(BY14:CB14) -> -22443 | CD14: -7609 | CE14: =-14854-CD14 -> -7245 | CF14: =-CF6*(1-CF15) -> -7745.999 | CG14: =-CG6*(1-CG15) -> -8338.0417 | CH14: =SUM(CD14:CG14) -> -30938.041 | CI14: =-CI6*(1-CI15) -> -7822.3414 | CJ14: =-CJ6*(1-CJ15) -> -7974.7343 | CK14: =-CK6*(1-CK15) -> -8379.964 | CL14: =-CL6*(1-CL15) -> -8838.1989 | CM14: =SUM(CI14:CL14) -> -33015.239 | CN14: =-CN6*(1-CN15) -> -8792.5215 | CO14: =-CO6*(1-CO15) -> -8890.9857 | CP14: =-CP6*(1-CP15) -> -9254.7294 | CQ14: =-CQ6*(1-CQ15) -> -9879.0067 | CR14: =SUM(CN14:CQ14) -> -36817.243 | CS14: =-CS6*(1-CS15) -> -9639.0409 | CT14: =-CT6*(1-CT15) -> -9688.8709 | CU14: =-CU6*(1-CU15) -> -10020.054 | CV14: =-CV6*(1-CV15) -> -10633.855 | CW14: =SUM(CS14:CV14) -> -39981.82 | CX14: =-CX6*(1-CX15) -> -10372.934 | CY14: =-CY6*(1-CY15) -> -10395.577 | CZ14: =-CZ6*(1-CZ15) -> -10721.945 | DA14: =-DA6*(1-DA15) -> -11337.081 | DB14: =SUM(CX14:DA14) -> -42827.537
A15: Services gross margin (%) | B15: =(1+B14/B6) -> 0.25577157 | C15: =(1+C14/C6) -> 0.20561269 | D15: =(1+D14/D6) -> 0.2627024 | E15: =(1+E14/E6) -> 0.37928731 | F15: =(1+F14/F6) -> 0.29728326 | G15: =(1+G14/G6) -> 0.19257752 | H15: =(1+H14/H6) -> 0.2388385 | I15: =(1+I14/I6) -> 0.41369121 | ... CE15: =(1+CE14/CE6) -> 0.83659983 | CF15: =CE15 -> 0.83659983 | CG15: =CF15 -> 0.83659983 | CH15: =(1+CH14/CH6) -> 0.82218847 | CI15: =CG15 -> 0.83659983 | CJ15: =CI15 -> 0.83659983 | CK15: =CJ15 -> 0.83659983 | CL15: =CK15 -> 0.83659983 | CM15: =(1+CM14/CM6) -> 0.83659983 | CN15: =CL15 -> 0.83659983 | CO15: =CN15 -> 0.83659983 | CP15: =CO15 -> 0.83659983 | CQ15: =CP15 -> 0.83659983 | CR15: =(1+CR14/CR6) -> 0.83659983 | CS15: =CQ15 -> 0.83659983 | CT15: =CS15 -> 0.83659983 | CU15: =CT15 -> 0.83659983 | CV15: =CU15 -> 0.83659983 | CW15: =(1+CW14/CW6) -> 0.83659983 | CX15: =CV15 -> 0.83659983 | CY15: =CX15 -> 0.83659983 | CZ15: =CY15 -> 0.83659983 | DA15: =CZ15 -> 0.83659983 | DB15: =(1+DB14/DB6) -> 0.83659983
A16: Gross profit | B16: =B9+B10 -> 394617 | C16: =C9+C10 -> 393041 | D16: =D9+D10 -> 408964 | E16: =E9+E10 -> 340008 | F16: =SUM(B16:E16) -> 1536630 | G16: =G9+G10 -> 328713 | H16: =H9+H10 -> 382496 | I16: =I9+I10 -> 445961 | J16: =J9+J10 -> 576320 | K16: =SUM(G16:J16) -> 1733490 | L16: =L9+L10 -> 459875 | M16: =M9+M10 -> 411571 | N16: =N9+N10 -> 428286 | O16: =O9+O10 -> 519080 | P16: =SUM(L16:O16) -> 1818812 | Q16: =Q9+Q10 -> 397020 | R16: =R9+R10 -> 447774 | S16: =S9+S10 -> 457250 | T16: =T9+T10 -> 457245 | U16: =SUM(Q16:T16) -> 1759289 | V16: =V9+V10 -> 437655 | W16: =W9+W10 -> 453552 | X16: =X9+X10 -> 482731 | Y16: =Y9+Y10 -> 494808 | Z16: =SUM(V16:Y16) -> 1868746 | AA16: =AA9+AA10 -> 360611 | AB16: =AB9+AB10 -> 399056 | AC16: =AC9+AC10 -> 394514 | AD16: =AD9+AD10 -> 348898 | AE16: =SUM(AA16:AD16) -> 1503079 | AF16: =AF9+AF10 -> 282261 | AG16: =AG9+AG10 -> 253930 | AH16: =AH9+AH10 -> 261421 | AI16: =AI9+AI10 -> 264911 | AJ16: =SUM(AF16:AI16) -> 1062523 | AK16: =AK9+AK10 -> 215017 | AL16: =AL9+AL10 -> 153589 | AM16: =AM9+AM10 -> 147332 | AN16: =AN9+AN10 -> 218575 | AO16: =SUM(AK16:AN16) -> 734513 | AP16: =AP9+AP10 -> 124783 | AQ16: =AQ9+AQ10 -> 171297 | AR16: =AR9+AR10 -> 204776 | AS16: =AS9+AS10 -> 314071 | AT16: =SUM(AP16:AS16) -> 814927 | AU16: =AU9+AU10 -> 248889 | AV16: =AV9+AV10 -> 292960 | AW16: =AW9+AW10 -> 288927 | AX16: =AX9+AX10 -> 384938 | AY16: =SUM(AU16:AX16) -> 1215714 | AZ16: =AZ9+AZ10 -> 260855 | BA16: =BA9+BA10 -> 274871 | BB16: =BB9+BB10 -> 378581 | BC16: =BC9+BC10 -> 336076 | BD16: =SUM(AZ16:BC16) -> 1250383 | BE16: =BE9+BE10 -> 346540 | BF16: =BF9+BF10 -> 432284 | BG16: =BG9+BG10 -> 446896 | BH16: =BH9+BH10 -> 440100 | BI16: =SUM(BE16:BH16) -> 1665820 | BJ16: =BJ9+BJ10 -> 383550 | BK16: =BK9+BK10 -> 391331 | BL16: =BL9+BL10 -> 528384 | BM16: =BM9+BM10 -> 430697 | BN16: =SUM(BJ16:BM16) -> 1733962 | BO16: =BO9+BO10 -> 394467 | BP16: =BP9+BP10 -> 527088 | BQ16: =BQ9+BQ10 -> 545464 | BR16: =BR9+BR10 -> 576580 | BS16: =SUM(BO16:BR16) -> 2043599 | BT16: =BT9+BT10 -> 493522 | BU16: =BU9+BU10 -> 610027 | BV16: =BV9+BV10 -> 676165 | BW16: =BW9+BW10 -> 800151 | BX16: =SUM(BT16:BW16) -> 2579865 | BY16: =BY9+BY10 -> 634339 | BZ16: =BZ9+BZ10 -> 689836 | CA16: =CA9+CA10 -> 702414 | CB16: =CB9+CB10 -> 1043380 | CC16: =SUM(BY16:CB16) -> 3069969 | CD16: =CD9+CD10 -> 665926 | CE16: =CE9+CE10 -> 852919 | CF16: =CF9+CF10 -> 897745.2 | CG16: =CG9+CG10 -> 965932.11 | CH16: =SUM(CD16:CG16) -> 3382522.3 | CI16: =CI9+CI10 -> 919808.04 | CJ16: =CJ9+CJ10 -> 934962.68 | CK16: =CK9+CK10 -> 979711.13 | CL16: =CL9+CL10 -> 1031027.8 | CM16: =SUM(CI16:CL16) -> 3865509.6 | CN16: =CN9+CN10 -> 1028265.2 | CO16: =CO9+CO10 -> 1037785.9 | CP16: =CP9+CP10 -> 1077167.5 | CQ16: =CQ9+CQ10 -> 1145166.6 | CR16: =SUM(CN16:CQ16) -> 4288385.3 | CS16: =CS9+CS10 -> 1116994.3 | CT16: =CT9+CT10 -> 1123001.5 | CU16: =CU9+CU10 -> 1160294.9 | CV16: =CV9+CV10 -> 1227815.7 | CW16: =SUM(CS16:CV16) -> 4628106.4 | CX16: =CX9+CX10 -> 1200951.2 | CY16: =CY9+CY10 -> 1204012.7 | CZ16: =CZ9+CZ10 -> 1240783.4 | DA16: =DA9+DA10 -> 1308484.5 | DB16: =SUM(CX16:DA16) -> 4954231.8
A17: Operating expenses | B17: =B18+B21+B23+B30+B34 -> -178833 | C17: =C18+C21+C23+C30+C34 -> -156810 | D17: =D18+D21+D23+D30+D34 -> -173217 | E17: =E18+E21+E23+E30+E34 -> -199860 | F17: =SUM(B17:E17) -> -708720 | G17: =G18+G21+G23+G30+G34 -> -196754 | H17: =H18+H21+H23+H30+H34 -> -228501 | I17: =I18+I21+I23+I30+I34 -> -221026 | J17: =J18+J21+J23+J30+J34 -> -306811 | K17: =SUM(G17:J17) -> -953092 | L17: =L18+L21+L23+L30+L34 -> -232954 | M17: =M18+M21+M23+M30+M34 -> -180102 | N17: =N18+N21+N23+N30+N34 -> -214192 | O17: =O18+O21+O23+O30+O34 -> -203195 | P17: =SUM(L17:O17) -> -830443 | Q17: =Q18+Q21+Q23+Q30+Q34 -> -161583 | R17: =R18+R21+R23+R30+R34 -> -189478 | S17: =S18+S21+S23+S30+S34 -> -196650 | T17: =T18+T21+T23+T30+T34 -> -187688 | U17: =SUM(Q17:T17) -> -735399 | V17: =V18+V21+V23+V30+V34 -> -209059 | W17: =W18+W21+W23+W30+W34 -> -202724 | X17: =X18+X21+X23+X30+X34 -> -222391 | Y17: =Y18+Y21+Y23+Y30+Y34 -> -258165 | Z17: =SUM(V17:Y17) -> -892339 | AA17: =AA18+AA21+AA23+AA30+AA34 -> -219357 | AB17: =AB18+AB21+AB23+AB30+AB34 -> -190079 | AC17: =AC18+AC21+AC23+AC30+AC34 -> -196105 | AD17: =AD18+AD21+AD23+AD30+AD34 -> -207134 | AE17: =SUM(AA17:AD17) -> -812675 | AF17: =AF18+AF21+AF23+AF30+AF34 -> -175144 | AG17: =AG18+AG21+AG23+AG30+AG34 -> -182593 | AH17: =AH18+AH21+AH23+AH30+AH34 -> -199948 | AI17: =AI18+AI21+AI23+AI30+AI34 -> -186495 | AJ17: =SUM(AF17:AI17) -> -744180 | AK17: =AK18+AK21+AK23+AK30+AK34 -> -165320 | AL17: =AL18+AL21+AL23+AL30+AL34 -> -273570 | AM17: =AM18+AM21+AM23+AM30+AM34 -> -118881 | AN17: =AN18+AN21+AN23+AN30+AN34 -> -122112 | AO17: =SUM(AK17:AN17) -> -679883 | AP17: =AP18+AP21+AP23+AP30+AP34 -> -147683 | AQ17: =AQ18+AQ21+AQ23+AQ30+AQ34 -> -176235 | AR17: =AR18+AR21+AR23+AR30+AR34 -> -283464 | AS17: =AS18+AS21+AS23+AS30+AS34 -> -132985 | AT17: =SUM(AP17:AS17) -> -740367 | AU17: =AU18+AU21+AU23+AU30+AU34 -> -169377 | AV17: =AV18+AV21+AV23+AV30+AV34 -> -131465 | AW17: =AW18+AW21+AW23+AW30+AW34 -> -145997 | AX17: =AX18+AX21+AX23+AX30+AX34 -> -148384 | AY17: =SUM(AU17:AX17) -> -595223 | AZ17: =AZ18+AZ21+AZ23+AZ30+AZ34 -> -195770 | BA17: =BA18+BA21+BA23+BA30+BA34 -> -165614 | BB17: =BB18+BB21+BB23+BB30+BB34 -> 1057582 | BC17: =BC18+BC21+BC23+BC30+BC34 -> -32202 | BD17: =SUM(AZ17:BC17) -> 663996 | BE17: =BE18+BE21+BE23+BE30+BE34 -> -120500 | BF17: =BF18+BF21+BF23+BF30+BF34 -> -120885 | BG17: =BG18+BG21+BG23+BG30+BG34 -> -154069 | BH17: =BH18+BH21+BH23+BH30+BH34 -> -164432 | BI17: =SUM(BE17:BH17) -> -559886 | BJ17: =BJ18+BJ21+BJ23+BJ30+BJ34 -> -186479 | BK17: =BK18+BK21+BK23+BK30+BK34 -> -199209 | BL17: =BL18+BL21+BL23+BL30+BL34 -> -186277 | BM17: =BM18+BM21+BM23+BM30+BM34 -> -180381 | BN17: =SUM(BJ17:BM17) -> -752346 | BO17: =BO18+BO21+BO23+BO30+BO34 -> -171430 | BP17: =BP18+BP21+BP23+BP30+BP34 -> -179239 | BQ17: =BQ18+BQ21+BQ23+BQ30+BQ34 -> -199818 | BR17: =BR18+BR21+BR23+BR30+BR34 -> -230901 | BS17: =SUM(BO17:BR17) -> -781388 | BT17: =BT18+BT21+BT23+BT30+BT34 -> -141678 | BU17: =BU18+BU21+BU23+BU30+BU34 -> -90783 | BV17: =BV18+BV21+BV23+BV30+BV34 -> -83457 | BW17: =BW18+BW21+BW23+BW30+BW34 -> -65465 | BX17: =SUM(BT17:BW17) -> -381383 | BY17: =BY18+BY21+BY23+BY30+BY34 -> -196376 | BZ17: =BZ18+BZ21+BZ23+BZ30+BZ34 -> -161100 | CA17: =CA18+CA21+CA23+CA30+CA34 -> 36389 | CB17: =CB18+CB21+CB23+CB30+CB34 -> -205022 | CC17: =SUM(BY17:CB17) -> -526109 | CD17: =CD18+CD21+CD23+CD30+CD34 -> -254645 | CE17: =CE18+CE21+CE23+CE30+CE34 -> -279186 | CF17: =CF18+CF21+CF23+CF30+CF34 -> -239923.32 | CG17: =CG18+CG21+CG23+CG30+CG34 -> -216697.38 | CH17: =SUM(CD17:CG17) -> -990451.7 | CI17: =CI18+CI21+CI23+CI30+CI34 -> -177121 | CJ17: =CJ18+CJ21+CJ23+CJ30+CJ34 -> -235967.21 | CK17: =CK18+CK21+CK23+CK30+CK34 -> -256236.37 | CL17: =CL18+CL21+CL23+CL30+CL34 -> -231962.64 | CM17: =SUM(CI17:CL17) -> -901287.21 | CN17: =CN18+CN21+CN23+CN30+CN34 -> -174573.79 | CO17: =CO18+CO21+CO23+CO30+CO34 -> -247897.03 | CP17: =CP18+CP21+CP23+CP30+CP34 -> -282346.99 | CQ17: =CQ18+CQ21+CQ23+CQ30+CQ34 -> -275015.97 | CR17: =SUM(CN17:CQ17) -> -979833.78 | CS17: =CS18+CS21+CS23+CS30+CS34 -> -198802.48 | CT17: =CT18+CT21+CT23+CT30+CT34 -> -273823.59 | CU17: =CU18+CU21+CU23+CU30+CU34 -> -304611.87 | CV17: =CV18+CV21+CV23+CV30+CV34 -> -299734.86 | CW17: =SUM(CS17:CV17) -> -1076972.8 | CX17: =CX18+CX21+CX23+CX30+CX34 -> -197644.85 | CY17: =CY18+CY21+CY23+CY30+CY34 -> -280386.18 | CZ17: =CZ18+CZ21+CZ23+CZ30+CZ34 -> -307742.21 | DA17: =DA18+DA21+DA23+DA30+DA34 -> -296732.49 | DB17: =SUM(CX17:DA17) -> -1082505.7
A18: Selling expenses | B18: -94188 | C18: -103019 | D18: -103927 | E18: -100686 | F18: =SUM(B18:E18) -> -401820 | G18: -112616 | H18: =-255554-G18 -> -142938 | I18: =-377323-G18-H18 -> -121769 | J18: =-511246-G18-H18-I18 -> -133923 | K18: =SUM(G18:J18) -> -511246 | L18: =-219037-M18 -> -109229 | M18: -109808 | N18: -110247 | O18: =-457139-L18-M18-N18 -> -127855 | P18: =SUM(L18:O18) -> -457139 | Q18: =-195945-R18 -> -92544 | R18: -103401 | S18: -113426 | T18: =-431373-SUM(Q18:S18) -> -122002 | U18: =SUM(Q18:T18) -> -431373 | V18: -105875 | W18: -110796 | X18: -118305 | Y18: =-466628-SUM(V18:X18) -> -131652 | Z18: =SUM(V18:Y18) -> -466628 | AA18: -107499 | AB18: -114777 | AC18: -119917 | AD18: =-459538-SUM(AA18:AC18) -> -117345 | AE18: =SUM(AA18:AD18) -> -459538 | AF18: -102376 | AG18: -94828 | AH18: -101971 | AI18: =-400579-SUM(AF18:AH18) -> -101404 | AJ18: =SUM(AF18:AI18) -> -400579 | AK18: -87376 | AL18: -87704 | AM18: -88456 | AN18: =-343283-SUM(AK18:AM18) -> -79747 | AO18: =SUM(AK18:AN18) -> -343283 | AP18: -73073 | AQ18: -84139 | AR18: -87973 | AS18: =-332795-SUM(AP18:AR18) -> -87610 | AT18: =SUM(AP18:AS18) -> -332795 | AU18: -87514 | AV18: -98449 | AW18: -95474 | AX18: =-382005-SUM(AU18:AW18) -> -100568 | AY18: =SUM(AU18:AX18) -> -382005 | AZ18: -90755 | BA18: -89321 | BB18: -71523 | BC18: =-326318-SUM(AZ18:BB18) -> -74719 | BD18: =SUM(AZ18:BC18) -> -326318 | BE18: -70578 | BF18: -75141 | BG18: -94562 | BH18: =-347846-SUM(BE18:BG18) -> -107565 | BI18: =SUM(BE18:BH18) -> -347846 | BJ18: -97954 | BK18: -108144 | BL18: -152389 | BM18: =-514969-SUM(BJ18:BL18) -> -156482 | BN18: =SUM(BJ18:BM18) -> -514969 | BO18: -142049 | BP18: -155437 | BQ18: -155053 | BR18: =-628585-SUM(BO18:BQ18) -> -176046 | BS18: =SUM(BO18:BR18) -> -628585 | BT18: -153798 | BU18: -147794 | BV18: -170109 | BW18: =-659284-SUM(BT18:BV18) -> -187583 | BX18: =SUM(BT18:BW18) -> -659284 | BY18: -200780 | BZ18: -225655 | CA18: -237709 | CB18: =-938220-SUM(BY18:CA18) -> -274076 | CC18: =SUM(BY18:CB18) -> -938220 | CD18: -276768 | CE18: -293757 | CF18: =-CF20*(Operating!CF15+Operating!CF17) -> -270429.69 | CG18: =-CG20*(Operating!CG15+Operating!CG17) -> -285969.01 | CH18: =SUM(CD18:CG18) -> -1126923.7 | CI18: =-CI20*(Operating!CI15+Operating!CI17) -> -275710.84 | CJ18: =-CJ20*(Operating!CJ15+Operating!CJ17) -> -279195.59 | CK18: =-CK20*(Operating!CK15+Operating!CK17) -> -300964.49 | CL18: =-CL20*(Operating!CL15+Operating!CL17) -> -315326.89 | CM18: =SUM(CI18:CL18) -> -1171197.8 | CN18: =-CN20*(Operating!CN15+Operating!CN17) -> -286839.33 | CO18: =-CO20*(Operating!CO15+Operating!CO17) -> -302528.99 | CP18: =-CP20*(Operating!CP15+Operating!CP17) -> -325416.41 | CQ18: =-CQ20*(Operating!CQ15+Operating!CQ17) -> -360445.14 | CR18: =SUM(CN18:CQ18) -> -1275229.9 | CS18: =-CS20*(Operating!CS15+Operating!CS17) -> -307495.44 | CT18: =-CT20*(Operating!CT15+Operating!CT17) -> -322259.34 | CU18: =-CU20*(Operating!CU15+Operating!CU17) -> -345289.24 | CV18: =-CV20*(Operating!CV15+Operating!CV17) -> -381401.39 | CW18: =SUM(CS18:CV18) -> -1356445.4 | CX18: =-CX20*(Operating!CX15+Operating!CX17) -> -313583.08 | CY18: =-CY20*(Operating!CY15+Operating!CY17) -> -330767.09 | CZ18: =-CZ20*(Operating!CZ15+Operating!CZ17) -> -356089.49 | DA18: =-DA20*(Operating!DA15+Operating!DA17) -> -394575.27 | DB18: =SUM(CX18:DA18) -> -1395014.9
A19: % of net revenues | B19: =-B18/B9 -> 0.083172031 | C19: =-C18/C9 -> 0.085433745 | D19: =-D18/D9 -> 0.089395802 | E19: =-E18/E9 -> 0.072473877 | F19: =-F18/F9 -> 0.082170015 | G19: =-G18/G9 -> 0.093788674 | H19: =-H18/H9 -> 0.10336225 | I19: =-I18/I9 -> 0.078076971 | ... DB19: =-DB18/DB9 -> 0.094551014
A20: % of net sales | B20: =-B18/Operating!B9 -> 0.088377066 | C20: =-C18/Operating!C9 -> 0.066899728 | D20: =-D18/Operating!D9 -> 0.10135567 | E20: =-E18/Operating!E9 -> 0.039618547 | F20: =-F18/Operating!F9 -> 0.065099389 | G20: =-G18/Operating!G9 -> 0.11277108 | H20: =-H18/Operating!H9 -> 0.085692493 | I20: =-I18/Operating!I9 -> 0.084053149 | ... K20: =-K18/Operating!K9 -> 0.078688338 | L20: =-L18/(Operating!L15+Operating!L17) -> 0.080922257 | M20: =-M18/(Operating!M15+Operating!M17) -> 0.07679691 | N20: =-N18/(Operating!N15+Operating!N17) -> 0.059099441 | O20: =-O18/(Operating!O15+Operating!O17) -> 0.070075076 | P20: =-P18/(Operating!P15+Operating!P17) -> 0.070659075 | Q20: =-Q18/(Operating!Q15+Operating!Q17) -> 0.062985015 | R20: =-R18/(Operating!R15+Operating!R17) -> 0.04501089 | S20: =-S18/(Operating!S15+Operating!S17) -> 0.07615583 | ... CE20: =-CE18/(Operating!CE15+Operating!CE17) -> 0.071875948 | CF20: 0.065 | CG20: 0.065 | CH20: =-CH18/(Operating!CH15+Operating!CH17) -> 0.070021443 | CI20: 0.065 | CJ20: =CI20 -> 0.065 | CK20: =CJ20 -> 0.065 | CL20: =CK20 -> 0.065 | CM20: =-CM18/(Operating!CM15+Operating!CM17) -> 0.065 | CN20: 0.065 | CO20: =CN20 -> 0.065 | CP20: =CO20 -> 0.065 | CQ20: =CP20 -> 0.065 | CR20: =-CR18/(Operating!CR15+Operating!CR17) -> 0.065 | CS20: =CN20 -> 0.065 | CT20: =CO20 -> 0.065 | CU20: =CP20 -> 0.065 | CV20: =CQ20 -> 0.065 | CW20: =-CW18/(Operating!CW15+Operating!CW17) -> 0.065 | CX20: =CS20 -> 0.065 | CY20: =CT20 -> 0.065 | CZ20: =CU20 -> 0.065 | DA20: =CV20 -> 0.065 | DB20: =-DB18/(Operating!DB15+Operating!DB17) -> 0.065
A21: G&A expenses | B21: =-73166-1227-B32 -> -56073 | C21: =-73035-1331-C32 -> -63450 | D21: =-79447-1247-D32 -> -69372 | E21: =-108018-1385-E32 -> -90428 | F21: =SUM(B21:E21) -> -279323 | G21: =-83303-1930-G32 -> -81847 | H21: =-101579-1927-H32 -> -99975 | I21: =-102443-I32 -> -96569 | J21: =-404033-G21-H21-I21-SUM(G32:J32) -> -112306 | K21: =SUM(G21:J21) -> -390697 | L21: =-229623-3571-L32-M21-M32-L33 -> -107149 | M21: =-103506-1632-M32 -> -98867 | N21: =-89636-N32-2518 -> -89846 | O21: =-397452-L21-M21-N21-SUM(L32:O32) -> -83181 | P21: =SUM(L21:O21) -> -379043 | Q21: =-186579-3351-Q32-R21-R32 -> -84934 | R21: =-97252-1586-R32 -> -94225 | S21: =-98777-S32-1590 -> -98089 | T21: =-401077-SUM(Q21:S21)-SUM(Q32:T32) -> -104248 | U21: =SUM(Q21:T21) -> -381496 | V21: =-105462-1375-V32 -> -102174 | W21: =-114861-1552-W32 -> -110181 | X21: =-114766-X32-1725 -> -111149 | Y21: =-467317-SUM(V21:X21)-SUM(V32:Y32) -> -122209 | Z21: =SUM(V21:Y21) -> -445713 | AA21: =-103807-1725-AA32 -> -101107 | AB21: =-88399-1754-AB32 -> -84496 | AC21: =-113883-AC32-1702 -> -110889 | AD21: =-412408-SUM(AA21:AC21)-SUM(AA32:AD32) -> -94312 | AE21: =SUM(AA21:AD21) -> -390804 | AF21: =-93379-1721-AF32 -> -88100 | AG21: =-113954-AG32-1564 -> -107828 | AH21: =-111709-AH32-1684 -> -102140 | AI21: =-438601-SUM(AF21:AH21)-SUM(AF32:AI32) -> -83590 | AJ21: =SUM(AF21:AI21) -> -381658 | AK21: =-98009-1501-AK32 -> -78168 | AL21: =-102822-AL32-1517 -> -75678 | AM21: =-92934-AM32-1441 -> -83500 | AN21: =-391470-5761-SUM(AK21:AM21)-SUM(AK32:AN32) -> -93350 | AO21: =SUM(AK21:AN21) -> -330696 | AP21: =-97415-1299-AP32 -> -82847 | AQ21: =-82780-AQ32-1327 -> -74523 | AR21: =-93939-AR32-1342 -> -84406 | AS21: =-364737-5261-SUM(AP21:AR21)-SUM(AP32:AS32) -> -66853 | AT21: =SUM(AP21:AS21) -> -308629 | AU21: =-78164-1268-AU32 -> -55073 | AV21: =-94502-AV32-1268 -> -103651 | AW21: =-103322-AW32-1260 -> -73044 | AX21: =-388305-5050-SUM(AU21:AW21)-SUM(AU32:AX32) -> -86909 | AY21: =SUM(AU21:AX21) -> -318677 | AZ21: =-94234-1568-AZ32 -> -78603 | BA21: =-95740-1458-BA32 -> -83473 | BB21: =-93025-BB32 -> -84062 | BC21: =-384720-5957-SUM(AZ21:BB21)-SUM(AZ32:BC32) -> -93376 | BD21: =SUM(AZ21:BC21) -> -339514 | BE21: =-118255-1332-BE32 -> -108655 | BF21: =-125166-BF32 -> -114704 | BG21: =-122372-BG32 -> -111352 | BH21: =-501453-SUM(BE21:BG21)-SUM(BE32:BH32) -> -126719 | BI21: =SUM(BE21:BH21) -> -461430 | BJ21: =-134623-1618-BJ32 -> -127709 | BK21: =-142746-BK32 -> -133495 | BL21: =-151238-BL32 -> -128406 | BM21: =-554805-SUM(BJ21:BL21)-SUM(BJ32:BM32) -> -121721 | BN21: =SUM(BJ21:BM21) -> -511331 | BO21: =-111939-1826-BO32 -> -84481 | BP21: =-118608-BP32 -> -102537 | BQ21: =-150553-BQ32 -> -108251 | BR21: =-517647-SUM(BO21:BQ21)-SUM(BO32:BR32) -> -155290 | BS21: =SUM(BO21:BR21) -> -450559 | BT21: =-105049-1827-BT32 -> -83238 | BU21: =-110024-BU32 -> -93659 | BV21: =-125048-BV32 -> -85049 | BW21: =-462436-SUM(BT21:BV21)-SUM(BT32:BW32) -> -100431 | BX21: =SUM(BT21:BW21) -> -362377 | BY21: =-124568-2139-BY32 -> -96435 | BZ21: =-126946-BZ32 -> -103144 | CA21: =-131713-CA32 -> -103084 | CB21: =-524921-SUM(BY21:CA21)-SUM(BY32:CB32) -> -89683 | CC21: =SUM(BY21:CB21) -> -392346 | CD21: =-131579-2266-CD32 -> -79262 | CE21: =-134332-CE32 -> -93166 | CF21: =CA21*(1+Macro!CF11)*1.05 -> -112079.5 | CG21: =CB21*(1+Macro!CG11)*1.05 -> -97569.641 | CH21: =SUM(CD21:CG21) -> -382077.14 | CI21: =CD21*(1+Macro!CI11)*1.1 -> -90614.409 | CJ21: =CE21*(1+Macro!CJ11)*1.1 -> -106641.19 | CK21: =CF21*(1+Macro!CK11)*1.1 -> -127942.33 | CL21: =CG21*(1+Macro!CL11)*1.1 -> -111555.52 | CM21: =SUM(CI21:CL21) -> -436753.45 | CN21: =CI21*(1+Macro!CN11) -> -94238.985 | CO21: =CJ21*(1+Macro!CO11) -> -110906.84 | CP21: =CK21*(1+Macro!CP11) -> -133060.03 | CQ21: =CL21*(1+Macro!CQ11) -> -116017.74 | CR21: =SUM(CN21:CQ21) -> -454223.59 | CS21: =CN21*(1+Macro!CS11) -> -97537.35 | CT21: =CO21*(1+Macro!CT11) -> -114788.58 | CU21: =CP21*(1+Macro!CU11) -> -137717.13 | CV21: =CQ21*(1+Macro!CV11) -> -120078.36 | CW21: =SUM(CS21:CV21) -> -470121.41 | CX21: =CS21*(1+Macro!CX11) -> -100951.16 | CY21: =CT21*(1+Macro!CY11) -> -118806.18 | CZ21: =CU21*(1+Macro!CZ11) -> -142537.23 | DA21: =CV21*(1+Macro!DA11) -> -124281.1 | DB21: =SUM(CX21:DA21) -> -486575.66
A22: as % of net revenues | B22: =-B21/B9 -> 0.049514856 | C22: =-C21/C9 -> 0.052619139 | D22: =-D21/D9 -> 0.059672323 | E22: =-E21/E9 -> 0.065090159 | F22: =-F21/F9 -> 0.057120041 | G22: =-G21/G9 -> 0.068163685 | H22: =-H21/H9 -> 0.072294567 | I22: =-I21/I9 -> 0.061919002 | ... DB22: =-DB21/DB9 -> 0.032979018
A23: Net financial results | B23: =B24+B26+B28 -> 5388 | C23: =C24+C26+C28 -> 20507 | D23: =D24+D26+D28 -> 22098 | E23: =E24+E26+E28 -> 17239 | F23: =SUM(B23:E23) -> 65232 | G23: =G24+G26+G28 -> 3210 | H23: =H24+H26+H28 -> 19574 | I23: =I24+I26+I28 -> 7204 | J23: =J24+J26+J28 -> 19631 | K23: =SUM(G23:J23) -> 49619 | L23: =L24+L26+L28 -> 7372 | M23: =M24+M26+M28 -> 3487 | N23: =N24+N26+N28 -> 2574 | O23: =O24+O26+O28 -> -2842 | P23: =SUM(L23:O23) -> 10591 | Q23: =Q24+Q26+Q28 -> 9802 | R23: =R24+R26+R28 -> 8806 | S23: =S24+S26+S28 -> 4964 | T23: =T24+T26+T28 -> 4306 | U23: =SUM(Q23:T23) -> 27878 | V23: =V24+V26+V28 -> 9440 | W23: =W24+W26+W28 -> 3202 | X23: =X24+X26+X28 -> 1584 | Y23: =Y24+Y26+Y28 -> 1918 | Z23: =SUM(V23:Y23) -> 16144 | AA23: =AA24+AA26+AA28 -> 6182 | AB23: =AB24+AB26+AB28 -> -10004 | AC23: =AC24+AC26+AC28 -> 5184 | AD23: =AD24+AD26+AD28 -> 16235 | AE23: =SUM(AA23:AD23) -> 17597 | AF23: =AF24+AF26+AF28 -> 20257 | AG23: =AG24+AG26+AG28 -> 25931 | AH23: =AH24+AH26+AH28 -> 18196 | AI23: =AI24+AI26+AI28 -> 14759 | AJ23: =SUM(AF23:AI23) -> 79143 | AK23: =AK24+AK26+AK28 -> 12967 | AL23: =AL24+AL26+AL28 -> 5208 | AM23: =AM24+AM26+AM28 -> 11674 | AN23: =AN24+AN26+AN28 -> 7963 | AO23: =SUM(AK23:AN23) -> 37812 | AP23: =AP24+AP26+AP28 -> 2760 | AQ23: =AQ24+AQ26+AQ28 -> 4473 | AR23: =AR24+AR26+AR28 -> -769 | AS23: =AS24+AS26+AS28 -> 15654 | AT23: =SUM(AP23:AS23) -> 22118 | AU23: =AU24+AU26+AU28 -> 1872 | AV23: =AV24+AV26+AV28 -> 17872 | AW23: =AW24+AW26+AW28 -> 9055 | AX23: =AX24+AX26+AX28 -> 1794 | AY23: =SUM(AU23:AX23) -> 30593 | AZ23: =AZ24+AZ26+AZ28 -> 3251 | BA23: =BA24+BA26+BA28 -> 6501 | BB23: =BB24+BB26+BB28 -> 24471 | BC23: =BC24+BC26+BC28 -> 50278 | BD23: =SUM(AZ23:BC23) -> 84501 | BE23: =BE24+BE26+BE28 -> 10887 | BF23: =BF24+BF26+BF28 -> 9293 | BG23: =BG24+BG26+BG28 -> 8859 | BH23: =BH24+BH26+BH28 -> 13958 | BI23: =SUM(BE23:BH23) -> 42997 | BJ23: =BJ24+BJ26+BJ28 -> 9333 | BK23: =BK24+BK26+BK28 -> 25501 | BL23: =BL24+BL26+BL28 -> 7027 | BM23: =BM24+BM26+BM28 -> 26466 | BN23: =SUM(BJ23:BM23) -> 68327 | BO23: =BO24+BO26+BO28 -> 45587 | BP23: =BP24+BP26+BP28 -> 29183 | BQ23: =BQ24+BQ26+BQ28 -> 28081 | BR23: =BR24+BR26+BR28 -> 33921 | BS23: =SUM(BO23:BR23) -> 136772 | BT23: =BT24+BT26+BT28 -> 13135 | BU23: =BU24+BU26+BU28 -> 44695 | BV23: =BV24+BV26+BV28 -> 39210 | BW23: =BW24+BW26+BW28 -> 16645 | BX23: =SUM(BT23:BW23) -> 113685 | BY23: =BY24+BY26+BY28 -> 59001 | BZ23: =BZ24+BZ26+BZ28 -> 66436 | CA23: =CA24+CA26+CA28 -> 56503 | CB23: =CB24+CB26+CB28 -> 65739 | CC23: =SUM(BY23:CB23) -> 247679 | CD23: =CD24+CD26+CD28 -> 37699 | CE23: =CE24+CE26+CE28 -> 69311 | CF23: =CF24+CF26+CF28 -> 71084.385 | CG23: =CG24+CG26+CG28 -> 65048.768 | CH23: =SUM(CD23:CG23) -> 243143.15 | CI23: =CI24+CI26+CI28 -> 99372.711 | CJ23: =CJ24+CJ26+CJ28 -> 71717.208 | CK23: =CK24+CK26+CK28 -> 65167.881 | CL23: =CL24+CL26+CL28 -> 77841.107 | CM23: =SUM(CI23:CL23) -> 314098.91 | CN23: =CN24+CN26+CN28 -> 91614.646 | CO23: =CO24+CO26+CO28 -> 70518.056 | CP23: =CP24+CP26+CP28 -> 51312.61 | CQ23: =CQ24+CQ26+CQ28 -> 68228.911 | CR23: =SUM(CN23:CQ23) -> 281674.22 | CS23: =CS24+CS26+CS28 -> 73833.83 | CT23: =CT24+CT26+CT28 -> 58524.31 | CU23: =CU24+CU26+CU28 -> 43983.289 | CV23: =CV24+CV26+CV28 -> 61507.703 | CW23: =SUM(CS23:CV23) -> 237849.13 | CX23: =CX24+CX26+CX28 -> 77037.016 | CY23: =CY24+CY26+CY28 -> 60075.166 | CZ23: =CZ24+CZ26+CZ28 -> 47982.25 | DA23: =DA24+DA26+DA28 -> 72634.42 | DB23: =SUM(CX23:DA23) -> 257728.85
A24: Financial income | B24: =57269 -> 57269 | C24: =79023 -> 79023 | D24: =82309 -> 82309 | E24: =69011 -> 69011 | F24: =SUM(B24:E24) -> 287612 | G24: =59606 -> 59606 | H24: =135741-46605 -> 89136 | I24: =101379 -> 101379 | J24: =363335-G24-H24-I24 -> 113214 | K24: =SUM(G24:J24) -> 363335 | L24: =156358-M24 -> 78009 | M24: =78349 -> 78349 | N24: =47580 -> 47580 | O24: =249302-L24-M24-N24 -> 45364 | P24: =SUM(L24:O24) -> 249302 | Q24: =99206-R24 -> 50737 | R24: =48469 -> 48469 | S24: =50340 -> 50340 | T24: =207166-Q24-R24-S24 -> 57620 | U24: =SUM(Q24:T24) -> 207166 | V24: =69890 -> 69890 | W24: =72020 -> 72020 | X24: =68287 -> 68287 | Y24: =278643-V24-W24-X24 -> 68446 | Z24: =SUM(V24:Y24) -> 278643 | AA24: =70199 -> 70199 | AB24: =78523 -> 78523 | AC24: =92358 -> 92358 | AD24: =330885-AA24-AB24-AC24 -> 89805 | AE24: =SUM(AA24:AD24) -> 330885 | AF24: =79540 -> 79540 | AG24: =82849 -> 82849 | AH24: =72404 -> 72404 | AI24: =305693-AF24-AG24-AH24 -> 70900 | AJ24: =SUM(AF24:AI24) -> 305693 | AK24: =64967 -> 64967 | AL24: =49577 -> 49577 | AM24: =53730 -> 53730 | AN24: =205392-AK24-AL24-AM24 -> 37118 | AO24: =SUM(AK24:AN24) -> 205392 | AP24: =31953 -> 31953 | AQ24: =33070 -> 33070 | AR24: =49281 -> 49281 | AS24: =173006-AP24-AQ24-AR24 -> 58702 | AT24: =SUM(AP24:AS24) -> 173006 | AU24: =40108 -> 40108 | AV24: =49286 -> 49286 | AW24: =47956 -> 47956 | AX24: =180522-AU24-AV24-AW24 -> 43172 | AY24: =SUM(AU24:AX24) -> 180522 | AZ24: =31141 -> 31141 | BA24: =42555 -> 42555 | BB24: =55454 -> 55454 | BC24: =202431-AZ24-BA24-BB24 -> 73281 | BD24: =SUM(AZ24:BC24) -> 202431 | BE24: =53921 -> 53921 | BF24: =51865 -> 51865 | BG24: =71473 -> 71473 | BH24: =271862-BE24-BF24-BG24 -> 94603 | BI24: =SUM(BE24:BH24) -> 271862 | BJ24: =95875 -> 95875 | BK24: =130109 -> 130109 | BL24: =130948 -> 130948 | BM24: =572713-BJ24-BK24-BL24 -> 215781 | BN24: =SUM(BJ24:BM24) -> 572713 | BO24: =190820 -> 190820 | BP24: =178032 -> 178032 | BQ24: =156108 -> 156108 | BR24: =694725-BO24-BP24-BQ24 -> 169765 | BS24: =SUM(BO24:BR24) -> 694725 | BT24: =157466 -> 157466 | BU24: =182301 -> 182301 | BV24: =169528 -> 169528 | BW24: =683473-SUM(BT24:BV24) -> 174178 | BX24: =SUM(BT24:BW24) -> 683473 | BY24: =211618 -> 211618 | BZ24: =252543 -> 252543 | CA24: 246895 | CB24: =975978-SUM(BY24:CA24) -> 264922 | CC24: =SUM(BY24:CB24) -> 975978 | CD24: 260988 | CE24: =332564 -> 332564 | CF24: =CF25*(AVERAGE('BS & FCF'!CE6:CF6)+AVERAGE('BS & FCF'!CE7:CF7))/4 -> 290756.11 | CG24: =CG25*(AVERAGE('BS & FCF'!CF6:CG6)+AVERAGE('BS & FCF'!CF7:CG7))/4 -> 287420.38 | CH24: =SUM(CD24:CG24) -> 1171728.5 | CI24: =CI25*(AVERAGE('BS & FCF'!CH6:CI6)+AVERAGE('BS & FCF'!CH7:CI7))/4 -> 356219.33 | CJ24: =CJ25*(AVERAGE('BS & FCF'!CI6:CJ6)+AVERAGE('BS & FCF'!CI7:CJ7))/4 -> 325784.01 | CK24: =CK25*(AVERAGE('BS & FCF'!CJ6:CK6)+AVERAGE('BS & FCF'!CJ7:CK7))/4 -> 306168.28 | CL24: =CL25*(AVERAGE('BS & FCF'!CK6:CL6)+AVERAGE('BS & FCF'!CK7:CL7))/4 -> 309270.79 | CM24: =SUM(CI24:CL24) -> 1297442.4 | CN24: =CN25*(AVERAGE('BS & FCF'!CM6:CN6)+AVERAGE('BS & FCF'!CM7:CN7))/4 -> 324523.49 | CO24: =CO25*(AVERAGE('BS & FCF'!CN6:CO6)+AVERAGE('BS & FCF'!CN7:CO7))/4 -> 304400.78 | CP24: =CP25*(AVERAGE('BS & FCF'!CO6:CP6)+AVERAGE('BS & FCF'!CO7:CP7))/4 -> 287211.21 | CQ24: =CQ25*(AVERAGE('BS & FCF'!CP6:CQ6)+AVERAGE('BS & FCF'!CP7:CQ7))/4 -> 307085.62 | CR24: =SUM(CN24:CQ24) -> 1223221.1 | CS24: =CS25*(AVERAGE('BS & FCF'!CR6:CS6)+AVERAGE('BS & FCF'!CR7:CS7))/4 -> 281345.51 | CT24: =CT25*(AVERAGE('BS & FCF'!CS6:CT6)+AVERAGE('BS & FCF'!CS7:CT7))/4 -> 265802.2 | CU24: =CU25*(AVERAGE('BS & FCF'!CT6:CU6)+AVERAGE('BS & FCF'!CT7:CU7))/4 -> 252220.73 | CV24: =CV25*(AVERAGE('BS & FCF'!CU6:CV6)+AVERAGE('BS & FCF'!CU7:CV7))/4 -> 272022.08 | CW24: =SUM(CS24:CV24) -> 1071390.5 | CX24: =CX25*(AVERAGE('BS & FCF'!CW6:CX6)+AVERAGE('BS & FCF'!CW7:CX7))/4 -> 289230.8 | CY24: =CY25*(AVERAGE('BS & FCF'!CX6:CY6)+AVERAGE('BS & FCF'!CX7:CY7))/4 -> 272691.08 | CZ24: =CZ25*(AVERAGE('BS & FCF'!CY6:CZ6)+AVERAGE('BS & FCF'!CY7:CZ7))/4 -> 261797.99 | DA24: =DA25*(AVERAGE('BS & FCF'!CZ6:DA6)+AVERAGE('BS & FCF'!CZ7:DA7))/4 -> 289216.53 | DB24: =SUM(CX24:DA24) -> 1112936.4
A25: Avg. cash rate (%) | B25: =(1+(B24)/(AVERAGE('BS & FCF'!B6:B6)+AVERAGE('BS & FCF'!B7:B7)))^4-1 -> 0.14190023 | C25: =(1+(C24)/(AVERAGE('BS & FCF'!B6:C6)+AVERAGE('BS & FCF'!B7:C7)))^4-1 -> 0.21647855 | D25: =(1+(D24)/(AVERAGE('BS & FCF'!C6:D6)+AVERAGE('BS & FCF'!C7:D7)))^4-1 -> 0.2496235 | E25: =(1+(E24)/(AVERAGE('BS & FCF'!D6:E6)+AVERAGE('BS & FCF'!D7:E7)))^4-1 -> 0.20106449 | F25: =(F24)/(AVERAGE('BS & FCF'!B6:E6)+AVERAGE('BS & FCF'!B7:E7)) -> 0.18882506 | G25: =(1+(G24)/(AVERAGE('BS & FCF'!F6:G6)+AVERAGE('BS & FCF'!F7:G7)))^4-1 -> 0.15971437 | H25: =(1+(H24)/(AVERAGE('BS & FCF'!G6:H6)+AVERAGE('BS & FCF'!G7:H7)))^4-1 -> 0.21270198 | I25: =(1+(I24)/(AVERAGE('BS & FCF'!H6:I6)+AVERAGE('BS & FCF'!H7:I7)))^4-1 -> 0.21143381 | J25: =(1+(J24)/(AVERAGE('BS & FCF'!I6:J6)+AVERAGE('BS & FCF'!I7:J7)))^4-1 -> 0.21876662 | K25: =(K24)/(AVERAGE('BS & FCF'!G6:J6)+AVERAGE('BS & FCF'!G7:J7)) -> 0.17998177 | L25: =(1+(L24)/(AVERAGE('BS & FCF'!K6:L6)+AVERAGE('BS & FCF'!K7:L7)))^4-1 -> 0.14251831 | M25: =(1+(M24)/(AVERAGE('BS & FCF'!L6:M6)+AVERAGE('BS & FCF'!L7:M7)))^4-1 -> 0.14850962 | N25: =(1+(N24)/(AVERAGE('BS & FCF'!M6:N6)+AVERAGE('BS & FCF'!M7:N7)))^4-1 -> 0.091124614 | O25: =(1+(O24)/(AVERAGE('BS & FCF'!N6:O6)+AVERAGE('BS & FCF'!N7:O7)))^4-1 -> 0.088646907 | P25: =(P24)/(AVERAGE('BS & FCF'!L6:O6)+AVERAGE('BS & FCF'!L7:O7)) -> 0.1149333 | Q25: =(1+(Q24)/(AVERAGE('BS & FCF'!P6:Q6)+AVERAGE('BS & FCF'!P7:Q7)))^4-1 -> 0.10150942 | R25: =(1+(R24)/(AVERAGE('BS & FCF'!Q6:R6)+AVERAGE('BS & FCF'!Q7:R7)))^4-1 -> 0.10111047 | S25: =(1+(S24)/(AVERAGE('BS & FCF'!R6:S6)+AVERAGE('BS & FCF'!R7:S7)))^4-1 -> 0.10903434 | T25: =(1+(T24)/(AVERAGE('BS & FCF'!S6:T6)+AVERAGE('BS & FCF'!S7:T7)))^4-1 -> 0.12340861 | U25: =(U24)/(AVERAGE('BS & FCF'!Q6:T6)+AVERAGE('BS & FCF'!Q7:T7)) -> 0.10514269 | V25: =(1+(V24)/(AVERAGE('BS & FCF'!U6:V6)+AVERAGE('BS & FCF'!U7:V7)))^4-1 -> 0.13512163 | W25: =(1+(W24)/(AVERAGE('BS & FCF'!V6:W6)+AVERAGE('BS & FCF'!V7:W7)))^4-1 -> 0.14001089 | X25: =(1+(X24)/(AVERAGE('BS & FCF'!W6:X6)+AVERAGE('BS & FCF'!W7:X7)))^4-1 -> 0.14823882 | Y25: =(1+(Y24)/(AVERAGE('BS & FCF'!X6:Y6)+AVERAGE('BS & FCF'!X7:Y7)))^4-1 -> 0.14832575 | Z25: =(Z24)/(AVERAGE('BS & FCF'!V6:Y6)+AVERAGE('BS & FCF'!V7:Y7)) -> 0.13565287 | AA25: =(1+(AA24)/(AVERAGE('BS & FCF'!Z6:AA6)+AVERAGE('BS & FCF'!Z7:AA7)))^4-1 -> 0.14169618 | AB25: =(1+(AB24)/(AVERAGE('BS & FCF'!AA6:AB6)+AVERAGE('BS & FCF'!AA7:AB7)))^4-1 -> 0.14133966 | AC25: =(1+(AC24)/(AVERAGE('BS & FCF'!AB6:AC6)+AVERAGE('BS & FCF'!AB7:AC7)))^4-1 -> 0.15059073 | AD25: =(1+(AD24)/(AVERAGE('BS & FCF'!AC6:AD6)+AVERAGE('BS & FCF'!AC7:AD7)))^4-1 -> 0.14620306 | AE25: =(AE24)/(AVERAGE('BS & FCF'!AA6:AD6)+AVERAGE('BS & FCF'!AA7:AD7)) -> 0.13437871 | AF25: =(1+(AF24)/(AVERAGE('BS & FCF'!AE6:AF6)+AVERAGE('BS & FCF'!AE7:AF7)))^4-1 -> 0.13668683 | AG25: =(1+(AG24)/(AVERAGE('BS & FCF'!AF6:AG6)+AVERAGE('BS & FCF'!AF7:AG7)))^4-1 -> 0.15173603 | AH25: =(1+(AH24)/(AVERAGE('BS & FCF'!AG6:AH6)+AVERAGE('BS & FCF'!AG7:AH7)))^4-1 -> 0.15040544 | AI25: =(1+(AI24)/(AVERAGE('BS & FCF'!AH6:AI6)+AVERAGE('BS & FCF'!AH7:AI7)))^4-1 -> 0.15236454 | AJ25: =(AJ24)/(AVERAGE('BS & FCF'!AF6:AI6)+AVERAGE('BS & FCF'!AF7:AI7)) -> 0.14320918 | AK25: =(1+(AK24)/(AVERAGE('BS & FCF'!AJ6:AK6)+AVERAGE('BS & FCF'!AJ7:AK7)))^4-1 -> 0.12526877 | AL25: =(1+(AL24)/(AVERAGE('BS & FCF'!AK6:AL6)+AVERAGE('BS & FCF'!AK7:AL7)))^4-1 -> 0.097043607 | AM25: =(1+(AM24)/(AVERAGE('BS & FCF'!AL6:AM6)+AVERAGE('BS & FCF'!AL7:AM7)))^4-1 -> 0.11697269 | AN25: =(1+(AN24)/(AVERAGE('BS & FCF'!AM6:AN6)+AVERAGE('BS & FCF'!AM7:AN7)))^4-1 -> 0.084784151 | AO25: =(AO24)/(AVERAGE('BS & FCF'!AK6:AN6)+AVERAGE('BS & FCF'!AK7:AN7)) -> 0.10472948 | AP25: =(1+(AP24)/(AVERAGE('BS & FCF'!AO6:AP6)+AVERAGE('BS & FCF'!AO7:AP7)))^4-1 -> 0.082480358 | AQ25: =(1+(AQ24)/(AVERAGE('BS & FCF'!AP6:AQ6)+AVERAGE('BS & FCF'!AP7:AQ7)))^4-1 -> 0.081423828 | AR25: =(1+(AR24)/(AVERAGE('BS & FCF'!AQ6:AR6)+AVERAGE('BS & FCF'!AQ7:AR7)))^4-1 -> 0.095957129 | AS25: =(1+(AS24)/(AVERAGE('BS & FCF'!AR6:AS6)+AVERAGE('BS & FCF'!AR7:AS7)))^4-1 -> 0.11586227 | AT25: =(AT24)/(AVERAGE('BS & FCF'!AP6:AS6)+AVERAGE('BS & FCF'!AP7:AS7)) -> 0.091391593 | AU25: =(1+(AU24)/(AVERAGE('BS & FCF'!AT6:AU6)+AVERAGE('BS & FCF'!AT7:AU7)))^4-1 -> 0.091974627 | AV25: =(1+(AV24)/(AVERAGE('BS & FCF'!AU6:AV6)+AVERAGE('BS & FCF'!AU7:AV7)))^4-1 -> 0.11310688 | AW25: =(1+(AW24)/(AVERAGE('BS & FCF'!AV6:AW6)+AVERAGE('BS & FCF'!AV7:AW7)))^4-1 -> 0.10019876 | AX25: =(1+(AX24)/(AVERAGE('BS & FCF'!AW6:AX6)+AVERAGE('BS & FCF'!AW7:AX7)))^4-1 -> 0.086058045 | AY25: =(AY24)/(AVERAGE('BS & FCF'!AU6:AX6)+AVERAGE('BS & FCF'!AU7:AX7)) -> 0.092919485 | AZ25: =(1+(AZ24)/(AVERAGE('BS & FCF'!AY6:AZ6)+AVERAGE('BS & FCF'!AY7:AZ7)))^4-1 -> 0.061768925 | BA25: =(1+(BA24)/(AVERAGE('BS & FCF'!AZ6:BA6)+AVERAGE('BS & FCF'!AZ7:BA7)))^4-1 -> 0.076895118 | BB25: =(1+(BB24)/(AVERAGE('BS & FCF'!BA6:BB6)+AVERAGE('BS & FCF'!BA7:BB7)))^4-1 -> 0.085530121 | BC25: =(1+(BC24)/(AVERAGE('BS & FCF'!BB6:BC6)+AVERAGE('BS & FCF'!BB7:BC7)))^4-1 -> 0.10735846 | BD25: =(BD24)/(AVERAGE('BS & FCF'!AZ6:BC6)+AVERAGE('BS & FCF'!AZ7:BC7)) -> 0.079160751 | BE25: =(1+(BE24)/(AVERAGE('BS & FCF'!BD6:BE6)+AVERAGE('BS & FCF'!BD7:BE7)))^4-1 -> 0.079092593 | BF25: =(1+(BF24)/(AVERAGE('BS & FCF'!BE6:BF6)+AVERAGE('BS & FCF'!BE7:BF7)))^4-1 -> 0.070707057 | BG25: =(1+(BG24)/(AVERAGE('BS & FCF'!BF6:BG6)+AVERAGE('BS & FCF'!BF7:BG7)))^4-1 -> 0.08927741 | BH25: =(1+(BH24)/(AVERAGE('BS & FCF'!BG6:BH6)+AVERAGE('BS & FCF'!BG7:BH7)))^4-1 -> 0.10816783 | BI25: =(BI24)/(AVERAGE('BS & FCF'!BE6:BH6)+AVERAGE('BS & FCF'!BE7:BH7)) -> 0.081787421 | BJ25: =(1+(BJ24)/(AVERAGE('BS & FCF'!BI6:BJ6)+AVERAGE('BS & FCF'!BI7:BJ7)))^4-1 -> 0.10469156 | BK25: =(1+(BK24)/(AVERAGE('BS & FCF'!BJ6:BK6)+AVERAGE('BS & FCF'!BJ7:BK7)))^4-1 -> 0.13809846 | BL25: =(1+(BL24)/(AVERAGE('BS & FCF'!BK6:BL6)+AVERAGE('BS & FCF'!BK7:BL7)))^4-1 -> 0.12802981 | BM25: =(1+(BM24)/(AVERAGE('BS & FCF'!BL6:BM6)+AVERAGE('BS & FCF'!BL7:BM7)))^4-1 -> 0.19329604 | BN25: =(BN24)/(AVERAGE('BS & FCF'!BJ6:BM6)+AVERAGE('BS & FCF'!BJ7:BM7)) -> 0.13112238 | BO25: =(1+(BO24)/(AVERAGE('BS & FCF'!BN6:BO6)+AVERAGE('BS & FCF'!BN7:BO7)))^4-1 -> 0.16062683 | BP25: =(1+(BP24)/(AVERAGE('BS & FCF'!BO6:BP6)+AVERAGE('BS & FCF'!BO7:BP7)))^4-1 -> 0.14948738 | BQ25: =(1+(BQ24)/(AVERAGE('BS & FCF'!BP6:BQ6)+AVERAGE('BS & FCF'!BP7:BQ7)))^4-1 -> 0.12782152 | BR25: =(1+(BR24)/(AVERAGE('BS & FCF'!BQ6:BR6)+AVERAGE('BS & FCF'!BQ7:BR7)))^4-1 -> 0.1409959 | BS25: =(BS24)/(AVERAGE('BS & FCF'!BO6:BR6)+AVERAGE('BS & FCF'!BO7:BR7)) -> 0.13774769 | BT25: =(1+(BT24)/(AVERAGE('BS & FCF'!BS6:BT6)+AVERAGE('BS & FCF'!BS7:BT7)))^4-1 -> 0.13471965 | BU25: =(1+(BU24)/(AVERAGE('BS & FCF'!BT6:BU6)+AVERAGE('BS & FCF'!BT7:BU7)))^4-1 -> 0.15551309 | BV25: =(1+(BV24)/(AVERAGE('BS & FCF'!BU6:BV6)+AVERAGE('BS & FCF'!BU7:BV7)))^4-1 -> 0.13577728 | BW25: =(1+(BW24)/(AVERAGE('BS & FCF'!BV6:BW6)+AVERAGE('BS & FCF'!BV7:BW7)))^4-1 -> 0.13427661 | BX25: =(BX24)/(AVERAGE('BS & FCF'!BT6:BW6)+AVERAGE('BS & FCF'!BT7:BW7)) -> 0.13147146 | BY25: =(1+(BY24)/(AVERAGE('BS & FCF'!BX6:BY6)+AVERAGE('BS & FCF'!BX7:BY7)))^4-1 -> 0.15888653 | BZ25: =(1+(BZ24)/(AVERAGE('BS & FCF'!BY6:BZ6)+AVERAGE('BS & FCF'!BY7:BZ7)))^4-1 -> 0.17902462 | CA25: =(1+(CA24)/(AVERAGE('BS & FCF'!BZ6:CA6)+AVERAGE('BS & FCF'!BZ7:CA7)))^4-1 -> 0.15348244 | CB25: =(1+(CB24)/(AVERAGE('BS & FCF'!CA6:CB6)+AVERAGE('BS & FCF'!CA7:CB7)))^4-1 -> 0.15442266 | CC25: =(CC24)/(AVERAGE('BS & FCF'!BY6:CB6)+AVERAGE('BS & FCF'!BY7:CB7)) -> 0.14724828 | CD25: =(1+(CD24)/(AVERAGE('BS & FCF'!CC6:CD6)+AVERAGE('BS & FCF'!CC7:CD7)))^4-1 -> 0.15044737 | CE25: =(1+(CE24)/(AVERAGE('BS & FCF'!CD6:CE6)+AVERAGE('BS & FCF'!CD7:CE7)))^4-1 -> 0.18407876 | CF25: =Macro!CF12*1.1 -> 0.143 | CG25: =Macro!CG12*1.1 -> 0.13566667 | CH25: =(CH24)/(AVERAGE('BS & FCF'!CD6:CG6)+AVERAGE('BS & FCF'!CD7:CG7)) -> 0.14481727 | CI25: =Macro!CI12*1.1 -> 0.16316667 | CJ25: =Macro!CJ12*1.1 -> 0.15216667 | CK25: =Macro!CK12*1.1 -> 0.143 | CL25: =Macro!CL12*1.1 -> 0.13566667 | CM25: =(CM24)/(AVERAGE('BS & FCF'!CI6:CL6)+AVERAGE('BS & FCF'!CI7:CL7)) -> 0.1467494 | CN25: =Macro!CN12*1.1 -> 0.13566667 | CO25: =Macro!CO12*1.1 -> 0.13566667 | CP25: =Macro!CP12*1.1 -> 0.13566667 | CQ25: =Macro!CQ12*1.1 -> 0.13566667 | CR25: =(CR24)/(AVERAGE('BS & FCF'!CN6:CQ6)+AVERAGE('BS & FCF'!CN7:CQ7)) -> 0.13569421 | CS25: =Macro!CS12*1.1 -> 0.1166 | CT25: =Macro!CT12*1.1 -> 0.1166 | CU25: =Macro!CU12*1.1 -> 0.1166 | CV25: =Macro!CV12*1.1 -> 0.1166 | CW25: =(CW24)/(AVERAGE('BS & FCF'!CS6:CV6)+AVERAGE('BS & FCF'!CS7:CV7)) -> 0.11613843 | CX25: =Macro!CX12*1.1 -> 0.1166 | CY25: =Macro!CY12*1.1 -> 0.1166 | CZ25: =Macro!CZ12*1.1 -> 0.1166 | DA25: =Macro!DA12*1.1 -> 0.1166 | DB25: =(DB24)/(AVERAGE('BS & FCF'!CX6:DA6)+AVERAGE('BS & FCF'!CX7:DA7)) -> 0.11547128
A26: Financial expenses | B26: -51881 | C26: -58516 | D26: -60211 | E26: -51772 | F26: =SUM(B26:E26) -> -222380 | G26: -56396 | H26: =-125958-G26 -> -69562 | I26: =-220133-G26-H26 -> -94175 | J26: =-313716-G26-H26-I26 -> -93583 | K26: =SUM(G26:J26) -> -313716 | L26: =-145499-M26 -> -70637 | M26: -74862 | N26: -45006 | O26: =-238711-L26-M26-N26 -> -48206 | P26: =SUM(L26:O26) -> -238711 | Q26: =-80598-R26 -> -40935 | R26: -39663 | S26: -45376 | T26: =-179288-Q26-R26-S26 -> -53314 | U26: =SUM(Q26:T26) -> -179288 | V26: -60450 | W26: -68818 | X26: -66703 | Y26: =-262499-V26-W26-X26 -> -66528 | Z26: =SUM(V26:Y26) -> -262499 | AA26: -64017 | AB26: -88527 | AC26: -87174 | AD26: =-313288-AA26-AB26-AC26 -> -73570 | AE26: =SUM(AA26:AD26) -> -313288 | AF26: -59283 | AG26: -56918 | AH26: -54208 | AI26: =-226550-AF26-AG26-AH26 -> -56141 | AJ26: =SUM(AF26:AI26) -> -226550 | AK26: -52000 | AL26: -44369 | AM26: -42056 | AN26: =-167580-AK26-AL26-AM26 -> -29155 | AO26: =SUM(AK26:AN26) -> -167580 | AP26: -29193 | AQ26: -28597 | AR26: -50050 | AS26: =-150888-AP26-AQ26-AR26 -> -43048 | AT26: =SUM(AP26:AS26) -> -150888 | AU26: -38236 | AV26: -31414 | AW26: -38901 | AX26: =-149929-AU26-AV26-AW26 -> -41378 | AY26: =SUM(AU26:AX26) -> -149929 | AZ26: -27890 | BA26: -36054 | BB26: -30983 | BC26: =-117930-AZ26-BA26-BB26 -> -23003 | BD26: =SUM(AZ26:BC26) -> -117930 | BE26: -43034 | BF26: -42572 | BG26: -62614 | BH26: =-228865-BE26-BF26-BG26 -> -80645 | BI26: =SUM(BE26:BH26) -> -228865 | BJ26: -86542 | BK26: -104608 | BL26: -123921 | BM26: =-504386-BJ26-BK26-BL26 -> -189315 | BN26: =SUM(BJ26:BM26) -> -504386 | BO26: -145233 | BP26: -148849 | BQ26: -128027 | BR26: =-557953-BO26-BP26-BQ26 -> -135844 | BS26: =SUM(BO26:BR26) -> -557953 | BT26: -144331 | BU26: -137606 | BV26: -130318 | BW26: =-569788-BT26-BU26-BV26 -> -157533 | BX26: =SUM(BT26:BW26) -> -569788 | BY26: -152617 | BZ26: -186107 | CA26: -190392 | CB26: =-728299-BY26-BZ26-CA26 -> -199183 | CC26: =SUM(BY26:CB26) -> -728299 | CD26: -223289 | CE26: -263253 | CF26: =CF95+CF94 -> -219671.73 | CG26: =CG95+CG94 -> -222371.62 | CH26: =SUM(CD26:CG26) -> -928585.34 | CI26: =CI95+CI94 -> -256846.62 | CJ26: =CJ95+CJ94 -> -254066.8 | CK26: =CK95+CK94 -> -241000.4 | CL26: =CL95+CL94 -> -231429.69 | CM26: =SUM(CI26:CL26) -> -983343.51 | CN26: =CN95+CN94 -> -232908.84 | CO26: =CO95+CO94 -> -233882.73 | CP26: =CP95+CP94 -> -235898.6 | CQ26: =CQ95+CQ94 -> -238856.71 | CR26: =SUM(CN26:CQ26) -> -941546.88 | CS26: =CS95+CS94 -> -207511.68 | CT26: =CT95+CT94 -> -207277.89 | CU26: =CU95+CU94 -> -208237.44 | CV26: =CV95+CV94 -> -210514.37 | CW26: =SUM(CS26:CV26) -> -833541.38 | CX26: =CX95+CX94 -> -212193.78 | CY26: =CY95+CY94 -> -212615.91 | CZ26: =CZ95+CZ94 -> -213815.74 | DA26: =DA95+DA94 -> -216582.11 | DB26: =SUM(CX26:DA26) -> -855207.54
A27: Avg. debt rate (%) | B27: =(1-B26/AVERAGE('BS & FCF'!B51:B51))^4-1 -> 0.083135497 | C27: =(1-C26/AVERAGE('BS & FCF'!B51:C51))^4-1 -> 0.090662522 | D27: =(1-D26/AVERAGE('BS & FCF'!C51:D51))^4-1 -> 0.086546441 | E27: =(1-E26/AVERAGE('BS & FCF'!D51:E51))^4-1 -> 0.066167141 | F27: =-F26/AVERAGE('BS & FCF'!B51:E51) -> 0.075713031 | G27: =(1-G26/AVERAGE('BS & FCF'!F51:G51))^4-1 -> 0.0653195 | H27: =(1-H26/AVERAGE('BS & FCF'!G51:H51))^4-1 -> 0.073011851 | I27: =(1-I26/AVERAGE('BS & FCF'!H51:I51))^4-1 -> 0.088362149 | J27: =(1-J26/AVERAGE('BS & FCF'!I51:J51))^4-1 -> 0.083830796 | K27: =-K26/AVERAGE('BS & FCF'!G51:J51) -> 0.073666831 | L27: =(1-L26/AVERAGE('BS & FCF'!K51:L51))^4-1 -> 0.062715171 | M27: =(1-M26/AVERAGE('BS & FCF'!L51:M51))^4-1 -> 0.06748662 | N27: =(1-N26/AVERAGE('BS & FCF'!M51:N51))^4-1 -> 0.041351301 | O27: =(1-O26/AVERAGE('BS & FCF'!N51:O51))^4-1 -> 0.046382953 | P27: =-P26/AVERAGE('BS & FCF'!L51:O51) -> 0.054396189 | Q27: =(1-Q26/AVERAGE('BS & FCF'!P51:Q51))^4-1 -> 0.042205846 | R27: =(1-R26/AVERAGE('BS & FCF'!Q51:R51))^4-1 -> 0.042528533 | S27: =(1-S26/AVERAGE('BS & FCF'!R51:S51))^4-1 -> 0.048268311 | T27: =(1-T26/AVERAGE('BS & FCF'!S51:T51))^4-1 -> 0.053778069 | U27: =-U26/AVERAGE('BS & FCF'!Q51:T51) -> 0.045771513 | V27: =(1-V26/AVERAGE('BS & FCF'!U51:V51))^4-1 -> 0.056075974 | W27: =(1-W26/AVERAGE('BS & FCF'!V51:W51))^4-1 -> 0.063527018 | X27: =(1-X26/AVERAGE('BS & FCF'!W51:X51))^4-1 -> 0.064275052 | Y27: =(1-Y26/AVERAGE('BS & FCF'!X51:Y51))^4-1 -> 0.067391389 | Z27: =-Z26/AVERAGE('BS & FCF'!V51:Y51) -> 0.061893785 | AA27: =(1-AA26/AVERAGE('BS & FCF'!Z51:AA51))^4-1 -> 0.068415267 | AB27: =(1-AB26/AVERAGE('BS & FCF'!AA51:AB51))^4-1 -> 0.094532785 | AC27: =(1-AC26/AVERAGE('BS & FCF'!AB51:AC51))^4-1 -> 0.09026102 | AD27: =(1-AD26/AVERAGE('BS & FCF'!AC51:AD51))^4-1 -> 0.077902313 | AE27: =-AE26/AVERAGE('BS & FCF'!AA51:AD51) -> 0.080719895 | AF27: =(1-AF26/AVERAGE('BS & FCF'!AE51:AF51))^4-1 -> 0.0655111 | AG27: =(1-AG26/AVERAGE('BS & FCF'!AF51:AG51))^4-1 -> 0.064664455 | AH27: =(1-AH26/AVERAGE('BS & FCF'!AG51:AH51))^4-1 -> 0.063320593 | AI27: =(1-AI26/AVERAGE('BS & FCF'!AH51:AI51))^4-1 -> 0.066736012 | AJ27: =-AJ26/AVERAGE('BS & FCF'!AF51:AI51) -> 0.064241055 | AK27: =(1-AK26/AVERAGE('BS & FCF'!AJ51:AK51))^4-1 -> 0.060858316 | AL27: =(1-AL26/AVERAGE('BS & FCF'!AK51:AL51))^4-1 -> 0.052111203 | AM27: =(1-AM26/AVERAGE('BS & FCF'!AL51:AM51))^4-1 -> 0.05310541 | AN27: =(1-AN26/AVERAGE('BS & FCF'!AM51:AN51))^4-1 -> 0.041871031 | AO27: =-AO26/AVERAGE('BS & FCF'!AK51:AN51) -> 0.053198784 | AP27: =(1-AP26/AVERAGE('BS & FCF'!AO51:AP51))^4-1 -> 0.050416126 | AQ27: =(1-AQ26/AVERAGE('BS & FCF'!AP51:AQ51))^4-1 -> 0.051701493 | AR27: =(1-AR26/AVERAGE('BS & FCF'!AQ51:AR51))^4-1 -> 0.078418203 | AS27: =(1-AS26/AVERAGE('BS & FCF'!AR51:AS51))^4-1 -> 0.067092475 | AT27: =-AT26/AVERAGE('BS & FCF'!AP51:AS51) -> 0.061774772 | AU27: =(1-AU26/AVERAGE('BS & FCF'!AT51:AU51))^4-1 -> 0.07008741 | AV27: =(1-AV26/AVERAGE('BS & FCF'!AU51:AV51))^4-1 -> 0.062756333 | AW27: =(1-AW26/AVERAGE('BS & FCF'!AV51:AW51))^4-1 -> 0.072152183 | AX27: =(1-AX26/AVERAGE('BS & FCF'!AW51:AX51))^4-1 -> 0.068699254 | AY27: =-AY26/AVERAGE('BS & FCF'!AU51:AX51) -> 0.066351407 | AZ27: =(1-AZ26/AVERAGE('BS & FCF'!AY51:AZ51))^4-1 -> 0.045210152 | BA27: =(1-BA26/AVERAGE('BS & FCF'!AZ51:BA51))^4-1 -> 0.054243222 | BB27: =(1-BB26/AVERAGE('BS & FCF'!BA51:BB51))^4-1 -> 0.047184601 | BC27: =(1-BC26/AVERAGE('BS & FCF'!BB51:BC51))^4-1 -> 0.036303237 | BD27: =-BD26/AVERAGE('BS & FCF'!AZ51:BC51) -> 0.044662288 | BE27: =(1-BE26/AVERAGE('BS & FCF'!BD51:BE51))^4-1 -> 0.065327748 | BF27: =(1-BF26/AVERAGE('BS & FCF'!BE51:BF51))^4-1 -> 0.057551557 | BG27: =(1-BG26/AVERAGE('BS & FCF'!BF51:BG51))^4-1 -> 0.076269454 | BH27: =(1-BH26/AVERAGE('BS & FCF'!BG51:BH51))^4-1 -> 0.094881631 | BI27: =-BI26/AVERAGE('BS & FCF'!BE51:BH51) -> 0.069984059 | BJ27: =(1-BJ26/AVERAGE('BS & FCF'!BI51:BJ51))^4-1 -> 0.098095106 | BK27: =(1-BK26/AVERAGE('BS & FCF'!BJ51:BK51))^4-1 -> 0.11304661 | BL27: =(1-BL26/AVERAGE('BS & FCF'!BK51:BL51))^4-1 -> 0.12319032 | BM27: =(1-BM26/AVERAGE('BS & FCF'!BL51:BM51))^4-1 -> 0.17198645 | BN27: =-BN26/AVERAGE('BS & FCF'!BJ51:BM51) -> 0.11822796 | BO27: =(1-BO26/AVERAGE('BS & FCF'!BN51:BO51))^4-1 -> 0.12418006 | BP27: =(1-BP26/AVERAGE('BS & FCF'!BO51:BP51))^4-1 -> 0.12755879 | BQ27: =(1-BQ26/AVERAGE('BS & FCF'!BP51:BQ51))^4-1 -> 0.10721686 | BR27: =(1-BR26/AVERAGE('BS & FCF'!BQ51:BR51))^4-1 -> 0.1117815 | BS27: =-BS26/AVERAGE('BS & FCF'!BO51:BR51) -> 0.11220058 | BT27: =(1-BT26/AVERAGE('BS & FCF'!BS51:BT51))^4-1 -> 0.11989417 | BU27: =(1-BU26/AVERAGE('BS & FCF'!BT51:BU51))^4-1 -> 0.1129822 | BV27: =(1-BV26/AVERAGE('BS & FCF'!BU51:BV51))^4-1 -> 0.10087937 | BW27: =(1-BW26/AVERAGE('BS & FCF'!BV51:BW51))^4-1 -> 0.11478857 | BX27: =-BX26/AVERAGE('BS & FCF'!BT51:BW51) -> 0.1055746 | BY27: =(1-BY26/AVERAGE('BS & FCF'!BX51:BY51))^4-1 -> 0.10576575 | BZ27: =(1-BZ26/AVERAGE('BS & FCF'!BY51:BZ51))^4-1 -> 0.12043765 | CA27: =(1-CA26/AVERAGE('BS & FCF'!BZ51:CA51))^4-1 -> 0.11015391 | CB27: =(1-CB26/AVERAGE('BS & FCF'!CA51:CB51))^4-1 -> 0.10196077 | CC27: =-CC26/AVERAGE('BS & FCF'!BY51:CB51) -> 0.10003827 | CD27: =(1-CD26/AVERAGE('BS & FCF'!CC51:CD51))^4-1 -> 0.10597927 | CE27: =(1-CE26/AVERAGE('BS & FCF'!CD51:CE51))^4-1 -> 0.12463878 | CF27: =(1-CF26/AVERAGE('BS & FCF'!CE51:CF51))^4-1 -> 0.10179763 | CG27: =(1-CG26/AVERAGE('BS & FCF'!CF51:CG51))^4-1 -> 0.10137615 | CH27: =-CH26/AVERAGE('BS & FCF'!CD51:CG51) -> 0.10355183 | CI27: =(1-CI26/AVERAGE('BS & FCF'!CH51:CI51))^4-1 -> 0.11593012 | CJ27: =(1-CJ26/AVERAGE('BS & FCF'!CI51:CJ51))^4-1 -> 0.11352395 | CK27: =(1-CK26/AVERAGE('BS & FCF'!CJ51:CK51))^4-1 -> 0.10673734 | CL27: =(1-CL26/AVERAGE('BS & FCF'!CK51:CL51))^4-1 -> 0.10129432 | CM27: =-CM26/AVERAGE('BS & FCF'!CI51:CL51) -> 0.10459076 | CN27: =(1-CN26/AVERAGE('BS & FCF'!CM51:CN51))^4-1 -> 0.10128157 | CO27: =(1-CO26/AVERAGE('BS & FCF'!CN51:CO51))^4-1 -> 0.10127326 | CP27: =(1-CP26/AVERAGE('BS & FCF'!CO51:CP51))^4-1 -> 0.1012563 | CQ27: =(1-CQ26/AVERAGE('BS & FCF'!CP51:CQ51))^4-1 -> 0.10123193 | CR27: =-CR26/AVERAGE('BS & FCF'!CN51:CQ51) -> 0.09721426 | CS27: =(1-CS26/AVERAGE('BS & FCF'!CR51:CS51))^4-1 -> 0.087111102 | CT27: =(1-CT26/AVERAGE('BS & FCF'!CS51:CT51))^4-1 -> 0.08711297 | CU27: =(1-CU26/AVERAGE('BS & FCF'!CT51:CU51))^4-1 -> 0.087105331 | CV27: =(1-CV26/AVERAGE('BS & FCF'!CU51:CV51))^4-1 -> 0.087087487 | CW27: =-CW26/AVERAGE('BS & FCF'!CS51:CV51) -> 0.084185282 | CX27: =(1-CX26/AVERAGE('BS & FCF'!CW51:CX51))^4-1 -> 0.087074576 | CY27: =(1-CY26/AVERAGE('BS & FCF'!CX51:CY51))^4-1 -> 0.087071363 | CZ27: =(1-CZ26/AVERAGE('BS & FCF'!CY51:CZ51))^4-1 -> 0.087062302 | DA27: =(1-DA26/AVERAGE('BS & FCF'!CZ51:DA51))^4-1 -> 0.0870418 | DB27: =-DB26/AVERAGE('BS & FCF'!CX51:DA51) -> 0.084037282
A28: Client financing (direct sales) | B28: 0 | C28: 0 | D28: 0 | E28: 0 | F28: =SUM(B28:E28) -> 0 | G28: 0 | H28: 0 | I28: 0 | J28: 0 | K28: =SUM(G28:J28) -> 0 | L28: 0 | M28: 0 | N28: 0 | O28: 0 | P28: =SUM(L28:O28) -> 0 | Q28: 0 | R28: 0 | S28: 0 | T28: 0 | U28: =SUM(Q28:T28) -> 0 | V28: 0 | W28: 0 | X28: 0 | Y28: 0 | Z28: =SUM(V28:Y28) -> 0 | AA28: 0 | AB28: 0 | AC28: 0 | AD28: 0 | AE28: =SUM(AA28:AD28) -> 0 | AF28: 0 | AG28: 0 | AH28: 0 | AI28: 0 | AJ28: =SUM(AF28:AI28) -> 0 | AK28: 0 | AL28: 0 | AM28: 0 | AN28: 0 | AO28: =SUM(AK28:AN28) -> 0 | AP28: 0 | AQ28: 0 | AR28: 0 | AS28: 0 | AT28: =SUM(AP28:AS28) -> 0 | AU28: 0 | AV28: 0 | AW28: 0 | AX28: 0 | AY28: =SUM(AU28:AX28) -> 0 | AZ28: 0 | BA28: 0 | BB28: 0 | BC28: 0 | BD28: =SUM(AZ28:BC28) -> 0 | BE28: 0 | BF28: 0 | BG28: 0 | BH28: 0 | BI28: =SUM(BE28:BH28) -> 0 | BJ28: 0 | BK28: 0 | BL28: 0 | BM28: 0 | BN28: =SUM(BJ28:BM28) -> 0 | BO28: 0 | BP28: 0 | BQ28: 0 | BR28: 0 | BS28: =SUM(BO28:BR28) -> 0 | BT28: 0 | BU28: 0 | BV28: 0 | BW28: 0 | BX28: =SUM(BT28:BW28) -> 0 | BY28: 0 | BZ28: 0 | CA28: 0 | CB28: 0 | CC28: =SUM(BY28:CB28) -> 0 | CD28: 0 | CE28: 0 | CF28: =((1+AVERAGE('BS & FCF'!CE11:CF11))^1/4)*CF29 -> 0 | CG28: =((1+AVERAGE('BS & FCF'!CF11:CG11))^1/4)*CG29 -> 0 | CH28: =SUM(CD28:CG28) -> 0 | CI28: =((1+AVERAGE('BS & FCF'!CH11:CI11))^1/4)*CI29 -> 0 | CJ28: =((1+AVERAGE('BS & FCF'!CI11:CJ11))^1/4)*CJ29 -> 0 | CK28: =((1+AVERAGE('BS & FCF'!CJ11:CK11))^1/4)*CK29 -> 0 | CL28: =((1+AVERAGE('BS & FCF'!CK11:CL11))^1/4)*CL29 -> 0 | CM28: =SUM(CI28:CL28) -> 0 | CN28: =((1+AVERAGE('BS & FCF'!CM11:CN11))^1/4)*CN29 -> 0 | CO28: =((1+AVERAGE('BS & FCF'!CN11:CO11))^1/4)*CO29 -> 0 | CP28: =((1+AVERAGE('BS & FCF'!CO11:CP11))^1/4)*CP29 -> 0 | CQ28: =((1+AVERAGE('BS & FCF'!CP11:CQ11))^1/4)*CQ29 -> 0 | CR28: =SUM(CN28:CQ28) -> 0 | CS28: =((1+AVERAGE('BS & FCF'!CR11:CS11))^1/4)*CS29 -> 0 | CT28: =((1+AVERAGE('BS & FCF'!CS11:CT11))^1/4)*CT29 -> 0 | CU28: =((1+AVERAGE('BS & FCF'!CT11:CU11))^1/4)*CU29 -> 0 | CV28: =((1+AVERAGE('BS & FCF'!CU11:CV11))^1/4)*CV29 -> 0 | CW28: =SUM(CS28:CV28) -> 0 | CX28: =((1+AVERAGE('BS & FCF'!CW11:CX11))^1/4)*CX29 -> 0 | CY28: =((1+AVERAGE('BS & FCF'!CX11:CY11))^1/4)*CY29 -> 0 | CZ28: =((1+AVERAGE('BS & FCF'!CY11:CZ11))^1/4)*CZ29 -> 0 | DA28: =((1+AVERAGE('BS & FCF'!CZ11:DA11))^1/4)*DA29 -> 0 | DB28: =SUM(CX28:DA28) -> 0
A29: Avg. client financing rate (%) | B29: =IFERROR((1-B28/AVERAGE('BS & FCF'!A11:B11))^4-1,0) -> 0 | C29: =IFERROR((1-C28/AVERAGE('BS & FCF'!B11:C11))^4-1,0) -> 0 | D29: =IFERROR((1-D28/AVERAGE('BS & FCF'!C11:D11))^4-1,0) -> 0 | E29: =IFERROR((1-E28/AVERAGE('BS & FCF'!D11:E11))^4-1,0) -> 0 | F29: =IFERROR(-F28/AVERAGE('BS & FCF'!B11:E11),0) -> 0 | G29: =IFERROR((1-G28/AVERAGE('BS & FCF'!F11:G11))^4-1,0) -> 0 | H29: =IFERROR((1-H28/AVERAGE('BS & FCF'!G11:H11))^4-1,0) -> 0 | I29: =IFERROR((1-I28/AVERAGE('BS & FCF'!H11:I11))^4-1,0) -> 0 | J29: =IFERROR((1-J28/AVERAGE('BS & FCF'!I11:J11))^4-1,0) -> 0 | K29: =IFERROR(-K28/AVERAGE('BS & FCF'!G11:J11),0) -> 0 | L29: =IFERROR((1-L28/AVERAGE('BS & FCF'!K11:L11))^4-1,0) -> 0 | M29: =IFERROR((1-M28/AVERAGE('BS & FCF'!L11:M11))^4-1,0) -> 0 | N29: =IFERROR((1-N28/AVERAGE('BS & FCF'!M11:N11))^4-1,0) -> 0 | O29: =IFERROR((1-O28/AVERAGE('BS & FCF'!N11:O11))^4-1,0) -> 0 | P29: =IFERROR(-P28/AVERAGE('BS & FCF'!L11:O11),0) -> 0 | Q29: =IFERROR((1-Q28/AVERAGE('BS & FCF'!P11:Q11))^4-1,0) -> 0 | R29: =IFERROR((1-R28/AVERAGE('BS & FCF'!Q11:R11))^4-1,0) -> 0 | S29: =IFERROR((1-S28/AVERAGE('BS & FCF'!R11:S11))^4-1,0) -> 0 | T29: =IFERROR((1-T28/AVERAGE('BS & FCF'!S11:T11))^4-1,0) -> 0 | U29: =IFERROR(-U28/AVERAGE('BS & FCF'!Q11:T11),0) -> 0 | V29: =IFERROR((1-V28/AVERAGE('BS & FCF'!U11:V11))^4-1,0) -> 0 | W29: =IFERROR((1-W28/AVERAGE('BS & FCF'!V11:W11))^4-1,0) -> 0 | X29: =IFERROR((1-X28/AVERAGE('BS & FCF'!W11:X11))^4-1,0) -> 0 | Y29: =IFERROR((1-Y28/AVERAGE('BS & FCF'!X11:Y11))^4-1,0) -> 0 | Z29: =IFERROR(-Z28/AVERAGE('BS & FCF'!V11:Y11),0) -> 0 | AA29: =IFERROR((1-AA28/AVERAGE('BS & FCF'!Z11:AA11))^4-1,0) -> 0 | AB29: =IFERROR((1-AB28/AVERAGE('BS & FCF'!AA11:AB11))^4-1,0) -> 0 | AC29: =IFERROR((1-AC28/AVERAGE('BS & FCF'!AB11:AC11))^4-1,0) -> 0 | AD29: =IFERROR((1-AD28/AVERAGE('BS & FCF'!AC11:AD11))^4-1,0) -> 0 | AE29: =IFERROR(-AE28/AVERAGE('BS & FCF'!AA11:AD11),0) -> 0 | AF29: =IFERROR((1-AF28/AVERAGE('BS & FCF'!AE11:AF11))^4-1,0) -> 0 | AG29: =IFERROR((1-AG28/AVERAGE('BS & FCF'!AF11:AG11))^4-1,0) -> 0 | AH29: =IFERROR((1-AH28/AVERAGE('BS & FCF'!AG11:AH11))^4-1,0) -> 0 | AI29: =IFERROR((1-AI28/AVERAGE('BS & FCF'!AH11:AI11))^4-1,0) -> 0 | AJ29: =IFERROR(-AJ28/AVERAGE('BS & FCF'!AF11:AI11),0) -> 0 | AK29: =IFERROR((1-AK28/AVERAGE('BS & FCF'!AJ11:AK11))^4-1,0) -> 0 | AL29: =IFERROR((1-AL28/AVERAGE('BS & FCF'!AK11:AL11))^4-1,0) -> 0 | AM29: =IFERROR((1-AM28/AVERAGE('BS & FCF'!AL11:AM11))^4-1,0) -> 0 | AN29: =IFERROR((1-AN28/AVERAGE('BS & FCF'!AM11:AN11))^4-1,0) -> 0 | AO29: =IFERROR(-AO28/AVERAGE('BS & FCF'!AK11:AN11),0) -> 0 | AP29: =IFERROR((1-AP28/AVERAGE('BS & FCF'!AO11:AP11))^4-1,0) -> 0 | AQ29: =IFERROR((1-AQ28/AVERAGE('BS & FCF'!AP11:AQ11))^4-1,0) -> 0 | AR29: =IFERROR((1-AR28/AVERAGE('BS & FCF'!AQ11:AR11))^4-1,0) -> 0 | AS29: =IFERROR((1-AS28/AVERAGE('BS & FCF'!AR11:AS11))^4-1,0) -> 0 | AT29: =IFERROR(-AT28/AVERAGE('BS & FCF'!AP11:AS11),0) -> 0 | AU29: =IFERROR((1-AU28/AVERAGE('BS & FCF'!AT11:AU11))^4-1,0) -> 0 | AV29: =IFERROR((1-AV28/AVERAGE('BS & FCF'!AU11:AV11))^4-1,0) -> 0 | AW29: =IFERROR((1-AW28/AVERAGE('BS & FCF'!AV11:AW11))^4-1,0) -> 0 | AX29: =IFERROR((1-AX28/AVERAGE('BS & FCF'!AW11:AX11))^4-1,0) -> 0 | AY29: =IFERROR(-AY28/AVERAGE('BS & FCF'!AU11:AX11),0) -> 0 | AZ29: =IFERROR((1-AZ28/AVERAGE('BS & FCF'!AY11:AZ11))^4-1,0) -> 0 | BA29: =IFERROR((1-BA28/AVERAGE('BS & FCF'!AZ11:BA11))^4-1,0) -> 0 | BB29: =IFERROR((1-BB28/AVERAGE('BS & FCF'!BA11:BB11))^4-1,0) -> 0 | BC29: =IFERROR((1-BC28/AVERAGE('BS & FCF'!BB11:BC11))^4-1,0) -> 0 | BD29: =IFERROR(-BD28/AVERAGE('BS & FCF'!AZ11:BC11),0) -> 0 | BE29: =IFERROR((1-BE28/AVERAGE('BS & FCF'!BD11:BE11))^4-1,0) -> 0 | BF29: =IFERROR((1-BF28/AVERAGE('BS & FCF'!BE11:BF11))^4-1,0) -> 0 | BG29: =IFERROR((1-BG28/AVERAGE('BS & FCF'!BF11:BG11))^4-1,0) -> 0 | BH29: =IFERROR((1-BH28/AVERAGE('BS & FCF'!BG11:BH11))^4-1,0) -> 0 | BI29: =IFERROR(-BI28/AVERAGE('BS & FCF'!BE11:BH11),0) -> 0 | BJ29: =IFERROR((1-BJ28/AVERAGE('BS & FCF'!BI11:BJ11))^4-1,0) -> 0 | BK29: =IFERROR((1-BK28/AVERAGE('BS & FCF'!BJ11:BK11))^4-1,0) -> 0 | BL29: =IFERROR((1-BL28/AVERAGE('BS & FCF'!BK11:BL11))^4-1,0) -> 0 | BM29: =IFERROR((1-BM28/AVERAGE('BS & FCF'!BL11:BM11))^4-1,0) -> 0 | BN29: =IFERROR(-BN28/AVERAGE('BS & FCF'!BJ11:BM11),0) -> 0 | BO29: =IFERROR((1-BO28/AVERAGE('BS & FCF'!BN11:BO11))^4-1,0) -> 0 | BP29: =IFERROR((1-BP28/AVERAGE('BS & FCF'!BO11:BP11))^4-1,0) -> 0 | BQ29: =IFERROR((1-BQ28/AVERAGE('BS & FCF'!BP11:BQ11))^4-1,0) -> 0 | BR29: =IFERROR((1-BR28/AVERAGE('BS & FCF'!BQ11:BR11))^4-1,0) -> 0 | BS29: =IFERROR(-BS28/AVERAGE('BS & FCF'!BO11:BR11),0) -> 0 | BT29: =IFERROR((1-BT28/AVERAGE('BS & FCF'!BS11:BT11))^4-1,0) -> 0 | BU29: =IFERROR((1-BU28/AVERAGE('BS & FCF'!BT11:BU11))^4-1,0) -> 0 | BV29: =IFERROR((1-BV28/AVERAGE('BS & FCF'!BU11:BV11))^4-1,0) -> 0 | BW29: =IFERROR((1-BW28/AVERAGE('BS & FCF'!BV11:BW11))^4-1,0) -> 0 | BX29: =IFERROR(-BX28/AVERAGE('BS & FCF'!BT11:BW11),0) -> 0 | BY29: =IFERROR((1+BY28/AVERAGE('BS & FCF'!BX11:BY11))^4-1,0) -> 0 | BZ29: =IFERROR((1-BZ28/AVERAGE('BS & FCF'!BY11:BZ11))^4-1,0) -> 0 | CA29: =IFERROR((1-CA28/AVERAGE('BS & FCF'!BZ11:CA11))^4-1,0) -> 0 | CB29: =IFERROR((1-CB28/AVERAGE('BS & FCF'!CA11:CB11))^4-1,0) -> 0 | CC29: =IFERROR(CC28/AVERAGE('BS & FCF'!BY11:CB11),0) -> 0 | CD29: =IFERROR((1+CD28/AVERAGE('BS & FCF'!CC11:CD11))^4-1,0) -> 0 | CE29: =IFERROR((1-CE28/AVERAGE('BS & FCF'!CD11:CE11))^4-1,0) -> 0 | CF29: =CE29 -> 0 | CG29: =CF29 -> 0 | CH29: =IFERROR(CH28/AVERAGE('BS & FCF'!CD11:CG11),0) -> 0 | CI29: =CG29 -> 0 | CJ29: =CI29 -> 0 | CK29: =CJ29 -> 0 | CL29: =CK29 -> 0 | CM29: =IFERROR(CM28/AVERAGE('BS & FCF'!CI11:CL11),0) -> 0 | CN29: =CL29 -> 0 | CO29: =CN29 -> 0 | CP29: =CO29 -> 0 | CQ29: =CP29 -> 0 | CR29: =IFERROR(CR28/AVERAGE('BS & FCF'!CN11:CQ11),0) -> 0 | CS29: =CQ29 -> 0 | CT29: =CS29 -> 0 | CU29: =CT29 -> 0 | CV29: =CU29 -> 0 | CW29: =IFERROR(CW28/AVERAGE('BS & FCF'!CS11:CV11),0) -> 0 | CX29: =CV29 -> 0 | CY29: =CX29 -> 0 | CZ29: =CY29 -> 0 | DA29: =CZ29 -> 0 | DB29: =IFERROR(DB28/AVERAGE('BS & FCF'!CX11:DA11),0) -> 0
A30: Other Operating Expenses | B30: =B31+B32+B33 -> -18319 | C30: =C31+C32+C33 -> -10848 | D30: =D31+D32+D33 -> -11262 | E30: =E31+E32+E33 -> -19250 | F30: =SUM(B30:E30) -> -59679 | G30: =G31+G32+G33 -> -2558 | H30: =H31+H32+H33 -> -2360 | I30: =I31+I32+I33 -> -5676 | J30: =J31+J32+J33 -> -36765 | K30: =SUM(G30:J30) -> -47359 | L30: =L31+L32+L33 -> -26056 | M30: =M31+M32+M33 -> -14249 | N30: =N31+N32+N33 -> -12641 | O30: =O31+O32+O33 -> -2202 | P30: =SUM(L30:O30) -> -55148 | Q30: =Q31+Q32+Q33 -> -15625 | R30: =R31+R32+R33 -> -20556 | S30: =S31+S32+S33 -> -11063 | T30: =T31+T32+T33 -> -9794 | U30: =SUM(Q30:T30) -> -57038 | V30: =V31+V32+V33 -> -14758 | W30: =W31+W32+W33 -> -16717 | X30: =X31+X32+X33 -> -32302 | Y30: =Y31+Y32+Y33 -> -51022 | Z30: =SUM(V30:Y30) -> -114799 | AA30: =AA31+AA32+AA33 -> -28353 | AB30: =AB31+AB32+AB33 -> 3216 | AC30: =AC31+AC32+AC33 -> -1513 | AD30: =AD31+AD32+AD33 -> -26931 | AE30: =SUM(AA30:AD30) -> -53581 | AF30: =AF31+AF32+AF33 -> -11807 | AG30: =AG31+AG32+AG33 -> -18604 | AH30: =AH31+AH32+AH33 -> -19828 | AI30: =AI31+AI32+AI33 -> -50573 | AJ30: =SUM(AF30:AI30) -> -100812 | AK30: =AK31+AK32+AK33 -> -14495 | AL30: =AL31+AL32+AL33 -> -149746 | AM30: =AM31+AM32+AM33 -> 16317 | AN30: =AN31+AN32+AN33 -> -23157 | AO30: =SUM(AK30:AN30) -> -171081 | AP30: =AP31+AP32+AP33 -> -4672 | AQ30: =AQ31+AQ32+AQ33 -> -36070 | AR30: =AR31+AR32+AR33 -> -133002 | AS30: =AS31+AS32+AS33 -> -54971 | AT30: =SUM(AP30:AS30) -> -228715 | AU30: =AU31+AU32+AU33 -> -27820 | AV30: =AV31+AV32+AV33 -> 1272 | AW30: =AW31+AW32+AW33 -> -22314 | AX30: =AX31+AX32+AX33 -> 19528 | AY30: =SUM(AU30:AX30) -> -29334 | AZ30: =AZ31+AZ32+AZ33 -> -40355 | BA30: =BA31+BA32+BA33 -> -20788 | BB30: =BB31+BB32+BB33 -> 1123896 | BC30: =BC31+BC32+BC33 -> 26862 | BD30: =SUM(AZ30:BC30) -> 1089615 | BE30: =BE31+BE32+BE33 -> -31171 | BF30: =BF31+BF32+BF33 -> -14738 | BG30: =BG31+BG32+BG33 -> -35335 | BH30: =BH31+BH32+BH33 -> -9530 | BI30: =SUM(BE30:BH30) -> -90774 | BJ30: =BJ31+BJ32+BJ33 -> -30483 | BK30: =BK31+BK32+BK33 -> -21795 | BL30: =BL31+BL32+BL33 -> 27790 | BM30: =BM31+BM32+BM33 -> 13030 | BN30: =SUM(BJ30:BM30) -> -11458 | BO30: =BO31+BO32+BO33 -> -37625 | BP30: =BP31+BP32+BP33 -> 16531 | BQ30: =BQ31+BQ32+BQ33 -> -54025 | BR30: =BR31+BR32+BR33 -> -25956 | BS30: =SUM(BO30:BR30) -> -101075 | BT30: =BT31+BT32+BT33 -> -18668 | BU30: =BU31+BU32+BU33 -> -10492 | BV30: =BV31+BV32+BV33 -> -3423 | BW30: =BW31+BW32+BW33 -> 58296 | BX30: =SUM(BT30:BW30) -> 25713 | BY30: =BY31+BY32+BY33 -> -70720 | BZ30: =BZ31+BZ32+BZ33 -> -38346 | CA30: =CA31+CA32+CA33 -> 188788 | CB30: =CB31+CB32+CB33 -> -71050 | CC30: =SUM(BY30:CB30) -> 8672 | CD30: =CD31+CD32+CD33 -> -64455 | CE30: =CE31+CE32+CE33 -> -68131 | CF30: =CF31+CF32+CF33 -> -82962.332 | CG30: =CG31+CG32+CG33 -> -86310.812 | CH30: =SUM(CD30:CG30) -> -301859.14 | CI30: =CI31+CI32+CI33 -> -83916.933 | CJ30: =CJ31+CJ32+CJ33 -> -84989.257 | CK30: =CK31+CK32+CK33 -> -87374.494 | CL30: =CL31+CL32+CL33 -> -90036.436 | CM30: =SUM(CI30:CL30) -> -346317.12 | CN30: =CN31+CN32+CN33 -> -90087.214 | CO30: =CO31+CO32+CO33 -> -90887.306 | CP30: =CP31+CP32+CP33 -> -93064.881 | CQ30: =CQ31+CQ32+CQ33 -> -96595.341 | CR30: =SUM(CN30:CQ30) -> -370634.74 | CS30: =CS31+CS32+CS33 -> -95646.202 | CT30: =CT31+CT32+CT33 -> -96201.711 | CU30: =CU31+CU32+CU33 -> -98218.101 | CV30: =CV31+CV32+CV33 -> -101701.94 | CW30: =SUM(CS30:CV30) -> -391767.96 | CX30: =CX31+CX32+CX33 -> -100651.91 | CY30: =CY31+CY32+CY33 -> -101074.25 | CZ30: =CZ31+CZ32+CZ33 -> -103073.52 | DA30: =DA31+DA32+DA33 -> -106572.21 | DB30: =SUM(CX30:DA30) -> -411371.88
A31: Expenses | B31: =1 -> 1 | C31: =68 -> 68 | D31: 60 | E31: -275 | F31: =SUM(B31:E31) -> -146 | G31: 828 | H31: 1171 | I31: 198 | J31: 0 | K31: =SUM(G31:J31) -> 2197 | L31: =-13127-M31 -> -5149 | M31: -7978 | N31: -10333 | O31: =-18739-N31-M31-L31 -> 4721 | P31: =SUM(L31:O31) -> -18739 | Q31: =-19410-R31 -> -9467 | R31: =-15943-R33 -> -9943 | S31: -8785 | T31: =-31457-S31-R31-Q31 -> -3262 | U31: =SUM(Q31:T31) -> -31457 | V31: -10095 | W31: -10485 | X31: -26960 | Y31: =-93195-X31-W31-V31 -> -45655 | Z31: =SUM(V31:Y31) -> -93195 | AA31: -23928 | AB31: 8873 | AC31: 3183 | AD31: =-31977-AC31-AB31-AA31 -> -20105 | AE31: =SUM(AA31:AD31) -> -31977 | AF31: -4807 | AG31: -10914 | AH31: -8575 | AI31: =-43869-AH31-AG31-AF31 -> -19573 | AJ31: =SUM(AF31:AI31) -> -43869 | AK31: 6847 | AL31: -121085 | AM31: =12013+15179 -> 27192 | AN31: =89804-194350-AM31-AL31-AK31 -> -17500 | AO31: =SUM(AK31:AN31) -> -104546 | AP31: =52786-41771+180 -> 11195 | AQ31: =20547-47033 -> -26486 | AR31: =35318-157445 -> -122127 | AS31: =27831-263185-AR31-AQ31-AP31+48008 -> -49928 | AT31: =SUM(AP31:AS31) -> -187346 | AU31: =6551-10012 -> -3461 | AV31: =8726-15335 -> -6609 | AW31: =34431-25207 -> 9224 | AX31: =-24458+110587-46506+5721-AW31-AV31-AU31 -> 46190 | AY31: =SUM(AU31:AX31) -> 45344 | AZ31: =44875-68031 -> -23156 | BA31: =10194-17257 -> -7063 | BB31: =1367584-109725-(1403000-250000+375000-250000) -> -20141 | BC31: =1492096-226318-BB31-BA31-AZ31-(1403000-250000+375000-250000) -> 38138 | BD31: =SUM(AZ31:BC31) -> -12222 | BE31: =2155-22394 -> -20239 | BF31: =5674-9950 -> -4276 | BG31: =47195-71510 -> -24315 | BH31: =79487-130238-BG31-BF31-BE31 -> -1921 | BI31: =SUM(BE31:BH31) -> -50751 | BJ31: =13339-35290 -> -21951 | BK31: =18890-31434 -> -12544 | BL31: =201308-150686 -> 50622 | BM31: =325209-293193-BL31-BK31-BJ31 -> 15889 | BN31: =SUM(BJ31:BM31) -> 32016 | BO31: =8303-16644 -> -8341 | BP31: =90079-57477 -> 32602 | BQ31: =26088-37811 -> -11723 | BR31: =123166-157153-BQ31-BP31-BO31 -> -46525 | BS31: =SUM(BO31:BR31) -> -33987 | BT31: =50588-45618 -> 4970 | BU31: =90642-84769 -> 5873 | BV31: =111059-74483-BV33 -> -55424 | BW31: =405906-372134-BV31-BU31-BT31 -> 78353 | BX31: =SUM(BT31:BW31) -> 33772 | BY31: =3278-43726 -> -40448 | BZ31: =26238-40782 -> -14544 | CA31: =270767-53350-CA33 -> 4417 | CB31: =424091-282844-CA31-BZ31-BY31-SUM(BY33:CB33) -> -91178 | CC31: =SUM(BY31:CB31) -> -141753 | CD31: =21481-31353 -> -9872 | CE31: =8744-35709 -> -26965 | CF31: =-1.5%*CF5 -> -40166.661 | CG31: =-1.5%*CG5 -> -43236.682 | CH31: =SUM(CD31:CG31) -> -120240.34 | CI31: =-1.5%*CI5 -> -40562.533 | CJ31: =-1.5%*CJ5 -> -41352.762 | CK31: =-1.5%*CK5 -> -43454.069 | CL31: =-1.5%*CL5 -> -45830.233 | CM31: =SUM(CI31:CL31) -> -171199.6 | CN31: =-1.5%*CN5 -> -45593.375 | CO31: =-1.5%*CO5 -> -46103.958 | CP31: =-1.5%*CP5 -> -47990.141 | CQ31: =-1.5%*CQ5 -> -51227.313 | CR31: =SUM(CN31:CQ31) -> -190914.79 | CS31: =-1.5%*CS5 -> -49982.977 | CT31: =-1.5%*CT5 -> -50241.369 | CU31: =-1.5%*CU5 -> -51958.708 | CV31: =-1.5%*CV5 -> -55141.555 | CW31: =SUM(CS31:CV31) -> -207324.61 | CX31: =-1.5%*CX5 -> -53788.561 | CY31: =-1.5%*CY5 -> -53905.975 | CZ31: =-1.5%*CZ5 -> -55598.344 | DA31: =-1.5%*DA5 -> -58788.118 | DB31: =SUM(CX31:DA31) -> -222081
A32: D&A | B32: =-B64 -> -18320 | C32: =-C64 -> -10916 | D32: =-D64 -> -11322 | E32: =-E64 -> -18975 | F32: =SUM(B32:E32) -> -59533 | G32: =-741-2645 -> -3386 | H32: =-1940-4977-G32 -> -3531 | I32: =-5926-6865-G32-H32 -> -5874 | J32: =-6826-6510-G32-H32-I32 -> -545 | K32: =SUM(G32:J32) -> -13336 | L32: =-4139-5039-M32 -> -2907 | M32: =-2562-3709 -> -6271 | N32: -2308 | O32: =-9228-9181-L32-M32-N32 -> -6923 | P32: =SUM(L32:O32) -> -18409 | Q32: =-6024-4747-R32 -> -6158 | R32: =-2286-2327 -> -4613 | S32: -2278 | T32: =-10186-9395-SUM(Q32:S32) -> -6532 | U32: =SUM(Q32:T32) -> -19581 | V32: =-2303-2360 -> -4663 | W32: -6232 | X32: -5342 | Y32: =-21604-SUM(V32:X32) -> -5367 | Z32: =SUM(V32:Y32) -> -21604 | AA32: -4425 | AB32: -5657 | AC32: -4696 | AD32: =-21604-SUM(AA32:AC32) -> -6826 | AE32: =SUM(AA32:AD32) -> -21604 | AF32: -7000 | AG32: -7690 | AH32: -11253 | AI32: -31000 | AJ32: =SUM(AF32:AI32) -> -56943 | AK32: =-AK64 -> -21342 | AL32: =-AL64 -> -28661 | AM32: -10875 | AN32: =-55495-11040-SUM(AK32:AM32) -> -5657 | AO32: =SUM(AK32:AN32) -> -66535 | AP32: =-AP64 -> -15867 | AQ32: =-AQ64 -> -9584 | AR32: -10875 | AS32: =-61369-SUM(AP32:AR32) -> -25043 | AT32: =SUM(AP32:AS32) -> -61369 | AU32: =-AU64 -> -24359 | AV32: =-AV64 -> 7881 | AW32: =-AW64 -> -31538 | AX32: =-74678-SUM(AU32:AW32) -> -26662 | AY32: =SUM(AU32:AX32) -> -74678 | AZ32: =-AZ64 -> -17199 | BA32: =-BA64 -> -13725 | BB32: =-BB64 -> -8963 | BC32: =-51163-SUM(AZ32:BB32) -> -11276 | BD32: =SUM(AZ32:BC32) -> -51163 | BE32: =-BE64 -> -10932 | BF32: =-BF64 -> -10462 | BG32: =-BG64 -> -11020 | BH32: =-40023-SUM(BE32:BG32) -> -7609 | BI32: =SUM(BE32:BH32) -> -40023 | BJ32: =-BJ64 -> -8532 | BK32: =-BK64 -> -9251 | BL32: =-BL64 -> -22832 | BM32: =-43474-SUM(BJ32:BL32) -> -2859 | BN32: =SUM(BJ32:BM32) -> -43474 | BO32: =-BO64 -> -29284 | BP32: =-BP64 -> -16071 | BQ32: =-BQ64 -> -42302 | BR32: =-67088-SUM(BO32:BQ32) -> 20569 | BS32: =SUM(BO32:BR32) -> -67088 | BT32: =-BT64 -> -23638 | BU32: =-BU64 -> -16365 | BV32: =-BV64 -> -39999 | BW32: =-BW64 -> -20057 | BX32: =SUM(BT32:BW32) -> -100059 | BY32: =-BY64 -> -30272 | BZ32: =-BZ64 -> -23802 | CA32: =-CA64 -> -28629 | CB32: =-CB64 -> -49872 | CC32: =SUM(BY32:CB32) -> -132575 | CD32: =-CD64 -> -54583 | CE32: =-CE64 -> -41166 | CF32: =CE32*CF64/CE64 -> -42795.671 | CG32: =CF32*CG64/CF64 -> -43074.13 | CH32: =SUM(CD32:CG32) -> -181618.8 | CI32: =CH32*CI64/CH64 -> -43354.4 | CJ32: =CI32*CJ64/CI64 -> -43636.495 | CK32: =CJ32*CK64/CJ64 -> -43920.425 | CL32: =CK32*CL64/CK64 -> -44206.202 | CM32: =SUM(CI32:CL32) -> -175117.52 | CN32: =CM32*CN64/CM64 -> -44493.839 | CO32: =CN32*CO64/CN64 -> -44783.348 | CP32: =CO32*CP64/CO64 -> -45074.74 | CQ32: =CP32*CQ64/CP64 -> -45368.028 | CR32: =SUM(CN32:CQ32) -> -179719.96 | CS32: =CR32*CS64/CR64 -> -45663.225 | CT32: =CS32*CT64/CS64 -> -45960.342 | CU32: =CT32*CU64/CT64 -> -46259.393 | CV32: =CU32*CV64/CU64 -> -46560.389 | CW32: =SUM(CS32:CV32) -> -184443.35 | CX32: =CW32*CX64/CW64 -> -46863.344 | CY32: =CX32*CY64/CX64 -> -47168.27 | CZ32: =CY32*CZ64/CY64 -> -47475.181 | DA32: =CZ32*DA64/CZ64 -> -47784.088 | DB32: =SUM(CX32:DA32) -> -189290.88
A33: Extraordinary items | B33: 0 | D33: 0 | E33: 0 | F33: =SUM(B33:E33) -> 0 | G33: 0 | H33: 0 | I33: 0 | J33: =-34023-G31-H31-I31 -> -36220 | K33: =SUM(G33:J33) -> -36220 | L33: -18000 | M33: 0 | N33: 0 | O33: 0 | P33: =SUM(L33:O33) -> -18000 | Q33: 0 | R33: -6000 | S33: 0 | T33: 0 | U33: =SUM(Q33:T33) -> -6000 | V33: 0 | W33: 0 | X33: 0 | Y33: 0 | Z33: =SUM(V33:Y33) -> 0 | AA33: 0 | AB33: 0 | AC33: 0 | AD33: 0 | AE33: =SUM(AA33:AD33) -> 0 | AF33: 0 | AG33: 0 | AH33: 0 | AI33: 0 | AJ33: =SUM(AF33:AI33) -> 0 | AK33: 0 | AL33: 0 | AM33: 0 | AN33: 0 | AO33: =SUM(AK33:AN33) -> 0 | AP33: 0 | AQ33: 0 | AR33: 0 | AS33: =254000-167000-67000 -> 20000 | AT33: =SUM(AP33:AS33) -> 20000 | AU33: 0 | AV33: 0 | AW33: 0 | AX33: 0 | AY33: =SUM(AU33:AX33) -> 0 | AZ33: 0 | BA33: 0 | BB33: =1403000-250000 -> 1153000 | BC33: 0 | BD33: =SUM(AZ33:BC33) -> 1153000 | BE33: 0 | BF33: 0 | BG33: 0 | BH33: 0 | BI33: =SUM(BE33:BH33) -> 0 | BJ33: 0 | BK33: 0 | BL33: 0 | BM33: 0 | BN33: =SUM(BJ33:BM33) -> 0 | BO33: 0 | BP33: 0 | BQ33: 0 | BR33: 0 | BS33: =SUM(BO33:BR33) -> 0 | BT33: 0 | BU33: 0 | BV33: =115000*0.8 -> 92000 | BW33: 0 | BX33: =SUM(BT33:BW33) -> 92000 | BY33: 0 | BZ33: 0 | CA33: 213000 | CB33: 70000 | CC33: =SUM(BY33:CB33) -> 283000 | CD33: 0 | CE33: 0 | CF33: 0 | CG33: 0 | CH33: =SUM(CD33:CG33) -> 0 | CI33: 0 | CJ33: 0 | CK33: 0 | CL33: 0 | CM33: =SUM(CI33:CL33) -> 0 | CN33: 0 | CO33: 0 | CP33: 0 | CQ33: 0 | CR33: =SUM(CN33:CQ33) -> 0 | CS33: 0 | CT33: 0 | CU33: 0 | CV33: 0 | CW33: =SUM(CS33:CV33) -> 0 | CX33: 0 | CY33: 0 | CZ33: 0 | DA33: 0 | DB33: =SUM(CX33:DA33) -> 0
A34: Equity Income | B34: =236-15877 -> -15641 | C34: 0 | D34: =167-10921 -> -10754 | E34: =579-7314 -> -6735 | F34: =SUM(B34:E34) -> -33130 | G34: =-3193+250 -> -2943 | H34: =-3293+491 -> -2802 | I34: =-4399+183 -> -4216 | J34: =-54858+1449-G34-H34-I34 -> -43448 | K34: =SUM(G34:J34) -> -53409 | L34: =41443-M34 -> 2108 | M34: =39335 -> 39335 | N34: =9719-13751 -> -4032 | O34: =-31731+64027-N34-M34-L34-L33 -> 12885 | P34: =SUM(L34:O34) -> 50296 | Q34: =25968+15648-R34 -> 21718 | R34: =12865+7033 -> 19898 | S34: =23195-2231 -> 20964 | T34: =90094+16536-SUM(Q34:S34) -> 44050 | U34: =SUM(Q34:T34) -> 106630 | V34: =6853-2545 -> 4308 | W34: =28886+2882 -> 31768 | X34: =35253+2528 -> 37781 | Y34: =118221+436-SUM(V34:X34) -> 44800 | Z34: =SUM(V34:Y34) -> 118657 | AA34: =8606+2814 -> 11420 | AB34: =22274-6292 -> 15982 | AC34: =28608+2422 -> 31030 | AD34: =73645+6-SUM(AA34:AC34) -> 15219 | AE34: =SUM(AA34:AD34) -> 73651 | AF34: =6821+61 -> 6882 | AG34: =13992-1256 -> 12736 | AH34: =-1606+7401 -> 5795 | AI34: =49438+10288-SUM(AF34:AH34) -> 34313 | AJ34: =SUM(AF34:AI34) -> 59726 | AK34: 1752 | AL34: =19303+15047 -> 34350 | AM34: =25084 -> 25084 | AN34: =73690+53675-SUM(AK34:AM34) -> 66179 | AO34: =SUM(AK34:AN34) -> 127365 | AP34: 10149 | AQ34: 14024 | AR34: 22686 | AS34: =107654-SUM(AP34:AR34) -> 60795 | AT34: =SUM(AP34:AS34) -> 107654 | AU34: -842 | AV34: 51491 | AW34: =86429-SUM(AU34:AV34) -> 35780 | AX34: =104200-SUM(AU34:AW34) -> 17771 | AY34: =SUM(AU34:AX34) -> 104200 | AZ34: 10692 | BA34: 21467 | BB34: =314800-250000 -> 64800 | BC34: =405712-SUM(AZ34:BB34)-250000 -> 58753 | BD34: =SUM(AZ34:BC34) -> 155712 | BE34: 79017 | BF34: 74405 | BG34: 78321 | BH34: =297167-SUM(BE34:BG34) -> 65424 | BI34: =SUM(BE34:BH34) -> 297167 | BJ34: 60334 | BK34: 38724 | BL34: 59701 | BM34: =217085-SUM(BJ34:BL34) -> 58326 | BN34: =SUM(BJ34:BM34) -> 217085 | BO34: 47138 | BP34: 33021 | BQ34: 89430 | BR34: =262059-SUM(BO34:BQ34) -> 92470 | BS34: =SUM(BO34:BR34) -> 262059 | BT34: 100891 | BU34: 116467 | BV34: 135914 | BW34: =500880-SUM(BT34:BV34) -> 147608 | BX34: =SUM(BT34:BW34) -> 500880 | BY34: 112558 | BZ34: 139609 | CA34: 131891 | CB34: =548106-SUM(BY34:CA34) -> 164048 | CC34: =SUM(BY34:CB34) -> 548106 | CD34: 128141 | CE34: 106557 | CF34: ='Joint-Ventures'!CF8 -> 154463.81 | CG34: ='Joint-Ventures'!CG8 -> 188103.31 | CH34: =SUM(CD34:CG34) -> 577265.13 | CI34: ='Joint-Ventures'!CI8 -> 173748.47 | CJ34: ='Joint-Ventures'!CJ8 -> 163141.62 | CK34: ='Joint-Ventures'!CK8 -> 194877.06 | CL34: ='Joint-Ventures'!CL8 -> 207115.1 | CM34: =SUM(CI34:CL34) -> 738882.25 | CN34: ='Joint-Ventures'!CN8 -> 204977.09 | CO34: ='Joint-Ventures'!CO8 -> 185908.05 | CP34: ='Joint-Ventures'!CP8 -> 217881.72 | CQ34: ='Joint-Ventures'!CQ8 -> 229813.33 | CR34: =SUM(CN34:CQ34) -> 838580.18 | CS34: ='Joint-Ventures'!CS8 -> 228042.68 | CT34: ='Joint-Ventures'!CT8 -> 200901.73 | CU34: ='Joint-Ventures'!CU8 -> 232629.31 | CV34: ='Joint-Ventures'!CV8 -> 241939.13 | CW34: =SUM(CS34:CV34) -> 903512.84 | CX34: ='Joint-Ventures'!CX8 -> 240504.28 | CY34: ='Joint-Ventures'!CY8 -> 210186.17 | CZ34: ='Joint-Ventures'!CZ8 -> 245975.78 | DA34: ='Joint-Ventures'!DA8 -> 256061.67 | DB34: =SUM(CX34:DA34) -> 952727.89
A35: Operating income | B35: =B16+B17 -> 215784 | C35: =C16+C17 -> 236231 | D35: =D16+D17 -> 235747 | E35: =E16+E17 -> 140148 | F35: =SUM(B35:E35) -> 827910 | G35: =G16+G17 -> 131959 | H35: =H16+H17 -> 153995 | I35: =I16+I17 -> 224935 | J35: =J16+J17 -> 269509 | K35: =SUM(G35:J35) -> 780398 | L35: =L16+L17 -> 226921 | M35: =M16+M17 -> 231469 | N35: =N16+N17 -> 214094 | O35: =O16+O17 -> 315885 | P35: =SUM(L35:O35) -> 988369 | Q35: =Q16+Q17 -> 235437 | R35: =R16+R17 -> 258296 | S35: =S16+S17 -> 260600 | T35: =T16+T17 -> 269557 | U35: =SUM(Q35:T35) -> 1023890 | V35: =V16+V17 -> 228596 | W35: =W16+W17 -> 250828 | X35: =X16+X17 -> 260340 | Y35: =Y16+Y17 -> 236643 | Z35: =SUM(V35:Y35) -> 976407 | AA35: =AA16+AA17 -> 141254 | AB35: =AB16+AB17 -> 208977 | AC35: =AC16+AC17 -> 198409 | AD35: =AD16+AD17 -> 141764 | AE35: =SUM(AA35:AD35) -> 690404 | AF35: =AF16+AF17 -> 107117 | AG35: =AG16+AG17 -> 71337 | AH35: =AH16+AH17 -> 61473 | AI35: =AI16+AI17 -> 78416 | AJ35: =SUM(AF35:AI35) -> 318343 | AK35: =AK16+AK17 -> 49697 | AL35: =AL16+AL17 -> -119981 | AM35: =AM16+AM17 -> 28451 | AN35: =AN16+AN17 -> 96463 | AO35: =SUM(AK35:AN35) -> 54630 | AP35: =AP16+AP17 -> -22900 | AQ35: =AQ16+AQ17 -> -4938 | AR35: =AR16+AR17 -> -78688 | AS35: =AS16+AS17 -> 181086 | AT35: =SUM(AP35:AS35) -> 74560 | AU35: =AU16+AU17 -> 79512 | AV35: =AV16+AV17 -> 161495 | AW35: =AW16+AW17 -> 142930 | AX35: =AX16+AX17 -> 236554 | AY35: =SUM(AU35:AX35) -> 620491 | AZ35: =AZ16+AZ17 -> 65085 | BA35: =BA16+BA17 -> 109257 | BB35: =BB16+BB17 -> 1436163 | BC35: =BC16+BC17 -> 303874 | BD35: =SUM(AZ35:BC35) -> 1914379 | BE35: =BE16+BE17 -> 226040 | BF35: =BF16+BF17 -> 311399 | BG35: =BG16+BG17 -> 292827 | BH35: =BH16+BH17 -> 275668 | BI35: =SUM(BE35:BH35) -> 1105934 | BJ35: =BJ16+BJ17 -> 197071 | BK35: =BK16+BK17 -> 192122 | BL35: =BL16+BL17 -> 342107 | BM35: =BM16+BM17 -> 250316 | BN35: =SUM(BJ35:BM35) -> 981616 | BO35: =BO16+BO17 -> 223037 | BP35: =BP16+BP17 -> 347849 | BQ35: =BQ16+BQ17 -> 345646 | BR35: =BR16+BR17 -> 345679 | BS35: =SUM(BO35:BR35) -> 1262211 | BT35: =BT16+BT17 -> 351844 | BU35: =BU16+BU17 -> 519244 | BV35: =BV16+BV17 -> 592708 | BW35: =BW16+BW17 -> 734686 | BX35: =SUM(BT35:BW35) -> 2198482 | BY35: =BY16+BY17 -> 437963 | BZ35: =BZ16+BZ17 -> 528736 | CA35: =CA16+CA17 -> 738803 | CB35: =CB16+CB17 -> 838358 | CC35: =SUM(BY35:CB35) -> 2543860 | CD35: =CD16+CD17 -> 411281 | CE35: =CE16+CE17 -> 573733 | CF35: =CF16+CF17 -> 657821.89 | CG35: =CG16+CG17 -> 749234.73 | CH35: =SUM(CD35:CG35) -> 2392070.6 | CI35: =CI16+CI17 -> 742687.04 | CJ35: =CJ16+CJ17 -> 698995.47 | CK35: =CK16+CK17 -> 723474.76 | CL35: =CL16+CL17 -> 799065.12 | CM35: =SUM(CI35:CL35) -> 2964222.4 | CN35: =CN16+CN17 -> 853691.38 | CO35: =CO16+CO17 -> 789888.91 | CP35: =CP16+CP17 -> 794820.56 | CQ35: =CQ16+CQ17 -> 870150.64 | CR35: =SUM(CN35:CQ35) -> 3308551.5 | CS35: =CS16+CS17 -> 918191.79 | CT35: =CT16+CT17 -> 849177.93 | CU35: =CU16+CU17 -> 855683.03 | CV35: =CV16+CV17 -> 928080.83 | CW35: =SUM(CS35:CV35) -> 3551133.6 | CX35: =CX16+CX17 -> 1003306.3 | CY35: =CY16+CY17 -> 923626.52 | CZ35: =CZ16+CZ17 -> 933041.15 | DA35: =DA16+DA17 -> 1011752.1 | DB35: =SUM(CX35:DA35) -> 3871726
A36: Non-operating income (expenses) | B36: -4987 | C36: -3544 | D36: -5038 | E36: 0 | F36: =SUM(B36:E36) -> -13569 | G36: 0 | H36: 0 | I36: 0 | J36: 0 | K36: =SUM(G36:J36) -> 0 | L36: 0 | M36: 0 | N36: 0 | O36: 0 | P36: =SUM(L36:O36) -> 0 | Q36: 0 | R36: 0 | S36: 0 | T36: 0 | U36: =SUM(Q36:T36) -> 0 | V36: 0 | W36: 0 | X36: 0 | Y36: 0 | Z36: =SUM(V36:Y36) -> 0 | AA36: 0 | AB36: 0 | AC36: 0 | AD36: 0 | AE36: =SUM(AA36:AD36) -> 0 | AF36: 0 | AG36: 0 | AH36: 0 | AI36: 0 | AJ36: =SUM(AF36:AI36) -> 0 | AK36: 0 | AL36: 0 | AM36: 0 | AN36: 0 | AO36: =SUM(AK36:AN36) -> 0 | AP36: 0 | AQ36: 0 | AR36: 0 | AS36: 0 | AT36: =SUM(AP36:AS36) -> 0 | AU36: 0 | AV36: 0 | AW36: 0 | AX36: 0 | AY36: =SUM(AU36:AX36) -> 0 | AZ36: 0 | BA36: 0 | BB36: 0 | BC36: 0 | BD36: =SUM(AZ36:BC36) -> 0 | BE36: 0 | BF36: 0 | BG36: 0 | BH36: 0 | BI36: =SUM(BE36:BH36) -> 0 | BJ36: 0 | BK36: 0 | BL36: 0 | BM36: 0 | BN36: =SUM(BJ36:BM36) -> 0 | BO36: 0 | BP36: 0 | BQ36: 0 | BR36: 0 | BS36: =SUM(BO36:BR36) -> 0 | BT36: 0 | BU36: 0 | BV36: 0 | BW36: 0 | BX36: =SUM(BT36:BW36) -> 0 | BY36: 0 | BZ36: 0 | CA36: 0 | CB36: 0 | CC36: =SUM(BY36:CB36) -> 0 | CD36: 0 | CE36: 0 | CF36: 0 | CG36: 0 | CH36: =SUM(CD36:CG36) -> 0 | CI36: 0 | CJ36: 0 | CK36: 0 | CL36: 0 | CM36: =SUM(CI36:CL36) -> 0 | CN36: 0 | CO36: 0 | CP36: 0 | CQ36: 0 | CR36: =SUM(CN36:CQ36) -> 0 | CS36: 0 | CT36: 0 | CU36: 0 | CV36: 0 | CW36: =SUM(CS36:CV36) -> 0 | CX36: 0 | CY36: 0 | CZ36: 0 | DA36: 0 | DB36: =SUM(CX36:DA36) -> 0
A37: Income before income tax | B37: =B35+B36 -> 210797 | C37: =C35+C36 -> 232687 | D37: =D35+D36 -> 230709 | E37: =E35+E36 -> 140148 | F37: =SUM(B37:E37) -> 814341 | G37: =G35+G36 -> 131959 | H37: =H35+H36 -> 153995 | I37: =I35+I36 -> 224935 | J37: =J35+J36 -> 269509 | K37: =SUM(G37:J37) -> 780398 | L37: =L35+L36 -> 226921 | M37: =M35+M36 -> 231469 | N37: =N35+N36 -> 214094 | O37: =O35+O36 -> 315885 | P37: =SUM(L37:O37) -> 988369 | Q37: =Q35+Q36 -> 235437 | R37: =R35+R36 -> 258296 | S37: =S35+S36 -> 260600 | T37: =T35+T36 -> 269557 | U37: =SUM(Q37:T37) -> 1023890 | V37: =V35+V36 -> 228596 | W37: =W35+W36 -> 250828 | X37: =X35+X36 -> 260340 | Y37: =Y35+Y36 -> 236643 | Z37: =SUM(V37:Y37) -> 976407 | AA37: =AA35+AA36 -> 141254 | AB37: =AB35+AB36 -> 208977 | AC37: =AC35+AC36 -> 198409 | AD37: =AD35+AD36 -> 141764 | AE37: =SUM(AA37:AD37) -> 690404 | AF37: =AF35+AF36 -> 107117 | AG37: =AG35+AG36 -> 71337 | AH37: =AH35+AH36 -> 61473 | AI37: =AI35+AI36 -> 78416 | AJ37: =SUM(AF37:AI37) -> 318343 | AK37: =AK35+AK36 -> 49697 | AL37: =AL35+AL36 -> -119981 | AM37: =AM35+AM36 -> 28451 | AN37: =AN35+AN36 -> 96463 | AO37: =SUM(AK37:AN37) -> 54630 | AP37: =AP35+AP36 -> -22900 | AQ37: =AQ35+AQ36 -> -4938 | AR37: =AR35+AR36 -> -78688 | AS37: =AS35+AS36 -> 181086 | AT37: =SUM(AP37:AS37) -> 74560 | AU37: =AU35+AU36 -> 79512 | AV37: =AV35+AV36 -> 161495 | AW37: =AW35+AW36 -> 142930 | AX37: =AX35+AX36 -> 236554 | AY37: =SUM(AU37:AX37) -> 620491 | AZ37: =AZ35+AZ36 -> 65085 | BA37: =BA35+BA36 -> 109257 | BB37: =BB35+BB36 -> 1436163 | BC37: =BC35+BC36 -> 303874 | BD37: =SUM(AZ37:BC37) -> 1914379 | BE37: =BE35+BE36 -> 226040 | BF37: =BF35+BF36 -> 311399 | BG37: =BG35+BG36 -> 292827 | BH37: =BH35+BH36 -> 275668 | BI37: =SUM(BE37:BH37) -> 1105934 | BJ37: =BJ35+BJ36 -> 197071 | BK37: =BK35+BK36 -> 192122 | BL37: =BL35+BL36 -> 342107 | BM37: =BM35+BM36 -> 250316 | BN37: =SUM(BJ37:BM37) -> 981616 | BO37: =BO35+BO36 -> 223037 | BP37: =BP35+BP36 -> 347849 | BQ37: =BQ35+BQ36 -> 345646 | BR37: =BR35+BR36 -> 345679 | BS37: =SUM(BO37:BR37) -> 1262211 | BT37: =BT35+BT36 -> 351844 | BU37: =BU35+BU36 -> 519244 | BV37: =BV35+BV36 -> 592708 | BW37: =BW35+BW36 -> 734686 | BX37: =SUM(BT37:BW37) -> 2198482 | BY37: =BY35+BY36 -> 437963 | BZ37: =BZ35+BZ36 -> 528736 | CA37: =CA35+CA36 -> 738803 | CB37: =CB35+CB36 -> 838358 | CC37: =SUM(BY37:CB37) -> 2543860 | CD37: =CD35+CD36 -> 411281 | CE37: =CE35+CE36 -> 573733 | CF37: =CF35+CF36 -> 657821.89 | CG37: =CG35+CG36 -> 749234.73 | CH37: =SUM(CD37:CG37) -> 2392070.6 | CI37: =CI35+CI36 -> 742687.04 | CJ37: =CJ35+CJ36 -> 698995.47 | CK37: =CK35+CK36 -> 723474.76 | CL37: =CL35+CL36 -> 799065.12 | CM37: =SUM(CI37:CL37) -> 2964222.4 | CN37: =CN35+CN36 -> 853691.38 | CO37: =CO35+CO36 -> 789888.91 | CP37: =CP35+CP36 -> 794820.56 | CQ37: =CQ35+CQ36 -> 870150.64 | CR37: =SUM(CN37:CQ37) -> 3308551.5 | CS37: =CS35+CS36 -> 918191.79 | CT37: =CT35+CT36 -> 849177.93 | CU37: =CU35+CU36 -> 855683.03 | CV37: =CV35+CV36 -> 928080.83 | CW37: =SUM(CS37:CV37) -> 3551133.6 | CX37: =CX35+CX36 -> 1003306.3 | CY37: =CY35+CY36 -> 923626.52 | CZ37: =CZ35+CZ36 -> 933041.15 | DA37: =DA35+DA36 -> 1011752.1 | DB37: =SUM(CX37:DA37) -> 3871726
A38: Income tax | B38: -23931 | C38: -15687 | D38: -29101 | E38: -33848 | F38: =SUM(B38:E38) -> -102567 | G38: -34565 | H38: -39626 | I38: -49893 | J38: =-178073-G38-H38-I38 -> -53989 | K38: =SUM(G38:J38) -> -178073 | L38: =-90450-M38 -> -42616 | M38: -47834 | N38: -41335 | O38: =-183130-L38-M38-N38 -> -51345 | P38: =SUM(L38:O38) -> -183130 | Q38: =-65574-R38 -> -29418 | R38: =-33111-R40 -> -36156 | S38: -33193 | T38: =-142835-SUM(Q38:S38) -> -44068 | U38: =SUM(Q38:T38) -> -142835 | V38: -35647 | W38: =-42613-W40 -> -34983 | X38: -36586 | Y38: =-139210-SUM(V38:X38) -> -31994 | Z38: =SUM(V38:Y38) -> -139210 | AA38: -32913 | AB38: =-23918-AB40 -> -31110 | AC38: -29243 | AD38: =-118474-SUM(AA38:AC38) -> -25208 | AE38: =SUM(AA38:AD38) -> -118474 | AF38: -20775 | AG38: -20557 | AH38: -17757 | AI38: =-83164-SUM(AF38:AH38) -> -24075 | AJ38: =SUM(AF38:AI38) -> -83164 | AK38: -21610 | AL38: -19338 | AM38: -20444 | AN38: =-82764-SUM(AK38:AM38) -> -21372 | AO38: =SUM(AK38:AN38) -> -82764 | AP38: -14173 | AQ38: -16481 | AR38: -18051 | AS38: =-67433-SUM(AP38:AR38) -> -18728 | AT38: =SUM(AP38:AS38) -> -67433 | AU38: -174 | AV38: 401 | AW38: -21871 | AX38: =-83217-SUM(AU38:AW38) -> -61573 | AY38: =SUM(AU38:AX38) -> -83217 | AZ38: -18306 | BA38: -13360 | BB38: =-129743-266545+375000 -> -21288 | BC38: =-197539-SUM(AZ38:BB38)+(-266545+375000) -> -36130 | BD38: =SUM(AZ38:BC38) -> -89084 | BE38: -17832 | BF38: -24464 | BG38: -24110 | BH38: =-93019-SUM(BE38:BG38) -> -26613 | BI38: =SUM(BE38:BH38) -> -93019 | BJ38: -25176 | BK38: -27899 | BL38: -35365 | BM38: =-121158-SUM(BJ38:BL38) -> -32718 | BN38: =SUM(BJ38:BM38) -> -121158 | BO38: -35951 | BP38: -33981 | BQ38: -35936 | BR38: =-143963-SUM(BO38:BQ38) -> -38095 | BS38: =SUM(BO38:BR38) -> -143963 | BT38: -34290 | BU38: -34111 | BV38: -44362 | BW38: =-158483-SUM(BT38:BV38) -> -45720 | BX38: =SUM(BT38:BW38) -> -158483 | BY38: -43072 | BZ38: -43481 | CA38: -54825 | CB38: =-197741-SUM(BY38:CA38) -> -56363 | CC38: =SUM(BY38:CB38) -> -197741 | CD38: -46053 | CE38: -52535 | CF38: =-CF39*(CF4+'BS & FCF'!CF96) -> -45970.686 | CG38: =-CG39*(CG4+'BS & FCF'!CG96) -> -50385.999 | CH38: =SUM(CD38:CG38) -> -194944.68 | CI38: =-CI39*(CI4+'BS & FCF'!CI96) -> -43076.288 | CJ38: =-CJ39*(CJ4+'BS & FCF'!CJ96) -> -52258.596 | CK38: =-CK39*(CK4+'BS & FCF'!CK96) -> -54564.295 | CL38: =-CL39*(CL4+'BS & FCF'!CL96) -> -58424.935 | CM38: =SUM(CI38:CL38) -> -208324.11 | CN38: =-CN39*(CN4+'BS & FCF'!CN96) -> -52825.118 | CO38: =-CO39*(CO4+'BS & FCF'!CO96) -> -57037.791 | CP38: =-CP39*(CP4+'BS & FCF'!CP96) -> -58968.999 | CQ38: =-CQ39*(CQ4+'BS & FCF'!CQ96) -> -65361.196 | CR38: =SUM(CN38:CQ38) -> -234193.1 | CS38: =-CS39*(CS4+'BS & FCF'!CS96) -> -61764.981 | CT38: =-CT39*(CT4+'BS & FCF'!CT96) -> -63646.101 | CU38: =-CU39*(CU4+'BS & FCF'!CU96) -> -65818.063 | CV38: =-CV39*(CV4+'BS & FCF'!CV96) -> -69404.976 | CW38: =SUM(CS38:CV38) -> -260634.12 | CX38: =-CX39*(CX4+'BS & FCF'!CX96) -> -63879.526 | CY38: =-CY39*(CY4+'BS & FCF'!CY96) -> -68494.168 | CZ38: =-CZ39*(CZ4+'BS & FCF'!CZ96) -> -70037.722 | DA38: =-DA39*(DA4+'BS & FCF'!DA96) -> -73044.089 | DB38: =SUM(CX38:DA38) -> -275455.5
A39: Cash tax rate (% of collection) | B39: =-B38/(B4+'BS & FCF'!B96) -> 0.020450892 | C39: =-C38/(C4+'BS & FCF'!C96) -> 0.016940038 | D39: =-D38/(D4+'BS & FCF'!D96) -> 0.032212716 | E39: =-E38/(E4+'BS & FCF'!E96) -> 0.026535609 | F39: =-F38/(F4+'BS & FCF'!F96) -> 0.020296026 | G39: =-G38/(G4+'BS & FCF'!G96) -> 0.030884246 | H39: =-H38/(H4+'BS & FCF'!H96) -> 0.029040908 | I39: =-I38/(I4+'BS & FCF'!I96) -> 0.031336163 | ... CE39: =-CE38/(CE4+'BS & FCF'!CE96) -> 0.022490376 | CF39: 0.0192 | CG39: 0.0192 | CH39: =-CH38/(CH4+'BS & FCF'!CH96) -> 0.021100859 | CI39: 0.0192 | CJ39: 0.0192 | CK39: 0.0192 | CL39: 0.0192 | CM39: =-CM38/(CM4+'BS & FCF'!CM96) -> 0.0192 | CN39: 0.0192 | CO39: 0.0192 | CP39: 0.0192 | CQ39: 0.0192 | CR39: =-CR38/(CR4+'BS & FCF'!CR96) -> 0.0192 | CS39: 0.0192 | CT39: 0.0192 | CU39: 0.0192 | CV39: 0.0192 | CW39: =-CW38/(CW4+'BS & FCF'!CW96) -> 0.0192 | CX39: 0.0192 | CY39: 0.0192 | CZ39: 0.0192 | DA39: 0.0192 | DB39: =-DB38/(DB4+'BS & FCF'!DB96) -> 0.0192
A40: Deffered taxes | B40: -593 | C40: -19909 | D40: -5466 | E40: -395 | F40: =SUM(B40:E40) -> -26363 | G40: -7319 | H40: 4572 | I40: 2519 | J40: =-10139-G40-H40-I40 -> -9911 | K40: =SUM(G40:J40) -> -10139 | L40: =-20103-M40 -> -6080 | M40: -14023 | N40: -6910 | O40: =30450-L40-M40-N40 -> 57463 | P40: =SUM(L40:O40) -> 30450 | Q40: =5483-R40 -> 2438 | R40: 3045 | S40: 687 | T40: =6944-SUM(Q40:S40) -> 774 | U40: =SUM(Q40:T40) -> 6944 | V40: -5605 | W40: -7630 | X40: 6039 | Y40: =-5811-SUM(V40:X40) -> 1385 | Z40: =SUM(V40:Y40) -> -5811 | AA40: 9591 | AB40: 7192 | AC40: -140 | AD40: =21223-SUM(AA40:AC40) -> 4580 | AE40: =SUM(AA40:AD40) -> 21223 | AF40: 2525 | AG40: 5723 | AH40: -741 | AI40: =9441-SUM(AF40:AH40) -> 1934 | AJ40: =SUM(AF40:AI40) -> 9441 | AK40: 6159 | AL40: 4999 | AM40: 6156 | AN40: =17595-SUM(AK40:AM40) -> 281 | AO40: =SUM(AK40:AN40) -> 17595 | AP40: 2418 | AQ40: 2288 | AR40: 2662 | AS40: =-1099-SUM(AP40:AR40) -> -8467 | AT40: =SUM(AP40:AS40) -> -1099 | AU40: -17937 | AV40: -19605 | AW40: 202 | AX40: =-2956-SUM(AU40:AW40) -> 34384 | AY40: =SUM(AU40:AX40) -> -2956 | AZ40: 1457 | BA40: -2972 | BB40: 0 | BC40: =-262343-SUM(AZ40:BB40)+266545 -> 5717 | BD40: =SUM(AZ40:BC40) -> 4202 | BE40: -15 | BF40: 3417 | BG40: -2474 | BH40: =4399-SUM(BE40:BG40) -> 3471 | BI40: =SUM(BE40:BH40) -> 4399 | BJ40: -1238 | BK40: -2609 | BL40: 2855 | BM40: =-1867-SUM(BJ40:BL40) -> -875 | BN40: =SUM(BJ40:BM40) -> -1867 | BO40: 3974 | BP40: -5843 | BQ40: -5072 | BR40: =-12548-SUM(BO40:BQ40) -> -5607 | BS40: =SUM(BO40:BR40) -> -12548 | BT40: -2751 | BU40: -7190 | BV40: -7334 | BW40: =-26947-SUM(BT40:BV40) -> -9672 | BX40: =SUM(BT40:BW40) -> -26947 | BY40: -1078 | BZ40: -6252 | CA40: -1015 | CB40: =49710-SUM(BY40:CA40) -> 58055 | CC40: =SUM(BY40:CB40) -> 49710 | CD40: -5169 | CE40: -2441 | CF40: =-CF41*CF9-CF38 -> -5044.731 | CG40: =-CG41*CG9-CG38 -> -4528.6314 | CH40: =SUM(CD40:CG40) -> -17183.362 | CI40: =-CI41*CI9-CI38 -> -8663.8473 | CJ40: =-CJ41*CJ9-CJ38 -> -489.5276 | CK40: =-CK41*CK9-CK38 -> -864.18166 | CL40: =-CL41*CL9-CL38 -> -34.492439 | CM40: =SUM(CI40:CL40) -> -10052.049 | CN40: =-CN41*CN9-CN38 -> -5332.1817 | CO40: =-CO41*CO9-CO38 -> -1770.7903 | CP40: =-CP41*CP9-CP38 -> -2245.5307 | CQ40: =-CQ41*CQ9-CQ38 -> 17.4435 | CR40: =SUM(CN40:CQ40) -> -9331.0593 | CS40: =-CS41*CS9-CS38 -> -1991.5408 | CT40: =-CT41*CT9-CT38 -> -440.01587 | CU40: =-CU41*CU9-CU38 -> -458.63112 | CV40: =-CV41*CV9-CV38 -> -931.64606 | CW40: =SUM(CS40:CV40) -> -3821.8339 | CX40: =-CX41*CX9-CX38 -> -4731.2641 | CY40: =-CY41*CY9-CY38 -> -266.39062 | CZ40: =-CZ41*CZ9-CZ38 -> -881.56266 | DA40: =-DA41*DA9-DA38 -> -1943.9591 | DB40: =SUM(CX40:DA40) -> -7823.1765
A41: Tax rate (% of revenues) | B41: =-(B38+B40)/B9 -> 0.02165574 | C41: =-(C38+C40)/C9 -> 0.029519793 | D41: =-(D38+D40)/D9 -> 0.0297338 | E41: =-(E38+E40)/E9 -> 0.024648143 | F41: =-(F38+F40)/F9 -> 0.026365487 | G41: =-(G38+G40)/G9 -> 0.034881765 | H41: =-(H38+H40)/H9 -> 0.025348475 | I41: =-(I38+I40)/I9 -> 0.030375698 | ... CE41: =-(CE38+CE40)/CE9 -> 0.022159959 | CF41: 0.0192 | CG41: 0.0192 | CH41: =-(CH38+CH40)/CH9 -> 0.021163929 | CI41: 0.0192 | CJ41: 0.0192 | CK41: 0.0192 | CL41: 0.0192 | CM41: =-(CM38+CM40)/CM9 -> 0.0192 | CN41: 0.0192 | CO41: 0.0192 | CP41: 0.0192 | CQ41: 0.0192 | CR41: =-(CR38+CR40)/CR9 -> 0.0192 | CS41: 0.0192 | CT41: 0.0192 | CU41: 0.0192 | CV41: 0.0192 | CW41: =-(CW38+CW40)/CW9 -> 0.0192 | CX41: 0.0192 | CY41: 0.0192 | CZ41: 0.0192 | DA41: 0.0192 | DB41: =-(DB38+DB40)/DB9 -> 0.0192
A42: Majority income | B42: =B37+B38+B40 -> 186273 | C42: =C37+C38+C40 -> 197091 | D42: =D37+D38+D40 -> 196142 | E42: =E37+E38+E40 -> 105905 | F42: =SUM(B42:E42) -> 685411 | G42: =G37+G38+G40 -> 90075 | H42: =H37+H38+H40 -> 118941 | I42: =I37+I38+I40 -> 177561 | J42: =J37+J38+J40 -> 205609 | K42: =SUM(G42:J42) -> 592186 | L42: =L37+L38+L40 -> 178225 | M42: =M37+M38+M40 -> 169612 | N42: =N37+N38+N40 -> 165849 | O42: =O37+O38+O40 -> 322003 | P42: =SUM(L42:O42) -> 835689 | Q42: =Q37+Q38+Q40 -> 208457 | R42: =R37+R38+R40 -> 225185 | S42: =S37+S38+S40 -> 228094 | T42: =T37+T38+T40 -> 226263 | U42: =SUM(Q42:T42) -> 887999 | V42: =V37+V38+V40 -> 187344 | W42: =W37+W38+W40 -> 208215 | X42: =X37+X38+X40 -> 229793 | Y42: =Y37+Y38+Y40 -> 206034 | Z42: =SUM(V42:Y42) -> 831386 | AA42: =AA37+AA38+AA40 -> 117932 | AB42: =AB37+AB38+AB40 -> 185059 | AC42: =AC37+AC38+AC40 -> 169026 | AD42: =AD37+AD38+AD40 -> 121136 | AE42: =SUM(AA42:AD42) -> 593153 | AF42: =AF37+AF38+AF40 -> 88867 | AG42: =AG37+AG38+AG40 -> 56503 | AH42: =AH37+AH38+AH40 -> 42975 | AI42: =AI37+AI38+AI40 -> 56275 | AJ42: =SUM(AF42:AI42) -> 244620 | AK42: =AK37+AK38+AK40 -> 34246 | AL42: =AL37+AL38+AL40 -> -134320 | AM42: =AM37+AM38+AM40 -> 14163 | AN42: =AN37+AN38+AN40 -> 75372 | AO42: =SUM(AK42:AN42) -> -10539 | AP42: =AP37+AP38+AP40 -> -34655 | AQ42: =AQ37+AQ38+AQ40 -> -19131 | AR42: =AR37+AR38+AR40 -> -94077 | AS42: =AS37+AS38+AS40 -> 153891 | AT42: =SUM(AP42:AS42) -> 6028 | AU42: =AU37+AU38+AU40 -> 61401 | AV42: =AV37+AV38+AV40 -> 142291 | AW42: =AW37+AW38+AW40 -> 121261 | AX42: =AX37+AX38+AX40 -> 209365 | AY42: =SUM(AU42:AX42) -> 534318 | AZ42: =AZ37+AZ38+AZ40 -> 48236 | BA42: =BA37+BA38+BA40 -> 92925 | BB42: =BB37+BB38+BB40 -> 1414875 | BC42: =BC37+BC38+BC40 -> 273461 | BD42: =SUM(AZ42:BC42) -> 1829497 | BE42: =BE37+BE38+BE40 -> 208193 | BF42: =BF37+BF38+BF40 -> 290352 | BG42: =BG37+BG38+BG40 -> 266243 | BH42: =BH37+BH38+BH40 -> 252526 | BI42: =SUM(BE42:BH42) -> 1017314 | BJ42: =BJ37+BJ38+BJ40 -> 170657 | BK42: =BK37+BK38+BK40 -> 161614 | BL42: =BL37+BL38+BL40 -> 309597 | BM42: =BM37+BM38+BM40 -> 216723 | BN42: =SUM(BJ42:BM42) -> 858591 | BO42: =BO37+BO38+BO40 -> 191060 | BP42: =BP37+BP38+BP40 -> 308025 | BQ42: =BQ37+BQ38+BQ40 -> 304638 | BR42: =BR37+BR38+BR40 -> 301977 | BS42: =SUM(BO42:BR42) -> 1105700 | BT42: =BT37+BT38+BT40 -> 314803 | BU42: =BU37+BU38+BU40 -> 477943 | BV42: =BV37+BV38+BV40 -> 541012 | BW42: =BW37+BW38+BW40 -> 679294 | BX42: =SUM(BT42:BW42) -> 2013052 | BY42: =BY37+BY38+BY40 -> 393813 | BZ42: =BZ37+BZ38+BZ40 -> 479003 | CA42: =CA37+CA38+CA40 -> 682963 | CB42: =CB37+CB38+CB40 -> 840050 | CC42: =SUM(BY42:CB42) -> 2395829 | CD42: =CD37+CD38+CD40 -> 360059 | CE42: =CE37+CE38+CE40 -> 518757 | CF42: =CF37+CF38+CF40 -> 606806.47 | CG42: =CG37+CG38+CG40 -> 694320.1 | CH42: =SUM(CD42:CG42) -> 2179942.6 | CI42: =CI37+CI38+CI40 -> 690946.9 | CJ42: =CJ37+CJ38+CJ40 -> 646247.35 | CK42: =CK37+CK38+CK40 -> 668046.29 | CL42: =CL37+CL38+CL40 -> 740605.7 | CM42: =SUM(CI42:CL42) -> 2745846.2 | CN42: =CN37+CN38+CN40 -> 795534.08 | CO42: =CO37+CO38+CO40 -> 731080.33 | CP42: =CP37+CP38+CP40 -> 733606.03 | CQ42: =CQ37+CQ38+CQ40 -> 804806.89 | CR42: =SUM(CN42:CQ42) -> 3065027.3 | CS42: =CS37+CS38+CS40 -> 854435.27 | CT42: =CT37+CT38+CT40 -> 785091.81 | CU42: =CU37+CU38+CU40 -> 789406.34 | CV42: =CV37+CV38+CV40 -> 857744.2 | CW42: =SUM(CS42:CV42) -> 3286677.6 | CX42: =CX37+CX38+CX40 -> 934695.53 | CY42: =CY37+CY38+CY40 -> 854865.96 | CZ42: =CZ37+CZ38+CZ40 -> 862121.87 | DA42: =DA37+DA38+DA40 -> 936764.01 | DB42: =SUM(CX42:DA42) -> 3588447.4
A43: Minority interest | B43: -12033 | C43: -29297 | D43: -20108 | E43: -23379 | F43: =SUM(B43:E43) -> -84817 | G43: -15894 | H43: -10068 | I43: -30808 | J43: =-94015-G43-H43-I43 -> -37245 | K43: =SUM(G43:J43) -> -94015 | L43: =-87186-M43 -> -60319 | M43: -26867 | N43: -15454 | O43: =-175541-L43-M43-N43 -> -72901 | P43: =SUM(L43:O43) -> -175541 | Q43: =-77936-R43 -> -35528 | R43: -42408 | S43: -53490 | T43: =-175167-SUM(Q43:S43) -> -43741 | U43: =SUM(Q43:T43) -> -175167 | V43: -23891 | W43: -39321 | X43: -50664 | Y43: =-169887-SUM(V43:X43) -> -56011 | Z43: =SUM(V43:Y43) -> -169887 | AA43: -17391 | AB43: -67053 | AC43: -37794 | AD43: =-145353-SUM(AA43:AC43) -> -23115 | AE43: =SUM(AA43:AD43) -> -145353 | AF43: -27595 | AG43: -11800 | AH43: -28531 | AI43: =-93268-SUM(AF43:AH43) -> -25342 | AJ43: =SUM(AF43:AI43) -> -93268 | AK43: -30221 | AL43: -6708 | AM43: -20926 | AN43: =-84465-SUM(AK43:AM43) -> -26610 | AO43: =SUM(AK43:AN43) -> -84465 | AP43: -16629 | AQ43: -9306 | AR43: -26676 | AS43: =-90391-SUM(AP43:AR43) -> -37780 | AT43: =SUM(AP43:AS43) -> -90391 | AU43: -12991 | AV43: -28456 | AW43: -16878 | AX43: =-118475-SUM(AU43:AW43) -> -60150 | AY43: =SUM(AU43:AX43) -> -118475 | AZ43: -20301 | BA43: -25114 | BB43: -11594 | BC43: =-69239-SUM(AZ43:BB43) -> -12230 | BD43: =SUM(AZ43:BC43) -> -69239 | BE43: -15908 | BF43: -23378 | BG43: -28696 | BH43: =-102959-SUM(BE43:BG43) -> -34977 | BI43: =SUM(BE43:BH43) -> -102959 | BJ43: -8906 | BK43: -10817 | BL43: -20969 | BM43: =-49711-SUM(BJ43:BL43) -> -9019 | BN43: =SUM(BJ43:BM43) -> -49711 | BO43: -27484 | BP43: -28640 | BQ43: -53319 | BR43: =-163610-SUM(BO43:BQ43) -> -54167 | BS43: =SUM(BO43:BR43) -> -163610 | BT43: -47545 | BU43: -65938 | BV43: -67911 | BW43: =-272056-SUM(BT43:BV43) -> -90662 | BX43: =SUM(BT43:BW43) -> -272056 | BY43: -66181 | BZ43: -91196 | CA43: -73848 | CB43: =-389073-SUM(BY43:CA43) -> -157848 | CC43: =SUM(BY43:CB43) -> -389073 | CD43: -63283 | CE43: -67151 | CF43: =-25%/4*'BS & FCF'!CE42 -> -80216.875 | CG43: =-25%/4*'BS & FCF'!CF42 -> -82399.517 | CH43: =SUM(CD43:CG43) -> -293050.39 | CI43: =-27.5%/4*'BS & FCF'!CH42 -> -92760.44 | CJ43: =-27.5%/4*'BS & FCF'!CI42 -> -96257.921 | CK43: =-27.5%/4*'BS & FCF'!CJ42 -> -97097.019 | CL43: =-27.5%/4*'BS & FCF'!CK42 -> -98064.72 | CM43: =SUM(CI43:CL43) -> -384180.1 | CN43: =-30%/4*'BS & FCF'!CM42 -> -107674.76 | CO43: =-30%/4*'BS & FCF'!CN42 -> -110322.5 | CP43: =-30%/4*'BS & FCF'!CO42 -> -111968.18 | CQ43: =-30%/4*'BS & FCF'!CP42 -> -113705.99 | CR43: =SUM(CN43:CQ43) -> -443671.43 | CS43: =-30%/4*'BS & FCF'!CR42 -> -114302.38 | CT43: =-30%/4*'BS & FCF'!CS42 -> -115668.7 | CU43: =-30%/4*'BS & FCF'!CT42 -> -116659.95 | CV43: =-30%/4*'BS & FCF'!CU42 -> -117576.35 | CW43: =SUM(CS43:CV43) -> -464207.38 | CX43: =-30%/4*'BS & FCF'!CW42 -> -118376 | CY43: =-30%/4*'BS & FCF'!CX42 -> -120941.2 | CZ43: =-30%/4*'BS & FCF'!CY42 -> -121213.05 | DA43: =-30%/4*'BS & FCF'!CZ42 -> -120337.55 | DB43: =SUM(CX43:DA43) -> -480867.81
A44: % of majority income | B44: =-B43/B42 -> 0.064598734 | C44: =-C43/C42 -> 0.14864707 | D44: =-D43/D42 -> 0.10251756 | E44: =-E43/E42 -> 0.22075445 | F44: =-F43/F42 -> 0.12374619 | G44: =-G43/G42 -> 0.17645296 | H44: =-H43/H42 -> 0.08464701 | I44: =-I43/I42 -> 0.17350657 | ... DB44: =-DB43/DB42 -> 0.13400442
A45: Net income | B45: =B42+B43 -> 174240 | C45: =C42+C43 -> 167794 | D45: =D42+D43 -> 176034 | E45: =E42+E43 -> 82526 | F45: =SUM(B45:E45) -> 600594 | G45: =G42+G43 -> 74181 | H45: =H42+H43 -> 108873 | I45: =I42+I43 -> 146753 | J45: =J42+J43 -> 168364 | K45: =SUM(G45:J45) -> 498171 | L45: =L42+L43 -> 117906 | M45: =M42+M43 -> 142745 | N45: =N42+N43 -> 150395 | O45: =O42+O43 -> 249102 | P45: =SUM(L45:O45) -> 660148 | Q45: =Q42+Q43 -> 172929 | R45: =R42+R43 -> 182777 | S45: =S42+S43 -> 174604 | T45: =T42+T43 -> 182522 | U45: =SUM(Q45:T45) -> 712832 | V45: =V42+V43 -> 163453 | W45: =W42+W43 -> 168894 | X45: =X42+X43 -> 179129 | Y45: =Y42+Y43 -> 150023 | Z45: =SUM(V45:Y45) -> 661499 | AA45: =AA42+AA43 -> 100541 | AB45: =AB42+AB43 -> 118006 | AC45: =AC42+AC43 -> 131232 | AD45: =AD42+AD43 -> 98021 | AE45: =SUM(AA45:AD45) -> 447800 | AF45: =AF42+AF43 -> 61272 | AG45: =AG42+AG43 -> 44703 | AH45: =AH42+AH43 -> 14444 | AI45: =AI42+AI43 -> 30933 | AJ45: =SUM(AF45:AI45) -> 151352 | AK45: =AK42+AK43 -> 4025 | AL45: =AL42+AL43 -> -141028 | AM45: =AM42+AM43 -> -6763 | AN45: =AN42+AN43 -> 48762 | AO45: =SUM(AK45:AN45) -> -95004 | AP45: =AP42+AP43 -> -51284 | AQ45: =AQ42+AQ43 -> -28437 | AR45: =AR42+AR43 -> -120753 | AS45: =AS42+AS43 -> 116111 | AT45: =SUM(AP45:AS45) -> -84363 | AU45: =AU42+AU43 -> 48410 | AV45: =AV42+AV43 -> 113835 | AW45: =AW42+AW43 -> 104383 | AX45: =AX42+AX43 -> 149215 | AY45: =SUM(AU45:AX45) -> 415843 | AZ45: =AZ42+AZ43 -> 27935 | BA45: =BA42+BA43 -> 67811 | BB45: =BB42+BB43 -> 1403281 | BC45: =BC42+BC43 -> 261231 | BD45: =SUM(AZ45:BC45) -> 1760258 | BE45: =BE42+BE43 -> 192285 | BF45: =BF42+BF43 -> 266974 | BG45: =BG42+BG43 -> 237547 | BH45: =BH42+BH43 -> 217549 | BI45: =SUM(BE45:BH45) -> 914355 | BJ45: =BJ42+BJ43 -> 161751 | BK45: =BK42+BK43 -> 150797 | BL45: =BL42+BL43 -> 288628 | BM45: =BM42+BM43 -> 207704 | BN45: =SUM(BJ45:BM45) -> 808880 | BO45: =BO42+BO43 -> 163576 | BP45: =BP42+BP43 -> 279385 | BQ45: =BQ42+BQ43 -> 251319 | BR45: =BR42+BR43 -> 247810 | BS45: =SUM(BO45:BR45) -> 942090 | BT45: =BT42+BT43 -> 267258 | BU45: =BU42+BU43 -> 412005 | BV45: =BV42+BV43 -> 473101 | BW45: =BW42+BW43 -> 588632 | BX45: =SUM(BT45:BW45) -> 1740996 | BY45: =BY42+BY43 -> 327632 | BZ45: =BZ42+BZ43 -> 387807 | CA45: =CA42+CA43 -> 609115 | CB45: =CB42+CB43 -> 682202 | CC45: =SUM(BY45:CB45) -> 2006756 | CD45: =CD42+CD43 -> 296776 | CE45: =CE42+CE43 -> 451606 | CF45: =CF42+CF43 -> 526589.59 | CG45: =CG42+CG43 -> 611920.58 | CH45: =SUM(CD45:CG45) -> 1886892.2 | CI45: =CI42+CI43 -> 598186.46 | CJ45: =CJ42+CJ43 -> 549989.43 | CK45: =CK42+CK43 -> 570949.27 | CL45: =CL42+CL43 -> 642540.98 | CM45: =SUM(CI45:CL45) -> 2361666.1 | CN45: =CN42+CN43 -> 687859.31 | CO45: =CO42+CO43 -> 620757.83 | CP45: =CP42+CP43 -> 621637.85 | CQ45: =CQ42+CQ43 -> 691100.9 | CR45: =SUM(CN45:CQ45) -> 2621355.9 | CS45: =CS42+CS43 -> 740132.89 | CT45: =CT42+CT43 -> 669423.11 | CU45: =CU42+CU43 -> 672746.38 | CV45: =CV42+CV43 -> 740167.86 | CW45: =SUM(CS45:CV45) -> 2822470.2 | CX45: =CX42+CX43 -> 816319.53 | CY45: =CY42+CY43 -> 733924.76 | CZ45: =CZ42+CZ43 -> 740908.81 | DA45: =DA42+DA43 -> 816426.45 | DB45: =SUM(CX45:DA45) -> 3107579.6
CC46: 1800 | CH46: 2050
A47: Per share (R$) | B47: =Macro!B$3 -> 1Q10 | C47: =Macro!C$3 -> 2Q10 | D47: =Macro!D$3 -> 3Q10 | E47: =Macro!E$3 -> 4Q10 | F47: =Macro!F$3 -> 2010 | G47: =Macro!G$3 -> 1Q11 | H47: =Macro!H$3 -> 2Q11 | I47: =Macro!I$3 -> 3Q11 | ... DB47: =Macro!DB$3 -> 2030E
A48: Shares outstanding (ex-treasury, 000') | B48: 422401 | C48: 422911.36 | D48: 422944 | E48: 423003.89 | F48: =E48 -> 423003.89 | G48: 423003.89 | H48: 423003.89 | I48: =423003.887-9527 -> 413476.89 | J48: =423003.887-12336 -> 410667.89 | K48: =J48 -> 410667.89 | L48: =423003.887-12336 -> 410667.89 | M48: =416659-5453 -> 411206 | N48: =416659-5453 -> 411206 | O48: =416659-4552 -> 412107 | P48: =O48 -> 412107 | Q48: =416659-4541 -> 412118 | R48: =416659-2243 -> 414416 | S48: 414455 | T48: =416658.829-9398.459 -> 407260.37 | U48: =T48 -> 407260.37 | V48: =416859-13127 -> 403732 | W48: =399743-5722 -> 394021 | X48: =399743-11848 -> 387895 | Y48: =399743-16807 -> 382936 | Z48: =Y48 -> 382936 | AA48: =399743-21166 -> 378577 | AB48: =399743-21049 -> 378694 | AC48: =399743-20948 -> 378795 | AD48: =399742.799-20662 -> 379080.8 | AE48: =AD48 -> 379080.8 | AF48: =399743-18789 -> 380954 | AG48: =399743-18565 -> 381178 | AH48: =399743-18127 -> 381616 | AI48: =399743-17594 -> 382149 | AJ48: =AI48 -> 382149 | AK48: =399743-17594 -> 382149 | AL48: =399743-17182 -> 382561 | AM48: =399743-17084 -> 382659 | AN48: =399743-17035 -> 382708 | AO48: =AN48 -> 382708 | AP48: =399743-16846 -> 382897 | AQ48: =399743-15586 -> 384157 | AR48: =399743-15586 -> 384157 | AS48: =399815-15586 -> 384229 | AT48: =AS48 -> 384229 | AU48: =399743-15383 -> 384360 | AV48: =399743-15330 -> 384413 | AW48: =399743-15316 -> 384427 | AX48: =399743-15316 -> 384427 | AY48: =AX48 -> 384427 | AZ48: =399743-15316 -> 384427 | BA48: =399743-15316 -> 384427 | BB48: =399743-15239 -> 384504 | BC48: =399743-15239 -> 384504 | BD48: =BC48 -> 384504 | BE48: =399743-15239 -> 384504 | BF48: =399743-15239 -> 384504 | BG48: =399743-15239 -> 384504 | BH48: =399743-15239 -> 384504 | BI48: =BH48 -> 384504 | BJ48: =399743-15239 -> 384504 | BK48: =399743-16918 -> 382825 | BL48: =399743-20772 -> 378971 | BM48: =399743-24012 -> 375731 | BN48: =BM48 -> 375731 | BO48: =399743-24822 -> 374921 | BP48: =399743-24822 -> 374921 | BQ48: =399743-24822 -> 374921 | BR48: =399743-24822 -> 374921 | BS48: =BR48 -> 374921 | BT48: =399743-24822 -> 374921 | BU48: =399743-24822 -> 374921 | BV48: =399743-24822 -> 374921 | BW48: =399743-17468+72800 -> 455075 | BX48: =BW48 -> 455075 | BY48: =384000-17689+72800 -> 439111 | BZ48: =384000-17689+72800 -> 439111 | CA48: =384000-17689+72800 -> 439111 | CB48: =384000-17689+72800 -> 439111 | CC48: =CB48 -> 439111 | CD48: =384000+72800-17689-3354 -> 435757 | CE48: =384000-17689+69446.45 -> 435757.45 | CF48: =CE48+CF49+CF50 -> 435757.45 | CG48: =CF48+CG49+CG50 -> 435757.45 | CH48: =CG48 -> 435757.45 | CI48: =CH48+CI49+CI50 -> 435757.45 | CJ48: =CI48+CJ49+CJ50 -> 435757.45 | CK48: =CJ48+CK49+CK50 -> 435757.45 | CL48: =CK48+CL49+CL50 -> 435757.45 | CM48: =CL48 -> 435757.45 | CN48: =CM48+CN49+CN50 -> 435757.45 | CO48: =CN48+CO49+CO50 -> 435757.45 | CP48: =CO48+CP49+CP50 -> 435757.45 | CQ48: =CP48+CQ49+CQ50 -> 435757.45 | CR48: =CQ48 -> 435757.45 | CS48: =CR48+CS49+CS50 -> 435757.45 | CT48: =CS48+CT49+CT50 -> 435757.45 | CU48: =CT48+CU49+CU50 -> 435757.45 | CV48: =CU48+CV49+CV50 -> 435757.45 | CW48: =CV48 -> 435757.45 | CX48: =CW48+CX49+CX50 -> 435757.45 | CY48: =CX48+CY49+CY50 -> 435757.45 | CZ48: =CY48+CZ49+CZ50 -> 435757.45 | DA48: =CZ48+DA49+DA50 -> 435757.45 | DB48: =DA48 -> 435757.45
A49: Equity issuance | B49: 0 | C49: 0 | D49: 0 | E49: 0 | F49: =SUM(B49:E49) -> 0 | G49: 0 | H49: 0 | I49: 0 | J49: 0 | K49: =SUM(G49:J49) -> 0 | L49: 0 | M49: 0 | N49: 0 | O49: 0 | P49: =SUM(L49:O49) -> 0 | Q49: 0 | R49: 0 | S49: 0 | T49: 0 | U49: =SUM(Q49:T49) -> 0 | V49: 0 | W49: 0 | X49: 0 | Y49: 0 | Z49: =SUM(V49:Y49) -> 0 | AA49: 0 | AB49: 0 | AC49: 0 | AD49: 0 | AE49: =SUM(AA49:AD49) -> 0 | AF49: 0 | AG49: 0 | AH49: 0 | AI49: 0 | AJ49: =SUM(AF49:AI49) -> 0 | AK49: 0 | AL49: 0 | AM49: 0 | AN49: 0 | AO49: =SUM(AK49:AN49) -> 0 | AP49: 0 | AQ49: 0 | AR49: 0 | AS49: 0 | AT49: =SUM(AP49:AS49) -> 0 | AU49: 0 | AV49: 0 | AW49: 0 | AX49: 0 | AY49: =SUM(AU49:AX49) -> 0 | AZ49: 0 | BA49: 0 | BB49: 0 | BC49: 0 | BD49: =SUM(AZ49:BC49) -> 0 | BE49: 0 | BF49: 0 | BG49: 0 | BH49: 0 | BI49: =SUM(BE49:BH49) -> 0 | BJ49: 0 | BK49: 0 | BL49: 0 | BM49: 0 | BN49: =SUM(BJ49:BM49) -> 0 | BO49: 0 | BP49: 0 | BQ49: 0 | BR49: 0 | BS49: =SUM(BO49:BR49) -> 0 | BT49: 0 | BU49: 0 | BV49: 0 | BW49: 0 | BX49: =SUM(BT49:BW49) -> 0 | BY49: 0 | BZ49: 0 | CA49: 0 | CB49: 0 | CC49: =SUM(BY49:CB49) -> 0 | CD49: 0 | CE49: 0 | CF49: =('BS & FCF'!CF44-'BS & FCF'!CE44)/Valuation!$B$6 -> 0 | CG49: =('BS & FCF'!CG44-'BS & FCF'!CF44)/Valuation!$B$6 -> 0 | CH49: =SUM(CD49:CG49) -> 0 | CI49: =('BS & FCF'!CI44-'BS & FCF'!CG44)/Valuation!$B$6 -> 0 | CJ49: =('BS & FCF'!CJ44-'BS & FCF'!CI44)/Valuation!$B$6 -> 0 | CK49: =('BS & FCF'!CK44-'BS & FCF'!CJ44)/Valuation!$B$6 -> 0 | CL49: =('BS & FCF'!CL44-'BS & FCF'!CK44)/Valuation!$B$6 -> 0 | CM49: =SUM(CI49:CL49) -> 0 | CN49: =('BS & FCF'!CN44-'BS & FCF'!CL44)/Valuation!$B$6 -> 0 | CO49: =('BS & FCF'!CO44-'BS & FCF'!CN44)/Valuation!$B$6 -> 0 | CP49: =('BS & FCF'!CP44-'BS & FCF'!CO44)/Valuation!$B$6 -> 0 | CQ49: =('BS & FCF'!CQ44-'BS & FCF'!CP44)/Valuation!$B$6 -> 0 | CR49: =SUM(CN49:CQ49) -> 0 | CS49: =('BS & FCF'!CS44-'BS & FCF'!CQ44)/Valuation!$B$6 -> 0 | CT49: =('BS & FCF'!CT44-'BS & FCF'!CS44)/Valuation!$B$6 -> 0 | CU49: =('BS & FCF'!CU44-'BS & FCF'!CT44)/Valuation!$B$6 -> 0 | CV49: =('BS & FCF'!CV44-'BS & FCF'!CU44)/Valuation!$B$6 -> 0 | CW49: =SUM(CS49:CV49) -> 0 | CX49: =('BS & FCF'!CX44-'BS & FCF'!CV44)/Valuation!$B$6 -> 0 | CY49: =('BS & FCF'!CY44-'BS & FCF'!CX44)/Valuation!$B$6 -> 0 | CZ49: =('BS & FCF'!CZ44-'BS & FCF'!CY44)/Valuation!$B$6 -> 0 | DA49: =('BS & FCF'!DA44-'BS & FCF'!CZ44)/Valuation!$B$6 -> 0 | DB49: =SUM(CX49:DA49) -> 0
A50: Share repurchase | C50: =C48-B48-C49 -> 510.356 | D50: =D48-C48-D49 -> 32.644 | E50: =E48-D48-E49 -> 59.887 | F50: =SUM(B50:E50) -> 602.887 | G50: =G48-E48-G49 -> 0 | H50: =H48-G48-H49 -> 0 | I50: =I48-H48-I49 -> -9527 | J50: =J48-I48-J49 -> -2809 | K50: =SUM(G50:J50) -> -12336 | L50: =L48-J48-L49 -> 0 | M50: =M48-L48-M49 -> 538.113 | N50: =N48-M48-N49 -> 0 | O50: =O48-N48-O49 -> 901 | P50: =SUM(L50:O50) -> 1439.113 | Q50: =Q48-O48-Q49 -> 11 | R50: =R48-Q48-R49 -> 2298 | S50: =S48-R48-S49 -> 39 | T50: =T48-S48-T49 -> -7194.63 | U50: =SUM(Q50:T50) -> -4846.63 | V50: =V48-T48-V49 -> -3528.37 | W50: =W48-V48-W49 -> -9711 | X50: =X48-W48-X49 -> -6126 | Y50: =Y48-X48-Y49 -> -4959 | Z50: =SUM(V50:Y50) -> -24324.37 | AA50: =AA48-Y48-AA49 -> -4359 | AB50: =AB48-AA48-AB49 -> 117 | AC50: =AC48-AB48-AC49 -> 101 | AD50: =AD48-AC48-AD49 -> 285.799 | AE50: =SUM(AA50:AD50) -> -3855.201 | AF50: =AF48-AD48-AF49 -> 1873.201 | AG50: =AG48-AF48-AG49 -> 224 | AH50: =AH48-AG48-AH49 -> 438 | AI50: =AI48-AH48-AI49 -> 533 | AJ50: =SUM(AF50:AI50) -> 3068.201 | AK50: =AK48-AI48-AK49 -> 0 | AL50: =AL48-AK48-AL49 -> 412 | AM50: =AM48-AL48-AM49 -> 98 | AN50: =AN48-AM48-AN49 -> 49 | AO50: =SUM(AK50:AN50) -> 559 | AP50: =AP48-AN48-AP49 -> 189 | AQ50: =AQ48-AP48-AQ49 -> 1260 | AR50: =AR48-AQ48-AR49 -> 0 | AS50: =AS48-AR48-AS49 -> 72 | AT50: =SUM(AP50:AS50) -> 1521 | AU50: =AU48-AS48-AU49 -> 131 | AV50: =AV48-AU48-AV49 -> 53 | AW50: =AW48-AV48-AW49 -> 14 | AX50: =AX48-AW48-AX49 -> 0 | AY50: =SUM(AU50:AX50) -> 198 | AZ50: =AZ48-AX48-AZ49 -> 0 | BA50: =BA48-AZ48-BA49 -> 0 | BB50: =BB48-BA48-BB49 -> 77 | BC50: =BC48-BB48-BC49 -> 0 | BD50: =SUM(AZ50:BC50) -> 77 | BE50: =BE48-BC48-BE49 -> 0 | BF50: =BF48-BE48-BF49 -> 0 | BG50: =BG48-BF48-BG49 -> 0 | BH50: =BH48-BG48-BH49 -> 0 | BI50: =SUM(BE50:BH50) -> 0 | BJ50: =BJ48-BH48-BJ49 -> 0 | BK50: =BK48-BJ48-BK49 -> -1679 | BL50: =BL48-BK48-BL49 -> -3854 | BM50: =BM48-BL48-BM49 -> -3240 | BN50: =SUM(BJ50:BM50) -> -8773 | BO50: =BO48-BM48-BO49 -> -810 | BP50: =BP48-BO48-BP49 -> 0 | BQ50: =BQ48-BP48-BQ49 -> 0 | BR50: =BR48-BQ48-BR49 -> 0 | BS50: =SUM(BO50:BR50) -> -810 | BT50: =BT48-BR48-BT49 -> 0 | BU50: =BU48-BT48-BU49 -> 0 | BV50: =BV48-BU48-BV49 -> 0 | BW50: =BW48-BV48-BW49 -> 80154 | BX50: =SUM(BT50:BW50) -> 80154 | BY50: =BY48-BW48-BY49 -> -15964 | BZ50: =BZ48-BY48-BZ49 -> 0 | CA50: =CA48-BZ48-CA49 -> 0 | CB50: =CB48-CA48-CB49 -> 0 | CC50: =SUM(BY50:CB50) -> -15964 | CD50: =CD48-CB48-CD49 -> -3354 | CE50: 0 | CF50: 0 | CG50: 0 | CH50: =SUM(CD50:CG50) -> -3354 | CI50: 0 | CJ50: 0 | CK50: 0 | CL50: 0 | CM50: =SUM(CI50:CL50) -> 0 | CN50: 0 | CO50: 0 | CP50: 0 | CQ50: 0 | CR50: =SUM(CN50:CQ50) -> 0 | CS50: 0 | CT50: 0 | CU50: 0 | CV50: 0 | CW50: =SUM(CS50:CV50) -> 0 | CX50: 0 | CY50: 0 | CZ50: 0 | DA50: 0 | DB50: =SUM(CX50:DA50) -> 0
A51: EPS | C51: =C73/AVERAGE(B48,C48) -> 0.39699881 | D51: =D73/AVERAGE(C48,D48) -> 0.41622719 | E51: =E73/AVERAGE(D48,E48) -> 0.19510895 | F51: =F73/AVERAGE(B48:E48) -> 1.420465 | G51: =G73/AVERAGE(E48,G48) -> 0.17536718 | H51: =H73/AVERAGE(G48,H48) -> 0.25738061 | I51: =I73/AVERAGE(H48,I48) -> 0.35088194 | J51: =J73/AVERAGE(I48,J48) -> 0.4085787 | K51: =K73/AVERAGE(G48:J48) -> 1.193115 | L51: =L73/AVERAGE(J48,L48) -> 0.28710791 | M51: =M73/AVERAGE(L48,M48) -> 0.34736473 | N51: =N73/AVERAGE(M48,N48) -> 0.36574126 | O51: =O73/AVERAGE(N48,O48) -> 0.60512102 | P51: =P73/AVERAGE(L48:O48) -> 1.6050408 | Q51: =Q73/AVERAGE(O48,Q48) -> 0.419616 | R51: =R73/AVERAGE(Q48,R48) -> 0.4422734 | S51: =S73/AVERAGE(R48,S48) -> 0.42130561 | T51: =T73/AVERAGE(S48,T48) -> 0.44424628 | U51: =U73/AVERAGE(Q48:T48) -> 1.729913 | V51: =V73/AVERAGE(T48,V48) -> 0.4030938 | W51: =W73/AVERAGE(V48,W48) -> 0.42342429 | X51: =X73/AVERAGE(W48,X48) -> 0.45817965 | Y51: =Y73/AVERAGE(X48,Y48) -> 0.38925004 | Z51: =Z73/AVERAGE(V48:Y48) -> 1.6868692 | AA51: =AA73/AVERAGE(Y48,AA48) -> 0.2640559 | AB51: =AB73/AVERAGE(AA48,AB48) -> 0.31166122 | AC51: =AC73/AVERAGE(AB48,AC48) -> 0.34649216 | AD51: =AD73/AVERAGE(AC48,AD48) -> 0.25867299 | AE51: =AE73/AVERAGE(AA48:AD48) -> 1.1821957 | AF51: =AF73/AVERAGE(AD48,AF48) -> 0.16123472 | AG51: =AG73/AVERAGE(AF48,AG48) -> 0.11731039 | AH51: =AH73/AVERAGE(AG48,AH48) -> 0.037871299 | AI51: =AI73/AVERAGE(AH48,AI48) -> 0.081001355 | AJ51: =AJ73/AVERAGE(AF48:AI48) -> 0.39675548 | AK51: =AK73/AVERAGE(AI48,AK48) -> 0.010532541 | AL51: =AL73/AVERAGE(AK48,AL48) -> -0.36884048 | AM51: =AM73/AVERAGE(AL48,AM48) -> -0.017675962 | AN51: =AN73/AVERAGE(AM48,AN48) -> 0.12742122 | AO51: =AO73/AVERAGE(AK48:AN48) -> -0.24836397 | AP51: =AP73/AVERAGE(AN48,AP48) -> -0.13396987 | AQ51: =AQ73/AVERAGE(AP48,AQ48) -> -0.074146018 | AR51: =AR73/AVERAGE(AQ48,AR48) -> -0.31433242 | AS51: =AS73/AVERAGE(AR48,AS48) -> 0.3022205 | AT51: =AT73/AVERAGE(AP48:AS48) -> -0.21977544 | AU51: =AU73/AVERAGE(AS48,AU48) -> 0.1259711 | AV51: =AV73/AVERAGE(AU48,AV48) -> 0.29614724 | AW51: =AW73/AVERAGE(AV48,AW48) -> 0.27153374 | AX51: =AX73/AVERAGE(AW48,AX48) -> 0.38814912 | AY51: =AY73/AVERAGE(AU48:AX48) -> 1.0817786 | AZ51: =AZ73/AVERAGE(AX48,AZ48) -> 0.072666592 | BA51: =BA73/AVERAGE(AZ48,BA48) -> 0.176395 | BB51: =BB73/AVERAGE(BA48,BB48) -> 3.649953 | BC51: =BC73/AVERAGE(BB48,BC48) -> 0.67939735 | BD51: =BD73/AVERAGE(AZ48:BC48) -> 4.578455 | BE51: =BE73/AVERAGE(BC48,BE48) -> 0.50008582 | BF51: =BF73/AVERAGE(BD48,BF48) -> 0.69433348 | BG51: =BG73/AVERAGE(BE48,BG48) -> 0.61780112 | BH51: =BH73/AVERAGE(BG48,BH48) -> 0.56579125 | BI51: =BI73/AVERAGE(BE48:BH48) -> 2.3780117 | BJ51: =BJ73/AVERAGE(BH48,BJ48) -> 0.42067443 | BK51: =BK73/AVERAGE(BI48,BK48) -> 0.39304392 | BL51: =BL73/AVERAGE(BJ48,BL48) -> 0.75609025 | BM51: =BM73/AVERAGE(BL48,BM48) -> 0.55042653 | BN51: =BN73/AVERAGE(BJ48:BM48) -> 2.1257911 | BO51: =BO73/AVERAGE(BM48,BO48) -> 0.43582379 | BP51: =BP73/AVERAGE(BN48,BP48) -> 0.74437955 | BQ51: =BQ73/AVERAGE(BP48,BQ48) -> 0.67032522 | BR51: =BR73/AVERAGE(BQ48,BR48) -> 0.66096591 | BS51: =BS73/AVERAGE(BO48:BR48) -> 2.5127694 | BT51: =BT73/AVERAGE(BR48,BT48) -> 0.71283817 | BU51: =BU73/AVERAGE(BT48,BU48) -> 1.0989115 | BV51: =BV73/AVERAGE(BU48,BV48) -> 1.2618685 | BW51: =BW73/AVERAGE(BV48,BW48) -> 1.4183972 | BX51: =BX73/AVERAGE(BT48:BW48) -> 4.4080368 | BY51: =BY73/AVERAGE(BW48,BY48) -> 0.73280503 | BZ51: =BZ73/AVERAGE(BY48,BZ48) -> 0.88316394 | CA51: =CA73/AVERAGE(BZ48,CA48) -> 1.387155 | CB51: =CB73/AVERAGE(CA48,CB48) -> 1.5535981 | CC51: =CC73/AVERAGE(BY48:CB48) -> 4.5700427 | CD51: =CD73/AVERAGE(CB48,CD48) -> 0.67844749 | CE51: =CE73/AVERAGE(CD48,CE48) -> 1.0363707 | CF51: =CF73/AVERAGE(CE48,CF48) -> 1.2084466 | CG51: =CG73/AVERAGE(CF48,CG48) -> 1.4042688 | CH51: =CH73/AVERAGE(CD48:CG48) -> 4.3301444 | CI51: =CI73/AVERAGE(CG48,CI48) -> 1.372751 | CJ51: =CJ73/AVERAGE(CI48,CJ48) -> 1.2621458 | CK51: =CK73/AVERAGE(CJ48,CK48) -> 1.3102456 | CL51: =CL73/AVERAGE(CK48,CL48) -> 1.4745381 | CM51: =CM73/AVERAGE(CI48:CL48) -> 5.4196805 | CN51: =CN73/AVERAGE(CL48,CN48) -> 1.5785371 | CO51: =CO73/AVERAGE(CN48,CO48) -> 1.424549 | CP51: =CP73/AVERAGE(CO48,CP48) -> 1.4265685 | CQ51: =CQ73/AVERAGE(CP48,CQ48) -> 1.5859761 | CR51: =CR73/AVERAGE(CN48:CQ48) -> 6.0156307 | CS51: =CS73/AVERAGE(CQ48,CS48) -> 1.6984974 | CT51: =CT73/AVERAGE(CS48,CT48) -> 1.5362287 | CU51: =CU73/AVERAGE(CT48,CU48) -> 1.5438551 | CV51: =CV73/AVERAGE(CU48,CV48) -> 1.6985776 | CW51: =CW73/AVERAGE(CS48:CV48) -> 6.4771589 | CX51: =CX73/AVERAGE(CV48,CX48) -> 1.8733346 | CY51: =CY73/AVERAGE(CX48,CY48) -> 1.6842506 | CZ51: =CZ73/AVERAGE(CY48,CZ48) -> 1.700278 | DA51: =DA73/AVERAGE(CZ48,DA48) -> 1.87358 | DB51: =DB73/AVERAGE(CX48:DA48) -> 7.1314433
A52: Adj. EPS | C52: =C74/AVERAGE(B48,C48) -> 0.40538388 | D52: =D74/AVERAGE(C48,D48) -> 0.42813939 | E52: =E74/AVERAGE(D48,E48) -> 0.19510895 | F52: =F74/AVERAGE(B48:E48) -> 1.4525571 | G52: =G74/AVERAGE(E48,G48) -> 0.17536718 | H52: =H74/AVERAGE(G48,H48) -> 0.25738061 | I52: =I74/AVERAGE(H48,I48) -> 0.35088194 | J52: =J74/AVERAGE(I48,J48) -> 0.49647588 | K52: =K74/AVERAGE(G48:J48) -> 1.2798615 | L52: =L74/AVERAGE(J48,L48) -> 0.33093895 | M52: =M74/AVERAGE(L48,M48) -> 0.34736473 | N52: =N74/AVERAGE(M48,N48) -> 0.36574126 | O52: =O74/AVERAGE(N48,O48) -> 0.60512102 | P52: =P74/AVERAGE(L48:O48) -> 1.6488048 | Q52: =Q74/AVERAGE(O48,Q48) -> 0.419616 | R52: =R74/AVERAGE(Q48,R48) -> 0.45679186 | S52: =S74/AVERAGE(R48,S48) -> 0.42130561 | T52: =T74/AVERAGE(S48,T48) -> 0.44424628 | U52: =U74/AVERAGE(Q48:T48) -> 1.7444739 | V52: =V74/AVERAGE(T48,V48) -> 0.4030938 | W52: =W74/AVERAGE(V48,W48) -> 0.42342429 | X52: =X74/AVERAGE(W48,X48) -> 0.45817965 | Y52: =Y74/AVERAGE(X48,Y48) -> 0.38925004 | Z52: =Z74/AVERAGE(V48:Y48) -> 1.6868692 | AA52: =AA74/AVERAGE(Y48,AA48) -> 0.2640559 | AB52: =AB74/AVERAGE(AA48,AB48) -> 0.31166122 | AC52: =AC74/AVERAGE(AB48,AC48) -> 0.34649216 | AD52: =AD74/AVERAGE(AC48,AD48) -> 0.25867299 | AE52: =AE74/AVERAGE(AA48:AD48) -> 1.1821957 | AF52: =AF74/AVERAGE(AD48,AF48) -> 0.16123472 | AG52: =AG74/AVERAGE(AF48,AG48) -> 0.11731039 | AH52: =AH74/AVERAGE(AG48,AH48) -> 0.037871299 | AI52: =AI74/AVERAGE(AH48,AI48) -> 0.081001355 | AJ52: =AJ74/AVERAGE(AF48:AI48) -> 0.39675548 | AK52: =AK74/AVERAGE(AI48,AK48) -> 0.010532541 | AL52: =AL74/AVERAGE(AK48,AL48) -> -0.36884048 | AM52: =AM74/AVERAGE(AL48,AM48) -> -0.017675962 | AN52: =AN74/AVERAGE(AM48,AN48) -> 0.12742122 | AO52: =AO74/AVERAGE(AK48:AN48) -> -0.24836397 | AP52: =AP74/AVERAGE(AN48,AP48) -> -0.13396987 | AQ52: =AQ74/AVERAGE(AP48,AQ48) -> -0.074146018 | AR52: =AR74/AVERAGE(AQ48,AR48) -> -0.31433242 | AS52: =AS74/AVERAGE(AR48,AS48) -> 0.25016333 | AT52: =AT74/AVERAGE(AP48:AS48) -> -0.27187777 | AU52: =AU74/AVERAGE(AS48,AU48) -> 0.1259711 | AV52: =AV74/AVERAGE(AU48,AV48) -> 0.29614724 | AW52: =AW74/AVERAGE(AV48,AW48) -> 0.27153374 | AX52: =AX74/AVERAGE(AW48,AX48) -> 0.38814912 | AY52: =AY74/AVERAGE(AU48:AX48) -> 1.0817786 | AZ52: =AZ74/AVERAGE(AX48,AZ48) -> 0.072666592 | BA52: =BA74/AVERAGE(AZ48,BA48) -> 0.176395 | BB52: =BB74/AVERAGE(BA48,BB48) -> 0.65098429 | BC52: =BC74/AVERAGE(BB48,BC48) -> 0.67939735 | BD52: =BD74/AVERAGE(AZ48:BC48) -> 1.5794863 | BE52: =BE74/AVERAGE(BC48,BE48) -> 0.50008582 | BF52: =BF74/AVERAGE(BD48,BF48) -> 0.69433348 | BG52: =BG74/AVERAGE(BE48,BG48) -> 0.61780112 | BH52: =BH74/AVERAGE(BG48,BH48) -> 0.56579125 | BI52: =BI74/AVERAGE(BE48:BH48) -> 2.3780117 | BJ52: =BJ74/AVERAGE(BH48,BJ48) -> 0.42067443 | BK52: =BK74/AVERAGE(BI48,BK48) -> 0.39304392 | BL52: =BL74/AVERAGE(BJ48,BL48) -> 0.75609025 | BM52: =BM74/AVERAGE(BL48,BM48) -> 0.55042653 | BN52: =BN74/AVERAGE(BJ48:BM48) -> 2.1257911 | BO52: =BO74/AVERAGE(BM48,BO48) -> 0.43582379 | BP52: =BP74/AVERAGE(BN48,BP48) -> 0.74437955 | BQ52: =BQ74/AVERAGE(BP48,BQ48) -> 0.67032522 | BR52: =BR74/AVERAGE(BQ48,BR48) -> 0.66096591 | BS52: =BS74/AVERAGE(BO48:BR48) -> 2.5127694 | BT52: =BT74/AVERAGE(BR48,BT48) -> 0.71283817 | BU52: =BU74/AVERAGE(BT48,BU48) -> 1.0989115 | BV52: =BV74/AVERAGE(BU48,BV48) -> 1.0164835 | BW52: =BW74/AVERAGE(BV48,BW48) -> 1.4183972 | BX52: =BX74/AVERAGE(BT48:BW48) -> 4.1751015 | BY52: =BY74/AVERAGE(BW48,BY48) -> 0.73280503 | BZ52: =BZ74/AVERAGE(BY48,BZ48) -> 0.88316394 | CA52: =CA74/AVERAGE(BZ48,CA48) -> 0.90208398 | CB52: =CB74/AVERAGE(CA48,CB48) -> 1.3941851 | CC52: =CC74/AVERAGE(BY48:CB48) -> 3.9255587 | CD52: =CD74/AVERAGE(CB48,CD48) -> 0.67844749 | CE52: =CE74/AVERAGE(CD48,CE48) -> 1.0363707 | CF52: =CF74/AVERAGE(CE48,CF48) -> 1.2084466 | CG52: =CG74/AVERAGE(CF48,CG48) -> 1.4042688 | CH52: =CH74/AVERAGE(CD48:CG48) -> 4.3301444 | CI52: =CI74/AVERAGE(CG48,CI48) -> 1.372751 | CJ52: =CJ74/AVERAGE(CI48,CJ48) -> 1.2621458 | CK52: =CK74/AVERAGE(CJ48,CK48) -> 1.3102456 | CL52: =CL74/AVERAGE(CK48,CL48) -> 1.4745381 | CM52: =CM74/AVERAGE(CI48:CL48) -> 5.4196805 | CN52: =CN74/AVERAGE(CL48,CN48) -> 1.5785371 | CO52: =CO74/AVERAGE(CN48,CO48) -> 1.424549 | CP52: =CP74/AVERAGE(CO48,CP48) -> 1.4265685 | CQ52: =CQ74/AVERAGE(CP48,CQ48) -> 1.5859761 | CR52: =CR74/AVERAGE(CN48:CQ48) -> 6.0156307 | CS52: =CS74/AVERAGE(CQ48,CS48) -> 1.6984974 | CT52: =CT74/AVERAGE(CS48,CT48) -> 1.5362287 | CU52: =CU74/AVERAGE(CT48,CU48) -> 1.5438551 | CV52: =CV74/AVERAGE(CU48,CV48) -> 1.6985776 | CW52: =CW74/AVERAGE(CS48:CV48) -> 6.4771589 | CX52: =CX74/AVERAGE(CV48,CX48) -> 1.8733346 | CY52: =CY74/AVERAGE(CX48,CY48) -> 1.6842506 | CZ52: =CZ74/AVERAGE(CY48,CZ48) -> 1.700278 | DA52: =DA74/AVERAGE(CZ48,DA48) -> 1.87358 | DB52: =DB74/AVERAGE(CX48:DA48) -> 7.1314433
A53: DPS | C53: =C55/AVERAGE(B48,C48) -> 0 | D53: =D55/AVERAGE(C48,D48) -> 0 | E53: =E55/AVERAGE(D48,E48) -> 0.33703967 | F53: =F55/AVERAGE(B48:E48) -> 0.33716632 | G53: =G55/AVERAGE(E48,G48) -> 0 | H53: =H55/AVERAGE(G48,H48) -> 0 | I53: =I55/AVERAGE(H48,I48) -> 0 | J53: =J55/AVERAGE(I48,J48) -> 0.28712188 | K53: =K55/AVERAGE(G48:J48) -> 0.28336334 | L53: =L55/AVERAGE(J48,L48) -> 0 | M53: =M55/AVERAGE(L48,M48) -> 0 | N53: =N55/AVERAGE(M48,N48) -> 0 | O53: =O55/AVERAGE(N48,O48) -> 0.38094382 | P53: =P55/AVERAGE(L48:O48) -> 0.38127705 | Q53: =Q55/AVERAGE(O48,Q48) -> 0.12132609 | R53: =R55/AVERAGE(Q48,R48) -> 0 | S53: =S55/AVERAGE(R48,S48) -> 0 | T53: =T55/AVERAGE(S48,T48) -> 0.41577901 | U53: =U55/AVERAGE(Q48:T48) -> 0.53590435 | V53: =V55/AVERAGE(T48,V48) -> 0 | W53: =W55/AVERAGE(V48,W48) -> 0 | X53: =X55/AVERAGE(W48,X48) -> 0 | Y53: =Y55/AVERAGE(X48,Y48) -> 0.40762761 | Z53: =Z55/AVERAGE(V48:Y48) -> 0.4006314 | AA53: =AA55/AVERAGE(Y48,AA48) -> 0 | AB53: =AB55/AVERAGE(AA48,AB48) -> 0 | AC53: =AC55/AVERAGE(AB48,AC48) -> 0 | AD53: =AD55/AVERAGE(AC48,AD48) -> 0.28066076 | AE53: =AE55/AVERAGE(AA48:AD48) -> 0.28077279 | AF53: =AF55/AVERAGE(AD48,AF48) -> 0 | AG53: =AG55/AVERAGE(AF48,AG48) -> 0 | AH53: =AH55/AVERAGE(AG48,AH48) -> 0 | AI53: =AI55/AVERAGE(AH48,AI48) -> 0.094128643 | AJ53: =AJ55/AVERAGE(AF48:AI48) -> 0.094229378 | AK53: =AK55/AVERAGE(AI48,AK48) -> 0 | AL53: =AL55/AVERAGE(AK48,AL48) -> 0 | AM53: =AM55/AVERAGE(AL48,AM48) -> 0 | AN53: =AN55/AVERAGE(AM48,AN48) -> 0 | AO53: =AO55/AVERAGE(AK48:AN48) -> 0 | AP53: =AP55/AVERAGE(AN48,AP48) -> 0 | AQ53: =AQ55/AVERAGE(AP48,AQ48) -> 0.52147567 | AR53: =AR55/AVERAGE(AQ48,AR48) -> 0 | AS53: =AS55/AVERAGE(AR48,AS48) -> 0.59865745 | AT53: =AT55/AVERAGE(AP48:AS48) -> 1.1202001 | AU53: =AU55/AVERAGE(AS48,AU48) -> 0 | AV53: =AV55/AVERAGE(AU48,AV48) -> 0 | AW53: =AW55/AVERAGE(AV48,AW48) -> 0.78039644 | AX53: =AX55/AVERAGE(AW48,AX48) -> 1.0405096 | AY53: =AY55/AVERAGE(AU48:AX48) -> 1.8209878 | AZ53: =AZ55/AVERAGE(AX48,AZ48) -> 0 | BA53: =BA55/AVERAGE(AZ48,BA48) -> 0 | BB53: =BB55/AVERAGE(BA48,BB48) -> 0.25688213 | BC53: =BC55/AVERAGE(BB48,BC48) -> 1.5604519 | BD53: =BD55/AVERAGE(AZ48:BC48) -> 1.8174903 | BE53: =BE55/AVERAGE(BC48,BE48) -> 0 | BF53: =BF55/AVERAGE(BD48,BF48) -> 1.0872734 | BG53: =BG55/AVERAGE(BE48,BG48) -> 0 | BH53: =BH55/AVERAGE(BG48,BH48) -> 0 | BI53: =BI55/AVERAGE(BE48:BH48) -> 1.0872734 | BJ53: =BJ55/AVERAGE(BH48,BJ48) -> 0 | BK53: =BK55/AVERAGE(BI48,BK48) -> 0.56601449 | BL53: =BL55/AVERAGE(BJ48,BL48) -> 0 | BM53: =BM55/AVERAGE(BL48,BM48) -> 0 | BN53: =BN55/AVERAGE(BJ48:BM48) -> 0.57071024 | BO53: =BO55/AVERAGE(BM48,BO48) -> 0 | BP53: =BP55/AVERAGE(BN48,BP48) -> 0.51184551 | BQ53: =BQ55/AVERAGE(BP48,BQ48) -> 0 | BR53: =BR55/AVERAGE(BQ48,BR48) -> 0.33340357 | BS53: =BS55/AVERAGE(BO48:BR48) -> 0.84580199 | BT53: =BT55/AVERAGE(BR48,BT48) -> 0 | BU53: =BU55/AVERAGE(BT48,BU48) -> 0.5967828 | BV53: =BV55/AVERAGE(BU48,BV48) -> 0 | BW53: =BW55/AVERAGE(BV48,BW48) -> 0 | BX53: =BX55/AVERAGE(BT48:BW48) -> 0.56650468 | BY53: =BY55/AVERAGE(BW48,BY48) -> 0 | BZ53: =BZ55/AVERAGE(BY48,BZ48) -> 0.89188515 | CA53: =CA55/AVERAGE(BZ48,CA48) -> 0 | CB53: =CB55/AVERAGE(CA48,CB48) -> 2.2773285 | CC53: =CC55/AVERAGE(BY48:CB48) -> 3.1692137 | CD53: =CD55/AVERAGE(CB48,CD48) -> 0 | CE53: =CE55/AVERAGE(CD48,CE48) -> 0 | CF53: =CF55/AVERAGE(CE48,CF48) -> 0 | CG53: =CG55/AVERAGE(CF48,CG48) -> 0 | CH53: =CH55/AVERAGE(CD48:CG48) -> 0 | CI53: =CI55/AVERAGE(CG48,CI48) -> 2.1650716 | CJ53: =CJ55/AVERAGE(CI48,CJ48) -> 0 | CK53: =CK55/AVERAGE(CJ48,CK48) -> 0 | CL53: =CL55/AVERAGE(CK48,CL48) -> 0 | CM53: =CM55/AVERAGE(CI48:CL48) -> 2.1650716 | CN53: =CN55/AVERAGE(CL48,CN48) -> 4.3357444 | CO53: =CO55/AVERAGE(CN48,CO48) -> 0 | CP53: =CP55/AVERAGE(CO48,CP48) -> 0 | CQ53: =CQ55/AVERAGE(CP48,CQ48) -> 0 | CR53: =CR55/AVERAGE(CN48:CQ48) -> 4.3357444 | CS53: =CS55/AVERAGE(CQ48,CS48) -> 4.8125046 | CT53: =CT55/AVERAGE(CS48,CT48) -> 0 | CU53: =CU55/AVERAGE(CT48,CU48) -> 0 | CV53: =CV55/AVERAGE(CU48,CV48) -> 0 | CW53: =CW55/AVERAGE(CS48:CV48) -> 4.8125046 | CX53: =CX55/AVERAGE(CV48,CX48) -> 5.1817271 | CY53: =CY55/AVERAGE(CX48,CY48) -> 0 | CZ53: =CZ55/AVERAGE(CY48,CZ48) -> 0 | DA53: =DA55/AVERAGE(CZ48,DA48) -> 0 | DB53: =DB55/AVERAGE(CX48:DA48) -> 5.1817271
A54: Dividends (R$000') | B54: =Macro!B$3 -> 1Q10 | C54: =Macro!C$3 -> 2Q10 | D54: =Macro!D$3 -> 3Q10 | E54: =Macro!E$3 -> 4Q10
A55: Declared dividends | B55: 0 | C55: 0 | D55: 0 | E55: 142559 | F55: =SUM(B55:E55) -> 142559 | G55: 0 | H55: 0 | I55: 0 | J55: 118315 | K55: =SUM(G55:J55) -> 118315 | L55: 0 | M55: 0 | N55: 0 | O55: ='BS & FCF'!O39 -> 156818 | P55: =SUM(L55:O55) -> 156818 | Q55: 50000 | R55: 0 | S55: 0 | T55: ='BS & FCF'!U39 -> 170826 | U55: =SUM(Q55:T55) -> 220826 | V55: 0 | W55: 0 | X55: 0 | Y55: 157106 | Z55: =SUM(V55:Y55) -> 157106 | AA55: 0 | AB55: 0 | AC55: 0 | AD55: 106353 | AE55: =SUM(AA55:AD55) -> 106353 | AF55: 0 | AG55: 0 | AH55: 0 | AI55: =0.094063*AI48 -> 35946.081 | AJ55: =SUM(AF55:AI55) -> 35946.081 | AK55: 0 | AL55: 0 | AM55: 0 | AN55: 0 | AO55: =SUM(AK55:AN55) -> 0 | AP55: 0 | AQ55: 200000 | AR55: 0 | AS55: 230000 | AT55: =SUM(AP55:AS55) -> 430000 | AU55: 0 | AV55: 0 | AW55: 300000 | AX55: 400000 | AY55: =SUM(AU55:AX55) -> 700000 | AZ55: 0 | BA55: 0 | BB55: 98762.316 | BC55: 600000 | BD55: =SUM(AZ55:BC55) -> 698762.32 | BE55: 0 | BF55: 418060.98 | BG55: 0 | BH55: 0 | BI55: =SUM(BE55:BH55) -> 418060.98 | BJ55: 0 | BK55: 217159.67 | BL55: 0 | BM55: 0 | BN55: =SUM(BJ55:BM55) -> 217159.67 | BO55: 0 | BP55: 192108.93 | BQ55: 0 | BR55: 125000 | BS55: =SUM(BO55:BR55) -> 317108.93 | BT55: 0 | BU55: 223746.4 | BV55: 0 | BW55: 0 | BX55: =SUM(BT55:BW55) -> 223746.4 | BY55: 0 | BZ55: 391636.58 | CA55: 0 | CB55: 1000000 | CC55: =SUM(BY55:CB55) -> 1391636.6 | CD55: 0 | CE55: 0 | CF55: 0 | CG55: 0 | CH55: =SUM(CD55:CG55) -> 0 | CI55: =50%*CH45 -> 943446.09 | CJ55: 0 | CK55: 0 | CL55: 0 | CM55: =SUM(CI55:CL55) -> 943446.09 | CN55: =CM45*80% -> 1889332.9 | CO55: 0 | CP55: 0 | CQ55: 0 | CR55: =SUM(CN55:CQ55) -> 1889332.9 | CS55: =CR45*80% -> 2097084.7 | CT55: 0 | CU55: 0 | CV55: 0 | CW55: =SUM(CS55:CV55) -> 2097084.7 | CX55: =CW45*80% -> 2257976.2 | CY55: 0 | CZ55: 0 | DA55: 0 | DB55: =SUM(CX55:DA55) -> 2257976.2
A56: Payout (%) | B56: =B55/B45 -> 0 | C56: =C55/C45 -> 0 | D56: =D55/D45 -> 0 | E56: =E55/E45 -> 1.7274435 | F56: =F55/F45 -> 0.23736334 | G56: =G55/G45 -> 0 | H56: =H55/H45 -> 0 | I56: =I55/I45 -> 0 | ... DB56: =DB55/DB45 -> 0.72660286
A58: Income statement summary | B58: =Macro!B$3 -> 1Q10 | C58: =Macro!C$3 -> 2Q10 | D58: =Macro!D$3 -> 3Q10 | E58: =Macro!E$3 -> 4Q10 | F58: =Macro!F$3 -> 2010 | G58: =Macro!G$3 -> 1Q11 | H58: =Macro!H$3 -> 2Q11 | I58: =Macro!I$3 -> 3Q11 | ... DB58: =Macro!DB$3 -> 2030E
A59: (=) Net revenues | B59: =B9 -> 1132448 | C59: =C9 -> 1205835 | D59: =D9 -> 1162549 | E59: =E9 -> 1389273 | F59: =F9 -> 4890105 | G59: =G9 -> 1200742 | H59: =H9 -> 1382884 | I59: =I9 -> 1559602 | ... DB59: =DB9 -> 14754098
A60: (-) COGS (ex-interest) | B60: =B11+B14 -> -728281 | C60: =C11+C14 -> -793472 | D60: =D11+D14 -> -736494 | E60: =E11+E14 -> -999033 | F60: =F11+F14 -> -3257280 | G60: =G11+G14 -> -832942 | H60: =H11+H14 -> -958024 | I60: =I11+I14 -> -1052896 | ... DB60: =DB11+DB14 -> -9567917.6
A61: (=) Adjusted gross profit | B61: =B59+B60 -> 404167 | C61: =C59+C60 -> 412363 | D61: =D59+D60 -> 426055 | E61: =E59+E60 -> 390240 | F61: =F59+F60 -> 1632825 | G61: =G59+G60 -> 367800 | H61: =H59+H60 -> 424860 | I61: =I59+I60 -> 506706 | ... DB61: =DB59+DB60 -> 5186180.4
A62: (-) Operating expenses | B62: =B18+B21+B31+B32 -> -168580 | C62: =C18+C21+C31+C32 -> -177317 | D62: =D18+D21+D31+D32 -> -184561 | E62: =E18+E21+E31+E32 -> -210364 | F62: =F18+F21+F31+F32 -> -740822 | G62: =G18+G21+G31+G32 -> -197021 | H62: =H18+H21+H31+H32 -> -245273 | I62: =I18+I21+I31+I32 -> -224014 | ... DB62: =DB18+DB21+DB31+DB32 -> -2292962.5
A63: (=) EBIT | B63: =B61+B62 -> 235587 | C63: =C61+C62 -> 235046 | D63: =D61+D62 -> 241494 | E63: =E61+E62 -> 179876 | F63: =F61+F62 -> 892003 | G63: =G61+G62 -> 170779 | H63: =H61+H62 -> 179587 | I63: =I61+I62 -> 282692 | ... DB63: =DB61+DB62 -> 2893217.9
A64: (+) D&A | B64: =1220+17100 -> 18320 | C64: =2622+8294 -> 10916 | D64: =2885+8437 -> 11322 | E64: =2158+16817 -> 18975 | F64: =SUM(B64:E64) -> 59533 | G64: =3377+7032 -> 10409 | H64: =6508+10102-G64 -> 6201 | I64: 9000 | J64: =13336+19781-G64-H64-I64 -> 7507 | K64: =SUM(G64:J64) -> 33117 | L64: =20169+2482 -> 22651 | M64: =51646+3520-L64 -> 32515 | N64: =85248-L64-M64 -> 30082 | O64: =12412+7450-N64-M64-L64 -> -65386 | P64: =SUM(L64:O64) -> 19862 | Q64: =25332+930 -> 26262 | R64: =49387+2079-Q64 -> 25204 | S64: =77057-Q64-R64 -> 25591 | T64: =96012-R64-S64-Q64 -> 18955 | U64: =SUM(Q64:T64) -> 96012 | V64: =23249+1390 -> 24639 | W64: =44196+3579-V64 -> 23136 | X64: =64043+3649-W64-V64 -> 19917 | Y64: =84350-4250-W64-X64-V64 -> 12408 | Z64: =SUM(V64:Y64) -> 80100 | AA64: =16871+1977 -> 18848 | AB64: =33239+2912-AA64 -> 17303 | AC64: =53231+4026-AB64-AA64 -> 21106 | AD64: =75953-8764-AB64-AC64-AA64 -> 9932 | AE64: =SUM(AA64:AD64) -> 67189 | AF64: =27748+2099 -> 29847 | AG64: =44261+3176-AF64 -> 17590 | AH64: =69344+3700-AG64-AF64 -> 25607 | AI64: =97438-8806-AG64-AH64-AF64 -> 15588 | AJ64: =SUM(AF64:AI64) -> 88632 | AK64: =21302+40 -> 21342 | AL64: =39063+10940-AK64 -> 28661 | AM64: =39755+11009-AL64-AK64 -> 761 | AN64: =55495-11039-AL64-AM64-AK64 -> -6308 | AO64: =SUM(AK64:AN64) -> 44456 | AP64: =15816+51 -> 15867 | AQ64: =25358+93-AP64 -> 9584 | AR64: =48170+175-AQ64-AP64 -> 22894 | AS64: =61369-AQ64-AR64-AP64 -> 13024 | AT64: =SUM(AP64:AS64) -> 61369 | AU64: =24163+196 -> 24359 | AV64: =15966+512-AU64 -> -7881 | AW64: =47230+786-AV64-AU64 -> 31538 | AX64: =74678-AV64-AW64-AU64 -> 26662 | AY64: =SUM(AU64:AX64) -> 74678 | AZ64: =17141+58 -> 17199 | BA64: =30729+195-AZ64 -> 13725 | BB64: =39572+315-BA64-AZ64 -> 8963 | BC64: =51163-BA64-BB64-AZ64 -> 11276 | BD64: =SUM(AZ64:BC64) -> 51163 | BE64: =10896+36 -> 10932 | BF64: =21318+76-BE64 -> 10462 | BG64: =32295+119-BF64-BE64 -> 11020 | BH64: =40023+149-BF64-BG64-BE64 -> 7758 | BI64: =SUM(BE64:BH64) -> 40172 | BJ64: =8497+35 -> 8532 | BK64: =17723+60-BJ64 -> 9251 | BL64: =32285+8330-BK64-BJ64 -> 22832 | BM64: =43474+19799-BK64-BL64-BJ64 -> 22658 | BN64: =SUM(BJ64:BM64) -> 63273 | BO64: =18751+10533 -> 29284 | BP64: =30059+15296-BO64 -> 16071 | BQ64: =46327+41330-BP64-BO64 -> 42302 | BR64: =67088+23861-BP64-BQ64-BO64 -> 3292 | BS64: =SUM(BO64:BR64) -> 90949 | BT64: =19888+3750 -> 23638 | BU64: =31427+8576-BT64 -> 16365 | BV64: =45054+34948-BU64-BT64 -> 39999 | BW64: =50815+49244-BU64-BV64-BT64 -> 20057 | BX64: =SUM(BT64:BW64) -> 100059 | BY64: =21373+8899 -> 30272 | BZ64: =35128+18946-BY64 -> 23802 | CA64: =47429+35274-BZ64-BY64 -> 28629 | CB64: =79338+53237-BZ64-CA64-BY64 -> 49872 | CC64: =SUM(BY64:CB64) -> 132575 | CD64: =38968+15615 -> 54583 | CE64: =68157+27592-CD64 -> 41166 | CF64: ='BS & FCF'!CF121 -> 42795.671 | CG64: ='BS & FCF'!CG121 -> 43074.13 | CH64: =SUM(CD64:CG64) -> 181618.8 | CI64: ='BS & FCF'!CI121 -> 43354.4 | CJ64: ='BS & FCF'!CJ121 -> 43636.495 | CK64: ='BS & FCF'!CK121 -> 43920.425 | CL64: ='BS & FCF'!CL121 -> 44206.202 | CM64: =SUM(CI64:CL64) -> 175117.52 | CN64: ='BS & FCF'!CN121 -> 44493.839 | CO64: ='BS & FCF'!CO121 -> 44783.348 | CP64: ='BS & FCF'!CP121 -> 45074.74 | CQ64: ='BS & FCF'!CQ121 -> 45368.028 | CR64: =SUM(CN64:CQ64) -> 179719.96 | CS64: ='BS & FCF'!CS121 -> 45663.225 | CT64: ='BS & FCF'!CT121 -> 45960.342 | CU64: ='BS & FCF'!CU121 -> 46259.393 | CV64: ='BS & FCF'!CV121 -> 46560.389 | CW64: =SUM(CS64:CV64) -> 184443.35 | CX64: ='BS & FCF'!CX121 -> 46863.344 | CY64: ='BS & FCF'!CY121 -> 47168.27 | CZ64: ='BS & FCF'!CZ121 -> 47475.181 | DA64: ='BS & FCF'!DA121 -> 47784.088 | DB64: =SUM(CX64:DA64) -> 189290.88
A65: (=) EBITDA | B65: =B63+B64 -> 253907 | C65: =C63+C64 -> 245962 | D65: =D63+D64 -> 252816 | E65: =E63+E64 -> 198851 | F65: =F63+F64 -> 951536 | G65: =G63+G64 -> 181188 | H65: =H63+H64 -> 185788 | I65: =I63+I64 -> 291692 | ... DB65: =DB63+DB64 -> 3082508.8
A66: (+/-) Net financial results | B66: =B67+B68 -> -4162 | C66: =C67+C68 -> 1185 | D66: =D67+D68 -> 5007 | E66: =E67+E68 -> -32993 | F66: =F67+F68 -> -30963 | G66: =G67+G68 -> -35877 | H66: =H67+H68 -> -22790 | I66: =I67+I68 -> -53541 | ... DB66: =DB67+DB68 -> 25780.268
A67: (+) Interest income | B67: =B24+B28 -> 57269 | C67: =C24+C28 -> 79023 | D67: =D24+D28 -> 82309 | E67: =E24+E28 -> 69011 | F67: =F24+F28 -> 287612 | G67: =G24+G28 -> 59606 | H67: =H24+H28 -> 89136 | I67: =I24+I28 -> 101379 | ... DB67: =DB24+DB28 -> 1112936.4
A68: (-) Interest expense | B68: =B26+B13 -> -61431 | C68: =C26+C13 -> -77838 | D68: =D26+D13 -> -77302 | E68: =E26+E13 -> -102004 | F68: =F26+F13 -> -318575 | G68: =G26+G13 -> -95483 | H68: =H26+H13 -> -111926 | I68: =I26+I13 -> -154920 | ... DB68: =DB26+DB13 -> -1087156.1
A69: (+/-) Other income (expenses) | B69: =B34+B36+B33 -> -20628 | C69: =C34+C36+C33 -> -3544 | D69: =D34+D36+D33 -> -15792 | E69: =E34+E36+E33 -> -6735 | F69: =F34+F36+F33 -> -46699 | G69: =G34+G36+G33 -> -2943 | H69: =H34+H36+H33 -> -2802 | I69: =I34+I36+I33 -> -4216 | ... DB69: =DB34+DB36+DB33 -> 952727.89
A70: (=) EBT | B70: =B37 -> 210797 | C70: =C37 -> 232687 | D70: =D37 -> 230709 | E70: =E37 -> 140148 | F70: =F37 -> 814341 | G70: =G37 -> 131959 | H70: =H37 -> 153995 | I70: =I37 -> 224935 | ... DB70: =DB37 -> 3871726
A71: (-) Income taxes | B71: =B38+B40 -> -24524 | C71: =C38+C40 -> -35596 | D71: =D38+D40 -> -34567 | E71: =E38+E40 -> -34243 | F71: =F38+F40 -> -128930 | G71: =G38+G40 -> -41884 | H71: =H38+H40 -> -35054 | I71: =I38+I40 -> -47374 | ... DB71: =DB38+DB40 -> -283278.68
A72: (-) Minority interest | B72: =B43 -> -12033 | C72: =C43 -> -29297 | D72: =D43 -> -20108 | E72: =E43 -> -23379 | F72: =F43 -> -84817 | G72: =G43 -> -15894 | H72: =H43 -> -10068 | I72: =I43 -> -30808 | ... DB72: =DB43 -> -480867.81
A73: (=) Net income (reported) | B73: =B45 -> 174240 | C73: =C45 -> 167794 | D73: =D45 -> 176034 | E73: =E45 -> 82526 | F73: =F45 -> 600594 | G73: =G45 -> 74181 | H73: =H45 -> 108873 | I73: =I45 -> 146753 | ... DB73: =DB45 -> 3107579.6
A74: (=) Net income (adjusted) | B74: =B73-B33-B36 -> 179227 | C74: =C73-C33-C36 -> 171338 | D74: =D73-D33-D36 -> 181072 | E74: =E73-E33-E36 -> 82526 | F74: =F73-F33-F36 -> 614163 | G74: =G73-G33-G36 -> 74181 | H74: =H73-H33-H36 -> 108873 | I74: =I73-I33-I36 -> 146753 | ... DB74: =DB73-DB33-DB36 -> 3107579.6
CE75: =CE74-'Business lines'!CE128 -> 360581.66
A76: Margins (%) | B76: =Macro!B$3 -> 1Q10 | C76: =Macro!C$3 -> 2Q10 | D76: =Macro!D$3 -> 3Q10 | E76: =Macro!E$3 -> 4Q10 | F76: =Macro!F$3 -> 2010 | G76: =Macro!G$3 -> 1Q11 | H76: =Macro!H$3 -> 2Q11 | I76: =Macro!I$3 -> 3Q11 | ... DB76: =Macro!DB$3 -> 2030E
A77: Adj. gross margin (ex-interest) | B77: =B61/B59 -> 0.35689674 | C77: =C61/C59 -> 0.34197299 | D77: =D61/D59 -> 0.36648348 | E77: =E61/E59 -> 0.28089512 | F77: =F61/F59 -> 0.33390387 | G77: =G61/G$59 -> 0.3063106 | H77: =H61/H$59 -> 0.3072275 | I77: =I61/I$59 -> 0.32489443 | J77: =J61/J$59 -> 0.31575662 | K77: =K61/K$59 -> 0.31430632 | L77: =L61/L$59 -> 0.34144467 | M77: =M61/M$59 -> 0.32272572 | N77: =N61/N$59 -> 0.3491376 | ... DB77: =DB61/DB$59 -> 0.35150779
A78: Gross margin | B78: =B16/B9 -> 0.34846368 | C78: =C16/C9 -> 0.32594924 | D78: =D16/D9 -> 0.35178216 | E78: =E16/E9 -> 0.24473808 | F78: =F16/F9 -> 0.31423252 | G78: =(G16)/G9 -> 0.27375823 | H78: =(H16)/H9 -> 0.27659298 | I78: =(I16)/I9 -> 0.28594539 | J78: =(J16)/J9 -> 0.29054933 | K78: =(K16)/K9 -> 0.2829365 | L78: =(L16)/L9 -> 0.31362035 | M78: =(M16)/M9 -> 0.29710676 | N78: =(N16)/N9 -> 0.31726017 | ... DB78: =(DB16)/DB9 -> 0.33578683
A79: Development gross margin (ex-interest) | B79: =(B5+B11)/B5 -> 0.37883928 | C79: =(C5+C11)/C5 -> 0.35928191 | D79: =(D5+D11)/D5 -> 0.38995335 | E79: =(E5+E11)/E5 -> 0.30720559 | F79: =(F5+F11)/F5 -> 0.35634728 | G79: =(G5+G11)/G5 -> 0.33569671 | H79: =(H5+H11)/H5 -> 0.3355713 | I79: =(I5+I11)/I5 -> 0.34851175 | ... DB79: =(DB5+DB11)/DB5 -> 0.35664756
A80: Services gross margin (ex-interest) | B80: =(B6+B14)/B6 -> 0.25577157 | C80: =(C6+C14)/C6 -> 0.20561269 | D80: =(D6+D14)/D6 -> 0.2627024 | E80: =(E6+E14)/E6 -> 0.37928731 | F80: =(F6+F14)/F6 -> 0.29728326 | G80: =(G6+G14)/G6 -> 0.19257752 | H80: =(H6+H14)/H6 -> 0.2388385 | I80: =(I6+I14)/I6 -> 0.41369121 | ... DB80: =(DB6+DB14)/DB6 -> 0.83659983
A81: EBITDA margin | B81: =B65/B59 -> 0.22421074 | C81: =C65/C59 -> 0.2039765 | D81: =D65/D59 -> 0.21746696 | E81: =E65/E59 -> 0.14313314 | F81: =F65/F59 -> 0.19458396 | G81: =G65/G$59 -> 0.1508967 | H81: =H65/H$59 -> 0.13434822 | I81: =I65/I$59 -> 0.18702977 | J81: =J65/J$59 -> 0.19513116 | K81: =K65/K$59 -> 0.17068033 | L81: =L65/L$59 -> 0.20383498 | M81: =M65/M$59 -> 0.1852724 | N81: =N65/N$59 -> 0.21383501 | ... DB81: =DB65/DB$59 -> 0.2089256
A82: EBIT Margin | B82: =B63/B59 -> 0.20803339 | C82: =C63/C59 -> 0.19492385 | D82: =D63/D59 -> 0.20772802 | E82: =E63/E59 -> 0.12947491 | F82: =F63/F59 -> 0.18240978 | G82: =G63/G59 -> 0.14222789 | H82: =H63/H59 -> 0.12986411 | I82: =I63/I59 -> 0.18125906 | ... DB82: =DB63/DB59 -> 0.19609588
A83: Adj. net margin | B83: =B74/B$59 -> 0.1582651 | C83: =C74/C$59 -> 0.14209075 | D83: =D74/D$59 -> 0.1557543 | E83: =E74/E$59 -> 0.059402292 | F83: =F74/F$59 -> 0.12559301 | G83: =G74/G$59 -> 0.0617793 | H83: =H74/H$59 -> 0.078728946 | I83: =I74/I$59 -> 0.094096443 | ... DB83: =DB74/DB$59 -> 0.21062484
A84: Growth rate (%)
A85: Net revenue | G85: =G59/B59-1 -> 0.060306522 | H85: =H59/C59-1 -> 0.14682689 | I85: =I59/D59-1 -> 0.34153657 | J85: =J59/E59-1 -> 0.4277633 | K85: =K59/F59-1 -> 0.25289355 | L85: =L59/G59-1 -> 0.22119739 | M85: =M59/H59-1 -> 0.0017203178 | N85: =N59/I59-1 -> -0.13442532 | ... DB85: =DB59/CW59-1 -> 0.071175283
A86: Adj. gross profit | G86: =G61/B61-1 -> -0.089980132 | H86: =H61/C61-1 -> 0.030305823 | I86: =I61/D61-1 -> 0.18929716 | J86: =J61/E61-1 -> 0.60496105 | K86: =K61/F61-1 -> 0.17935847 | L86: =L61/G61-1 -> 0.36126971 | M86: =M61/H61-1 -> 0.052252507 | N86: =N61/I61-1 -> -0.069837342 | ... DB86: =DB61/CW61-1 -> 0.069121935
A87: Adj. gross margin (bps) | G87: =(G77-B77)*10000 -> -505.86143 | H87: =(H77-C77)*10000 -> -347.45485 | I87: =(I77-D77)*10000 -> -415.89049 | J87: =(J77-E77)*10000 -> 348.61509 | K87: =(K77-F77)*10000 -> -195.97552 | L87: =(L77-G77)*10000 -> 351.34071 | M87: =(M77-H77)*10000 -> 154.98216 | N87: =(N77-I77)*10000 -> 242.43171 | ... DB87: =(DB77-CW77)*10000 -> -6.7510312
A88: Gross margin (bps) | G88: =(G78-B78)*10000 -> -747.05456 | H88: =(H78-C78)*10000 -> -493.56263 | I88: =(I78-D78)*10000 -> -658.36773 | J88: =(J78-E78)*10000 -> 458.11257 | K88: =(K78-F78)*10000 -> -312.96012 | L88: =(L78-G78)*10000 -> 398.62121 | M88: =(M78-H78)*10000 -> 205.13784 | N88: =(N78-I78)*10000 -> 313.14781 | ... DB88: =(DB78-CW78)*10000 -> -2.2240485
A89: EBITDA | G89: =G65/B65-1 -> -0.28640014 | H89: =H65/C65-1 -> -0.24464755 | I89: =I65/D65-1 -> 0.15377191 | J89: =J65/E65-1 -> 0.94644734 | K89: =K65/F65-1 -> 0.098982067 | L89: =L65/G65-1 -> 0.6496236 | M89: =M65/H65-1 -> 0.38141861 | N89: =N65/I65-1 -> -0.010370528 | ... DB89: =DB65/CW65-1 -> 0.094257428
A90: Net income | G90: =G73/B73-1 -> -0.57425964 | H90: =H73/C73-1 -> -0.35115082 | I90: =I73/D73-1 -> -0.16633718 | J90: =J73/E73-1 -> 1.0401328 | K90: =K73/F73-1 -> -0.17053617 | L90: =L73/G73-1 -> 0.58943665 | M90: =M73/H73-1 -> 0.31111479 | N90: =N73/I73-1 -> 0.02481721 | ... DB90: =DB73/CW73-1 -> 0.10101411
A91: Net margin (bps) | G91: =(G83-B83)*10000 -> -964.85804 | H91: =(H83-C83)*10000 -> -633.61804 | I91: =(I83-D83)*10000 -> -616.57853 | J91: =(J83-E83)*10000 -> 437.37882 | K91: =(K83-F83)*10000 -> -383.70861 | L91: =(L83-G83)*10000 -> 309.04336 | M91: =(M83-H83)*10000 -> 243.16468 | N91: =(N83-I83)*10000 -> 173.11222 | ... DB91: =(DB83-CW83)*10000 -> 57.081905
A93: Financial results calculation (R$000') | B93: =Macro!B$3 -> 1Q10 | C93: =Macro!C$3 -> 2Q10 | D93: =Macro!D$3 -> 3Q10 | E93: =Macro!E$3 -> 4Q10 | F93: =Macro!F$3 -> 2010 | G93: =Macro!G$3 -> 1Q11 | H93: =Macro!H$3 -> 2Q11 | I93: =Macro!I$3 -> 3Q11 | ... DB93: =Macro!DB$3 -> 2030E
A94: Capitalized Interest | B94: 8096 | C94: 10284 | D94: =16997+86989-B94-C94 -> 85606 | E94: 104647 | F94: =SUM(B94:E94) -> 208633 | G94: 63000 | H94: 68000 | I94: =170236-G94-H94+47296 -> 86532 | J94: =335173-G94-H94-I94 -> 117641 | K94: =SUM(G94:J94) -> 335173 | L94: =129059-M94 -> 69442 | M94: 59617 | N94: 71175 | O94: =267453-L94-M94-N94 -> 67219 | P94: =SUM(L94:O94) -> 267453 | Q94: =100196-R94 -> 51736 | R94: 48460 | S94: 54533 | T94: =200016-SUM(Q94:S94) -> 45287 | U94: =SUM(Q94:T94) -> 200016 | V94: 48730 | W94: 49819 | X94: 44249 | Y94: =188497-SUM(V94:X94) -> 45699 | Z94: =SUM(V94:Y94) -> 188497 | AA94: 47765 | AB94: 49474 | AC94: 48156 | AD94: =195059-SUM(AA94:AC94) -> 49664 | AE94: =SUM(AA94:AD94) -> 195059 | AF94: 58289 | AG94: 61648 | AH94: 60476 | AI94: =232947-SUM(AF94:AH94) -> 52534 | AJ94: =SUM(AF94:AI94) -> 232947 | AK94: 50242 | AL94: 49444 | AM94: 41912 | AN94: =173966-SUM(AK94:AM94) -> 32368 | AO94: =SUM(AK94:AN94) -> 173966 | AP94: 22538 | AQ94: 17595 | AR94: 3348 | AS94: =49467-SUM(AP94:AR94) -> 5986 | AT94: =SUM(AP94:AS94) -> 49467 | AU94: 5455 | AV94: 3624 | AW94: 2786 | AX94: =13161-SUM(AU94:AW94) -> 1296 | AY94: =SUM(AU94:AX94) -> 13161 | AZ94: 939 | BA94: 2072 | BB94: 3783 | BC94: =9479-SUM(AZ94:BB94) -> 2685 | BD94: =SUM(AZ94:BC94) -> 9479 | BE94: 2666 | BF94: 2840 | BG94: 5477 | BH94: =19439-SUM(BE94:BG94) -> 8456 | BI94: =SUM(BE94:BH94) -> 19439 | BJ94: 13289 | BK94: 16218 | BL94: 20236 | BM94: =72116-SUM(BJ94:BL94) -> 22373 | BN94: =SUM(BJ94:BM94) -> 72116 | BO94: 26123 | BP94: 31816 | BQ94: 31929 | BR94: =117769-SUM(BO94:BQ94) -> 27901 | BS94: =SUM(BO94:BR94) -> 117769 | BT94: 13914 | BU94: 35072 | BV94: 33742 | BW94: =117769-SUM(BT94:BV94) -> 35041 | BX94: =SUM(BT94:BW94) -> 117769 | BY94: 41655 | BZ94: 49081 | CA94: 53894 | CB94: =208994-SUM(BY94:CA94) -> 64364 | CC94: =SUM(BY94:CB94) -> 208994 | CD94: 68227 | CE94: 58060 | CF94: =-CF95*CF98 -> 63775.663 | CG94: =-CG95*CG98 -> 64559.501 | CH94: =SUM(CD94:CG94) -> 254622.16 | CI94: =-CI95*CI98 -> 74568.374 | CJ94: =-CJ95*CJ98 -> 73761.33 | CK94: =-CK95*CK98 -> 69967.859 | CL94: =-CL95*CL98 -> 67189.264 | CM94: =SUM(CI94:CL94) -> 285486.83 | CN94: =-CN95*CN98 -> 67618.695 | CO94: =-CO95*CO98 -> 67901.437 | CP94: =-CP95*CP98 -> 68486.691 | CQ94: =-CQ95*CQ98 -> 69345.497 | CR94: =SUM(CN94:CQ94) -> 273352.32 | CS94: =-CS95*CS98 -> 60245.325 | CT94: =-CT95*CT98 -> 60177.452 | CU94: =-CU95*CU98 -> 60456.031 | CV94: =-CV95*CV98 -> 61117.076 | CW94: =SUM(CS94:CV94) -> 241995.88 | CX94: =-CX95*CX98 -> 61604.646 | CY94: =-CY95*CY98 -> 61727.199 | CZ94: =-CZ95*CZ98 -> 62075.537 | DA94: =-DA95*DA98 -> 62878.676 | DB94: =SUM(CX94:DA94) -> 248286.06
A95: Total Interest Expense | B95: =B26-B94 -> -59977 | C95: =C26-C94 -> -68800 | D95: =D26-D94 -> -145817 | E95: =E26-E94 -> -156419 | F95: =SUM(B95:E95) -> -431013 | G95: =G26-G94 -> -119396 | H95: =H26-H94 -> -137562 | I95: =I26-I94 -> -180707 | J95: =J26-J94 -> -211224 | K95: =SUM(G95:J95) -> -648889 | L95: =L26-L94 -> -140079 | M95: =M26-M94 -> -134479 | N95: =N26-N94 -> -116181 | O95: =O26-O94 -> -115425 | P95: =SUM(L95:O95) -> -506164 | Q95: =Q26-Q94 -> -92671 | R95: =R26-R94 -> -88123 | S95: =S26-S94 -> -99909 | T95: =T26-T94 -> -98601 | U95: =SUM(Q95:T95) -> -379304 | V95: =V26-V94 -> -109180 | W95: =W26-W94 -> -118637 | X95: =X26-X94 -> -110952 | Y95: =Y26-Y94 -> -112227 | Z95: =SUM(V95:Y95) -> -450996 | AA95: =AA26-AA94 -> -111782 | AB95: =AB26-AB94 -> -138001 | AC95: =AC26-AC94 -> -135330 | AD95: =AD26-AD94 -> -123234 | AE95: =SUM(AA95:AD95) -> -508347 | AF95: =AF26-AF94 -> -117572 | AG95: =AG26-AG94 -> -118566 | AH95: =AH26-AH94 -> -114684 | AI95: =AI26-AI94 -> -108675 | AJ95: =SUM(AF95:AI95) -> -459497 | AK95: =AK26-AK94 -> -102242 | AL95: =AL26-AL94 -> -93813 | AM95: =AM26-AM94 -> -83968 | AN95: =AN26-AN94 -> -61523 | AO95: =SUM(AK95:AN95) -> -341546 | AP95: =AP26-AP94 -> -51731 | AQ95: =AQ26-AQ94 -> -46192 | AR95: =AR26-AR94 -> -53398 | AS95: =AS26-AS94 -> -49034 | AT95: =SUM(AP95:AS95) -> -200355 | AU95: =AU26-AU94 -> -43691 | AV95: =AV26-AV94 -> -35038 | AW95: =AW26-AW94 -> -41687 | AX95: =AX26-AX94 -> -42674 | AY95: =SUM(AU95:AX95) -> -163090 | AZ95: =AZ26-AZ94 -> -28829 | BA95: =BA26-BA94 -> -38126 | BB95: =BB26-BB94 -> -34766 | BC95: =BC26-BC94 -> -25688 | BD95: =SUM(AZ95:BC95) -> -127409 | BE95: =BE26-BE94 -> -45700 | BF95: =BF26-BF94 -> -45412 | BG95: =BG26-BG94 -> -68091 | BH95: =BH26-BH94 -> -89101 | BI95: =SUM(BE95:BH95) -> -248304 | BJ95: =BJ26-BJ94 -> -99831 | BK95: =BK26-BK94 -> -120826 | BL95: =BL26-BL94 -> -144157 | BM95: =BM26-BM94 -> -211688 | BN95: =SUM(BJ95:BM95) -> -576502 | BO95: =BO26-BO94 -> -171356 | BP95: =BP26-BP94 -> -180665 | BQ95: =BQ26-BQ94 -> -159956 | BR95: =BR26-BR94 -> -163745 | BS95: =SUM(BO95:BR95) -> -675722 | BT95: =BT26-BT94 -> -158245 | BU95: =BU26-BU94 -> -172678 | BV95: =BV26-BV94 -> -164060 | BW95: =BW26-BW94 -> -192574 | BX95: =SUM(BT95:BW95) -> -687557 | BY95: =BY26-BY94 -> -194272 | BZ95: =BZ26-BZ94 -> -235188 | CA95: =CA26-CA94 -> -244286 | CB95: =CB26-CB94 -> -263547 | CC95: =SUM(BY95:CB95) -> -937293 | CD95: =CD26-CD94 -> -291516 | CE95: =CE26-CE94 -> -321313 | CF95: =CF99+CF102 -> -283447.39 | CG95: =CG99+CG102 -> -286931.12 | CH95: =SUM(CD95:CG95) -> -1183207.5 | CI95: =CI99+CI102 -> -331414.99 | CJ95: =CJ99+CJ102 -> -327828.13 | CK95: =CK99+CK102 -> -310968.26 | CL95: =CL99+CL102 -> -298618.95 | CM95: =SUM(CI95:CL95) -> -1268830.3 | CN95: =CN99+CN102 -> -300527.53 | CO95: =CO99+CO102 -> -301784.16 | CP95: =CP99+CP102 -> -304385.29 | CQ95: =CQ99+CQ102 -> -308202.21 | CR95: =SUM(CN95:CQ95) -> -1214899.2 | CS95: =CS99+CS102 -> -267757 | CT95: =CT99+CT102 -> -267455.34 | CU95: =CU99+CU102 -> -268693.47 | CV95: =CV99+CV102 -> -271631.45 | CW95: =SUM(CS95:CV95) -> -1075537.3 | CX95: =CX99+CX102 -> -273798.43 | CY95: =CY99+CY102 -> -274343.11 | CZ95: =CZ99+CZ102 -> -275891.28 | DA95: =DA99+DA102 -> -279460.78 | DB95: =SUM(CX95:DA95) -> -1103493.6
A96: Yield | B96: =(1-B95/(AVERAGE('BS & FCF'!B28:B28)+AVERAGE('BS & FCF'!B31:B31)))^4-1 -> 0.090647431 | C96: =(1-C95/(AVERAGE('BS & FCF'!B28:C28)+AVERAGE('BS & FCF'!B31:C31)))^4-1 -> 0.10100923 | D96: =(1-D95/(AVERAGE('BS & FCF'!C28:D28)+AVERAGE('BS & FCF'!C31:D31)))^4-1 -> 0.20809052 | E96: =(1-E95/(AVERAGE('BS & FCF'!D28:E28)+AVERAGE('BS & FCF'!D31:E31)))^4-1 -> 0.20113118 | F96: =(1-F95/(AVERAGE('BS & FCF'!B28:E28)+AVERAGE('BS & FCF'!B31:E31)))-1 -> 0.13989167 | G96: =(1-G95/(AVERAGE('BS & FCF'!F28:G28)+AVERAGE('BS & FCF'!F31:G31)))^4-1 -> 0.1361132 | H96: =(1-H95/(AVERAGE('BS & FCF'!G28:H28)+AVERAGE('BS & FCF'!G31:H31)))^4-1 -> 0.14237779 | I96: =(1-I95/(AVERAGE('BS & FCF'!H28:I28)+AVERAGE('BS & FCF'!H31:I31)))^4-1 -> 0.16841655 | J96: =(1-J95/(AVERAGE('BS & FCF'!I28:J28)+AVERAGE('BS & FCF'!I31:J31)))^4-1 -> 0.18905082 | K96: =(1-K95/(AVERAGE('BS & FCF'!G28:J28)+AVERAGE('BS & FCF'!G31:J31)))-1 -> 0.14680935 | L96: =(1-L95/(AVERAGE('BS & FCF'!K28:L28)+AVERAGE('BS & FCF'!K31:L31)))^4-1 -> 0.12202805 | M96: =(1-M95/(AVERAGE('BS & FCF'!L28:M28)+AVERAGE('BS & FCF'!L31:M31)))^4-1 -> 0.11843366 | N96: =(1-N95/(AVERAGE('BS & FCF'!M28:N28)+AVERAGE('BS & FCF'!M31:N31)))^4-1 -> 0.10515279 | O96: =(1-O95/(AVERAGE('BS & FCF'!N28:O28)+AVERAGE('BS & FCF'!N31:O31)))^4-1 -> 0.10833668 | P96: =(1-P95/(AVERAGE('BS & FCF'!L28:O28)+AVERAGE('BS & FCF'!L31:O31)))-1 -> 0.11039472 | Q96: =(1-Q95/(AVERAGE('BS & FCF'!P28:Q28)+AVERAGE('BS & FCF'!P31:Q31)))^4-1 -> 0.090592921 | R96: =(1-R95/(AVERAGE('BS & FCF'!Q28:R28)+AVERAGE('BS & FCF'!Q31:R31)))^4-1 -> 0.08940948 | S96: =(1-S95/(AVERAGE('BS & FCF'!R28:S28)+AVERAGE('BS & FCF'!R31:S31)))^4-1 -> 0.10152326 | T96: =(1-T95/(AVERAGE('BS & FCF'!S28:T28)+AVERAGE('BS & FCF'!S31:T31)))^4-1 -> 0.095767989 | U96: =(1-U95/(AVERAGE('BS & FCF'!Q28:T28)+AVERAGE('BS & FCF'!Q31:T31)))-1 -> 0.091007289 | V96: =(1-V95/(AVERAGE('BS & FCF'!U28:V28)+AVERAGE('BS & FCF'!U31:V31)))^4-1 -> 0.099075002 | W96: =(1-W95/(AVERAGE('BS & FCF'!V28:W28)+AVERAGE('BS & FCF'!V31:W31)))^4-1 -> 0.10740077 | X96: =(1-X95/(AVERAGE('BS & FCF'!W28:X28)+AVERAGE('BS & FCF'!W31:X31)))^4-1 -> 0.10461471 | Y96: =(1-Y95/(AVERAGE('BS & FCF'!X28:Y28)+AVERAGE('BS & FCF'!X31:Y31)))^4-1 -> 0.11120309 | Z96: =(1-Z95/(AVERAGE('BS & FCF'!V28:Y28)+AVERAGE('BS & FCF'!V31:Y31)))-1 -> 0.10256755 | AA96: =(1-AA95/(AVERAGE('BS & FCF'!Z28:AA28)+AVERAGE('BS & FCF'!Z31:AA31)))^4-1 -> 0.11690984 | AB96: =(1-AB95/(AVERAGE('BS & FCF'!AA28:AB28)+AVERAGE('BS & FCF'!AA31:AB31)))^4-1 -> 0.14478041 | AC96: =(1-AC95/(AVERAGE('BS & FCF'!AB28:AC28)+AVERAGE('BS & FCF'!AB31:AC31)))^4-1 -> 0.13823559 | AD96: =(1-AD95/(AVERAGE('BS & FCF'!AC28:AD28)+AVERAGE('BS & FCF'!AC31:AD31)))^4-1 -> 0.1285996 | AE96: =(1-AE95/(AVERAGE('BS & FCF'!AA28:AD28)+AVERAGE('BS & FCF'!AA31:AD31)))-1 -> 0.12665658 | AF96: =(1-AF95/(AVERAGE('BS & FCF'!AE28:AF28)+AVERAGE('BS & FCF'!AE31:AF31)))^4-1 -> 0.12790663 | AG96: =(1-AG95/(AVERAGE('BS & FCF'!AF28:AG28)+AVERAGE('BS & FCF'!AF31:AG31)))^4-1 -> 0.13321961 | AH96: =(1-AH95/(AVERAGE('BS & FCF'!AG28:AH28)+AVERAGE('BS & FCF'!AG31:AH31)))^4-1 -> 0.13294514 | AI96: =(1-AI95/(AVERAGE('BS & FCF'!AH28:AI28)+AVERAGE('BS & FCF'!AH31:AI31)))^4-1 -> 0.12854289 | AJ96: =(1-AJ95/(AVERAGE('BS & FCF'!AF28:AI28)+AVERAGE('BS & FCF'!AF31:AI31)))-1 -> 0.12634147 | AK96: =(1-AK95/(AVERAGE('BS & FCF'!AJ28:AK28)+AVERAGE('BS & FCF'!AJ31:AK31)))^4-1 -> 0.11995652 | AL96: =(1-AL95/(AVERAGE('BS & FCF'!AK28:AL28)+AVERAGE('BS & FCF'!AK31:AL31)))^4-1 -> 0.11032062 | AM96: =(1-AM95/(AVERAGE('BS & FCF'!AL28:AM28)+AVERAGE('BS & FCF'!AL31:AM31)))^4-1 -> 0.10594309 | AN96: =(1-AN95/(AVERAGE('BS & FCF'!AM28:AN28)+AVERAGE('BS & FCF'!AM31:AN31)))^4-1 -> 0.088181138 | AO96: =(1-AO95/(AVERAGE('BS & FCF'!AK28:AN28)+AVERAGE('BS & FCF'!AK31:AN31)))-1 -> 0.10639176 | AP96: =(1-AP95/(AVERAGE('BS & FCF'!AO28:AP28)+AVERAGE('BS & FCF'!AO31:AP31)))^4-1 -> 0.089153819 | AQ96: =(1-AQ95/(AVERAGE('BS & FCF'!AP28:AQ28)+AVERAGE('BS & FCF'!AP31:AQ31)))^4-1 -> 0.083463032 | AR96: =(1-AR95/(AVERAGE('BS & FCF'!AQ28:AR28)+AVERAGE('BS & FCF'!AQ31:AR31)))^4-1 -> 0.082538071 | AS96: =(1-AS95/(AVERAGE('BS & FCF'!AR28:AS28)+AVERAGE('BS & FCF'!AR31:AS31)))^4-1 -> 0.075502139 | AT96: =(1-AT95/(AVERAGE('BS & FCF'!AP28:AS28)+AVERAGE('BS & FCF'!AP31:AS31)))-1 -> 0.080917326 | AU96: =(1-AU95/(AVERAGE('BS & FCF'!AT28:AU28)+AVERAGE('BS & FCF'!AT31:AU31)))^4-1 -> 0.07869662 | AV96: =(1-AV95/(AVERAGE('BS & FCF'!AU28:AV28)+AVERAGE('BS & FCF'!AU31:AV31)))^4-1 -> 0.067789523 | AW96: =(1-AW95/(AVERAGE('BS & FCF'!AV28:AW28)+AVERAGE('BS & FCF'!AV31:AW31)))^4-1 -> 0.075030567 | AX96: =(1-AX95/(AVERAGE('BS & FCF'!AW28:AX28)+AVERAGE('BS & FCF'!AW31:AX31)))^4-1 -> 0.068447538 | AY96: =(1-AY95/(AVERAGE('BS & FCF'!AU28:AX28)+AVERAGE('BS & FCF'!AU31:AX31)))-1 -> 0.06975251 | AZ96: =(1-AZ95/(AVERAGE('BS & FCF'!AY28:AZ28)+AVERAGE('BS & FCF'!AY31:AZ31)))^4-1 -> 0.044991227 | BA96: =(1-BA95/(AVERAGE('BS & FCF'!AZ28:BA28)+AVERAGE('BS & FCF'!AZ31:BA31)))^4-1 -> 0.055594469 | BB96: =(1-BB95/(AVERAGE('BS & FCF'!BA28:BB28)+AVERAGE('BS & FCF'!BA31:BB31)))^4-1 -> 0.051306902 | BC96: =(1-BC95/(AVERAGE('BS & FCF'!BB28:BC28)+AVERAGE('BS & FCF'!BB31:BC31)))^4-1 -> 0.039233529 | BD96: =(1-BD95/(AVERAGE('BS & FCF'!AZ28:BC28)+AVERAGE('BS & FCF'!AZ31:BC31)))-1 -> 0.046696455 | BE96: =(1-BE95/(AVERAGE('BS & FCF'!BD28:BE28)+AVERAGE('BS & FCF'!BD31:BE31)))^4-1 -> 0.066710564 | BF96: =(1-BF95/(AVERAGE('BS & FCF'!BE28:BF28)+AVERAGE('BS & FCF'!BE31:BF31)))^4-1 -> 0.059323332 | BG96: =(1-BG95/(AVERAGE('BS & FCF'!BF28:BG28)+AVERAGE('BS & FCF'!BF31:BG31)))^4-1 -> 0.081176449 | BH96: =(1-BH95/(AVERAGE('BS & FCF'!BG28:BH28)+AVERAGE('BS & FCF'!BG31:BH31)))^4-1 -> 0.10244385 | BI96: =(1-BI95/(AVERAGE('BS & FCF'!BE28:BH28)+AVERAGE('BS & FCF'!BE31:BH31)))-1 -> 0.073688868 | BJ96: =(1-BJ95/(AVERAGE('BS & FCF'!BI28:BJ28)+AVERAGE('BS & FCF'!BI31:BJ31)))^4-1 -> 0.11057125 | BK96: =(1-BK95/(AVERAGE('BS & FCF'!BJ28:BK28)+AVERAGE('BS & FCF'!BJ31:BK31)))^4-1 -> 0.12785427 | BL96: =(1-BL95/(AVERAGE('BS & FCF'!BK28:BL28)+AVERAGE('BS & FCF'!BK31:BL31)))^4-1 -> 0.13950261 | BM96: =(1-BM95/(AVERAGE('BS & FCF'!BL28:BM28)+AVERAGE('BS & FCF'!BL31:BM31)))^4-1 -> 0.18780831 | BN96: =(1-BN95/(AVERAGE('BS & FCF'!BJ28:BM28)+AVERAGE('BS & FCF'!BJ31:BM31)))-1 -> 0.13144795 | BO96: =(1-BO95/(AVERAGE('BS & FCF'!BN28:BO28)+AVERAGE('BS & FCF'!BN31:BO31)))^4-1 -> 0.14460165 | BP96: =(1-BP95/(AVERAGE('BS & FCF'!BO28:BP28)+AVERAGE('BS & FCF'!BO31:BP31)))^4-1 -> 0.15353948 | BQ96: =(1-BQ95/(AVERAGE('BS & FCF'!BP28:BQ28)+AVERAGE('BS & FCF'!BP31:BQ31)))^4-1 -> 0.13287811 | BR96: =(1-BR95/(AVERAGE('BS & FCF'!BQ28:BR28)+AVERAGE('BS & FCF'!BQ31:BR31)))^4-1 -> 0.13381437 | BS96: =(1-BS95/(AVERAGE('BS & FCF'!BO28:BR28)+AVERAGE('BS & FCF'!BO31:BR31)))-1 -> 0.13376008 | BT96: =(1-BT95/(AVERAGE('BS & FCF'!BS28:BT28)+AVERAGE('BS & FCF'!BS31:BT31)))^4-1 -> 0.12963983 | BU96: =(1-BU95/(AVERAGE('BS & FCF'!BT28:BU28)+AVERAGE('BS & FCF'!BT31:BU31)))^4-1 -> 0.14006712 | BV96: =(1-BV95/(AVERAGE('BS & FCF'!BU28:BV28)+AVERAGE('BS & FCF'!BU31:BV31)))^4-1 -> 0.12594358 | BW96: =(1-BW95/(AVERAGE('BS & FCF'!BV28:BW28)+AVERAGE('BS & FCF'!BV31:BW31)))^4-1 -> 0.13890736 | BX96: =(1-BX95/(AVERAGE('BS & FCF'!BT28:BW28)+AVERAGE('BS & FCF'!BT31:BW31)))-1 -> 0.12490059 | BY96: =(1-BY95/(AVERAGE('BS & FCF'!BX28:BY28)+AVERAGE('BS & FCF'!BX31:BY31)))^4-1 -> 0.13247984 | BZ96: =(1-BZ95/(AVERAGE('BS & FCF'!BY28:BZ28)+AVERAGE('BS & FCF'!BY31:BZ31)))^4-1 -> 0.1490643 | CA96: =(1-CA95/(AVERAGE('BS & FCF'!BZ28:CA28)+AVERAGE('BS & FCF'!BZ31:CA31)))^4-1 -> 0.13837435 | CB96: =(1-CB95/(AVERAGE('BS & FCF'!CA28:CB28)+AVERAGE('BS & FCF'!CA31:CB31)))^4-1 -> 0.13344003 | CC96: =(1-CC95/(AVERAGE('BS & FCF'!BY28:CB28)+AVERAGE('BS & FCF'!BY31:CB31)))-1 -> 0.12548507 | CD96: =(1-CD95/(AVERAGE('BS & FCF'!CC28:CD28)+AVERAGE('BS & FCF'!CC31:CD31)))^4-1 -> 0.1378258 | CE96: =(1-CE95/(AVERAGE('BS & FCF'!CD28:CE28)+AVERAGE('BS & FCF'!CD31:CE31)))^4-1 -> 0.15080493 | CF96: =(1-CF95/(AVERAGE('BS & FCF'!CE28:CF28)+AVERAGE('BS & FCF'!CE31:CF31)))^4-1 -> 0.13 | CG96: =(1-CG95/(AVERAGE('BS & FCF'!CF28:CG28)+AVERAGE('BS & FCF'!CF31:CG31)))^4-1 -> 0.1295 | CH96: =(1-CH95/(AVERAGE('BS & FCF'!CD28:CG28)+AVERAGE('BS & FCF'!CD31:CG31)))-1 -> 0.12950548 | CI96: =(1-CI95/(AVERAGE('BS & FCF'!CH28:CI28)+AVERAGE('BS & FCF'!CH31:CI31)))^4-1 -> 0.14833333 | CJ96: =(1-CJ95/(AVERAGE('BS & FCF'!CI28:CJ28)+AVERAGE('BS & FCF'!CI31:CJ31)))^4-1 -> 0.14525 | CK96: =(1-CK95/(AVERAGE('BS & FCF'!CJ28:CK28)+AVERAGE('BS & FCF'!CJ31:CK31)))^4-1 -> 0.1365 | CL96: =(1-CL95/(AVERAGE('BS & FCF'!CK28:CL28)+AVERAGE('BS & FCF'!CK31:CL31)))^4-1 -> 0.1295 | CM96: =(1-CM95/(AVERAGE('BS & FCF'!CI28:CL28)+AVERAGE('BS & FCF'!CI31:CL31)))-1 -> 0.13240332 | CN96: =(1-CN95/(AVERAGE('BS & FCF'!CM28:CN28)+AVERAGE('BS & FCF'!CM31:CN31)))^4-1 -> 0.1295 | CO96: =(1-CO95/(AVERAGE('BS & FCF'!CN28:CO28)+AVERAGE('BS & FCF'!CN31:CO31)))^4-1 -> 0.1295 | CP96: =(1-CP95/(AVERAGE('BS & FCF'!CO28:CP28)+AVERAGE('BS & FCF'!CO31:CP31)))^4-1 -> 0.1295 | CQ96: =(1-CQ95/(AVERAGE('BS & FCF'!CP28:CQ28)+AVERAGE('BS & FCF'!CP31:CQ31)))^4-1 -> 0.1295 | CR96: =(1-CR95/(AVERAGE('BS & FCF'!CN28:CQ28)+AVERAGE('BS & FCF'!CN31:CQ31)))-1 -> 0.12313344 | CS96: =(1-CS95/(AVERAGE('BS & FCF'!CR28:CS28)+AVERAGE('BS & FCF'!CR31:CS31)))^4-1 -> 0.1113 | CT96: =(1-CT95/(AVERAGE('BS & FCF'!CS28:CT28)+AVERAGE('BS & FCF'!CS31:CT31)))^4-1 -> 0.1113 | CU96: =(1-CU95/(AVERAGE('BS & FCF'!CT28:CU28)+AVERAGE('BS & FCF'!CT31:CU31)))^4-1 -> 0.1113 | CV96: =(1-CV95/(AVERAGE('BS & FCF'!CU28:CV28)+AVERAGE('BS & FCF'!CU31:CV31)))^4-1 -> 0.1113 | CW96: =(1-CW95/(AVERAGE('BS & FCF'!CS28:CV28)+AVERAGE('BS & FCF'!CS31:CV31)))-1 -> 0.10667344 | CX96: =(1-CX95/(AVERAGE('BS & FCF'!CW28:CX28)+AVERAGE('BS & FCF'!CW31:CX31)))^4-1 -> 0.1113 | CY96: =(1-CY95/(AVERAGE('BS & FCF'!CX28:CY28)+AVERAGE('BS & FCF'!CX31:CY31)))^4-1 -> 0.1113 | CZ96: =(1-CZ95/(AVERAGE('BS & FCF'!CY28:CZ28)+AVERAGE('BS & FCF'!CY31:CZ31)))^4-1 -> 0.1113 | DA96: =(1-DA95/(AVERAGE('BS & FCF'!CZ28:DA28)+AVERAGE('BS & FCF'!CZ31:DA31)))^4-1 -> 0.1113 | DB96: =(1-DB95/(AVERAGE('BS & FCF'!CX28:DA28)+AVERAGE('BS & FCF'!CX31:DA31)))-1 -> 0.1065377
A97: % of CDI | B97: =B96/Macro!B12 -> 1.0359706 | C97: =C96/Macro!C12 -> 1.0359921 | D97: =D96/Macro!D12 -> 1.9357258 | E97: =E96/Macro!E12 -> 1.8709877 | F97: =F96/Macro!F12 -> 1.3989167 | G97: =G96/Macro!G12 -> 1.1922324 | H97: =H96/Macro!H12 -> 1.1782989 | I97: =I96/Macro!I12 -> 1.3842456 | ... DB97: =DB96/Macro!DB12 -> 1.0050727
A98: % interest capitalization | B98: =B94/-B95 -> 0.13498508 | C98: =C94/-C95 -> 0.14947674 | D98: =D94/-D95 -> 0.58707832 | E98: =E94/-E95 -> 0.66901719 | F98: =F94/-F95 -> 0.48405269 | G98: =G94/-G95 -> 0.52765587 | H98: =H94/-H95 -> 0.49432256 | I98: =I94/-I95 -> 0.47885251 | ... CE98: =CE94/-CE95 -> 0.18069608 | CF98: 0.225 | CG98: 0.225 | CH98: =CH94/-CH95 -> 0.21519654 | CI98: =CG98 -> 0.225 | CJ98: =CI98 -> 0.225 | CK98: =CJ98 -> 0.225 | CL98: =CK98 -> 0.225 | CM98: =CM94/-CM95 -> 0.225 | CN98: =CL98 -> 0.225 | CO98: =CN98 -> 0.225 | CP98: =CO98 -> 0.225 | CQ98: =CP98 -> 0.225 | CR98: =CR94/-CR95 -> 0.225 | CS98: =CQ98 -> 0.225 | CT98: =CS98 -> 0.225 | CU98: =CT98 -> 0.225 | CV98: =CU98 -> 0.225 | CW98: =CW94/-CW95 -> 0.225 | CX98: =CV98 -> 0.225 | CY98: =CX98 -> 0.225 | CZ98: =CY98 -> 0.225 | DA98: =CZ98 -> 0.225 | DB98: =DB94/-DB95 -> 0.225
A99: Securitization financial expenses | B99: 0 | C99: 0 | D99: 0 | E99: 0 | F99: =SUM(B99:E99) -> 0 | G99: 0 | H99: 0 | I99: 0 | J99: 0 | K99: =SUM(G99:J99) -> 0 | L99: 0 | M99: 0 | N99: 0 | O99: 0 | P99: =SUM(L99:O99) -> 0 | Q99: 0 | R99: 0 | S99: 0 | T99: 0 | U99: =SUM(Q99:T99) -> 0 | V99: 0 | W99: 0 | X99: 0 | Y99: 0 | Z99: =SUM(V99:Y99) -> 0 | AA99: 0 | AB99: 0 | AC99: 0 | AD99: 0 | AE99: =SUM(AA99:AD99) -> 0 | AF99: 0 | AG99: 0 | AH99: 0 | AI99: 0 | AJ99: =SUM(AF99:AI99) -> 0 | AK99: 0 | AL99: 0 | AM99: 0 | AN99: 0 | AO99: =SUM(AK99:AN99) -> 0 | AP99: 0 | AQ99: 0 | AR99: 0 | AS99: 0 | AT99: =SUM(AP99:AS99) -> 0 | AU99: 0 | AV99: 0 | AW99: 0 | AX99: 0 | AY99: =SUM(AU99:AX99) -> 0 | AZ99: 0 | BA99: 0 | BB99: 0 | BC99: 0 | BD99: =SUM(AZ99:BC99) -> 0 | BE99: 0 | BF99: 0 | BG99: 0 | BH99: 0 | BI99: =SUM(BE99:BH99) -> 0 | BJ99: 0 | BK99: 0 | BL99: 0 | BM99: 0 | BN99: =SUM(BJ99:BM99) -> 0 | BO99: 0 | BP99: 0 | BQ99: 0 | BR99: 0 | BS99: =SUM(BO99:BR99) -> 0 | BT99: 0 | BU99: 0 | BV99: 0 | BW99: 0 | BX99: =SUM(BT99:BW99) -> 0 | BY99: 0 | BZ99: 0 | CA99: 0 | CB99: 0 | CC99: =SUM(BY99:CB99) -> 0 | CD99: 0 | CE99: 0 | CF99: =IFERROR(-CF100*AVERAGE('BS & FCF'!CE32:CF32)/4,0) -> 0 | CG99: =IFERROR(-CG100*AVERAGE('BS & FCF'!CF32:CG32)/4,0) -> 0 | CH99: =SUM(CD99:CG99) -> 0 | CI99: =IFERROR(-CI100*AVERAGE('BS & FCF'!CH32:CI32)/4,0) -> 0 | CJ99: =IFERROR(-CJ100*AVERAGE('BS & FCF'!CI32:CJ32)/4,0) -> 0 | CK99: =IFERROR(-CK100*AVERAGE('BS & FCF'!CJ32:CK32)/4,0) -> 0 | CL99: =IFERROR(-CL100*AVERAGE('BS & FCF'!CK32:CL32)/4,0) -> 0 | CM99: =SUM(CI99:CL99) -> 0 | CN99: =IFERROR(-CN100*AVERAGE('BS & FCF'!CM32:CN32)/4,0) -> 0 | CO99: =IFERROR(-CO100*AVERAGE('BS & FCF'!CN32:CO32)/4,0) -> 0 | CP99: =IFERROR(-CP100*AVERAGE('BS & FCF'!CO32:CP32)/4,0) -> 0 | CQ99: =IFERROR(-CQ100*AVERAGE('BS & FCF'!CP32:CQ32)/4,0) -> 0 | CR99: =SUM(CN99:CQ99) -> 0 | CS99: =IFERROR(-CS100*AVERAGE('BS & FCF'!CR32:CS32)/4,0) -> 0 | CT99: =IFERROR(-CT100*AVERAGE('BS & FCF'!CS32:CT32)/4,0) -> 0 | CU99: =IFERROR(-CU100*AVERAGE('BS & FCF'!CT32:CU32)/4,0) -> 0 | CV99: =IFERROR(-CV100*AVERAGE('BS & FCF'!CU32:CV32)/4,0) -> 0 | CW99: =SUM(CS99:CV99) -> 0 | CX99: =IFERROR(-CX100*AVERAGE('BS & FCF'!CW32:CX32)/4,0) -> 0 | CY99: =IFERROR(-CY100*AVERAGE('BS & FCF'!CX32:CY32)/4,0) -> 0 | CZ99: =IFERROR(-CZ100*AVERAGE('BS & FCF'!CY32:CZ32)/4,0) -> 0 | DA99: =IFERROR(-DA100*AVERAGE('BS & FCF'!CZ32:DA32)/4,0) -> 0 | DB99: =SUM(CX99:DA99) -> 0
